{
  "type": "Feature",
  "properties": {
    "gn:admin1_code":"22",
    "gn:asciiname":"Agua Viva",
    "gn:country_code":"VE",
    "gn:dem":137,
    "gn:feature_class":"P",
    "gn:feature_code":"PPL",
    "gn:name":"Agua Viva",
    "gn:population":0,
    "gn:timezone":"America/Caracas",
    "iso:country":"VE",
    "wof:name":"Agua Viva",
    "wof:placetype":"locality"
},
  "geometry": {"coordinates":[-68.68415999999999,10.65678],"type":"Point"}
}