{
  "type": "Feature",
  "properties": {
    "gn:admin1_code":"13",
    "gn:asciiname":"La Danta",
    "gn:country_code":"VE",
    "gn:dem":571,
    "gn:feature_class":"P",
    "gn:feature_code":"PPL",
    "gn:name":"La Danta",
    "gn:population":0,
    "gn:timezone":"America/Caracas",
    "iso:country":"VE",
    "wof:name":"La Danta",
    "wof:placetype":"locality"
},
  "geometry": {"coordinates":[-69.09858,10.33551],"type":"Point"}
}