{
  "type": "Feature",
  "properties": {
    "gn:admin1_code":"14",
    "gn:asciiname":"Culebra",
    "gn:country_code":"VE",
    "gn:dem":49,
    "gn:feature_class":"P",
    "gn:feature_code":"PPL",
    "gn:name":"Culebra",
    "gn:population":0,
    "gn:timezone":"America/Caracas",
    "iso:country":"VE",
    "name:ceb_x_preferred":[
        "Culebra"
    ],
    "name:fra_x_preferred":[
        "Culebra"
    ],
    "name:ita_x_preferred":[
        "Culebra"
    ],
    "name:pol_x_preferred":[
        "Culebra"
    ],
    "name:rus_x_preferred":[
        "\u041a\u0443\u043b\u0435\u0431\u0440\u0430"
    ],
    "name:spa_x_preferred":[
        "Culebra"
    ],
    "name:swe_x_preferred":[
        "Culebra"
    ],
    "wof:name":"Culebra",
    "wof:placetype":"locality"
},
  "geometry": {"coordinates":[-71.16399,9.04875],"type":"Point"}
}