{
  "type": "Feature",
  "properties": {
    "gn:admin1_code":"19.0",
    "gn:asciiname":"Las Peonias",
    "gn:country_code":"VE",
    "gn:dem":762,
    "gn:feature_class":"P",
    "gn:feature_code":"PPL",
    "gn:name":"Las Peonias",
    "gn:population":0,
    "gn:timezone":"America/Caracas",
    "iso:country":"VE",
    "wof:name":"Las Peonias",
    "wof:placetype":"locality"
},
  "geometry": {"coordinates":[-63.79326,10.1622],"type":"Point"}
}