{
  "type": "Feature",
  "properties": {
    "gn:admin1_code":"12",
    "gn:asciiname":"La Cocinera",
    "gn:country_code":"VE",
    "gn:dem":324,
    "gn:feature_class":"P",
    "gn:feature_code":"PPL",
    "gn:name":"La Cocinera",
    "gn:population":0,
    "gn:timezone":"America/Caracas",
    "iso:country":"VE",
    "wof:name":"La Cocinera",
    "wof:placetype":"locality"
},
  "geometry": {"coordinates":[-67.62106,9.76777],"type":"Point"}
}