{
  "type": "Feature",
  "properties": {
    "gn:admin1_code":"15",
    "gn:asciiname":"Guareguarito",
    "gn:country_code":"VE",
    "gn:dem":611,
    "gn:feature_class":"P",
    "gn:feature_code":"PPL",
    "gn:name":"Guareguarito",
    "gn:population":0,
    "gn:timezone":"America/Caracas",
    "iso:country":"VE",
    "wof:name":"Guareguarito",
    "wof:placetype":"locality"
},
  "geometry": {"coordinates":[-66.99843,10.30958],"type":"Point"}
}