{
  "type": "Feature",
  "properties": {
    "gn:admin1_code":"22",
    "gn:asciiname":"Madera",
    "gn:country_code":"VE",
    "gn:dem":762,
    "gn:feature_class":"P",
    "gn:feature_code":"PPL",
    "gn:name":"Madera",
    "gn:population":0,
    "gn:timezone":"America/Caracas",
    "iso:country":"VE",
    "wof:name":"Madera",
    "wof:placetype":"locality"
},
  "geometry": {"coordinates":[-68.51721999999999,10.11769],"type":"Point"}
}