{
  "type": "Feature",
  "properties": {
    "gn:admin1_code":"19.0",
    "gn:asciiname":"Orinoco",
    "gn:country_code":"VE",
    "gn:dem":368,
    "gn:feature_class":"P",
    "gn:feature_code":"PPL",
    "gn:name":"Orinoco",
    "gn:population":0,
    "gn:timezone":"America/Caracas",
    "iso:country":"VE",
    "wof:name":"Orinoco",
    "wof:placetype":"locality"
},
  "geometry": {"coordinates":[-63.89292,10.20675],"type":"Point"}
}