{
  "type": "Feature",
  "properties": {
    "gn:admin1_code":"15",
    "gn:asciiname":"Quebrada de Miguel",
    "gn:country_code":"VE",
    "gn:dem":350,
    "gn:feature_class":"P",
    "gn:feature_code":"PPL",
    "gn:name":"Quebrada de Miguel",
    "gn:population":0,
    "gn:timezone":"America/Caracas",
    "iso:country":"VE",
    "wof:name":"Quebrada de Miguel",
    "wof:placetype":"locality"
},
  "geometry": {"coordinates":[-66.71774000000001,10.11676],"type":"Point"}
}