{
  "type": "Feature",
  "properties": {
    "gn:admin1_code":"02",
    "gn:asciiname":"La Cruz",
    "gn:country_code":"VE",
    "gn:dem":163,
    "gn:feature_class":"P",
    "gn:feature_code":"PPLL",
    "gn:name":"La Cruz",
    "gn:population":0,
    "gn:timezone":"America/Caracas",
    "iso:country":"VE",
    "wof:name":"La Cruz",
    "wof:placetype":"locality"
},
  "geometry": {"coordinates":[-64.61193,9.68353],"type":"Point"}
}