{
  "type": "Feature",
  "properties": {
    "gn:admin1_code":"19.0",
    "gn:asciiname":"Trompillar",
    "gn:country_code":"VE",
    "gn:dem":873,
    "gn:feature_class":"P",
    "gn:feature_code":"PPLL",
    "gn:name":"Trompillar",
    "gn:population":0,
    "gn:timezone":"America/Caracas",
    "iso:country":"VE",
    "wof:name":"Trompillar",
    "wof:placetype":"locality"
},
  "geometry": {"coordinates":[-63.80016,10.30896],"type":"Point"}
}