{
  "type": "Feature",
  "properties": {
    "gn:admin1_code":"23",
    "gn:admin2_code":"2307.0",
    "gn:asciiname":"La Concepcion",
    "gn:country_code":"VE",
    "gn:dem":75,
    "gn:feature_class":"P",
    "gn:feature_code":"PPLA2",
    "gn:name":"La Concepci\u00f3n",
    "gn:population":0,
    "gn:timezone":"America/Caracas",
    "iso:country":"VE",
    "wof:name":"La Concepcion",
    "wof:placetype":"locality"
},
  "geometry": {"coordinates":[-71.83814,10.61919],"type":"Point"}
}