{
  "type": "Feature",
  "properties": {
    "gn:admin1_code":"16.0",
    "gn:asciiname":"La Loma de la Virgen",
    "gn:country_code":"VE",
    "gn:dem":1122,
    "gn:feature_class":"P",
    "gn:feature_code":"PPL",
    "gn:name":"La Loma de la Virgen",
    "gn:population":0,
    "gn:timezone":"America/Caracas",
    "iso:country":"VE",
    "wof:name":"La Loma de la Virgen",
    "wof:placetype":"locality"
},
  "geometry": {"coordinates":[-63.72139,10.08385],"type":"Point"}
}