{
  "type": "Feature",
  "properties": {
    "gn:admin1_code":"0",
    "gn:asciiname":"Paso Largo",
    "gn:country_code":"VE",
    "gn:dem":160,
    "gn:feature_class":"P",
    "gn:feature_code":"PPL",
    "gn:name":"Paso Largo",
    "gn:population":0,
    "gn:timezone":"America/Caracas",
    "iso:country":"VE",
    "wof:name":"Paso Largo",
    "wof:placetype":"locality"
},
  "geometry": {"coordinates":[-63.47908,10.30996],"type":"Point"}
}