{
  "type": "Feature",
  "properties": {
    "gn:admin1_code":"23.0",
    "gn:asciiname":"Corral Puerto Rico",
    "gn:country_code":"VE",
    "gn:dem":1,
    "gn:feature_class":"P",
    "gn:feature_code":"PPLL",
    "gn:name":"Corral Puerto Rico",
    "gn:population":0,
    "gn:timezone":"America/Caracas",
    "iso:country":"VE",
    "wof:name":"Corral Puerto Rico",
    "wof:placetype":"locality"
},
  "geometry": {"coordinates":[-71.90808,10.16843],"type":"Point"}
}