{
  "type": "Feature",
  "properties": {
    "gn:admin1_code":"8",
    "gn:asciiname":"Apartadero",
    "gn:country_code":"VE",
    "gn:dem":144,
    "gn:feature_class":"P",
    "gn:feature_code":"PPL",
    "gn:name":"Apartadero",
    "gn:population":0,
    "gn:timezone":"America/Caracas",
    "iso:country":"VE",
    "wof:name":"Apartadero",
    "wof:placetype":"locality"
},
  "geometry": {"coordinates":[-68.90000000000001,9.65],"type":"Point"}
}