{
  "type": "Feature",
  "properties": {
    "gn:admin1_code":"8.0",
    "gn:asciiname":"Los Tanques",
    "gn:country_code":"VE",
    "gn:dem":210,
    "gn:feature_class":"P",
    "gn:feature_code":"PPL",
    "gn:name":"Los Tanques",
    "gn:population":0,
    "gn:timezone":"America/Caracas",
    "iso:country":"VE",
    "wof:name":"Los Tanques",
    "wof:placetype":"locality"
},
  "geometry": {"coordinates":[-68.49167,9.755],"type":"Point"}
}