{
  "type": "Feature",
  "properties": {
    "gn:admin1_code":"13.0",
    "gn:asciiname":"Carorita Arriba",
    "gn:country_code":"VE",
    "gn:dem":649,
    "gn:feature_class":"P",
    "gn:feature_code":"PPL",
    "gn:name":"Carorita Arriba",
    "gn:population":0,
    "gn:timezone":"America/Caracas",
    "iso:country":"VE",
    "wof:name":"Carorita Arriba",
    "wof:placetype":"locality"
},
  "geometry": {"coordinates":[-69.36431,10.1183],"type":"Point"}
}