{
  "type": "Feature",
  "properties": {
    "gn:admin1_code":"5",
    "gn:asciiname":"La Quebrada",
    "gn:country_code":"VE",
    "gn:dem":183,
    "gn:feature_class":"P",
    "gn:feature_code":"PPL",
    "gn:name":"La Quebrada",
    "gn:population":0,
    "gn:timezone":"America/Caracas",
    "iso:country":"VE",
    "name:ceb_x_preferred":[
        "La Quebrada"
    ],
    "name:swe_x_preferred":[
        "La Quebrada"
    ],
    "wof:name":"La Quebrada",
    "wof:placetype":"locality"
},
  "geometry": {"coordinates":[-71.16667,7.78333],"type":"Point"}
}