{
  "type": "Feature",
  "properties": {
    "gn:admin1_code":"15",
    "gn:asciiname":"La Rosa",
    "gn:country_code":"VE",
    "gn:dem":17,
    "gn:feature_class":"P",
    "gn:feature_code":"PPL",
    "gn:name":"La Rosa",
    "gn:population":0,
    "gn:timezone":"America/Caracas",
    "iso:country":"VE",
    "wof:name":"La Rosa",
    "wof:placetype":"locality"
},
  "geometry": {"coordinates":[-66.05556,10.27472],"type":"Point"}
}