{
  "type": "Feature",
  "properties": {
    "gn:admin1_code":"15",
    "gn:asciiname":"Mundo Nuevo",
    "gn:country_code":"VE",
    "gn:dem":318,
    "gn:feature_class":"P",
    "gn:feature_code":"PPL",
    "gn:name":"Mundo Nuevo",
    "gn:population":0,
    "gn:timezone":"America/Caracas",
    "iso:country":"VE",
    "wof:name":"Mundo Nuevo",
    "wof:placetype":"locality"
},
  "geometry": {"coordinates":[-65.59999999999999,10.03333],"type":"Point"}
}