{
  "type": "Feature",
  "properties": {
    "gn:admin1_code":"13",
    "gn:asciiname":"El Jobito",
    "gn:country_code":"VE",
    "gn:dem":552,
    "gn:feature_class":"P",
    "gn:feature_code":"PPL",
    "gn:name":"El Jobito",
    "gn:population":0,
    "gn:timezone":"America/Caracas",
    "iso:country":"VE",
    "wof:name":"El Jobito",
    "wof:placetype":"locality"
},
  "geometry": {"coordinates":[-70.11265999999999,10.59948],"type":"Point"}
}