{
  "type": "Feature",
  "properties": {
    "gn:admin1_code":"19.0",
    "gn:asciiname":"La Ceiba",
    "gn:country_code":"VE",
    "gn:dem":468,
    "gn:feature_class":"P",
    "gn:feature_code":"PPL",
    "gn:name":"La Ceiba",
    "gn:population":0,
    "gn:timezone":"America/Caracas",
    "iso:country":"VE",
    "wof:name":"La Ceiba",
    "wof:placetype":"locality"
},
  "geometry": {"coordinates":[-63.2722,10.51005],"type":"Point"}
}