{
  "type": "Feature",
  "properties": {
    "gn:admin1_code":"19.0",
    "gn:asciiname":"Quebrada de Mono",
    "gn:country_code":"VE",
    "gn:dem":368,
    "gn:feature_class":"P",
    "gn:feature_code":"PPL",
    "gn:name":"Quebrada de Mono",
    "gn:population":0,
    "gn:timezone":"America/Caracas",
    "iso:country":"VE",
    "wof:name":"Quebrada de Mono",
    "wof:placetype":"locality"
},
  "geometry": {"coordinates":[-63.01133000000001,10.6051],"type":"Point"}
}