{
  "type": "Feature",
  "properties": {
    "gn:admin1_code":"13",
    "gn:asciiname":"El Tural",
    "gn:country_code":"VE",
    "gn:dem":801,
    "gn:feature_class":"P",
    "gn:feature_code":"PPL",
    "gn:name":"El Tural",
    "gn:population":0,
    "gn:timezone":"America/Caracas",
    "iso:country":"VE",
    "wof:name":"El Tural",
    "wof:placetype":"locality"
},
  "geometry": {"coordinates":[-69.38580999999999,10.21208],"type":"Point"}
}