{
  "type": "Feature",
  "properties": {
    "gn:admin1_code":"12",
    "gn:asciiname":"Los Rastrojos",
    "gn:country_code":"VE",
    "gn:dem":52,
    "gn:feature_class":"P",
    "gn:feature_code":"PPL",
    "gn:name":"Los Rastrojos",
    "gn:population":0,
    "gn:timezone":"America/Caracas",
    "iso:country":"VE",
    "name:por_x_preferred":[
        "Los Rastrojos"
    ],
    "name:rus_x_preferred":[
        "\u041b\u043e\u0441 \u0420\u0430\u0441\u0442\u0440\u043e\u0445\u043e\u0441"
    ],
    "name:sco_x_preferred":[
        "Los Rastrojos"
    ],
    "name:spa_x_preferred":[
        "Los Rastrojos"
    ],
    "name:und_x_variant":[
        "Los Rastrojas"
    ],
    "wof:name":"Los Rastrojos",
    "wof:placetype":"locality"
},
  "geometry": {"coordinates":[-67.13381,8.16266],"type":"Point"}
}