{
  "type": "Feature",
  "properties": {
    "gn:admin1_code":"12",
    "gn:asciiname":"Los Rastrojos",
    "gn:country_code":"VE",
    "gn:dem":52,
    "gn:feature_class":"P",
    "gn:feature_code":"PPL",
    "gn:name":"Los Rastrojos",
    "gn:population":0,
    "gn:timezone":"America/Caracas",
    "iso:country":"VE",
    "name:und_x_variant":[
        "Los Rastrojas",
        "Los Rastrojos"
    ],
    "wof:name":"Los Rastrojos",
    "wof:placetype":"locality"
},
  "geometry": {"coordinates":[-67.13381,8.16266],"type":"Point"}
}