{
  "type": "Feature",
  "properties": {
    "gn:admin1_code":"26",
    "gn:asciiname":"Boqueron",
    "gn:country_code":"VE",
    "gn:dem":580,
    "gn:feature_class":"P",
    "gn:feature_code":"PPL",
    "gn:name":"Boquer\u00f3n",
    "gn:population":0,
    "gn:timezone":"America/Caracas",
    "iso:country":"VE",
    "wof:name":"Boqueron",
    "wof:placetype":"locality"
},
  "geometry": {"coordinates":[-66.98886,10.57072],"type":"Point"}
}