{
  "type": "Feature",
  "properties": {
    "gn:admin1_code":"1.0",
    "gn:asciiname":"Cuyunabiteri",
    "gn:country_code":"VE",
    "gn:dem":579,
    "gn:feature_class":"P",
    "gn:feature_code":"PPL",
    "gn:name":"Cuyunabiteri",
    "gn:population":0,
    "gn:timezone":"America/Caracas",
    "iso:country":"VE",
    "wof:name":"Cuyunabiteri",
    "wof:placetype":"locality"
},
  "geometry": {"coordinates":[-64.54637,1.47699],"type":"Point"}
}