{
  "type": "Feature",
  "properties": {
    "gn:admin1_code":"7",
    "gn:asciiname":"La Masiera",
    "gn:country_code":"VE",
    "gn:dem":645,
    "gn:feature_class":"P",
    "gn:feature_code":"PPL",
    "gn:name":"La Masiera",
    "gn:population":0,
    "gn:timezone":"America/Caracas",
    "iso:country":"VE",
    "wof:name":"La Masiera",
    "wof:placetype":"locality"
},
  "geometry": {"coordinates":[-68.35680000000001,10.05508],"type":"Point"}
}