{
  "type": "Feature",
  "properties": {
    "gn:admin1_code":"13",
    "gn:asciiname":"Los Higuerones",
    "gn:country_code":"VE",
    "gn:dem":1315,
    "gn:feature_class":"P",
    "gn:feature_code":"PPL",
    "gn:name":"Los Higuerones",
    "gn:population":0,
    "gn:timezone":"America/Caracas",
    "iso:country":"VE",
    "wof:name":"Los Higuerones",
    "wof:placetype":"locality"
},
  "geometry": {"coordinates":[-69.7252,9.67654],"type":"Point"}
}