{
  "type": "Feature",
  "properties": {
    "gn:admin1_code":"23.0",
    "gn:asciiname":"Murichipa",
    "gn:country_code":"VE",
    "gn:dem":0,
    "gn:feature_class":"P",
    "gn:feature_code":"PPL",
    "gn:name":"Murichipa",
    "gn:population":0,
    "gn:timezone":"America/Caracas",
    "iso:country":"VE",
    "wof:name":"Murichipa",
    "wof:placetype":"locality"
},
  "geometry": {"coordinates":[-71.99164,11.26953],"type":"Point"}
}