{
  "type": "Feature",
  "properties": {
    "gn:admin1_code":"4.0",
    "gn:asciiname":"Los Ranchos",
    "gn:country_code":"VE",
    "gn:dem":620,
    "gn:feature_class":"P",
    "gn:feature_code":"PPL",
    "gn:name":"Los Ranchos",
    "gn:population":0,
    "gn:timezone":"America/Caracas",
    "iso:country":"VE",
    "name:ceb_x_preferred":[
        "Los Ranchos"
    ],
    "name:swe_x_preferred":[
        "Los Ranchos"
    ],
    "wof:name":"Los Ranchos",
    "wof:placetype":"locality"
},
  "geometry": {"coordinates":[-67.14601,10.07255],"type":"Point"}
}