{
  "type": "Feature",
  "properties": {
    "gn:admin1_code":"4.0",
    "gn:asciiname":"Tamborito",
    "gn:country_code":"VE",
    "gn:dem":544,
    "gn:feature_class":"P",
    "gn:feature_code":"PPL",
    "gn:name":"Tamborito",
    "gn:population":0,
    "gn:timezone":"America/Caracas",
    "iso:country":"VE",
    "wof:name":"Tamborito",
    "wof:placetype":"locality"
},
  "geometry": {"coordinates":[-67.43611,10.18389],"type":"Point"}
}