{
  "type": "Feature",
  "properties": {
    "gn:admin1_code":"21",
    "gn:asciiname":"Puerta Arriba",
    "gn:country_code":"VE",
    "gn:dem":1847,
    "gn:feature_class":"P",
    "gn:feature_code":"PPL",
    "gn:name":"Puerta Arriba",
    "gn:population":0,
    "gn:timezone":"America/Caracas",
    "iso:country":"VE",
    "wof:name":"Puerta Arriba",
    "wof:placetype":"locality"
},
  "geometry": {"coordinates":[-70.20593000000001,9.66919],"type":"Point"}
}