{
  "type": "Feature",
  "properties": {
    "gn:admin1_code":"11",
    "gn:asciiname":"Copey",
    "gn:country_code":"VE",
    "gn:dem":76,
    "gn:feature_class":"P",
    "gn:feature_code":"PPL",
    "gn:name":"Copey",
    "gn:population":0,
    "gn:timezone":"America/Caracas",
    "iso:country":"VE",
    "wof:name":"Copey",
    "wof:placetype":"locality"
},
  "geometry": {"coordinates":[-70.95883000000001,10.81567],"type":"Point"}
}