{
  "type": "Feature",
  "properties": {
    "gn:admin1_code":"20",
    "gn:asciiname":"La Teura",
    "gn:country_code":"VE",
    "gn:dem":1366,
    "gn:feature_class":"P",
    "gn:feature_code":"PPL",
    "gn:name":"La Teura",
    "gn:population":0,
    "gn:timezone":"America/Caracas",
    "iso:country":"VE",
    "wof:name":"La Teura",
    "wof:placetype":"locality"
},
  "geometry": {"coordinates":[-72.34475999999999,7.92647],"type":"Point"}
}