{
  "type": "Feature",
  "properties": {
    "gn:admin1_code":"19.0",
    "gn:asciiname":"Guaraguara",
    "gn:country_code":"VE",
    "gn:dem":6,
    "gn:feature_class":"P",
    "gn:feature_code":"PPLL",
    "gn:name":"Guaraguara",
    "gn:population":0,
    "gn:timezone":"America/Caracas",
    "iso:country":"VE",
    "wof:name":"Guaraguara",
    "wof:placetype":"locality"
},
  "geometry": {"coordinates":[-62.32123000000001,10.54201],"type":"Point"}
}