{
  "type": "Feature",
  "properties": {
    "gn:admin1_code":"6.0",
    "gn:asciiname":"Agua Linda",
    "gn:country_code":"VE",
    "gn:dem":305,
    "gn:feature_class":"P",
    "gn:feature_code":"PPL",
    "gn:name":"Agua Linda",
    "gn:population":0,
    "gn:timezone":"America/Caracas",
    "iso:country":"VE",
    "wof:name":"Agua Linda",
    "wof:placetype":"locality"
},
  "geometry": {"coordinates":[-63.805,7.85056],"type":"Point"}
}