{
  "type": "Feature",
  "properties": {
    "gn:admin1_code":"12.0",
    "gn:asciiname":"Curtidor",
    "gn:country_code":"VE",
    "gn:dem":61,
    "gn:feature_class":"P",
    "gn:feature_code":"PPL",
    "gn:name":"Curtidor",
    "gn:population":0,
    "gn:timezone":"America/Caracas",
    "iso:country":"VE",
    "wof:name":"Curtidor",
    "wof:placetype":"locality"
},
  "geometry": {"coordinates":[-67.45917,8.14694],"type":"Point"}
}