{
  "type": "Feature",
  "properties": {
    "gn:admin1_code":"14",
    "gn:asciiname":"Gavidia",
    "gn:country_code":"VE",
    "gn:dem":3245,
    "gn:feature_class":"P",
    "gn:feature_code":"PPL",
    "gn:name":"Gavidia",
    "gn:population":0,
    "gn:timezone":"America/Caracas",
    "iso:country":"VE",
    "name:eng_x_preferred":[
        "Gavidia"
    ],
    "name:por_x_preferred":[
        "Gavidia"
    ],
    "name:spa_x_preferred":[
        "Gavidia"
    ],
    "wof:name":"Gavidia",
    "wof:placetype":"locality"
},
  "geometry": {"coordinates":[-70.92886999999997,8.68701],"type":"Point"}
}