{
  "type": "Feature",
  "properties": {
    "gn:admin1_code":"7",
    "gn:asciiname":"Banco Largo",
    "gn:country_code":"VE",
    "gn:dem":716,
    "gn:feature_class":"P",
    "gn:feature_code":"PPL",
    "gn:name":"Banco Largo",
    "gn:population":0,
    "gn:timezone":"America/Caracas",
    "iso:country":"VE",
    "wof:name":"Banco Largo",
    "wof:placetype":"locality"
},
  "geometry": {"coordinates":[-68.25336999999999,10.15783],"type":"Point"}
}