{
  "type": "Feature",
  "properties": {
    "gn:admin1_code":"6",
    "gn:asciiname":"Puerto",
    "gn:country_code":"VE",
    "gn:dem":277,
    "gn:feature_class":"P",
    "gn:feature_code":"PPL",
    "gn:name":"Puerto",
    "gn:population":0,
    "gn:timezone":"America/Caracas",
    "iso:country":"VE",
    "name:arg_x_preferred":[
        "Puerto"
    ],
    "name:ast_x_preferred":[
        "Puertu"
    ],
    "name:ceb_x_preferred":[
        "Puerto"
    ],
    "name:deu_x_preferred":[
        "Puerto"
    ],
    "name:ita_x_preferred":[
        "Puerto"
    ],
    "name:rus_x_preferred":[
        "\u041f\u0443\u044d\u0440\u0442\u043e"
    ],
    "name:spa_x_preferred":[
        "Puerto"
    ],
    "name:swe_x_preferred":[
        "Puerto"
    ],
    "wof:name":"Puerto",
    "wof:placetype":"locality"
},
  "geometry": {"coordinates":[-62.26667,7.08333],"type":"Point"}
}