{
  "type": "Feature",
  "properties": {
    "gn:admin1_code":"6",
    "gn:asciiname":"Puerto",
    "gn:country_code":"VE",
    "gn:dem":277,
    "gn:feature_class":"P",
    "gn:feature_code":"PPL",
    "gn:name":"Puerto",
    "gn:population":0,
    "gn:timezone":"America/Caracas",
    "iso:country":"VE",
    "wof:name":"Puerto",
    "wof:placetype":"locality"
},
  "geometry": {"coordinates":[-62.26667,7.08333],"type":"Point"}
}