{
  "type": "Feature",
  "properties": {
    "gn:admin1_code":"14",
    "gn:asciiname":"La Pueblita",
    "gn:country_code":"VE",
    "gn:dem":205,
    "gn:feature_class":"P",
    "gn:feature_code":"PPL",
    "gn:name":"La Pueblita",
    "gn:population":0,
    "gn:timezone":"America/Caracas",
    "iso:country":"VE",
    "wof:name":"La Pueblita",
    "wof:placetype":"locality"
},
  "geometry": {"coordinates":[-71.10399,9.06193],"type":"Point"}
}