{
  "type": "Feature",
  "properties": {
    "gn:admin1_code":"15",
    "gn:asciiname":"Bella Vista",
    "gn:country_code":"VE",
    "gn:dem":1025,
    "gn:feature_class":"P",
    "gn:feature_code":"PPL",
    "gn:name":"Bella Vista",
    "gn:population":0,
    "gn:timezone":"America/Caracas",
    "iso:country":"VE",
    "wof:name":"Bella Vista",
    "wof:placetype":"locality"
},
  "geometry": {"coordinates":[-66.71744,10.42568],"type":"Point"}
}