{
  "type": "Feature",
  "properties": {
    "gn:admin1_code":"18.0",
    "gn:asciiname":"Micro Sur Tres",
    "gn:country_code":"VE",
    "gn:dem":96,
    "gn:feature_class":"P",
    "gn:feature_code":"PPL",
    "gn:name":"Micro Sur Tres",
    "gn:population":0,
    "gn:timezone":"America/Caracas",
    "iso:country":"VE",
    "name:spa_x_preferred":[
        "Micro Sur Tres"
    ],
    "wof:name":"Micro Sur Tres",
    "wof:placetype":"locality"
},
  "geometry": {"coordinates":[-69.01909000000001,9.08719],"type":"Point"}
}