{
  "type": "Feature",
  "properties": {
    "gn:admin1_code":"14",
    "gn:asciiname":"Mesa de Quintero",
    "gn:country_code":"VE",
    "gn:dem":1517,
    "gn:feature_class":"P",
    "gn:feature_code":"PPL",
    "gn:name":"Mesa de Quintero",
    "gn:population":0,
    "gn:timezone":"America/Caracas",
    "iso:country":"VE",
    "wof:name":"Mesa de Quintero",
    "wof:placetype":"locality"
},
  "geometry": {"coordinates":[-71.6185,8.09594],"type":"Point"}
}