{
  "type": "Feature",
  "properties": {
    "gn:admin1_code":"12",
    "gn:asciiname":"La Deleitosa",
    "gn:cc2":"VE",
    "gn:country_code":"VE",
    "gn:dem":17,
    "gn:feature_class":"P",
    "gn:feature_code":"PPL",
    "gn:name":"La Deleitosa",
    "gn:population":0,
    "gn:timezone":"America/Caracas",
    "iso:country":"VE",
    "name:und_x_variant":[
        "Deleitosa",
        "Electrosa",
        "La Deleitosa"
    ],
    "wof:name":"La Deleitosa",
    "wof:placetype":"locality"
},
  "geometry": {"coordinates":[-65.48333000000001,7.88333],"type":"Point"}
}