{
  "type": "Feature",
  "properties": {
    "gn:admin1_code":"02",
    "gn:asciiname":"Sangrillo",
    "gn:country_code":"VE",
    "gn:dem":58,
    "gn:feature_class":"P",
    "gn:feature_code":"PPL",
    "gn:name":"Sangrillo",
    "gn:population":0,
    "gn:timezone":"America/Caracas",
    "iso:country":"VE",
    "wof:name":"Sangrillo",
    "wof:placetype":"locality"
},
  "geometry": {"coordinates":[-64.97903000000001,9.85225],"type":"Point"}
}