{
  "type": "Feature",
  "properties": {
    "gn:admin1_code":"12",
    "gn:asciiname":"Medano del Burro",
    "gn:cc2":"VE",
    "gn:country_code":"VE",
    "gn:dem":69,
    "gn:feature_class":"P",
    "gn:feature_code":"PPL",
    "gn:name":"M\u00e9dano del Burro",
    "gn:population":0,
    "gn:timezone":"America/Caracas",
    "iso:country":"VE",
    "name:und_x_variant":[
        "M\u00e9dano el Burro",
        "M\u00e9dano del Burro"
    ],
    "wof:name":"Medano del Burro",
    "wof:placetype":"locality"
},
  "geometry": {"coordinates":[-67.56667,8.43333],"type":"Point"}
}