{
  "type": "Feature",
  "properties": {
    "gn:admin1_code":"16",
    "gn:asciiname":"Las Casitas",
    "gn:country_code":"VE",
    "gn:dem":146,
    "gn:feature_class":"P",
    "gn:feature_code":"PPL",
    "gn:name":"Las Casitas",
    "gn:population":0,
    "gn:timezone":"America/Caracas",
    "iso:country":"VE",
    "wof:name":"Las Casitas",
    "wof:placetype":"locality"
},
  "geometry": {"coordinates":[-63.61666999999999,9.16667],"type":"Point"}
}