{
  "type": "Feature",
  "properties": {
    "gn:admin1_code":"13.0",
    "gn:asciiname":"Agua Turbia",
    "gn:country_code":"VE",
    "gn:dem":1125,
    "gn:feature_class":"P",
    "gn:feature_code":"PPL",
    "gn:name":"Agua Turbia",
    "gn:population":0,
    "gn:timezone":"America/Caracas",
    "iso:country":"VE",
    "wof:name":"Agua Turbia",
    "wof:placetype":"locality"
},
  "geometry": {"coordinates":[-69.88655,9.63522],"type":"Point"}
}