{
  "type": "Feature",
  "properties": {
    "gn:admin1_code":"5",
    "gn:admin2_code":"604.0",
    "gn:admin3_code":"60412.0",
    "gn:asciiname":"Caramuca",
    "gn:country_code":"VE",
    "gn:dem":227,
    "gn:feature_class":"P",
    "gn:feature_code":"PPLA3",
    "gn:name":"Caramuca",
    "gn:population":0,
    "gn:timezone":"America/Caracas",
    "iso:country":"VE",
    "name:und_x_variant":[
        "La Caramuca",
        "Coramuca",
        "Caramuca"
    ],
    "wof:name":"Caramuca",
    "wof:placetype":"locality"
},
  "geometry": {"coordinates":[-70.32056,8.59708],"type":"Point"}
}