{
  "type": "Feature",
  "properties": {
    "iso:country":"VE",
    "name:bul_x_preferred":[
        "\u0413\u0443\u0430\u0440\u0435\u043d\u0430\u0441"
    ],
    "name:ceb_x_preferred":[
        "Guarenas"
    ],
    "name:deu_x_preferred":[
        "Guarenas"
    ],
    "name:epo_x_preferred":[
        "Guarenas"
    ],
    "name:fra_x_preferred":[
        "Guarenas"
    ],
    "name:ita_x_preferred":[
        "Guarenas"
    ],
    "name:jpn_x_preferred":[
        "\u30b0\u30a2\u30ec\u30ca\u30b9"
    ],
    "name:kat_x_preferred":[
        "\u10d2\u10e3\u10d0\u10e0\u10d4\u10dc\u10d0\u10e1\u10d8"
    ],
    "name:kor_x_preferred":[
        "\uacfc\ub808\ub098\uc2a4"
    ],
    "name:nno_x_preferred":[
        "Guarenas"
    ],
    "name:pol_x_preferred":[
        "Guarenas"
    ],
    "name:por_x_preferred":[
        "Guarenas"
    ],
    "name:rus_x_preferred":[
        "\u0413\u0443\u0430\u0440\u0435\u043d\u0430\u0441"
    ],
    "name:spa_x_preferred":[
        "Guarenas"
    ],
    "name:swe_x_preferred":[
        "Guarenas"
    ],
    "name:war_x_preferred":[
        "Guarenas"
    ],
    "name:zho_x_preferred":[
        "\u74dc\u96f7\u7d0d\u65af"
    ],
    "qs:gn_pop":0,
    "qs:name":"Guarenas",
    "qs:name_adm0":"Venezuela",
    "qs:name_adm1":"Miranda",
    "qs:photos":10,
    "qs:photos_1k":2,
    "qs:photos_9k":2,
    "qs:photos_9r":5,
    "qs:photos_all":355,
    "qs:photos_sr":1,
    "qs:placetype":"LocalAdmin",
    "qs:pop_sr":"0",
    "qs:woe_adm0":23424982,
    "wof:name":"Guarenas",
    "wof:placetype":"localadmin"
},
  "geometry": {"coordinates":[-66.605665,10.465452],"type":"Point"}
}