{
  "type": "Feature",
  "properties": {
    "iso:country":"VE",
    "qs:gn_pop":0,
    "qs:name":"Guarenas",
    "qs:name_adm0":"Venezuela",
    "qs:name_adm1":"Miranda",
    "qs:photos":10,
    "qs:photos_1k":2,
    "qs:photos_9k":2,
    "qs:photos_9r":5,
    "qs:photos_all":355,
    "qs:photos_sr":1,
    "qs:placetype":"LocalAdmin",
    "qs:pop_sr":"0",
    "qs:woe_adm0":23424982,
    "wof:name":"Guarenas",
    "wof:placetype":"localadmin"
},
  "geometry": {"coordinates":[-66.605665,10.465452],"type":"Point"}
}