{
  "type": "Feature",
  "properties": {
    "gn:admin1_code":"13",
    "gn:asciiname":"Miranda",
    "gn:country_code":"VE",
    "gn:dem":817,
    "gn:feature_class":"P",
    "gn:feature_code":"PPL",
    "gn:name":"Miranda",
    "gn:population":0,
    "gn:timezone":"America/Caracas",
    "iso:country":"VE",
    "wof:name":"Miranda",
    "wof:placetype":"locality"
},
  "geometry": {"coordinates":[-69.58551,10.52124],"type":"Point"}
}