{
  "type": "Feature",
  "properties": {
    "gn:admin1_code":"13",
    "gn:asciiname":"Miranda",
    "gn:country_code":"VE",
    "gn:dem":817,
    "gn:feature_class":"P",
    "gn:feature_code":"PPL",
    "gn:name":"Miranda",
    "gn:population":0,
    "gn:timezone":"America/Caracas",
    "iso:country":"VE",
    "name:arg_x_preferred":[
        "Miranda"
    ],
    "name:ast_x_preferred":[
        "Miranda"
    ],
    "name:aze_x_preferred":[
        "Miranda"
    ],
    "name:bre_x_preferred":[
        "Miranda"
    ],
    "name:bul_x_preferred":[
        "\u041c\u0438\u0440\u0430\u043d\u0434\u0430"
    ],
    "name:cat_x_preferred":[
        "Miranda"
    ],
    "name:ceb_x_preferred":[
        "Miranda"
    ],
    "name:ces_x_preferred":[
        "Miranda"
    ],
    "name:cym_x_preferred":[
        "Miranda"
    ],
    "name:dan_x_preferred":[
        "Miranda"
    ],
    "name:deu_x_preferred":[
        "Miranda"
    ],
    "name:epo_x_preferred":[
        "Miranda"
    ],
    "name:est_x_preferred":[
        "Miranda"
    ],
    "name:eus_x_preferred":[
        "Miranda"
    ],
    "name:fas_x_preferred":[
        "\u0645\u06cc\u0631\u0627\u0646\u062f\u0627"
    ],
    "name:fin_x_preferred":[
        "Miranda"
    ],
    "name:fra_x_preferred":[
        "Miranda"
    ],
    "name:glg_x_preferred":[
        "Miranda"
    ],
    "name:heb_x_preferred":[
        "\u05de\u05d9\u05e8\u05e0\u05d3\u05d4"
    ],
    "name:hrv_x_preferred":[
        "Miranda"
    ],
    "name:hun_x_preferred":[
        "Miranda"
    ],
    "name:ind_x_preferred":[
        "Miranda"
    ],
    "name:ita_x_preferred":[
        "Miranda"
    ],
    "name:jpn_x_preferred":[
        "\u30df\u30e9\u30f3\u30c0"
    ],
    "name:kor_x_preferred":[
        "\ubbf8\ub780\ub2e4"
    ],
    "name:lit_x_preferred":[
        "Miranda"
    ],
    "name:mlg_x_preferred":[
        "Miranda"
    ],
    "name:nds_x_preferred":[
        "Miranda"
    ],
    "name:nld_x_preferred":[
        "Miranda"
    ],
    "name:nno_x_preferred":[
        "Miranda"
    ],
    "name:nor_x_preferred":[
        "Miranda"
    ],
    "name:pol_x_preferred":[
        "Miranda"
    ],
    "name:por_x_preferred":[
        "Miranda"
    ],
    "name:rus_x_preferred":[
        "\u041c\u0438\u0440\u0430\u043d\u0434\u0430"
    ],
    "name:sco_x_preferred":[
        "Miranda"
    ],
    "name:slk_x_preferred":[
        "Miranda"
    ],
    "name:slv_x_preferred":[
        "Miranda"
    ],
    "name:spa_x_preferred":[
        "Miranda"
    ],
    "name:srp_x_preferred":[
        "Miranda"
    ],
    "name:swe_x_preferred":[
        "Miranda"
    ],
    "name:ukr_x_preferred":[
        "\u041c\u0456\u0440\u0430\u043d\u0434\u0430"
    ],
    "name:uzb_x_preferred":[
        "Miranda"
    ],
    "name:vie_x_preferred":[
        "Miranda"
    ],
    "name:vol_x_preferred":[
        "Miranda"
    ],
    "name:war_x_preferred":[
        "Miranda"
    ],
    "name:zho_x_preferred":[
        "\u7c73\u5170\u8fbe"
    ],
    "wof:name":"Miranda",
    "wof:placetype":"locality"
},
  "geometry": {"coordinates":[-69.58551,10.52124],"type":"Point"}
}