{
  "type": "Feature",
  "properties": {
    "gn:admin1_code":"23",
    "gn:asciiname":"Siberia",
    "gn:country_code":"VE",
    "gn:dem":6,
    "gn:feature_class":"P",
    "gn:feature_code":"PPL",
    "gn:name":"Siberia",
    "gn:population":0,
    "gn:timezone":"America/Caracas",
    "iso:country":"VE",
    "wof:name":"Siberia",
    "wof:placetype":"locality"
},
  "geometry": {"coordinates":[-71.96666999999999,8.86667],"type":"Point"}
}