{
  "type": "Feature",
  "properties": {
    "gn:admin1_code":"16",
    "gn:admin2_code":"1606.0",
    "gn:asciiname":"Punta de Mata",
    "gn:country_code":"VE",
    "gn:dem":246,
    "gn:feature_class":"P",
    "gn:feature_code":"PPLA2",
    "gn:name":"Punta de Mata",
    "gn:population":0,
    "gn:timezone":"America/Caracas",
    "iso:country":"VE",
    "name:und_x_variant":[
        "Punta de Mota",
        "Punta de Mata"
    ],
    "name:zho_x_preferred":[
        "\u84ec\u5854\u5fb7\u99ac\u5854"
    ],
    "wof:name":"Punta de Mata",
    "wof:placetype":"locality"
},
  "geometry": {"coordinates":[-63.60921,9.69131],"type":"Point"}
}