{
  "type": "Feature",
  "properties": {
    "gn:admin1_code":"6.0",
    "gn:asciiname":"Dividive",
    "gn:country_code":"VE",
    "gn:dem":29,
    "gn:feature_class":"P",
    "gn:feature_code":"PPL",
    "gn:name":"Dividive",
    "gn:population":0,
    "gn:timezone":"America/Caracas",
    "iso:country":"VE",
    "wof:name":"Dividive",
    "wof:placetype":"locality"
},
  "geometry": {"coordinates":[-64.03112,7.90064],"type":"Point"}
}