{
  "type": "Feature",
  "properties": {
    "gn:admin1_code":"9",
    "gn:asciiname":"Asuncion",
    "gn:cc2":"VE",
    "gn:country_code":"VE",
    "gn:dem":38,
    "gn:feature_class":"P",
    "gn:feature_code":"PPL",
    "gn:name":"Asunci\u00f3n",
    "gn:population":0,
    "gn:timezone":"America/Caracas",
    "iso:country":"VE",
    "name:und_x_variant":[
        "La Asenci\u00f3n",
        "La Ascensi\u00f3n",
        "Asunci\u00f3n"
    ],
    "wof:name":"Asuncion",
    "wof:placetype":"locality"
},
  "geometry": {"coordinates":[-61.60444,8.43861],"type":"Point"}
}