{
  "type": "Feature",
  "properties": {
    "gn:admin1_code":"11.0",
    "gn:asciiname":"El Cemerucal",
    "gn:country_code":"VE",
    "gn:dem":291,
    "gn:feature_class":"P",
    "gn:feature_code":"PPL",
    "gn:name":"El Cemerucal",
    "gn:population":0,
    "gn:timezone":"America/Caracas",
    "iso:country":"VE",
    "wof:name":"El Cemerucal",
    "wof:placetype":"locality"
},
  "geometry": {"coordinates":[-69.73224999999999,11.06951],"type":"Point"}
}