{
  "type": "Feature",
  "properties": {
    "gn:admin1_code":"13",
    "gn:asciiname":"Docore",
    "gn:country_code":"VE",
    "gn:dem":967,
    "gn:feature_class":"P",
    "gn:feature_code":"PPLL",
    "gn:name":"Docore",
    "gn:population":0,
    "gn:timezone":"America/Caracas",
    "iso:country":"VE",
    "wof:name":"Docore",
    "wof:placetype":"locality"
},
  "geometry": {"coordinates":[-69.62836999999999,10.51115],"type":"Point"}
}