{
  "type": "Feature",
  "properties": {
    "gn:admin1_code":"8",
    "gn:asciiname":"Higuerote",
    "gn:country_code":"VE",
    "gn:dem":384,
    "gn:feature_class":"P",
    "gn:feature_code":"PPL",
    "gn:name":"Higuerote",
    "gn:population":0,
    "gn:timezone":"America/Caracas",
    "iso:country":"VE",
    "wof:name":"Higuerote",
    "wof:placetype":"locality"
},
  "geometry": {"coordinates":[-68.32485,9.77784],"type":"Point"}
}