{
  "type": "Feature",
  "properties": {
    "gn:admin1_code":"13",
    "gn:asciiname":"El Paramito",
    "gn:country_code":"VE",
    "gn:dem":571,
    "gn:feature_class":"P",
    "gn:feature_code":"PPL",
    "gn:name":"El Paramito",
    "gn:population":0,
    "gn:timezone":"America/Caracas",
    "iso:country":"VE",
    "wof:name":"El Paramito",
    "wof:placetype":"locality"
},
  "geometry": {"coordinates":[-69.35188000000001,10.37146],"type":"Point"}
}