{
  "type": "Feature",
  "properties": {
    "gn:admin1_code":"16",
    "gn:asciiname":"Los Barrancos",
    "gn:country_code":"VE",
    "gn:dem":33,
    "gn:feature_class":"P",
    "gn:feature_code":"PPL",
    "gn:name":"Los Barrancos",
    "gn:population":0,
    "gn:timezone":"America/Caracas",
    "iso:country":"VE",
    "name:und_x_variant":[
        "Los Barrancos de Fajardo",
        "Los Barrancos"
    ],
    "wof:name":"Los Barrancos",
    "wof:placetype":"locality"
},
  "geometry": {"coordinates":[-62.48891,8.76779],"type":"Point"}
}