{
  "type": "Feature",
  "properties": {
    "gn:admin1_code":"23",
    "gn:asciiname":"El Pensado",
    "gn:country_code":"VE",
    "gn:dem":264,
    "gn:feature_class":"P",
    "gn:feature_code":"PPL",
    "gn:name":"El Pensado",
    "gn:population":0,
    "gn:timezone":"America/Caracas",
    "iso:country":"VE",
    "wof:name":"El Pensado",
    "wof:placetype":"locality"
},
  "geometry": {"coordinates":[-71.02158,10.41031],"type":"Point"}
}