{
  "type": "Feature",
  "properties": {
    "gn:admin1_code":"23.0",
    "gn:asciiname":"La Perdida",
    "gn:country_code":"VE",
    "gn:dem":13,
    "gn:feature_class":"P",
    "gn:feature_code":"PPLL",
    "gn:name":"La Perdida",
    "gn:population":0,
    "gn:timezone":"America/Caracas",
    "iso:country":"VE",
    "name:fra_x_preferred":[
        "La Perdida"
    ],
    "wof:name":"La Perdida",
    "wof:placetype":"locality"
},
  "geometry": {"coordinates":[-72.17624000000001,9.9036],"type":"Point"}
}