{
  "type": "Feature",
  "properties": {
    "gn:admin1_code":"4",
    "gn:asciiname":"La Vega de Santa Cruz",
    "gn:country_code":"VE",
    "gn:dem":24,
    "gn:feature_class":"P",
    "gn:feature_code":"PPL",
    "gn:name":"La Vega de Santa Cruz",
    "gn:population":0,
    "gn:timezone":"America/Caracas",
    "iso:country":"VE",
    "wof:name":"La Vega de Santa Cruz",
    "wof:placetype":"locality"
},
  "geometry": {"coordinates":[-67.76799,10.43366],"type":"Point"}
}