{
  "type": "Feature",
  "properties": {
    "gn:admin1_code":"6",
    "gn:asciiname":"Las Bonitas",
    "gn:cc2":"VE",
    "gn:country_code":"VE",
    "gn:dem":211,
    "gn:feature_class":"P",
    "gn:feature_code":"PPL",
    "gn:name":"Las Bonitas",
    "gn:population":0,
    "gn:timezone":"America/Caracas",
    "iso:country":"VE",
    "name:und_x_variant":[
        "Bonitas",
        "Las Bonitas"
    ],
    "wof:name":"Las Bonitas",
    "wof:placetype":"locality"
},
  "geometry": {"coordinates":[-62.08333,7.23333],"type":"Point"}
}