{
  "type": "Feature",
  "properties": {
    "gn:admin1_code":"2",
    "gn:asciiname":"Las Camazas",
    "gn:country_code":"VE",
    "gn:dem":235,
    "gn:feature_class":"P",
    "gn:feature_code":"PPL",
    "gn:name":"Las Camazas",
    "gn:population":0,
    "gn:timezone":"America/Caracas",
    "iso:country":"VE",
    "wof:name":"Las Camazas",
    "wof:placetype":"locality"
},
  "geometry": {"coordinates":[-64.58662,8.76701],"type":"Point"}
}