{
  "type": "Feature",
  "properties": {
    "gn:admin1_code":"11",
    "gn:asciiname":"Tiguadare",
    "gn:country_code":"VE",
    "gn:dem":3,
    "gn:feature_class":"P",
    "gn:feature_code":"PPL",
    "gn:name":"Tiguadare",
    "gn:population":0,
    "gn:timezone":"America/Caracas",
    "iso:country":"VE",
    "name:und_x_variant":[
        "Figuadera",
        "Tiguadore",
        "Tiguajada",
        "Tiguadaro",
        "Tiguadare"
    ],
    "wof:name":"Tiguadare",
    "wof:placetype":"locality"
},
  "geometry": {"coordinates":[-70.14175,11.623],"type":"Point"}
}