{
  "type": "Feature",
  "properties": {
    "gn:admin1_code":"13",
    "gn:asciiname":"Volcancito",
    "gn:country_code":"VE",
    "gn:dem":1349,
    "gn:feature_class":"P",
    "gn:feature_code":"PPL",
    "gn:name":"Volcancito",
    "gn:population":0,
    "gn:timezone":"America/Caracas",
    "iso:country":"VE",
    "wof:name":"Volcancito",
    "wof:placetype":"locality"
},
  "geometry": {"coordinates":[-69.50855,9.83264],"type":"Point"}
}