{
  "type": "Feature",
  "properties": {
    "gn:admin1_code":"8",
    "gn:asciiname":"El Penusco",
    "gn:country_code":"VE",
    "gn:dem":134,
    "gn:feature_class":"P",
    "gn:feature_code":"PPL",
    "gn:name":"El Pe\u00f1usco",
    "gn:population":0,
    "gn:timezone":"America/Caracas",
    "iso:country":"VE",
    "wof:name":"El Penusco",
    "wof:placetype":"locality"
},
  "geometry": {"coordinates":[-68.90245,9.57451],"type":"Point"}
}