{
  "type": "Feature",
  "properties": {
    "gn:admin1_code":"12",
    "gn:asciiname":"Bejuco",
    "gn:country_code":"VE",
    "gn:dem":43,
    "gn:feature_class":"P",
    "gn:feature_code":"PPL",
    "gn:name":"Bejuco",
    "gn:population":0,
    "gn:timezone":"America/Caracas",
    "iso:country":"VE",
    "name:ceb_x_preferred":[
        "Bejuco"
    ],
    "name:ita_x_preferred":[
        "Bejuco"
    ],
    "name:spa_x_preferred":[
        "Bejuco"
    ],
    "name:swe_x_preferred":[
        "Bejuco"
    ],
    "wof:name":"Bejuco",
    "wof:placetype":"locality"
},
  "geometry": {"coordinates":[-66.97067,8.06099],"type":"Point"}
}