{
  "type": "Feature",
  "properties": {
    "gn:admin1_code":"02",
    "gn:asciiname":"Mallorquin",
    "gn:country_code":"VE",
    "gn:dem":16,
    "gn:feature_class":"P",
    "gn:feature_code":"PPL",
    "gn:name":"Mallorquin",
    "gn:population":0,
    "gn:timezone":"America/Caracas",
    "iso:country":"VE",
    "wof:name":"Mallorquin",
    "wof:placetype":"locality"
},
  "geometry": {"coordinates":[-64.62908,10.07961],"type":"Point"}
}