{
  "type": "Feature",
  "properties": {
    "gn:admin1_code":"6.0",
    "gn:asciiname":"Casas Viejas",
    "gn:country_code":"VE",
    "gn:dem":149,
    "gn:feature_class":"P",
    "gn:feature_code":"PPL",
    "gn:name":"Casas Viejas",
    "gn:population":0,
    "gn:timezone":"America/Caracas",
    "iso:country":"VE",
    "wof:name":"Casas Viejas",
    "wof:placetype":"locality"
},
  "geometry": {"coordinates":[-63.55848,7.69217],"type":"Point"}
}