{
  "type": "Feature",
  "properties": {
    "gn:admin1_code":"18.0",
    "gn:asciiname":"El Trapiche",
    "gn:country_code":"VE",
    "gn:dem":132,
    "gn:feature_class":"P",
    "gn:feature_code":"PPLL",
    "gn:name":"El Trapiche",
    "gn:population":0,
    "gn:timezone":"America/Caracas",
    "iso:country":"VE",
    "name:spa_x_preferred":[
        "El Trapiche"
    ],
    "wof:name":"El Trapiche",
    "wof:placetype":"locality"
},
  "geometry": {"coordinates":[-69.00591999999999,9.54791],"type":"Point"}
}