{
  "type": "Feature",
  "properties": {
    "gn:admin1_code":"8",
    "gn:asciiname":"Cogollalito",
    "gn:country_code":"VE",
    "gn:dem":439,
    "gn:feature_class":"P",
    "gn:feature_code":"PPL",
    "gn:name":"Cogollalito",
    "gn:population":0,
    "gn:timezone":"America/Caracas",
    "iso:country":"VE",
    "wof:name":"Cogollalito",
    "wof:placetype":"locality"
},
  "geometry": {"coordinates":[-67.86421999999999,9.75966],"type":"Point"}
}