{
  "type": "Feature",
  "properties": {
    "gn:admin1_code":"9",
    "gn:asciiname":"Ibacuajarina",
    "gn:country_code":"VE",
    "gn:dem":7,
    "gn:feature_class":"P",
    "gn:feature_code":"PPL",
    "gn:name":"Ibacuajarina",
    "gn:population":0,
    "gn:timezone":"America/Caracas",
    "iso:country":"VE",
    "wof:name":"Ibacuajarina",
    "wof:placetype":"locality"
},
  "geometry": {"coordinates":[-60.72231,8.6059],"type":"Point"}
}