{
  "type": "Feature",
  "properties": {
    "gn:admin1_code":"19",
    "gn:asciiname":"Agua Blanca",
    "gn:country_code":"VE",
    "gn:dem":446,
    "gn:feature_class":"P",
    "gn:feature_code":"PPL",
    "gn:name":"Agua Blanca",
    "gn:population":0,
    "gn:timezone":"America/Caracas",
    "iso:country":"VE",
    "wof:name":"Agua Blanca",
    "wof:placetype":"locality"
},
  "geometry": {"coordinates":[-63.8249,10.23748],"type":"Point"}
}