{
  "type": "Feature",
  "properties": {
    "gn:admin1_code":"11.0",
    "gn:asciiname":"Los Banqueros",
    "gn:country_code":"VE",
    "gn:dem":780,
    "gn:feature_class":"P",
    "gn:feature_code":"PPLL",
    "gn:name":"Los Banqueros",
    "gn:population":0,
    "gn:timezone":"America/Caracas",
    "iso:country":"VE",
    "wof:name":"Los Banqueros",
    "wof:placetype":"locality"
},
  "geometry": {"coordinates":[-69.14778000000001,10.88222],"type":"Point"}
}