{
  "type": "Feature",
  "properties": {
    "gn:admin1_code":"6",
    "gn:asciiname":"Mundo Nuevo",
    "gn:country_code":"VE",
    "gn:dem":327,
    "gn:feature_class":"P",
    "gn:feature_code":"PPL",
    "gn:name":"Mundo Nuevo",
    "gn:population":0,
    "gn:timezone":"America/Caracas",
    "iso:country":"VE",
    "wof:name":"Mundo Nuevo",
    "wof:placetype":"locality"
},
  "geometry": {"coordinates":[-62.45817,8.04066],"type":"Point"}
}