{
  "type": "Feature",
  "properties": {
    "gn:admin1_code":"3.0",
    "gn:asciiname":"Maravillas",
    "gn:country_code":"VE",
    "gn:dem":83,
    "gn:feature_class":"P",
    "gn:feature_code":"PPL",
    "gn:name":"Maravillas",
    "gn:population":0,
    "gn:timezone":"America/Caracas",
    "iso:country":"VE",
    "name:spa_x_preferred":[
        "Maravillas"
    ],
    "wof:name":"Maravillas",
    "wof:placetype":"locality"
},
  "geometry": {"coordinates":[-69.07422,6.66222],"type":"Point"}
}