{
  "type": "Feature",
  "properties": {
    "gn:admin1_code":"16",
    "gn:asciiname":"Mata Linda",
    "gn:country_code":"VE",
    "gn:dem":251,
    "gn:feature_class":"P",
    "gn:feature_code":"PPL",
    "gn:name":"Mata Linda",
    "gn:population":0,
    "gn:timezone":"America/Caracas",
    "iso:country":"VE",
    "wof:name":"Mata Linda",
    "wof:placetype":"locality"
},
  "geometry": {"coordinates":[-63.62861,9.69693],"type":"Point"}
}