{
  "type": "Feature",
  "properties": {
    "gn:admin1_code":"02",
    "gn:asciiname":"Vallecito",
    "gn:country_code":"VE",
    "gn:dem":155,
    "gn:feature_class":"P",
    "gn:feature_code":"PPL",
    "gn:name":"Vallecito",
    "gn:population":0,
    "gn:timezone":"America/Caracas",
    "iso:country":"VE",
    "wof:name":"Vallecito",
    "wof:placetype":"locality"
},
  "geometry": {"coordinates":[-64.38333,8.58333],"type":"Point"}
}