{
  "type": "Feature",
  "properties": {
    "gn:admin1_code":"16",
    "gn:asciiname":"Laguna Grande",
    "gn:country_code":"VE",
    "gn:dem":29,
    "gn:feature_class":"P",
    "gn:feature_code":"PPL",
    "gn:name":"Laguna Grande",
    "gn:population":0,
    "gn:timezone":"America/Caracas",
    "iso:country":"VE",
    "wof:name":"Laguna Grande",
    "wof:placetype":"locality"
},
  "geometry": {"coordinates":[-63.05726,9.77009],"type":"Point"}
}