{
  "type": "Feature",
  "properties": {
    "gn:admin1_code":"21",
    "gn:asciiname":"Sabana Libre",
    "gn:country_code":"VE",
    "gn:dem":231,
    "gn:feature_class":"P",
    "gn:feature_code":"PPL",
    "gn:name":"Sabana Libre",
    "gn:population":0,
    "gn:timezone":"America/Caracas",
    "iso:country":"VE",
    "wof:name":"Sabana Libre",
    "wof:placetype":"locality"
},
  "geometry": {"coordinates":[-70.68845,9.62095],"type":"Point"}
}