{
  "type": "Feature",
  "properties": {
    "gn:admin1_code":"13.0",
    "gn:asciiname":"El Cardonalito",
    "gn:country_code":"VE",
    "gn:dem":408,
    "gn:feature_class":"P",
    "gn:feature_code":"PPL",
    "gn:name":"El Cardonalito",
    "gn:population":0,
    "gn:timezone":"America/Caracas",
    "iso:country":"VE",
    "wof:name":"El Cardonalito",
    "wof:placetype":"locality"
},
  "geometry": {"coordinates":[-70.09156999999999,10.1925],"type":"Point"}
}