{
  "type": "Feature",
  "properties": {
    "gn:admin1_code":"6",
    "gn:asciiname":"Catisimina",
    "gn:country_code":"VE",
    "gn:dem":457,
    "gn:feature_class":"P",
    "gn:feature_code":"PPL",
    "gn:name":"Catisimi\u00f1a",
    "gn:population":0,
    "gn:timezone":"America/Caracas",
    "iso:country":"VE",
    "wof:name":"Catisimina",
    "wof:placetype":"locality"
},
  "geometry": {"coordinates":[-63.83427,4.05309],"type":"Point"}
}