{
  "type": "Feature",
  "properties": {
    "gn:admin1_code":"12",
    "gn:asciiname":"Las Lajas",
    "gn:country_code":"VE",
    "gn:dem":184,
    "gn:feature_class":"P",
    "gn:feature_code":"PPL",
    "gn:name":"Las Lajas",
    "gn:population":0,
    "gn:timezone":"America/Caracas",
    "iso:country":"VE",
    "wof:name":"Las Lajas",
    "wof:placetype":"locality"
},
  "geometry": {"coordinates":[-65.75789,9.77826],"type":"Point"}
}