{
  "type": "Feature",
  "properties": {
    "gn:admin1_code":"5",
    "gn:admin2_code":"604.0",
    "gn:admin3_code":"60413.0",
    "gn:asciiname":"El Corozo",
    "gn:cc2":"VE",
    "gn:country_code":"VE",
    "gn:dem":213,
    "gn:feature_class":"P",
    "gn:feature_code":"PPLA3",
    "gn:name":"El Corozo",
    "gn:population":0,
    "gn:timezone":"America/Caracas",
    "iso:country":"VE",
    "name:und_x_variant":[
        "Corozo Pando",
        "Corozo",
        "El Corozo"
    ],
    "wof:name":"El Corozo",
    "wof:placetype":"locality"
},
  "geometry": {"coordinates":[-70.35778000000001,8.5675],"type":"Point"}
}