{
  "type": "Feature",
  "properties": {
    "gn:admin1_code":"9",
    "gn:asciiname":"Guamal",
    "gn:country_code":"VE",
    "gn:dem":3,
    "gn:feature_class":"P",
    "gn:feature_code":"PPL",
    "gn:name":"Guamal",
    "gn:population":0,
    "gn:timezone":"America/Caracas",
    "iso:country":"VE",
    "wof:name":"Guamal",
    "wof:placetype":"locality"
},
  "geometry": {"coordinates":[-62.41667,9.51667],"type":"Point"}
}