{
  "type": "Feature",
  "properties": {
    "iso:country":"VE",
    "qs:gn_country":"VE",
    "qs:gn_fcode":"PPL",
    "qs:gn_pop":0,
    "qs:name":"San Jos\u00e9",
    "qs:name_adm0":"Venezuela",
    "qs:name_adm1":"M\u00e9rida",
    "qs:photos":139,
    "qs:photos_1k":28,
    "qs:photos_9k":1,
    "qs:photos_9r":3,
    "qs:photos_all":139,
    "qs:photos_sr":3,
    "qs:placetype":"Town",
    "qs:pop_sr":"0",
    "qs:woe_adm0":23424982,
    "wof:name":"San Jos\u00e9",
    "wof:placetype":"locality"
},
  "geometry": {"coordinates":[-71.31572,8.36176],"type":"Point"}
}