{
  "type": "Feature",
  "properties": {
    "iso:country":"VE",
    "name:ara_x_preferred":[
        "\u0625\u062e\u064a\u062f\u0648"
    ],
    "name:ben_x_preferred":[
        "\u098f\u099c\u09bf\u09a1\u09c1"
    ],
    "name:chi_x_preferred":[
        "\u57c3\u5e0c\u591a"
    ],
    "name:dan_x_preferred":[
        "Ejido"
    ],
    "name:dut_x_preferred":[
        "Ejido"
    ],
    "name:eng_x_preferred":[
        "Ejido"
    ],
    "name:epo_x_preferred":[
        "Ejido"
    ],
    "name:fin_x_preferred":[
        "Ejido"
    ],
    "name:fre_x_preferred":[
        "Ejido"
    ],
    "name:geo_x_preferred":[
        "\u10d4\u10ee\u10d8\u10d3\u10dd"
    ],
    "name:gre_x_preferred":[
        "\u0395\u03c4\u03b6\u03af\u03bd\u03c4\u03bf"
    ],
    "name:guj_x_preferred":[
        "\u0a87\u0a9c\u0abf\u0aa1\u0acb"
    ],
    "name:hin_x_preferred":[
        "\u090f\u091c\u093f\u0926\u094b"
    ],
    "name:ina_x_preferred":[
        "Ejido"
    ],
    "name:ind_x_preferred":[
        "Ejido"
    ],
    "name:ita_x_preferred":[
        "Ejido"
    ],
    "name:jpn_x_preferred":[
        "\u30a8\u30d2\u30fc\u30c9"
    ],
    "name:kan_x_preferred":[
        "\u0c8e\u0c9c\u0cbf\u0ca1\u0ccb"
    ],
    "name:kor_x_preferred":[
        "\uc5d0\ud788\ub3c4"
    ],
    "name:lav_x_preferred":[
        "Ehido"
    ],
    "name:lit_x_preferred":[
        "Echidas"
    ],
    "name:mar_x_preferred":[
        "\u090f\u091c\u093f\u0926\u094b"
    ],
    "name:may_x_preferred":[
        "Ejido"
    ],
    "name:nah_x_preferred":[
        "Ejido"
    ],
    "name:nob_x_preferred":[
        "Ejido"
    ],
    "name:pol_x_preferred":[
        "Ejido"
    ],
    "name:por_x_preferred":[
        "Ejido"
    ],
    "name:rus_x_preferred":[
        "\u042d\u0445\u0438\u0434\u043e"
    ],
    "name:scn_x_preferred":[
        "Ejido"
    ],
    "name:sin_x_preferred":[
        "\u0d91\u0da2\u0dd2\u0da9\u0ddd"
    ],
    "name:spa_x_preferred":[
        "Ejido"
    ],
    "name:swe_x_preferred":[
        "Ejido"
    ],
    "name:tam_x_preferred":[
        "\u0b8f\u0b9c\u0bbf\u0b9f\u0bcb"
    ],
    "name:tat_x_preferred":[
        "\u042d\u0445\u0438\u0434\u043e"
    ],
    "name:tel_x_preferred":[
        "\u0c07\u0c1c\u0c3f\u0c21\u0c4b"
    ],
    "name:tha_x_preferred":[
        "\u0e2d\u0e35\u0e08\u0e34\u0e42\u0e14\u0e49"
    ],
    "name:tur_x_preferred":[
        "Ejido"
    ],
    "name:ukr_x_preferred":[
        "\u0415\u0445\u0456\u0434\u043e"
    ],
    "name:unk_x_variant":[
        "Egido"
    ],
    "name:urd_x_preferred":[
        "\u06cc\u062c\u06cc\u062f\u0648 \u060c \u0648\u0646\u0632\u0648\u06cc\u0644\u06c1"
    ],
    "name:vie_x_preferred":[
        "Ejido"
    ],
    "name:vol_x_preferred":[
        "Ejido"
    ],
    "qs:gn_pop":0,
    "qs:name":"Ejido",
    "qs:name_adm0":"Venezuela",
    "qs:name_adm1":"M\u00e9rida",
    "qs:photos":106,
    "qs:photos_1k":21,
    "qs:photos_9k":1,
    "qs:photos_9r":3,
    "qs:photos_all":106,
    "qs:photos_sr":3,
    "qs:placetype":"Town",
    "qs:pop_sr":"0",
    "qs:woe_adm0":23424982,
    "wd:wordcount":697,
    "wof:name":"Ejido",
    "wof:placetype":"locality"
},
  "geometry": {"coordinates":[-71.207714,8.555474],"type":"Point"}
}