{
  "type": "Feature",
  "properties": {
    "gn:admin1_code":"13",
    "gn:asciiname":"Cararapa",
    "gn:country_code":"VE",
    "gn:dem":120,
    "gn:feature_class":"P",
    "gn:feature_code":"PPL",
    "gn:name":"Cararapa",
    "gn:population":0,
    "gn:timezone":"America/Caracas",
    "iso:country":"VE",
    "wof:name":"Cararapa",
    "wof:placetype":"locality"
},
  "geometry": {"coordinates":[-68.89004,10.64329],"type":"Point"}
}