{
  "type": "Feature",
  "properties": {
    "gn:admin1_code":"3",
    "gn:asciiname":"Inglaterra",
    "gn:cc2":"VE",
    "gn:country_code":"VE",
    "gn:dem":54,
    "gn:feature_class":"P",
    "gn:feature_code":"PPL",
    "gn:name":"Inglaterra",
    "gn:population":0,
    "gn:timezone":"America/Caracas",
    "iso:country":"VE",
    "name:und_x_variant":[
        "Engleterra",
        "Inglaterra"
    ],
    "wof:name":"Inglaterra",
    "wof:placetype":"locality"
},
  "geometry": {"coordinates":[-67.45,7.86667],"type":"Point"}
}