{
  "type": "Feature",
  "properties": {
    "gn:admin1_code":"02",
    "gn:asciiname":"Galeron",
    "gn:country_code":"VE",
    "gn:dem":542,
    "gn:feature_class":"P",
    "gn:feature_code":"PPLL",
    "gn:name":"Galer\u00f3n",
    "gn:population":0,
    "gn:timezone":"America/Caracas",
    "iso:country":"VE",
    "wof:name":"Galeron",
    "wof:placetype":"locality"
},
  "geometry": {"coordinates":[-64.34456999999999,10.05967],"type":"Point"}
}