{
  "type": "Feature",
  "properties": {
    "gn:admin1_code":"02",
    "gn:asciiname":"El Carito",
    "gn:country_code":"VE",
    "gn:dem":138,
    "gn:feature_class":"P",
    "gn:feature_code":"PPLL",
    "gn:name":"El Carito",
    "gn:population":0,
    "gn:timezone":"America/Caracas",
    "iso:country":"VE",
    "wof:name":"El Carito",
    "wof:placetype":"locality"
},
  "geometry": {"coordinates":[-64.09222,8.62],"type":"Point"}
}