{
  "type": "Feature",
  "properties": {
    "gn:admin1_code":"18.0",
    "gn:asciiname":"Banco de Morrones",
    "gn:country_code":"VE",
    "gn:dem":99,
    "gn:feature_class":"P",
    "gn:feature_code":"PPL",
    "gn:name":"Banco de Morrones",
    "gn:population":0,
    "gn:timezone":"America/Caracas",
    "iso:country":"VE",
    "wof:name":"Banco de Morrones",
    "wof:placetype":"locality"
},
  "geometry": {"coordinates":[-69.37611,8.68917],"type":"Point"}
}