{
  "type": "Feature",
  "properties": {
    "gn:admin1_code":"3",
    "gn:asciiname":"El Remolino",
    "gn:country_code":"VE",
    "gn:dem":162,
    "gn:feature_class":"P",
    "gn:feature_code":"PPL",
    "gn:name":"El Remolino",
    "gn:population":0,
    "gn:timezone":"America/Caracas",
    "iso:country":"VE",
    "name:fra_x_preferred":[
        "El Remolino"
    ],
    "name:spa_x_preferred":[
        "El Remolino"
    ],
    "wof:name":"El Remolino",
    "wof:placetype":"locality"
},
  "geometry": {"coordinates":[-71.46890999999999,7.044],"type":"Point"}
}