{
  "type": "Feature",
  "properties": {
    "gn:admin1_code":"6.0",
    "gn:asciiname":"Laja Larga",
    "gn:country_code":"VE",
    "gn:dem":47,
    "gn:feature_class":"P",
    "gn:feature_code":"PPL",
    "gn:name":"Laja Larga",
    "gn:population":0,
    "gn:timezone":"America/Caracas",
    "iso:country":"VE",
    "wof:name":"Laja Larga",
    "wof:placetype":"locality"
},
  "geometry": {"coordinates":[-67.15581,6.42478],"type":"Point"}
}