{
  "type": "Feature",
  "properties": {
    "gn:admin1_code":"11.0",
    "gn:asciiname":"La Llanada",
    "gn:country_code":"VE",
    "gn:dem":127,
    "gn:feature_class":"P",
    "gn:feature_code":"PPLL",
    "gn:name":"La Llanada",
    "gn:population":0,
    "gn:timezone":"America/Caracas",
    "iso:country":"VE",
    "wof:name":"La Llanada",
    "wof:placetype":"locality"
},
  "geometry": {"coordinates":[-69.31394,11.42452],"type":"Point"}
}