{
  "type": "Feature",
  "properties": {
    "gn:admin1_code":"11",
    "gn:asciiname":"Ricoa",
    "gn:country_code":"VE",
    "gn:dem":137,
    "gn:feature_class":"P",
    "gn:feature_code":"PPL",
    "gn:name":"Ricoa",
    "gn:population":0,
    "gn:timezone":"America/Caracas",
    "iso:country":"VE",
    "wof:name":"Ricoa",
    "wof:placetype":"locality"
},
  "geometry": {"coordinates":[-69.41967,11.29758],"type":"Point"}
}