{
  "type": "Feature",
  "properties": {
    "gn:admin1_code":"13.0",
    "gn:asciiname":"Piedra de Agua",
    "gn:country_code":"VE",
    "gn:dem":443,
    "gn:feature_class":"P",
    "gn:feature_code":"PPL",
    "gn:name":"Piedra de Agua",
    "gn:population":0,
    "gn:timezone":"America/Caracas",
    "iso:country":"VE",
    "wof:name":"Piedra de Agua",
    "wof:placetype":"locality"
},
  "geometry": {"coordinates":[-70.3509,10.11132],"type":"Point"}
}