{
  "type": "Feature",
  "properties": {
    "gn:admin1_code":"07",
    "gn:asciiname":"San Juan de Dios",
    "gn:country_code":"VE",
    "gn:dem":445,
    "gn:feature_class":"P",
    "gn:feature_code":"PPL",
    "gn:name":"San Juan de Dios",
    "gn:population":0,
    "gn:timezone":"America/Caracas",
    "iso:country":"VE",
    "wof:name":"San Juan de Dios",
    "wof:placetype":"locality"
},
  "geometry": {"coordinates":[-67.79092,10.08021],"type":"Point"}
}