{
  "type": "Feature",
  "properties": {
    "gn:admin1_code":"12.0",
    "gn:asciiname":"Los Arroyuelos",
    "gn:country_code":"VE",
    "gn:dem":125,
    "gn:feature_class":"P",
    "gn:feature_code":"PPL",
    "gn:name":"Los Arroyuelos",
    "gn:population":0,
    "gn:timezone":"America/Caracas",
    "iso:country":"VE",
    "wof:name":"Los Arroyuelos",
    "wof:placetype":"locality"
},
  "geometry": {"coordinates":[-66.73063,9.0295],"type":"Point"}
}