{
  "type": "Feature",
  "properties": {
    "gn:admin1_code":"3.0",
    "gn:asciiname":"El Guamal",
    "gn:country_code":"VE",
    "gn:dem":42,
    "gn:feature_class":"P",
    "gn:feature_code":"PPL",
    "gn:name":"El Guamal",
    "gn:population":0,
    "gn:timezone":"America/Caracas",
    "iso:country":"VE",
    "wof:name":"El Guamal",
    "wof:placetype":"locality"
},
  "geometry": {"coordinates":[-66.84756,7.72149],"type":"Point"}
}