{
  "type": "Feature",
  "properties": {
    "gn:admin1_code":"16",
    "gn:asciiname":"Las Chacaras",
    "gn:country_code":"VE",
    "gn:dem":325,
    "gn:feature_class":"P",
    "gn:feature_code":"PPL",
    "gn:name":"Las Ch\u00e1caras",
    "gn:population":0,
    "gn:timezone":"America/Caracas",
    "iso:country":"VE",
    "wof:name":"Las Chacaras",
    "wof:placetype":"locality"
},
  "geometry": {"coordinates":[-63.38902,9.95128],"type":"Point"}
}