{
  "type": "Feature",
  "properties": {
    "gn:admin1_code":"14",
    "gn:asciiname":"La Lomita",
    "gn:country_code":"VE",
    "gn:dem":1361,
    "gn:feature_class":"P",
    "gn:feature_code":"PPL",
    "gn:name":"La Lomita",
    "gn:population":0,
    "gn:timezone":"America/Caracas",
    "iso:country":"VE",
    "wof:name":"La Lomita",
    "wof:placetype":"locality"
},
  "geometry": {"coordinates":[-71.20354,8.10485],"type":"Point"}
}