{
  "type": "Feature",
  "properties": {
    "gn:admin1_code":"13",
    "gn:asciiname":"Bocoy",
    "gn:country_code":"VE",
    "gn:dem":429,
    "gn:feature_class":"P",
    "gn:feature_code":"PPL",
    "gn:name":"Bocoy",
    "gn:population":0,
    "gn:timezone":"America/Caracas",
    "iso:country":"VE",
    "wof:name":"Bocoy",
    "wof:placetype":"locality"
},
  "geometry": {"coordinates":[-69.72156,10.59454],"type":"Point"}
}