{
  "type": "Feature",
  "properties": {
    "gn:admin1_code":"15.0",
    "gn:asciiname":"Bella Vista",
    "gn:country_code":"VE",
    "gn:dem":524,
    "gn:feature_class":"P",
    "gn:feature_code":"PPLL",
    "gn:name":"Bella Vista",
    "gn:population":0,
    "gn:timezone":"America/Caracas",
    "iso:country":"VE",
    "wof:name":"Bella Vista",
    "wof:placetype":"locality"
},
  "geometry": {"coordinates":[-66.69189,10.47627],"type":"Point"}
}