{
  "type": "Feature",
  "properties": {
    "gn:admin1_code":"11",
    "gn:asciiname":"Aracua",
    "gn:country_code":"VE",
    "gn:dem":592,
    "gn:feature_class":"P",
    "gn:feature_code":"PPL",
    "gn:name":"Aracua",
    "gn:population":0,
    "gn:timezone":"America/Caracas",
    "iso:country":"VE",
    "wof:name":"Aracua",
    "wof:placetype":"locality"
},
  "geometry": {"coordinates":[-69.58750000000001,10.985],"type":"Point"}
}