{
  "type": "Feature",
  "properties": {
    "gn:admin1_code":"02",
    "gn:asciiname":"Las Marmoletas",
    "gn:country_code":"VE",
    "gn:dem":332,
    "gn:feature_class":"P",
    "gn:feature_code":"PPL",
    "gn:name":"Las Marmoletas",
    "gn:population":0,
    "gn:timezone":"America/Caracas",
    "iso:country":"VE",
    "wof:name":"Las Marmoletas",
    "wof:placetype":"locality"
},
  "geometry": {"coordinates":[-64.35556,10.02056],"type":"Point"}
}