{
  "type": "Feature",
  "properties": {
    "gn:admin1_code":"19",
    "gn:asciiname":"Quebrada de Tigre Adentro",
    "gn:country_code":"VE",
    "gn:dem":192,
    "gn:feature_class":"P",
    "gn:feature_code":"PPL",
    "gn:name":"Quebrada de Tigre Adentro",
    "gn:population":0,
    "gn:timezone":"America/Caracas",
    "iso:country":"VE",
    "wof:name":"Quebrada de Tigre Adentro",
    "wof:placetype":"locality"
},
  "geometry": {"coordinates":[-63.51331999999999,10.47368],"type":"Point"}
}