{
  "type": "Feature",
  "properties": {
    "gn:admin1_code":"11.0",
    "gn:asciiname":"Goacoita",
    "gn:country_code":"VE",
    "gn:dem":878,
    "gn:feature_class":"P",
    "gn:feature_code":"PPL",
    "gn:name":"Goacoita",
    "gn:population":0,
    "gn:timezone":"America/Caracas",
    "iso:country":"VE",
    "wof:name":"Goacoita",
    "wof:placetype":"locality"
},
  "geometry": {"coordinates":[-69.65763000000001,11.13921],"type":"Point"}
}