{
  "type": "Feature",
  "properties": {
    "gn:admin1_code":"5",
    "gn:admin2_code":"602.0",
    "gn:admin3_code":"60203.0",
    "gn:asciiname":"Chameta",
    "gn:country_code":"VE",
    "gn:dem":213,
    "gn:feature_class":"P",
    "gn:feature_code":"PPLA3",
    "gn:name":"Chameta",
    "gn:population":0,
    "gn:timezone":"America/Caracas",
    "iso:country":"VE",
    "name:und_x_variant":[
        "La Chameta",
        "Chameta"
    ],
    "wof:name":"Chameta",
    "wof:placetype":"locality"
},
  "geometry": {"coordinates":[-70.90671,8.10023],"type":"Point"}
}