{
  "type": "Feature",
  "properties": {
    "gn:admin1_code":"19.0",
    "gn:asciiname":"Chorreron",
    "gn:country_code":"VE",
    "gn:dem":1141,
    "gn:feature_class":"P",
    "gn:feature_code":"PPL",
    "gn:name":"Chorrer\u00f3n",
    "gn:population":0,
    "gn:timezone":"America/Caracas",
    "iso:country":"VE",
    "wof:name":"Chorreron",
    "wof:placetype":"locality"
},
  "geometry": {"coordinates":[-63.64376,10.23723],"type":"Point"}
}