{
  "type": "Feature",
  "properties": {
    "gn:admin1_code":"15",
    "gn:asciiname":"Curupao",
    "gn:country_code":"VE",
    "gn:dem":449,
    "gn:feature_class":"P",
    "gn:feature_code":"PPL",
    "gn:name":"Curupao",
    "gn:population":0,
    "gn:timezone":"America/Caracas",
    "iso:country":"VE",
    "name:und_x_variant":[
        "Gurupao",
        "Curupao"
    ],
    "wof:name":"Curupao",
    "wof:placetype":"locality"
},
  "geometry": {"coordinates":[-66.64423000000001,10.49964],"type":"Point"}
}