{
  "type": "Feature",
  "properties": {
    "gn:admin1_code":"12",
    "gn:asciiname":"Palambra",
    "gn:country_code":"VE",
    "gn:dem":424,
    "gn:feature_class":"P",
    "gn:feature_code":"PPL",
    "gn:name":"Palambra",
    "gn:population":0,
    "gn:timezone":"America/Caracas",
    "iso:country":"VE",
    "wof:name":"Palambra",
    "wof:placetype":"locality"
},
  "geometry": {"coordinates":[-67.51963000000001,9.81142],"type":"Point"}
}