{
  "type": "Feature",
  "properties": {
    "gn:admin1_code":"13",
    "gn:asciiname":"Campo Solo",
    "gn:country_code":"VE",
    "gn:dem":557,
    "gn:feature_class":"P",
    "gn:feature_code":"PPL",
    "gn:name":"Campo Solo",
    "gn:population":0,
    "gn:timezone":"America/Caracas",
    "iso:country":"VE",
    "wof:name":"Campo Solo",
    "wof:placetype":"locality"
},
  "geometry": {"coordinates":[-69.04343,10.40352],"type":"Point"}
}