{
  "type": "Feature",
  "properties": {
    "gn:admin1_code":"4",
    "gn:asciiname":"Guiripa",
    "gn:country_code":"VE",
    "gn:dem":794,
    "gn:feature_class":"P",
    "gn:feature_code":"PPL",
    "gn:name":"G\u00fciripa",
    "gn:population":0,
    "gn:timezone":"America/Caracas",
    "iso:country":"VE",
    "name:und_x_variant":[
        "Guripa",
        "G\u00fciripa"
    ],
    "wof:name":"Guiripa",
    "wof:placetype":"locality"
},
  "geometry": {"coordinates":[-67.01689,10.0447],"type":"Point"}
}