{
  "type": "Feature",
  "properties": {
    "gn:admin1_code":"6.0",
    "gn:asciiname":"El Merey",
    "gn:country_code":"VE",
    "gn:dem":164,
    "gn:feature_class":"P",
    "gn:feature_code":"PPL",
    "gn:name":"El Merey",
    "gn:population":0,
    "gn:timezone":"America/Caracas",
    "iso:country":"VE",
    "wof:name":"El Merey",
    "wof:placetype":"locality"
},
  "geometry": {"coordinates":[-61.44444,7.22278],"type":"Point"}
}