{
  "type": "Feature",
  "properties": {
    "gn:admin1_code":"5",
    "gn:asciiname":"El Tigre",
    "gn:country_code":"VE",
    "gn:dem":67,
    "gn:feature_class":"P",
    "gn:feature_code":"PPL",
    "gn:name":"El Tigre",
    "gn:population":0,
    "gn:timezone":"America/Caracas",
    "iso:country":"VE",
    "wof:name":"El Tigre",
    "wof:placetype":"locality"
},
  "geometry": {"coordinates":[-68.35129000000001,8.49297],"type":"Point"}
}