{
  "type": "Feature",
  "properties": {
    "gn:admin1_code":"8.0",
    "gn:asciiname":"Las Lajitas",
    "gn:country_code":"VE",
    "gn:dem":189,
    "gn:feature_class":"P",
    "gn:feature_code":"PPL",
    "gn:name":"Las Lajitas",
    "gn:population":0,
    "gn:timezone":"America/Caracas",
    "iso:country":"VE",
    "wof:name":"Las Lajitas",
    "wof:placetype":"locality"
},
  "geometry": {"coordinates":[-68.24006999999999,9.73951],"type":"Point"}
}