{
  "type": "Feature",
  "properties": {
    "gn:admin1_code":"5",
    "gn:asciiname":"La Aguadita",
    "gn:country_code":"VE",
    "gn:dem":97,
    "gn:feature_class":"P",
    "gn:feature_code":"PPL",
    "gn:name":"La Aguadita",
    "gn:population":0,
    "gn:timezone":"America/Caracas",
    "iso:country":"VE",
    "name:und_x_variant":[
        "Aguadela",
        "La Aguadita"
    ],
    "wof:name":"La Aguadita",
    "wof:placetype":"locality"
},
  "geometry": {"coordinates":[-69.56859,8.27524],"type":"Point"}
}