{
  "type": "Feature",
  "properties": {
    "gn:admin1_code":"12.0",
    "gn:asciiname":"Kilometro 133",
    "gn:country_code":"VE",
    "gn:dem":185,
    "gn:feature_class":"P",
    "gn:feature_code":"PPL",
    "gn:name":"Kil\u00f3metro 133",
    "gn:population":0,
    "gn:timezone":"America/Caracas",
    "iso:country":"VE",
    "wof:name":"Kilometro 133",
    "wof:placetype":"locality"
},
  "geometry": {"coordinates":[-65.63564000000001,9.57518],"type":"Point"}
}