{
  "type": "Feature",
  "properties": {
    "gn:admin1_code":"4.0",
    "gn:asciiname":"Roncador",
    "gn:country_code":"VE",
    "gn:dem":782,
    "gn:feature_class":"P",
    "gn:feature_code":"PPL",
    "gn:name":"Roncador",
    "gn:population":0,
    "gn:timezone":"America/Caracas",
    "iso:country":"VE",
    "wof:name":"Roncador",
    "wof:placetype":"locality"
},
  "geometry": {"coordinates":[-67.04779000000001,10.02505],"type":"Point"}
}