{
  "type": "Feature",
  "properties": {
    "gn:admin1_code":"02",
    "gn:asciiname":"Paujisal",
    "gn:country_code":"VE",
    "gn:dem":158,
    "gn:feature_class":"P",
    "gn:feature_code":"PPLL",
    "gn:name":"Paujisal",
    "gn:population":0,
    "gn:timezone":"America/Caracas",
    "iso:country":"VE",
    "wof:name":"Paujisal",
    "wof:placetype":"locality"
},
  "geometry": {"coordinates":[-65.49069,9.93249],"type":"Point"}
}