{
  "type": "Feature",
  "properties": {
    "gn:admin1_code":"18.0",
    "gn:asciiname":"El Carretero",
    "gn:country_code":"VE",
    "gn:dem":118,
    "gn:feature_class":"P",
    "gn:feature_code":"PPL",
    "gn:name":"El Carretero",
    "gn:population":0,
    "gn:timezone":"America/Caracas",
    "iso:country":"VE",
    "name:spa_x_preferred":[
        "El Carretero"
    ],
    "wof:name":"El Carretero",
    "wof:placetype":"locality"
},
  "geometry": {"coordinates":[-69.03501999999999,9.27871],"type":"Point"}
}