{
  "type": "Feature",
  "properties": {
    "gn:admin1_code":"11.0",
    "gn:asciiname":"La Sabana",
    "gn:country_code":"VE",
    "gn:dem":1057,
    "gn:feature_class":"P",
    "gn:feature_code":"PPL",
    "gn:name":"La Sabana",
    "gn:population":0,
    "gn:timezone":"America/Caracas",
    "iso:country":"VE",
    "name:ceb_x_preferred":[
        "La S\u00e1bana"
    ],
    "name:spa_x_preferred":[
        "La Sabana"
    ],
    "name:urd_x_preferred":[
        "\u0644\u0627 \u0633\u0627\u0628\u0627\u0646\u0627"
    ],
    "wof:name":"La Sabana",
    "wof:placetype":"locality"
},
  "geometry": {"coordinates":[-70.40685000000001,10.85485],"type":"Point"}
}