{
  "type": "Feature",
  "properties": {
    "gn:admin1_code":"12.0",
    "gn:asciiname":"La Castillera",
    "gn:country_code":"VE",
    "gn:dem":288,
    "gn:feature_class":"P",
    "gn:feature_code":"PPLL",
    "gn:name":"La Castillera",
    "gn:population":0,
    "gn:timezone":"America/Caracas",
    "iso:country":"VE",
    "wof:name":"La Castillera",
    "wof:placetype":"locality"
},
  "geometry": {"coordinates":[-66.05405,9.80516],"type":"Point"}
}