{
  "type": "Feature",
  "properties": {
    "gn:admin1_code":"15",
    "gn:asciiname":"Yaguapa",
    "gn:country_code":"VE",
    "gn:dem":122,
    "gn:feature_class":"P",
    "gn:feature_code":"PPL",
    "gn:name":"Yaguapa",
    "gn:population":0,
    "gn:timezone":"America/Caracas",
    "iso:country":"VE",
    "wof:name":"Yaguapa",
    "wof:placetype":"locality"
},
  "geometry": {"coordinates":[-66.29038,10.38847],"type":"Point"}
}