{
  "type": "Feature",
  "properties": {
    "gn:admin1_code":"6.0",
    "gn:asciiname":"Chapepe",
    "gn:country_code":"VE",
    "gn:dem":103,
    "gn:feature_class":"P",
    "gn:feature_code":"PPL",
    "gn:name":"Chapepe",
    "gn:population":0,
    "gn:timezone":"America/Caracas",
    "iso:country":"VE",
    "wof:name":"Chapepe",
    "wof:placetype":"locality"
},
  "geometry": {"coordinates":[-64.09058,7.76096],"type":"Point"}
}