{
  "type": "Feature",
  "properties": {
    "gn:admin1_code":"15",
    "gn:asciiname":"Los Chaguaramos",
    "gn:country_code":"VE",
    "gn:dem":558,
    "gn:feature_class":"P",
    "gn:feature_code":"PPL",
    "gn:name":"Los Chaguaramos",
    "gn:population":0,
    "gn:timezone":"America/Caracas",
    "iso:country":"VE",
    "wof:name":"Los Chaguaramos",
    "wof:placetype":"locality"
},
  "geometry": {"coordinates":[-66.94773000000001,10.04651],"type":"Point"}
}