{
  "type": "Feature",
  "properties": {
    "gn:admin1_code":"14",
    "gn:asciiname":"El Cerrajon",
    "gn:country_code":"VE",
    "gn:dem":1491,
    "gn:feature_class":"P",
    "gn:feature_code":"PPL",
    "gn:name":"El Cerraj\u00f3n",
    "gn:population":0,
    "gn:timezone":"America/Caracas",
    "iso:country":"VE",
    "wof:name":"El Cerrajon",
    "wof:placetype":"locality"
},
  "geometry": {"coordinates":[-71.13056,8.315],"type":"Point"}
}