{
  "type": "Feature",
  "properties": {
    "gn:admin1_code":"12",
    "gn:asciiname":"El Acapral",
    "gn:country_code":"VE",
    "gn:dem":87,
    "gn:feature_class":"P",
    "gn:feature_code":"PPL",
    "gn:name":"El Acapral",
    "gn:population":0,
    "gn:timezone":"America/Caracas",
    "iso:country":"VE",
    "wof:name":"El Acapral",
    "wof:placetype":"locality"
},
  "geometry": {"coordinates":[-65.68810999999999,9.33734],"type":"Point"}
}