{
  "type": "Feature",
  "properties": {
    "gn:admin1_code":"19.0",
    "gn:asciiname":"Catuaro",
    "gn:country_code":"VE",
    "gn:dem":111,
    "gn:feature_class":"P",
    "gn:feature_code":"PPL",
    "gn:name":"Catuaro",
    "gn:population":0,
    "gn:timezone":"America/Caracas",
    "iso:country":"VE",
    "wof:name":"Catuaro",
    "wof:placetype":"locality"
},
  "geometry": {"coordinates":[-63.04183,10.64494],"type":"Point"}
}