{
  "type": "Feature",
  "properties": {
    "gn:admin1_code":"13.0",
    "gn:asciiname":"Macuto",
    "gn:country_code":"VE",
    "gn:dem":558,
    "gn:feature_class":"P",
    "gn:feature_code":"PPL",
    "gn:name":"Macuto",
    "gn:population":0,
    "gn:timezone":"America/Caracas",
    "iso:country":"VE",
    "wof:name":"Macuto",
    "wof:placetype":"locality"
},
  "geometry": {"coordinates":[-69.30775,10.04792],"type":"Point"}
}