{
  "type": "Feature",
  "properties": {
    "gn:admin1_code":"02",
    "gn:asciiname":"Los Mamones",
    "gn:country_code":"VE",
    "gn:dem":27,
    "gn:feature_class":"P",
    "gn:feature_code":"PPL",
    "gn:name":"Los Mamones",
    "gn:population":0,
    "gn:timezone":"America/Caracas",
    "iso:country":"VE",
    "wof:name":"Los Mamones",
    "wof:placetype":"locality"
},
  "geometry": {"coordinates":[-65.18486999999999,9.6121],"type":"Point"}
}