{
  "type": "Feature",
  "properties": {
    "gn:admin1_code":"16",
    "gn:asciiname":"Botabanero",
    "gn:country_code":"VE",
    "gn:dem":66,
    "gn:feature_class":"P",
    "gn:feature_code":"PPLL",
    "gn:name":"Botabanero",
    "gn:population":0,
    "gn:timezone":"America/Caracas",
    "iso:country":"VE",
    "wof:name":"Botabanero",
    "wof:placetype":"locality"
},
  "geometry": {"coordinates":[-63.03656,8.71642],"type":"Point"}
}