{
  "type": "Feature",
  "properties": {
    "gn:admin1_code":"19.0",
    "gn:asciiname":"Las Trampas",
    "gn:country_code":"VE",
    "gn:dem":582,
    "gn:feature_class":"P",
    "gn:feature_code":"PPL",
    "gn:name":"Las Trampas",
    "gn:population":0,
    "gn:timezone":"America/Caracas",
    "iso:country":"VE",
    "wof:name":"Las Trampas",
    "wof:placetype":"locality"
},
  "geometry": {"coordinates":[-64.41049,10.15977],"type":"Point"}
}