{
  "type": "Feature",
  "properties": {
    "gn:admin1_code":"12",
    "gn:asciiname":"Los Almizcles",
    "gn:country_code":"VE",
    "gn:dem":165,
    "gn:feature_class":"P",
    "gn:feature_code":"PPL",
    "gn:name":"Los Almizcles",
    "gn:population":0,
    "gn:timezone":"America/Caracas",
    "iso:country":"VE",
    "wof:name":"Los Almizcles",
    "wof:placetype":"locality"
},
  "geometry": {"coordinates":[-66.53945999999999,9.32486],"type":"Point"}
}