{
  "type": "Feature",
  "properties": {
    "gn:admin1_code":"19.0",
    "gn:asciiname":"Guaraguara",
    "gn:country_code":"VE",
    "gn:dem":206,
    "gn:feature_class":"P",
    "gn:feature_code":"PPL",
    "gn:name":"Guaraguara",
    "gn:population":0,
    "gn:timezone":"America/Caracas",
    "iso:country":"VE",
    "wof:name":"Guaraguara",
    "wof:placetype":"locality"
},
  "geometry": {"coordinates":[-63.18775,10.42728],"type":"Point"}
}