{
  "type": "Feature",
  "properties": {
    "gn:admin1_code":"15",
    "gn:asciiname":"Pan de Azucar",
    "gn:country_code":"VE",
    "gn:dem":1232,
    "gn:feature_class":"P",
    "gn:feature_code":"PPL",
    "gn:name":"Pan de Az\u00facar",
    "gn:population":0,
    "gn:timezone":"America/Caracas",
    "iso:country":"VE",
    "wof:name":"Pan de Azucar",
    "wof:placetype":"locality"
},
  "geometry": {"coordinates":[-67.01666999999999,10.36667],"type":"Point"}
}