{
  "type": "Feature",
  "properties": {
    "gn:admin1_code":"15.0",
    "gn:asciiname":"Guaratalupe",
    "gn:country_code":"VE",
    "gn:dem":19,
    "gn:feature_class":"P",
    "gn:feature_code":"PPLL",
    "gn:name":"Guaratalupe",
    "gn:population":0,
    "gn:timezone":"America/Caracas",
    "iso:country":"VE",
    "wof:name":"Guaratalupe",
    "wof:placetype":"locality"
},
  "geometry": {"coordinates":[-66.12376,10.39927],"type":"Point"}
}