{
  "type": "Feature",
  "properties": {
    "gn:admin1_code":"19",
    "gn:asciiname":"Capiantar",
    "gn:country_code":"VE",
    "gn:dem":7,
    "gn:feature_class":"P",
    "gn:feature_code":"PPL",
    "gn:name":"Capiantar",
    "gn:population":0,
    "gn:timezone":"America/Caracas",
    "iso:country":"VE",
    "wof:name":"Capiantar",
    "wof:placetype":"locality"
},
  "geometry": {"coordinates":[-63.86787,10.44209],"type":"Point"}
}