{
  "type": "Feature",
  "properties": {
    "gn:admin1_code":"6.0",
    "gn:asciiname":"La Bendicion",
    "gn:country_code":"VE",
    "gn:dem":179,
    "gn:feature_class":"P",
    "gn:feature_code":"PPL",
    "gn:name":"La Bendici\u00f3n",
    "gn:population":0,
    "gn:timezone":"America/Caracas",
    "iso:country":"VE",
    "wof:name":"La Bendicion",
    "wof:placetype":"locality"
},
  "geometry": {"coordinates":[-63.72079,7.73221],"type":"Point"}
}