{
  "type": "Feature",
  "properties": {
    "gn:admin1_code":"23.0",
    "gn:asciiname":"Soler",
    "gn:country_code":"VE",
    "gn:dem":29,
    "gn:feature_class":"P",
    "gn:feature_code":"PPLL",
    "gn:name":"Soler",
    "gn:population":0,
    "gn:timezone":"America/Caracas",
    "iso:country":"VE",
    "name:bul_x_preferred":[
        "\u0421\u043e\u043b\u0435\u0440"
    ],
    "name:cat_x_preferred":[
        "Soler"
    ],
    "name:deu_x_preferred":[
        "Soler"
    ],
    "name:fra_x_preferred":[
        "Soler"
    ],
    "name:heb_x_preferred":[
        "\u05e1\u05d5\u05dc\u05e8"
    ],
    "name:ita_x_preferred":[
        "Soler"
    ],
    "name:jpn_x_preferred":[
        "\u30bd\u30ec\u30eb"
    ],
    "name:rus_x_preferred":[
        "\u0421\u043e\u043b\u0435\u0440"
    ],
    "name:slv_x_preferred":[
        "Soler"
    ],
    "name:spa_x_preferred":[
        "Soler"
    ],
    "wof:name":"Soler",
    "wof:placetype":"locality"
},
  "geometry": {"coordinates":[-71.84124,10.41576],"type":"Point"}
}