{
  "type": "Feature",
  "properties": {
    "gn:admin1_code":"5",
    "gn:asciiname":"El Infierno",
    "gn:country_code":"VE",
    "gn:dem":152,
    "gn:feature_class":"P",
    "gn:feature_code":"PPL",
    "gn:name":"El Infierno",
    "gn:population":0,
    "gn:timezone":"America/Caracas",
    "iso:country":"VE",
    "wof:name":"El Infierno",
    "wof:placetype":"locality"
},
  "geometry": {"coordinates":[-70.41667,8.35],"type":"Point"}
}