{
  "type": "Feature",
  "properties": {
    "gn:admin1_code":"13",
    "gn:asciiname":"Bojo",
    "gn:country_code":"VE",
    "gn:dem":1450,
    "gn:feature_class":"P",
    "gn:feature_code":"PPL",
    "gn:name":"Boj\u00f3",
    "gn:population":0,
    "gn:timezone":"America/Caracas",
    "iso:country":"VE",
    "wof:name":"Bojo",
    "wof:placetype":"locality"
},
  "geometry": {"coordinates":[-69.62255,9.74203],"type":"Point"}
}