{
  "type": "Feature",
  "properties": {
    "gn:admin1_code":"6.0",
    "gn:asciiname":"Laguna Alta",
    "gn:country_code":"VE",
    "gn:dem":198,
    "gn:feature_class":"P",
    "gn:feature_code":"PPL",
    "gn:name":"Laguna Alta",
    "gn:population":0,
    "gn:timezone":"America/Caracas",
    "iso:country":"VE",
    "wof:name":"Laguna Alta",
    "wof:placetype":"locality"
},
  "geometry": {"coordinates":[-63.26,7.83389],"type":"Point"}
}