{
  "type": "Feature",
  "properties": {
    "gn:admin1_code":"15",
    "gn:asciiname":"Aponte",
    "gn:country_code":"VE",
    "gn:dem":61,
    "gn:feature_class":"P",
    "gn:feature_code":"PPL",
    "gn:name":"Aponte",
    "gn:population":0,
    "gn:timezone":"America/Caracas",
    "iso:country":"VE",
    "wof:name":"Aponte",
    "wof:placetype":"locality"
},
  "geometry": {"coordinates":[-66.45810999999999,10.21708],"type":"Point"}
}