{
  "type": "Feature",
  "properties": {
    "gn:admin1_code":"23.0",
    "gn:asciiname":"Las Cuatro Bocas",
    "gn:country_code":"VE",
    "gn:dem":47,
    "gn:feature_class":"P",
    "gn:feature_code":"PPL",
    "gn:name":"Las Cuatro Bocas",
    "gn:population":0,
    "gn:timezone":"America/Caracas",
    "iso:country":"VE",
    "wof:name":"Las Cuatro Bocas",
    "wof:placetype":"locality"
},
  "geometry": {"coordinates":[-71.77889,10.77889],"type":"Point"}
}