{
  "type": "Feature",
  "properties": {
    "gn:admin1_code":"6.0",
    "gn:asciiname":"Las Matas",
    "gn:country_code":"VE",
    "gn:dem":163,
    "gn:feature_class":"P",
    "gn:feature_code":"PPL",
    "gn:name":"Las Matas",
    "gn:population":0,
    "gn:timezone":"America/Caracas",
    "iso:country":"VE",
    "wof:name":"Las Matas",
    "wof:placetype":"locality"
},
  "geometry": {"coordinates":[-66.09611,6.90444],"type":"Point"}
}