{
  "type": "Feature",
  "properties": {
    "gn:admin1_code":"19.0",
    "gn:asciiname":"Las Puertas",
    "gn:country_code":"VE",
    "gn:dem":409,
    "gn:feature_class":"P",
    "gn:feature_code":"PPLL",
    "gn:name":"Las Puertas",
    "gn:population":0,
    "gn:timezone":"America/Caracas",
    "iso:country":"VE",
    "wof:name":"Las Puertas",
    "wof:placetype":"locality"
},
  "geometry": {"coordinates":[-63.97818,10.27459],"type":"Point"}
}