{
  "type": "Feature",
  "properties": {
    "gn:admin1_code":"13.0",
    "gn:asciiname":"El Tinajon",
    "gn:country_code":"VE",
    "gn:dem":741,
    "gn:feature_class":"P",
    "gn:feature_code":"PPL",
    "gn:name":"El Tinaj\u00f3n",
    "gn:population":0,
    "gn:timezone":"America/Caracas",
    "iso:country":"VE",
    "wof:name":"El Tinajon",
    "wof:placetype":"locality"
},
  "geometry": {"coordinates":[-70.58221999999998,10.41778],"type":"Point"}
}