{
  "type": "Feature",
  "properties": {
    "gn:admin1_code":"12.0",
    "gn:asciiname":"Parate Ahi",
    "gn:country_code":"VE",
    "gn:dem":32,
    "gn:feature_class":"P",
    "gn:feature_code":"PPL",
    "gn:name":"P\u00e1rate Ah\u00ed",
    "gn:population":0,
    "gn:timezone":"America/Caracas",
    "iso:country":"VE",
    "wof:name":"Parate Ahi",
    "wof:placetype":"locality"
},
  "geometry": {"coordinates":[-66.29948,7.66801],"type":"Point"}
}