{
  "type": "Feature",
  "properties": {
    "gn:admin1_code":"19.0",
    "gn:asciiname":"Canturria",
    "gn:country_code":"VE",
    "gn:dem":102,
    "gn:feature_class":"P",
    "gn:feature_code":"PPL",
    "gn:name":"Canturria",
    "gn:population":0,
    "gn:timezone":"America/Caracas",
    "iso:country":"VE",
    "wof:name":"Canturria",
    "wof:placetype":"locality"
},
  "geometry": {"coordinates":[-64.10281999999999,10.40249],"type":"Point"}
}