{
  "type": "Feature",
  "properties": {
    "gn:admin1_code":"5",
    "gn:asciiname":"La Matiera",
    "gn:country_code":"VE",
    "gn:dem":160,
    "gn:feature_class":"P",
    "gn:feature_code":"PPL",
    "gn:name":"La Matiera",
    "gn:population":0,
    "gn:timezone":"America/Caracas",
    "iso:country":"VE",
    "name:und_x_variant":[
        "La Matera",
        "La Matiera"
    ],
    "wof:name":"La Matiera",
    "wof:placetype":"locality"
},
  "geometry": {"coordinates":[-70.11898000000001,8.64368],"type":"Point"}
}