{
  "type": "Feature",
  "properties": {
    "gn:admin1_code":"3.0",
    "gn:asciiname":"El Chircal",
    "gn:country_code":"VE",
    "gn:dem":47,
    "gn:feature_class":"P",
    "gn:feature_code":"PPLL",
    "gn:name":"El Chircal",
    "gn:population":0,
    "gn:timezone":"America/Caracas",
    "iso:country":"VE",
    "wof:name":"El Chircal",
    "wof:placetype":"locality"
},
  "geometry": {"coordinates":[-67.44221999999999,6.20611],"type":"Point"}
}