{
  "type": "Feature",
  "properties": {
    "gn:admin1_code":"4.0",
    "gn:asciiname":"Caicara",
    "gn:country_code":"VE",
    "gn:dem":860,
    "gn:feature_class":"P",
    "gn:feature_code":"PPL",
    "gn:name":"Caicara",
    "gn:population":0,
    "gn:timezone":"America/Caracas",
    "iso:country":"VE",
    "name:ceb_x_preferred":[
        "Caicara"
    ],
    "name:deu_x_preferred":[
        "Caicara"
    ],
    "name:fra_x_preferred":[
        "Caicara"
    ],
    "name:ita_x_preferred":[
        "Caicara"
    ],
    "name:nld_x_preferred":[
        "Caicara"
    ],
    "name:spa_x_preferred":[
        "Caicara"
    ],
    "name:swe_x_preferred":[
        "Caicara"
    ],
    "wof:name":"Caicara",
    "wof:placetype":"locality"
},
  "geometry": {"coordinates":[-67.31228,10.09774],"type":"Point"}
}