{
  "type": "Feature",
  "properties": {
    "gn:admin1_code":"2",
    "gn:asciiname":"Los Cuajos",
    "gn:country_code":"VE",
    "gn:dem":149,
    "gn:feature_class":"P",
    "gn:feature_code":"PPL",
    "gn:name":"Los Cuajos",
    "gn:population":0,
    "gn:timezone":"America/Caracas",
    "iso:country":"VE",
    "wof:name":"Los Cuajos",
    "wof:placetype":"locality"
},
  "geometry": {"coordinates":[-64.26174,8.34072],"type":"Point"}
}