{
  "type": "Feature",
  "properties": {
    "gn:admin1_code":"11",
    "gn:asciiname":"San Patricio",
    "gn:country_code":"VE",
    "gn:dem":204,
    "gn:feature_class":"P",
    "gn:feature_code":"PPL",
    "gn:name":"San Patricio",
    "gn:population":0,
    "gn:timezone":"America/Caracas",
    "iso:country":"VE",
    "name:ceb_x_preferred":[
        "San Patricio"
    ],
    "name:deu_x_preferred":[
        "San Patricio"
    ],
    "name:ita_x_preferred":[
        "San Patricio"
    ],
    "name:pol_x_preferred":[
        "San Patricio"
    ],
    "name:por_x_preferred":[
        "San Patricio"
    ],
    "name:spa_x_preferred":[
        "San Patricio"
    ],
    "name:srp_x_preferred":[
        "\u0421\u0430\u043d \u041f\u0430\u0442\u0440\u0438\u0448\u0438\u043e"
    ],
    "name:swe_x_preferred":[
        "San Patricio"
    ],
    "name:und_x_variant":[
        "San Patric\u00f3n",
        "San Patricio"
    ],
    "wof:name":"San Patricio",
    "wof:placetype":"locality"
},
  "geometry": {"coordinates":[-69.28752,11.4719],"type":"Point"}
}