{
  "type": "Feature",
  "properties": {
    "gn:admin1_code":"16.0",
    "gn:asciiname":"Cambural",
    "gn:country_code":"VE",
    "gn:dem":259,
    "gn:feature_class":"P",
    "gn:feature_code":"PPL",
    "gn:name":"Cambural",
    "gn:population":0,
    "gn:timezone":"America/Caracas",
    "iso:country":"VE",
    "wof:name":"Cambural",
    "wof:placetype":"locality"
},
  "geometry": {"coordinates":[-63.79833000000001,9.96444],"type":"Point"}
}