{
  "type": "Feature",
  "properties": {
    "gn:admin1_code":"23.0",
    "gn:asciiname":"Portugal",
    "gn:country_code":"VE",
    "gn:dem":19,
    "gn:feature_class":"P",
    "gn:feature_code":"PPL",
    "gn:name":"Portugal",
    "gn:population":0,
    "gn:timezone":"America/Caracas",
    "iso:country":"VE",
    "wof:name":"Portugal",
    "wof:placetype":"locality"
},
  "geometry": {"coordinates":[-72.43459,9.56006],"type":"Point"}
}