{
  "type": "Feature",
  "properties": {
    "gn:admin1_code":"14.0",
    "gn:asciiname":"La Aguadita",
    "gn:country_code":"VE",
    "gn:dem":1852,
    "gn:feature_class":"P",
    "gn:feature_code":"PPLL",
    "gn:name":"La Aguadita",
    "gn:population":0,
    "gn:timezone":"America/Caracas",
    "iso:country":"VE",
    "wof:name":"La Aguadita",
    "wof:placetype":"locality"
},
  "geometry": {"coordinates":[-71.73265000000001,8.27002],"type":"Point"}
}