{
  "type": "Feature",
  "properties": {
    "gn:admin1_code":"13",
    "gn:asciiname":"Balsamito",
    "gn:country_code":"VE",
    "gn:dem":559,
    "gn:feature_class":"P",
    "gn:feature_code":"PPL",
    "gn:name":"Balsamito",
    "gn:population":0,
    "gn:timezone":"America/Caracas",
    "iso:country":"VE",
    "wof:name":"Balsamito",
    "wof:placetype":"locality"
},
  "geometry": {"coordinates":[-69.97856999999999,10.12384],"type":"Point"}
}