{
  "type": "Feature",
  "properties": {
    "gn:admin1_code":"23.0",
    "gn:asciiname":"Atascoso",
    "gn:country_code":"VE",
    "gn:dem":2,
    "gn:feature_class":"P",
    "gn:feature_code":"PPL",
    "gn:name":"Atascoso",
    "gn:population":0,
    "gn:timezone":"America/Caracas",
    "iso:country":"VE",
    "wof:name":"Atascoso",
    "wof:placetype":"locality"
},
  "geometry": {"coordinates":[-72.07762,8.96759],"type":"Point"}
}