{
  "type": "Feature",
  "properties": {
    "gn:admin1_code":"15",
    "gn:asciiname":"Los Rosos",
    "gn:country_code":"VE",
    "gn:dem":472,
    "gn:feature_class":"P",
    "gn:feature_code":"PPL",
    "gn:name":"Los Rosos",
    "gn:population":0,
    "gn:timezone":"America/Caracas",
    "iso:country":"VE",
    "wof:name":"Los Rosos",
    "wof:placetype":"locality"
},
  "geometry": {"coordinates":[-66.92629000000001,10.08156],"type":"Point"}
}