{
  "type": "Feature",
  "properties": {
    "gn:admin1_code":"11",
    "gn:asciiname":"El Pantano",
    "gn:country_code":"VE",
    "gn:dem":833,
    "gn:feature_class":"P",
    "gn:feature_code":"PPL",
    "gn:name":"El Pantano",
    "gn:population":0,
    "gn:timezone":"America/Caracas",
    "iso:country":"VE",
    "name:ita_x_preferred":[
        "El Pantano"
    ],
    "name:spa_x_preferred":[
        "El Pantano"
    ],
    "name:zho_x_preferred":[
        "\u57c3\u5c14\u6f58\u5854\u8bfa"
    ],
    "wof:name":"El Pantano",
    "wof:placetype":"locality"
},
  "geometry": {"coordinates":[-69.11634000000001,10.85771],"type":"Point"}
}