{
  "type": "Feature",
  "properties": {
    "gn:admin1_code":"26",
    "gn:asciiname":"Oficina Pauarigua",
    "gn:country_code":"VE",
    "gn:dem":-9999,
    "gn:feature_class":"P",
    "gn:feature_code":"PPL",
    "gn:name":"Oficina Pauarigua",
    "gn:population":0,
    "gn:timezone":"America/Caracas",
    "iso:country":"VE",
    "wof:name":"Oficina Pauarigua",
    "wof:placetype":"locality"
},
  "geometry": {"coordinates":[-67.34999999999999,10.55],"type":"Point"}
}