{
  "type": "Feature",
  "properties": {
    "gn:admin1_code":"20.0",
    "gn:asciiname":"La Hormiga",
    "gn:country_code":"VE",
    "gn:dem":964,
    "gn:feature_class":"P",
    "gn:feature_code":"PPL",
    "gn:name":"La Hormiga",
    "gn:population":0,
    "gn:timezone":"America/Caracas",
    "iso:country":"VE",
    "wof:name":"La Hormiga",
    "wof:placetype":"locality"
},
  "geometry": {"coordinates":[-71.81732,7.8216],"type":"Point"}
}