{
  "type": "Feature",
  "properties": {
    "gn:admin1_code":"12",
    "gn:asciiname":"La Fabrica",
    "gn:country_code":"VE",
    "gn:dem":107,
    "gn:feature_class":"P",
    "gn:feature_code":"PPL",
    "gn:name":"La F\u00e1brica",
    "gn:population":0,
    "gn:timezone":"America/Caracas",
    "iso:country":"VE",
    "wof:name":"La Fabrica",
    "wof:placetype":"locality"
},
  "geometry": {"coordinates":[-65.63944000000001,9.19778],"type":"Point"}
}