{
  "type": "Feature",
  "properties": {
    "gn:admin1_code":"1",
    "gn:asciiname":"Laja Suiza",
    "gn:country_code":"VE",
    "gn:dem":101,
    "gn:feature_class":"P",
    "gn:feature_code":"PPL",
    "gn:name":"Laja Suiza",
    "gn:population":0,
    "gn:timezone":"America/Caracas",
    "iso:country":"VE",
    "wof:name":"Laja Suiza",
    "wof:placetype":"locality"
},
  "geometry": {"coordinates":[-67.42833,3.20611],"type":"Point"}
}