{
  "type": "Feature",
  "properties": {
    "gn:admin1_code":"6.0",
    "gn:asciiname":"Polleta",
    "gn:country_code":"VE",
    "gn:dem":22,
    "gn:feature_class":"P",
    "gn:feature_code":"PPL",
    "gn:name":"Polleta",
    "gn:population":0,
    "gn:timezone":"America/Caracas",
    "iso:country":"VE",
    "wof:name":"Polleta",
    "wof:placetype":"locality"
},
  "geometry": {"coordinates":[-64.29863,8.00529],"type":"Point"}
}