{
  "type": "Feature",
  "properties": {
    "gn:admin1_code":"21",
    "gn:asciiname":"El Chao",
    "gn:country_code":"VE",
    "gn:dem":1167,
    "gn:feature_class":"P",
    "gn:feature_code":"PPL",
    "gn:name":"El Chao",
    "gn:population":0,
    "gn:timezone":"America/Caracas",
    "iso:country":"VE",
    "wof:name":"El Chao",
    "wof:placetype":"locality"
},
  "geometry": {"coordinates":[-70.24734000000001,9.59683],"type":"Point"}
}