{
  "type": "Feature",
  "properties": {
    "gn:admin1_code":"23",
    "gn:asciiname":"El Campamento",
    "gn:country_code":"VE",
    "gn:dem":7,
    "gn:feature_class":"P",
    "gn:feature_code":"PPL",
    "gn:name":"El Campamento",
    "gn:population":0,
    "gn:timezone":"America/Caracas",
    "iso:country":"VE",
    "name:und_x_variant":[
        "Campamento",
        "El Campamento"
    ],
    "wof:name":"El Campamento",
    "wof:placetype":"locality"
},
  "geometry": {"coordinates":[-71.97762,11.36006],"type":"Point"}
}