{
  "type": "Feature",
  "properties": {
    "gn:admin1_code":"13",
    "gn:asciiname":"El Abra",
    "gn:country_code":"VE",
    "gn:dem":243,
    "gn:feature_class":"P",
    "gn:feature_code":"PPL",
    "gn:name":"El Abra",
    "gn:population":0,
    "gn:timezone":"America/Caracas",
    "iso:country":"VE",
    "wof:name":"El Abra",
    "wof:placetype":"locality"
},
  "geometry": {"coordinates":[-69.60093000000001,10.63385],"type":"Point"}
}