{
  "type": "Feature",
  "properties": {
    "gn:admin1_code":"23",
    "gn:asciiname":"Santa Rosa",
    "gn:country_code":"VE",
    "gn:dem":-9999,
    "gn:feature_class":"P",
    "gn:feature_code":"PPL",
    "gn:name":"Santa Rosa",
    "gn:population":0,
    "gn:timezone":"America/Caracas",
    "iso:country":"VE",
    "wof:name":"Santa Rosa",
    "wof:placetype":"locality"
},
  "geometry": {"coordinates":[-71.59999999999999,10.71667],"type":"Point"}
}