{
  "type": "Feature",
  "properties": {
    "gn:admin1_code":"12.0",
    "gn:asciiname":"La Catalinera",
    "gn:country_code":"VE",
    "gn:dem":295,
    "gn:feature_class":"P",
    "gn:feature_code":"PPL",
    "gn:name":"La Catalinera",
    "gn:population":0,
    "gn:timezone":"America/Caracas",
    "iso:country":"VE",
    "wof:name":"La Catalinera",
    "wof:placetype":"locality"
},
  "geometry": {"coordinates":[-66.29966,9.77355],"type":"Point"}
}