{
  "type": "Feature",
  "properties": {
    "gn:admin1_code":"13.0",
    "gn:asciiname":"Quebrada Negra",
    "gn:country_code":"VE",
    "gn:dem":1373,
    "gn:feature_class":"P",
    "gn:feature_code":"PPL",
    "gn:name":"Quebrada Negra",
    "gn:population":0,
    "gn:timezone":"America/Caracas",
    "iso:country":"VE",
    "wof:name":"Quebrada Negra",
    "wof:placetype":"locality"
},
  "geometry": {"coordinates":[-70.00688000000001,9.6418],"type":"Point"}
}