{
  "type": "Feature",
  "properties": {
    "gn:admin1_code":"22",
    "gn:asciiname":"El Caliche",
    "gn:country_code":"VE",
    "gn:dem":329,
    "gn:feature_class":"P",
    "gn:feature_code":"PPL",
    "gn:name":"El Caliche",
    "gn:population":0,
    "gn:timezone":"America/Caracas",
    "iso:country":"VE",
    "wof:name":"El Caliche",
    "wof:placetype":"locality"
},
  "geometry": {"coordinates":[-68.77531,10.12812],"type":"Point"}
}