{
  "type": "Feature",
  "properties": {
    "gn:admin1_code":"15",
    "gn:asciiname":"Hornito",
    "gn:country_code":"VE",
    "gn:dem":227,
    "gn:feature_class":"P",
    "gn:feature_code":"PPL",
    "gn:name":"Hornito",
    "gn:population":0,
    "gn:timezone":"America/Caracas",
    "iso:country":"VE",
    "wof:name":"Hornito",
    "wof:placetype":"locality"
},
  "geometry": {"coordinates":[-66.73971999999999,10.09267],"type":"Point"}
}