{
  "type": "Feature",
  "properties": {
    "gn:admin1_code":"15",
    "gn:asciiname":"Hornito",
    "gn:country_code":"VE",
    "gn:dem":227,
    "gn:feature_class":"P",
    "gn:feature_code":"PPL",
    "gn:name":"Hornito",
    "gn:population":0,
    "gn:timezone":"America/Caracas",
    "iso:country":"VE",
    "name:deu_x_preferred":[
        "Hornito"
    ],
    "name:fra_x_preferred":[
        "Hornito"
    ],
    "name:isl_x_preferred":[
        "Hraunketill"
    ],
    "name:kor_x_preferred":[
        "\ud638\ub2c8\ud1a0"
    ],
    "name:nld_x_preferred":[
        "Hornito"
    ],
    "name:por_x_preferred":[
        "Hornito"
    ],
    "wof:name":"Hornito",
    "wof:placetype":"locality"
},
  "geometry": {"coordinates":[-66.73971999999999,10.09267],"type":"Point"}
}