{
  "type": "Feature",
  "properties": {
    "gn:admin1_code":"5",
    "gn:asciiname":"Los Novillos",
    "gn:country_code":"VE",
    "gn:dem":65,
    "gn:feature_class":"P",
    "gn:feature_code":"PPL",
    "gn:name":"Los Novillos",
    "gn:population":0,
    "gn:timezone":"America/Caracas",
    "iso:country":"VE",
    "wof:name":"Los Novillos",
    "wof:placetype":"locality"
},
  "geometry": {"coordinates":[-68.71666999999999,8.15],"type":"Point"}
}