{
  "type": "Feature",
  "properties": {
    "gn:admin1_code":"16.0",
    "gn:asciiname":"Triste",
    "gn:country_code":"VE",
    "gn:dem":541,
    "gn:feature_class":"P",
    "gn:feature_code":"PPL",
    "gn:name":"Triste",
    "gn:population":0,
    "gn:timezone":"America/Caracas",
    "iso:country":"VE",
    "name:rus_x_preferred":[
        "\u0422\u0440\u0438\u0441\u0442\u0435"
    ],
    "wof:name":"Triste",
    "wof:placetype":"locality"
},
  "geometry": {"coordinates":[-63.71412,10.1479],"type":"Point"}
}