{
  "type": "Feature",
  "properties": {
    "gn:admin1_code":"15",
    "gn:asciiname":"Rengito",
    "gn:country_code":"VE",
    "gn:dem":83,
    "gn:feature_class":"P",
    "gn:feature_code":"PPL",
    "gn:name":"Rengito",
    "gn:population":0,
    "gn:timezone":"America/Caracas",
    "iso:country":"VE",
    "wof:name":"Rengito",
    "wof:placetype":"locality"
},
  "geometry": {"coordinates":[-66.39894,10.29897],"type":"Point"}
}