{
  "type": "Feature",
  "properties": {
    "gn:admin1_code":"3.0",
    "gn:asciiname":"Los Algodones",
    "gn:country_code":"VE",
    "gn:dem":97,
    "gn:feature_class":"P",
    "gn:feature_code":"PPLL",
    "gn:name":"Los Algodones",
    "gn:population":0,
    "gn:timezone":"America/Caracas",
    "iso:country":"VE",
    "name:dan_x_preferred":[
        "Los Algodones"
    ],
    "name:deu_x_preferred":[
        "Vicente Guerrero"
    ],
    "name:fra_x_preferred":[
        "Los Algodones"
    ],
    "name:nld_x_preferred":[
        "Los Algodones"
    ],
    "name:nor_x_preferred":[
        "Los Algodones"
    ],
    "name:rus_x_preferred":[
        "\u041b\u043e\u0441-\u0410\u043b\u044c\u0433\u043e\u0434\u043e\u043d\u0435\u0441"
    ],
    "name:spa_x_preferred":[
        "Algodones"
    ],
    "wof:name":"Los Algodones",
    "wof:placetype":"locality"
},
  "geometry": {"coordinates":[-69.71084,7.54276],"type":"Point"}
}