{
  "type": "Feature",
  "properties": {
    "gn:admin1_code":"22",
    "gn:asciiname":"Quigua",
    "gn:country_code":"VE",
    "gn:dem":586,
    "gn:feature_class":"P",
    "gn:feature_code":"PPL",
    "gn:name":"Quigua",
    "gn:population":0,
    "gn:timezone":"America/Caracas",
    "iso:country":"VE",
    "wof:name":"Quigua",
    "wof:placetype":"locality"
},
  "geometry": {"coordinates":[-68.85991999999999,10.29219],"type":"Point"}
}