{
  "type": "Feature",
  "properties": {
    "gn:admin1_code":"06",
    "gn:asciiname":"Uarapata",
    "gn:country_code":"VE",
    "gn:dem":1047,
    "gn:feature_class":"P",
    "gn:feature_code":"PPL",
    "gn:name":"Uarapata",
    "gn:population":0,
    "gn:timezone":"America/Caracas",
    "iso:country":"VE",
    "wof:name":"Uarapata",
    "wof:placetype":"locality"
},
  "geometry": {"coordinates":[-61.11666999999999,5.45],"type":"Point"}
}