{
  "type": "Feature",
  "properties": {
    "gn:admin1_code":"1",
    "gn:asciiname":"Carinagua",
    "gn:country_code":"VE",
    "gn:dem":70,
    "gn:feature_class":"P",
    "gn:feature_code":"PPL",
    "gn:name":"Carinagua",
    "gn:population":0,
    "gn:timezone":"America/Caracas",
    "iso:country":"VE",
    "wof:name":"Carinagua",
    "wof:placetype":"locality"
},
  "geometry": {"coordinates":[-67.60951999999999,5.63197],"type":"Point"}
}