{
  "type": "Feature",
  "properties": {
    "gn:admin1_code":"23",
    "gn:asciiname":"Tio Agustin",
    "gn:country_code":"VE",
    "gn:dem":103,
    "gn:feature_class":"P",
    "gn:feature_code":"PPL",
    "gn:name":"T\u00edo Agust\u00edn",
    "gn:population":0,
    "gn:timezone":"America/Caracas",
    "iso:country":"VE",
    "wof:name":"Tio Agustin",
    "wof:placetype":"locality"
},
  "geometry": {"coordinates":[-72.57666999999999,10.07861],"type":"Point"}
}