{
  "type": "Feature",
  "properties": {
    "gn:admin1_code":"2",
    "gn:asciiname":"El Zamuro",
    "gn:cc2":"VE",
    "gn:country_code":"VE",
    "gn:dem":150,
    "gn:feature_class":"P",
    "gn:feature_code":"PPL",
    "gn:name":"El Zamuro",
    "gn:population":0,
    "gn:timezone":"America/Caracas",
    "iso:country":"VE",
    "name:und_x_variant":[
        "Zamuro",
        "El Zamuro"
    ],
    "wof:name":"El Zamuro",
    "wof:placetype":"locality"
},
  "geometry": {"coordinates":[-64.63333,9.33333],"type":"Point"}
}