{
  "type": "Feature",
  "properties": {
    "gn:admin1_code":"16.0",
    "gn:asciiname":"La Mata",
    "gn:country_code":"VE",
    "gn:dem":117,
    "gn:feature_class":"P",
    "gn:feature_code":"PPL",
    "gn:name":"La Mata",
    "gn:population":0,
    "gn:timezone":"America/Caracas",
    "iso:country":"VE",
    "name:arg_x_preferred":[
        "La Mata"
    ],
    "name:ast_x_preferred":[
        "La Mata"
    ],
    "name:cat_x_preferred":[
        "La Mata"
    ],
    "name:ceb_x_preferred":[
        "La Mata"
    ],
    "name:eus_x_preferred":[
        "La Mata"
    ],
    "name:fra_x_preferred":[
        "La Mata"
    ],
    "name:por_x_preferred":[
        "La Mata"
    ],
    "name:spa_x_preferred":[
        "La Mata"
    ],
    "name:srp_x_preferred":[
        "\u041b\u0430 \u041c\u0430\u0442\u0430"
    ],
    "name:swe_x_preferred":[
        "La Mata"
    ],
    "wof:name":"La Mata",
    "wof:placetype":"locality"
},
  "geometry": {"coordinates":[-63.4477,9.02518],"type":"Point"}
}