{
  "type": "Feature",
  "properties": {
    "gn:admin1_code":"11.0",
    "gn:asciiname":"Puente Rio Tocuyo",
    "gn:country_code":"VE",
    "gn:dem":19,
    "gn:feature_class":"P",
    "gn:feature_code":"PPL",
    "gn:name":"Puente R\u00edo Tocuyo",
    "gn:population":0,
    "gn:timezone":"America/Caracas",
    "iso:country":"VE",
    "wof:name":"Puente Rio Tocuyo",
    "wof:placetype":"locality"
},
  "geometry": {"coordinates":[-68.48524,10.93672],"type":"Point"}
}