{
  "type": "Feature",
  "properties": {
    "gn:admin1_code":"13",
    "gn:asciiname":"Potrero Ramirez",
    "gn:country_code":"VE",
    "gn:dem":721,
    "gn:feature_class":"P",
    "gn:feature_code":"PPL",
    "gn:name":"Potrero Ram\u00edrez",
    "gn:population":0,
    "gn:timezone":"America/Caracas",
    "iso:country":"VE",
    "name:und_x_variant":[
        "Potrero",
        "Potrero Ram\u00edrez"
    ],
    "wof:name":"Potrero Ramirez",
    "wof:placetype":"locality"
},
  "geometry": {"coordinates":[-69.45138,10.34818],"type":"Point"}
}