{
  "type": "Feature",
  "properties": {
    "gn:admin1_code":"6.0",
    "gn:asciiname":"Boca de Tonoro",
    "gn:country_code":"VE",
    "gn:dem":311,
    "gn:feature_class":"P",
    "gn:feature_code":"PPL",
    "gn:name":"Boca de Tonoro",
    "gn:population":0,
    "gn:timezone":"America/Caracas",
    "iso:country":"VE",
    "wof:name":"Boca de Tonoro",
    "wof:placetype":"locality"
},
  "geometry": {"coordinates":[-63.74166999999999,6.15278],"type":"Point"}
}