{
  "type": "Feature",
  "properties": {
    "gn:admin1_code":"11.0",
    "gn:admin2_code":"1125.0",
    "gn:asciiname":"Quirigua",
    "gn:country_code":"VE",
    "gn:dem":397,
    "gn:feature_class":"P",
    "gn:feature_code":"PPL",
    "gn:name":"Quirigu\u00e1",
    "gn:population":0,
    "gn:timezone":"America/Caracas",
    "iso:country":"VE",
    "wof:name":"Quirigua",
    "wof:placetype":"locality"
},
  "geometry": {"coordinates":[-69.33,11.45],"type":"Point"}
}