{
  "type": "Feature",
  "properties": {
    "gn:admin1_code":"3.0",
    "gn:asciiname":"Rincon de Caro",
    "gn:country_code":"VE",
    "gn:dem":32,
    "gn:feature_class":"P",
    "gn:feature_code":"PPL",
    "gn:name":"Rinc\u00f3n de Caro",
    "gn:population":0,
    "gn:timezone":"America/Caracas",
    "iso:country":"VE",
    "wof:name":"Rincon de Caro",
    "wof:placetype":"locality"
},
  "geometry": {"coordinates":[-66.35406999999999,7.65297],"type":"Point"}
}