{
  "type": "Feature",
  "properties": {
    "gn:admin1_code":"13.0",
    "gn:asciiname":"El Venado",
    "gn:country_code":"VE",
    "gn:dem":206,
    "gn:feature_class":"P",
    "gn:feature_code":"PPL",
    "gn:name":"El Venado",
    "gn:population":0,
    "gn:timezone":"America/Caracas",
    "iso:country":"VE",
    "wof:name":"El Venado",
    "wof:placetype":"locality"
},
  "geometry": {"coordinates":[-68.875,10.61667],"type":"Point"}
}