{
  "type": "Feature",
  "properties": {
    "gn:admin1_code":"11",
    "gn:asciiname":"Santa Barbara",
    "gn:country_code":"VE",
    "gn:dem":332,
    "gn:feature_class":"P",
    "gn:feature_code":"PPL",
    "gn:name":"Santa B\u00e1rbara",
    "gn:population":0,
    "gn:timezone":"America/Caracas",
    "iso:country":"VE",
    "name:arg_x_preferred":[
        "Santa Barbara"
    ],
    "name:bpy_x_preferred":[
        "\u09b8\u09be\u09a8\u09cd\u099f\u09be \u09ac\u09be\u09b0\u09cd\u09ac\u09be\u09b0\u09be"
    ],
    "name:bre_x_preferred":[
        "Santa B\u00e1rbara"
    ],
    "name:bul_x_preferred":[
        "\u0421\u0430\u043d\u0442\u0430 \u0411\u0430\u0440\u0431\u0430\u0440\u0430"
    ],
    "name:cat_x_preferred":[
        "Santa B\u00e0rbara"
    ],
    "name:ceb_x_preferred":[
        "Santa B\u00e1rbara"
    ],
    "name:deu_x_preferred":[
        "Santa Barbara"
    ],
    "name:epo_x_preferred":[
        "Santa Barbara"
    ],
    "name:eus_x_preferred":[
        "Santa Barbara"
    ],
    "name:fas_x_preferred":[
        "\u0633\u0627\u0646\u062a\u0627 \u0628\u0627\u0631\u0628\u0627\u0631\u0627"
    ],
    "name:fin_x_preferred":[
        "Santa Barbara"
    ],
    "name:fra_x_preferred":[
        "Santa Barbara"
    ],
    "name:glg_x_preferred":[
        "Santa B\u00e1rbara"
    ],
    "name:heb_x_preferred":[
        "\u05e1\u05e0\u05d8\u05d4 \u05d1\u05e8\u05d1\u05e8\u05d4"
    ],
    "name:hrv_x_preferred":[
        "Santa Barbara"
    ],
    "name:hun_x_preferred":[
        "Santa Barbara"
    ],
    "name:hye_x_preferred":[
        "\u054d\u0561\u0576\u057f\u0561 \u0532\u0561\u0580\u0562\u0561\u0580\u0561"
    ],
    "name:ilo_x_preferred":[
        "Santa Barbara"
    ],
    "name:ita_x_preferred":[
        "Santa Barbara"
    ],
    "name:kat_x_preferred":[
        "\u10e1\u10d0\u10dc\u10e2\u10d0-\u10d1\u10d0\u10e0\u10d1\u10d0\u10e0\u10d0"
    ],
    "name:kor_x_preferred":[
        "\uc0b0\ud0c0\ubc14\ub974\ubc14\ub77c"
    ],
    "name:nld_x_preferred":[
        "Santa Barbara"
    ],
    "name:nor_x_preferred":[
        "Santa Barbara"
    ],
    "name:pan_x_preferred":[
        "\u0a38\u0a3e\u0a02\u0a24\u0a3e \u0a2c\u0a3e\u0a30\u0a2c\u0a30\u0a3e"
    ],
    "name:pol_x_preferred":[
        "Santa Barbara"
    ],
    "name:por_x_preferred":[
        "Santa B\u00e1rbara"
    ],
    "name:que_x_preferred":[
        "Santa Barbara"
    ],
    "name:rus_x_preferred":[
        "\u0421\u0430\u043d\u0442\u0430-\u0411\u0430\u0440\u0431\u0430\u0440\u0430"
    ],
    "name:sco_x_preferred":[
        "Santa Barbara"
    ],
    "name:slk_x_preferred":[
        "Santa Barbara"
    ],
    "name:spa_x_preferred":[
        "Santa B\u00e1rbara"
    ],
    "name:srp_x_preferred":[
        "\u0421\u0430\u043d\u0442\u0430 \u0411\u0430\u0440\u0431\u0430\u0440\u0430"
    ],
    "name:swe_x_preferred":[
        "Santa Barbara"
    ],
    "name:tur_x_preferred":[
        "Santa Barbara"
    ],
    "name:ukr_x_preferred":[
        "\u0421\u0430\u043d\u0442\u0430-\u0411\u0430\u0440\u0431\u0430\u0440\u0430"
    ],
    "name:vol_x_preferred":[
        "Santa B\u00e1rbara"
    ],
    "name:war_x_preferred":[
        "Santa Barbara"
    ],
    "wof:name":"Santa Barbara",
    "wof:placetype":"locality"
},
  "geometry": {"coordinates":[-68.61667,11.15],"type":"Point"}
}