{
  "type": "Feature",
  "properties": {
    "gn:admin1_code":"11",
    "gn:asciiname":"Tupurito",
    "gn:country_code":"VE",
    "gn:dem":329,
    "gn:feature_class":"P",
    "gn:feature_code":"PPL",
    "gn:name":"Tupurito",
    "gn:population":0,
    "gn:timezone":"America/Caracas",
    "iso:country":"VE",
    "wof:name":"Tupurito",
    "wof:placetype":"locality"
},
  "geometry": {"coordinates":[-70.62179,10.68702],"type":"Point"}
}