{
  "type": "Feature",
  "properties": {
    "gn:admin1_code":"2",
    "gn:asciiname":"Cabecera de Morichalote",
    "gn:country_code":"VE",
    "gn:dem":140,
    "gn:feature_class":"P",
    "gn:feature_code":"PPL",
    "gn:name":"Cabecera de Morichalote",
    "gn:population":0,
    "gn:timezone":"America/Caracas",
    "iso:country":"VE",
    "wof:name":"Cabecera de Morichalote",
    "wof:placetype":"locality"
},
  "geometry": {"coordinates":[-63.5453,9.03844],"type":"Point"}
}