{
  "type": "Feature",
  "properties": {
    "gn:admin1_code":"15",
    "gn:asciiname":"Mata Linda",
    "gn:country_code":"VE",
    "gn:dem":262,
    "gn:feature_class":"P",
    "gn:feature_code":"PPL",
    "gn:name":"Mata Linda",
    "gn:population":0,
    "gn:timezone":"America/Caracas",
    "iso:country":"VE",
    "wof:name":"Mata Linda",
    "wof:placetype":"locality"
},
  "geometry": {"coordinates":[-66.84277,10.1986],"type":"Point"}
}