{
  "type": "Feature",
  "properties": {
    "gn:admin1_code":"19.0",
    "gn:asciiname":"Cabimbal",
    "gn:country_code":"VE",
    "gn:dem":596,
    "gn:feature_class":"P",
    "gn:feature_code":"PPL",
    "gn:name":"Cabimbal",
    "gn:population":0,
    "gn:timezone":"America/Caracas",
    "iso:country":"VE",
    "wof:name":"Cabimbal",
    "wof:placetype":"locality"
},
  "geometry": {"coordinates":[-64.08700999999999,10.1754],"type":"Point"}
}