{
  "type": "Feature",
  "properties": {
    "gn:admin1_code":"7",
    "gn:asciiname":"Corocito",
    "gn:country_code":"VE",
    "gn:dem":953,
    "gn:feature_class":"P",
    "gn:feature_code":"PPL",
    "gn:name":"Corocito",
    "gn:population":0,
    "gn:timezone":"America/Caracas",
    "iso:country":"VE",
    "wof:name":"Corocito",
    "wof:placetype":"locality"
},
  "geometry": {"coordinates":[-67.56667,9.98333],"type":"Point"}
}