{
  "type": "Feature",
  "properties": {
    "gn:admin1_code":"15",
    "gn:asciiname":"El Paramo",
    "gn:country_code":"VE",
    "gn:dem":631,
    "gn:feature_class":"P",
    "gn:feature_code":"PPL",
    "gn:name":"El Paramo",
    "gn:population":0,
    "gn:timezone":"America/Caracas",
    "iso:country":"VE",
    "wof:name":"El Paramo",
    "wof:placetype":"locality"
},
  "geometry": {"coordinates":[-65.98333000000001,9.93333],"type":"Point"}
}