{
  "type": "Feature",
  "properties": {
    "gn:admin1_code":"6.0",
    "gn:asciiname":"El Guayapo",
    "gn:country_code":"VE",
    "gn:dem":54,
    "gn:feature_class":"P",
    "gn:feature_code":"PPL",
    "gn:name":"El Guayapo",
    "gn:population":0,
    "gn:timezone":"America/Caracas",
    "iso:country":"VE",
    "wof:name":"El Guayapo",
    "wof:placetype":"locality"
},
  "geometry": {"coordinates":[-65.66846,7.7521],"type":"Point"}
}