{
  "type": "Feature",
  "properties": {
    "gn:admin1_code":"8",
    "gn:asciiname":"Campo Alegre",
    "gn:country_code":"VE",
    "gn:dem":110,
    "gn:feature_class":"P",
    "gn:feature_code":"PPL",
    "gn:name":"Campo Alegre",
    "gn:population":0,
    "gn:timezone":"America/Caracas",
    "iso:country":"VE",
    "name:ceb_x_preferred":[
        "Campo Alegre"
    ],
    "name:deu_x_preferred":[
        "Campo Alegre"
    ],
    "name:fra_x_preferred":[
        "Campo Alegre"
    ],
    "name:ita_x_preferred":[
        "Campo Alegre"
    ],
    "name:nld_x_preferred":[
        "Campo Alegre"
    ],
    "name:nor_x_preferred":[
        "Campo Alegre"
    ],
    "name:por_x_preferred":[
        "Campo Alegre"
    ],
    "name:rus_x_preferred":[
        "\u041a\u0430\u043c\u043f\u0443-\u0410\u043b\u0435\u0433\u0440\u0438"
    ],
    "name:spa_x_preferred":[
        "Campo Alegre"
    ],
    "name:swe_x_preferred":[
        "Campo Alegre"
    ],
    "name:vie_x_preferred":[
        "Campo Alegre"
    ],
    "name:vol_x_preferred":[
        "Campo Alegre"
    ],
    "wof:name":"Campo Alegre",
    "wof:placetype":"locality"
},
  "geometry": {"coordinates":[-68.68118,9.47036],"type":"Point"}
}