{
  "type": "Feature",
  "properties": {
    "gn:admin1_code":"23",
    "gn:asciiname":"Montepio",
    "gn:country_code":"VE",
    "gn:dem":38,
    "gn:feature_class":"P",
    "gn:feature_code":"PPL",
    "gn:name":"Montepio",
    "gn:population":0,
    "gn:timezone":"America/Caracas",
    "iso:country":"VE",
    "name:srp_x_preferred":[
        "\u041c\u043e\u043d\u0442\u0435\u043f\u0438\u043e"
    ],
    "name:und_x_variant":[
        "Monte P\u00edo",
        "Montepio"
    ],
    "wof:name":"Montepio",
    "wof:placetype":"locality"
},
  "geometry": {"coordinates":[-71.41431,10.47567],"type":"Point"}
}