{
  "type": "Feature",
  "properties": {
    "gn:admin1_code":"4",
    "gn:asciiname":"Sabana Larga",
    "gn:country_code":"VE",
    "gn:dem":298,
    "gn:feature_class":"P",
    "gn:feature_code":"PPL",
    "gn:name":"Sabana Larga",
    "gn:population":0,
    "gn:timezone":"America/Caracas",
    "iso:country":"VE",
    "wof:name":"Sabana Larga",
    "wof:placetype":"locality"
},
  "geometry": {"coordinates":[-66.84999999999999,9.81667],"type":"Point"}
}