{
  "type": "Feature",
  "properties": {
    "gn:admin1_code":"3",
    "gn:asciiname":"Paraguito",
    "gn:country_code":"VE",
    "gn:dem":94,
    "gn:feature_class":"P",
    "gn:feature_code":"PPL",
    "gn:name":"Parag\u00fcito",
    "gn:population":0,
    "gn:timezone":"America/Caracas",
    "iso:country":"VE",
    "name:und_x_variant":[
        "Paraguitos",
        "Paraquitos",
        "Parag\u00fcito"
    ],
    "wof:name":"Paraguito",
    "wof:placetype":"locality"
},
  "geometry": {"coordinates":[-69.74417,7.73491],"type":"Point"}
}