{
  "type": "Feature",
  "properties": {
    "gn:admin1_code":"14",
    "gn:asciiname":"El Molino",
    "gn:country_code":"VE",
    "gn:dem":1064,
    "gn:feature_class":"P",
    "gn:feature_code":"PPL",
    "gn:name":"El Molino",
    "gn:population":0,
    "gn:timezone":"America/Caracas",
    "iso:country":"VE",
    "wof:name":"El Molino",
    "wof:placetype":"locality"
},
  "geometry": {"coordinates":[-71.4076,8.50664],"type":"Point"}
}