{
  "type": "Feature",
  "properties": {
    "gn:admin1_code":"02",
    "gn:asciiname":"La Esquina",
    "gn:country_code":"VE",
    "gn:dem":113,
    "gn:feature_class":"P",
    "gn:feature_code":"PPLL",
    "gn:name":"La Esquina",
    "gn:population":0,
    "gn:timezone":"America/Caracas",
    "iso:country":"VE",
    "wof:name":"La Esquina",
    "wof:placetype":"locality"
},
  "geometry": {"coordinates":[-64.62964000000001,8.24283],"type":"Point"}
}