{
  "type": "Feature",
  "properties": {
    "gn:admin1_code":"23.0",
    "gn:asciiname":"Barranco",
    "gn:country_code":"VE",
    "gn:dem":85,
    "gn:feature_class":"P",
    "gn:feature_code":"PPLL",
    "gn:name":"Barranco",
    "gn:population":0,
    "gn:timezone":"America/Caracas",
    "iso:country":"VE",
    "name:ceb_x_preferred":[
        "Barranco"
    ],
    "name:deu_x_preferred":[
        "Barranco"
    ],
    "name:glg_x_preferred":[
        "Barranco"
    ],
    "name:nds_x_preferred":[
        "Barranco"
    ],
    "name:por_x_preferred":[
        "Barranco"
    ],
    "name:spa_x_preferred":[
        "Barranco"
    ],
    "name:swe_x_preferred":[
        "Barranco"
    ],
    "wof:name":"Barranco",
    "wof:placetype":"locality"
},
  "geometry": {"coordinates":[-71.90114,10.53825],"type":"Point"}
}