{
  "type": "Feature",
  "properties": {
    "gn:admin1_code":"19.0",
    "gn:asciiname":"La Pascuala",
    "gn:country_code":"VE",
    "gn:dem":191,
    "gn:feature_class":"P",
    "gn:feature_code":"PPL",
    "gn:name":"La Pascuala",
    "gn:population":0,
    "gn:timezone":"America/Caracas",
    "iso:country":"VE",
    "wof:name":"La Pascuala",
    "wof:placetype":"locality"
},
  "geometry": {"coordinates":[-63.22644,10.49917],"type":"Point"}
}