{
  "type": "Feature",
  "properties": {
    "gn:admin1_code":"5",
    "gn:asciiname":"Rebolledo",
    "gn:country_code":"VE",
    "gn:dem":172,
    "gn:feature_class":"P",
    "gn:feature_code":"PPL",
    "gn:name":"Rebolledo",
    "gn:population":0,
    "gn:timezone":"America/Caracas",
    "iso:country":"VE",
    "name:spa_x_preferred":[
        "Rebolledo"
    ],
    "wof:name":"Rebolledo",
    "wof:placetype":"locality"
},
  "geometry": {"coordinates":[-70.40000000000001,8.46667],"type":"Point"}
}