{
  "type": "Feature",
  "properties": {
    "gn:admin1_code":"5",
    "gn:asciiname":"Barba de Tigre",
    "gn:country_code":"VE",
    "gn:dem":68,
    "gn:feature_class":"P",
    "gn:feature_code":"PPL",
    "gn:name":"Barba de Tigre",
    "gn:population":0,
    "gn:timezone":"America/Caracas",
    "iso:country":"VE",
    "wof:name":"Barba de Tigre",
    "wof:placetype":"locality"
},
  "geometry": {"coordinates":[-68.36667,8.48333],"type":"Point"}
}