{
  "type": "Feature",
  "properties": {
    "gn:admin1_code":"23",
    "gn:asciiname":"Las Guadas",
    "gn:country_code":"VE",
    "gn:dem":5,
    "gn:feature_class":"P",
    "gn:feature_code":"PPL",
    "gn:name":"Las Guadas",
    "gn:population":0,
    "gn:timezone":"America/Caracas",
    "iso:country":"VE",
    "wof:name":"Las Guadas",
    "wof:placetype":"locality"
},
  "geometry": {"coordinates":[-72.03076,9.96134],"type":"Point"}
}