{
  "type": "Feature",
  "properties": {
    "gn:admin1_code":"2",
    "gn:asciiname":"Cunaguaro",
    "gn:cc2":"VE",
    "gn:country_code":"VE",
    "gn:dem":166,
    "gn:feature_class":"P",
    "gn:feature_code":"PPL",
    "gn:name":"Cunaguaro",
    "gn:population":0,
    "gn:timezone":"America/Caracas",
    "iso:country":"VE",
    "name:und_x_variant":[
        "El Canaguaro",
        "Cunaguaro"
    ],
    "wof:name":"Cunaguaro",
    "wof:placetype":"locality"
},
  "geometry": {"coordinates":[-64.51666999999999,8.63333],"type":"Point"}
}