{
  "type": "Feature",
  "properties": {
    "gn:admin1_code":"13.0",
    "gn:asciiname":"Piedras Negras",
    "gn:country_code":"VE",
    "gn:dem":490,
    "gn:feature_class":"P",
    "gn:feature_code":"PPL",
    "gn:name":"Piedras Negras",
    "gn:population":0,
    "gn:timezone":"America/Caracas",
    "iso:country":"VE",
    "wof:name":"Piedras Negras",
    "wof:placetype":"locality"
},
  "geometry": {"coordinates":[-70.38093000000001,10.23973],"type":"Point"}
}