{
  "type": "Feature",
  "properties": {
    "gn:admin1_code":"13.0",
    "gn:asciiname":"El Banco",
    "gn:country_code":"VE",
    "gn:dem":612,
    "gn:feature_class":"P",
    "gn:feature_code":"PPL",
    "gn:name":"El Banco",
    "gn:population":0,
    "gn:timezone":"America/Caracas",
    "iso:country":"VE",
    "wof:name":"El Banco",
    "wof:placetype":"locality"
},
  "geometry": {"coordinates":[-69.74500999999999,10.16844],"type":"Point"}
}