{
  "type": "Feature",
  "properties": {
    "gn:admin1_code":"19.0",
    "gn:asciiname":"El Cacho",
    "gn:country_code":"VE",
    "gn:dem":637,
    "gn:feature_class":"P",
    "gn:feature_code":"PPL",
    "gn:name":"El Cacho",
    "gn:population":0,
    "gn:timezone":"America/Caracas",
    "iso:country":"VE",
    "wof:name":"El Cacho",
    "wof:placetype":"locality"
},
  "geometry": {"coordinates":[-63.86486,10.18774],"type":"Point"}
}