{
  "type": "Feature",
  "properties": {
    "gn:admin1_code":"11",
    "gn:asciiname":"Llano Largo",
    "gn:country_code":"VE",
    "gn:dem":27,
    "gn:feature_class":"P",
    "gn:feature_code":"PPL",
    "gn:name":"Llano Largo",
    "gn:population":0,
    "gn:timezone":"America/Caracas",
    "iso:country":"VE",
    "name:ceb_x_preferred":[
        "Llano Largo"
    ],
    "name:ita_x_preferred":[
        "Llano Largo"
    ],
    "name:kat_x_preferred":[
        "\u10da\u10d8\u10d0\u10dc\u10dd-\u10da\u10d0\u10e0\u10d2\u10dd"
    ],
    "name:spa_x_preferred":[
        "Llano Largo"
    ],
    "name:zho_x_preferred":[
        "\u5229\u4e9e\u8afe\u62c9\u723e\u6208"
    ],
    "wof:name":"Llano Largo",
    "wof:placetype":"locality"
},
  "geometry": {"coordinates":[-71.05883,10.89172],"type":"Point"}
}