{
  "type": "Feature",
  "properties": {
    "gn:admin1_code":"16.0",
    "gn:asciiname":"El Vegote",
    "gn:country_code":"VE",
    "gn:dem":1046,
    "gn:feature_class":"P",
    "gn:feature_code":"PPL",
    "gn:name":"El Vegote",
    "gn:population":0,
    "gn:timezone":"America/Caracas",
    "iso:country":"VE",
    "wof:name":"El Vegote",
    "wof:placetype":"locality"
},
  "geometry": {"coordinates":[-63.68722,10.23167],"type":"Point"}
}