{
  "type": "Feature",
  "properties": {
    "gn:gn_country":"VE",
    "gn:gn_fcode":"PPLX",
    "gn:gn_pop":80029,
    "gn:population":80029,
    "iso:country":"VE",
    "name:spa_x_preferred":[
        "El Cafetal"
    ],
    "qs_pg:aaroncc":"VE",
    "qs_pg:gn_country":"VE",
    "qs_pg:gn_fcode":"PPLX",
    "qs_pg:gn_pop":80029,
    "qs_pg:name":"El Cafetal",
    "qs_pg:photos_9r":0,
    "qs_pg:photos_sr":0,
    "qs_pg:pop_sr":8,
    "qs_pg:qs_pg_placetype":"neighbourhood",
    "wof:name":"El Cafetal",
    "wof:placetype":"neighbourhood",
    "wof:population":80029
},
  "geometry": {"coordinates":[-66.83063,10.46941],"type":"Point"}
}