{
  "type": "Feature",
  "properties": {
    "gn:admin1_code":"3.0",
    "gn:asciiname":"Cano Negro",
    "gn:country_code":"VE",
    "gn:dem":50,
    "gn:feature_class":"P",
    "gn:feature_code":"PPLL",
    "gn:name":"Ca\u00f1o Negro",
    "gn:population":0,
    "gn:timezone":"America/Caracas",
    "iso:country":"VE",
    "wof:name":"Cano Negro",
    "wof:placetype":"locality"
},
  "geometry": {"coordinates":[-67.19556,7.985],"type":"Point"}
}