{
  "type": "Feature",
  "properties": {
    "gn:admin1_code":"16",
    "gn:asciiname":"Viento Fresco",
    "gn:country_code":"VE",
    "gn:dem":280,
    "gn:feature_class":"P",
    "gn:feature_code":"PPL",
    "gn:name":"Viento Fresco",
    "gn:population":0,
    "gn:timezone":"America/Caracas",
    "iso:country":"VE",
    "wof:name":"Viento Fresco",
    "wof:placetype":"locality"
},
  "geometry": {"coordinates":[-63.67473,9.77019],"type":"Point"}
}