{
  "type": "Feature",
  "properties": {
    "gn:admin1_code":"3",
    "gn:asciiname":"Celedonero",
    "gn:cc2":"VE",
    "gn:country_code":"VE",
    "gn:dem":45,
    "gn:feature_class":"P",
    "gn:feature_code":"PPL",
    "gn:name":"Celedo\u00f1ero",
    "gn:population":0,
    "gn:timezone":"America/Caracas",
    "iso:country":"VE",
    "name:und_x_variant":[
        "Celedomero",
        "Celedo\u00f1ero"
    ],
    "wof:name":"Celedonero",
    "wof:placetype":"locality"
},
  "geometry": {"coordinates":[-67.09999999999999,7.21667],"type":"Point"}
}