{
  "type": "Feature",
  "properties": {
    "gn:admin1_code":"6",
    "gn:asciiname":"Sabanetica",
    "gn:country_code":"VE",
    "gn:dem":381,
    "gn:feature_class":"P",
    "gn:feature_code":"PPL",
    "gn:name":"Sabanetica",
    "gn:population":0,
    "gn:timezone":"America/Caracas",
    "iso:country":"VE",
    "wof:name":"Sabanetica",
    "wof:placetype":"locality"
},
  "geometry": {"coordinates":[-62.44778,8.0025],"type":"Point"}
}