{
  "type": "Feature",
  "properties": {
    "gn:admin1_code":"18.0",
    "gn:asciiname":"Cano Colorado",
    "gn:country_code":"VE",
    "gn:dem":166,
    "gn:feature_class":"P",
    "gn:feature_code":"PPL",
    "gn:name":"Ca\u00f1o Colorado",
    "gn:population":0,
    "gn:timezone":"America/Caracas",
    "iso:country":"VE",
    "name:spa_x_preferred":[
        "Ca\u00f1o Colorado"
    ],
    "wof:name":"Cano Colorado",
    "wof:placetype":"locality"
},
  "geometry": {"coordinates":[-69.80604,9.00382],"type":"Point"}
}