{
  "type": "Feature",
  "properties": {
    "gn:admin1_code":"03",
    "gn:asciiname":"Yaruro",
    "gn:country_code":"VE",
    "gn:dem":63,
    "gn:feature_class":"P",
    "gn:feature_code":"PPL",
    "gn:name":"Yaruro",
    "gn:population":0,
    "gn:timezone":"America/Caracas",
    "iso:country":"VE",
    "wof:name":"Yaruro",
    "wof:placetype":"locality"
},
  "geometry": {"coordinates":[-68.31600999999999,6.20246],"type":"Point"}
}