{
  "type": "Feature",
  "properties": {
    "gn:admin1_code":"6.0",
    "gn:asciiname":"Piloncito",
    "gn:country_code":"VE",
    "gn:dem":273,
    "gn:feature_class":"P",
    "gn:feature_code":"PPL",
    "gn:name":"Piloncito",
    "gn:population":0,
    "gn:timezone":"America/Caracas",
    "iso:country":"VE",
    "wof:name":"Piloncito",
    "wof:placetype":"locality"
},
  "geometry": {"coordinates":[-63.225,7.04556],"type":"Point"}
}