{
  "type": "Feature",
  "properties": {
    "gn:admin1_code":"18.0",
    "gn:asciiname":"Palo Solo",
    "gn:country_code":"VE",
    "gn:dem":681,
    "gn:feature_class":"P",
    "gn:feature_code":"PPL",
    "gn:name":"Palo Solo",
    "gn:population":0,
    "gn:timezone":"America/Caracas",
    "iso:country":"VE",
    "name:cat_x_preferred":[
        "Palo Solo"
    ],
    "name:deu_x_preferred":[
        "Palo Solo"
    ],
    "name:fra_x_preferred":[
        "Palo Solo"
    ],
    "name:nor_x_preferred":[
        "Palo Solo"
    ],
    "name:spa_x_preferred":[
        "Palo Solo"
    ],
    "wof:name":"Palo Solo",
    "wof:placetype":"locality"
},
  "geometry": {"coordinates":[-69.86111,9.32278],"type":"Point"}
}