{
  "type": "Feature",
  "properties": {
    "gn:admin1_code":"2",
    "gn:asciiname":"Malpica",
    "gn:country_code":"VE",
    "gn:dem":62,
    "gn:feature_class":"P",
    "gn:feature_code":"PPL",
    "gn:name":"Malpica",
    "gn:population":0,
    "gn:timezone":"America/Caracas",
    "iso:country":"VE",
    "wof:name":"Malpica",
    "wof:placetype":"locality"
},
  "geometry": {"coordinates":[-63.6606,8.25499],"type":"Point"}
}