{
  "type": "Feature",
  "properties": {
    "gn:admin1_code":"03",
    "gn:asciiname":"San Pablo Segoviero",
    "gn:cc2":"VE",
    "gn:country_code":"VE",
    "gn:dem":66,
    "gn:feature_class":"P",
    "gn:feature_code":"PPL",
    "gn:name":"San Pablo Segoviero",
    "gn:population":0,
    "gn:timezone":"America/Caracas",
    "iso:country":"VE",
    "name:und_x_variant":[
        "San Pablo Sego\u00f1ero",
        "San Pablo Segoviero"
    ],
    "wof:name":"San Pablo Segoviero",
    "wof:placetype":"locality"
},
  "geometry": {"coordinates":[-68.56667,7.46667],"type":"Point"}
}