{
  "type": "Feature",
  "properties": {
    "gn:admin1_code":"11.0",
    "gn:asciiname":"San Juan",
    "gn:country_code":"VE",
    "gn:dem":183,
    "gn:feature_class":"P",
    "gn:feature_code":"PPLL",
    "gn:name":"San Juan",
    "gn:population":0,
    "gn:timezone":"America/Caracas",
    "iso:country":"VE",
    "wof:name":"San Juan",
    "wof:placetype":"locality"
},
  "geometry": {"coordinates":[-69.27880999999999,11.43464],"type":"Point"}
}