{
  "type": "Feature",
  "properties": {
    "gn:admin1_code":"12.0",
    "gn:asciiname":"Buena Vista",
    "gn:country_code":"VE",
    "gn:dem":251,
    "gn:feature_class":"P",
    "gn:feature_code":"PPLL",
    "gn:name":"Buena Vista",
    "gn:population":0,
    "gn:timezone":"America/Caracas",
    "iso:country":"VE",
    "wof:name":"Buena Vista",
    "wof:placetype":"locality"
},
  "geometry": {"coordinates":[-64.78966,8.81076],"type":"Point"}
}