{
  "type": "Feature",
  "properties": {
    "gn:admin1_code":"12.0",
    "gn:asciiname":"Buena Vista",
    "gn:country_code":"VE",
    "gn:dem":251,
    "gn:feature_class":"P",
    "gn:feature_code":"PPLL",
    "gn:name":"Buena Vista",
    "gn:population":0,
    "gn:timezone":"America/Caracas",
    "iso:country":"VE",
    "name:ara_x_preferred":[
        "\u0628\u0648\u064a\u0646\u0627 \u0641\u064a\u0633\u062a\u0627"
    ],
    "name:bre_x_preferred":[
        "Buena Vista"
    ],
    "name:ceb_x_preferred":[
        "Buena Vista"
    ],
    "name:ces_x_preferred":[
        "Buena Vista"
    ],
    "name:deu_x_preferred":[
        "Buena Vista"
    ],
    "name:fin_x_preferred":[
        "Buena Vista"
    ],
    "name:fra_x_preferred":[
        "Buena Vista"
    ],
    "name:ita_x_preferred":[
        "Buena Vista"
    ],
    "name:jpn_x_preferred":[
        "\u30d6\u30a8\u30ca\u30d3\u30b9\u30bf"
    ],
    "name:kor_x_preferred":[
        "\ubd80\uc5d0\ub098 \ube44\uc2a4\ud0c0"
    ],
    "name:nds_x_preferred":[
        "Buena Vista"
    ],
    "name:pol_x_preferred":[
        "Buena Vista"
    ],
    "name:por_x_preferred":[
        "Buena Vista"
    ],
    "name:spa_x_preferred":[
        "Buena Vista"
    ],
    "name:srp_x_preferred":[
        "\u0411\u0443\u0435\u043d\u0430 \u0412\u0438\u0441\u0442\u0430"
    ],
    "name:swe_x_preferred":[
        "Buena Vista"
    ],
    "name:ukr_x_preferred":[
        "\u0411\u0443\u0435\u043d\u0430-\u0412\u0456\u0441\u0442\u0430"
    ],
    "name:urd_x_preferred":[
        "\u0628\u06cc\u0648\u0646\u0627 \u0648\u0633\u0679\u0627"
    ],
    "name:vol_x_preferred":[
        "Buena Vista"
    ],
    "wof:name":"Buena Vista",
    "wof:placetype":"locality"
},
  "geometry": {"coordinates":[-64.78966,8.81076],"type":"Point"}
}