{
  "type": "Feature",
  "properties": {
    "gn:admin1_code":"22.0",
    "gn:asciiname":"Canaveral",
    "gn:country_code":"VE",
    "gn:dem":485,
    "gn:feature_class":"P",
    "gn:feature_code":"PPL",
    "gn:name":"Ca\u00f1averal",
    "gn:population":0,
    "gn:timezone":"America/Caracas",
    "iso:country":"VE",
    "name:ceb_x_preferred":[
        "Ca\u00f1averal"
    ],
    "name:nld_x_preferred":[
        "Ca\u00f1averal"
    ],
    "name:por_x_preferred":[
        "Canaveral"
    ],
    "name:rus_x_preferred":[
        "\u041a\u0430\u043d\u044c\u044f\u0432\u0435\u0440\u0430\u043b\u044c"
    ],
    "name:spa_x_preferred":[
        "Ca\u00f1averal"
    ],
    "name:swe_x_preferred":[
        "Ca\u00f1averal"
    ],
    "wof:name":"Canaveral",
    "wof:placetype":"locality"
},
  "geometry": {"coordinates":[-68.11333,10.11111],"type":"Point"}
}