{
  "type": "Feature",
  "properties": {
    "gn:admin1_code":"13.0",
    "gn:asciiname":"El Maporal",
    "gn:country_code":"VE",
    "gn:dem":870,
    "gn:feature_class":"P",
    "gn:feature_code":"PPL",
    "gn:name":"El Maporal",
    "gn:population":0,
    "gn:timezone":"America/Caracas",
    "iso:country":"VE",
    "wof:name":"El Maporal",
    "wof:placetype":"locality"
},
  "geometry": {"coordinates":[-70.0099,9.95845],"type":"Point"}
}