{
  "type": "Feature",
  "properties": {
    "gn:admin1_code":"13",
    "gn:asciiname":"Las Trojas",
    "gn:country_code":"VE",
    "gn:dem":683,
    "gn:feature_class":"P",
    "gn:feature_code":"PPLL",
    "gn:name":"Las Trojas",
    "gn:population":0,
    "gn:timezone":"America/Caracas",
    "iso:country":"VE",
    "wof:name":"Las Trojas",
    "wof:placetype":"locality"
},
  "geometry": {"coordinates":[-69.77216999999999,10.35886],"type":"Point"}
}