{
  "type": "Feature",
  "properties": {
    "gn:admin1_code":"4",
    "gn:asciiname":"El Placer",
    "gn:country_code":"VE",
    "gn:dem":250,
    "gn:feature_class":"P",
    "gn:feature_code":"PPL",
    "gn:name":"El Placer",
    "gn:population":0,
    "gn:timezone":"America/Caracas",
    "iso:country":"VE",
    "wof:name":"El Placer",
    "wof:placetype":"locality"
},
  "geometry": {"coordinates":[-67.59437,10.45739],"type":"Point"}
}