{
  "type": "Feature",
  "properties": {
    "gn:admin1_code":"19",
    "gn:asciiname":"El Malpaso",
    "gn:country_code":"VE",
    "gn:dem":310,
    "gn:feature_class":"P",
    "gn:feature_code":"PPL",
    "gn:name":"El Malpaso",
    "gn:population":0,
    "gn:timezone":"America/Caracas",
    "iso:country":"VE",
    "wof:name":"El Malpaso",
    "wof:placetype":"locality"
},
  "geometry": {"coordinates":[-63.8941,10.30024],"type":"Point"}
}