{
  "type": "Feature",
  "properties": {
    "gn:admin1_code":"11.0",
    "gn:asciiname":"Cerro Largo",
    "gn:country_code":"VE",
    "gn:dem":312,
    "gn:feature_class":"P",
    "gn:feature_code":"PPL",
    "gn:name":"Cerro Largo",
    "gn:population":0,
    "gn:timezone":"America/Caracas",
    "iso:country":"VE",
    "wof:name":"Cerro Largo",
    "wof:placetype":"locality"
},
  "geometry": {"coordinates":[-69.10845999999999,11.37571],"type":"Point"}
}