{
  "type": "Feature",
  "properties": {
    "gn:admin1_code":"11.0",
    "gn:asciiname":"Cerro Largo",
    "gn:country_code":"VE",
    "gn:dem":312,
    "gn:feature_class":"P",
    "gn:feature_code":"PPL",
    "gn:name":"Cerro Largo",
    "gn:population":0,
    "gn:timezone":"America/Caracas",
    "iso:country":"VE",
    "name:ceb_x_preferred":[
        "Cerro Largo"
    ],
    "name:deu_x_preferred":[
        "Cerro Largo"
    ],
    "name:fra_x_preferred":[
        "Cerro Largo"
    ],
    "name:nld_x_preferred":[
        "Cerro Largo"
    ],
    "name:pol_x_preferred":[
        "Cerro Largo"
    ],
    "name:por_x_preferred":[
        "Cerro Largo"
    ],
    "name:rus_x_preferred":[
        "\u0421\u0435\u0440\u0440\u043e-\u041b\u0430\u0440\u0433\u043e"
    ],
    "name:slk_x_preferred":[
        "Cerro Largo"
    ],
    "name:spa_x_preferred":[
        "Cerro Largo"
    ],
    "name:swe_x_preferred":[
        "Cerro Largo"
    ],
    "wof:name":"Cerro Largo",
    "wof:placetype":"locality"
},
  "geometry": {"coordinates":[-69.10845999999999,11.37571],"type":"Point"}
}