{
  "type": "Feature",
  "properties": {
    "gn:admin1_code":"4",
    "gn:asciiname":"Bejucal",
    "gn:country_code":"VE",
    "gn:dem":646,
    "gn:feature_class":"P",
    "gn:feature_code":"PPL",
    "gn:name":"Bejucal",
    "gn:population":0,
    "gn:timezone":"America/Caracas",
    "iso:country":"VE",
    "wof:name":"Bejucal",
    "wof:placetype":"locality"
},
  "geometry": {"coordinates":[-66.97341999999999,10.00748],"type":"Point"}
}