{
  "type": "Feature",
  "properties": {
    "gn:admin1_code":"16",
    "gn:asciiname":"Moreno",
    "gn:country_code":"VE",
    "gn:dem":84,
    "gn:feature_class":"P",
    "gn:feature_code":"PPL",
    "gn:name":"Moreno",
    "gn:population":0,
    "gn:timezone":"America/Caracas",
    "iso:country":"VE",
    "wof:name":"Moreno",
    "wof:placetype":"locality"
},
  "geometry": {"coordinates":[-63.278,9.60697],"type":"Point"}
}