{
  "type": "Feature",
  "properties": {
    "gn:admin1_code":"12.0",
    "gn:asciiname":"Murcielago",
    "gn:country_code":"VE",
    "gn:dem":124,
    "gn:feature_class":"P",
    "gn:feature_code":"PPLL",
    "gn:name":"Murcielago",
    "gn:population":0,
    "gn:timezone":"America/Caracas",
    "iso:country":"VE",
    "wof:name":"Murcielago",
    "wof:placetype":"locality"
},
  "geometry": {"coordinates":[-65.71275,9.48081],"type":"Point"}
}