{
  "type": "Feature",
  "properties": {
    "gn:admin1_code":"19.0",
    "gn:asciiname":"Los Ramales",
    "gn:country_code":"VE",
    "gn:dem":825,
    "gn:feature_class":"P",
    "gn:feature_code":"PPLL",
    "gn:name":"Los Ramales",
    "gn:population":0,
    "gn:timezone":"America/Caracas",
    "iso:country":"VE",
    "wof:name":"Los Ramales",
    "wof:placetype":"locality"
},
  "geometry": {"coordinates":[-64.32522,10.19948],"type":"Point"}
}