{
  "type": "Feature",
  "properties": {
    "gn:admin1_code":"12",
    "gn:admin2_code":"1203.0",
    "gn:asciiname":"El Socorro",
    "gn:country_code":"VE",
    "gn:dem":118,
    "gn:feature_class":"P",
    "gn:feature_code":"PPLA2",
    "gn:name":"El Socorro",
    "gn:population":0,
    "gn:timezone":"America/Caracas",
    "iso:country":"VE",
    "name:und_x_variant":[
        "Socorro",
        "El Socorro"
    ],
    "wof:name":"El Socorro",
    "wof:placetype":"locality"
},
  "geometry": {"coordinates":[-65.74247,8.99352],"type":"Point"}
}