{
  "type": "Feature",
  "properties": {
    "gn:admin1_code":"9",
    "gn:asciiname":"Siawani",
    "gn:country_code":"VE",
    "gn:dem":21,
    "gn:feature_class":"P",
    "gn:feature_code":"PPL",
    "gn:name":"Siawani",
    "gn:population":0,
    "gn:timezone":"America/Caracas",
    "iso:country":"VE",
    "name:und_x_variant":[
        "Siaguani",
        "Siawani"
    ],
    "wof:name":"Siawani",
    "wof:placetype":"locality"
},
  "geometry": {"coordinates":[-60.94474,9.16989],"type":"Point"}
}