{
  "type": "Feature",
  "properties": {
    "gn:admin1_code":"12",
    "gn:asciiname":"Las Lajas",
    "gn:country_code":"VE",
    "gn:dem":76,
    "gn:feature_class":"P",
    "gn:feature_code":"PPL",
    "gn:name":"Las Lajas",
    "gn:population":0,
    "gn:timezone":"America/Caracas",
    "iso:country":"VE",
    "name:bre_x_preferred":[
        "Las Lajas"
    ],
    "name:ceb_x_preferred":[
        "Las Lajas"
    ],
    "name:deu_x_preferred":[
        "Las Lajas"
    ],
    "name:fra_x_preferred":[
        "Las Lajas"
    ],
    "name:ita_x_preferred":[
        "Las Lajas"
    ],
    "name:lit_x_preferred":[
        "Las Lachasas"
    ],
    "name:nld_x_preferred":[
        "Las Lajas"
    ],
    "name:pol_x_preferred":[
        "Las Lajas"
    ],
    "name:spa_x_preferred":[
        "Las Lajas"
    ],
    "name:swe_x_preferred":[
        "Las Lajas"
    ],
    "wof:name":"Las Lajas",
    "wof:placetype":"locality"
},
  "geometry": {"coordinates":[-67.64929000000001,8.84201],"type":"Point"}
}