{
  "type": "Feature",
  "properties": {
    "gn:admin1_code":"15.0",
    "gn:asciiname":"Higuerota",
    "gn:country_code":"VE",
    "gn:dem":792,
    "gn:feature_class":"P",
    "gn:feature_code":"PPL",
    "gn:name":"Higuerota",
    "gn:population":0,
    "gn:timezone":"America/Caracas",
    "iso:country":"VE",
    "wof:name":"Higuerota",
    "wof:placetype":"locality"
},
  "geometry": {"coordinates":[-66.53333000000001,9.99722],"type":"Point"}
}