{
  "type": "Feature",
  "properties": {
    "iso:country":"VE",
    "qs:gn_pop":0,
    "qs:name":"Capital Libertad",
    "qs:name_adm0":"Venezuela",
    "qs:name_adm1":"Tachira",
    "qs:photos":37,
    "qs:photos_1k":7,
    "qs:photos_9k":1,
    "qs:photos_9r":4,
    "qs:photos_all":257,
    "qs:photos_sr":2,
    "qs:placetype":"LocalAdmin",
    "qs:pop_sr":"0",
    "qs:woe_adm0":23424982,
    "wof:name":"Capital Libertad",
    "wof:placetype":"localadmin"
},
  "geometry": {"coordinates":[-72.30943600000001,7.826649],"type":"Point"}
}