{
  "type": "Feature",
  "properties": {
    "gn:admin1_code":"13.0",
    "gn:asciiname":"El Jobo",
    "gn:country_code":"VE",
    "gn:dem":515,
    "gn:feature_class":"P",
    "gn:feature_code":"PPL",
    "gn:name":"El Jobo",
    "gn:population":0,
    "gn:timezone":"America/Caracas",
    "iso:country":"VE",
    "wof:name":"El Jobo",
    "wof:placetype":"locality"
},
  "geometry": {"coordinates":[-70.29836,10.29652],"type":"Point"}
}