{
  "type": "Feature",
  "properties": {
    "gn:admin1_code":"14",
    "gn:asciiname":"Loma del Carmen",
    "gn:country_code":"VE",
    "gn:dem":1949,
    "gn:feature_class":"P",
    "gn:feature_code":"PPL",
    "gn:name":"Loma del Carmen",
    "gn:population":0,
    "gn:timezone":"America/Caracas",
    "iso:country":"VE",
    "wof:name":"Loma del Carmen",
    "wof:placetype":"locality"
},
  "geometry": {"coordinates":[-71.36095,8.5539],"type":"Point"}
}