{
  "type": "Feature",
  "properties": {
    "gn:admin1_code":"11",
    "gn:asciiname":"Borobo",
    "gn:country_code":"VE",
    "gn:dem":11,
    "gn:feature_class":"P",
    "gn:feature_code":"PPL",
    "gn:name":"Borobo",
    "gn:population":0,
    "gn:timezone":"America/Caracas",
    "iso:country":"VE",
    "wof:name":"Borobo",
    "wof:placetype":"locality"
},
  "geometry": {"coordinates":[-70.88333,11.16667],"type":"Point"}
}