{
  "type": "Feature",
  "properties": {
    "gn:admin1_code":"11",
    "gn:asciiname":"Majagual",
    "gn:country_code":"VE",
    "gn:dem":10,
    "gn:feature_class":"P",
    "gn:feature_code":"PPL",
    "gn:name":"Majagual",
    "gn:population":0,
    "gn:timezone":"America/Caracas",
    "iso:country":"VE",
    "name:ceb_x_preferred":[
        "Majagual"
    ],
    "name:sco_x_preferred":[
        "Majagual"
    ],
    "name:swe_x_preferred":[
        "Majagual"
    ],
    "name:vie_x_preferred":[
        "Majagual"
    ],
    "wof:name":"Majagual",
    "wof:placetype":"locality"
},
  "geometry": {"coordinates":[-69.97717,11.41623],"type":"Point"}
}