{
  "type": "Feature",
  "properties": {
    "gn:admin1_code":"6.0",
    "gn:asciiname":"Los Hicoteos",
    "gn:country_code":"VE",
    "gn:dem":192,
    "gn:feature_class":"P",
    "gn:feature_code":"PPL",
    "gn:name":"Los Hicoteos",
    "gn:population":0,
    "gn:timezone":"America/Caracas",
    "iso:country":"VE",
    "wof:name":"Los Hicoteos",
    "wof:placetype":"locality"
},
  "geometry": {"coordinates":[-63.95611,7.64111],"type":"Point"}
}