{
  "type": "Feature",
  "properties": {
    "gn:admin1_code":"15.0",
    "gn:asciiname":"El Penon",
    "gn:country_code":"VE",
    "gn:dem":605,
    "gn:feature_class":"P",
    "gn:feature_code":"PPLL",
    "gn:name":"El Pe\u00f1\u00f3n",
    "gn:population":0,
    "gn:timezone":"America/Caracas",
    "iso:country":"VE",
    "wof:name":"El Penon",
    "wof:placetype":"locality"
},
  "geometry": {"coordinates":[-66.78333000000001,10.29167],"type":"Point"}
}