{
  "type": "Feature",
  "properties": {
    "gn:admin1_code":"18.0",
    "gn:asciiname":"Quebrada Seca",
    "gn:country_code":"VE",
    "gn:dem":275,
    "gn:feature_class":"P",
    "gn:feature_code":"PPL",
    "gn:name":"Quebrada Seca",
    "gn:population":0,
    "gn:timezone":"America/Caracas",
    "iso:country":"VE",
    "name:spa_x_preferred":[
        "Quebrada Seca"
    ],
    "wof:name":"Quebrada Seca",
    "wof:placetype":"locality"
},
  "geometry": {"coordinates":[-69.69391,9.25258],"type":"Point"}
}