{
  "type": "Feature",
  "properties": {
    "gn:admin1_code":"20.0",
    "gn:asciiname":"Pueblo Viejo",
    "gn:country_code":"VE",
    "gn:dem":298,
    "gn:feature_class":"P",
    "gn:feature_code":"PPLL",
    "gn:name":"Pueblo Viejo",
    "gn:population":0,
    "gn:timezone":"America/Caracas",
    "iso:country":"VE",
    "name:ceb_x_preferred":[
        "Pueblo Viejo"
    ],
    "name:deu_x_preferred":[
        "Pueblo Viejo"
    ],
    "name:fra_x_preferred":[
        "Pueblo Viejo"
    ],
    "name:nds_x_preferred":[
        "Pueblo Viejo"
    ],
    "name:sco_x_preferred":[
        "Pueblo Viejo"
    ],
    "name:spa_x_preferred":[
        "Pueblo Viejo"
    ],
    "name:swe_x_preferred":[
        "Pueblo Viejo"
    ],
    "name:vie_x_preferred":[
        "Pueblo Viejo"
    ],
    "wof:name":"Pueblo Viejo",
    "wof:placetype":"locality"
},
  "geometry": {"coordinates":[-71.60684000000001,7.79638],"type":"Point"}
}