{
  "type": "Feature",
  "properties": {
    "gn:admin1_code":"8",
    "gn:asciiname":"Cueva Honda",
    "gn:country_code":"VE",
    "gn:dem":179,
    "gn:feature_class":"P",
    "gn:feature_code":"PPL",
    "gn:name":"Cueva Honda",
    "gn:population":0,
    "gn:timezone":"America/Caracas",
    "iso:country":"VE",
    "wof:name":"Cueva Honda",
    "wof:placetype":"locality"
},
  "geometry": {"coordinates":[-68.55,9.68333],"type":"Point"}
}