{
  "type": "Feature",
  "properties": {
    "gn:admin1_code":"6.0",
    "gn:asciiname":"Los Moriches",
    "gn:country_code":"VE",
    "gn:dem":179,
    "gn:feature_class":"P",
    "gn:feature_code":"PPL",
    "gn:name":"Los Moriches",
    "gn:population":0,
    "gn:timezone":"America/Caracas",
    "iso:country":"VE",
    "wof:name":"Los Moriches",
    "wof:placetype":"locality"
},
  "geometry": {"coordinates":[-61.84111,7.185],"type":"Point"}
}