{
  "type": "Feature",
  "properties": {
    "gn:admin1_code":"12.0",
    "gn:asciiname":"Marin",
    "gn:country_code":"VE",
    "gn:dem":114,
    "gn:feature_class":"P",
    "gn:feature_code":"PPL",
    "gn:name":"Mar\u00edn",
    "gn:population":0,
    "gn:timezone":"America/Caracas",
    "iso:country":"VE",
    "wof:name":"Marin",
    "wof:placetype":"locality"
},
  "geometry": {"coordinates":[-67.70652,9.26533],"type":"Point"}
}