{
  "type": "Feature",
  "properties": {
    "gn:admin1_code":"8",
    "gn:asciiname":"Espinito",
    "gn:country_code":"VE",
    "gn:dem":180,
    "gn:feature_class":"P",
    "gn:feature_code":"PPL",
    "gn:name":"Espinito",
    "gn:population":0,
    "gn:timezone":"America/Caracas",
    "iso:country":"VE",
    "name:und_x_variant":[
        "Hato Espinito",
        "Espinito"
    ],
    "wof:name":"Espinito",
    "wof:placetype":"locality"
},
  "geometry": {"coordinates":[-67.99964,9.68349],"type":"Point"}
}