{
  "type": "Feature",
  "properties": {
    "gn:admin1_code":"23",
    "gn:asciiname":"El Pozon de Lucia",
    "gn:country_code":"VE",
    "gn:dem":42,
    "gn:feature_class":"P",
    "gn:feature_code":"PPL",
    "gn:name":"El Poz\u00f3n de Luc\u00eda",
    "gn:population":0,
    "gn:timezone":"America/Caracas",
    "iso:country":"VE",
    "wof:name":"El Pozon de Lucia",
    "wof:placetype":"locality"
},
  "geometry": {"coordinates":[-72.60507,8.71414],"type":"Point"}
}