{
  "type": "Feature",
  "properties": {
    "gn:admin1_code":"16.0",
    "gn:asciiname":"El Bagre",
    "gn:country_code":"VE",
    "gn:dem":76,
    "gn:feature_class":"P",
    "gn:feature_code":"PPL",
    "gn:name":"El Bagre",
    "gn:population":0,
    "gn:timezone":"America/Caracas",
    "iso:country":"VE",
    "wof:name":"El Bagre",
    "wof:placetype":"locality"
},
  "geometry": {"coordinates":[-63.29667,9.925],"type":"Point"}
}