{
  "type": "Feature",
  "properties": {
    "gn:admin1_code":"6.0",
    "gn:asciiname":"Mamural",
    "gn:country_code":"VE",
    "gn:dem":281,
    "gn:feature_class":"P",
    "gn:feature_code":"PPL",
    "gn:name":"Mamural",
    "gn:population":0,
    "gn:timezone":"America/Caracas",
    "iso:country":"VE",
    "wof:name":"Mamural",
    "wof:placetype":"locality"
},
  "geometry": {"coordinates":[-63.20278,7.15278],"type":"Point"}
}