{
  "type": "Feature",
  "properties": {
    "gn:admin1_code":"12",
    "gn:asciiname":"La Mision de Los Angeles",
    "gn:country_code":"VE",
    "gn:dem":124,
    "gn:feature_class":"P",
    "gn:feature_code":"PPL",
    "gn:name":"La Misi\u00f3n de Los \u00c1ngeles",
    "gn:population":0,
    "gn:timezone":"America/Caracas",
    "iso:country":"VE",
    "name:und_x_variant":[
        "Misi\u00f3n Arriba",
        "La Misi\u00f3n",
        "La Misi\u00f3n de Los \u00c1ngeles"
    ],
    "wof:name":"La Mision de Los Angeles",
    "wof:placetype":"locality"
},
  "geometry": {"coordinates":[-67.3901,8.93934],"type":"Point"}
}