{
  "type": "Feature",
  "properties": {
    "gn:admin1_code":"02",
    "gn:asciiname":"Juan Nicolas",
    "gn:country_code":"VE",
    "gn:dem":38,
    "gn:feature_class":"P",
    "gn:feature_code":"PPLL",
    "gn:name":"Juan Nicol\u00e1s",
    "gn:population":0,
    "gn:timezone":"America/Caracas",
    "iso:country":"VE",
    "wof:name":"Juan Nicolas",
    "wof:placetype":"locality"
},
  "geometry": {"coordinates":[-64.63333,9.95833],"type":"Point"}
}