{
  "type": "Feature",
  "properties": {
    "gn:admin1_code":"8.0",
    "gn:asciiname":"Totumito",
    "gn:country_code":"VE",
    "gn:dem":179,
    "gn:feature_class":"P",
    "gn:feature_code":"PPL",
    "gn:name":"Totumito",
    "gn:population":0,
    "gn:timezone":"America/Caracas",
    "iso:country":"VE",
    "wof:name":"Totumito",
    "wof:placetype":"locality"
},
  "geometry": {"coordinates":[-68.38648000000001,9.69507],"type":"Point"}
}