{
  "type": "Feature",
  "properties": {
    "iso:country":"VE",
    "qs:gn_pop":0,
    "qs:name":"Idelfonso Vasquez",
    "qs:name_adm0":"Venezuela",
    "qs:name_adm1":"Zulia",
    "qs:photos":192,
    "qs:photos_1k":39,
    "qs:photos_9k":19,
    "qs:photos_9r":12,
    "qs:photos_all":4177,
    "qs:photos_sr":4,
    "qs:placetype":"LocalAdmin",
    "qs:pop_sr":"0",
    "qs:woe_adm0":23424982,
    "wof:name":"Idelfonso Vasquez",
    "wof:placetype":"localadmin"
},
  "geometry": {"coordinates":[-71.630561,10.693375],"type":"Point"}
}