{
  "type": "Feature",
  "properties": {
    "gn:admin1_code":"02",
    "gn:asciiname":"Las Violetas",
    "gn:country_code":"VE",
    "gn:dem":112,
    "gn:feature_class":"P",
    "gn:feature_code":"PPLL",
    "gn:name":"Las Violetas",
    "gn:population":0,
    "gn:timezone":"America/Caracas",
    "iso:country":"VE",
    "wof:name":"Las Violetas",
    "wof:placetype":"locality"
},
  "geometry": {"coordinates":[-64.81608,8.23987],"type":"Point"}
}