{
  "type": "Feature",
  "properties": {
    "gn:admin1_code":"11",
    "gn:asciiname":"El Derramadero",
    "gn:country_code":"VE",
    "gn:dem":39,
    "gn:feature_class":"P",
    "gn:feature_code":"PPL",
    "gn:name":"El Derramadero",
    "gn:population":0,
    "gn:timezone":"America/Caracas",
    "iso:country":"VE",
    "name:und_x_variant":[
        "Derramadero",
        "Desparramadero",
        "El Derramadero"
    ],
    "wof:name":"El Derramadero",
    "wof:placetype":"locality"
},
  "geometry": {"coordinates":[-70.87814,11.02957],"type":"Point"}
}