{
  "type": "Feature",
  "properties": {
    "gn:admin1_code":"23.0",
    "gn:asciiname":"El Bejuco",
    "gn:country_code":"VE",
    "gn:dem":12,
    "gn:feature_class":"P",
    "gn:feature_code":"PPLL",
    "gn:name":"El Bejuco",
    "gn:population":0,
    "gn:timezone":"America/Caracas",
    "iso:country":"VE",
    "wof:name":"El Bejuco",
    "wof:placetype":"locality"
},
  "geometry": {"coordinates":[-72.06279000000001,10.98458],"type":"Point"}
}