{
  "type": "Feature",
  "properties": {
    "gn:admin1_code":"5",
    "gn:asciiname":"Cano Seco Arriba",
    "gn:country_code":"VE",
    "gn:dem":86,
    "gn:feature_class":"P",
    "gn:feature_code":"PPL",
    "gn:name":"Ca\u00f1o Seco Arriba",
    "gn:population":0,
    "gn:timezone":"America/Caracas",
    "iso:country":"VE",
    "wof:name":"Cano Seco Arriba",
    "wof:placetype":"locality"
},
  "geometry": {"coordinates":[-69.34999999999999,8.15],"type":"Point"}
}