{
  "type": "Feature",
  "properties": {
    "gn:admin1_code":"6",
    "gn:asciiname":"El Descanso",
    "gn:country_code":"VE",
    "gn:dem":155,
    "gn:feature_class":"P",
    "gn:feature_code":"PPL",
    "gn:name":"El Descanso",
    "gn:population":0,
    "gn:timezone":"America/Caracas",
    "iso:country":"VE",
    "wof:name":"El Descanso",
    "wof:placetype":"locality"
},
  "geometry": {"coordinates":[-61.93333000000001,6.98333],"type":"Point"}
}