{
  "type": "Feature",
  "properties": {
    "gn:admin1_code":"6.0",
    "gn:asciiname":"La Montanita",
    "gn:country_code":"VE",
    "gn:dem":120,
    "gn:feature_class":"P",
    "gn:feature_code":"PPL",
    "gn:name":"La Monta\u00f1ita",
    "gn:population":0,
    "gn:timezone":"America/Caracas",
    "iso:country":"VE",
    "wof:name":"La Montanita",
    "wof:placetype":"locality"
},
  "geometry": {"coordinates":[-64.07980999999999,7.74085],"type":"Point"}
}