{
  "type": "Feature",
  "properties": {
    "gn:admin1_code":"03",
    "gn:asciiname":"Santa Rufina",
    "gn:country_code":"VE",
    "gn:dem":56,
    "gn:feature_class":"P",
    "gn:feature_code":"PPL",
    "gn:name":"Santa Rufina",
    "gn:population":0,
    "gn:timezone":"America/Caracas",
    "iso:country":"VE",
    "wof:name":"Santa Rufina",
    "wof:placetype":"locality"
},
  "geometry": {"coordinates":[-67.66667,7.26667],"type":"Point"}
}