{
  "type": "Feature",
  "properties": {
    "gn:admin1_code":"1",
    "gn:asciiname":"Paridagua",
    "gn:cc2":"VE",
    "gn:country_code":"VE",
    "gn:dem":94,
    "gn:feature_class":"P",
    "gn:feature_code":"PPL",
    "gn:name":"Paridagua",
    "gn:population":0,
    "gn:timezone":"America/Caracas",
    "iso:country":"VE",
    "name:und_x_variant":[
        "Piridagua",
        "Paridagua"
    ],
    "wof:name":"Paridagua",
    "wof:placetype":"locality"
},
  "geometry": {"coordinates":[-66.58333,1.96667],"type":"Point"}
}