{
  "type": "Feature",
  "properties": {
    "gn:admin1_code":"14",
    "gn:asciiname":"Nuestra Senora",
    "gn:country_code":"VE",
    "gn:dem":2685,
    "gn:feature_class":"P",
    "gn:feature_code":"PPL",
    "gn:name":"Nuestra Se\u00f1ora",
    "gn:population":0,
    "gn:timezone":"America/Caracas",
    "iso:country":"VE",
    "wof:name":"Nuestra Senora",
    "wof:placetype":"locality"
},
  "geometry": {"coordinates":[-71.02589,8.46001],"type":"Point"}
}