{
  "type": "Feature",
  "properties": {
    "gn:admin1_code":"3",
    "gn:asciiname":"Manglarote",
    "gn:country_code":"VE",
    "gn:dem":50,
    "gn:feature_class":"P",
    "gn:feature_code":"PPL",
    "gn:name":"Manglarote",
    "gn:population":0,
    "gn:timezone":"America/Caracas",
    "iso:country":"VE",
    "wof:name":"Manglarote",
    "wof:placetype":"locality"
},
  "geometry": {"coordinates":[-67.33722,7.76583],"type":"Point"}
}