{
  "type": "Feature",
  "properties": {
    "gn:admin1_code":"5",
    "gn:asciiname":"Masparro",
    "gn:country_code":"VE",
    "gn:dem":140,
    "gn:feature_class":"P",
    "gn:feature_code":"PPL",
    "gn:name":"Masparro",
    "gn:population":0,
    "gn:timezone":"America/Caracas",
    "iso:country":"VE",
    "wof:name":"Masparro",
    "wof:placetype":"locality"
},
  "geometry": {"coordinates":[-69.95333000000001,8.61667],"type":"Point"}
}