{
  "type": "Feature",
  "properties": {
    "gn:admin1_code":"12",
    "gn:asciiname":"Campo Claro",
    "gn:country_code":"VE",
    "gn:dem":161,
    "gn:feature_class":"P",
    "gn:feature_code":"PPL",
    "gn:name":"Campo Claro",
    "gn:population":0,
    "gn:timezone":"America/Caracas",
    "iso:country":"VE",
    "wof:name":"Campo Claro",
    "wof:placetype":"locality"
},
  "geometry": {"coordinates":[-64.93333,8.83333],"type":"Point"}
}