{
  "type": "Feature",
  "properties": {
    "gn:admin1_code":"18",
    "gn:asciiname":"Barrio Ajuro",
    "gn:country_code":"VE",
    "gn:dem":316,
    "gn:feature_class":"P",
    "gn:feature_code":"PPL",
    "gn:name":"Barrio Ajuro",
    "gn:population":0,
    "gn:timezone":"America/Caracas",
    "iso:country":"VE",
    "wof:name":"Barrio Ajuro",
    "wof:placetype":"locality"
},
  "geometry": {"coordinates":[-69.32884,9.60896],"type":"Point"}
}