{
  "type": "Feature",
  "properties": {
    "gn:admin1_code":"12.0",
    "gn:asciiname":"Los Naranjeros",
    "gn:country_code":"VE",
    "gn:dem":127,
    "gn:feature_class":"P",
    "gn:feature_code":"PPLL",
    "gn:name":"Los Naranjeros",
    "gn:population":0,
    "gn:timezone":"America/Caracas",
    "iso:country":"VE",
    "wof:name":"Los Naranjeros",
    "wof:placetype":"locality"
},
  "geometry": {"coordinates":[-66.2903,9.04393],"type":"Point"}
}