{
  "type": "Feature",
  "properties": {
    "gn:admin1_code":"6",
    "gn:asciiname":"La Pica",
    "gn:country_code":"VE",
    "gn:dem":43,
    "gn:feature_class":"P",
    "gn:feature_code":"PPL",
    "gn:name":"La Pica",
    "gn:population":0,
    "gn:timezone":"America/Caracas",
    "iso:country":"VE",
    "wof:name":"La Pica",
    "wof:placetype":"locality"
},
  "geometry": {"coordinates":[-65.50442,7.83255],"type":"Point"}
}