{
  "type": "Feature",
  "properties": {
    "gn:admin1_code":"19.0",
    "gn:asciiname":"Mochimita",
    "gn:country_code":"VE",
    "gn:dem":34,
    "gn:feature_class":"P",
    "gn:feature_code":"PPL",
    "gn:name":"Mochimita",
    "gn:population":0,
    "gn:timezone":"America/Caracas",
    "iso:country":"VE",
    "wof:name":"Mochimita",
    "wof:placetype":"locality"
},
  "geometry": {"coordinates":[-64.16045,10.35187],"type":"Point"}
}