{
  "type": "Feature",
  "properties": {
    "gn:admin1_code":"3",
    "gn:asciiname":"Boralito",
    "gn:country_code":"VE",
    "gn:dem":82,
    "gn:feature_class":"P",
    "gn:feature_code":"PPL",
    "gn:name":"Boralito",
    "gn:population":0,
    "gn:timezone":"America/Caracas",
    "iso:country":"VE",
    "wof:name":"Boralito",
    "wof:placetype":"locality"
},
  "geometry": {"coordinates":[-69.02686,7.40942],"type":"Point"}
}