{
  "type": "Feature",
  "properties": {
    "gn:admin1_code":"18.0",
    "gn:asciiname":"Naranjitos",
    "gn:country_code":"VE",
    "gn:dem":113,
    "gn:feature_class":"P",
    "gn:feature_code":"PPL",
    "gn:name":"Naranjitos",
    "gn:population":0,
    "gn:timezone":"America/Caracas",
    "iso:country":"VE",
    "name:spa_x_preferred":[
        "Naranjitos"
    ],
    "wof:name":"Naranjitos",
    "wof:placetype":"locality"
},
  "geometry": {"coordinates":[-69.48865000000001,9.04694],"type":"Point"}
}