{
  "type": "Feature",
  "properties": {
    "gn:admin1_code":"15",
    "gn:asciiname":"Araguita",
    "gn:country_code":"VE",
    "gn:dem":262,
    "gn:feature_class":"P",
    "gn:feature_code":"PPL",
    "gn:name":"Arag\u00fcita",
    "gn:population":0,
    "gn:timezone":"America/Caracas",
    "iso:country":"VE",
    "wof:name":"Araguita",
    "wof:placetype":"locality"
},
  "geometry": {"coordinates":[-66.90338,10.12568],"type":"Point"}
}