{
  "type": "Feature",
  "properties": {
    "gn:admin1_code":"02",
    "gn:asciiname":"La Guatarama Abajo",
    "gn:country_code":"VE",
    "gn:dem":147,
    "gn:feature_class":"P",
    "gn:feature_code":"PPLL",
    "gn:name":"La Guatarama Abajo",
    "gn:population":0,
    "gn:timezone":"America/Caracas",
    "iso:country":"VE",
    "wof:name":"La Guatarama Abajo",
    "wof:placetype":"locality"
},
  "geometry": {"coordinates":[-64.53191,9.66225],"type":"Point"}
}