{
  "type": "Feature",
  "properties": {
    "gn:admin1_code":"02",
    "gn:asciiname":"El Jabillo",
    "gn:country_code":"VE",
    "gn:dem":560,
    "gn:feature_class":"P",
    "gn:feature_code":"PPLL",
    "gn:name":"El Jabillo",
    "gn:population":0,
    "gn:timezone":"America/Caracas",
    "iso:country":"VE",
    "wof:name":"El Jabillo",
    "wof:placetype":"locality"
},
  "geometry": {"coordinates":[-64.42163000000001,10.01429],"type":"Point"}
}