{
  "type": "Feature",
  "properties": {
    "gn:admin1_code":"11.0",
    "gn:asciiname":"La Pega de los Cerros",
    "gn:country_code":"VE",
    "gn:dem":409,
    "gn:feature_class":"P",
    "gn:feature_code":"PPLL",
    "gn:name":"La Pega de los Cerros",
    "gn:population":0,
    "gn:timezone":"America/Caracas",
    "iso:country":"VE",
    "wof:name":"La Pega de los Cerros",
    "wof:placetype":"locality"
},
  "geometry": {"coordinates":[-70.71715999999998,10.69185],"type":"Point"}
}