{
  "type": "Feature",
  "properties": {
    "gn:admin1_code":"11",
    "gn:asciiname":"Pecaya",
    "gn:country_code":"VE",
    "gn:dem":249,
    "gn:feature_class":"P",
    "gn:feature_code":"PPL",
    "gn:name":"Pecaya",
    "gn:population":0,
    "gn:timezone":"America/Caracas",
    "iso:country":"VE",
    "wof:name":"Pecaya",
    "wof:placetype":"locality"
},
  "geometry": {"coordinates":[-69.86466999999999,11.07631],"type":"Point"}
}