{
  "type": "Feature",
  "properties": {
    "gn:admin1_code":"19.0",
    "gn:asciiname":"La Magnifica",
    "gn:country_code":"VE",
    "gn:dem":376,
    "gn:feature_class":"P",
    "gn:feature_code":"PPLL",
    "gn:name":"La Magnifica",
    "gn:population":0,
    "gn:timezone":"America/Caracas",
    "iso:country":"VE",
    "wof:name":"La Magnifica",
    "wof:placetype":"locality"
},
  "geometry": {"coordinates":[-64.36234,10.25569],"type":"Point"}
}