{
  "type": "Feature",
  "properties": {
    "gn:admin1_code":"02",
    "gn:asciiname":"La Toma",
    "gn:country_code":"VE",
    "gn:dem":152,
    "gn:feature_class":"P",
    "gn:feature_code":"PPLL",
    "gn:name":"La Toma",
    "gn:population":0,
    "gn:timezone":"America/Caracas",
    "iso:country":"VE",
    "wof:name":"La Toma",
    "wof:placetype":"locality"
},
  "geometry": {"coordinates":[-64.49198,10.18214],"type":"Point"}
}