{
  "type": "Feature",
  "properties": {
    "gn:admin1_code":"2",
    "gn:asciiname":"La Margarita",
    "gn:country_code":"VE",
    "gn:dem":53,
    "gn:feature_class":"P",
    "gn:feature_code":"PPL",
    "gn:name":"La Margarita",
    "gn:population":0,
    "gn:timezone":"America/Caracas",
    "iso:country":"VE",
    "wof:name":"La Margarita",
    "wof:placetype":"locality"
},
  "geometry": {"coordinates":[-64.96191999999999,9.67042],"type":"Point"}
}