{
  "type": "Feature",
  "properties": {
    "gn:admin1_code":"13",
    "gn:asciiname":"Los Planes del Guayabo",
    "gn:country_code":"VE",
    "gn:dem":661,
    "gn:feature_class":"P",
    "gn:feature_code":"PPL",
    "gn:name":"Los Planes del Guayabo",
    "gn:population":0,
    "gn:timezone":"America/Caracas",
    "iso:country":"VE",
    "wof:name":"Los Planes del Guayabo",
    "wof:placetype":"locality"
},
  "geometry": {"coordinates":[-70.43361,10.34624],"type":"Point"}
}