{
  "type": "Feature",
  "properties": {
    "gn:admin1_code":"13",
    "gn:asciiname":"El Potrero",
    "gn:country_code":"VE",
    "gn:dem":570,
    "gn:feature_class":"P",
    "gn:feature_code":"PPL",
    "gn:name":"El Potrero",
    "gn:population":0,
    "gn:timezone":"America/Caracas",
    "iso:country":"VE",
    "wof:name":"El Potrero",
    "wof:placetype":"locality"
},
  "geometry": {"coordinates":[-69.25968,10.18106],"type":"Point"}
}