{
  "type": "Feature",
  "properties": {
    "gn:admin1_code":"6.0",
    "gn:asciiname":"Corobal",
    "gn:country_code":"VE",
    "gn:dem":41,
    "gn:feature_class":"P",
    "gn:feature_code":"PPL",
    "gn:name":"Corobal",
    "gn:population":0,
    "gn:timezone":"America/Caracas",
    "iso:country":"VE",
    "wof:name":"Corobal",
    "wof:placetype":"locality"
},
  "geometry": {"coordinates":[-65.69835999999999,7.80205],"type":"Point"}
}