{
  "type": "Feature",
  "properties": {
    "gn:admin1_code":"20",
    "gn:asciiname":"Mesa de Aura",
    "gn:country_code":"VE",
    "gn:dem":2212,
    "gn:feature_class":"P",
    "gn:feature_code":"PPL",
    "gn:name":"Mesa de Aura",
    "gn:population":0,
    "gn:timezone":"America/Caracas",
    "iso:country":"VE",
    "wof:name":"Mesa de Aura",
    "wof:placetype":"locality"
},
  "geometry": {"coordinates":[-72.11024,7.95185],"type":"Point"}
}