{
  "type": "Feature",
  "properties": {
    "gn:admin1_code":"19",
    "gn:asciiname":"Caliche",
    "gn:country_code":"VE",
    "gn:dem":41,
    "gn:feature_class":"P",
    "gn:feature_code":"PPL",
    "gn:name":"Caliche",
    "gn:population":0,
    "gn:timezone":"America/Caracas",
    "iso:country":"VE",
    "name:ara_x_preferred":[
        "\u0643\u0627\u0644\u064a\u0634"
    ],
    "name:arg_x_preferred":[
        "Mallac\u00e1n"
    ],
    "name:cat_x_preferred":[
        "Caliche"
    ],
    "name:heb_x_preferred":[
        "\u05e0\u05d0\u05e8\u05d9"
    ],
    "name:ita_x_preferred":[
        "Caliche"
    ],
    "name:nno_x_preferred":[
        "Caliche"
    ],
    "name:nor_x_preferred":[
        "Caliche"
    ],
    "name:pol_x_preferred":[
        "Caliche"
    ],
    "name:por_x_preferred":[
        "Caliche"
    ],
    "name:rus_x_preferred":[
        "\u041a\u0430\u043b\u0438\u0447\u0435"
    ],
    "name:spa_x_preferred":[
        "Caliche"
    ],
    "name:tur_x_preferred":[
        "Kali\u015f"
    ],
    "name:ukr_x_preferred":[
        "\u041a\u0430\u043b\u0456\u0447\u0435"
    ],
    "wof:name":"Caliche",
    "wof:placetype":"locality"
},
  "geometry": {"coordinates":[-63.2347,10.29489],"type":"Point"}
}