{
  "type": "Feature",
  "properties": {
    "gn:admin1_code":"21",
    "gn:asciiname":"El Jarillo",
    "gn:country_code":"VE",
    "gn:dem":2131,
    "gn:feature_class":"P",
    "gn:feature_code":"PPL",
    "gn:name":"El Jarillo",
    "gn:population":0,
    "gn:timezone":"America/Caracas",
    "iso:country":"VE",
    "wof:name":"El Jarillo",
    "wof:placetype":"locality"
},
  "geometry": {"coordinates":[-70.27717,9.36819],"type":"Point"}
}