{
  "type": "Feature",
  "properties": {
    "gn:admin1_code":"12",
    "gn:asciiname":"Taguapire",
    "gn:country_code":"VE",
    "gn:dem":100,
    "gn:feature_class":"P",
    "gn:feature_code":"PPL",
    "gn:name":"Taguapire",
    "gn:population":0,
    "gn:timezone":"America/Caracas",
    "iso:country":"VE",
    "wof:name":"Taguapire",
    "wof:placetype":"locality"
},
  "geometry": {"coordinates":[-65.63481,9.25686],"type":"Point"}
}