{
  "type": "Feature",
  "properties": {
    "gn:admin1_code":"19.0",
    "gn:asciiname":"Montanas Negras",
    "gn:country_code":"VE",
    "gn:dem":658,
    "gn:feature_class":"P",
    "gn:feature_code":"PPL",
    "gn:name":"Monta\u00f1as Negras",
    "gn:population":0,
    "gn:timezone":"America/Caracas",
    "iso:country":"VE",
    "wof:name":"Montanas Negras",
    "wof:placetype":"locality"
},
  "geometry": {"coordinates":[-63.71222,10.29667],"type":"Point"}
}