{
  "type": "Feature",
  "properties": {
    "gn:admin1_code":"20",
    "gn:admin2_code":"2020",
    "gn:asciiname":"Urena",
    "gn:country_code":"VE",
    "gn:dem":338,
    "gn:feature_class":"P",
    "gn:feature_code":"PPLA2",
    "gn:name":"Ure\u00f1a",
    "gn:population":0,
    "gn:timezone":"America/Caracas",
    "iso:country":"VE",
    "name:ceb_x_preferred":[
        "Urena"
    ],
    "name:ces_x_preferred":[
        "Urena"
    ],
    "name:eng_x_preferred":[
        "Ure\u00f1a"
    ],
    "name:eng_x_variant":[
        "Urena"
    ],
    "name:nld_x_preferred":[
        "Urena"
    ],
    "name:por_x_preferred":[
        "Ure\u00f1a"
    ],
    "name:por_x_variant":[
        "Urena"
    ],
    "name:spa_x_preferred":[
        "Ure\u00f1a"
    ],
    "name:spa_x_variant":[
        "Urena"
    ],
    "name:swe_x_preferred":[
        "Urena"
    ],
    "name:vie_x_preferred":[
        "Chi K\u00e9"
    ],
    "name:war_x_preferred":[
        "Urena"
    ],
    "name:zho_x_preferred":[
        "\u68b5\u5929\u82b1\u5c5e"
    ],
    "wof:name":"Urena",
    "wof:placetype":"locality"
},
  "geometry": {"coordinates":[-72.44188,7.91689],"type":"Point"}
}