{
  "type": "Feature",
  "properties": {
    "gn:admin1_code":"17.0",
    "gn:asciiname":"El Toco",
    "gn:country_code":"VE",
    "gn:dem":36,
    "gn:feature_class":"P",
    "gn:feature_code":"PPL",
    "gn:name":"El Toco",
    "gn:population":0,
    "gn:timezone":"America/Caracas",
    "iso:country":"VE",
    "wof:name":"El Toco",
    "wof:placetype":"locality"
},
  "geometry": {"coordinates":[-63.86099,11.1227],"type":"Point"}
}