{
  "type": "Feature",
  "properties": {
    "gn:admin1_code":"6",
    "gn:asciiname":"La Encrucijada",
    "gn:country_code":"VE",
    "gn:dem":137,
    "gn:feature_class":"P",
    "gn:feature_code":"PPL",
    "gn:name":"La Encrucijada",
    "gn:population":0,
    "gn:timezone":"America/Caracas",
    "iso:country":"VE",
    "wof:name":"La Encrucijada",
    "wof:placetype":"locality"
},
  "geometry": {"coordinates":[-62.94231,8.14951],"type":"Point"}
}