{
  "type": "Feature",
  "properties": {
    "gn:admin1_code":"2",
    "gn:asciiname":"La Pega",
    "gn:country_code":"VE",
    "gn:dem":1194,
    "gn:feature_class":"P",
    "gn:feature_code":"PPL",
    "gn:name":"La Pega",
    "gn:population":0,
    "gn:timezone":"America/Caracas",
    "iso:country":"VE",
    "wof:name":"La Pega",
    "wof:placetype":"locality"
},
  "geometry": {"coordinates":[-64.28333000000001,10.05],"type":"Point"}
}