{
  "type": "Feature",
  "properties": {
    "gn:admin1_code":"17.0",
    "gn:asciiname":"La Chica",
    "gn:country_code":"VE",
    "gn:dem":81,
    "gn:feature_class":"P",
    "gn:feature_code":"PPL",
    "gn:name":"La Chica",
    "gn:population":0,
    "gn:timezone":"America/Caracas",
    "iso:country":"VE",
    "wof:name":"La Chica",
    "wof:placetype":"locality"
},
  "geometry": {"coordinates":[-63.86885,11.11693],"type":"Point"}
}