{
  "type": "Feature",
  "properties": {
    "gn:admin1_code":"20",
    "gn:asciiname":"Santa Filomena",
    "gn:country_code":"VE",
    "gn:dem":893,
    "gn:feature_class":"P",
    "gn:feature_code":"PPL",
    "gn:name":"Santa Filomena",
    "gn:population":0,
    "gn:timezone":"America/Caracas",
    "iso:country":"VE",
    "name:ceb_x_preferred":[
        "Santa Filomena"
    ],
    "name:deu_x_preferred":[
        "Santa Filomena"
    ],
    "name:fra_x_preferred":[
        "Santa Filomena"
    ],
    "name:ita_x_preferred":[
        "Santa Filomena"
    ],
    "name:nld_x_preferred":[
        "Santa Filomena"
    ],
    "name:nor_x_preferred":[
        "Santa Filomena"
    ],
    "name:por_x_preferred":[
        "Santa Filomena"
    ],
    "name:rus_x_preferred":[
        "\u0421\u0430\u043d\u0442\u0430-\u0424\u0438\u043b\u043e\u043c\u0435\u043d\u0430"
    ],
    "name:spa_x_preferred":[
        "Santa Filomena"
    ],
    "name:srp_x_preferred":[
        "\u0421\u0430\u043d\u0442\u0430 \u0424\u0438\u043b\u043e\u043c\u0435\u043d\u0430"
    ],
    "name:swe_x_preferred":[
        "Santa Filomena"
    ],
    "name:vie_x_preferred":[
        "Santa Filomena"
    ],
    "name:vol_x_preferred":[
        "Santa Filomena"
    ],
    "wof:name":"Santa Filomena",
    "wof:placetype":"locality"
},
  "geometry": {"coordinates":[-72.08168000000001,8.13919],"type":"Point"}
}