{
  "type": "Feature",
  "properties": {
    "gn:admin1_code":"20",
    "gn:asciiname":"Santa Filomena",
    "gn:country_code":"VE",
    "gn:dem":893,
    "gn:feature_class":"P",
    "gn:feature_code":"PPL",
    "gn:name":"Santa Filomena",
    "gn:population":0,
    "gn:timezone":"America/Caracas",
    "iso:country":"VE",
    "wof:name":"Santa Filomena",
    "wof:placetype":"locality"
},
  "geometry": {"coordinates":[-72.08168000000001,8.13919],"type":"Point"}
}