{
  "type": "Feature",
  "properties": {
    "gn:admin1_code":"16",
    "gn:asciiname":"Lomas de Rio Arriba",
    "gn:country_code":"VE",
    "gn:dem":246,
    "gn:feature_class":"P",
    "gn:feature_code":"PPL",
    "gn:name":"Lomas de R\u00edo Arriba",
    "gn:population":0,
    "gn:timezone":"America/Caracas",
    "iso:country":"VE",
    "wof:name":"Lomas de Rio Arriba",
    "wof:placetype":"locality"
},
  "geometry": {"coordinates":[-63.2112,10.07059],"type":"Point"}
}