{
  "type": "Feature",
  "properties": {
    "gn:admin1_code":"7",
    "gn:asciiname":"Canoabito",
    "gn:country_code":"VE",
    "gn:dem":301,
    "gn:feature_class":"P",
    "gn:feature_code":"PPL",
    "gn:name":"Canoabito",
    "gn:population":0,
    "gn:timezone":"America/Caracas",
    "iso:country":"VE",
    "wof:name":"Canoabito",
    "wof:placetype":"locality"
},
  "geometry": {"coordinates":[-68.26467,10.31744],"type":"Point"}
}