{
  "type": "Feature",
  "properties": {
    "gn:admin1_code":"22",
    "gn:asciiname":"Taria",
    "gn:country_code":"VE",
    "gn:dem":45,
    "gn:feature_class":"P",
    "gn:feature_code":"PPL",
    "gn:name":"Tar\u00eda",
    "gn:population":0,
    "gn:timezone":"America/Caracas",
    "iso:country":"VE",
    "wof:name":"Taria",
    "wof:placetype":"locality"
},
  "geometry": {"coordinates":[-68.56754000000001,10.42602],"type":"Point"}
}