{
  "type": "Feature",
  "properties": {
    "gn:admin1_code":"6.0",
    "gn:asciiname":"Piedra de Buena Vista",
    "gn:country_code":"VE",
    "gn:dem":40,
    "gn:feature_class":"P",
    "gn:feature_code":"PPL",
    "gn:name":"Piedra de Buena Vista",
    "gn:population":0,
    "gn:timezone":"America/Caracas",
    "iso:country":"VE",
    "wof:name":"Piedra de Buena Vista",
    "wof:placetype":"locality"
},
  "geometry": {"coordinates":[-66.84563,7.19825],"type":"Point"}
}