{
  "type": "Feature",
  "properties": {
    "gn:admin1_code":"02",
    "gn:asciiname":"Santoyo",
    "gn:country_code":"VE",
    "gn:dem":43,
    "gn:feature_class":"P",
    "gn:feature_code":"PPL",
    "gn:name":"Santoyo",
    "gn:population":0,
    "gn:timezone":"America/Caracas",
    "iso:country":"VE",
    "name:ast_x_preferred":[
        "Santoyo"
    ],
    "name:azb_x_preferred":[
        "\u0633\u0627\u0646\u062a\u06cc\u0648"
    ],
    "name:cat_x_preferred":[
        "Santoyo"
    ],
    "name:ceb_x_preferred":[
        "Santoyo"
    ],
    "name:eus_x_preferred":[
        "Santoyo"
    ],
    "name:fas_x_preferred":[
        "\u0633\u0627\u0646\u062a\u06cc\u0648"
    ],
    "name:fra_x_preferred":[
        "Santoyo"
    ],
    "name:glg_x_preferred":[
        "Santoyo"
    ],
    "name:hun_x_preferred":[
        "Santoyo"
    ],
    "name:ina_x_preferred":[
        "Santoyo"
    ],
    "name:ita_x_preferred":[
        "Santoyo"
    ],
    "name:msa_x_preferred":[
        "Santoyo"
    ],
    "name:nld_x_preferred":[
        "Santoyo"
    ],
    "name:oci_x_preferred":[
        "Santoyo"
    ],
    "name:pol_x_preferred":[
        "Santoyo"
    ],
    "name:por_x_preferred":[
        "Santoyo"
    ],
    "name:rus_x_preferred":[
        "\u0421\u0430\u043d\u0442\u043e\u0439\u043e"
    ],
    "name:spa_x_preferred":[
        "Santoyo"
    ],
    "name:swe_x_preferred":[
        "Santoyo"
    ],
    "name:ukr_x_preferred":[
        "\u0421\u0430\u043d\u0442\u043e\u0439\u043e"
    ],
    "name:uzb_x_preferred":[
        "Santoyo"
    ],
    "name:vie_x_preferred":[
        "Santoyo"
    ],
    "name:war_x_preferred":[
        "Santoyo"
    ],
    "name:zho_x_preferred":[
        "\u6851\u6258\u7ea6"
    ],
    "wof:name":"Santoyo",
    "wof:placetype":"locality"
},
  "geometry": {"coordinates":[-63.42728,8.29863],"type":"Point"}
}