{
  "type": "Feature",
  "properties": {
    "gn:admin1_code":"6.0",
    "gn:asciiname":"Mata Negra",
    "gn:country_code":"VE",
    "gn:dem":62,
    "gn:feature_class":"P",
    "gn:feature_code":"PPL",
    "gn:name":"Mata Negra",
    "gn:population":0,
    "gn:timezone":"America/Caracas",
    "iso:country":"VE",
    "wof:name":"Mata Negra",
    "wof:placetype":"locality"
},
  "geometry": {"coordinates":[-64.96214000000001,7.34008],"type":"Point"}
}