{
  "type": "Feature",
  "properties": {
    "gn:admin1_code":"02",
    "gn:asciiname":"Teneria Anzoategui",
    "gn:country_code":"VE",
    "gn:dem":72,
    "gn:feature_class":"P",
    "gn:feature_code":"PPLL",
    "gn:name":"Tener\u00eda Anzoategui",
    "gn:population":0,
    "gn:timezone":"America/Caracas",
    "iso:country":"VE",
    "wof:name":"Teneria Anzoategui",
    "wof:placetype":"locality"
},
  "geometry": {"coordinates":[-63.57911,8.19685],"type":"Point"}
}