{
  "type": "Feature",
  "properties": {
    "gn:admin1_code":"11.0",
    "gn:asciiname":"El Saladillo",
    "gn:country_code":"VE",
    "gn:dem":323,
    "gn:feature_class":"P",
    "gn:feature_code":"PPLL",
    "gn:name":"El Saladillo",
    "gn:population":0,
    "gn:timezone":"America/Caracas",
    "iso:country":"VE",
    "wof:name":"El Saladillo",
    "wof:placetype":"locality"
},
  "geometry": {"coordinates":[-70.68783000000001,10.70375],"type":"Point"}
}