{
  "type": "Feature",
  "properties": {
    "gn:admin1_code":"6",
    "gn:asciiname":"Morichito",
    "gn:country_code":"VE",
    "gn:dem":40,
    "gn:feature_class":"P",
    "gn:feature_code":"PPL",
    "gn:name":"Morichito",
    "gn:population":0,
    "gn:timezone":"America/Caracas",
    "iso:country":"VE",
    "wof:name":"Morichito",
    "wof:placetype":"locality"
},
  "geometry": {"coordinates":[-66.03093,7.62767],"type":"Point"}
}