{
  "type": "Feature",
  "properties": {
    "gn:admin1_code":"3.0",
    "gn:asciiname":"El Charo",
    "gn:country_code":"VE",
    "gn:dem":97,
    "gn:feature_class":"P",
    "gn:feature_code":"PPLL",
    "gn:name":"El Charo",
    "gn:population":0,
    "gn:timezone":"America/Caracas",
    "iso:country":"VE",
    "wof:name":"El Charo",
    "wof:placetype":"locality"
},
  "geometry": {"coordinates":[-69.95147,7.61618],"type":"Point"}
}