{
  "type": "Feature",
  "properties": {
    "gn:admin1_code":"2",
    "gn:asciiname":"Cunaguaro",
    "gn:country_code":"VE",
    "gn:dem":158,
    "gn:feature_class":"P",
    "gn:feature_code":"PPL",
    "gn:name":"Cunaguaro",
    "gn:population":0,
    "gn:timezone":"America/Caracas",
    "iso:country":"VE",
    "wof:name":"Cunaguaro",
    "wof:placetype":"locality"
},
  "geometry": {"coordinates":[-64.27545000000001,8.46457],"type":"Point"}
}