{
  "type": "Feature",
  "properties": {
    "gn:admin1_code":"1",
    "gn:asciiname":"Colon",
    "gn:country_code":"VE",
    "gn:dem":100,
    "gn:feature_class":"P",
    "gn:feature_code":"PPL",
    "gn:name":"Col\u00f3n",
    "gn:population":0,
    "gn:timezone":"America/Caracas",
    "iso:country":"VE",
    "wof:name":"Colon",
    "wof:placetype":"locality"
},
  "geometry": {"coordinates":[-67.10972,2.14056],"type":"Point"}
}