{
  "type": "Feature",
  "properties": {
    "gn:admin1_code":"14",
    "gn:asciiname":"Puente Real",
    "gn:country_code":"VE",
    "gn:dem":623,
    "gn:feature_class":"P",
    "gn:feature_code":"PPL",
    "gn:name":"Puente Real",
    "gn:population":0,
    "gn:timezone":"America/Caracas",
    "iso:country":"VE",
    "wof:name":"Puente Real",
    "wof:placetype":"locality"
},
  "geometry": {"coordinates":[-71.41023,8.4712],"type":"Point"}
}