{
  "type": "Feature",
  "properties": {
    "gn:admin1_code":"15",
    "gn:asciiname":"La Lima",
    "gn:country_code":"VE",
    "gn:dem":528,
    "gn:feature_class":"P",
    "gn:feature_code":"PPL",
    "gn:name":"La Lima",
    "gn:population":0,
    "gn:timezone":"America/Caracas",
    "iso:country":"VE",
    "wof:name":"La Lima",
    "wof:placetype":"locality"
},
  "geometry": {"coordinates":[-66.74002,10.03356],"type":"Point"}
}