{
  "type": "Feature",
  "properties": {
    "gn:admin1_code":"19.0",
    "gn:asciiname":"Caiguire Abajo",
    "gn:country_code":"VE",
    "gn:dem":225,
    "gn:feature_class":"P",
    "gn:feature_code":"PPLL",
    "gn:name":"Caiguire Abajo",
    "gn:population":0,
    "gn:timezone":"America/Caracas",
    "iso:country":"VE",
    "wof:name":"Caiguire Abajo",
    "wof:placetype":"locality"
},
  "geometry": {"coordinates":[-63.93806,10.25112],"type":"Point"}
}