{
  "type": "Feature",
  "properties": {
    "gn:admin1_code":"15.0",
    "gn:asciiname":"El Rosario",
    "gn:country_code":"VE",
    "gn:dem":982,
    "gn:feature_class":"P",
    "gn:feature_code":"PPLL",
    "gn:name":"El Rosario",
    "gn:population":0,
    "gn:timezone":"America/Caracas",
    "iso:country":"VE",
    "wof:name":"El Rosario",
    "wof:placetype":"locality"
},
  "geometry": {"coordinates":[-66.74764999999999,10.4291],"type":"Point"}
}