{
  "type": "Feature",
  "properties": {
    "gn:admin1_code":"18",
    "gn:asciiname":"Payara",
    "gn:country_code":"VE",
    "gn:dem":140,
    "gn:feature_class":"P",
    "gn:feature_code":"PPL",
    "gn:name":"Payara",
    "gn:population":0,
    "gn:timezone":"America/Caracas",
    "iso:country":"VE",
    "wof:name":"Payara",
    "wof:placetype":"locality"
},
  "geometry": {"coordinates":[-69.08138000000001,9.4936],"type":"Point"}
}