{
  "type": "Feature",
  "properties": {
    "gn:admin1_code":"18",
    "gn:asciiname":"Payara",
    "gn:country_code":"VE",
    "gn:dem":140,
    "gn:feature_class":"P",
    "gn:feature_code":"PPL",
    "gn:name":"Payara",
    "gn:population":0,
    "gn:timezone":"America/Caracas",
    "iso:country":"VE",
    "name:cat_x_preferred":[
        "Hydrolycus scomberoides"
    ],
    "name:ceb_x_preferred":[
        "Hydrolycus scomberoides"
    ],
    "name:deu_x_preferred":[
        "Hydrolycus scomberoides"
    ],
    "name:eus_x_preferred":[
        "Hydrolycus scomberoides"
    ],
    "name:fas_x_preferred":[
        "\u0632\u0634\u062a\u200c\u0645\u0627\u0647\u06cc"
    ],
    "name:fra_x_preferred":[
        "T\u00e9tra vampire"
    ],
    "name:ita_x_preferred":[
        "Hydrolycus scomberoides"
    ],
    "name:jpn_x_preferred":[
        "\u30da\u30fc\u30b7\u30e5\u30fb\u30ab\u30b7\u30e7\u30fc\u30ed"
    ],
    "name:nld_x_preferred":[
        "Hydrolycus scomberoides"
    ],
    "name:rus_x_preferred":[
        "\u0421\u043a\u0443\u043c\u0431\u0440\u0438\u0435\u0432\u0438\u0434\u043d\u044b\u0439 \u0433\u0438\u0434\u0440\u043e\u043b\u0438\u043a"
    ],
    "name:spa_x_preferred":[
        "Hydrolycus scomberoides"
    ],
    "name:swe_x_preferred":[
        "Hydrolycus scomberoides"
    ],
    "name:tha_x_preferred":[
        "\u0e1b\u0e25\u0e32\u0e2a\u0e04\u0e2d\u0e21\u0e1a\u0e34\u0e23\u0e2d\u0e22\u0e14\u0e4c"
    ],
    "name:war_x_preferred":[
        "Hydrolycus scomberoides"
    ],
    "name:zho_x_preferred":[
        "\u4f3c\u9bd6\u6c34\u72fc\u7259\u9b5a"
    ],
    "wof:name":"Payara",
    "wof:placetype":"locality"
},
  "geometry": {"coordinates":[-69.08138000000001,9.4936],"type":"Point"}
}