{
  "type": "Feature",
  "properties": {
    "gn:admin1_code":"20",
    "gn:asciiname":"Rio Frio",
    "gn:country_code":"VE",
    "gn:dem":498,
    "gn:feature_class":"P",
    "gn:feature_code":"PPL",
    "gn:name":"R\u00edo Fr\u00edo",
    "gn:population":0,
    "gn:timezone":"America/Caracas",
    "iso:country":"VE",
    "wof:name":"Rio Frio",
    "wof:placetype":"locality"
},
  "geometry": {"coordinates":[-72.1292,7.58294],"type":"Point"}
}