{
  "type": "Feature",
  "properties": {
    "gn:admin1_code":"2",
    "gn:asciiname":"El Merey",
    "gn:country_code":"VE",
    "gn:dem":312,
    "gn:feature_class":"P",
    "gn:feature_code":"PPL",
    "gn:name":"El Merey",
    "gn:population":0,
    "gn:timezone":"America/Caracas",
    "iso:country":"VE",
    "wof:name":"El Merey",
    "wof:placetype":"locality"
},
  "geometry": {"coordinates":[-63.96833,9.73641],"type":"Point"}
}