{
  "type": "Feature",
  "properties": {
    "gn:admin1_code":"02",
    "gn:asciiname":"Los Barrancos",
    "gn:country_code":"VE",
    "gn:dem":15,
    "gn:feature_class":"P",
    "gn:feature_code":"PPL",
    "gn:name":"Los Barrancos",
    "gn:population":0,
    "gn:timezone":"America/Caracas",
    "iso:country":"VE",
    "wof:name":"Los Barrancos",
    "wof:placetype":"locality"
},
  "geometry": {"coordinates":[-64.93433,7.69278],"type":"Point"}
}