{
  "type": "Feature",
  "properties": {
    "gn:admin1_code":"19.0",
    "gn:asciiname":"Vuelta de Culebra",
    "gn:country_code":"VE",
    "gn:dem":354,
    "gn:feature_class":"P",
    "gn:feature_code":"PPL",
    "gn:name":"Vuelta de Culebra",
    "gn:population":0,
    "gn:timezone":"America/Caracas",
    "iso:country":"VE",
    "wof:name":"Vuelta de Culebra",
    "wof:placetype":"locality"
},
  "geometry": {"coordinates":[-63.95889,10.325],"type":"Point"}
}