{
  "type": "Feature",
  "properties": {
    "gn:admin1_code":"12",
    "gn:asciiname":"El Granadillo",
    "gn:cc2":"VE",
    "gn:country_code":"VE",
    "gn:dem":650,
    "gn:feature_class":"P",
    "gn:feature_code":"PPL",
    "gn:name":"El Granadillo",
    "gn:population":0,
    "gn:timezone":"America/Caracas",
    "iso:country":"VE",
    "name:und_x_variant":[
        "Granadillo",
        "El Granadillo"
    ],
    "wof:name":"El Granadillo",
    "wof:placetype":"locality"
},
  "geometry": {"coordinates":[-66.06667,9.96667],"type":"Point"}
}