{
  "type": "Feature",
  "properties": {
    "gn:admin1_code":"18.0",
    "gn:asciiname":"San Jorge",
    "gn:country_code":"VE",
    "gn:dem":106,
    "gn:feature_class":"P",
    "gn:feature_code":"PPL",
    "gn:name":"San Jorge",
    "gn:population":0,
    "gn:timezone":"America/Caracas",
    "iso:country":"VE",
    "name:spa_x_preferred":[
        "San Jorge"
    ],
    "wof:name":"San Jorge",
    "wof:placetype":"locality"
},
  "geometry": {"coordinates":[-69.23875,9.10205],"type":"Point"}
}