{
  "type": "Feature",
  "properties": {
    "gn:admin1_code":"13.0",
    "gn:asciiname":"Cobalombo",
    "gn:country_code":"VE",
    "gn:dem":1902,
    "gn:feature_class":"P",
    "gn:feature_code":"PPL",
    "gn:name":"Cobalombo",
    "gn:population":0,
    "gn:timezone":"America/Caracas",
    "iso:country":"VE",
    "wof:name":"Cobalombo",
    "wof:placetype":"locality"
},
  "geometry": {"coordinates":[-70.03764,9.65579],"type":"Point"}
}