{
  "type": "Feature",
  "properties": {
    "gn:admin1_code":"20.0",
    "gn:asciiname":"Las Trincheras",
    "gn:country_code":"VE",
    "gn:dem":1191,
    "gn:feature_class":"P",
    "gn:feature_code":"PPLL",
    "gn:name":"Las Trincheras",
    "gn:population":0,
    "gn:timezone":"America/Caracas",
    "iso:country":"VE",
    "wof:name":"Las Trincheras",
    "wof:placetype":"locality"
},
  "geometry": {"coordinates":[-71.71505000000001,7.93837],"type":"Point"}
}