{
  "type": "Feature",
  "properties": {
    "gn:admin1_code":"13",
    "gn:asciiname":"Cotua",
    "gn:country_code":"VE",
    "gn:dem":731,
    "gn:feature_class":"P",
    "gn:feature_code":"PPL",
    "gn:name":"Cotua",
    "gn:population":0,
    "gn:timezone":"America/Caracas",
    "iso:country":"VE",
    "wof:name":"Cotua",
    "wof:placetype":"locality"
},
  "geometry": {"coordinates":[-69.48333000000001,10.05],"type":"Point"}
}