{
  "type": "Feature",
  "properties": {
    "gn:admin1_code":"11",
    "gn:asciiname":"Palo Quemado",
    "gn:country_code":"VE",
    "gn:dem":299,
    "gn:feature_class":"P",
    "gn:feature_code":"PPL",
    "gn:name":"Palo Quemado",
    "gn:population":0,
    "gn:timezone":"America/Caracas",
    "iso:country":"VE",
    "wof:name":"Palo Quemado",
    "wof:placetype":"locality"
},
  "geometry": {"coordinates":[-69.54356,11.15352],"type":"Point"}
}