{
  "type": "Feature",
  "properties": {
    "gn:admin1_code":"6.0",
    "gn:asciiname":"Pueblo al Medio",
    "gn:country_code":"VE",
    "gn:dem":367,
    "gn:feature_class":"P",
    "gn:feature_code":"PPL",
    "gn:name":"Pueblo al Medio",
    "gn:population":0,
    "gn:timezone":"America/Caracas",
    "iso:country":"VE",
    "wof:name":"Pueblo al Medio",
    "wof:placetype":"locality"
},
  "geometry": {"coordinates":[-63.20721999999999,6.04056],"type":"Point"}
}