{
  "type": "Feature",
  "properties": {
    "gn:admin1_code":"07",
    "gn:asciiname":"Las Queseras",
    "gn:country_code":"VE",
    "gn:dem":496,
    "gn:feature_class":"P",
    "gn:feature_code":"PPLL",
    "gn:name":"Las Queseras",
    "gn:population":0,
    "gn:timezone":"America/Caracas",
    "iso:country":"VE",
    "wof:name":"Las Queseras",
    "wof:placetype":"locality"
},
  "geometry": {"coordinates":[-67.92918,9.8658],"type":"Point"}
}