{
  "type": "Feature",
  "properties": {
    "gn:admin1_code":"12",
    "gn:asciiname":"Las Lajitas",
    "gn:country_code":"VE",
    "gn:dem":186,
    "gn:feature_class":"P",
    "gn:feature_code":"PPL",
    "gn:name":"Las Lajitas",
    "gn:population":0,
    "gn:timezone":"America/Caracas",
    "iso:country":"VE",
    "name:ceb_x_preferred":[
        "Las Lajitas"
    ],
    "name:por_x_preferred":[
        "Las Lajitas"
    ],
    "name:spa_x_preferred":[
        "Las Lajitas"
    ],
    "name:urd_x_preferred":[
        "\u0644\u0627\u0633 \u0644\u0627\u062c\u06cc\u0679\u0627\u0633"
    ],
    "wof:name":"Las Lajitas",
    "wof:placetype":"locality"
},
  "geometry": {"coordinates":[-67.67454000000001,9.55174],"type":"Point"}
}