{
  "type": "Feature",
  "properties": {
    "gn:admin1_code":"6",
    "gn:asciiname":"Parupa",
    "gn:country_code":"VE",
    "gn:dem":325,
    "gn:feature_class":"P",
    "gn:feature_code":"PPL",
    "gn:name":"Parupa",
    "gn:population":0,
    "gn:timezone":"America/Caracas",
    "iso:country":"VE",
    "wof:name":"Parupa",
    "wof:placetype":"locality"
},
  "geometry": {"coordinates":[-63.61816999999999,5.47469],"type":"Point"}
}