{
  "type": "Feature",
  "properties": {
    "gn:admin1_code":"20",
    "gn:asciiname":"Las Lapas",
    "gn:country_code":"VE",
    "gn:dem":1098,
    "gn:feature_class":"P",
    "gn:feature_code":"PPL",
    "gn:name":"Las Lapas",
    "gn:population":0,
    "gn:timezone":"America/Caracas",
    "iso:country":"VE",
    "wof:name":"Las Lapas",
    "wof:placetype":"locality"
},
  "geometry": {"coordinates":[-71.68333,7.96667],"type":"Point"}
}