{
  "type": "Feature",
  "properties": {
    "gn:admin1_code":"5",
    "gn:asciiname":"Cano Grande",
    "gn:country_code":"VE",
    "gn:dem":747,
    "gn:feature_class":"P",
    "gn:feature_code":"PPL",
    "gn:name":"Ca\u00f1o Grande",
    "gn:population":0,
    "gn:timezone":"America/Caracas",
    "iso:country":"VE",
    "wof:name":"Cano Grande",
    "wof:placetype":"locality"
},
  "geometry": {"coordinates":[-70.81739,8.43287],"type":"Point"}
}