{
  "type": "Feature",
  "properties": {
    "gn:admin1_code":"07",
    "gn:asciiname":"Sabanita",
    "gn:country_code":"VE",
    "gn:dem":477,
    "gn:feature_class":"P",
    "gn:feature_code":"PPL",
    "gn:name":"Sabanita",
    "gn:population":0,
    "gn:timezone":"America/Caracas",
    "iso:country":"VE",
    "wof:name":"Sabanita",
    "wof:placetype":"locality"
},
  "geometry": {"coordinates":[-68.76333000000001,9.96722],"type":"Point"}
}