{
  "type": "Feature",
  "properties": {
    "gn:admin1_code":"14",
    "gn:asciiname":"Las Uvas",
    "gn:country_code":"VE",
    "gn:dem":1214,
    "gn:feature_class":"P",
    "gn:feature_code":"PPL",
    "gn:name":"Las Uvas",
    "gn:population":0,
    "gn:timezone":"America/Caracas",
    "iso:country":"VE",
    "name:ita_x_preferred":[
        "Las Uvas"
    ],
    "name:spa_x_preferred":[
        "Las Uvas"
    ],
    "name:zho_x_preferred":[
        "\u62c9\u65af\u70cf\u74e6\u65af"
    ],
    "wof:name":"Las Uvas",
    "wof:placetype":"locality"
},
  "geometry": {"coordinates":[-71.50010999999998,8.53988],"type":"Point"}
}