{
  "type": "Feature",
  "properties": {
    "gn:admin1_code":"20",
    "gn:asciiname":"La Paragua",
    "gn:country_code":"VE",
    "gn:dem":248,
    "gn:feature_class":"P",
    "gn:feature_code":"PPLL",
    "gn:name":"La Paragua",
    "gn:population":0,
    "gn:timezone":"America/Caracas",
    "iso:country":"VE",
    "wof:name":"La Paragua",
    "wof:placetype":"locality"
},
  "geometry": {"coordinates":[-71.73572,7.70322],"type":"Point"}
}