{
  "type": "Feature",
  "properties": {
    "gn:admin1_code":"12",
    "gn:asciiname":"La Viuda",
    "gn:country_code":"VE",
    "gn:dem":119,
    "gn:feature_class":"P",
    "gn:feature_code":"PPL",
    "gn:name":"La Viuda",
    "gn:population":0,
    "gn:timezone":"America/Caracas",
    "iso:country":"VE",
    "wof:name":"La Viuda",
    "wof:placetype":"locality"
},
  "geometry": {"coordinates":[-66.54844,8.53906],"type":"Point"}
}