{
  "type": "Feature",
  "properties": {
    "gn:admin1_code":"9",
    "gn:asciiname":"Manoa",
    "gn:cc2":"VE",
    "gn:country_code":"VE",
    "gn:dem":36,
    "gn:feature_class":"P",
    "gn:feature_code":"PPL",
    "gn:name":"Manoa",
    "gn:population":0,
    "gn:timezone":"America/Caracas",
    "iso:country":"VE",
    "name:fra_x_preferred":[
        "M\u0101noa"
    ],
    "name:haw_x_preferred":[
        "M\u0101noa"
    ],
    "name:ilo_x_preferred":[
        "Manoa"
    ],
    "name:jpn_x_preferred":[
        "\u30de\u30ce\u30a2"
    ],
    "name:nor_x_preferred":[
        "Manoa"
    ],
    "name:por_x_preferred":[
        "Manoa"
    ],
    "name:und_x_variant":[
        "Imataca"
    ],
    "wof:name":"Manoa",
    "wof:placetype":"locality"
},
  "geometry": {"coordinates":[-61.33139,8.42056],"type":"Point"}
}