{
  "type": "Feature",
  "properties": {
    "gn:admin1_code":"11",
    "gn:asciiname":"Nepomuceno",
    "gn:country_code":"VE",
    "gn:dem":228,
    "gn:feature_class":"P",
    "gn:feature_code":"PPL",
    "gn:name":"Nepomuceno",
    "gn:population":0,
    "gn:timezone":"America/Caracas",
    "iso:country":"VE",
    "wof:name":"Nepomuceno",
    "wof:placetype":"locality"
},
  "geometry": {"coordinates":[-70.16922,11.02974],"type":"Point"}
}