{
  "type": "Feature",
  "properties": {
    "gn:admin1_code":"11",
    "gn:asciiname":"Nepomuceno",
    "gn:country_code":"VE",
    "gn:dem":228,
    "gn:feature_class":"P",
    "gn:feature_code":"PPL",
    "gn:name":"Nepomuceno",
    "gn:population":0,
    "gn:timezone":"America/Caracas",
    "iso:country":"VE",
    "name:bpy_x_preferred":[
        "\u09a8\u09c7\u09aa\u09cb\u09ae\u0989\u09b8\u09c7\u09a8\u09cb"
    ],
    "name:ceb_x_preferred":[
        "Nepomuceno"
    ],
    "name:deu_x_preferred":[
        "Nepomuceno"
    ],
    "name:epo_x_preferred":[
        "Nepomuceno"
    ],
    "name:eus_x_preferred":[
        "Nepomuceno"
    ],
    "name:fra_x_preferred":[
        "Nepomuceno"
    ],
    "name:ita_x_preferred":[
        "Nepomuceno"
    ],
    "name:kat_x_preferred":[
        "\u10dc\u10d4\u10de\u10dd\u10db\u10e3\u10e1\u10d4\u10dc\u10e3"
    ],
    "name:kaz_x_preferred":[
        "\u041d\u0435\u043f\u043e\u043c\u0443\u0441\u0435\u043d\u0443"
    ],
    "name:mlg_x_preferred":[
        "Nepomuceno"
    ],
    "name:nld_x_preferred":[
        "Nepomuceno"
    ],
    "name:nor_x_preferred":[
        "Nepomuceno"
    ],
    "name:pol_x_preferred":[
        "Nepomuceno"
    ],
    "name:por_x_preferred":[
        "Nepomuceno"
    ],
    "name:ron_x_preferred":[
        "Nepomuceno"
    ],
    "name:rus_x_preferred":[
        "\u041d\u0435\u043f\u043e\u043c\u0443\u0441\u0435\u043d\u0443"
    ],
    "name:swe_x_preferred":[
        "Nepomuceno"
    ],
    "name:vie_x_preferred":[
        "Nepomuceno"
    ],
    "name:vol_x_preferred":[
        "Nepomuceno"
    ],
    "name:war_x_preferred":[
        "Nepomuceno"
    ],
    "name:zho_x_preferred":[
        "\u5185\u6ce2\u7a46\u585e\u52aa"
    ],
    "wof:name":"Nepomuceno",
    "wof:placetype":"locality"
},
  "geometry": {"coordinates":[-70.16922,11.02974],"type":"Point"}
}