{
  "type": "Feature",
  "properties": {
    "gn:admin1_code":"6.0",
    "gn:asciiname":"Las Marias",
    "gn:country_code":"VE",
    "gn:dem":126,
    "gn:feature_class":"P",
    "gn:feature_code":"PPL",
    "gn:name":"Las Mar\u00edas",
    "gn:population":0,
    "gn:timezone":"America/Caracas",
    "iso:country":"VE",
    "wof:name":"Las Marias",
    "wof:placetype":"locality"
},
  "geometry": {"coordinates":[-63.75278,7.42778],"type":"Point"}
}