{
  "type": "Feature",
  "properties": {
    "gn:admin1_code":"5",
    "gn:asciiname":"Madre Vieja",
    "gn:country_code":"VE",
    "gn:dem":106,
    "gn:feature_class":"P",
    "gn:feature_code":"PPL",
    "gn:name":"Madre Vieja",
    "gn:population":0,
    "gn:timezone":"America/Caracas",
    "iso:country":"VE",
    "wof:name":"Madre Vieja",
    "wof:placetype":"locality"
},
  "geometry": {"coordinates":[-69.88333,8.21667],"type":"Point"}
}