{
  "type": "Feature",
  "properties": {
    "gn:admin1_code":"18.0",
    "gn:asciiname":"Poblado Tres",
    "gn:country_code":"VE",
    "gn:dem":88,
    "gn:feature_class":"P",
    "gn:feature_code":"PPL",
    "gn:name":"Poblado Tres",
    "gn:population":0,
    "gn:timezone":"America/Caracas",
    "iso:country":"VE",
    "name:spa_x_preferred":[
        "Poblado Tres"
    ],
    "wof:name":"Poblado Tres",
    "wof:placetype":"locality"
},
  "geometry": {"coordinates":[-68.89005999999999,9.05151],"type":"Point"}
}