{
  "type": "Feature",
  "properties": {
    "gn:admin1_code":"4.0",
    "gn:asciiname":"Casupo",
    "gn:country_code":"VE",
    "gn:dem":510,
    "gn:feature_class":"P",
    "gn:feature_code":"PPL",
    "gn:name":"Casupo",
    "gn:population":0,
    "gn:timezone":"America/Caracas",
    "iso:country":"VE",
    "wof:name":"Casupo",
    "wof:placetype":"locality"
},
  "geometry": {"coordinates":[-67.23444000000001,10.07667],"type":"Point"}
}