{
  "type": "Feature",
  "properties": {
    "gn:admin1_code":"18.0",
    "gn:asciiname":"El Ovallero",
    "gn:country_code":"VE",
    "gn:dem":131,
    "gn:feature_class":"P",
    "gn:feature_code":"PPLL",
    "gn:name":"El Ovallero",
    "gn:population":0,
    "gn:timezone":"America/Caracas",
    "iso:country":"VE",
    "name:spa_x_preferred":[
        "El Ovallero"
    ],
    "wof:name":"El Ovallero",
    "wof:placetype":"locality"
},
  "geometry": {"coordinates":[-69.52576999999999,9.17094],"type":"Point"}
}