{
  "type": "Feature",
  "properties": {
    "gn:admin1_code":"14",
    "gn:asciiname":"Mocao",
    "gn:country_code":"VE",
    "gn:dem":2821,
    "gn:feature_class":"P",
    "gn:feature_code":"PPL",
    "gn:name":"Mocao",
    "gn:population":0,
    "gn:timezone":"America/Caracas",
    "iso:country":"VE",
    "wof:name":"Mocao",
    "wof:placetype":"locality"
},
  "geometry": {"coordinates":[-70.92378000000002,8.74073],"type":"Point"}
}