{
  "type": "Feature",
  "properties": {
    "gn:admin1_code":"19",
    "gn:asciiname":"El Oculto",
    "gn:country_code":"VE",
    "gn:dem":25,
    "gn:feature_class":"P",
    "gn:feature_code":"PPL",
    "gn:name":"El Oculto",
    "gn:population":0,
    "gn:timezone":"America/Caracas",
    "iso:country":"VE",
    "wof:name":"El Oculto",
    "wof:placetype":"locality"
},
  "geometry": {"coordinates":[-64.37989,10.35449],"type":"Point"}
}