{
  "type": "Feature",
  "properties": {
    "gn:admin1_code":"02",
    "gn:asciiname":"Sacristan",
    "gn:country_code":"VE",
    "gn:dem":153,
    "gn:feature_class":"P",
    "gn:feature_code":"PPLL",
    "gn:name":"Sacristan",
    "gn:population":0,
    "gn:timezone":"America/Caracas",
    "iso:country":"VE",
    "name:cat_x_preferred":[
        "Sagrist\u00e0"
    ],
    "name:ces_x_preferred":[
        "Kosteln\u00edk"
    ],
    "name:deu_x_preferred":[
        "K\u00fcster"
    ],
    "name:epo_x_preferred":[
        "Sakristiisto"
    ],
    "name:est_x_preferred":[
        "K\u00f6ster"
    ],
    "name:eus_x_preferred":[
        "Sakristau"
    ],
    "name:fin_x_preferred":[
        "Suntio"
    ],
    "name:fra_x_preferred":[
        "Sacristain"
    ],
    "name:frr_x_preferred":[
        "K\u00f6ster"
    ],
    "name:glg_x_preferred":[
        "Sancrist\u00e1n"
    ],
    "name:ido_x_preferred":[
        "Sakristo"
    ],
    "name:ind_x_preferred":[
        "Koster"
    ],
    "name:ita_x_preferred":[
        "Sacrestano"
    ],
    "name:lat_x_preferred":[
        "Aedituus"
    ],
    "name:lit_x_preferred":[
        "Zakristijonas"
    ],
    "name:mal_x_preferred":[
        "\u0d15\u0d2a\u0d4d\u0d2f\u0d3e\u0d7c"
    ],
    "name:nld_x_preferred":[
        "Koster"
    ],
    "name:nor_x_preferred":[
        "Sakristan"
    ],
    "name:pol_x_preferred":[
        "Zakrystian"
    ],
    "name:por_x_preferred":[
        "Sacrist\u00e3o"
    ],
    "name:rue_x_preferred":[
        "\u041a\u043e\u0441\u0442\u0435\u043b\u043d\u0438\u043a"
    ],
    "name:rus_x_preferred":[
        "\u041a\u0438\u0441\u0442\u0435\u0440"
    ],
    "name:spa_x_preferred":[
        "Sacrist\u00e1n"
    ],
    "wof:name":"Sacristan",
    "wof:placetype":"locality"
},
  "geometry": {"coordinates":[-64.7847,8.37815],"type":"Point"}
}