{
  "type": "Feature",
  "properties": {
    "gn:admin1_code":"02",
    "gn:asciiname":"Sacristan",
    "gn:country_code":"VE",
    "gn:dem":153,
    "gn:feature_class":"P",
    "gn:feature_code":"PPLL",
    "gn:name":"Sacristan",
    "gn:population":0,
    "gn:timezone":"America/Caracas",
    "iso:country":"VE",
    "wof:name":"Sacristan",
    "wof:placetype":"locality"
},
  "geometry": {"coordinates":[-64.7847,8.37815],"type":"Point"}
}