{
  "type": "Feature",
  "properties": {
    "gn:admin1_code":"19.0",
    "gn:asciiname":"Putucual",
    "gn:country_code":"VE",
    "gn:dem":47,
    "gn:feature_class":"P",
    "gn:feature_code":"PPL",
    "gn:name":"Putucual",
    "gn:population":0,
    "gn:timezone":"America/Caracas",
    "iso:country":"VE",
    "wof:name":"Putucual",
    "wof:placetype":"locality"
},
  "geometry": {"coordinates":[-63.27415,10.39655],"type":"Point"}
}