{
  "type": "Feature",
  "properties": {
    "gn:admin1_code":"3.0",
    "gn:asciiname":"Canito de Mina",
    "gn:country_code":"VE",
    "gn:dem":52,
    "gn:feature_class":"P",
    "gn:feature_code":"PPL",
    "gn:name":"Ca\u00f1ito de Mina",
    "gn:population":0,
    "gn:timezone":"America/Caracas",
    "iso:country":"VE",
    "wof:name":"Canito de Mina",
    "wof:placetype":"locality"
},
  "geometry": {"coordinates":[-67.20475999999999,6.94659],"type":"Point"}
}