{
  "type": "Feature",
  "properties": {
    "gn:admin1_code":"16",
    "gn:asciiname":"Punta de Piedra",
    "gn:country_code":"VE",
    "gn:dem":58,
    "gn:feature_class":"P",
    "gn:feature_code":"PPL",
    "gn:name":"Punta de Piedra",
    "gn:population":0,
    "gn:timezone":"America/Caracas",
    "iso:country":"VE",
    "wof:name":"Punta de Piedra",
    "wof:placetype":"locality"
},
  "geometry": {"coordinates":[-63.07822,8.96472],"type":"Point"}
}