{
  "type": "Feature",
  "properties": {
    "gn:admin1_code":"6",
    "gn:asciiname":"Momuran",
    "gn:country_code":"VE",
    "gn:dem":468,
    "gn:feature_class":"P",
    "gn:feature_code":"PPL",
    "gn:name":"Momur\u00e1n",
    "gn:population":0,
    "gn:timezone":"America/Caracas",
    "iso:country":"VE",
    "wof:name":"Momuran",
    "wof:placetype":"locality"
},
  "geometry": {"coordinates":[-62.93333000000001,4.46667],"type":"Point"}
}