{
  "type": "Feature",
  "properties": {
    "iso:country":"VE",
    "name:ceb_x_preferred":[
        "Sanare"
    ],
    "name:swe_x_preferred":[
        "Sanare"
    ],
    "qs:gn_country":"VE",
    "qs:gn_fcode":"PPL",
    "qs:gn_pop":0,
    "qs:name":"Sanare",
    "qs:name_adm0":"Venezuela",
    "qs:name_adm1":"Lara",
    "qs:photos":44,
    "qs:photos_1k":9,
    "qs:photos_9k":1,
    "qs:photos_9r":2,
    "qs:photos_all":44,
    "qs:photos_sr":2,
    "qs:placetype":"Town",
    "qs:pop_sr":"0",
    "qs:woe_adm0":23424982,
    "wd:wordcount":9,
    "wof:name":"Sanare",
    "wof:placetype":"locality"
},
  "geometry": {"coordinates":[-68.81171999999999,10.10091],"type":"Point"}
}