{
  "type": "Feature",
  "properties": {
    "gn:admin1_code":"25",
    "gn:asciiname":"Puerto Escondido",
    "gn:country_code":"VE",
    "gn:dem":1019,
    "gn:feature_class":"P",
    "gn:feature_code":"PPL",
    "gn:name":"Puerto Escondido",
    "gn:population":0,
    "gn:timezone":"America/Caracas",
    "iso:country":"VE",
    "name:ara_x_preferred":[
        "\u0628\u0648\u064a\u0631\u062a\u0648 \u0623\u0634\u0643\u0646\u062f\u064a\u062f\u0648"
    ],
    "name:ceb_x_preferred":[
        "Puerto Escondido"
    ],
    "name:deu_x_preferred":[
        "Puerto Escondido"
    ],
    "name:ell_x_preferred":[
        "\u03a0\u03bf\u03c5\u03ad\u03c1\u03c4\u03bf \u0395\u03c3\u03ba\u03bf\u03bd\u03c4\u03af\u03b4\u03bf"
    ],
    "name:fas_x_preferred":[
        "\u06cc\u0648\u0626\u062a\u0631\u0648 \u0627\u0633\u06a9\u0648\u0646\u062f\u06cc\u062f\u0648"
    ],
    "name:fra_x_preferred":[
        "Puerto Escondido"
    ],
    "name:heb_x_preferred":[
        "\u05e4\u05d5\u05d0\u05e8\u05d8\u05d5 \u05e7\u05e1\u05e7\u05d5\u05e0\u05d3\u05d9\u05d3\u05d5"
    ],
    "name:hin_x_preferred":[
        "\u092a\u094d\u092f\u0942\u0930\u094d\u091f\u094b \u090f\u0938\u094d\u0915\u094b\u0902\u0921\u093f\u0921\u094b"
    ],
    "name:hun_x_preferred":[
        "Puerto Escondido"
    ],
    "name:ind_x_preferred":[
        "Puerto Escondido"
    ],
    "name:ita_x_preferred":[
        "Puerto Escondido"
    ],
    "name:nld_x_preferred":[
        "Puerto Escondido"
    ],
    "name:pol_x_preferred":[
        "Puerto Escondido"
    ],
    "name:rus_x_preferred":[
        "\u041f\u0443\u044d\u0440\u0442\u043e-\u042d\u0441\u043a\u043e\u043d\u0434\u0438\u0434\u043e"
    ],
    "name:sco_x_preferred":[
        "Puerto Escondido"
    ],
    "name:spa_x_preferred":[
        "Puerto Escondido"
    ],
    "name:swe_x_preferred":[
        "Puerto Escondido"
    ],
    "name:tur_x_preferred":[
        "Puerto Escondido"
    ],
    "name:ukr_x_preferred":[
        "\u041f\u0443\u0435\u0440\u0442\u043e-\u0415\u0441\u043a\u043e\u043d\u0434\u0456\u0434\u043e"
    ],
    "name:urd_x_preferred":[
        "\u067e\u0648\u0631\u062a\u0627 \u0627\u06cc\u0633\u06a9\u0648\u0646\u062f\u06cc\u062f\u0648"
    ],
    "name:vie_x_preferred":[
        "Puerto Escondido"
    ],
    "wof:name":"Puerto Escondido",
    "wof:placetype":"locality"
},
  "geometry": {"coordinates":[-66.91667,10.41667],"type":"Point"}
}