{
  "type": "Feature",
  "properties": {
    "gn:admin1_code":"7",
    "gn:asciiname":"La Sapera",
    "gn:country_code":"VE",
    "gn:dem":433,
    "gn:feature_class":"P",
    "gn:feature_code":"PPL",
    "gn:name":"La Sapera",
    "gn:population":0,
    "gn:timezone":"America/Caracas",
    "iso:country":"VE",
    "wof:name":"La Sapera",
    "wof:placetype":"locality"
},
  "geometry": {"coordinates":[-67.90504,10.07954],"type":"Point"}
}