{
  "type": "Feature",
  "properties": {
    "gn:admin1_code":"6",
    "gn:asciiname":"Juan Lorenzo",
    "gn:cc2":"VE",
    "gn:country_code":"VE",
    "gn:dem":68,
    "gn:feature_class":"P",
    "gn:feature_code":"PPL",
    "gn:name":"Juan Lorenzo",
    "gn:population":0,
    "gn:timezone":"America/Caracas",
    "iso:country":"VE",
    "name:und_x_variant":[
        "San Lorenzo",
        "Juan Lorenzo"
    ],
    "wof:name":"Juan Lorenzo",
    "wof:placetype":"locality"
},
  "geometry": {"coordinates":[-65.63333,7.65],"type":"Point"}
}