{
  "type": "Feature",
  "properties": {
    "gn:admin1_code":"13.0",
    "gn:asciiname":"El Hatico",
    "gn:country_code":"VE",
    "gn:dem":815,
    "gn:feature_class":"P",
    "gn:feature_code":"PPL",
    "gn:name":"El Hatico",
    "gn:population":0,
    "gn:timezone":"America/Caracas",
    "iso:country":"VE",
    "wof:name":"El Hatico",
    "wof:placetype":"locality"
},
  "geometry": {"coordinates":[-69.4744,10.17459],"type":"Point"}
}