{
  "type": "Feature",
  "properties": {
    "gn:admin1_code":"13",
    "gn:asciiname":"Puz",
    "gn:country_code":"VE",
    "gn:dem":486,
    "gn:feature_class":"P",
    "gn:feature_code":"PPL",
    "gn:name":"Puz",
    "gn:population":0,
    "gn:timezone":"America/Caracas",
    "iso:country":"VE",
    "wof:name":"Puz",
    "wof:placetype":"locality"
},
  "geometry": {"coordinates":[-69.80552,10.48416],"type":"Point"}
}