{
  "type": "Feature",
  "properties": {
    "gn:admin1_code":"14",
    "gn:asciiname":"Urbanizacion La Pedregosa",
    "gn:country_code":"VE",
    "gn:dem":1508,
    "gn:feature_class":"P",
    "gn:feature_code":"PPL",
    "gn:name":"Urbanizaci\u00f3n La Pedregosa",
    "gn:population":0,
    "gn:timezone":"America/Caracas",
    "iso:country":"VE",
    "wof:name":"Urbanizacion La Pedregosa",
    "wof:placetype":"locality"
},
  "geometry": {"coordinates":[-71.1875,8.58444],"type":"Point"}
}