{
  "type": "Feature",
  "properties": {
    "gn:admin1_code":"11",
    "gn:asciiname":"Viento Suave",
    "gn:country_code":"VE",
    "gn:dem":62,
    "gn:feature_class":"P",
    "gn:feature_code":"PPL",
    "gn:name":"Viento Suave",
    "gn:population":0,
    "gn:timezone":"America/Caracas",
    "iso:country":"VE",
    "wof:name":"Viento Suave",
    "wof:placetype":"locality"
},
  "geometry": {"coordinates":[-68.60534,11.26403],"type":"Point"}
}