{
  "type": "Feature",
  "properties": {
    "gn:admin1_code":"14.0",
    "gn:asciiname":"La Capellania",
    "gn:country_code":"VE",
    "gn:dem":2460,
    "gn:feature_class":"P",
    "gn:feature_code":"PPL",
    "gn:name":"La Capellania",
    "gn:population":0,
    "gn:timezone":"America/Caracas",
    "iso:country":"VE",
    "wof:name":"La Capellania",
    "wof:placetype":"locality"
},
  "geometry": {"coordinates":[-70.67716999999998,8.92377],"type":"Point"}
}