{
  "type": "Feature",
  "properties": {
    "gn:admin1_code":"18.0",
    "gn:asciiname":"El Cerro",
    "gn:country_code":"VE",
    "gn:dem":161,
    "gn:feature_class":"P",
    "gn:feature_code":"PPLL",
    "gn:name":"El Cerro",
    "gn:population":0,
    "gn:timezone":"America/Caracas",
    "iso:country":"VE",
    "name:spa_x_preferred":[
        "El Cerro"
    ],
    "wof:name":"El Cerro",
    "wof:placetype":"locality"
},
  "geometry": {"coordinates":[-69.71521,9.10193],"type":"Point"}
}