{
  "type": "Feature",
  "properties": {
    "gn:admin1_code":"12",
    "gn:asciiname":"Los Caros",
    "gn:country_code":"VE",
    "gn:dem":139,
    "gn:feature_class":"P",
    "gn:feature_code":"PPL",
    "gn:name":"Los Caros",
    "gn:population":0,
    "gn:timezone":"America/Caracas",
    "iso:country":"VE",
    "wof:name":"Los Caros",
    "wof:placetype":"locality"
},
  "geometry": {"coordinates":[-65.7072,8.81338],"type":"Point"}
}