{
  "type": "Feature",
  "properties": {
    "gn:admin1_code":"18.0",
    "gn:asciiname":"Negroncito",
    "gn:country_code":"VE",
    "gn:dem":121,
    "gn:feature_class":"P",
    "gn:feature_code":"PPL",
    "gn:name":"Negroncito",
    "gn:population":0,
    "gn:timezone":"America/Caracas",
    "iso:country":"VE",
    "name:spa_x_preferred":[
        "Negroncito"
    ],
    "wof:name":"Negroncito",
    "wof:placetype":"locality"
},
  "geometry": {"coordinates":[-69.17811,9.20572],"type":"Point"}
}