{
  "type": "Feature",
  "properties": {
    "gn:admin1_code":"19",
    "gn:asciiname":"La Rinconada",
    "gn:country_code":"VE",
    "gn:dem":55,
    "gn:feature_class":"P",
    "gn:feature_code":"PPL",
    "gn:name":"La Rinconada",
    "gn:population":0,
    "gn:timezone":"America/Caracas",
    "iso:country":"VE",
    "wof:name":"La Rinconada",
    "wof:placetype":"locality"
},
  "geometry": {"coordinates":[-63.17264,10.67593],"type":"Point"}
}