{
  "type": "Feature",
  "properties": {
    "gn:admin1_code":"15",
    "gn:asciiname":"Los Limoncitos",
    "gn:country_code":"VE",
    "gn:dem":985,
    "gn:feature_class":"P",
    "gn:feature_code":"PPL",
    "gn:name":"Los Limoncitos",
    "gn:population":0,
    "gn:timezone":"America/Caracas",
    "iso:country":"VE",
    "name:und_x_variant":[
        "El Limoncito",
        "Los Limoncitos"
    ],
    "wof:name":"Los Limoncitos",
    "wof:placetype":"locality"
},
  "geometry": {"coordinates":[-66.76175000000001,10.48246],"type":"Point"}
}