{
  "type": "Feature",
  "properties": {
    "gn:admin1_code":"11",
    "gn:asciiname":"Savino",
    "gn:country_code":"VE",
    "gn:dem":23,
    "gn:feature_class":"P",
    "gn:feature_code":"PPL",
    "gn:name":"Savino",
    "gn:population":0,
    "gn:timezone":"America/Caracas",
    "iso:country":"VE",
    "name:ceb_x_preferred":[
        "Savino"
    ],
    "name:deu_x_preferred":[
        "Savino"
    ],
    "name:ita_x_preferred":[
        "Savino"
    ],
    "name:pol_x_preferred":[
        "Savino"
    ],
    "wof:name":"Savino",
    "wof:placetype":"locality"
},
  "geometry": {"coordinates":[-70.16667,11.68333],"type":"Point"}
}