{
  "type": "Feature",
  "properties": {
    "gn:admin1_code":"13",
    "gn:asciiname":"Uveral",
    "gn:country_code":"VE",
    "gn:dem":685,
    "gn:feature_class":"P",
    "gn:feature_code":"PPL",
    "gn:name":"Uveral",
    "gn:population":0,
    "gn:timezone":"America/Caracas",
    "iso:country":"VE",
    "name:und_x_variant":[
        "Ubedal",
        "Uvedal",
        "Uberal",
        "Uveral"
    ],
    "wof:name":"Uveral",
    "wof:placetype":"locality"
},
  "geometry": {"coordinates":[-69.55816999999999,10.28435],"type":"Point"}
}