{
  "type": "Feature",
  "properties": {
    "gn:admin1_code":"22",
    "gn:admin2_code":"2201",
    "gn:asciiname":"San Pablo",
    "gn:country_code":"VE",
    "gn:dem":349,
    "gn:feature_class":"P",
    "gn:feature_code":"PPLA2",
    "gn:name":"San Pablo",
    "gn:population":0,
    "gn:timezone":"America/Caracas",
    "iso:country":"VE",
    "name:spa_x_preferred":[
        "San Pablo"
    ],
    "wof:name":"San Pablo",
    "wof:placetype":"locality"
},
  "geometry": {"coordinates":[-68.84451,10.24828],"type":"Point"}
}