{
  "type": "Feature",
  "properties": {
    "gn:admin1_code":"15",
    "gn:asciiname":"Velasquez",
    "gn:cc2":"VE",
    "gn:country_code":"VE",
    "gn:dem":23,
    "gn:feature_class":"P",
    "gn:feature_code":"PPL",
    "gn:name":"Vel\u00e1squez",
    "gn:population":0,
    "gn:timezone":"America/Caracas",
    "iso:country":"VE",
    "name:und_x_variant":[
        "Los Velazquez",
        "Vel\u00e1squez"
    ],
    "wof:name":"Velasquez",
    "wof:placetype":"locality"
},
  "geometry": {"coordinates":[-66.08806,10.3275],"type":"Point"}
}