{
  "type": "Feature",
  "properties": {
    "gn:admin1_code":"13",
    "gn:asciiname":"Canoitas",
    "gn:country_code":"VE",
    "gn:dem":734,
    "gn:feature_class":"P",
    "gn:feature_code":"PPL",
    "gn:name":"Cano\u00edtas",
    "gn:population":0,
    "gn:timezone":"America/Caracas",
    "iso:country":"VE",
    "wof:name":"Canoitas",
    "wof:placetype":"locality"
},
  "geometry": {"coordinates":[-69.59439999999999,10.09306],"type":"Point"}
}