{
  "type": "Feature",
  "properties": {
    "gn:admin1_code":"17",
    "gn:asciiname":"La Cruz del Pastel",
    "gn:country_code":"VE",
    "gn:dem":10,
    "gn:feature_class":"P",
    "gn:feature_code":"PPL",
    "gn:name":"La Cruz del Pastel",
    "gn:population":0,
    "gn:timezone":"America/Caracas",
    "iso:country":"VE",
    "wof:name":"La Cruz del Pastel",
    "wof:placetype":"locality"
},
  "geometry": {"coordinates":[-63.92493,10.94571],"type":"Point"}
}