{
  "type": "Feature",
  "properties": {
    "gn:admin1_code":"5",
    "gn:asciiname":"El Algarrobo",
    "gn:country_code":"VE",
    "gn:dem":182,
    "gn:feature_class":"P",
    "gn:feature_code":"PPL",
    "gn:name":"El Algarrobo",
    "gn:population":0,
    "gn:timezone":"America/Caracas",
    "iso:country":"VE",
    "name:und_x_variant":[
        "Algorrobo",
        "Algarrobo",
        "El Algarrobo"
    ],
    "wof:name":"El Algarrobo",
    "wof:placetype":"locality"
},
  "geometry": {"coordinates":[-70.11685,8.75865],"type":"Point"}
}