{
  "type": "Feature",
  "properties": {
    "gn:admin1_code":"21",
    "gn:asciiname":"Ocanto",
    "gn:country_code":"VE",
    "gn:dem":1242,
    "gn:feature_class":"P",
    "gn:feature_code":"PPL",
    "gn:name":"Ocanto",
    "gn:population":0,
    "gn:timezone":"America/Caracas",
    "iso:country":"VE",
    "wof:name":"Ocanto",
    "wof:placetype":"locality"
},
  "geometry": {"coordinates":[-70.4512,9.33865],"type":"Point"}
}