{
  "type": "Feature",
  "properties": {
    "gn:admin1_code":"3",
    "gn:asciiname":"La Rinconera",
    "gn:country_code":"VE",
    "gn:dem":59,
    "gn:feature_class":"P",
    "gn:feature_code":"PPL",
    "gn:name":"La Rinconera",
    "gn:population":0,
    "gn:timezone":"America/Caracas",
    "iso:country":"VE",
    "wof:name":"La Rinconera",
    "wof:placetype":"locality"
},
  "geometry": {"coordinates":[-68.08333,7.88333],"type":"Point"}
}