{
  "type": "Feature",
  "properties": {
    "gn:admin1_code":"23",
    "gn:asciiname":"Guayamurise",
    "gn:cc2":"VE",
    "gn:country_code":"VE",
    "gn:dem":3,
    "gn:feature_class":"P",
    "gn:feature_code":"PPL",
    "gn:name":"Guayamurise",
    "gn:population":0,
    "gn:timezone":"America/Caracas",
    "iso:country":"VE",
    "name:und_x_variant":[
        "Guayamri",
        "Guayamuriz",
        "Guayamurice",
        "Guayamurise"
    ],
    "wof:name":"Guayamurise",
    "wof:placetype":"locality"
},
  "geometry": {"coordinates":[-71.99250000000001,11.43556],"type":"Point"}
}