{
  "type": "Feature",
  "properties": {
    "gn:admin1_code":"3",
    "gn:asciiname":"El Dragal",
    "gn:country_code":"VE",
    "gn:dem":53,
    "gn:feature_class":"P",
    "gn:feature_code":"PPL",
    "gn:name":"El Dragal",
    "gn:population":0,
    "gn:timezone":"America/Caracas",
    "iso:country":"VE",
    "wof:name":"El Dragal",
    "wof:placetype":"locality"
},
  "geometry": {"coordinates":[-68.03333000000001,7.56667],"type":"Point"}
}