{
  "type": "Feature",
  "properties": {
    "gn:admin1_code":"23.0",
    "gn:asciiname":"Kilometro Cuarenta y uno",
    "gn:country_code":"VE",
    "gn:dem":46,
    "gn:feature_class":"P",
    "gn:feature_code":"PPL",
    "gn:name":"Kil\u00f3metro Cuarenta y uno",
    "gn:population":0,
    "gn:timezone":"America/Caracas",
    "iso:country":"VE",
    "wof:name":"Kilometro Cuarenta y uno",
    "wof:placetype":"locality"
},
  "geometry": {"coordinates":[-71.72759000000001,8.72567],"type":"Point"}
}