{
  "type": "Feature",
  "properties": {
    "gn:admin1_code":"7",
    "gn:asciiname":"La Haciendita",
    "gn:country_code":"VE",
    "gn:dem":445,
    "gn:feature_class":"P",
    "gn:feature_code":"PPL",
    "gn:name":"La Haciendita",
    "gn:population":0,
    "gn:timezone":"America/Caracas",
    "iso:country":"VE",
    "wof:name":"La Haciendita",
    "wof:placetype":"locality"
},
  "geometry": {"coordinates":[-67.71306,10.28639],"type":"Point"}
}