{
  "type": "Feature",
  "properties": {
    "gn:admin1_code":"3",
    "gn:asciiname":"La Enea",
    "gn:cc2":"VE",
    "gn:country_code":"VE",
    "gn:dem":52,
    "gn:feature_class":"P",
    "gn:feature_code":"PPL",
    "gn:name":"La Enea",
    "gn:population":0,
    "gn:timezone":"America/Caracas",
    "iso:country":"VE",
    "name:ita_x_preferred":[
        "La Enea"
    ],
    "name:spa_x_preferred":[
        "La Enea"
    ],
    "name:und_x_variant":[
        "La Linea",
        "La Enea"
    ],
    "name:zho_x_preferred":[
        "\u62c9\u57c3\u5167\u963f"
    ],
    "wof:name":"La Enea",
    "wof:placetype":"locality"
},
  "geometry": {"coordinates":[-67.58333,7.81667],"type":"Point"}
}