{
  "type": "Feature",
  "properties": {
    "gn:admin1_code":"13",
    "gn:asciiname":"La Cruz del Padre",
    "gn:country_code":"VE",
    "gn:dem":963,
    "gn:feature_class":"P",
    "gn:feature_code":"PPL",
    "gn:name":"La Cruz del Padre",
    "gn:population":0,
    "gn:timezone":"America/Caracas",
    "iso:country":"VE",
    "wof:name":"La Cruz del Padre",
    "wof:placetype":"locality"
},
  "geometry": {"coordinates":[-69.77079999999999,9.66591],"type":"Point"}
}