{
  "type": "Feature",
  "properties": {
    "gn:admin1_code":"1",
    "gn:asciiname":"Laja Lopez",
    "gn:country_code":"VE",
    "gn:dem":85,
    "gn:feature_class":"P",
    "gn:feature_code":"PPL",
    "gn:name":"Laja L\u00f3pez",
    "gn:population":0,
    "gn:timezone":"America/Caracas",
    "iso:country":"VE",
    "wof:name":"Laja Lopez",
    "wof:placetype":"locality"
},
  "geometry": {"coordinates":[-67.39778000000001,3.12917],"type":"Point"}
}