{
  "type": "Feature",
  "properties": {
    "gn:admin1_code":"11.0",
    "gn:asciiname":"Chirino",
    "gn:country_code":"VE",
    "gn:dem":9,
    "gn:feature_class":"P",
    "gn:feature_code":"PPLL",
    "gn:name":"Chirino",
    "gn:population":0,
    "gn:timezone":"America/Caracas",
    "iso:country":"VE",
    "wof:name":"Chirino",
    "wof:placetype":"locality"
},
  "geometry": {"coordinates":[-71.12631999999998,10.92525],"type":"Point"}
}