{
  "type": "Feature",
  "properties": {
    "gn:admin1_code":"23",
    "gn:asciiname":"Agua Santa",
    "gn:country_code":"VE",
    "gn:dem":142,
    "gn:feature_class":"P",
    "gn:feature_code":"PPL",
    "gn:name":"Agua Santa",
    "gn:population":0,
    "gn:timezone":"America/Caracas",
    "iso:country":"VE",
    "wof:name":"Agua Santa",
    "wof:placetype":"locality"
},
  "geometry": {"coordinates":[-71.12765999999998,10.40886],"type":"Point"}
}