{
  "type": "Feature",
  "properties": {
    "gn:admin1_code":"15",
    "gn:asciiname":"Mampote",
    "gn:country_code":"VE",
    "gn:dem":489,
    "gn:feature_class":"P",
    "gn:feature_code":"PPL",
    "gn:name":"Mampote",
    "gn:population":0,
    "gn:timezone":"America/Caracas",
    "iso:country":"VE",
    "wof:name":"Mampote",
    "wof:placetype":"locality"
},
  "geometry": {"coordinates":[-66.67385999999999,10.47618],"type":"Point"}
}