{
  "type": "Feature",
  "properties": {
    "gn:admin1_code":"14",
    "gn:asciiname":"La Rancheria",
    "gn:country_code":"VE",
    "gn:dem":1206,
    "gn:feature_class":"P",
    "gn:feature_code":"PPL",
    "gn:name":"La Rancher\u00eda",
    "gn:population":0,
    "gn:timezone":"America/Caracas",
    "iso:country":"VE",
    "name:und_x_variant":[
        "La Ranchera",
        "La Rancher\u00eda"
    ],
    "wof:name":"La Rancheria",
    "wof:placetype":"locality"
},
  "geometry": {"coordinates":[-71.27334999999999,8.54292],"type":"Point"}
}