{
  "type": "Feature",
  "properties": {
    "gn:admin1_code":"12",
    "gn:asciiname":"Pozo Claro",
    "gn:country_code":"VE",
    "gn:dem":380,
    "gn:feature_class":"P",
    "gn:feature_code":"PPL",
    "gn:name":"Pozo Claro",
    "gn:population":0,
    "gn:timezone":"America/Caracas",
    "iso:country":"VE",
    "wof:name":"Pozo Claro",
    "wof:placetype":"locality"
},
  "geometry": {"coordinates":[-66.29048,9.88005],"type":"Point"}
}