{
  "type": "Feature",
  "properties": {
    "gn:admin1_code":"11.0",
    "gn:asciiname":"Ventura",
    "gn:country_code":"VE",
    "gn:dem":171,
    "gn:feature_class":"P",
    "gn:feature_code":"PPLL",
    "gn:name":"Ventura",
    "gn:population":0,
    "gn:timezone":"America/Caracas",
    "iso:country":"VE",
    "name:bul_x_preferred":[
        "\u0412\u0435\u043d\u0442\u0443\u0440\u0430"
    ],
    "name:cat_x_preferred":[
        "Ventura"
    ],
    "name:ceb_x_preferred":[
        "Ventura"
    ],
    "name:ces_x_preferred":[
        "Ventura"
    ],
    "name:deu_x_preferred":[
        "Ventura"
    ],
    "name:est_x_preferred":[
        "Ventura"
    ],
    "name:fas_x_preferred":[
        "\u0648\u0646\u062a\u0648\u0631\u0627"
    ],
    "name:fra_x_preferred":[
        "Ventura"
    ],
    "name:heb_x_preferred":[
        "\u05d5\u05e0\u05d8\u05d5\u05e8\u05d4"
    ],
    "name:ita_x_preferred":[
        "Ventura"
    ],
    "name:jpn_x_preferred":[
        "\u30d9\u30f3\u30c1\u30e5\u30e9"
    ],
    "name:kor_x_preferred":[
        "\ubca4\ud22c\ub77c"
    ],
    "name:nld_x_preferred":[
        "Ventura"
    ],
    "name:pol_x_preferred":[
        "Ventura"
    ],
    "name:por_x_preferred":[
        "Ventura"
    ],
    "name:rus_x_preferred":[
        "\u0412\u0435\u043d\u0442\u0443\u0440\u0430"
    ],
    "name:scn_x_preferred":[
        "Vintura"
    ],
    "name:spa_x_preferred":[
        "Ventura"
    ],
    "name:srp_x_preferred":[
        "\u0412\u0435\u043d\u0442\u0443\u0440\u0430"
    ],
    "name:swe_x_preferred":[
        "Ventura"
    ],
    "name:tur_x_preferred":[
        "Ventura"
    ],
    "name:ukr_x_preferred":[
        "\u0412\u0435\u043d\u0442\u0443\u0440\u0430"
    ],
    "name:vol_x_preferred":[
        "Ventura"
    ],
    "name:zho_x_preferred":[
        "\u6587\u5716\u62c9"
    ],
    "wof:name":"Ventura",
    "wof:placetype":"locality"
},
  "geometry": {"coordinates":[-70.68132,10.86374],"type":"Point"}
}