{
  "type": "Feature",
  "properties": {
    "gn:admin1_code":"11.0",
    "gn:asciiname":"Ventura",
    "gn:country_code":"VE",
    "gn:dem":171,
    "gn:feature_class":"P",
    "gn:feature_code":"PPLL",
    "gn:name":"Ventura",
    "gn:population":0,
    "gn:timezone":"America/Caracas",
    "iso:country":"VE",
    "wof:name":"Ventura",
    "wof:placetype":"locality"
},
  "geometry": {"coordinates":[-70.68132,10.86374],"type":"Point"}
}