{
  "type": "Feature",
  "properties": {
    "gn:admin1_code":"23",
    "gn:asciiname":"El Sur",
    "gn:country_code":"VE",
    "gn:dem":58,
    "gn:feature_class":"P",
    "gn:feature_code":"PPL",
    "gn:name":"El Sur",
    "gn:population":0,
    "gn:timezone":"America/Caracas",
    "iso:country":"VE",
    "wof:name":"El Sur",
    "wof:placetype":"locality"
},
  "geometry": {"coordinates":[-72.15000000000001,10.76667],"type":"Point"}
}