{
  "type": "Feature",
  "properties": {
    "gn:admin1_code":"14",
    "gn:asciiname":"Chorros de Milla",
    "gn:country_code":"VE",
    "gn:dem":1812,
    "gn:feature_class":"P",
    "gn:feature_code":"PPL",
    "gn:name":"Chorros de Milla",
    "gn:population":0,
    "gn:timezone":"America/Caracas",
    "iso:country":"VE",
    "wof:name":"Chorros de Milla",
    "wof:placetype":"locality"
},
  "geometry": {"coordinates":[-71.14416999999997,8.62875],"type":"Point"}
}