{
  "type": "Feature",
  "properties": {
    "gn:admin1_code":"1",
    "gn:asciiname":"Aratana",
    "gn:cc2":"VE",
    "gn:country_code":"VE",
    "gn:dem":595,
    "gn:feature_class":"P",
    "gn:feature_code":"PPL",
    "gn:name":"Arata\u00f1a",
    "gn:population":0,
    "gn:timezone":"America/Caracas",
    "iso:country":"VE",
    "name:und_x_variant":[
        "Arauta\u00f1a",
        "Arata\u00f1a"
    ],
    "wof:name":"Aratana",
    "wof:placetype":"locality"
},
  "geometry": {"coordinates":[-64.93333,4.48333],"type":"Point"}
}