{
  "type": "Feature",
  "properties": {
    "gn:admin1_code":"21",
    "gn:asciiname":"El Amarillo",
    "gn:country_code":"VE",
    "gn:dem":1136,
    "gn:feature_class":"P",
    "gn:feature_code":"PPL",
    "gn:name":"El Amarillo",
    "gn:population":0,
    "gn:timezone":"America/Caracas",
    "iso:country":"VE",
    "wof:name":"El Amarillo",
    "wof:placetype":"locality"
},
  "geometry": {"coordinates":[-70.52167,9.325],"type":"Point"}
}