{
  "type": "Feature",
  "properties": {
    "gn:admin1_code":"22",
    "gn:asciiname":"Las Vegas",
    "gn:country_code":"VE",
    "gn:dem":424,
    "gn:feature_class":"P",
    "gn:feature_code":"PPL",
    "gn:name":"Las Vegas",
    "gn:population":0,
    "gn:timezone":"America/Caracas",
    "iso:country":"VE",
    "wof:name":"Las Vegas",
    "wof:placetype":"locality"
},
  "geometry": {"coordinates":[-68.44131999999999,10.23785],"type":"Point"}
}