{
  "type": "Feature",
  "properties": {
    "gn:admin1_code":"9",
    "gn:asciiname":"Puchima",
    "gn:cc2":"VE",
    "gn:country_code":"VE",
    "gn:dem":317,
    "gn:feature_class":"P",
    "gn:feature_code":"PPL",
    "gn:name":"Puchima",
    "gn:population":0,
    "gn:timezone":"America/Caracas",
    "iso:country":"VE",
    "name:und_x_variant":[
        "Puchima Arriba",
        "Puchima"
    ],
    "wof:name":"Puchima",
    "wof:placetype":"locality"
},
  "geometry": {"coordinates":[-61.88333000000001,8.01667],"type":"Point"}
}