{
  "type": "Feature",
  "properties": {
    "gn:admin1_code":"05",
    "gn:asciiname":"El Bongo",
    "gn:country_code":"VE",
    "gn:dem":88,
    "gn:feature_class":"P",
    "gn:feature_code":"PPL",
    "gn:name":"El Bongo",
    "gn:population":0,
    "gn:timezone":"America/Caracas",
    "iso:country":"VE",
    "name:ita_x_preferred":[
        "El Bongo"
    ],
    "name:spa_x_preferred":[
        "El Bongo"
    ],
    "name:zho_x_preferred":[
        "\u57c3\u5c14\u90a6\u6208"
    ],
    "wof:name":"El Bongo",
    "wof:placetype":"locality"
},
  "geometry": {"coordinates":[-69.27294000000001,8.15193],"type":"Point"}
}