{
  "type": "Feature",
  "properties": {
    "gn:admin1_code":"19.0",
    "gn:asciiname":"Cumbre de Manacal",
    "gn:country_code":"VE",
    "gn:dem":541,
    "gn:feature_class":"P",
    "gn:feature_code":"PPL",
    "gn:name":"Cumbre de Manacal",
    "gn:population":0,
    "gn:timezone":"America/Caracas",
    "iso:country":"VE",
    "wof:name":"Cumbre de Manacal",
    "wof:placetype":"locality"
},
  "geometry": {"coordinates":[-63.05114,10.60319],"type":"Point"}
}