{
  "type": "Feature",
  "properties": {
    "gn:admin1_code":"23",
    "gn:asciiname":"Tio Pancho",
    "gn:cc2":"VE",
    "gn:country_code":"VE",
    "gn:dem":-9999,
    "gn:feature_class":"P",
    "gn:feature_code":"PPL",
    "gn:name":"T\u00edo Pancho",
    "gn:population":0,
    "gn:timezone":"America/Caracas",
    "iso:country":"VE",
    "name:und_x_variant":[
        "Tio Pacho",
        "T\u00edo Pancho"
    ],
    "wof:name":"Tio Pancho",
    "wof:placetype":"locality"
},
  "geometry": {"coordinates":[-72.03333000000001,9.95],"type":"Point"}
}