{
  "type": "Feature",
  "properties": {
    "gn:admin1_code":"1",
    "gn:asciiname":"Guapachana",
    "gn:country_code":"VE",
    "gn:dem":102,
    "gn:feature_class":"P",
    "gn:feature_code":"PPL",
    "gn:name":"Guapachana",
    "gn:population":0,
    "gn:timezone":"America/Caracas",
    "iso:country":"VE",
    "name:und_x_variant":[
        "Sitio Guachapana",
        "Guachapana",
        "Guapachana"
    ],
    "wof:name":"Guapachana",
    "wof:placetype":"locality"
},
  "geometry": {"coordinates":[-67.02632,3.87967],"type":"Point"}
}