{
  "type": "Feature",
  "properties": {
    "gn:admin1_code":"6.0",
    "gn:asciiname":"Yauno Viejo",
    "gn:country_code":"VE",
    "gn:dem":236,
    "gn:feature_class":"P",
    "gn:feature_code":"PPL",
    "gn:name":"Yauno Viejo",
    "gn:population":0,
    "gn:timezone":"America/Caracas",
    "iso:country":"VE",
    "wof:name":"Yauno Viejo",
    "wof:placetype":"locality"
},
  "geometry": {"coordinates":[-63.33611,7.51944],"type":"Point"}
}