{
  "type": "Feature",
  "properties": {
    "gn:admin1_code":"12",
    "gn:asciiname":"La Bonanza",
    "gn:country_code":"VE",
    "gn:dem":103,
    "gn:feature_class":"P",
    "gn:feature_code":"PPL",
    "gn:name":"La Bonanza",
    "gn:population":0,
    "gn:timezone":"America/Caracas",
    "iso:country":"VE",
    "wof:name":"La Bonanza",
    "wof:placetype":"locality"
},
  "geometry": {"coordinates":[-65.27079999999999,9.20011],"type":"Point"}
}