{
  "type": "Feature",
  "properties": {
    "iso:country":"VE",
    "name:eng_x_colloquial":[
        "Choroni"
    ],
    "name:eng_x_preferred":[
        "Choroni"
    ],
    "name:eng_x_variant":[
        "Choron\u00ed"
    ],
    "name:fra_x_preferred":[
        "Choron\u00ed"
    ],
    "name:nld_x_preferred":[
        "Choron\u00ed"
    ],
    "name:por_x_preferred":[
        "Choron\u00ed"
    ],
    "name:spa_x_colloquial":[
        "Choroni"
    ],
    "name:spa_x_preferred":[
        "Parroquia Choron\u00ed"
    ],
    "name:spa_x_variant":[
        "Choroni"
    ],
    "qs:gn_country":"VE",
    "qs:gn_fcode":"PPL",
    "qs:gn_pop":0,
    "qs:name":"Choron\u00ed",
    "qs:name_adm0":"Venezuela",
    "qs:name_adm1":"Aragua",
    "qs:photos":223,
    "qs:photos_1k":45,
    "qs:photos_9k":1,
    "qs:photos_9r":4,
    "qs:photos_all":223,
    "qs:photos_sr":4,
    "qs:placetype":"Town",
    "qs:pop_sr":"0",
    "qs:woe_adm0":23424982,
    "wd:wordcount":105,
    "wof:name":"Choron\u00ed",
    "wof:placetype":"locality"
},
  "geometry": {"coordinates":[-67.60971000000001,10.492],"type":"Point"}
}