{
  "type": "Feature",
  "properties": {
    "gn:admin1_code":"16",
    "gn:asciiname":"Macanillal",
    "gn:country_code":"VE",
    "gn:dem":528,
    "gn:feature_class":"P",
    "gn:feature_code":"PPL",
    "gn:name":"Macanillal",
    "gn:population":0,
    "gn:timezone":"America/Caracas",
    "iso:country":"VE",
    "wof:name":"Macanillal",
    "wof:placetype":"locality"
},
  "geometry": {"coordinates":[-63.41672,10.05273],"type":"Point"}
}