{
  "type": "Feature",
  "properties": {
    "gn:admin1_code":"3",
    "gn:asciiname":"El Pesquero",
    "gn:cc2":"VE",
    "gn:country_code":"VE",
    "gn:dem":51,
    "gn:feature_class":"P",
    "gn:feature_code":"PPL",
    "gn:name":"El Pesquero",
    "gn:population":0,
    "gn:timezone":"America/Caracas",
    "iso:country":"VE",
    "name:und_x_variant":[
        "El Pesquera",
        "El Pesquero"
    ],
    "wof:name":"El Pesquero",
    "wof:placetype":"locality"
},
  "geometry": {"coordinates":[-67.21666999999999,6.58333],"type":"Point"}
}