{
  "type": "Feature",
  "properties": {
    "gn:admin1_code":"5",
    "gn:asciiname":"La Ururita",
    "gn:country_code":"VE",
    "gn:dem":160,
    "gn:feature_class":"P",
    "gn:feature_code":"PPL",
    "gn:name":"La Ururita",
    "gn:population":0,
    "gn:timezone":"America/Caracas",
    "iso:country":"VE",
    "wof:name":"La Ururita",
    "wof:placetype":"locality"
},
  "geometry": {"coordinates":[-70.21576999999999,8.50361],"type":"Point"}
}