{
  "type": "Feature",
  "properties": {
    "gn:admin1_code":"2",
    "gn:asciiname":"Mata Sola",
    "gn:country_code":"VE",
    "gn:dem":3,
    "gn:feature_class":"P",
    "gn:feature_code":"PPL",
    "gn:name":"Mata Sola",
    "gn:population":0,
    "gn:timezone":"America/Caracas",
    "iso:country":"VE",
    "wof:name":"Mata Sola",
    "wof:placetype":"locality"
},
  "geometry": {"coordinates":[-65.33235999999999,10.11632],"type":"Point"}
}