{
  "type": "Feature",
  "properties": {
    "gn:admin1_code":"11.0",
    "gn:asciiname":"La Campana",
    "gn:country_code":"VE",
    "gn:dem":597,
    "gn:feature_class":"P",
    "gn:feature_code":"PPL",
    "gn:name":"La Campana",
    "gn:population":0,
    "gn:timezone":"America/Caracas",
    "iso:country":"VE",
    "wof:name":"La Campana",
    "wof:placetype":"locality"
},
  "geometry": {"coordinates":[-70.35051,10.82265],"type":"Point"}
}