{
  "type": "Feature",
  "properties": {
    "iso:country":"VE",
    "name:spa_x_preferred":[
        "El Tunal"
    ],
    "qs:gn_country":"VE",
    "qs:gn_fcode":"PPL",
    "qs:gn_pop":0,
    "qs:name":"El Tunal",
    "qs:name_adm0":"Venezuela",
    "qs:name_adm1":"Nueva Esparta",
    "qs:photos":30,
    "qs:photos_1k":6,
    "qs:photos_9k":1,
    "qs:photos_9r":2,
    "qs:photos_all":30,
    "qs:photos_sr":2,
    "qs:placetype":"Town",
    "qs:pop_sr":"5",
    "qs:woe_adm0":23424982,
    "wd:wordcount":35,
    "wof:name":"El Tunal",
    "wof:placetype":"locality"
},
  "geometry": {"coordinates":[-64.29552,11.06878],"type":"Point"}
}