{
  "type": "Feature",
  "properties": {
    "gn:admin1_code":"19.0",
    "gn:asciiname":"Tacarigua",
    "gn:country_code":"VE",
    "gn:dem":68,
    "gn:feature_class":"P",
    "gn:feature_code":"PPL",
    "gn:name":"Tacarigua",
    "gn:population":0,
    "gn:timezone":"America/Caracas",
    "iso:country":"VE",
    "name:deu_x_preferred":[
        "Tacarigua"
    ],
    "name:fas_x_preferred":[
        "\u062a\u0627\u06a9\u0627\u0631\u06cc\u06af\u0648\u0622"
    ],
    "wof:name":"Tacarigua",
    "wof:placetype":"locality"
},
  "geometry": {"coordinates":[-63.14453,10.47375],"type":"Point"}
}