{
  "type": "Feature",
  "properties": {
    "gn:admin1_code":"23.0",
    "gn:asciiname":"Santa Rosa",
    "gn:country_code":"VE",
    "gn:dem":73,
    "gn:feature_class":"P",
    "gn:feature_code":"PPLL",
    "gn:name":"Santa Rosa",
    "gn:population":0,
    "gn:timezone":"America/Caracas",
    "iso:country":"VE",
    "wof:name":"Santa Rosa",
    "wof:placetype":"locality"
},
  "geometry": {"coordinates":[-71.89234,10.70818],"type":"Point"}
}