{
  "type": "Feature",
  "properties": {
    "gn:admin1_code":"6",
    "gn:asciiname":"Bons",
    "gn:country_code":"VE",
    "gn:dem":143,
    "gn:feature_class":"P",
    "gn:feature_code":"PPL",
    "gn:name":"Bons",
    "gn:population":0,
    "gn:timezone":"America/Caracas",
    "iso:country":"VE",
    "wof:name":"Bons",
    "wof:placetype":"locality"
},
  "geometry": {"coordinates":[-61.75,6.78333],"type":"Point"}
}