{
  "type": "Feature",
  "properties": {
    "gn:admin1_code":"23",
    "gn:asciiname":"Kilometro Trece",
    "gn:country_code":"VE",
    "gn:dem":64,
    "gn:feature_class":"P",
    "gn:feature_code":"PPL",
    "gn:name":"Kil\u00f3metro Trece",
    "gn:population":0,
    "gn:timezone":"America/Caracas",
    "iso:country":"VE",
    "name:und_x_variant":[
        "Kil\u00f3metro 13",
        "Kil\u00f3metro Trece"
    ],
    "wof:name":"Kilometro Trece",
    "wof:placetype":"locality"
},
  "geometry": {"coordinates":[-71.33743,10.38369],"type":"Point"}
}