{
  "type": "Feature",
  "properties": {
    "iso:country":"VE",
    "name:unk_x_variant":[
        "Puerto Ocumare"
    ],
    "qs:gn_country":"VE",
    "qs:gn_fcode":"PPL",
    "qs:gn_pop":0,
    "qs:name":"Puerto de Ocumare",
    "qs:name_adm0":"Venezuela",
    "qs:name_adm1":"Aragua",
    "qs:photos":36,
    "qs:photos_1k":7,
    "qs:photos_9k":1,
    "qs:photos_9r":2,
    "qs:photos_all":36,
    "qs:photos_sr":2,
    "qs:placetype":"Town",
    "qs:pop_sr":"0",
    "qs:woe_adm0":23424982,
    "wof:name":"Puerto de Ocumare",
    "wof:placetype":"locality"
},
  "geometry": {"coordinates":[-67.76667,10.48333],"type":"Point"}
}