{
  "type": "Feature",
  "properties": {
    "gn:admin1_code":"23.0",
    "gn:asciiname":"La Guacharaca",
    "gn:country_code":"VE",
    "gn:dem":41,
    "gn:feature_class":"P",
    "gn:feature_code":"PPLL",
    "gn:name":"La Guacharaca",
    "gn:population":0,
    "gn:timezone":"America/Caracas",
    "iso:country":"VE",
    "wof:name":"La Guacharaca",
    "wof:placetype":"locality"
},
  "geometry": {"coordinates":[-71.49023000000003,10.66883],"type":"Point"}
}