{
  "type": "Feature",
  "properties": {
    "gn:admin1_code":"13",
    "gn:asciiname":"La Mejor",
    "gn:country_code":"VE",
    "gn:dem":686,
    "gn:feature_class":"P",
    "gn:feature_code":"PPL",
    "gn:name":"La Mejor",
    "gn:population":0,
    "gn:timezone":"America/Caracas",
    "iso:country":"VE",
    "wof:name":"La Mejor",
    "wof:placetype":"locality"
},
  "geometry": {"coordinates":[-69.80019,9.72525],"type":"Point"}
}