{
  "type": "Feature",
  "properties": {
    "gn:admin1_code":"21",
    "gn:asciiname":"Mesa Adentro",
    "gn:country_code":"VE",
    "gn:dem":1987,
    "gn:feature_class":"P",
    "gn:feature_code":"PPL",
    "gn:name":"Mesa Adentro",
    "gn:population":0,
    "gn:timezone":"America/Caracas",
    "iso:country":"VE",
    "wof:name":"Mesa Adentro",
    "wof:placetype":"locality"
},
  "geometry": {"coordinates":[-70.2458,9.43361],"type":"Point"}
}