{
  "type": "Feature",
  "properties": {
    "gn:admin1_code":"11.0",
    "gn:asciiname":"Cayo Los Muertos",
    "gn:country_code":"VE",
    "gn:dem":-9999,
    "gn:feature_class":"P",
    "gn:feature_code":"PPL",
    "gn:name":"Cayo Los Muertos",
    "gn:population":0,
    "gn:timezone":"America/Caracas",
    "iso:country":"VE",
    "wof:name":"Cayo Los Muertos",
    "wof:placetype":"locality"
},
  "geometry": {"coordinates":[-68.25610999999999,10.93],"type":"Point"}
}