{
  "type": "Feature",
  "properties": {
    "gn:admin1_code":"13.0",
    "gn:asciiname":"Cuatro Esquinas",
    "gn:country_code":"VE",
    "gn:dem":1183,
    "gn:feature_class":"P",
    "gn:feature_code":"PPL",
    "gn:name":"Cuatro Esquinas",
    "gn:population":0,
    "gn:timezone":"America/Caracas",
    "iso:country":"VE",
    "wof:name":"Cuatro Esquinas",
    "wof:placetype":"locality"
},
  "geometry": {"coordinates":[-69.55500000000001,9.82722],"type":"Point"}
}