{
  "type": "Feature",
  "properties": {
    "gn:admin1_code":"23",
    "gn:asciiname":"Zarrupiai",
    "gn:country_code":"VE",
    "gn:dem":21,
    "gn:feature_class":"P",
    "gn:feature_code":"PPL",
    "gn:name":"Zarrupiai",
    "gn:population":0,
    "gn:timezone":"America/Caracas",
    "iso:country":"VE",
    "wof:name":"Zarrupiai",
    "wof:placetype":"locality"
},
  "geometry": {"coordinates":[-71.63355,11.73711],"type":"Point"}
}