{
  "type": "Feature",
  "properties": {
    "gn:admin1_code":"19",
    "gn:asciiname":"El Gavilan",
    "gn:country_code":"VE",
    "gn:dem":364,
    "gn:feature_class":"P",
    "gn:feature_code":"PPL",
    "gn:name":"El Gavilan",
    "gn:population":0,
    "gn:timezone":"America/Caracas",
    "iso:country":"VE",
    "wof:name":"El Gavilan",
    "wof:placetype":"locality"
},
  "geometry": {"coordinates":[-63.13454,10.66733],"type":"Point"}
}