{
  "type": "Feature",
  "properties": {
    "gn:admin1_code":"7",
    "gn:asciiname":"La Juajuita",
    "gn:country_code":"VE",
    "gn:dem":624,
    "gn:feature_class":"P",
    "gn:feature_code":"PPL",
    "gn:name":"La Juajuita",
    "gn:population":0,
    "gn:timezone":"America/Caracas",
    "iso:country":"VE",
    "wof:name":"La Juajuita",
    "wof:placetype":"locality"
},
  "geometry": {"coordinates":[-67.64668,9.91754],"type":"Point"}
}