{
  "type": "Feature",
  "properties": {
    "gn:admin1_code":"7",
    "gn:asciiname":"Rio Abajo",
    "gn:country_code":"VE",
    "gn:dem":614,
    "gn:feature_class":"P",
    "gn:feature_code":"PPL",
    "gn:name":"R\u00edo Abajo",
    "gn:population":0,
    "gn:timezone":"America/Caracas",
    "iso:country":"VE",
    "wof:name":"Rio Abajo",
    "wof:placetype":"locality"
},
  "geometry": {"coordinates":[-67.93813,9.96952],"type":"Point"}
}