{
  "type": "Feature",
  "properties": {
    "gn:admin1_code":"13",
    "gn:asciiname":"Los Valles de Maria",
    "gn:country_code":"VE",
    "gn:dem":964,
    "gn:feature_class":"P",
    "gn:feature_code":"PPL",
    "gn:name":"Los Valles de Mar\u00eda",
    "gn:population":0,
    "gn:timezone":"America/Caracas",
    "iso:country":"VE",
    "wof:name":"Los Valles de Maria",
    "wof:placetype":"locality"
},
  "geometry": {"coordinates":[-70.6151,10.22711],"type":"Point"}
}