{
  "type": "Feature",
  "properties": {
    "gn:admin1_code":"19",
    "gn:asciiname":"La Placeta",
    "gn:country_code":"VE",
    "gn:dem":475,
    "gn:feature_class":"P",
    "gn:feature_code":"PPL",
    "gn:name":"La Placeta",
    "gn:population":0,
    "gn:timezone":"America/Caracas",
    "iso:country":"VE",
    "wof:name":"La Placeta",
    "wof:placetype":"locality"
},
  "geometry": {"coordinates":[-63.71191999999999,10.43728],"type":"Point"}
}