{
  "type": "Feature",
  "properties": {
    "gn:admin1_code":"13",
    "gn:asciiname":"Agua Salada",
    "gn:country_code":"VE",
    "gn:dem":384,
    "gn:feature_class":"P",
    "gn:feature_code":"PPL",
    "gn:name":"Agua Salada",
    "gn:population":0,
    "gn:timezone":"America/Caracas",
    "iso:country":"VE",
    "wof:name":"Agua Salada",
    "wof:placetype":"locality"
},
  "geometry": {"coordinates":[-69.91346,10.30729],"type":"Point"}
}