{
  "type": "Feature",
  "properties": {
    "gn:admin1_code":"8",
    "gn:asciiname":"Chaparrote",
    "gn:country_code":"VE",
    "gn:dem":397,
    "gn:feature_class":"P",
    "gn:feature_code":"PPL",
    "gn:name":"Chaparrote",
    "gn:population":0,
    "gn:timezone":"America/Caracas",
    "iso:country":"VE",
    "wof:name":"Chaparrote",
    "wof:placetype":"locality"
},
  "geometry": {"coordinates":[-67.8458,9.75484],"type":"Point"}
}