{
  "type": "Feature",
  "properties": {
    "gn:admin1_code":"19.0",
    "gn:asciiname":"El Chaco",
    "gn:country_code":"VE",
    "gn:dem":150,
    "gn:feature_class":"P",
    "gn:feature_code":"PPL",
    "gn:name":"El Chaco",
    "gn:population":0,
    "gn:timezone":"America/Caracas",
    "iso:country":"VE",
    "wof:name":"El Chaco",
    "wof:placetype":"locality"
},
  "geometry": {"coordinates":[-64.01125999999999,10.33273],"type":"Point"}
}