{
  "type": "Feature",
  "properties": {
    "gn:admin1_code":"3.0",
    "gn:asciiname":"El Encantico",
    "gn:country_code":"VE",
    "gn:dem":48,
    "gn:feature_class":"P",
    "gn:feature_code":"PPL",
    "gn:name":"El Encantico",
    "gn:population":0,
    "gn:timezone":"America/Caracas",
    "iso:country":"VE",
    "wof:name":"El Encantico",
    "wof:placetype":"locality"
},
  "geometry": {"coordinates":[-67.05818000000001,7.71586],"type":"Point"}
}