{
  "type": "Feature",
  "properties": {
    "gn:admin1_code":"19.0",
    "gn:asciiname":"Tres Picos",
    "gn:country_code":"VE",
    "gn:dem":346,
    "gn:feature_class":"P",
    "gn:feature_code":"PPL",
    "gn:name":"Tres Picos",
    "gn:population":0,
    "gn:timezone":"America/Caracas",
    "iso:country":"VE",
    "wof:name":"Tres Picos",
    "wof:placetype":"locality"
},
  "geometry": {"coordinates":[-63.99373000000001,10.28161],"type":"Point"}
}