{
  "type": "Feature",
  "properties": {
    "gn:admin1_code":"04",
    "gn:asciiname":"Santo Domingo",
    "gn:country_code":"VE",
    "gn:dem":15,
    "gn:feature_class":"P",
    "gn:feature_code":"PPL",
    "gn:name":"Santo Domingo",
    "gn:population":0,
    "gn:timezone":"America/Caracas",
    "iso:country":"VE",
    "wof:name":"Santo Domingo",
    "wof:placetype":"locality"
},
  "geometry": {"coordinates":[-67.84999999999999,10.43333],"type":"Point"}
}