{
  "type": "Feature",
  "properties": {
    "gn:admin1_code":"11",
    "gn:asciiname":"Curari",
    "gn:country_code":"VE",
    "gn:dem":14,
    "gn:feature_class":"P",
    "gn:feature_code":"PPL",
    "gn:name":"Curar\u00ed",
    "gn:population":0,
    "gn:timezone":"America/Caracas",
    "iso:country":"VE",
    "name:und_x_variant":[
        "El Curar\u00ed",
        "Curar\u00ed"
    ],
    "wof:name":"Curari",
    "wof:placetype":"locality"
},
  "geometry": {"coordinates":[-68.97158,11.31897],"type":"Point"}
}