{
  "type": "Feature",
  "properties": {
    "gn:admin1_code":"18",
    "gn:asciiname":"Colorado de Maparia",
    "gn:country_code":"VE",
    "gn:dem":130,
    "gn:feature_class":"P",
    "gn:feature_code":"PPL",
    "gn:name":"Colorado de Maparia",
    "gn:population":0,
    "gn:timezone":"America/Caracas",
    "iso:country":"VE",
    "wof:name":"Colorado de Maparia",
    "wof:placetype":"locality"
},
  "geometry": {"coordinates":[-69.06624000000001,9.3798],"type":"Point"}
}