{
  "type": "Feature",
  "properties": {
    "gn:admin1_code":"12",
    "gn:asciiname":"Faldiquera",
    "gn:country_code":"VE",
    "gn:dem":68,
    "gn:feature_class":"P",
    "gn:feature_code":"PPL",
    "gn:name":"Faldiquera",
    "gn:population":0,
    "gn:timezone":"America/Caracas",
    "iso:country":"VE",
    "wof:name":"Faldiquera",
    "wof:placetype":"locality"
},
  "geometry": {"coordinates":[-66.53957,8.25036],"type":"Point"}
}