{
  "type": "Feature",
  "properties": {
    "gn:admin1_code":"19",
    "gn:asciiname":"Juajillal",
    "gn:cc2":"VE",
    "gn:country_code":"VE",
    "gn:dem":447,
    "gn:feature_class":"P",
    "gn:feature_code":"PPL",
    "gn:name":"Juajillal",
    "gn:population":0,
    "gn:timezone":"America/Caracas",
    "iso:country":"VE",
    "name:und_x_variant":[
        "Juajuillal",
        "Juajillal"
    ],
    "wof:name":"Juajillal",
    "wof:placetype":"locality"
},
  "geometry": {"coordinates":[-63.36666999999999,10.28333],"type":"Point"}
}