{
  "type": "Feature",
  "properties": {
    "gn:admin1_code":"21",
    "gn:asciiname":"Tierra Morada",
    "gn:country_code":"VE",
    "gn:dem":1412,
    "gn:feature_class":"P",
    "gn:feature_code":"PPL",
    "gn:name":"Tierra Morada",
    "gn:population":0,
    "gn:timezone":"America/Caracas",
    "iso:country":"VE",
    "wof:name":"Tierra Morada",
    "wof:placetype":"locality"
},
  "geometry": {"coordinates":[-70.4055,9.35956],"type":"Point"}
}