{
  "type": "Feature",
  "properties": {
    "gn:admin1_code":"14.0",
    "gn:asciiname":"Las Duaras",
    "gn:country_code":"VE",
    "gn:dem":452,
    "gn:feature_class":"P",
    "gn:feature_code":"PPL",
    "gn:name":"Las Duaras",
    "gn:population":0,
    "gn:timezone":"America/Caracas",
    "iso:country":"VE",
    "wof:name":"Las Duaras",
    "wof:placetype":"locality"
},
  "geometry": {"coordinates":[-70.97176,9.13955],"type":"Point"}
}