{
  "type": "Feature",
  "properties": {
    "gn:admin1_code":"15.0",
    "gn:asciiname":"La Providencia",
    "gn:country_code":"VE",
    "gn:dem":1096,
    "gn:feature_class":"P",
    "gn:feature_code":"PPLL",
    "gn:name":"La Providencia",
    "gn:population":0,
    "gn:timezone":"America/Caracas",
    "iso:country":"VE",
    "wof:name":"La Providencia",
    "wof:placetype":"locality"
},
  "geometry": {"coordinates":[-66.75827,10.46409],"type":"Point"}
}