{
  "type": "Feature",
  "properties": {
    "gn:admin1_code":"22",
    "gn:asciiname":"El Cobre",
    "gn:country_code":"VE",
    "gn:dem":114,
    "gn:feature_class":"P",
    "gn:feature_code":"PPL",
    "gn:name":"El Cobre",
    "gn:population":0,
    "gn:timezone":"America/Caracas",
    "iso:country":"VE",
    "name:bre_x_preferred":[
        "El Cobre"
    ],
    "name:ceb_x_preferred":[
        "El Cobre"
    ],
    "name:deu_x_preferred":[
        "El Cobre"
    ],
    "name:swe_x_preferred":[
        "El Cobre"
    ],
    "wof:name":"El Cobre",
    "wof:placetype":"locality"
},
  "geometry": {"coordinates":[-68.80941999999999,10.54143],"type":"Point"}
}