{
  "type": "Feature",
  "properties": {
    "gn:admin1_code":"26",
    "gn:asciiname":"El Copey",
    "gn:country_code":"VE",
    "gn:dem":668,
    "gn:feature_class":"P",
    "gn:feature_code":"PPL",
    "gn:name":"El Copey",
    "gn:population":0,
    "gn:timezone":"America/Caracas",
    "iso:country":"VE",
    "wof:name":"El Copey",
    "wof:placetype":"locality"
},
  "geometry": {"coordinates":[-66.96666999999999,10.56667],"type":"Point"}
}