{
  "type": "Feature",
  "properties": {
    "gn:admin1_code":"26",
    "gn:asciiname":"El Copey",
    "gn:country_code":"VE",
    "gn:dem":668,
    "gn:feature_class":"P",
    "gn:feature_code":"PPL",
    "gn:name":"El Copey",
    "gn:population":0,
    "gn:timezone":"America/Caracas",
    "iso:country":"VE",
    "name:ceb_x_preferred":[
        "El Copey"
    ],
    "name:deu_x_preferred":[
        "El Copey"
    ],
    "name:fas_x_preferred":[
        "\u0627\u0644 \u06a9\u0648\u067e\u06cc"
    ],
    "name:fra_x_preferred":[
        "El Copey"
    ],
    "name:ita_x_preferred":[
        "El Copey"
    ],
    "name:kat_x_preferred":[
        "\u10d4\u10da-\u10d9\u10dd\u10de\u10d4\u10d8"
    ],
    "name:msa_x_preferred":[
        "El Copey"
    ],
    "name:nld_x_preferred":[
        "El Copey"
    ],
    "name:por_x_preferred":[
        "El Copey"
    ],
    "name:rus_x_preferred":[
        "\u042d\u043b\u044c-\u041a\u043e\u043f\u0435\u0439"
    ],
    "name:spa_x_preferred":[
        "El Copey"
    ],
    "name:swe_x_preferred":[
        "El Copey"
    ],
    "name:tgl_x_preferred":[
        "El Copey"
    ],
    "name:vie_x_preferred":[
        "El Copey"
    ],
    "name:war_x_preferred":[
        "El Copey"
    ],
    "name:zho_x_preferred":[
        "\u57c3\u723e\u79d1\u4f69"
    ],
    "wof:name":"El Copey",
    "wof:placetype":"locality"
},
  "geometry": {"coordinates":[-66.96666999999999,10.56667],"type":"Point"}
}