{
  "type": "Feature",
  "properties": {
    "gn:admin1_code":"3",
    "gn:asciiname":"La Ceibita",
    "gn:country_code":"VE",
    "gn:dem":103,
    "gn:feature_class":"P",
    "gn:feature_code":"PPL",
    "gn:name":"La Ceibita",
    "gn:population":0,
    "gn:timezone":"America/Caracas",
    "iso:country":"VE",
    "wof:name":"La Ceibita",
    "wof:placetype":"locality"
},
  "geometry": {"coordinates":[-69.73532,7.10241],"type":"Point"}
}