{
  "type": "Feature",
  "properties": {
    "gn:admin1_code":"12",
    "gn:asciiname":"Labra",
    "gn:country_code":"VE",
    "gn:dem":49,
    "gn:feature_class":"P",
    "gn:feature_code":"PPL",
    "gn:name":"Labra",
    "gn:population":0,
    "gn:timezone":"America/Caracas",
    "iso:country":"VE",
    "name:ceb_x_preferred":[
        "Labra"
    ],
    "name:srp_x_preferred":[
        "\u041b\u0430\u0431\u0440\u0430"
    ],
    "name:swe_x_preferred":[
        "Labra"
    ],
    "wof:name":"Labra",
    "wof:placetype":"locality"
},
  "geometry": {"coordinates":[-67.05923,8.07889],"type":"Point"}
}