{
  "type": "Feature",
  "properties": {
    "gn:admin1_code":"7",
    "gn:asciiname":"El Faldo",
    "gn:country_code":"VE",
    "gn:dem":706,
    "gn:feature_class":"P",
    "gn:feature_code":"PPL",
    "gn:name":"El Faldo",
    "gn:population":0,
    "gn:timezone":"America/Caracas",
    "iso:country":"VE",
    "wof:name":"El Faldo",
    "wof:placetype":"locality"
},
  "geometry": {"coordinates":[-67.67610999999999,10.02722],"type":"Point"}
}