{
  "type": "Feature",
  "properties": {
    "gn:admin1_code":"2",
    "gn:asciiname":"La Zorra",
    "gn:country_code":"VE",
    "gn:dem":58,
    "gn:feature_class":"P",
    "gn:feature_code":"PPL",
    "gn:name":"La Zorra",
    "gn:population":0,
    "gn:timezone":"America/Caracas",
    "iso:country":"VE",
    "wof:name":"La Zorra",
    "wof:placetype":"locality"
},
  "geometry": {"coordinates":[-63.40278000000001,8.41504],"type":"Point"}
}