{
  "type": "Feature",
  "properties": {
    "gn:admin1_code":"19.0",
    "gn:admin2_code":"1913.0",
    "gn:asciiname":"Jabillar",
    "gn:country_code":"VE",
    "gn:dem":443,
    "gn:feature_class":"P",
    "gn:feature_code":"PPL",
    "gn:name":"Jabillar",
    "gn:population":0,
    "gn:timezone":"America/Caracas",
    "iso:country":"VE",
    "wof:name":"Jabillar",
    "wof:placetype":"locality"
},
  "geometry": {"coordinates":[-63.50123000000001,10.38901],"type":"Point"}
}