{
  "type": "Feature",
  "properties": {
    "gn:admin1_code":"19.0",
    "gn:asciiname":"La Peluca",
    "gn:country_code":"VE",
    "gn:dem":654,
    "gn:feature_class":"P",
    "gn:feature_code":"PPL",
    "gn:name":"La Peluca",
    "gn:population":0,
    "gn:timezone":"America/Caracas",
    "iso:country":"VE",
    "wof:name":"La Peluca",
    "wof:placetype":"locality"
},
  "geometry": {"coordinates":[-64.37181,10.20101],"type":"Point"}
}