{
  "type": "Feature",
  "properties": {
    "gn:admin1_code":"18.0",
    "gn:asciiname":"La Raya",
    "gn:country_code":"VE",
    "gn:dem":381,
    "gn:feature_class":"P",
    "gn:feature_code":"PPL",
    "gn:name":"La Raya",
    "gn:population":0,
    "gn:timezone":"America/Caracas",
    "iso:country":"VE",
    "name:spa_x_preferred":[
        "La Raya"
    ],
    "wof:name":"La Raya",
    "wof:placetype":"locality"
},
  "geometry": {"coordinates":[-69.93038,9.23212],"type":"Point"}
}