{
  "type": "Feature",
  "properties": {
    "gn:admin1_code":"02",
    "gn:asciiname":"El Milanero",
    "gn:country_code":"VE",
    "gn:dem":104,
    "gn:feature_class":"P",
    "gn:feature_code":"PPLL",
    "gn:name":"El Milanero",
    "gn:population":0,
    "gn:timezone":"America/Caracas",
    "iso:country":"VE",
    "wof:name":"El Milanero",
    "wof:placetype":"locality"
},
  "geometry": {"coordinates":[-63.29769,8.65488],"type":"Point"}
}