{
  "type": "Feature",
  "properties": {
    "gn:admin1_code":"02",
    "gn:asciiname":"Quebrada de Aqua",
    "gn:country_code":"VE",
    "gn:dem":779,
    "gn:feature_class":"P",
    "gn:feature_code":"PPL",
    "gn:name":"Quebrada de Aqua",
    "gn:population":0,
    "gn:timezone":"America/Caracas",
    "iso:country":"VE",
    "wof:name":"Quebrada de Aqua",
    "wof:placetype":"locality"
},
  "geometry": {"coordinates":[-64.23219,10.00892],"type":"Point"}
}