{
  "type": "Feature",
  "properties": {
    "gn:admin1_code":"18.0",
    "gn:admin2_code":"1812.0",
    "gn:asciiname":"El Playon",
    "gn:country_code":"VE",
    "gn:dem":100,
    "gn:feature_class":"P",
    "gn:feature_code":"PPLA2",
    "gn:name":"El Play\u00f3n",
    "gn:population":0,
    "gn:timezone":"America/Caracas",
    "iso:country":"VE",
    "name:spa_x_preferred":[
        "El Play\u00f3n"
    ],
    "name:spa_x_variant":[
        "Santa Rosalia"
    ],
    "wof:name":"El Playon",
    "wof:placetype":"locality"
},
  "geometry": {"coordinates":[-69.04914000000001,9.09857],"type":"Point"}
}