{
  "type": "Feature",
  "properties": {
    "gn:admin1_code":"05",
    "gn:asciiname":"Santa Eduvigis",
    "gn:country_code":"VE",
    "gn:dem":50,
    "gn:feature_class":"P",
    "gn:feature_code":"PPL",
    "gn:name":"Santa Eduvigis",
    "gn:population":0,
    "gn:timezone":"America/Caracas",
    "iso:country":"VE",
    "wof:name":"Santa Eduvigis",
    "wof:placetype":"locality"
},
  "geometry": {"coordinates":[-67.65389,7.96611],"type":"Point"}
}