{
  "type": "Feature",
  "properties": {
    "gn:admin1_code":"4",
    "gn:asciiname":"Guanape",
    "gn:country_code":"VE",
    "gn:dem":379,
    "gn:feature_class":"P",
    "gn:feature_code":"PPL",
    "gn:name":"Guanape",
    "gn:population":0,
    "gn:timezone":"America/Caracas",
    "iso:country":"VE",
    "wof:name":"Guanape",
    "wof:placetype":"locality"
},
  "geometry": {"coordinates":[-66.75,9.78333],"type":"Point"}
}