{
  "type": "Feature",
  "properties": {
    "gn:admin1_code":"4",
    "gn:asciiname":"Las Adjuntas",
    "gn:country_code":"VE",
    "gn:dem":664,
    "gn:feature_class":"P",
    "gn:feature_code":"PPL",
    "gn:name":"Las Adjuntas",
    "gn:population":0,
    "gn:timezone":"America/Caracas",
    "iso:country":"VE",
    "name:jpn_x_preferred":[
        "\u30e9\u30b9\u30fb\u30a2\u30c9\u30d5\u30f3\u30bf\u30b9\u99c5"
    ],
    "name:por_x_preferred":[
        "Esta\u00e7\u00e3o Las Adjuntas"
    ],
    "wof:name":"Las Adjuntas",
    "wof:placetype":"locality"
},
  "geometry": {"coordinates":[-66.94508,10.03479],"type":"Point"}
}