{
  "type": "Feature",
  "properties": {
    "gn:admin1_code":"6.0",
    "gn:asciiname":"Las Mercedes",
    "gn:country_code":"VE",
    "gn:dem":252,
    "gn:feature_class":"P",
    "gn:feature_code":"PPL",
    "gn:name":"Las Mercedes",
    "gn:population":0,
    "gn:timezone":"America/Caracas",
    "iso:country":"VE",
    "name:ceb_x_preferred":[
        "Las Mercedes"
    ],
    "name:deu_x_preferred":[
        "Las Mercedes"
    ],
    "name:spa_x_preferred":[
        "Las Mercedes"
    ],
    "name:swe_x_preferred":[
        "Las Mercedes"
    ],
    "wof:name":"Las Mercedes",
    "wof:placetype":"locality"
},
  "geometry": {"coordinates":[-62.26221999999999,7.755],"type":"Point"}
}