{
  "type": "Feature",
  "properties": {
    "gn:admin1_code":"15.0",
    "gn:asciiname":"El Reten",
    "gn:country_code":"VE",
    "gn:dem":1238,
    "gn:feature_class":"P",
    "gn:feature_code":"PPLL",
    "gn:name":"El Reten",
    "gn:population":0,
    "gn:timezone":"America/Caracas",
    "iso:country":"VE",
    "wof:name":"El Reten",
    "wof:placetype":"locality"
},
  "geometry": {"coordinates":[-67.06444,10.34333],"type":"Point"}
}