{
  "type": "Feature",
  "properties": {
    "gn:admin1_code":"12",
    "gn:asciiname":"Corocito Penero",
    "gn:country_code":"VE",
    "gn:dem":188,
    "gn:feature_class":"P",
    "gn:feature_code":"PPL",
    "gn:name":"Corocito Pe\u00f1ero",
    "gn:population":0,
    "gn:timezone":"America/Caracas",
    "iso:country":"VE",
    "wof:name":"Corocito Penero",
    "wof:placetype":"locality"
},
  "geometry": {"coordinates":[-65.81778,8.82222],"type":"Point"}
}