{
  "type": "Feature",
  "properties": {
    "gn:admin1_code":"23.0",
    "gn:asciiname":"La Virgen",
    "gn:country_code":"VE",
    "gn:dem":81,
    "gn:feature_class":"P",
    "gn:feature_code":"PPLL",
    "gn:name":"La Virgen",
    "gn:population":0,
    "gn:timezone":"America/Caracas",
    "iso:country":"VE",
    "wof:name":"La Virgen",
    "wof:placetype":"locality"
},
  "geometry": {"coordinates":[-71.98264,10.51068],"type":"Point"}
}