{
  "type": "Feature",
  "properties": {
    "gn:admin1_code":"4",
    "gn:asciiname":"Las Horas",
    "gn:country_code":"VE",
    "gn:dem":1522,
    "gn:feature_class":"P",
    "gn:feature_code":"PPL",
    "gn:name":"Las Horas",
    "gn:population":0,
    "gn:timezone":"America/Caracas",
    "iso:country":"VE",
    "wof:name":"Las Horas",
    "wof:placetype":"locality"
},
  "geometry": {"coordinates":[-67.31667,10.36667],"type":"Point"}
}