{
  "type": "Feature",
  "properties": {
    "gn:admin1_code":"05",
    "gn:asciiname":"Las Mulas",
    "gn:country_code":"VE",
    "gn:dem":76,
    "gn:feature_class":"P",
    "gn:feature_code":"PPLL",
    "gn:name":"Las Mulas",
    "gn:population":0,
    "gn:timezone":"America/Caracas",
    "iso:country":"VE",
    "wof:name":"Las Mulas",
    "wof:placetype":"locality"
},
  "geometry": {"coordinates":[-68.81324000000001,7.90637],"type":"Point"}
}