{
  "type": "Feature",
  "properties": {
    "gn:admin1_code":"18.0",
    "gn:asciiname":"La Chipola",
    "gn:country_code":"VE",
    "gn:dem":69,
    "gn:feature_class":"P",
    "gn:feature_code":"PPLL",
    "gn:name":"La Chipola",
    "gn:population":0,
    "gn:timezone":"America/Caracas",
    "iso:country":"VE",
    "name:spa_x_preferred":[
        "La Chipola"
    ],
    "wof:name":"La Chipola",
    "wof:placetype":"locality"
},
  "geometry": {"coordinates":[-68.85615,8.1613],"type":"Point"}
}