{
  "type": "Feature",
  "properties": {
    "gn:admin1_code":"15.0",
    "gn:asciiname":"La Reinosa",
    "gn:country_code":"VE",
    "gn:dem":1572,
    "gn:feature_class":"P",
    "gn:feature_code":"PPL",
    "gn:name":"La Reinosa",
    "gn:population":0,
    "gn:timezone":"America/Caracas",
    "iso:country":"VE",
    "wof:name":"La Reinosa",
    "wof:placetype":"locality"
},
  "geometry": {"coordinates":[-67.07779000000001,10.38452],"type":"Point"}
}