{
  "type": "Feature",
  "properties": {
    "gn:admin1_code":"6",
    "gn:asciiname":"Mariajisina",
    "gn:country_code":"VE",
    "gn:dem":330,
    "gn:feature_class":"P",
    "gn:feature_code":"PPL",
    "gn:name":"Mar\u00edajisi\u00f1a",
    "gn:population":0,
    "gn:timezone":"America/Caracas",
    "iso:country":"VE",
    "wof:name":"Mariajisina",
    "wof:placetype":"locality"
},
  "geometry": {"coordinates":[-64.63333,5.25],"type":"Point"}
}