{
  "type": "Feature",
  "properties": {
    "gn:admin1_code":"16",
    "gn:asciiname":"Jabilla",
    "gn:country_code":"VE",
    "gn:dem":94,
    "gn:feature_class":"P",
    "gn:feature_code":"PPL",
    "gn:name":"Jabilla",
    "gn:population":0,
    "gn:timezone":"America/Caracas",
    "iso:country":"VE",
    "name:und_x_variant":[
        "Jabillal",
        "Jabilla"
    ],
    "wof:name":"Jabilla",
    "wof:placetype":"locality"
},
  "geometry": {"coordinates":[-63.35126,8.96476],"type":"Point"}
}