{
  "type": "Feature",
  "properties": {
    "gn:admin1_code":"19.0",
    "gn:asciiname":"Agua Santa",
    "gn:country_code":"VE",
    "gn:dem":59,
    "gn:feature_class":"P",
    "gn:feature_code":"PPL",
    "gn:name":"Agua Santa",
    "gn:population":0,
    "gn:timezone":"America/Caracas",
    "iso:country":"VE",
    "wof:name":"Agua Santa",
    "wof:placetype":"locality"
},
  "geometry": {"coordinates":[-64.11079000000001,10.34383],"type":"Point"}
}