{
  "type": "Feature",
  "properties": {
    "gn:admin1_code":"14",
    "gn:asciiname":"Valle de La Cruz",
    "gn:country_code":"VE",
    "gn:dem":1504,
    "gn:feature_class":"P",
    "gn:feature_code":"PPL",
    "gn:name":"Valle de La Cruz",
    "gn:population":0,
    "gn:timezone":"America/Caracas",
    "iso:country":"VE",
    "wof:name":"Valle de La Cruz",
    "wof:placetype":"locality"
},
  "geometry": {"coordinates":[-71.46779000000002,8.11472],"type":"Point"}
}