{
  "type": "Feature",
  "properties": {
    "gn:admin1_code":"17",
    "gn:asciiname":"Las Barrancas",
    "gn:country_code":"VE",
    "gn:dem":51,
    "gn:feature_class":"P",
    "gn:feature_code":"PPL",
    "gn:name":"Las Barrancas",
    "gn:population":0,
    "gn:timezone":"America/Caracas",
    "iso:country":"VE",
    "name:und_x_variant":[
        "Barrancas",
        "Las Barrancas"
    ],
    "wof:name":"Las Barrancas",
    "wof:placetype":"locality"
},
  "geometry": {"coordinates":[-63.98428000000001,10.99091],"type":"Point"}
}