{
  "type": "Feature",
  "properties": {
    "gn:admin1_code":"19.0",
    "gn:asciiname":"El Algarrobo",
    "gn:country_code":"VE",
    "gn:dem":467,
    "gn:feature_class":"P",
    "gn:feature_code":"PPL",
    "gn:name":"El Algarrobo",
    "gn:population":0,
    "gn:timezone":"America/Caracas",
    "iso:country":"VE",
    "wof:name":"El Algarrobo",
    "wof:placetype":"locality"
},
  "geometry": {"coordinates":[-62.81113000000001,10.64166],"type":"Point"}
}