{
  "type": "Feature",
  "properties": {
    "gn:admin1_code":"18.0",
    "gn:asciiname":"La Sabanita",
    "gn:country_code":"VE",
    "gn:dem":1023,
    "gn:feature_class":"P",
    "gn:feature_code":"PPL",
    "gn:name":"La Sabanita",
    "gn:population":0,
    "gn:timezone":"America/Caracas",
    "iso:country":"VE",
    "name:spa_x_preferred":[
        "La Sabanita"
    ],
    "wof:name":"La Sabanita",
    "wof:placetype":"locality"
},
  "geometry": {"coordinates":[-69.96486,9.34777],"type":"Point"}
}