{
  "type": "Feature",
  "properties": {
    "gn:admin1_code":"4",
    "gn:asciiname":"El Rosario",
    "gn:cc2":"VE",
    "gn:country_code":"VE",
    "gn:dem":203,
    "gn:feature_class":"P",
    "gn:feature_code":"PPL",
    "gn:name":"El Rosario",
    "gn:population":0,
    "gn:timezone":"America/Caracas",
    "iso:country":"VE",
    "name:und_x_variant":[
        "Rosario",
        "El Rosario"
    ],
    "wof:name":"El Rosario",
    "wof:placetype":"locality"
},
  "geometry": {"coordinates":[-66.84999999999999,9.65],"type":"Point"}
}