{
  "type": "Feature",
  "properties": {
    "gn:admin1_code":"04",
    "gn:asciiname":"Trincheras",
    "gn:country_code":"VE",
    "gn:dem":250,
    "gn:feature_class":"P",
    "gn:feature_code":"PPL",
    "gn:name":"Trincheras",
    "gn:population":0,
    "gn:timezone":"America/Caracas",
    "iso:country":"VE",
    "name:deu_x_preferred":[
        "Trincheras"
    ],
    "name:epo_x_preferred":[
        "Trincheras"
    ],
    "name:ita_x_preferred":[
        "Trincheras"
    ],
    "name:ron_x_preferred":[
        "Trincheras"
    ],
    "name:spa_x_preferred":[
        "Trincheras"
    ],
    "name:vie_x_preferred":[
        "Trincheras"
    ],
    "wof:name":"Trincheras",
    "wof:placetype":"locality"
},
  "geometry": {"coordinates":[-66.65864999999999,9.64197],"type":"Point"}
}