{
  "type": "Feature",
  "properties": {
    "gn:admin1_code":"5",
    "gn:asciiname":"Manirote",
    "gn:country_code":"VE",
    "gn:dem":62,
    "gn:feature_class":"P",
    "gn:feature_code":"PPL",
    "gn:name":"Manirote",
    "gn:population":0,
    "gn:timezone":"America/Caracas",
    "iso:country":"VE",
    "wof:name":"Manirote",
    "wof:placetype":"locality"
},
  "geometry": {"coordinates":[-67.91667,8.36667],"type":"Point"}
}