{
  "type": "Feature",
  "properties": {
    "gn:admin1_code":"1.0",
    "gn:asciiname":"Sipariateri",
    "gn:country_code":"VE",
    "gn:dem":169,
    "gn:feature_class":"P",
    "gn:feature_code":"PPL",
    "gn:name":"Sipariateri",
    "gn:population":0,
    "gn:timezone":"America/Caracas",
    "iso:country":"VE",
    "wof:name":"Sipariateri",
    "wof:placetype":"locality"
},
  "geometry": {"coordinates":[-64.93725000000001,2.66666],"type":"Point"}
}