{
  "type": "Feature",
  "properties": {
    "gn:admin1_code":"3",
    "gn:asciiname":"Remolino",
    "gn:country_code":"VE",
    "gn:dem":131,
    "gn:feature_class":"P",
    "gn:feature_code":"PPL",
    "gn:name":"Remolino",
    "gn:population":0,
    "gn:timezone":"America/Caracas",
    "iso:country":"VE",
    "wof:name":"Remolino",
    "wof:placetype":"locality"
},
  "geometry": {"coordinates":[-70.81661,7.23158],"type":"Point"}
}