{
  "type": "Feature",
  "properties": {
    "gn:admin1_code":"2",
    "gn:asciiname":"Lindero de la Mejorana",
    "gn:country_code":"VE",
    "gn:dem":106,
    "gn:feature_class":"P",
    "gn:feature_code":"PPL",
    "gn:name":"Lindero de la Mejorana",
    "gn:population":0,
    "gn:timezone":"America/Caracas",
    "iso:country":"VE",
    "wof:name":"Lindero de la Mejorana",
    "wof:placetype":"locality"
},
  "geometry": {"coordinates":[-64.86667,9.38333],"type":"Point"}
}