{
  "type": "Feature",
  "properties": {
    "gn:admin1_code":"11",
    "gn:asciiname":"Sabana Grande",
    "gn:country_code":"VE",
    "gn:dem":195,
    "gn:feature_class":"P",
    "gn:feature_code":"PPL",
    "gn:name":"Sabana Grande",
    "gn:population":0,
    "gn:timezone":"America/Caracas",
    "iso:country":"VE",
    "name:ceb_x_preferred":[
        "Sabana Grande"
    ],
    "name:fra_x_preferred":[
        "Sabana Grande"
    ],
    "name:ita_x_preferred":[
        "Sabana Grande"
    ],
    "name:nld_x_preferred":[
        "Sabana Grande"
    ],
    "name:pol_x_preferred":[
        "Sabana Grande"
    ],
    "name:spa_x_preferred":[
        "Sabanagrande"
    ],
    "name:srp_x_preferred":[
        "\u0421\u0430\u0431\u0430\u043d\u0430 \u0413\u0440\u0430\u043d\u0434\u0435"
    ],
    "name:swe_x_preferred":[
        "Sabana Grande"
    ],
    "wof:name":"Sabana Grande",
    "wof:placetype":"locality"
},
  "geometry": {"coordinates":[-70.88333,10.65],"type":"Point"}
}