{
  "type": "Feature",
  "properties": {
    "gn:admin1_code":"08",
    "gn:asciiname":"Santa Maria",
    "gn:country_code":"VE",
    "gn:dem":606,
    "gn:feature_class":"P",
    "gn:feature_code":"PPL",
    "gn:name":"Santa Mar\u00eda",
    "gn:population":0,
    "gn:timezone":"America/Caracas",
    "iso:country":"VE",
    "wof:name":"Santa Maria",
    "wof:placetype":"locality"
},
  "geometry": {"coordinates":[-68.71666999999999,9.85],"type":"Point"}
}