{
  "type": "Feature",
  "properties": {
    "iso:country":"VE",
    "name:deu_x_preferred":[
        "Chaguaramas"
    ],
    "name:fra_x_preferred":[
        "Chaguaramas"
    ],
    "name:nld_x_preferred":[
        "Chaguaramas"
    ],
    "name:spa_x_preferred":[
        "Chaguaramas"
    ],
    "qs:gn_pop":0,
    "qs:name":"Chaguaramas",
    "qs:name_adm0":"Venezuela",
    "qs:name_adm1":"Guarico",
    "qs:photos":1,
    "qs:photos_1k":1,
    "qs:photos_9k":1,
    "qs:photos_9r":1,
    "qs:photos_all":1,
    "qs:photos_sr":1,
    "qs:placetype":"LocalAdmin",
    "qs:pop_sr":"0",
    "qs:woe_adm0":23424982,
    "wof:name":"Chaguaramas",
    "wof:placetype":"localadmin"
},
  "geometry": {"coordinates":[-66.25255,9.33855],"type":"Point"}
}