{
  "type": "Feature",
  "properties": {
    "iso:country":"VE",
    "name:ara_x_preferred":[
        "\u0634\u0627\u063a\u0627\u0631\u0627\u0645\u0627\u0633"
    ],
    "name:ben_x_preferred":[
        "\u099a\u09be\u0997\u09c1\u09df\u09be\u09b0\u09be\u09ae\u09be\u09b8"
    ],
    "name:deu_x_preferred":[
        "Chaguaramas"
    ],
    "name:ell_x_preferred":[
        "\u03a4\u03c3\u03b1\u03b3\u03ba\u03bf\u03c5\u03b1\u03c1\u03ac\u03bc\u03b1\u03c2"
    ],
    "name:fas_x_preferred":[
        "\u0686\u0627\u06af\u0648\u0627\u0631\u0627\u0645\u0627\u0633"
    ],
    "name:fra_x_preferred":[
        "Chaguaramas"
    ],
    "name:heb_x_preferred":[
        "\u05e6'\u05d0\u05d2\u05d5\u05d0\u05e8\u05de\u05d0\u05e1"
    ],
    "name:hin_x_preferred":[
        "\u091a\u0948\u0917\u0941\u0906\u0930\u093e\u092e\u093e\u091c\u093c"
    ],
    "name:hun_x_preferred":[
        "Chaguaramas"
    ],
    "name:ind_x_preferred":[
        "Chaguaramas"
    ],
    "name:ita_x_preferred":[
        "Chaguaramas"
    ],
    "name:jpn_x_preferred":[
        "\u30c1\u30e3\u30b0\u30a2\u30e9\u30de"
    ],
    "name:kor_x_preferred":[
        "\ucc28\uacfc\ub77c\ub9c8"
    ],
    "name:nld_x_preferred":[
        "Chaguaramas"
    ],
    "name:rus_x_preferred":[
        "\u0427\u0430\u0433\u0443\u0430\u0440\u0430\u043c\u0430\u0441"
    ],
    "name:spa_x_preferred":[
        "Chaguaramas"
    ],
    "name:swe_x_preferred":[
        "Chaguaramas"
    ],
    "name:tur_x_preferred":[
        "Chaguaramas"
    ],
    "name:ukr_x_preferred":[
        "\u0427\u0430\u0433\u0443\u0430\u0440\u0430\u043c\u0430\u0441"
    ],
    "name:urd_x_preferred":[
        "\u0686\u0627\u06af\u0648\u0627\u0631\u0627\u0645\u0627\u0633"
    ],
    "name:vie_x_preferred":[
        "Chaguaramas"
    ],
    "qs:gn_pop":0,
    "qs:name":"Chaguaramas",
    "qs:name_adm0":"Venezuela",
    "qs:name_adm1":"Guarico",
    "qs:photos":1,
    "qs:photos_1k":1,
    "qs:photos_9k":1,
    "qs:photos_9r":1,
    "qs:photos_all":1,
    "qs:photos_sr":1,
    "qs:placetype":"LocalAdmin",
    "qs:pop_sr":"0",
    "qs:woe_adm0":23424982,
    "wof:name":"Chaguaramas",
    "wof:placetype":"localadmin"
},
  "geometry": {"coordinates":[-66.25255,9.33855],"type":"Point"}
}