{
  "type": "Feature",
  "properties": {
    "gn:admin1_code":"19",
    "gn:admin2_code":"1904.0",
    "gn:asciiname":"El Pilar",
    "gn:country_code":"VE",
    "gn:dem":63,
    "gn:feature_class":"P",
    "gn:feature_code":"PPLA2",
    "gn:name":"El Pilar",
    "gn:population":0,
    "gn:timezone":"America/Caracas",
    "iso:country":"VE",
    "name:eng_x_preferred":[
        "El Pilar"
    ],
    "name:fra_x_preferred":[
        "El Pilar"
    ],
    "name:por_x_preferred":[
        "El Pilar"
    ],
    "name:spa_x_preferred":[
        "El Pilar"
    ],
    "wof:name":"El Pilar",
    "wof:placetype":"locality"
},
  "geometry": {"coordinates":[-63.15,10.53333],"type":"Point"}
}