{
  "type": "Feature",
  "properties": {
    "gn:admin1_code":"11",
    "gn:asciiname":"Sabana de Humoria",
    "gn:country_code":"VE",
    "gn:dem":148,
    "gn:feature_class":"P",
    "gn:feature_code":"PPL",
    "gn:name":"Sabana de Humoria",
    "gn:population":0,
    "gn:timezone":"America/Caracas",
    "iso:country":"VE",
    "wof:name":"Sabana de Humoria",
    "wof:placetype":"locality"
},
  "geometry": {"coordinates":[-69.39917,11.09917],"type":"Point"}
}