{
  "type": "Feature",
  "properties": {
    "gn:admin1_code":"23",
    "gn:asciiname":"Medio Cuarto",
    "gn:country_code":"VE",
    "gn:dem":5,
    "gn:feature_class":"P",
    "gn:feature_code":"PPL",
    "gn:name":"Medio Cuarto",
    "gn:population":0,
    "gn:timezone":"America/Caracas",
    "iso:country":"VE",
    "wof:name":"Medio Cuarto",
    "wof:placetype":"locality"
},
  "geometry": {"coordinates":[-71.76000999999999,8.98751],"type":"Point"}
}