{
  "type": "Feature",
  "properties": {
    "gn:admin1_code":"16",
    "gn:asciiname":"Quebrada Grande",
    "gn:country_code":"VE",
    "gn:dem":860,
    "gn:feature_class":"P",
    "gn:feature_code":"PPL",
    "gn:name":"Quebrada Grande",
    "gn:population":0,
    "gn:timezone":"America/Caracas",
    "iso:country":"VE",
    "wof:name":"Quebrada Grande",
    "wof:placetype":"locality"
},
  "geometry": {"coordinates":[-63.43691,10.21629],"type":"Point"}
}