{
  "type": "Feature",
  "properties": {
    "gn:admin1_code":"23",
    "gn:asciiname":"Los Pozos",
    "gn:country_code":"VE",
    "gn:dem":19,
    "gn:feature_class":"P",
    "gn:feature_code":"PPL",
    "gn:name":"Los Pozos",
    "gn:population":0,
    "gn:timezone":"America/Caracas",
    "iso:country":"VE",
    "wof:name":"Los Pozos",
    "wof:placetype":"locality"
},
  "geometry": {"coordinates":[-71.73510999999998,10.7286],"type":"Point"}
}