{
  "type": "Feature",
  "properties": {
    "gn:admin1_code":"12",
    "gn:asciiname":"El Palmar",
    "gn:country_code":"VE",
    "gn:dem":115,
    "gn:feature_class":"P",
    "gn:feature_code":"PPL",
    "gn:name":"El Palmar",
    "gn:population":0,
    "gn:timezone":"America/Caracas",
    "iso:country":"VE",
    "wof:name":"El Palmar",
    "wof:placetype":"locality"
},
  "geometry": {"coordinates":[-65.59066,9.08199],"type":"Point"}
}