{
  "type": "Feature",
  "properties": {
    "gn:admin1_code":"4.0",
    "gn:asciiname":"La Cumbre",
    "gn:country_code":"VE",
    "gn:dem":480,
    "gn:feature_class":"P",
    "gn:feature_code":"PPL",
    "gn:name":"La Cumbre",
    "gn:population":0,
    "gn:timezone":"America/Caracas",
    "iso:country":"VE",
    "name:ceb_x_preferred":[
        "La Cumbre"
    ],
    "name:deu_x_preferred":[
        "La Cumbre"
    ],
    "name:eus_x_preferred":[
        "La Cumbre"
    ],
    "name:fra_x_preferred":[
        "La Cumbre"
    ],
    "name:ita_x_preferred":[
        "La Cumbre"
    ],
    "name:msa_x_preferred":[
        "La Cumbre"
    ],
    "name:nld_x_preferred":[
        "La Cumbre"
    ],
    "name:pol_x_preferred":[
        "La Cumbre"
    ],
    "name:spa_x_preferred":[
        "La Cumbre"
    ],
    "name:swe_x_preferred":[
        "La Cumbre"
    ],
    "name:vie_x_preferred":[
        "La Cumbre"
    ],
    "name:war_x_preferred":[
        "La Cumbre"
    ],
    "wof:name":"La Cumbre",
    "wof:placetype":"locality"
},
  "geometry": {"coordinates":[-67.40111,9.97878],"type":"Point"}
}