{
  "type": "Feature",
  "properties": {
    "gn:admin1_code":"4.0",
    "gn:asciiname":"La Cumbre",
    "gn:country_code":"VE",
    "gn:dem":480,
    "gn:feature_class":"P",
    "gn:feature_code":"PPL",
    "gn:name":"La Cumbre",
    "gn:population":0,
    "gn:timezone":"America/Caracas",
    "iso:country":"VE",
    "wof:name":"La Cumbre",
    "wof:placetype":"locality"
},
  "geometry": {"coordinates":[-67.40111,9.97878],"type":"Point"}
}