{
  "type": "Feature",
  "properties": {
    "gn:admin1_code":"16.0",
    "gn:asciiname":"Las Pinas",
    "gn:country_code":"VE",
    "gn:dem":25,
    "gn:feature_class":"P",
    "gn:feature_code":"PPL",
    "gn:name":"Las Pi\u00f1as",
    "gn:population":0,
    "gn:timezone":"America/Caracas",
    "iso:country":"VE",
    "wof:name":"Las Pinas",
    "wof:placetype":"locality"
},
  "geometry": {"coordinates":[-62.91336999999999,9.49391],"type":"Point"}
}