{
  "type": "Feature",
  "properties": {
    "gn:admin1_code":"3",
    "gn:asciiname":"Medanos de Jobal",
    "gn:country_code":"VE",
    "gn:dem":50,
    "gn:feature_class":"P",
    "gn:feature_code":"PPL",
    "gn:name":"Medanos de Jobal",
    "gn:population":0,
    "gn:timezone":"America/Caracas",
    "iso:country":"VE",
    "wof:name":"Medanos de Jobal",
    "wof:placetype":"locality"
},
  "geometry": {"coordinates":[-67.58804000000001,7.31809],"type":"Point"}
}