{
  "type": "Feature",
  "properties": {
    "gn:admin1_code":"16",
    "gn:asciiname":"La Madera",
    "gn:country_code":"VE",
    "gn:dem":208,
    "gn:feature_class":"P",
    "gn:feature_code":"PPL",
    "gn:name":"La Madera",
    "gn:population":0,
    "gn:timezone":"America/Caracas",
    "iso:country":"VE",
    "name:urd_x_preferred":[
        "\u0644\u0627 \u0645\u0627\u062f\u06cc\u0631\u0627"
    ],
    "wof:name":"La Madera",
    "wof:placetype":"locality"
},
  "geometry": {"coordinates":[-63.72409,9.36327],"type":"Point"}
}