{
  "type": "Feature",
  "properties": {
    "gn:admin1_code":"6.0",
    "gn:asciiname":"El Guapango",
    "gn:country_code":"VE",
    "gn:dem":203,
    "gn:feature_class":"P",
    "gn:feature_code":"PPL",
    "gn:name":"El Guapango",
    "gn:population":0,
    "gn:timezone":"America/Caracas",
    "iso:country":"VE",
    "wof:name":"El Guapango",
    "wof:placetype":"locality"
},
  "geometry": {"coordinates":[-61.54667,7.32722],"type":"Point"}
}