{
  "type": "Feature",
  "properties": {
    "gn:admin1_code":"13.0",
    "gn:asciiname":"San Jacinto",
    "gn:country_code":"VE",
    "gn:dem":584,
    "gn:feature_class":"P",
    "gn:feature_code":"PPL",
    "gn:name":"San Jacinto",
    "gn:population":0,
    "gn:timezone":"America/Caracas",
    "iso:country":"VE",
    "name:ceb_x_preferred":[
        "San Jacinto"
    ],
    "name:ces_x_preferred":[
        "San Jacinto"
    ],
    "name:deu_x_preferred":[
        "San Jacinto"
    ],
    "name:fas_x_preferred":[
        "\u0633\u0646 \u062c\u0627\u0633\u06cc\u0646\u062a\u0648"
    ],
    "name:fra_x_preferred":[
        "San Jacinto"
    ],
    "name:ilo_x_preferred":[
        "San Jacinto"
    ],
    "name:ita_x_preferred":[
        "San Jacinto"
    ],
    "name:jpn_x_preferred":[
        "\u30b5\u30f3\u30b8\u30e3\u30b7\u30f3\u30c8"
    ],
    "name:nld_x_preferred":[
        "San Jacinto"
    ],
    "name:pol_x_preferred":[
        "San Jacinto"
    ],
    "name:por_x_preferred":[
        "San Jacinto"
    ],
    "name:rus_x_preferred":[
        "\u0421\u0430\u043d-\u0425\u0430\u0441\u0438\u043d\u0442\u043e"
    ],
    "name:sco_x_preferred":[
        "San Jacinto"
    ],
    "name:spa_x_preferred":[
        "San Jacinto"
    ],
    "name:swe_x_preferred":[
        "San Jacinto"
    ],
    "name:vol_x_preferred":[
        "San Jacinto"
    ],
    "name:war_x_preferred":[
        "San Jacinto"
    ],
    "wof:name":"San Jacinto",
    "wof:placetype":"locality"
},
  "geometry": {"coordinates":[-69.32262,10.09938],"type":"Point"}
}