{
  "type": "Feature",
  "properties": {
    "gn:admin1_code":"19",
    "gn:asciiname":"El Potrero",
    "gn:country_code":"VE",
    "gn:dem":414,
    "gn:feature_class":"P",
    "gn:feature_code":"PPL",
    "gn:name":"El Potrero",
    "gn:population":0,
    "gn:timezone":"America/Caracas",
    "iso:country":"VE",
    "wof:name":"El Potrero",
    "wof:placetype":"locality"
},
  "geometry": {"coordinates":[-64.04246999999999,10.39198],"type":"Point"}
}