{
  "type": "Feature",
  "properties": {
    "gn:admin1_code":"4.0",
    "gn:asciiname":"Chaparral",
    "gn:country_code":"VE",
    "gn:dem":175,
    "gn:feature_class":"P",
    "gn:feature_code":"PPL",
    "gn:name":"Chaparral",
    "gn:population":0,
    "gn:timezone":"America/Caracas",
    "iso:country":"VE",
    "wof:name":"Chaparral",
    "wof:placetype":"locality"
},
  "geometry": {"coordinates":[-66.89433000000001,9.38645],"type":"Point"}
}