{
  "type": "Feature",
  "properties": {
    "gn:admin1_code":"4",
    "gn:asciiname":"El Infiernito",
    "gn:country_code":"VE",
    "gn:dem":907,
    "gn:feature_class":"P",
    "gn:feature_code":"PPL",
    "gn:name":"El Infiernito",
    "gn:population":0,
    "gn:timezone":"America/Caracas",
    "iso:country":"VE",
    "wof:name":"El Infiernito",
    "wof:placetype":"locality"
},
  "geometry": {"coordinates":[-66.8426,10.00057],"type":"Point"}
}