{
  "type": "Feature",
  "properties": {
    "gn:admin1_code":"4",
    "gn:asciiname":"El Infiernito",
    "gn:country_code":"VE",
    "gn:dem":907,
    "gn:feature_class":"P",
    "gn:feature_code":"PPL",
    "gn:name":"El Infiernito",
    "gn:population":0,
    "gn:timezone":"America/Caracas",
    "iso:country":"VE",
    "name:ita_x_preferred":[
        "El Infiernito"
    ],
    "name:rus_x_preferred":[
        "\u0410\u0440\u0445\u0435\u043e\u043b\u043e\u0433\u0438\u0447\u0435\u0441\u043a\u0438\u0439 \u043f\u0430\u0440\u043a \u041c\u043e\u043d\u043a\u0438\u0440\u0430"
    ],
    "wof:name":"El Infiernito",
    "wof:placetype":"locality"
},
  "geometry": {"coordinates":[-66.8426,10.00057],"type":"Point"}
}