{
  "type": "Feature",
  "properties": {
    "gn:admin1_code":"13",
    "gn:asciiname":"Gamelotal",
    "gn:country_code":"VE",
    "gn:dem":326,
    "gn:feature_class":"P",
    "gn:feature_code":"PPL",
    "gn:name":"Gamelotal",
    "gn:population":0,
    "gn:timezone":"America/Caracas",
    "iso:country":"VE",
    "wof:name":"Gamelotal",
    "wof:placetype":"locality"
},
  "geometry": {"coordinates":[-69.13784,9.82639],"type":"Point"}
}