{
  "type": "Feature",
  "properties": {
    "iso:country":"VE",
    "qs:gn_pop":0,
    "qs:name":"Zabala",
    "qs:name_adm0":"Venezuela",
    "qs:name_adm1":"Nueva Esparta",
    "qs:photos":1,
    "qs:photos_1k":1,
    "qs:photos_9k":1,
    "qs:photos_9r":3,
    "qs:photos_all":80,
    "qs:photos_sr":1,
    "qs:placetype":"LocalAdmin",
    "qs:pop_sr":"0",
    "qs:woe_adm0":23424982,
    "wof:name":"Zabala",
    "wof:placetype":"localadmin"
},
  "geometry": {"coordinates":[-64.016338,11.016699],"type":"Point"}
}