{
  "type": "Feature",
  "properties": {
    "gn:admin1_code":"22",
    "gn:asciiname":"Jiraquito",
    "gn:country_code":"VE",
    "gn:dem":954,
    "gn:feature_class":"P",
    "gn:feature_code":"PPL",
    "gn:name":"Jiraquito",
    "gn:population":0,
    "gn:timezone":"America/Caracas",
    "iso:country":"VE",
    "wof:name":"Jiraquito",
    "wof:placetype":"locality"
},
  "geometry": {"coordinates":[-68.52995,10.10894],"type":"Point"}
}