{
  "type": "Feature",
  "properties": {
    "gn:admin1_code":"12.0",
    "gn:asciiname":"Carutico",
    "gn:country_code":"VE",
    "gn:dem":151,
    "gn:feature_class":"P",
    "gn:feature_code":"PPLL",
    "gn:name":"Carutico",
    "gn:population":0,
    "gn:timezone":"America/Caracas",
    "iso:country":"VE",
    "wof:name":"Carutico",
    "wof:placetype":"locality"
},
  "geometry": {"coordinates":[-65.89135999999999,9.05573],"type":"Point"}
}