{
  "type": "Feature",
  "properties": {
    "gn:admin1_code":"12",
    "gn:asciiname":"Carrizal",
    "gn:country_code":"VE",
    "gn:dem":209,
    "gn:feature_class":"P",
    "gn:feature_code":"PPL",
    "gn:name":"Carrizal",
    "gn:population":0,
    "gn:timezone":"America/Caracas",
    "iso:country":"VE",
    "name:ceb_x_preferred":[
        "Carrizal"
    ],
    "name:fra_x_preferred":[
        "Carrizal"
    ],
    "name:ita_x_preferred":[
        "Carrizal"
    ],
    "name:jpn_x_preferred":[
        "\u30ab\u30ea\u30b5\u30eb"
    ],
    "name:mlg_x_preferred":[
        "Carrizal"
    ],
    "name:por_x_preferred":[
        "Carrizal"
    ],
    "name:rus_x_preferred":[
        "\u041a\u0430\u0440\u0440\u0438\u0441\u0430\u043b\u044c"
    ],
    "name:spa_x_preferred":[
        "Carrizal"
    ],
    "name:swe_x_preferred":[
        "Carrizal"
    ],
    "wof:name":"Carrizal",
    "wof:placetype":"locality"
},
  "geometry": {"coordinates":[-66.94877,9.36161],"type":"Point"}
}