{
  "type": "Feature",
  "properties": {
    "gn:admin1_code":"13",
    "gn:asciiname":"El Cucharo",
    "gn:country_code":"VE",
    "gn:dem":873,
    "gn:feature_class":"P",
    "gn:feature_code":"PPL",
    "gn:name":"El Cucharo",
    "gn:population":0,
    "gn:timezone":"America/Caracas",
    "iso:country":"VE",
    "wof:name":"El Cucharo",
    "wof:placetype":"locality"
},
  "geometry": {"coordinates":[-69.94628,9.67453],"type":"Point"}
}