{
  "type": "Feature",
  "properties": {
    "gn:admin1_code":"7",
    "gn:asciiname":"Adjuntas",
    "gn:country_code":"VE",
    "gn:dem":581,
    "gn:feature_class":"P",
    "gn:feature_code":"PPL",
    "gn:name":"Adjuntas",
    "gn:population":0,
    "gn:timezone":"America/Caracas",
    "iso:country":"VE",
    "wof:name":"Adjuntas",
    "wof:placetype":"locality"
},
  "geometry": {"coordinates":[-67.76666999999999,10.05],"type":"Point"}
}