{
  "type": "Feature",
  "properties": {
    "gn:admin1_code":"3",
    "gn:asciiname":"Naciente",
    "gn:country_code":"VE",
    "gn:dem":81,
    "gn:feature_class":"P",
    "gn:feature_code":"PPL",
    "gn:name":"Naciente",
    "gn:population":0,
    "gn:timezone":"America/Caracas",
    "iso:country":"VE",
    "wof:name":"Naciente",
    "wof:placetype":"locality"
},
  "geometry": {"coordinates":[-69.13333,7.16667],"type":"Point"}
}