{
  "type": "Feature",
  "properties": {
    "gn:admin1_code":"15",
    "gn:asciiname":"Zandra",
    "gn:country_code":"VE",
    "gn:dem":36,
    "gn:feature_class":"P",
    "gn:feature_code":"PPL",
    "gn:name":"Zandra",
    "gn:population":0,
    "gn:timezone":"America/Caracas",
    "iso:country":"VE",
    "wof:name":"Zandra",
    "wof:placetype":"locality"
},
  "geometry": {"coordinates":[-66.25,10.21667],"type":"Point"}
}