{
  "type": "Feature",
  "properties": {
    "gn:admin1_code":"11.0",
    "gn:asciiname":"Las Casitas",
    "gn:country_code":"VE",
    "gn:dem":685,
    "gn:feature_class":"P",
    "gn:feature_code":"PPL",
    "gn:name":"Las Casitas",
    "gn:population":0,
    "gn:timezone":"America/Caracas",
    "iso:country":"VE",
    "wof:name":"Las Casitas",
    "wof:placetype":"locality"
},
  "geometry": {"coordinates":[-70.39383000000002,10.80031],"type":"Point"}
}