{
  "type": "Feature",
  "properties": {
    "gn:admin1_code":"23.0",
    "gn:asciiname":"La Estrella",
    "gn:country_code":"VE",
    "gn:dem":5,
    "gn:feature_class":"P",
    "gn:feature_code":"PPLL",
    "gn:name":"La Estrella",
    "gn:population":0,
    "gn:timezone":"America/Caracas",
    "iso:country":"VE",
    "wof:name":"La Estrella",
    "wof:placetype":"locality"
},
  "geometry": {"coordinates":[-71.74616,10.3898],"type":"Point"}
}