{
  "type": "Feature",
  "properties": {
    "gn:admin1_code":"11",
    "gn:asciiname":"San Vicente",
    "gn:country_code":"VE",
    "gn:dem":58,
    "gn:feature_class":"P",
    "gn:feature_code":"PPL",
    "gn:name":"San Vicente",
    "gn:population":0,
    "gn:timezone":"America/Caracas",
    "iso:country":"VE",
    "wof:name":"San Vicente",
    "wof:placetype":"locality"
},
  "geometry": {"coordinates":[-70.09350000000001,11.9359],"type":"Point"}
}