{
  "type": "Feature",
  "properties": {
    "gn:admin1_code":"08",
    "gn:asciiname":"Valle Hondo",
    "gn:country_code":"VE",
    "gn:dem":271,
    "gn:feature_class":"P",
    "gn:feature_code":"PPL",
    "gn:name":"Valle Hondo",
    "gn:population":0,
    "gn:timezone":"America/Caracas",
    "iso:country":"VE",
    "wof:name":"Valle Hondo",
    "wof:placetype":"locality"
},
  "geometry": {"coordinates":[-68.57680000000001,9.74593],"type":"Point"}
}