{
  "type": "Feature",
  "properties": {
    "gn:admin1_code":"2",
    "gn:asciiname":"El Roble",
    "gn:country_code":"VE",
    "gn:dem":199,
    "gn:feature_class":"P",
    "gn:feature_code":"PPL",
    "gn:name":"El Roble",
    "gn:population":0,
    "gn:timezone":"America/Caracas",
    "iso:country":"VE",
    "name:ceb_x_preferred":[
        "El Roble"
    ],
    "name:fra_x_preferred":[
        "El Roble"
    ],
    "name:ita_x_preferred":[
        "El Roble"
    ],
    "name:nld_x_preferred":[
        "El Roble"
    ],
    "name:srp_x_preferred":[
        "\u0415\u043b \u0420\u043e\u0431\u043b\u0435"
    ],
    "name:swe_x_preferred":[
        "El Roble"
    ],
    "wof:name":"El Roble",
    "wof:placetype":"locality"
},
  "geometry": {"coordinates":[-64.53333000000001,9.43333],"type":"Point"}
}