{
  "type": "Feature",
  "properties": {
    "gn:admin1_code":"12.0",
    "gn:asciiname":"Dividival",
    "gn:country_code":"VE",
    "gn:dem":38,
    "gn:feature_class":"P",
    "gn:feature_code":"PPL",
    "gn:name":"Dividival",
    "gn:population":0,
    "gn:timezone":"America/Caracas",
    "iso:country":"VE",
    "wof:name":"Dividival",
    "wof:placetype":"locality"
},
  "geometry": {"coordinates":[-66.65425,7.76837],"type":"Point"}
}