{
  "type": "Feature",
  "properties": {
    "gn:admin1_code":"15",
    "gn:asciiname":"El Quebradon",
    "gn:country_code":"VE",
    "gn:dem":553,
    "gn:feature_class":"P",
    "gn:feature_code":"PPL",
    "gn:name":"El Quebrad\u00f3n",
    "gn:population":0,
    "gn:timezone":"America/Caracas",
    "iso:country":"VE",
    "wof:name":"El Quebradon",
    "wof:placetype":"locality"
},
  "geometry": {"coordinates":[-65.86608000000001,9.98885],"type":"Point"}
}