{
  "type": "Feature",
  "properties": {
    "gn:admin1_code":"2",
    "gn:asciiname":"El Corozo",
    "gn:country_code":"VE",
    "gn:dem":327,
    "gn:feature_class":"P",
    "gn:feature_code":"PPL",
    "gn:name":"El Corozo",
    "gn:population":0,
    "gn:timezone":"America/Caracas",
    "iso:country":"VE",
    "wof:name":"El Corozo",
    "wof:placetype":"locality"
},
  "geometry": {"coordinates":[-64.28865,9.58566],"type":"Point"}
}