{
  "type": "Feature",
  "properties": {
    "gn:admin1_code":"4",
    "gn:asciiname":"La Cesiva",
    "gn:country_code":"VE",
    "gn:dem":319,
    "gn:feature_class":"P",
    "gn:feature_code":"PPL",
    "gn:name":"La Cesiva",
    "gn:population":0,
    "gn:timezone":"America/Caracas",
    "iso:country":"VE",
    "wof:name":"La Cesiva",
    "wof:placetype":"locality"
},
  "geometry": {"coordinates":[-67.58528000000001,10.46667],"type":"Point"}
}