{
  "type": "Feature",
  "properties": {
    "gn:admin1_code":"1.0",
    "gn:asciiname":"Tushava",
    "gn:country_code":"VE",
    "gn:dem":911,
    "gn:feature_class":"P",
    "gn:feature_code":"PPL",
    "gn:name":"Tushava",
    "gn:population":0,
    "gn:timezone":"America/Caracas",
    "iso:country":"VE",
    "wof:name":"Tushava",
    "wof:placetype":"locality"
},
  "geometry": {"coordinates":[-64.73165,1.3545],"type":"Point"}
}