{
  "type": "Feature",
  "properties": {
    "gn:admin1_code":"7",
    "gn:asciiname":"Guere",
    "gn:country_code":"VE",
    "gn:dem":501,
    "gn:feature_class":"P",
    "gn:feature_code":"PPL",
    "gn:name":"G\u00fcere",
    "gn:population":0,
    "gn:timezone":"America/Caracas",
    "iso:country":"VE",
    "wof:name":"Guere",
    "wof:placetype":"locality"
},
  "geometry": {"coordinates":[-68.01666999999999,10.25],"type":"Point"}
}