{
  "type": "Feature",
  "properties": {
    "gn:admin1_code":"5",
    "gn:asciiname":"Filo Viejo",
    "gn:country_code":"VE",
    "gn:dem":265,
    "gn:feature_class":"P",
    "gn:feature_code":"PPL",
    "gn:name":"Filo Viejo",
    "gn:population":0,
    "gn:timezone":"America/Caracas",
    "iso:country":"VE",
    "wof:name":"Filo Viejo",
    "wof:placetype":"locality"
},
  "geometry": {"coordinates":[-70.15000000000001,8.91667],"type":"Point"}
}