{
  "type": "Feature",
  "properties": {
    "gn:admin1_code":"15",
    "gn:asciiname":"Navaja",
    "gn:country_code":"VE",
    "gn:dem":544,
    "gn:feature_class":"P",
    "gn:feature_code":"PPL",
    "gn:name":"Navaja",
    "gn:population":0,
    "gn:timezone":"America/Caracas",
    "iso:country":"VE",
    "name:deu_x_preferred":[
        "Navaja"
    ],
    "name:ita_x_preferred":[
        "Navaja"
    ],
    "name:pol_x_preferred":[
        "Navaja"
    ],
    "name:rus_x_preferred":[
        "\u041d\u0430\u0432\u0430\u0445\u0430"
    ],
    "name:tur_x_preferred":[
        "Navaja"
    ],
    "name:ukr_x_preferred":[
        "\u041d\u0430\u0432\u0430\u0445\u0430"
    ],
    "wof:name":"Navaja",
    "wof:placetype":"locality"
},
  "geometry": {"coordinates":[-66.46544,10.28896],"type":"Point"}
}