{
  "type": "Feature",
  "properties": {
    "gn:admin1_code":"5",
    "gn:asciiname":"Guasimito",
    "gn:country_code":"VE",
    "gn:dem":63,
    "gn:feature_class":"P",
    "gn:feature_code":"PPL",
    "gn:name":"Guasimito",
    "gn:population":0,
    "gn:timezone":"America/Caracas",
    "iso:country":"VE",
    "wof:name":"Guasimito",
    "wof:placetype":"locality"
},
  "geometry": {"coordinates":[-68.45,8.33333],"type":"Point"}
}