{
  "type": "Feature",
  "properties": {
    "gn:admin1_code":"3",
    "gn:asciiname":"El Pescado",
    "gn:cc2":"VE",
    "gn:country_code":"VE",
    "gn:dem":49,
    "gn:feature_class":"P",
    "gn:feature_code":"PPL",
    "gn:name":"El Pescado",
    "gn:population":0,
    "gn:timezone":"America/Caracas",
    "iso:country":"VE",
    "name:und_x_variant":[
        "Pescado",
        "El Pescado"
    ],
    "wof:name":"El Pescado",
    "wof:placetype":"locality"
},
  "geometry": {"coordinates":[-67.65000000000001,7.73333],"type":"Point"}
}