{
  "type": "Feature",
  "properties": {
    "gn:admin1_code":"19",
    "gn:asciiname":"Quebrada Honda",
    "gn:country_code":"VE",
    "gn:dem":194,
    "gn:feature_class":"P",
    "gn:feature_code":"PPL",
    "gn:name":"Quebrada Honda",
    "gn:population":0,
    "gn:timezone":"America/Caracas",
    "iso:country":"VE",
    "wof:name":"Quebrada Honda",
    "wof:placetype":"locality"
},
  "geometry": {"coordinates":[-63.15776999999999,10.41091],"type":"Point"}
}