{
  "type": "Feature",
  "properties": {
    "gn:admin1_code":"4",
    "gn:asciiname":"El Guarenal",
    "gn:cc2":"VE",
    "gn:country_code":"VE",
    "gn:dem":415,
    "gn:feature_class":"P",
    "gn:feature_code":"PPL",
    "gn:name":"El Guarenal",
    "gn:population":0,
    "gn:timezone":"America/Caracas",
    "iso:country":"VE",
    "name:und_x_variant":[
        "Guarenas",
        "El Guarenal"
    ],
    "wof:name":"El Guarenal",
    "wof:placetype":"locality"
},
  "geometry": {"coordinates":[-67.59999999999999,10.43333],"type":"Point"}
}