{
  "type": "Feature",
  "properties": {
    "gn:admin1_code":"12",
    "gn:asciiname":"Juncalito",
    "gn:country_code":"VE",
    "gn:dem":279,
    "gn:feature_class":"P",
    "gn:feature_code":"PPL",
    "gn:name":"Juncalito",
    "gn:population":0,
    "gn:timezone":"America/Caracas",
    "iso:country":"VE",
    "wof:name":"Juncalito",
    "wof:placetype":"locality"
},
  "geometry": {"coordinates":[-67.36001,9.79007],"type":"Point"}
}