{
  "type": "Feature",
  "properties": {
    "gn:admin1_code":"02",
    "gn:asciiname":"Capaya",
    "gn:country_code":"VE",
    "gn:dem":138,
    "gn:feature_class":"P",
    "gn:feature_code":"PPL",
    "gn:name":"Capaya",
    "gn:population":0,
    "gn:timezone":"America/Caracas",
    "iso:country":"VE",
    "name:und_x_variant":[
        "San Antonio",
        "Capalla",
        "San Antonio de Capaya",
        "Capaya"
    ],
    "wof:name":"Capaya",
    "wof:placetype":"locality"
},
  "geometry": {"coordinates":[-64.39808000000001,9.96405],"type":"Point"}
}