{
  "type": "Feature",
  "properties": {
    "gn:admin1_code":"20",
    "gn:asciiname":"Villa Paez",
    "gn:country_code":"VE",
    "gn:dem":2050,
    "gn:feature_class":"P",
    "gn:feature_code":"PPL",
    "gn:name":"Villa P\u00e1ez",
    "gn:population":0,
    "gn:timezone":"America/Caracas",
    "iso:country":"VE",
    "wof:name":"Villa Paez",
    "wof:placetype":"locality"
},
  "geometry": {"coordinates":[-72.45907,7.48978],"type":"Point"}
}