{
  "type": "Feature",
  "properties": {
    "gn:admin1_code":"15.0",
    "gn:asciiname":"Los Amarillos",
    "gn:country_code":"VE",
    "gn:dem":568,
    "gn:feature_class":"P",
    "gn:feature_code":"PPLL",
    "gn:name":"Los Amarillos",
    "gn:population":0,
    "gn:timezone":"America/Caracas",
    "iso:country":"VE",
    "wof:name":"Los Amarillos",
    "wof:placetype":"locality"
},
  "geometry": {"coordinates":[-67.0407,10.28324],"type":"Point"}
}