{
  "type": "Feature",
  "properties": {
    "gn:admin1_code":"5",
    "gn:asciiname":"El Cinal",
    "gn:country_code":"VE",
    "gn:dem":126,
    "gn:feature_class":"P",
    "gn:feature_code":"PPL",
    "gn:name":"El Cinal",
    "gn:population":0,
    "gn:timezone":"America/Caracas",
    "iso:country":"VE",
    "wof:name":"El Cinal",
    "wof:placetype":"locality"
},
  "geometry": {"coordinates":[-70.20121,8.20257],"type":"Point"}
}