{
  "type": "Feature",
  "properties": {
    "gn:admin1_code":"6.0",
    "gn:asciiname":"El Machete",
    "gn:country_code":"VE",
    "gn:dem":33,
    "gn:feature_class":"P",
    "gn:feature_code":"PPL",
    "gn:name":"El Machete",
    "gn:population":0,
    "gn:timezone":"America/Caracas",
    "iso:country":"VE",
    "wof:name":"El Machete",
    "wof:placetype":"locality"
},
  "geometry": {"coordinates":[-65.76444000000001,7.36222],"type":"Point"}
}