{
  "type": "Feature",
  "properties": {
    "gn:admin1_code":"2",
    "gn:asciiname":"El Oscurito",
    "gn:country_code":"VE",
    "gn:dem":180,
    "gn:feature_class":"P",
    "gn:feature_code":"PPL",
    "gn:name":"El Oscurito",
    "gn:population":0,
    "gn:timezone":"America/Caracas",
    "iso:country":"VE",
    "wof:name":"El Oscurito",
    "wof:placetype":"locality"
},
  "geometry": {"coordinates":[-64.77353000000001,8.55169],"type":"Point"}
}