{
  "type": "Feature",
  "properties": {
    "gn:admin1_code":"16",
    "gn:asciiname":"Masacua",
    "gn:country_code":"VE",
    "gn:dem":198,
    "gn:feature_class":"P",
    "gn:feature_code":"PPL",
    "gn:name":"Masacua",
    "gn:population":0,
    "gn:timezone":"America/Caracas",
    "iso:country":"VE",
    "wof:name":"Masacua",
    "wof:placetype":"locality"
},
  "geometry": {"coordinates":[-63.66195,9.6951],"type":"Point"}
}