{
  "type": "Feature",
  "properties": {
    "gn:admin1_code":"16",
    "gn:asciiname":"El Paramo",
    "gn:country_code":"VE",
    "gn:dem":1247,
    "gn:feature_class":"P",
    "gn:feature_code":"PPL",
    "gn:name":"El P\u00e1ramo",
    "gn:population":0,
    "gn:timezone":"America/Caracas",
    "iso:country":"VE",
    "wof:name":"El Paramo",
    "wof:placetype":"locality"
},
  "geometry": {"coordinates":[-63.4897,10.22454],"type":"Point"}
}