{
  "type": "Feature",
  "properties": {
    "gn:admin1_code":"16",
    "gn:asciiname":"Guarauno",
    "gn:country_code":"VE",
    "gn:dem":539,
    "gn:feature_class":"P",
    "gn:feature_code":"PPL",
    "gn:name":"Guara\u00fano",
    "gn:population":0,
    "gn:timezone":"America/Caracas",
    "iso:country":"VE",
    "wof:name":"Guarauno",
    "wof:placetype":"locality"
},
  "geometry": {"coordinates":[-63.92507,9.94734],"type":"Point"}
}