{
  "type": "Feature",
  "properties": {
    "gn:admin1_code":"02",
    "gn:asciiname":"La Erica",
    "gn:country_code":"VE",
    "gn:dem":43,
    "gn:feature_class":"P",
    "gn:feature_code":"PPLL",
    "gn:name":"La Erica",
    "gn:population":0,
    "gn:timezone":"America/Caracas",
    "iso:country":"VE",
    "wof:name":"La Erica",
    "wof:placetype":"locality"
},
  "geometry": {"coordinates":[-65.05614,9.78192],"type":"Point"}
}