{
  "type": "Feature",
  "properties": {
    "gn:admin1_code":"11.0",
    "gn:asciiname":"La Loma de Jusal",
    "gn:country_code":"VE",
    "gn:dem":627,
    "gn:feature_class":"P",
    "gn:feature_code":"PPLL",
    "gn:name":"La Loma de Jusal",
    "gn:population":0,
    "gn:timezone":"America/Caracas",
    "iso:country":"VE",
    "wof:name":"La Loma de Jusal",
    "wof:placetype":"locality"
},
  "geometry": {"coordinates":[-69.46333,10.74],"type":"Point"}
}