{
  "type": "Feature",
  "properties": {
    "gn:admin1_code":"19.0",
    "gn:asciiname":"Cerro del Diablo",
    "gn:country_code":"VE",
    "gn:dem":67,
    "gn:feature_class":"P",
    "gn:feature_code":"PPL",
    "gn:name":"Cerro del Diablo",
    "gn:population":0,
    "gn:timezone":"America/Caracas",
    "iso:country":"VE",
    "wof:name":"Cerro del Diablo",
    "wof:placetype":"locality"
},
  "geometry": {"coordinates":[-62.38824,10.61504],"type":"Point"}
}