{
  "type": "Feature",
  "properties": {
    "gn:admin1_code":"18",
    "gn:asciiname":"Camburito",
    "gn:country_code":"VE",
    "gn:dem":295,
    "gn:feature_class":"P",
    "gn:feature_code":"PPL",
    "gn:name":"Camburito",
    "gn:population":0,
    "gn:timezone":"America/Caracas",
    "iso:country":"VE",
    "wof:name":"Camburito",
    "wof:placetype":"locality"
},
  "geometry": {"coordinates":[-69.32023000000001,9.59754],"type":"Point"}
}