{
  "type": "Feature",
  "properties": {
    "gn:admin1_code":"6.0",
    "gn:asciiname":"Chaviripa",
    "gn:country_code":"VE",
    "gn:dem":22,
    "gn:feature_class":"P",
    "gn:feature_code":"PPL",
    "gn:name":"Chaviripa",
    "gn:population":0,
    "gn:timezone":"America/Caracas",
    "iso:country":"VE",
    "wof:name":"Chaviripa",
    "wof:placetype":"locality"
},
  "geometry": {"coordinates":[-66.55946,7.31642],"type":"Point"}
}