{
  "type": "Feature",
  "properties": {
    "gn:admin1_code":"11",
    "gn:asciiname":"La Fila",
    "gn:country_code":"VE",
    "gn:dem":915,
    "gn:feature_class":"P",
    "gn:feature_code":"PPL",
    "gn:name":"La Fila",
    "gn:population":0,
    "gn:timezone":"America/Caracas",
    "iso:country":"VE",
    "wof:name":"La Fila",
    "wof:placetype":"locality"
},
  "geometry": {"coordinates":[-69.18313000000001,10.8246],"type":"Point"}
}