{
  "type": "Feature",
  "properties": {
    "gn:admin1_code":"11",
    "gn:asciiname":"Campo Elias",
    "gn:country_code":"VE",
    "gn:dem":764,
    "gn:feature_class":"P",
    "gn:feature_code":"PPL",
    "gn:name":"Campo El\u00edas",
    "gn:population":0,
    "gn:timezone":"America/Caracas",
    "iso:country":"VE",
    "wof:name":"Campo Elias",
    "wof:placetype":"locality"
},
  "geometry": {"coordinates":[-69.76325,10.79148],"type":"Point"}
}