{
  "type": "Feature",
  "properties": {
    "gn:admin1_code":"19.0",
    "gn:asciiname":"Cerro Tapasol",
    "gn:country_code":"VE",
    "gn:dem":1526,
    "gn:feature_class":"P",
    "gn:feature_code":"PPLL",
    "gn:name":"Cerro Tapasol",
    "gn:population":0,
    "gn:timezone":"America/Caracas",
    "iso:country":"VE",
    "wof:name":"Cerro Tapasol",
    "wof:placetype":"locality"
},
  "geometry": {"coordinates":[-64.07778,10.12056],"type":"Point"}
}