{
  "type": "Feature",
  "properties": {
    "gn:admin1_code":"14",
    "gn:asciiname":"Las Vegas",
    "gn:country_code":"VE",
    "gn:dem":1455,
    "gn:feature_class":"P",
    "gn:feature_code":"PPL",
    "gn:name":"Las Vegas",
    "gn:population":0,
    "gn:timezone":"America/Caracas",
    "iso:country":"VE",
    "wof:name":"Las Vegas",
    "wof:placetype":"locality"
},
  "geometry": {"coordinates":[-71.72483000000003,8.1529],"type":"Point"}
}