{
  "type": "Feature",
  "properties": {
    "gn:admin1_code":"19.0",
    "gn:asciiname":"Palosanal",
    "gn:country_code":"VE",
    "gn:dem":524,
    "gn:feature_class":"P",
    "gn:feature_code":"PPL",
    "gn:name":"Palosanal",
    "gn:population":0,
    "gn:timezone":"America/Caracas",
    "iso:country":"VE",
    "wof:name":"Palosanal",
    "wof:placetype":"locality"
},
  "geometry": {"coordinates":[-63.33586,10.53271],"type":"Point"}
}