{
  "type": "Feature",
  "properties": {
    "gn:admin1_code":"12",
    "gn:asciiname":"Loma de Piedra",
    "gn:country_code":"VE",
    "gn:dem":199,
    "gn:feature_class":"P",
    "gn:feature_code":"PPL",
    "gn:name":"Loma de Piedra",
    "gn:population":0,
    "gn:timezone":"America/Caracas",
    "iso:country":"VE",
    "wof:name":"Loma de Piedra",
    "wof:placetype":"locality"
},
  "geometry": {"coordinates":[-65.90873000000001,9.1876],"type":"Point"}
}