{
  "type": "Feature",
  "properties": {
    "gn:admin1_code":"12.0",
    "gn:asciiname":"Cano del Medio",
    "gn:country_code":"VE",
    "gn:dem":139,
    "gn:feature_class":"P",
    "gn:feature_code":"PPLL",
    "gn:name":"Ca\u00f1o del Medio",
    "gn:population":0,
    "gn:timezone":"America/Caracas",
    "iso:country":"VE",
    "wof:name":"Cano del Medio",
    "wof:placetype":"locality"
},
  "geometry": {"coordinates":[-65.32415,8.70214],"type":"Point"}
}