{
  "type": "Feature",
  "properties": {
    "gn:admin1_code":"15.0",
    "gn:asciiname":"Maya",
    "gn:country_code":"VE",
    "gn:dem":961,
    "gn:feature_class":"P",
    "gn:feature_code":"PPLL",
    "gn:name":"Maya",
    "gn:population":0,
    "gn:timezone":"America/Caracas",
    "iso:country":"VE",
    "wof:name":"Maya",
    "wof:placetype":"locality"
},
  "geometry": {"coordinates":[-66.86296,10.45691],"type":"Point"}
}