{
  "type": "Feature",
  "properties": {
    "gn:admin1_code":"11",
    "gn:asciiname":"Quebrada Seca",
    "gn:country_code":"VE",
    "gn:dem":894,
    "gn:feature_class":"P",
    "gn:feature_code":"PPL",
    "gn:name":"Quebrada Seca",
    "gn:population":0,
    "gn:timezone":"America/Caracas",
    "iso:country":"VE",
    "wof:name":"Quebrada Seca",
    "wof:placetype":"locality"
},
  "geometry": {"coordinates":[-69.26689,10.79238],"type":"Point"}
}