{
  "type": "Feature",
  "properties": {
    "gn:admin1_code":"12",
    "gn:asciiname":"Esteves",
    "gn:country_code":"VE",
    "gn:dem":182,
    "gn:feature_class":"P",
    "gn:feature_code":"PPL",
    "gn:name":"Esteves",
    "gn:population":0,
    "gn:timezone":"America/Caracas",
    "iso:country":"VE",
    "wof:name":"Esteves",
    "wof:placetype":"locality"
},
  "geometry": {"coordinates":[-67.60556,9.54556],"type":"Point"}
}