{
  "type": "Feature",
  "properties": {
    "gn:admin1_code":"15",
    "gn:asciiname":"La Fundacion",
    "gn:country_code":"VE",
    "gn:dem":344,
    "gn:feature_class":"P",
    "gn:feature_code":"PPL",
    "gn:name":"La Fundaci\u00f3n",
    "gn:population":0,
    "gn:timezone":"America/Caracas",
    "iso:country":"VE",
    "wof:name":"La Fundacion",
    "wof:placetype":"locality"
},
  "geometry": {"coordinates":[-66.59393,10.46413],"type":"Point"}
}