{
  "type": "Feature",
  "properties": {
    "iso:country":"VE",
    "name:deu_x_preferred":[
        "Chuao"
    ],
    "name:fra_x_preferred":[
        "Chuao"
    ],
    "name:spa_x_preferred":[
        "Chuao"
    ],
    "qs:gn_pop":0,
    "qs:name":"Chuao",
    "qs:name_adm0":"Venezuela",
    "qs:name_adm1":"Aragua",
    "qs:photos":2,
    "qs:photos_1k":1,
    "qs:photos_9k":1,
    "qs:photos_9r":4,
    "qs:photos_all":255,
    "qs:photos_sr":1,
    "qs:placetype":"LocalAdmin",
    "qs:pop_sr":"0",
    "qs:woe_adm0":23424982,
    "wof:name":"Chuao",
    "wof:placetype":"localadmin"
},
  "geometry": {"coordinates":[-67.54174,10.521146],"type":"Point"}
}