{
  "type": "Feature",
  "properties": {
    "gn:admin1_code":"13",
    "gn:asciiname":"Corobore Abajo",
    "gn:country_code":"VE",
    "gn:dem":338,
    "gn:feature_class":"P",
    "gn:feature_code":"PPLL",
    "gn:name":"Corobore Abajo",
    "gn:population":0,
    "gn:timezone":"America/Caracas",
    "iso:country":"VE",
    "wof:name":"Corobore Abajo",
    "wof:placetype":"locality"
},
  "geometry": {"coordinates":[-69.76408000000001,10.45268],"type":"Point"}
}