{
  "type": "Feature",
  "properties": {
    "gn:admin1_code":"12.0",
    "gn:asciiname":"Valle de Macaira",
    "gn:country_code":"VE",
    "gn:dem":495,
    "gn:feature_class":"P",
    "gn:feature_code":"PPL",
    "gn:name":"Valle de Macaira",
    "gn:population":0,
    "gn:timezone":"America/Caracas",
    "iso:country":"VE",
    "wof:name":"Valle de Macaira",
    "wof:placetype":"locality"
},
  "geometry": {"coordinates":[-66.26261,9.95076],"type":"Point"}
}