{
  "type": "Feature",
  "properties": {
    "gn:admin1_code":"8.0",
    "gn:asciiname":"Mango Redondo",
    "gn:country_code":"VE",
    "gn:dem":194,
    "gn:feature_class":"P",
    "gn:feature_code":"PPL",
    "gn:name":"Mango Redondo",
    "gn:population":0,
    "gn:timezone":"America/Caracas",
    "iso:country":"VE",
    "wof:name":"Mango Redondo",
    "wof:placetype":"locality"
},
  "geometry": {"coordinates":[-68.52846,9.73303],"type":"Point"}
}