{
  "type": "Feature",
  "properties": {
    "gn:admin1_code":"23",
    "gn:asciiname":"La Linea",
    "gn:country_code":"VE",
    "gn:dem":64,
    "gn:feature_class":"P",
    "gn:feature_code":"PPL",
    "gn:name":"La L\u00ednea",
    "gn:population":0,
    "gn:timezone":"America/Caracas",
    "iso:country":"VE",
    "name:ceb_x_preferred":[
        "La Linea"
    ],
    "name:deu_x_preferred":[
        "La Linea"
    ],
    "name:ita_x_preferred":[
        "La Linea"
    ],
    "name:nld_x_preferred":[
        "La Linea"
    ],
    "name:spa_x_preferred":[
        "La l\u00ednea"
    ],
    "name:srp_x_preferred":[
        "\u041b\u0430 \u041b\u0438\u043d\u0435\u0430"
    ],
    "name:swe_x_preferred":[
        "La Linea"
    ],
    "wof:name":"La Linea",
    "wof:placetype":"locality"
},
  "geometry": {"coordinates":[-72.50887,8.79311],"type":"Point"}
}