{
  "type": "Feature",
  "properties": {
    "gn:admin1_code":"16",
    "gn:asciiname":"Bajada La Chaguarama",
    "gn:cc2":"VE",
    "gn:country_code":"VE",
    "gn:dem":327,
    "gn:feature_class":"P",
    "gn:feature_code":"PPL",
    "gn:name":"Bajada La Chaguarama",
    "gn:population":0,
    "gn:timezone":"America/Caracas",
    "iso:country":"VE",
    "name:und_x_variant":[
        "La Chagurama",
        "Chaguarama",
        "La Chaguarama",
        "Bajada La Chaguarama"
    ],
    "wof:name":"Bajada La Chaguarama",
    "wof:placetype":"locality"
},
  "geometry": {"coordinates":[-64.0325,9.34444],"type":"Point"}
}