{
  "type": "Feature",
  "properties": {
    "gn:admin1_code":"12.0",
    "gn:asciiname":"Queseras",
    "gn:country_code":"VE",
    "gn:dem":141,
    "gn:feature_class":"P",
    "gn:feature_code":"PPLL",
    "gn:name":"Queseras",
    "gn:population":0,
    "gn:timezone":"America/Caracas",
    "iso:country":"VE",
    "wof:name":"Queseras",
    "wof:placetype":"locality"
},
  "geometry": {"coordinates":[-67.75636,9.55278],"type":"Point"}
}