{
  "type": "Feature",
  "properties": {
    "gn:admin1_code":"15",
    "gn:asciiname":"Rebelon",
    "gn:country_code":"VE",
    "gn:dem":84,
    "gn:feature_class":"P",
    "gn:feature_code":"PPL",
    "gn:name":"Rebel\u00f3n",
    "gn:population":0,
    "gn:timezone":"America/Caracas",
    "iso:country":"VE",
    "wof:name":"Rebelon",
    "wof:placetype":"locality"
},
  "geometry": {"coordinates":[-65.63333,10.11181],"type":"Point"}
}