{
  "type": "Feature",
  "properties": {
    "gn:admin1_code":"18.0",
    "gn:asciiname":"La Mesa del Toco",
    "gn:country_code":"VE",
    "gn:dem":984,
    "gn:feature_class":"P",
    "gn:feature_code":"PPL",
    "gn:name":"La Mesa del Toco",
    "gn:population":0,
    "gn:timezone":"America/Caracas",
    "iso:country":"VE",
    "name:spa_x_preferred":[
        "La Mesa del Toco"
    ],
    "wof:name":"La Mesa del Toco",
    "wof:placetype":"locality"
},
  "geometry": {"coordinates":[-69.57148000000001,9.42926],"type":"Point"}
}