{
  "type": "Feature",
  "properties": {
    "gn:admin1_code":"02",
    "gn:asciiname":"Botalon del Paso la Tigra",
    "gn:country_code":"VE",
    "gn:dem":190,
    "gn:feature_class":"P",
    "gn:feature_code":"PPLL",
    "gn:name":"Botal\u00f3n del Paso la Tigra",
    "gn:population":0,
    "gn:timezone":"America/Caracas",
    "iso:country":"VE",
    "wof:name":"Botalon del Paso la Tigra",
    "wof:placetype":"locality"
},
  "geometry": {"coordinates":[-65.62222,9.60167],"type":"Point"}
}