{
  "type": "Feature",
  "properties": {
    "gn:admin1_code":"19.0",
    "gn:asciiname":"La Cumbre Mariano Leon",
    "gn:country_code":"VE",
    "gn:dem":477,
    "gn:feature_class":"P",
    "gn:feature_code":"PPL",
    "gn:name":"La Cumbre Mariano Le\u00f3n",
    "gn:population":0,
    "gn:timezone":"America/Caracas",
    "iso:country":"VE",
    "wof:name":"La Cumbre Mariano Leon",
    "wof:placetype":"locality"
},
  "geometry": {"coordinates":[-63.06536,10.60793],"type":"Point"}
}