{
  "type": "Feature",
  "properties": {
    "gn:admin1_code":"5",
    "gn:asciiname":"Corozal",
    "gn:country_code":"VE",
    "gn:dem":87,
    "gn:feature_class":"P",
    "gn:feature_code":"PPL",
    "gn:name":"Corozal",
    "gn:population":0,
    "gn:timezone":"America/Caracas",
    "iso:country":"VE",
    "name:ceb_x_preferred":[
        "Corozal"
    ],
    "name:deu_x_preferred":[
        "Corozal"
    ],
    "name:fra_x_preferred":[
        "Corozal"
    ],
    "name:ita_x_preferred":[
        "Corozal"
    ],
    "name:nds_x_preferred":[
        "Corozal"
    ],
    "name:nld_x_preferred":[
        "Corozal"
    ],
    "name:pol_x_preferred":[
        "Corozal"
    ],
    "name:por_x_preferred":[
        "Corozal"
    ],
    "name:rus_x_preferred":[
        "\u041a\u043e\u0440\u043e\u0441\u0430\u043b\u044c"
    ],
    "name:spa_x_preferred":[
        "Corozal"
    ],
    "name:swe_x_preferred":[
        "Corozal"
    ],
    "name:ukr_x_preferred":[
        "\u041a\u043e\u0440\u043e\u0441\u0430\u043b\u044c"
    ],
    "name:vie_x_preferred":[
        "Corozal"
    ],
    "wof:name":"Corozal",
    "wof:placetype":"locality"
},
  "geometry": {"coordinates":[-69.28553000000001,8.29455],"type":"Point"}
}