{
  "type": "Feature",
  "properties": {
    "gn:admin1_code":"5",
    "gn:asciiname":"Corozal",
    "gn:country_code":"VE",
    "gn:dem":87,
    "gn:feature_class":"P",
    "gn:feature_code":"PPL",
    "gn:name":"Corozal",
    "gn:population":0,
    "gn:timezone":"America/Caracas",
    "iso:country":"VE",
    "wof:name":"Corozal",
    "wof:placetype":"locality"
},
  "geometry": {"coordinates":[-69.28553000000001,8.29455],"type":"Point"}
}