{
  "type": "Feature",
  "properties": {
    "gn:admin1_code":"5",
    "gn:asciiname":"Mata de Bejuco",
    "gn:cc2":"VE",
    "gn:country_code":"VE",
    "gn:dem":95,
    "gn:feature_class":"P",
    "gn:feature_code":"PPL",
    "gn:name":"Mata de Bejuco",
    "gn:population":0,
    "gn:timezone":"America/Caracas",
    "iso:country":"VE",
    "name:und_x_variant":[
        "Mata Bejuco",
        "Mata de Bejuco"
    ],
    "wof:name":"Mata de Bejuco",
    "wof:placetype":"locality"
},
  "geometry": {"coordinates":[-69.34999999999999,8.46667],"type":"Point"}
}