{
  "type": "Feature",
  "properties": {
    "iso:country":"VE",
    "name:ara_x_preferred":[
        "\u0628\u0627\u0631\u064a\u0646\u0627\u0633"
    ],
    "name:arg_x_preferred":[
        "Barinas"
    ],
    "name:bul_x_preferred":[
        "\u0411\u0430\u0440\u0438\u043d\u0430\u0441"
    ],
    "name:deu_x_preferred":[
        "Barinas"
    ],
    "name:ell_x_preferred":[
        "\u039c\u03c0\u03b1\u03c1\u03af\u03bd\u03b1\u03c2"
    ],
    "name:eng_x_preferred":[
        "Barinas"
    ],
    "name:epo_x_preferred":[
        "Barinas"
    ],
    "name:est_x_preferred":[
        "Barinas"
    ],
    "name:fas_x_preferred":[
        "\u0628\u0627\u0631\u06cc\u0646\u0627\u0633\u060c \u0628\u0627\u0631\u06cc\u0646\u0627\u0633"
    ],
    "name:fra_x_preferred":[
        "Barinas"
    ],
    "name:ita_x_preferred":[
        "Barinas"
    ],
    "name:kat_x_preferred":[
        "\u10d1\u10d0\u10e0\u10d8\u10dc\u10d0\u10e1\u10d8"
    ],
    "name:kor_x_preferred":[
        "\ubc14\ub9ac\ub098\uc2a4"
    ],
    "name:lit_x_preferred":[
        "Barinasas"
    ],
    "name:nld_x_preferred":[
        "Barinas"
    ],
    "name:nor_x_preferred":[
        "Barinas"
    ],
    "name:pol_x_preferred":[
        "Barinas"
    ],
    "name:por_x_preferred":[
        "Barinas"
    ],
    "name:que_x_preferred":[
        "Barinas llaqta"
    ],
    "name:ron_x_preferred":[
        "Barinas"
    ],
    "name:rus_x_preferred":[
        "\u0411\u0430\u0440\u0438\u043d\u0430\u0441"
    ],
    "name:sco_x_preferred":[
        "Barinas"
    ],
    "name:spa_x_preferred":[
        "Barinas"
    ],
    "name:swe_x_preferred":[
        "Barinas"
    ],
    "name:szl_x_preferred":[
        "Barinas"
    ],
    "name:tgk_x_preferred":[
        "\u0418\u0451\u043b\u043e\u0442\u0438 \u0411\u0430\u0440\u0438\u043d\u0430\u0441"
    ],
    "name:ukr_x_preferred":[
        "\u0411\u0430\u0440\u0438\u043d\u0430\u0441"
    ],
    "name:ukr_x_variant":[
        "\u0411\u0430\u0440\u0456\u043d\u0430\u0441"
    ],
    "name:urd_x_preferred":[
        "\u0628\u0627\u0631\u06cc\u0646\u0627\u0633\u060c \u0628\u0627\u0631\u06cc\u0646\u0627\u0633"
    ],
    "name:vol_x_preferred":[
        "Barinas"
    ],
    "name:war_x_preferred":[
        "Barinas"
    ],
    "name:zho_min_nan_x_preferred":[
        "Barinas"
    ],
    "name:zho_x_preferred":[
        "\u5df4\u91cc\u7d0d\u65af"
    ],
    "qs:gn_country":"VE",
    "qs:gn_fcode":"PPLA",
    "qs:gn_pop":0,
    "qs:name":"Barinas",
    "qs:name_adm0":"Venezuela",
    "qs:name_adm1":"Barinas",
    "qs:photos":114,
    "qs:photos_1k":23,
    "qs:photos_9k":3,
    "qs:photos_9r":5,
    "qs:photos_all":728,
    "qs:photos_sr":3,
    "qs:placetype":"LocalAdmin",
    "qs:pop_sr":"0",
    "qs:woe_adm0":23424982,
    "wd:elevation":187.0,
    "wd:wordcount":497,
    "wof:name":"Barinas",
    "wof:placetype":"localadmin"
},
  "geometry": {"coordinates":[-70.20749000000001,8.62261],"type":"Point"}
}