{
  "type": "Feature",
  "properties": {
    "gn:admin1_code":"1",
    "gn:asciiname":"Lucero",
    "gn:country_code":"VE",
    "gn:dem":59,
    "gn:feature_class":"P",
    "gn:feature_code":"PPL",
    "gn:name":"Lucero",
    "gn:population":0,
    "gn:timezone":"America/Caracas",
    "iso:country":"VE",
    "name:bre_x_preferred":[
        "Lucero"
    ],
    "name:ceb_x_preferred":[
        "Lucero"
    ],
    "name:deu_x_preferred":[
        "Lucero"
    ],
    "name:ita_x_preferred":[
        "Lucero"
    ],
    "name:por_x_preferred":[
        "Lucero"
    ],
    "name:sco_x_preferred":[
        "Lucero"
    ],
    "name:spa_x_preferred":[
        "Lucero"
    ],
    "name:swe_x_preferred":[
        "Lucero"
    ],
    "wof:name":"Lucero",
    "wof:placetype":"locality"
},
  "geometry": {"coordinates":[-67.39224,5.97327],"type":"Point"}
}