{
  "type": "Feature",
  "properties": {
    "gn:admin1_code":"13",
    "gn:asciiname":"San Marino",
    "gn:country_code":"VE",
    "gn:dem":887,
    "gn:feature_class":"P",
    "gn:feature_code":"PPL",
    "gn:name":"San Marino",
    "gn:population":0,
    "gn:timezone":"America/Caracas",
    "iso:country":"VE",
    "wof:name":"San Marino",
    "wof:placetype":"locality"
},
  "geometry": {"coordinates":[-69.7191,9.74832],"type":"Point"}
}