{
  "type": "Feature",
  "properties": {
    "gn:admin1_code":"12.0",
    "gn:asciiname":"Las Dos Bocas",
    "gn:country_code":"VE",
    "gn:dem":414,
    "gn:feature_class":"P",
    "gn:feature_code":"PPL",
    "gn:name":"Las Dos Bocas",
    "gn:population":0,
    "gn:timezone":"America/Caracas",
    "iso:country":"VE",
    "wof:name":"Las Dos Bocas",
    "wof:placetype":"locality"
},
  "geometry": {"coordinates":[-67.67863,9.81115],"type":"Point"}
}