{
  "type": "Feature",
  "properties": {
    "gn:admin1_code":"3",
    "gn:asciiname":"Las Pinitas",
    "gn:cc2":"VE",
    "gn:country_code":"VE",
    "gn:dem":46,
    "gn:feature_class":"P",
    "gn:feature_code":"PPL",
    "gn:name":"Las Pi\u00f1itas",
    "gn:population":0,
    "gn:timezone":"America/Caracas",
    "iso:country":"VE",
    "name:und_x_variant":[
        "Los Pa\u00f1itos",
        "Las Pi\u00f1itas"
    ],
    "wof:name":"Las Pinitas",
    "wof:placetype":"locality"
},
  "geometry": {"coordinates":[-67.65000000000001,7.46667],"type":"Point"}
}