{
  "type": "Feature",
  "properties": {
    "gn:admin1_code":"14",
    "gn:asciiname":"Las Labranzas",
    "gn:country_code":"VE",
    "gn:dem":1710,
    "gn:feature_class":"P",
    "gn:feature_code":"PPL",
    "gn:name":"Las Labranzas",
    "gn:population":0,
    "gn:timezone":"America/Caracas",
    "iso:country":"VE",
    "wof:name":"Las Labranzas",
    "wof:placetype":"locality"
},
  "geometry": {"coordinates":[-71.55314,8.34204],"type":"Point"}
}