{
  "type": "Feature",
  "properties": {
    "gn:admin1_code":"20",
    "gn:asciiname":"La Quinta",
    "gn:country_code":"VE",
    "gn:dem":1400,
    "gn:feature_class":"P",
    "gn:feature_code":"PPL",
    "gn:name":"La Quinta",
    "gn:population":0,
    "gn:timezone":"America/Caracas",
    "iso:country":"VE",
    "wof:name":"La Quinta",
    "wof:placetype":"locality"
},
  "geometry": {"coordinates":[-72.00820999999998,7.91247],"type":"Point"}
}