{
  "type": "Feature",
  "properties": {
    "gn:admin1_code":"23.0",
    "gn:asciiname":"Puerto Escondido",
    "gn:country_code":"VE",
    "gn:dem":25,
    "gn:feature_class":"P",
    "gn:feature_code":"PPL",
    "gn:name":"Puerto Escondido",
    "gn:population":0,
    "gn:timezone":"America/Caracas",
    "iso:country":"VE",
    "wof:name":"Puerto Escondido",
    "wof:placetype":"locality"
},
  "geometry": {"coordinates":[-71.58055999999998,8.83278],"type":"Point"}
}