{
  "type": "Feature",
  "properties": {
    "gn:admin1_code":"22",
    "gn:asciiname":"Kilometro Treinta y Cinco",
    "gn:cc2":"VE",
    "gn:country_code":"VE",
    "gn:dem":72,
    "gn:feature_class":"P",
    "gn:feature_code":"PPL",
    "gn:name":"Kil\u00f3metro Treinta y Cinco",
    "gn:population":0,
    "gn:timezone":"America/Caracas",
    "iso:country":"VE",
    "name:und_x_variant":[
        "Kil\u00f3metro 35",
        "Kil\u00f3metro Treinta y Cinco"
    ],
    "wof:name":"Kilometro Treinta y Cinco",
    "wof:placetype":"locality"
},
  "geometry": {"coordinates":[-68.69028,10.60111],"type":"Point"}
}