{
  "type": "Feature",
  "properties": {
    "gn:admin1_code":"12",
    "gn:asciiname":"Papayal",
    "gn:country_code":"VE",
    "gn:dem":726,
    "gn:feature_class":"P",
    "gn:feature_code":"PPL",
    "gn:name":"Papayal",
    "gn:population":0,
    "gn:timezone":"America/Caracas",
    "iso:country":"VE",
    "wof:name":"Papayal",
    "wof:placetype":"locality"
},
  "geometry": {"coordinates":[-67.79125999999999,9.80353],"type":"Point"}
}