{
  "type": "Feature",
  "properties": {
    "gn:admin1_code":"20",
    "gn:asciiname":"Velandria",
    "gn:country_code":"VE",
    "gn:dem":1146,
    "gn:feature_class":"P",
    "gn:feature_code":"PPL",
    "gn:name":"Velandria",
    "gn:population":0,
    "gn:timezone":"America/Caracas",
    "iso:country":"VE",
    "wof:name":"Velandria",
    "wof:placetype":"locality"
},
  "geometry": {"coordinates":[-72.28079,7.81589],"type":"Point"}
}