{
  "type": "Feature",
  "properties": {
    "gn:admin1_code":"4",
    "gn:asciiname":"Oficina Cedral",
    "gn:country_code":"VE",
    "gn:dem":1194,
    "gn:feature_class":"P",
    "gn:feature_code":"PPL",
    "gn:name":"Oficina Cedral",
    "gn:population":0,
    "gn:timezone":"America/Caracas",
    "iso:country":"VE",
    "wof:name":"Oficina Cedral",
    "wof:placetype":"locality"
},
  "geometry": {"coordinates":[-67.21666999999999,10.16667],"type":"Point"}
}