{
  "type": "Feature",
  "properties": {
    "gn:admin1_code":"12",
    "gn:asciiname":"Los Corocitos",
    "gn:country_code":"VE",
    "gn:dem":125,
    "gn:feature_class":"P",
    "gn:feature_code":"PPL",
    "gn:name":"Los Corocitos",
    "gn:population":0,
    "gn:timezone":"America/Caracas",
    "iso:country":"VE",
    "wof:name":"Los Corocitos",
    "wof:placetype":"locality"
},
  "geometry": {"coordinates":[-65.37111,8.65667],"type":"Point"}
}