{
  "type": "Feature",
  "properties": {
    "gn:admin1_code":"11.0",
    "gn:asciiname":"Macuca",
    "gn:country_code":"VE",
    "gn:dem":438,
    "gn:feature_class":"P",
    "gn:feature_code":"PPL",
    "gn:name":"Macuca",
    "gn:population":0,
    "gn:timezone":"America/Caracas",
    "iso:country":"VE",
    "wof:name":"Macuca",
    "wof:placetype":"locality"
},
  "geometry": {"coordinates":[-69.67206999999999,11.10587],"type":"Point"}
}