{
  "type": "Feature",
  "properties": {
    "gn:admin1_code":"02",
    "gn:asciiname":"Centella",
    "gn:country_code":"VE",
    "gn:dem":138,
    "gn:feature_class":"P",
    "gn:feature_code":"PPLL",
    "gn:name":"Centella",
    "gn:population":0,
    "gn:timezone":"America/Caracas",
    "iso:country":"VE",
    "name:azb_x_preferred":[
        "\u0633\u0646\u062a\u0644\u0644\u0627"
    ],
    "name:aze_x_preferred":[
        "Sentella"
    ],
    "name:cat_x_preferred":[
        "Centella"
    ],
    "name:ceb_x_preferred":[
        "Centella"
    ],
    "name:fas_x_preferred":[
        "\u0622\u0628 \u0628\u0634\u0642\u0627\u0628\u06cc"
    ],
    "name:fra_x_preferred":[
        "Centella"
    ],
    "name:msa_x_preferred":[
        "Pegaga Cina"
    ],
    "name:rus_x_preferred":[
        "\u0426\u0435\u043d\u0442\u0435\u043b\u043b\u0430"
    ],
    "name:spa_x_preferred":[
        "Centella"
    ],
    "name:swe_x_preferred":[
        "Centellor"
    ],
    "name:war_x_preferred":[
        "Centella"
    ],
    "name:zho_x_preferred":[
        "\u79ef\u96ea\u8349\u5c5e"
    ],
    "wof:name":"Centella",
    "wof:placetype":"locality"
},
  "geometry": {"coordinates":[-65.07668000000001,8.68371],"type":"Point"}
}