{
  "type": "Feature",
  "properties": {
    "gn:admin1_code":"02",
    "gn:asciiname":"Centella",
    "gn:country_code":"VE",
    "gn:dem":138,
    "gn:feature_class":"P",
    "gn:feature_code":"PPLL",
    "gn:name":"Centella",
    "gn:population":0,
    "gn:timezone":"America/Caracas",
    "iso:country":"VE",
    "wof:name":"Centella",
    "wof:placetype":"locality"
},
  "geometry": {"coordinates":[-65.07668000000001,8.68371],"type":"Point"}
}