{
  "type": "Feature",
  "properties": {
    "gn:admin1_code":"19.0",
    "gn:asciiname":"Chirgua",
    "gn:country_code":"VE",
    "gn:dem":45,
    "gn:feature_class":"P",
    "gn:feature_code":"PPL",
    "gn:name":"Chirgua",
    "gn:population":0,
    "gn:timezone":"America/Caracas",
    "iso:country":"VE",
    "wof:name":"Chirgua",
    "wof:placetype":"locality"
},
  "geometry": {"coordinates":[-64.17553000000001,10.3606],"type":"Point"}
}