{
  "type": "Feature",
  "properties": {
    "gn:admin1_code":"21",
    "gn:asciiname":"La Mesa del Guayabal",
    "gn:country_code":"VE",
    "gn:dem":1669,
    "gn:feature_class":"P",
    "gn:feature_code":"PPL",
    "gn:name":"La Mesa del Guayabal",
    "gn:population":0,
    "gn:timezone":"America/Caracas",
    "iso:country":"VE",
    "wof:name":"La Mesa del Guayabal",
    "wof:placetype":"locality"
},
  "geometry": {"coordinates":[-70.54295999999999,9.20932],"type":"Point"}
}