{
  "type": "Feature",
  "properties": {
    "gn:admin1_code":"2",
    "gn:asciiname":"El Cochino",
    "gn:country_code":"VE",
    "gn:dem":113,
    "gn:feature_class":"P",
    "gn:feature_code":"PPL",
    "gn:name":"El Cochino",
    "gn:population":0,
    "gn:timezone":"America/Caracas",
    "iso:country":"VE",
    "wof:name":"El Cochino",
    "wof:placetype":"locality"
},
  "geometry": {"coordinates":[-64.79709,8.07643],"type":"Point"}
}