{
  "type": "Feature",
  "properties": {
    "gn:admin1_code":"13",
    "gn:asciiname":"La Pastora",
    "gn:country_code":"VE",
    "gn:dem":839,
    "gn:feature_class":"P",
    "gn:feature_code":"PPL",
    "gn:name":"La Pastora",
    "gn:population":0,
    "gn:timezone":"America/Caracas",
    "iso:country":"VE",
    "wof:name":"La Pastora",
    "wof:placetype":"locality"
},
  "geometry": {"coordinates":[-69.21401999999999,10.33657],"type":"Point"}
}