{
  "type": "Feature",
  "properties": {
    "gn:admin1_code":"6.0",
    "gn:asciiname":"Zapata",
    "gn:country_code":"VE",
    "gn:dem":467,
    "gn:feature_class":"P",
    "gn:feature_code":"PPL",
    "gn:name":"Zapata",
    "gn:population":0,
    "gn:timezone":"America/Caracas",
    "iso:country":"VE",
    "wof:name":"Zapata",
    "wof:placetype":"locality"
},
  "geometry": {"coordinates":[-61.77,4.29722],"type":"Point"}
}