{
  "type": "Feature",
  "properties": {
    "gn:admin1_code":"6.0",
    "gn:asciiname":"Zapata",
    "gn:country_code":"VE",
    "gn:dem":467,
    "gn:feature_class":"P",
    "gn:feature_code":"PPL",
    "gn:name":"Zapata",
    "gn:population":0,
    "gn:timezone":"America/Caracas",
    "iso:country":"VE",
    "name:ceb_x_preferred":[
        "Zapata"
    ],
    "name:ces_x_preferred":[
        "Zapata"
    ],
    "name:deu_x_preferred":[
        "Zapata"
    ],
    "name:est_x_preferred":[
        "Zapata"
    ],
    "name:eus_x_preferred":[
        "Zapata"
    ],
    "name:fin_x_preferred":[
        "Zapata"
    ],
    "name:fra_x_preferred":[
        "Zapata"
    ],
    "name:glg_x_preferred":[
        "Zapata"
    ],
    "name:ita_x_preferred":[
        "Zapata"
    ],
    "name:jpn_x_preferred":[
        "\u30b5\u30d1\u30bf"
    ],
    "name:kor_x_preferred":[
        "\uc790\ud30c\ud0c0"
    ],
    "name:nld_x_preferred":[
        "Zapata"
    ],
    "name:pol_x_preferred":[
        "Zapata"
    ],
    "name:ron_x_preferred":[
        "Zapata"
    ],
    "name:rus_x_preferred":[
        "\u0421\u0430\u043f\u0430\u0442\u0430"
    ],
    "name:spa_x_preferred":[
        "Zapata"
    ],
    "name:srp_x_preferred":[
        "\u0417\u0430\u043f\u0430\u0442\u0430"
    ],
    "name:swe_x_preferred":[
        "Zapata"
    ],
    "name:tur_x_preferred":[
        "Zapata"
    ],
    "wof:name":"Zapata",
    "wof:placetype":"locality"
},
  "geometry": {"coordinates":[-61.77,4.29722],"type":"Point"}
}