{
  "type": "Feature",
  "properties": {
    "gn:admin1_code":"7",
    "gn:asciiname":"Reyes Arriba",
    "gn:country_code":"VE",
    "gn:dem":705,
    "gn:feature_class":"P",
    "gn:feature_code":"PPL",
    "gn:name":"Reyes Arriba",
    "gn:population":0,
    "gn:timezone":"America/Caracas",
    "iso:country":"VE",
    "wof:name":"Reyes Arriba",
    "wof:placetype":"locality"
},
  "geometry": {"coordinates":[-68.26730999999999,10.1453],"type":"Point"}
}