{
  "type": "Feature",
  "properties": {
    "gn:admin1_code":"3.0",
    "gn:asciiname":"San Eduardo",
    "gn:country_code":"VE",
    "gn:dem":42,
    "gn:feature_class":"P",
    "gn:feature_code":"PPL",
    "gn:name":"San Eduardo",
    "gn:population":0,
    "gn:timezone":"America/Caracas",
    "iso:country":"VE",
    "wof:name":"San Eduardo",
    "wof:placetype":"locality"
},
  "geometry": {"coordinates":[-67.08034000000001,7.60045],"type":"Point"}
}