{
  "type": "Feature",
  "properties": {
    "gn:admin1_code":"4",
    "gn:asciiname":"Rancho Rumbos",
    "gn:country_code":"VE",
    "gn:dem":521,
    "gn:feature_class":"P",
    "gn:feature_code":"PPL",
    "gn:name":"Rancho Rumbos",
    "gn:population":0,
    "gn:timezone":"America/Caracas",
    "iso:country":"VE",
    "wof:name":"Rancho Rumbos",
    "wof:placetype":"locality"
},
  "geometry": {"coordinates":[-67.50627,10.04158],"type":"Point"}
}