{
  "type": "Feature",
  "properties": {
    "gn:admin1_code":"18.0",
    "gn:asciiname":"San Jose de la Montana",
    "gn:country_code":"VE",
    "gn:dem":1360,
    "gn:feature_class":"P",
    "gn:feature_code":"PPL",
    "gn:name":"San Jos\u00e9 de la Monta\u00f1a",
    "gn:population":0,
    "gn:timezone":"America/Caracas",
    "iso:country":"VE",
    "name:spa_x_preferred":[
        "San Jos\u00e9 de la Monta\u00f1a"
    ],
    "wof:name":"San Jose de la Montana",
    "wof:placetype":"locality"
},
  "geometry": {"coordinates":[-69.8981,9.3384],"type":"Point"}
}