{
  "type": "Feature",
  "properties": {
    "gn:admin1_code":"11.0",
    "gn:asciiname":"La Sibucara",
    "gn:country_code":"VE",
    "gn:dem":46,
    "gn:feature_class":"P",
    "gn:feature_code":"PPLL",
    "gn:name":"La Sibucara",
    "gn:population":0,
    "gn:timezone":"America/Caracas",
    "iso:country":"VE",
    "wof:name":"La Sibucara",
    "wof:placetype":"locality"
},
  "geometry": {"coordinates":[-70.90167,10.96333],"type":"Point"}
}