{
  "type": "Feature",
  "properties": {
    "gn:admin1_code":"12.0",
    "gn:asciiname":"Aguada del Cielo",
    "gn:country_code":"VE",
    "gn:dem":202,
    "gn:feature_class":"P",
    "gn:feature_code":"PPL",
    "gn:name":"Aguada del Cielo",
    "gn:population":0,
    "gn:timezone":"America/Caracas",
    "iso:country":"VE",
    "wof:name":"Aguada del Cielo",
    "wof:placetype":"locality"
},
  "geometry": {"coordinates":[-65.95709000000001,9.714],"type":"Point"}
}