{
  "type": "Feature",
  "properties": {
    "gn:admin1_code":"02",
    "gn:asciiname":"Valle Hermoso",
    "gn:country_code":"VE",
    "gn:dem":170,
    "gn:feature_class":"P",
    "gn:feature_code":"PPLL",
    "gn:name":"Valle Hermoso",
    "gn:population":0,
    "gn:timezone":"America/Caracas",
    "iso:country":"VE",
    "name:ceb_x_preferred":[
        "Valle Hermoso"
    ],
    "name:deu_x_preferred":[
        "Valle Hermoso"
    ],
    "name:fra_x_preferred":[
        "Valle Hermoso"
    ],
    "name:ita_x_preferred":[
        "Valle Hermoso"
    ],
    "name:rus_x_preferred":[
        "\u0412\u0430\u043b\u044c\u0435-\u042d\u0440\u043c\u043e\u0441\u043e"
    ],
    "name:spa_x_preferred":[
        "Valle Hermoso"
    ],
    "name:swe_x_preferred":[
        "Valle Hermoso"
    ],
    "wof:name":"Valle Hermoso",
    "wof:placetype":"locality"
},
  "geometry": {"coordinates":[-64.6309,8.36026],"type":"Point"}
}