{
  "type": "Feature",
  "properties": {
    "gn:admin1_code":"4",
    "gn:asciiname":"Cano Rico",
    "gn:country_code":"VE",
    "gn:dem":428,
    "gn:feature_class":"P",
    "gn:feature_code":"PPL",
    "gn:name":"Ca\u00f1o Rico",
    "gn:population":0,
    "gn:timezone":"America/Caracas",
    "iso:country":"VE",
    "wof:name":"Cano Rico",
    "wof:placetype":"locality"
},
  "geometry": {"coordinates":[-67.59484999999999,10.12384],"type":"Point"}
}