{
  "type": "Feature",
  "properties": {
    "gn:admin1_code":"12.0",
    "gn:asciiname":"Las Yeguas",
    "gn:country_code":"VE",
    "gn:dem":39,
    "gn:feature_class":"P",
    "gn:feature_code":"PPLL",
    "gn:name":"Las Yeguas",
    "gn:population":0,
    "gn:timezone":"America/Caracas",
    "iso:country":"VE",
    "wof:name":"Las Yeguas",
    "wof:placetype":"locality"
},
  "geometry": {"coordinates":[-66.6461,7.85146],"type":"Point"}
}