{
  "type": "Feature",
  "properties": {
    "gn:admin1_code":"02",
    "gn:asciiname":"Suina",
    "gn:country_code":"VE",
    "gn:dem":1501,
    "gn:feature_class":"P",
    "gn:feature_code":"PPL",
    "gn:name":"Sui\u00f1a",
    "gn:population":0,
    "gn:timezone":"America/Caracas",
    "iso:country":"VE",
    "wof:name":"Suina",
    "wof:placetype":"locality"
},
  "geometry": {"coordinates":[-64.68333,4.25],"type":"Point"}
}