{
  "type": "Feature",
  "properties": {
    "gn:admin1_code":"23",
    "gn:asciiname":"La Cataneja",
    "gn:country_code":"VE",
    "gn:dem":69,
    "gn:feature_class":"P",
    "gn:feature_code":"PPL",
    "gn:name":"La Cataneja",
    "gn:population":0,
    "gn:timezone":"America/Caracas",
    "iso:country":"VE",
    "name:und_x_variant":[
        "Catanejo",
        "La Cataneja"
    ],
    "wof:name":"La Cataneja",
    "wof:placetype":"locality"
},
  "geometry": {"coordinates":[-71.26045000000001,10.68561],"type":"Point"}
}