{
  "type": "Feature",
  "properties": {
    "gn:admin1_code":"19",
    "gn:asciiname":"Cogollal",
    "gn:country_code":"VE",
    "gn:dem":700,
    "gn:feature_class":"P",
    "gn:feature_code":"PPLL",
    "gn:name":"Cogollal",
    "gn:population":0,
    "gn:timezone":"America/Caracas",
    "iso:country":"VE",
    "name:und_x_variant":[
        "R\u00edo Cocollar",
        "Cogoyal",
        "Cocoyas",
        "Cocovar",
        "Cocoyan",
        "Cocoyar",
        "Cogollal"
    ],
    "wof:name":"Cogollal",
    "wof:placetype":"locality"
},
  "geometry": {"coordinates":[-63.96097,10.35502],"type":"Point"}
}