{
  "type": "Feature",
  "properties": {
    "gn:admin1_code":"12",
    "gn:asciiname":"El Cuji",
    "gn:country_code":"VE",
    "gn:dem":101,
    "gn:feature_class":"P",
    "gn:feature_code":"PPL",
    "gn:name":"El Cuj\u00ed",
    "gn:population":0,
    "gn:timezone":"America/Caracas",
    "iso:country":"VE",
    "wof:name":"El Cuji",
    "wof:placetype":"locality"
},
  "geometry": {"coordinates":[-65.53272,9.1459],"type":"Point"}
}