{
  "type": "Feature",
  "properties": {
    "gn:admin1_code":"2",
    "gn:asciiname":"Finlandia",
    "gn:country_code":"VE",
    "gn:dem":115,
    "gn:feature_class":"P",
    "gn:feature_code":"PPL",
    "gn:name":"Finlandia",
    "gn:population":0,
    "gn:timezone":"America/Caracas",
    "iso:country":"VE",
    "wof:name":"Finlandia",
    "wof:placetype":"locality"
},
  "geometry": {"coordinates":[-64.79666999999999,9.47995],"type":"Point"}
}