{
  "type": "Feature",
  "properties": {
    "gn:admin1_code":"2",
    "gn:asciiname":"Maracay",
    "gn:country_code":"VE",
    "gn:dem":85,
    "gn:feature_class":"P",
    "gn:feature_code":"PPL",
    "gn:name":"Maracay",
    "gn:population":0,
    "gn:timezone":"America/Caracas",
    "iso:country":"VE",
    "wof:name":"Maracay",
    "wof:placetype":"locality"
},
  "geometry": {"coordinates":[-63.66492,8.2275],"type":"Point"}
}