{
  "type": "Feature",
  "properties": {
    "gn:admin1_code":"15",
    "gn:asciiname":"El Jobal",
    "gn:country_code":"VE",
    "gn:dem":17,
    "gn:feature_class":"P",
    "gn:feature_code":"PPL",
    "gn:name":"El Jobal",
    "gn:population":0,
    "gn:timezone":"America/Caracas",
    "iso:country":"VE",
    "wof:name":"El Jobal",
    "wof:placetype":"locality"
},
  "geometry": {"coordinates":[-66.12,10.23194],"type":"Point"}
}