{
  "type": "Feature",
  "properties": {
    "gn:admin1_code":"21",
    "gn:asciiname":"Cristobal",
    "gn:country_code":"VE",
    "gn:dem":686,
    "gn:feature_class":"P",
    "gn:feature_code":"PPL",
    "gn:name":"Cristobal",
    "gn:population":0,
    "gn:timezone":"America/Caracas",
    "iso:country":"VE",
    "wof:name":"Cristobal",
    "wof:placetype":"locality"
},
  "geometry": {"coordinates":[-70.83055999999998,9.21764],"type":"Point"}
}