{
  "type": "Feature",
  "properties": {
    "gn:admin1_code":"11.0",
    "gn:asciiname":"Catuto",
    "gn:country_code":"VE",
    "gn:dem":182,
    "gn:feature_class":"P",
    "gn:feature_code":"PPLL",
    "gn:name":"Catuto",
    "gn:population":0,
    "gn:timezone":"America/Caracas",
    "iso:country":"VE",
    "wof:name":"Catuto",
    "wof:placetype":"locality"
},
  "geometry": {"coordinates":[-69.3087,11.21858],"type":"Point"}
}