{
  "type": "Feature",
  "properties": {
    "gn:admin1_code":"4",
    "gn:asciiname":"La Morota",
    "gn:country_code":"VE",
    "gn:dem":233,
    "gn:feature_class":"P",
    "gn:feature_code":"PPL",
    "gn:name":"La Morota",
    "gn:population":0,
    "gn:timezone":"America/Caracas",
    "iso:country":"VE",
    "wof:name":"La Morota",
    "wof:placetype":"locality"
},
  "geometry": {"coordinates":[-66.62456999999999,9.58387],"type":"Point"}
}