{
  "type": "Feature",
  "properties": {
    "gn:admin1_code":"14",
    "gn:asciiname":"El Estanquillo",
    "gn:country_code":"VE",
    "gn:dem":2122,
    "gn:feature_class":"P",
    "gn:feature_code":"PPL",
    "gn:name":"El Estanquillo",
    "gn:population":0,
    "gn:timezone":"America/Caracas",
    "iso:country":"VE",
    "wof:name":"El Estanquillo",
    "wof:placetype":"locality"
},
  "geometry": {"coordinates":[-71.44830999999998,8.53293],"type":"Point"}
}