{
  "type": "Feature",
  "properties": {
    "gn:admin1_code":"3",
    "gn:asciiname":"El Loco",
    "gn:country_code":"VE",
    "gn:dem":159,
    "gn:feature_class":"P",
    "gn:feature_code":"PPL",
    "gn:name":"El Loco",
    "gn:population":0,
    "gn:timezone":"America/Caracas",
    "iso:country":"VE",
    "name:ces_x_preferred":[
        "El Loco"
    ],
    "name:deu_x_preferred":[
        "El Loco"
    ],
    "name:fin_x_preferred":[
        "El Loco"
    ],
    "name:fra_x_preferred":[
        "El Loco"
    ],
    "name:ita_x_preferred":[
        "El Loco"
    ],
    "name:jpn_x_preferred":[
        "\u30a8\u30eb\u30fb\u30ed\u30b3"
    ],
    "name:nno_x_preferred":[
        "El Loco"
    ],
    "name:por_x_preferred":[
        "El Loco"
    ],
    "name:rus_x_preferred":[
        "El Loco"
    ],
    "name:swe_x_preferred":[
        "El Loco"
    ],
    "wof:name":"El Loco",
    "wof:placetype":"locality"
},
  "geometry": {"coordinates":[-71.38333,7.36667],"type":"Point"}
}