{
  "type": "Feature",
  "properties": {
    "gn:admin1_code":"16",
    "gn:asciiname":"Boca de Uracoa",
    "gn:country_code":"VE",
    "gn:dem":7,
    "gn:feature_class":"P",
    "gn:feature_code":"PPL",
    "gn:name":"Boca de Uracoa",
    "gn:population":0,
    "gn:timezone":"America/Caracas",
    "iso:country":"VE",
    "name:und_x_variant":[
        "La Boca",
        "Bocas de Uracoa",
        "Boca Uracoa",
        "Boca de Uracoa"
    ],
    "wof:name":"Boca de Uracoa",
    "wof:placetype":"locality"
},
  "geometry": {"coordinates":[-62.33173000000001,9.12943],"type":"Point"}
}