{
  "type": "Feature",
  "properties": {
    "gn:admin1_code":"19.0",
    "gn:asciiname":"Rio Sotillo",
    "gn:country_code":"VE",
    "gn:dem":379,
    "gn:feature_class":"P",
    "gn:feature_code":"PPL",
    "gn:name":"R\u00edo Sotillo",
    "gn:population":0,
    "gn:timezone":"America/Caracas",
    "iso:country":"VE",
    "wof:name":"Rio Sotillo",
    "wof:placetype":"locality"
},
  "geometry": {"coordinates":[-63.86944,10.28444],"type":"Point"}
}