{
  "type": "Feature",
  "properties": {
    "gn:admin1_code":"20",
    "gn:asciiname":"La Espuma",
    "gn:country_code":"VE",
    "gn:dem":329,
    "gn:feature_class":"P",
    "gn:feature_code":"PPL",
    "gn:name":"La Espuma",
    "gn:population":0,
    "gn:timezone":"America/Caracas",
    "iso:country":"VE",
    "wof:name":"La Espuma",
    "wof:placetype":"locality"
},
  "geometry": {"coordinates":[-72.08773000000002,7.55374],"type":"Point"}
}