{
  "type": "Feature",
  "properties": {
    "gn:admin1_code":"16",
    "gn:asciiname":"El Pescado",
    "gn:country_code":"VE",
    "gn:dem":157,
    "gn:feature_class":"P",
    "gn:feature_code":"PPL",
    "gn:name":"El Pescado",
    "gn:population":0,
    "gn:timezone":"America/Caracas",
    "iso:country":"VE",
    "wof:name":"El Pescado",
    "wof:placetype":"locality"
},
  "geometry": {"coordinates":[-63.68189,9.67973],"type":"Point"}
}