{
  "type": "Feature",
  "properties": {
    "gn:admin1_code":"2",
    "gn:asciiname":"Orijuan",
    "gn:country_code":"VE",
    "gn:dem":176,
    "gn:feature_class":"P",
    "gn:feature_code":"PPL",
    "gn:name":"Oriju\u00e1n",
    "gn:population":0,
    "gn:timezone":"America/Caracas",
    "iso:country":"VE",
    "name:und_x_variant":[
        "Orij\u00e1n",
        "Origu\u00e1n",
        "Oriju\u00e1n"
    ],
    "wof:name":"Orijuan",
    "wof:placetype":"locality"
},
  "geometry": {"coordinates":[-64.39067,9.71954],"type":"Point"}
}