{
  "type": "Feature",
  "properties": {
    "gn:admin1_code":"6.0",
    "gn:asciiname":"El Amparo",
    "gn:country_code":"VE",
    "gn:dem":172,
    "gn:feature_class":"P",
    "gn:feature_code":"PPL",
    "gn:name":"El Amparo",
    "gn:population":0,
    "gn:timezone":"America/Caracas",
    "iso:country":"VE",
    "wof:name":"El Amparo",
    "wof:placetype":"locality"
},
  "geometry": {"coordinates":[-63.28833,7.92389],"type":"Point"}
}