{
  "type": "Feature",
  "properties": {
    "gn:admin1_code":"19",
    "gn:asciiname":"La Baba",
    "gn:country_code":"VE",
    "gn:dem":101,
    "gn:feature_class":"P",
    "gn:feature_code":"PPL",
    "gn:name":"La Baba",
    "gn:population":0,
    "gn:timezone":"America/Caracas",
    "iso:country":"VE",
    "wof:name":"La Baba",
    "wof:placetype":"locality"
},
  "geometry": {"coordinates":[-63.45085,10.32403],"type":"Point"}
}