{
  "type": "Feature",
  "properties": {
    "gn:admin1_code":"8.0",
    "gn:asciiname":"El Cajon del Tigre",
    "gn:country_code":"VE",
    "gn:dem":79,
    "gn:feature_class":"P",
    "gn:feature_code":"PPL",
    "gn:name":"El Caj\u00f3n del Tigre",
    "gn:population":0,
    "gn:timezone":"America/Caracas",
    "iso:country":"VE",
    "wof:name":"El Cajon del Tigre",
    "wof:placetype":"locality"
},
  "geometry": {"coordinates":[-67.98555999999999,9.13833],"type":"Point"}
}