{
  "type": "Feature",
  "properties": {
    "gn:admin1_code":"7",
    "gn:asciiname":"La Gonzalera",
    "gn:country_code":"VE",
    "gn:dem":721,
    "gn:feature_class":"P",
    "gn:feature_code":"PPL",
    "gn:name":"La Gonzalera",
    "gn:population":0,
    "gn:timezone":"America/Caracas",
    "iso:country":"VE",
    "wof:name":"La Gonzalera",
    "wof:placetype":"locality"
},
  "geometry": {"coordinates":[-67.7544,9.91916],"type":"Point"}
}