{
  "type": "Feature",
  "properties": {
    "gn:admin1_code":"11.0",
    "gn:asciiname":"Cruz del Medio",
    "gn:country_code":"VE",
    "gn:dem":275,
    "gn:feature_class":"P",
    "gn:feature_code":"PPLL",
    "gn:name":"Cruz del Medio",
    "gn:population":0,
    "gn:timezone":"America/Caracas",
    "iso:country":"VE",
    "wof:name":"Cruz del Medio",
    "wof:placetype":"locality"
},
  "geometry": {"coordinates":[-69.06721999999999,10.90722],"type":"Point"}
}