{
  "type": "Feature",
  "properties": {
    "gn:admin1_code":"6",
    "gn:asciiname":"Ipotureima",
    "gn:country_code":"VE",
    "gn:dem":487,
    "gn:feature_class":"P",
    "gn:feature_code":"PPL",
    "gn:name":"Ipotureima",
    "gn:population":0,
    "gn:timezone":"America/Caracas",
    "iso:country":"VE",
    "wof:name":"Ipotureima",
    "wof:placetype":"locality"
},
  "geometry": {"coordinates":[-62.28333000000001,5.03333],"type":"Point"}
}