{
  "type": "Feature",
  "properties": {
    "gn:admin1_code":"14.0",
    "gn:asciiname":"Guayana",
    "gn:country_code":"VE",
    "gn:dem":54,
    "gn:feature_class":"P",
    "gn:feature_code":"PPL",
    "gn:name":"Guayana",
    "gn:population":0,
    "gn:timezone":"America/Caracas",
    "iso:country":"VE",
    "wof:name":"Guayana",
    "wof:placetype":"locality"
},
  "geometry": {"coordinates":[-71.09625,9.15042],"type":"Point"}
}