{
  "type": "Feature",
  "properties": {
    "gn:admin1_code":"19",
    "gn:asciiname":"Guayana",
    "gn:country_code":"VE",
    "gn:dem":22,
    "gn:feature_class":"P",
    "gn:feature_code":"PPL",
    "gn:name":"Guayana",
    "gn:population":0,
    "gn:timezone":"America/Caracas",
    "iso:country":"VE",
    "wof:name":"Guayana",
    "wof:placetype":"locality"
},
  "geometry": {"coordinates":[-62.94403000000001,10.58834],"type":"Point"}
}