{
  "type": "Feature",
  "properties": {
    "gn:admin1_code":"4",
    "gn:asciiname":"Guayabita",
    "gn:country_code":"VE",
    "gn:dem":495,
    "gn:feature_class":"P",
    "gn:feature_code":"PPL",
    "gn:name":"Guayabita",
    "gn:population":0,
    "gn:timezone":"America/Caracas",
    "iso:country":"VE",
    "wof:name":"Guayabita",
    "wof:placetype":"locality"
},
  "geometry": {"coordinates":[-67.48232,10.25644],"type":"Point"}
}