{
  "type": "Feature",
  "properties": {
    "gn:admin1_code":"3",
    "gn:asciiname":"Palmar Candelaria",
    "gn:cc2":"VE",
    "gn:country_code":"VE",
    "gn:dem":55,
    "gn:feature_class":"P",
    "gn:feature_code":"PPL",
    "gn:name":"Palmar Candelaria",
    "gn:population":0,
    "gn:timezone":"America/Caracas",
    "iso:country":"VE",
    "name:und_x_variant":[
        "Palmar de Candelaria",
        "Palmar de La Candelaria",
        "Palmar Candelaria"
    ],
    "wof:name":"Palmar Candelaria",
    "wof:placetype":"locality"
},
  "geometry": {"coordinates":[-67.73333000000001,7.51667],"type":"Point"}
}