{
  "type": "Feature",
  "properties": {
    "gn:admin1_code":"5",
    "gn:asciiname":"La Morelena",
    "gn:cc2":"VE",
    "gn:country_code":"VE",
    "gn:dem":131,
    "gn:feature_class":"P",
    "gn:feature_code":"PPL",
    "gn:name":"La Morele\u00f1a",
    "gn:population":0,
    "gn:timezone":"America/Caracas",
    "iso:country":"VE",
    "name:und_x_variant":[
        "Morele\u00f1a",
        "La Morele\u00f1a"
    ],
    "wof:name":"La Morelena",
    "wof:placetype":"locality"
},
  "geometry": {"coordinates":[-70.26666999999999,8.26667],"type":"Point"}
}