{
  "type": "Feature",
  "properties": {
    "gn:admin1_code":"02",
    "gn:asciiname":"El Picacho",
    "gn:country_code":"VE",
    "gn:dem":126,
    "gn:feature_class":"P",
    "gn:feature_code":"PPLL",
    "gn:name":"El Picacho",
    "gn:population":0,
    "gn:timezone":"America/Caracas",
    "iso:country":"VE",
    "name:ceb_x_preferred":[
        "El Picacho"
    ],
    "name:spa_x_preferred":[
        "El Picacho"
    ],
    "name:swe_x_preferred":[
        "El Picacho"
    ],
    "wof:name":"El Picacho",
    "wof:placetype":"locality"
},
  "geometry": {"coordinates":[-64.47608000000001,8.19372],"type":"Point"}
}