{
  "type": "Feature",
  "properties": {
    "gn:admin1_code":"11.0",
    "gn:asciiname":"Miraflores",
    "gn:country_code":"VE",
    "gn:dem":58,
    "gn:feature_class":"P",
    "gn:feature_code":"PPL",
    "gn:name":"Miraflores",
    "gn:population":0,
    "gn:timezone":"America/Caracas",
    "iso:country":"VE",
    "wof:name":"Miraflores",
    "wof:placetype":"locality"
},
  "geometry": {"coordinates":[-70.44261,11.12879],"type":"Point"}
}