{
  "type": "Feature",
  "properties": {
    "gn:admin1_code":"2",
    "gn:asciiname":"Fernandero",
    "gn:country_code":"VE",
    "gn:dem":87,
    "gn:feature_class":"P",
    "gn:feature_code":"PPL",
    "gn:name":"Fernandero",
    "gn:population":0,
    "gn:timezone":"America/Caracas",
    "iso:country":"VE",
    "wof:name":"Fernandero",
    "wof:placetype":"locality"
},
  "geometry": {"coordinates":[-65.07451999999999,9.2854],"type":"Point"}
}