{
  "type": "Feature",
  "properties": {
    "gn:admin1_code":"05",
    "gn:asciiname":"Uvero Gacho",
    "gn:country_code":"VE",
    "gn:dem":106,
    "gn:feature_class":"P",
    "gn:feature_code":"PPL",
    "gn:name":"Uvero Gacho",
    "gn:population":0,
    "gn:timezone":"America/Caracas",
    "iso:country":"VE",
    "wof:name":"Uvero Gacho",
    "wof:placetype":"locality"
},
  "geometry": {"coordinates":[-69.66667,8.36667],"type":"Point"}
}