{
  "type": "Feature",
  "properties": {
    "gn:admin1_code":"1",
    "gn:asciiname":"Majeicodoteri",
    "gn:country_code":"VE",
    "gn:dem":166,
    "gn:feature_class":"P",
    "gn:feature_code":"PPL",
    "gn:name":"Majeicodoteri",
    "gn:population":0,
    "gn:timezone":"America/Caracas",
    "iso:country":"VE",
    "name:und_x_variant":[
        "Sitio Platanal",
        "Platanal",
        "Majeicodoteri"
    ],
    "wof:name":"Majeicodoteri",
    "wof:placetype":"locality"
},
  "geometry": {"coordinates":[-64.95409000000001,2.44367],"type":"Point"}
}