{
  "type": "Feature",
  "properties": {
    "gn:admin1_code":"11",
    "gn:asciiname":"Turaguapo",
    "gn:cc2":"VE",
    "gn:country_code":"VE",
    "gn:dem":244,
    "gn:feature_class":"P",
    "gn:feature_code":"PPL",
    "gn:name":"Turaguapo",
    "gn:population":0,
    "gn:timezone":"America/Caracas",
    "iso:country":"VE",
    "name:und_x_variant":[
        "Turuguapo",
        "Turaguapo"
    ],
    "wof:name":"Turaguapo",
    "wof:placetype":"locality"
},
  "geometry": {"coordinates":[-69.34999999999999,11.36667],"type":"Point"}
}