{
  "type": "Feature",
  "properties": {
    "gn:admin1_code":"11",
    "gn:asciiname":"El Congal",
    "gn:country_code":"VE",
    "gn:dem":52,
    "gn:feature_class":"P",
    "gn:feature_code":"PPL",
    "gn:name":"El Congal",
    "gn:population":0,
    "gn:timezone":"America/Caracas",
    "iso:country":"VE",
    "name:und_x_variant":[
        "Gongal",
        "Congal",
        "El Congo",
        "El Congal"
    ],
    "wof:name":"El Congal",
    "wof:placetype":"locality"
},
  "geometry": {"coordinates":[-69.23826,11.14749],"type":"Point"}
}