{
  "type": "Feature",
  "properties": {
    "gn:admin1_code":"7",
    "gn:asciiname":"Palmichal",
    "gn:country_code":"VE",
    "gn:dem":1024,
    "gn:feature_class":"P",
    "gn:feature_code":"PPL",
    "gn:name":"Palmichal",
    "gn:population":0,
    "gn:timezone":"America/Caracas",
    "iso:country":"VE",
    "name:und_x_variant":[
        "Palmicha",
        "Palmichal"
    ],
    "wof:name":"Palmichal",
    "wof:placetype":"locality"
},
  "geometry": {"coordinates":[-68.22954,10.29891],"type":"Point"}
}