{
  "type": "Feature",
  "properties": {
    "gn:admin1_code":"16",
    "gn:asciiname":"El Hoyo",
    "gn:country_code":"VE",
    "gn:dem":701,
    "gn:feature_class":"P",
    "gn:feature_code":"PPL",
    "gn:name":"El Hoyo",
    "gn:population":0,
    "gn:timezone":"America/Caracas",
    "iso:country":"VE",
    "name:ita_x_preferred":[
        "El Hoyo"
    ],
    "name:spa_x_preferred":[
        "El Hoyo"
    ],
    "wof:name":"El Hoyo",
    "wof:placetype":"locality"
},
  "geometry": {"coordinates":[-63.8375,9.96806],"type":"Point"}
}