{
  "type": "Feature",
  "properties": {
    "gn:admin1_code":"23",
    "gn:asciiname":"Inciarte",
    "gn:cc2":"VE",
    "gn:country_code":"VE",
    "gn:dem":98,
    "gn:feature_class":"P",
    "gn:feature_code":"PPL",
    "gn:name":"Inciarte",
    "gn:population":0,
    "gn:timezone":"America/Caracas",
    "iso:country":"VE",
    "name:und_x_variant":[
        "Inciarle",
        "Inciarte"
    ],
    "wof:name":"Inciarte",
    "wof:placetype":"locality"
},
  "geometry": {"coordinates":[-72.23333000000002,10.78333],"type":"Point"}
}