{
  "type": "Feature",
  "properties": {
    "gn:admin1_code":"5",
    "gn:asciiname":"El Martinero",
    "gn:cc2":"VE",
    "gn:country_code":"VE",
    "gn:dem":147,
    "gn:feature_class":"P",
    "gn:feature_code":"PPL",
    "gn:name":"El Martinero",
    "gn:population":0,
    "gn:timezone":"America/Caracas",
    "iso:country":"VE",
    "name:und_x_variant":[
        "El Martimero",
        "El Martinero"
    ],
    "wof:name":"El Martinero",
    "wof:placetype":"locality"
},
  "geometry": {"coordinates":[-70.33333,8.41667],"type":"Point"}
}