{
  "type": "Feature",
  "properties": {
    "gn:admin1_code":"02",
    "gn:asciiname":"Agua Sola",
    "gn:country_code":"VE",
    "gn:dem":143,
    "gn:feature_class":"P",
    "gn:feature_code":"PPL",
    "gn:name":"Agua Sola",
    "gn:population":0,
    "gn:timezone":"America/Caracas",
    "iso:country":"VE",
    "wof:name":"Agua Sola",
    "wof:placetype":"locality"
},
  "geometry": {"coordinates":[-64.64841,9.3236],"type":"Point"}
}