{
  "type": "Feature",
  "properties": {
    "gn:admin1_code":"5",
    "gn:asciiname":"Roblecito",
    "gn:country_code":"VE",
    "gn:dem":109,
    "gn:feature_class":"P",
    "gn:feature_code":"PPL",
    "gn:name":"Roblecito",
    "gn:population":0,
    "gn:timezone":"America/Caracas",
    "iso:country":"VE",
    "wof:name":"Roblecito",
    "wof:placetype":"locality"
},
  "geometry": {"coordinates":[-69.98333000000001,8.15],"type":"Point"}
}