{
  "type": "Feature",
  "properties": {
    "gn:admin1_code":"12.0",
    "gn:asciiname":"La Mariposa",
    "gn:country_code":"VE",
    "gn:dem":38,
    "gn:feature_class":"P",
    "gn:feature_code":"PPLL",
    "gn:name":"La Mariposa",
    "gn:population":0,
    "gn:timezone":"America/Caracas",
    "iso:country":"VE",
    "wof:name":"La Mariposa",
    "wof:placetype":"locality"
},
  "geometry": {"coordinates":[-66.61345,7.86369],"type":"Point"}
}