{
  "type": "Feature",
  "properties": {
    "gn:admin1_code":"2",
    "gn:asciiname":"Cabeceras del Pao",
    "gn:country_code":"VE",
    "gn:dem":269,
    "gn:feature_class":"P",
    "gn:feature_code":"PPL",
    "gn:name":"Cabeceras del Pao",
    "gn:population":0,
    "gn:timezone":"America/Caracas",
    "iso:country":"VE",
    "wof:name":"Cabeceras del Pao",
    "wof:placetype":"locality"
},
  "geometry": {"coordinates":[-64.51600999999999,8.89717],"type":"Point"}
}