{
  "type": "Feature",
  "properties": {
    "gn:admin1_code":"5",
    "gn:asciiname":"Limoncito",
    "gn:country_code":"VE",
    "gn:dem":143,
    "gn:feature_class":"P",
    "gn:feature_code":"PPLL",
    "gn:name":"Limoncito",
    "gn:population":0,
    "gn:timezone":"America/Caracas",
    "iso:country":"VE",
    "name:ceb_x_preferred":[
        "Limoncito"
    ],
    "name:deu_x_preferred":[
        "Limoncito"
    ],
    "name:zho_x_preferred":[
        "\u5229\u8499\u897f\u6258"
    ],
    "wof:name":"Limoncito",
    "wof:placetype":"locality"
},
  "geometry": {"coordinates":[-70.99333,7.53361],"type":"Point"}
}