{
  "type": "Feature",
  "properties": {
    "gn:admin1_code":"2",
    "gn:asciiname":"El Pericoco",
    "gn:country_code":"VE",
    "gn:dem":264,
    "gn:feature_class":"P",
    "gn:feature_code":"PPL",
    "gn:name":"El Pericoco",
    "gn:population":0,
    "gn:timezone":"America/Caracas",
    "iso:country":"VE",
    "wof:name":"El Pericoco",
    "wof:placetype":"locality"
},
  "geometry": {"coordinates":[-64.3706,9.31765],"type":"Point"}
}