{
  "type": "Feature",
  "properties": {
    "gn:admin1_code":"14",
    "gn:asciiname":"Rio Arriba",
    "gn:country_code":"VE",
    "gn:dem":2464,
    "gn:feature_class":"P",
    "gn:feature_code":"PPL",
    "gn:name":"R\u00edo Arriba",
    "gn:population":0,
    "gn:timezone":"America/Caracas",
    "iso:country":"VE",
    "wof:name":"Rio Arriba",
    "wof:placetype":"locality"
},
  "geometry": {"coordinates":[-71.88336,8.1983],"type":"Point"}
}