{
  "type": "Feature",
  "properties": {
    "gn:admin1_code":"12.0",
    "gn:asciiname":"Los Chivos",
    "gn:country_code":"VE",
    "gn:dem":145,
    "gn:feature_class":"P",
    "gn:feature_code":"PPLL",
    "gn:name":"Los Chivos",
    "gn:population":0,
    "gn:timezone":"America/Caracas",
    "iso:country":"VE",
    "wof:name":"Los Chivos",
    "wof:placetype":"locality"
},
  "geometry": {"coordinates":[-65.76000000000001,8.81944],"type":"Point"}
}