{
  "type": "Feature",
  "properties": {
    "gn:admin1_code":"15",
    "gn:asciiname":"Obispo",
    "gn:country_code":"VE",
    "gn:dem":110,
    "gn:feature_class":"P",
    "gn:feature_code":"PPL",
    "gn:name":"Obispo",
    "gn:population":0,
    "gn:timezone":"America/Caracas",
    "iso:country":"VE",
    "name:ceb_x_preferred":[
        "Obispo"
    ],
    "name:deu_x_preferred":[
        "Obispo"
    ],
    "name:fra_x_preferred":[
        "Obispo"
    ],
    "name:ita_x_preferred":[
        "Obispo"
    ],
    "name:rus_x_preferred":[
        "\u041e\u0431\u0438\u0441\u043f\u043e"
    ],
    "name:swe_x_preferred":[
        "Obispo"
    ],
    "name:tgl_x_preferred":[
        "Obispo"
    ],
    "wof:name":"Obispo",
    "wof:placetype":"locality"
},
  "geometry": {"coordinates":[-66.31667,10.35],"type":"Point"}
}