{
  "type": "Feature",
  "properties": {
    "gn:admin1_code":"8",
    "gn:asciiname":"La Concepcion",
    "gn:cc2":"VE",
    "gn:country_code":"VE",
    "gn:dem":86,
    "gn:feature_class":"P",
    "gn:feature_code":"PPL",
    "gn:name":"La Concepci\u00f3n",
    "gn:population":0,
    "gn:timezone":"America/Caracas",
    "iso:country":"VE",
    "name:und_x_variant":[
        "Hato Concepci\u00f3n",
        "Concepci\u00f3n",
        "La Concepci\u00f3n"
    ],
    "wof:name":"La Concepcion",
    "wof:placetype":"locality"
},
  "geometry": {"coordinates":[-68.13333,8.96667],"type":"Point"}
}