{
  "type": "Feature",
  "properties": {
    "gn:admin1_code":"6.0",
    "gn:asciiname":"Calceta de Maripal",
    "gn:country_code":"VE",
    "gn:dem":284,
    "gn:feature_class":"P",
    "gn:feature_code":"PPL",
    "gn:name":"Calceta de Maripal",
    "gn:population":0,
    "gn:timezone":"America/Caracas",
    "iso:country":"VE",
    "wof:name":"Calceta de Maripal",
    "wof:placetype":"locality"
},
  "geometry": {"coordinates":[-62.55611,7.23944],"type":"Point"}
}