{
  "type": "Feature",
  "properties": {
    "gn:admin1_code":"20.0",
    "gn:asciiname":"Kilometro 10",
    "gn:country_code":"VE",
    "gn:dem":192,
    "gn:feature_class":"P",
    "gn:feature_code":"PPL",
    "gn:name":"Kil\u00f3metro 10",
    "gn:population":0,
    "gn:timezone":"America/Caracas",
    "iso:country":"VE",
    "wof:name":"Kilometro 10",
    "wof:placetype":"locality"
},
  "geometry": {"coordinates":[-71.7469,7.55399],"type":"Point"}
}