{
  "type": "Feature",
  "properties": {
    "gn:admin1_code":"13.0",
    "gn:asciiname":"Siguao",
    "gn:country_code":"VE",
    "gn:dem":1373,
    "gn:feature_class":"P",
    "gn:feature_code":"PPL",
    "gn:name":"Siguao",
    "gn:population":0,
    "gn:timezone":"America/Caracas",
    "iso:country":"VE",
    "wof:name":"Siguao",
    "wof:placetype":"locality"
},
  "geometry": {"coordinates":[-70.03703,9.94049],"type":"Point"}
}