{
  "type": "Feature",
  "properties": {
    "gn:admin1_code":"19.0",
    "gn:asciiname":"Salsipuedes",
    "gn:country_code":"VE",
    "gn:dem":132,
    "gn:feature_class":"P",
    "gn:feature_code":"PPL",
    "gn:name":"Salsipuedes",
    "gn:population":0,
    "gn:timezone":"America/Caracas",
    "iso:country":"VE",
    "wof:name":"Salsipuedes",
    "wof:placetype":"locality"
},
  "geometry": {"coordinates":[-64.04352,10.34169],"type":"Point"}
}