{
  "type": "Feature",
  "properties": {
    "gn:admin1_code":"7",
    "gn:asciiname":"Perico",
    "gn:country_code":"VE",
    "gn:dem":786,
    "gn:feature_class":"P",
    "gn:feature_code":"PPL",
    "gn:name":"Perico",
    "gn:population":0,
    "gn:timezone":"America/Caracas",
    "iso:country":"VE",
    "wof:name":"Perico",
    "wof:placetype":"locality"
},
  "geometry": {"coordinates":[-68.20206,10.25293],"type":"Point"}
}