{
  "type": "Feature",
  "properties": {
    "gn:admin1_code":"4",
    "gn:asciiname":"Apamatico",
    "gn:country_code":"VE",
    "gn:dem":471,
    "gn:feature_class":"P",
    "gn:feature_code":"PPL",
    "gn:name":"Apamatico",
    "gn:population":0,
    "gn:timezone":"America/Caracas",
    "iso:country":"VE",
    "wof:name":"Apamatico",
    "wof:placetype":"locality"
},
  "geometry": {"coordinates":[-67.32836999999999,9.95648],"type":"Point"}
}