{
  "type": "Feature",
  "properties": {
    "gn:admin1_code":"1",
    "gn:asciiname":"Aramare",
    "gn:country_code":"VE",
    "gn:dem":115,
    "gn:feature_class":"P",
    "gn:feature_code":"PPL",
    "gn:name":"Aramare",
    "gn:population":0,
    "gn:timezone":"America/Caracas",
    "iso:country":"VE",
    "wof:name":"Aramare",
    "wof:placetype":"locality"
},
  "geometry": {"coordinates":[-66.30492,5.06142],"type":"Point"}
}