{
  "type": "Feature",
  "properties": {
    "gn:admin1_code":"23.0",
    "gn:asciiname":"La Canada Fresca",
    "gn:country_code":"VE",
    "gn:dem":56,
    "gn:feature_class":"P",
    "gn:feature_code":"PPLL",
    "gn:name":"La Ca\u00f1ada Fresca",
    "gn:population":0,
    "gn:timezone":"America/Caracas",
    "iso:country":"VE",
    "wof:name":"La Canada Fresca",
    "wof:placetype":"locality"
},
  "geometry": {"coordinates":[-71.84033000000002,10.8591],"type":"Point"}
}