{
  "type": "Feature",
  "properties": {
    "gn:admin1_code":"11.0",
    "gn:asciiname":"El Paso",
    "gn:country_code":"VE",
    "gn:dem":184,
    "gn:feature_class":"P",
    "gn:feature_code":"PPL",
    "gn:name":"El Paso",
    "gn:population":0,
    "gn:timezone":"America/Caracas",
    "iso:country":"VE",
    "wof:name":"El Paso",
    "wof:placetype":"locality"
},
  "geometry": {"coordinates":[-69.44842,11.32917],"type":"Point"}
}