{
  "type": "Feature",
  "properties": {
    "gn:admin1_code":"3",
    "gn:asciiname":"Atamaica Arriba",
    "gn:cc2":"VE",
    "gn:country_code":"VE",
    "gn:dem":46,
    "gn:feature_class":"P",
    "gn:feature_code":"PPL",
    "gn:name":"Atamaica Arriba",
    "gn:population":0,
    "gn:timezone":"America/Caracas",
    "iso:country":"VE",
    "name:und_x_variant":[
        "Atamaica",
        "Atamaica Arriba"
    ],
    "wof:name":"Atamaica Arriba",
    "wof:placetype":"locality"
},
  "geometry": {"coordinates":[-67.36667,7.51667],"type":"Point"}
}