{
  "type": "Feature",
  "properties": {
    "gn:admin1_code":"11.0",
    "gn:asciiname":"La Sabanita",
    "gn:country_code":"VE",
    "gn:dem":1201,
    "gn:feature_class":"P",
    "gn:feature_code":"PPL",
    "gn:name":"La Sabanita",
    "gn:population":0,
    "gn:timezone":"America/Caracas",
    "iso:country":"VE",
    "wof:name":"La Sabanita",
    "wof:placetype":"locality"
},
  "geometry": {"coordinates":[-69.71944999999999,11.13203],"type":"Point"}
}