{
  "type": "Feature",
  "properties": {
    "gn:admin1_code":"5",
    "gn:asciiname":"Igues",
    "gn:cc2":"VE",
    "gn:country_code":"VE",
    "gn:dem":65,
    "gn:feature_class":"P",
    "gn:feature_code":"PPL",
    "gn:name":"Ig\u00fc\u00e9s",
    "gn:population":0,
    "gn:timezone":"America/Caracas",
    "iso:country":"VE",
    "name:und_x_variant":[
        "Ig\u00fcez",
        "Ig\u00fc\u00e9s"
    ],
    "wof:name":"Igues",
    "wof:placetype":"locality"
},
  "geometry": {"coordinates":[-68.34999999999999,8.76667],"type":"Point"}
}