{
  "type": "Feature",
  "properties": {
    "gn:admin1_code":"4.0",
    "gn:asciiname":"Primer Paso",
    "gn:country_code":"VE",
    "gn:dem":445,
    "gn:feature_class":"P",
    "gn:feature_code":"PPL",
    "gn:name":"Primer Paso",
    "gn:population":0,
    "gn:timezone":"America/Caracas",
    "iso:country":"VE",
    "wof:name":"Primer Paso",
    "wof:placetype":"locality"
},
  "geometry": {"coordinates":[-67.19444,9.96667],"type":"Point"}
}