{
  "type": "Feature",
  "properties": {
    "gn:admin1_code":"21",
    "gn:admin2_code":"2104.0",
    "gn:asciiname":"Chejende",
    "gn:country_code":"VE",
    "gn:dem":986,
    "gn:feature_class":"P",
    "gn:feature_code":"PPLA2",
    "gn:name":"Chejend\u00e9",
    "gn:population":0,
    "gn:timezone":"America/Caracas",
    "iso:country":"VE",
    "name:spa_x_preferred":[
        "Chejend\u00e9"
    ],
    "wof:name":"Chejende",
    "wof:placetype":"locality"
},
  "geometry": {"coordinates":[-70.35696,9.61892],"type":"Point"}
}