{
  "type": "Feature",
  "properties": {
    "gn:admin1_code":"05",
    "gn:asciiname":"Las Cocuizas",
    "gn:country_code":"VE",
    "gn:dem":109,
    "gn:feature_class":"P",
    "gn:feature_code":"PPLL",
    "gn:name":"Las Cocuizas",
    "gn:population":0,
    "gn:timezone":"America/Caracas",
    "iso:country":"VE",
    "wof:name":"Las Cocuizas",
    "wof:placetype":"locality"
},
  "geometry": {"coordinates":[-69.99720000000001,8.01982],"type":"Point"}
}