{
  "type": "Feature",
  "properties": {
    "gn:admin1_code":"11",
    "gn:asciiname":"La Comunidad",
    "gn:cc2":"VE",
    "gn:country_code":"VE",
    "gn:dem":119,
    "gn:feature_class":"P",
    "gn:feature_code":"PPL",
    "gn:name":"La Comunidad",
    "gn:population":0,
    "gn:timezone":"America/Caracas",
    "iso:country":"VE",
    "name:und_x_variant":[
        "Comunidad",
        "Comodidad",
        "La Comunidad"
    ],
    "wof:name":"La Comunidad",
    "wof:placetype":"locality"
},
  "geometry": {"coordinates":[-69.13028,11.38222],"type":"Point"}
}