{
  "type": "Feature",
  "properties": {
    "gn:admin1_code":"13.0",
    "gn:asciiname":"La Aguada",
    "gn:country_code":"VE",
    "gn:dem":1131,
    "gn:feature_class":"P",
    "gn:feature_code":"PPL",
    "gn:name":"La Aguada",
    "gn:population":0,
    "gn:timezone":"America/Caracas",
    "iso:country":"VE",
    "wof:name":"La Aguada",
    "wof:placetype":"locality"
},
  "geometry": {"coordinates":[-69.90089,9.65082],"type":"Point"}
}