{
  "type": "Feature",
  "properties": {
    "gn:admin1_code":"15.0",
    "gn:asciiname":"Alto de La Represa",
    "gn:country_code":"VE",
    "gn:dem":224,
    "gn:feature_class":"P",
    "gn:feature_code":"PPL",
    "gn:name":"Alto de La Represa",
    "gn:population":0,
    "gn:timezone":"America/Caracas",
    "iso:country":"VE",
    "name:und_x_variant":[
        "El Alto de La Represa",
        "Alto de La Represa"
    ],
    "wof:name":"Alto de La Represa",
    "wof:placetype":"locality"
},
  "geometry": {"coordinates":[-66.7257,10.27799],"type":"Point"}
}