{
  "type": "Feature",
  "properties": {
    "gn:admin1_code":"22",
    "gn:asciiname":"Kilometro Cuarenta y Uno",
    "gn:country_code":"VE",
    "gn:dem":71,
    "gn:feature_class":"P",
    "gn:feature_code":"PPL",
    "gn:name":"Kil\u00f3metro Cuarenta y Uno",
    "gn:population":0,
    "gn:timezone":"America/Caracas",
    "iso:country":"VE",
    "name:und_x_variant":[
        "Kil\u00f3metro 41",
        "Kil\u00f3metro Cuarenta y Uno"
    ],
    "wof:name":"Kilometro Cuarenta y Uno",
    "wof:placetype":"locality"
},
  "geometry": {"coordinates":[-68.72689,10.57561],"type":"Point"}
}