{
  "type": "Feature",
  "properties": {
    "gn:admin1_code":"23.0",
    "gn:asciiname":"Santa Marta",
    "gn:country_code":"VE",
    "gn:dem":26,
    "gn:feature_class":"P",
    "gn:feature_code":"PPL",
    "gn:name":"Santa Marta",
    "gn:population":0,
    "gn:timezone":"America/Caracas",
    "iso:country":"VE",
    "wof:name":"Santa Marta",
    "wof:placetype":"locality"
},
  "geometry": {"coordinates":[-72.59164,9.53006],"type":"Point"}
}