{
  "type": "Feature",
  "properties": {
    "gn:admin1_code":"13",
    "gn:asciiname":"La Guapa",
    "gn:country_code":"VE",
    "gn:dem":1043,
    "gn:feature_class":"P",
    "gn:feature_code":"PPL",
    "gn:name":"La Guapa",
    "gn:population":0,
    "gn:timezone":"America/Caracas",
    "iso:country":"VE",
    "name:und_x_variant":[
        "Guapa",
        "La Guapa"
    ],
    "wof:name":"La Guapa",
    "wof:placetype":"locality"
},
  "geometry": {"coordinates":[-69.59479,9.64685],"type":"Point"}
}