{
  "type": "Feature",
  "properties": {
    "gn:admin1_code":"18.0",
    "gn:asciiname":"El Cogollal",
    "gn:country_code":"VE",
    "gn:dem":1548,
    "gn:feature_class":"P",
    "gn:feature_code":"PPL",
    "gn:name":"El Cogollal",
    "gn:population":0,
    "gn:timezone":"America/Caracas",
    "iso:country":"VE",
    "name:spa_x_preferred":[
        "El Cogollal"
    ],
    "wof:name":"El Cogollal",
    "wof:placetype":"locality"
},
  "geometry": {"coordinates":[-69.91833000000001,9.54444],"type":"Point"}
}