{
  "type": "Feature",
  "properties": {
    "gn:admin1_code":"20",
    "gn:asciiname":"Toituna",
    "gn:country_code":"VE",
    "gn:dem":1303,
    "gn:feature_class":"P",
    "gn:feature_code":"PPL",
    "gn:name":"Toituna",
    "gn:population":0,
    "gn:timezone":"America/Caracas",
    "iso:country":"VE",
    "wof:name":"Toituna",
    "wof:placetype":"locality"
},
  "geometry": {"coordinates":[-72.25891999999997,7.85057],"type":"Point"}
}