{
  "type": "Feature",
  "properties": {
    "gn:admin1_code":"20",
    "gn:asciiname":"El Hatico",
    "gn:country_code":"VE",
    "gn:dem":1033,
    "gn:feature_class":"P",
    "gn:feature_code":"PPL",
    "gn:name":"El Hatico",
    "gn:population":0,
    "gn:timezone":"America/Caracas",
    "iso:country":"VE",
    "wof:name":"El Hatico",
    "wof:placetype":"locality"
},
  "geometry": {"coordinates":[-72.0437,8.15302],"type":"Point"}
}