{
  "type": "Feature",
  "properties": {
    "gn:admin1_code":"20",
    "gn:asciiname":"La Trampa",
    "gn:country_code":"VE",
    "gn:dem":1098,
    "gn:feature_class":"P",
    "gn:feature_code":"PPL",
    "gn:name":"La Trampa",
    "gn:population":0,
    "gn:timezone":"America/Caracas",
    "iso:country":"VE",
    "name:spa_x_preferred":[
        "La Trampa"
    ],
    "wof:name":"La Trampa",
    "wof:placetype":"locality"
},
  "geometry": {"coordinates":[-71.73333000000002,7.93333],"type":"Point"}
}