{
  "type": "Feature",
  "properties": {
    "gn:admin1_code":"15.0",
    "gn:asciiname":"Yumare",
    "gn:country_code":"VE",
    "gn:dem":1103,
    "gn:feature_class":"P",
    "gn:feature_code":"PPLL",
    "gn:name":"Yumare",
    "gn:population":0,
    "gn:timezone":"America/Caracas",
    "iso:country":"VE",
    "name:fra_x_preferred":[
        "Yumare"
    ],
    "name:por_x_preferred":[
        "Yumare"
    ],
    "name:spa_x_preferred":[
        "Yumare"
    ],
    "name:zho_x_preferred":[
        "\u5c24\u99ac\u96f7"
    ],
    "wof:name":"Yumare",
    "wof:placetype":"locality"
},
  "geometry": {"coordinates":[-66.79163,10.38507],"type":"Point"}
}