{
  "type": "Feature",
  "properties": {
    "gn:admin1_code":"23",
    "gn:asciiname":"Corral El Mangle",
    "gn:cc2":"VE",
    "gn:country_code":"VE",
    "gn:dem":3,
    "gn:feature_class":"P",
    "gn:feature_code":"PPLL",
    "gn:name":"Corral El Mangle",
    "gn:population":0,
    "gn:timezone":"America/Caracas",
    "iso:country":"VE",
    "name:und_x_variant":[
        "Hacienda El Mangle",
        "Corral El Mangle"
    ],
    "wof:name":"Corral El Mangle",
    "wof:placetype":"locality"
},
  "geometry": {"coordinates":[-71.92166999999998,10.15611],"type":"Point"}
}