{
  "type": "Feature",
  "properties": {
    "gn:admin1_code":"23",
    "gn:asciiname":"Boca del Roto",
    "gn:country_code":"VE",
    "gn:dem":31,
    "gn:feature_class":"P",
    "gn:feature_code":"PPL",
    "gn:name":"Boca del Roto",
    "gn:population":0,
    "gn:timezone":"America/Caracas",
    "iso:country":"VE",
    "wof:name":"Boca del Roto",
    "wof:placetype":"locality"
},
  "geometry": {"coordinates":[-72.62035999999998,8.68595],"type":"Point"}
}