{
  "type": "Feature",
  "properties": {
    "gn:admin1_code":"4.0",
    "gn:asciiname":"El Cambur",
    "gn:country_code":"VE",
    "gn:dem":599,
    "gn:feature_class":"P",
    "gn:feature_code":"PPL",
    "gn:name":"El Cambur",
    "gn:population":0,
    "gn:timezone":"America/Caracas",
    "iso:country":"VE",
    "wof:name":"El Cambur",
    "wof:placetype":"locality"
},
  "geometry": {"coordinates":[-67.434,10.28514],"type":"Point"}
}