{
  "type": "Feature",
  "properties": {
    "gn:admin1_code":"21",
    "gn:asciiname":"Los Canos",
    "gn:country_code":"VE",
    "gn:dem":11,
    "gn:feature_class":"P",
    "gn:feature_code":"PPL",
    "gn:name":"Los Ca\u00f1os",
    "gn:population":0,
    "gn:timezone":"America/Caracas",
    "iso:country":"VE",
    "wof:name":"Los Canos",
    "wof:placetype":"locality"
},
  "geometry": {"coordinates":[-70.97235999999999,9.61598],"type":"Point"}
}