{
  "type": "Feature",
  "properties": {
    "gn:admin1_code":"9",
    "gn:asciiname":"El Raudal",
    "gn:cc2":"VE",
    "gn:country_code":"VE",
    "gn:dem":52,
    "gn:feature_class":"P",
    "gn:feature_code":"PPL",
    "gn:name":"El Raudal",
    "gn:population":0,
    "gn:timezone":"America/Caracas",
    "iso:country":"VE",
    "name:und_x_variant":[
        "Raudal",
        "El Raudal"
    ],
    "wof:name":"El Raudal",
    "wof:placetype":"locality"
},
  "geometry": {"coordinates":[-61.68333000000001,8.38333],"type":"Point"}
}