{
  "type": "Feature",
  "properties": {
    "gn:admin1_code":"4",
    "gn:asciiname":"Puerto Maya",
    "gn:country_code":"VE",
    "gn:dem":29,
    "gn:feature_class":"P",
    "gn:feature_code":"PPL",
    "gn:name":"Puerto Maya",
    "gn:population":0,
    "gn:timezone":"America/Caracas",
    "iso:country":"VE",
    "name:deu_x_preferred":[
        "Puerto Maya"
    ],
    "name:fra_x_preferred":[
        "Puerto Maya"
    ],
    "name:por_x_preferred":[
        "Puerto Maya"
    ],
    "name:spa_x_preferred":[
        "Puerto Maya"
    ],
    "wof:name":"Puerto Maya",
    "wof:placetype":"locality"
},
  "geometry": {"coordinates":[-67.40000000000001,10.53333],"type":"Point"}
}