{
  "type": "Feature",
  "properties": {
    "gn:admin1_code":"16",
    "gn:asciiname":"El Tamarindo",
    "gn:cc2":"VE",
    "gn:country_code":"VE",
    "gn:dem":48,
    "gn:feature_class":"P",
    "gn:feature_code":"PPL",
    "gn:name":"El Tamarindo",
    "gn:population":0,
    "gn:timezone":"America/Caracas",
    "iso:country":"VE",
    "name:und_x_variant":[
        "Amana",
        "Tamarindo",
        "El Tamarindo"
    ],
    "wof:name":"El Tamarindo",
    "wof:placetype":"locality"
},
  "geometry": {"coordinates":[-63.13333000000001,9.65],"type":"Point"}
}