{
  "type": "Feature",
  "properties": {
    "gn:admin1_code":"15",
    "gn:asciiname":"Cano Hondo",
    "gn:country_code":"VE",
    "gn:dem":19,
    "gn:feature_class":"P",
    "gn:feature_code":"PPL",
    "gn:name":"Ca\u00f1o Hondo",
    "gn:population":0,
    "gn:timezone":"America/Caracas",
    "iso:country":"VE",
    "wof:name":"Cano Hondo",
    "wof:placetype":"locality"
},
  "geometry": {"coordinates":[-65.94019,10.2369],"type":"Point"}
}