{
  "type": "Feature",
  "properties": {
    "gn:admin1_code":"6.0",
    "gn:asciiname":"El Merey",
    "gn:country_code":"VE",
    "gn:dem":48,
    "gn:feature_class":"P",
    "gn:feature_code":"PPL",
    "gn:name":"El Merey",
    "gn:population":0,
    "gn:timezone":"America/Caracas",
    "iso:country":"VE",
    "wof:name":"El Merey",
    "wof:placetype":"locality"
},
  "geometry": {"coordinates":[-64.80911999999999,7.61186],"type":"Point"}
}