{
  "type": "Feature",
  "properties": {
    "gn:admin1_code":"6",
    "gn:asciiname":"El Valle",
    "gn:country_code":"VE",
    "gn:dem":300,
    "gn:feature_class":"P",
    "gn:feature_code":"PPL",
    "gn:name":"El Valle",
    "gn:population":0,
    "gn:timezone":"America/Caracas",
    "iso:country":"VE",
    "wof:name":"El Valle",
    "wof:placetype":"locality"
},
  "geometry": {"coordinates":[-62.40917,8.10251],"type":"Point"}
}