{
  "type": "Feature",
  "properties": {
    "gn:admin1_code":"6.0",
    "gn:asciiname":"Comepoco",
    "gn:country_code":"VE",
    "gn:dem":16,
    "gn:feature_class":"P",
    "gn:feature_code":"PPL",
    "gn:name":"Comepoco",
    "gn:population":0,
    "gn:timezone":"America/Caracas",
    "iso:country":"VE",
    "wof:name":"Comepoco",
    "wof:placetype":"locality"
},
  "geometry": {"coordinates":[-65.18444000000001,7.80278],"type":"Point"}
}