{
  "type": "Feature",
  "properties": {
    "gn:admin1_code":"11",
    "gn:asciiname":"El Cardon",
    "gn:country_code":"VE",
    "gn:dem":284,
    "gn:feature_class":"P",
    "gn:feature_code":"PPL",
    "gn:name":"El Card\u00f3n",
    "gn:population":0,
    "gn:timezone":"America/Caracas",
    "iso:country":"VE",
    "wof:name":"El Cardon",
    "wof:placetype":"locality"
},
  "geometry": {"coordinates":[-69.48333000000001,11.21667],"type":"Point"}
}