{
  "type": "Feature",
  "properties": {
    "gn:admin1_code":"6",
    "gn:asciiname":"Sabaneta del Medio",
    "gn:cc2":"VE",
    "gn:country_code":"VE",
    "gn:dem":176,
    "gn:feature_class":"P",
    "gn:feature_code":"PPL",
    "gn:name":"Sabaneta del Medio",
    "gn:population":0,
    "gn:timezone":"America/Caracas",
    "iso:country":"VE",
    "name:und_x_variant":[
        "Sabaneta",
        "Sabaneta del Medio"
    ],
    "wof:name":"Sabaneta del Medio",
    "wof:placetype":"locality"
},
  "geometry": {"coordinates":[-62.73333,7.98333],"type":"Point"}
}