{
  "type": "Feature",
  "properties": {
    "gn:admin1_code":"14.0",
    "gn:asciiname":"Mesa de Poleo",
    "gn:country_code":"VE",
    "gn:dem":2244,
    "gn:feature_class":"P",
    "gn:feature_code":"PPLL",
    "gn:name":"Mesa de Poleo",
    "gn:population":0,
    "gn:timezone":"America/Caracas",
    "iso:country":"VE",
    "wof:name":"Mesa de Poleo",
    "wof:placetype":"locality"
},
  "geometry": {"coordinates":[-71.61754000000001,8.27319],"type":"Point"}
}