{
  "type": "Feature",
  "properties": {
    "gn:admin1_code":"19.0",
    "gn:asciiname":"Canchunchu Viejo",
    "gn:country_code":"VE",
    "gn:dem":72,
    "gn:feature_class":"P",
    "gn:feature_code":"PPL",
    "gn:name":"Canchunchu Viejo",
    "gn:population":0,
    "gn:timezone":"America/Caracas",
    "iso:country":"VE",
    "wof:name":"Canchunchu Viejo",
    "wof:placetype":"locality"
},
  "geometry": {"coordinates":[-63.23889000000001,10.63611],"type":"Point"}
}