{
  "type": "Feature",
  "properties": {
    "gn:admin1_code":"23.0",
    "gn:asciiname":"Rancho L",
    "gn:country_code":"VE",
    "gn:dem":64,
    "gn:feature_class":"P",
    "gn:feature_code":"PPLL",
    "gn:name":"Rancho L",
    "gn:population":0,
    "gn:timezone":"America/Caracas",
    "iso:country":"VE",
    "wof:name":"Rancho L",
    "wof:placetype":"locality"
},
  "geometry": {"coordinates":[-72.22311999999999,10.8403],"type":"Point"}
}