{
  "type": "Feature",
  "properties": {
    "gn:admin1_code":"21",
    "gn:asciiname":"Macarena",
    "gn:country_code":"VE",
    "gn:dem":1165,
    "gn:feature_class":"P",
    "gn:feature_code":"PPL",
    "gn:name":"Macarena",
    "gn:population":0,
    "gn:timezone":"America/Caracas",
    "iso:country":"VE",
    "wof:name":"Macarena",
    "wof:placetype":"locality"
},
  "geometry": {"coordinates":[-70.68049999999999,9.28675],"type":"Point"}
}