{
  "type": "Feature",
  "properties": {
    "gn:admin1_code":"21",
    "gn:asciiname":"Macarena",
    "gn:country_code":"VE",
    "gn:dem":1165,
    "gn:feature_class":"P",
    "gn:feature_code":"PPL",
    "gn:name":"Macarena",
    "gn:population":0,
    "gn:timezone":"America/Caracas",
    "iso:country":"VE",
    "name:deu_x_preferred":[
        "Macarena"
    ],
    "name:fra_x_preferred":[
        "La Macarena"
    ],
    "name:ita_x_preferred":[
        "Macarena"
    ],
    "name:jpn_x_preferred":[
        "\u30de\u30ab\u30ec\u30ca"
    ],
    "name:kor_x_preferred":[
        "\ub9c8\uce74\ub808\ub098"
    ],
    "name:nld_x_preferred":[
        "Macarena"
    ],
    "name:spa_x_preferred":[
        "Macarena"
    ],
    "name:swe_x_preferred":[
        "Macarena"
    ],
    "name:zho_x_preferred":[
        "\u99ac\u5361\u96f7\u7d0d"
    ],
    "wof:name":"Macarena",
    "wof:placetype":"locality"
},
  "geometry": {"coordinates":[-70.68049999999999,9.28675],"type":"Point"}
}