{
  "type": "Feature",
  "properties": {
    "gn:admin1_code":"15",
    "gn:asciiname":"El Guayabo",
    "gn:cc2":"VE",
    "gn:country_code":"VE",
    "gn:dem":1216,
    "gn:feature_class":"P",
    "gn:feature_code":"PPL",
    "gn:name":"El Guayabo",
    "gn:population":0,
    "gn:timezone":"America/Caracas",
    "iso:country":"VE",
    "name:und_x_variant":[
        "La Cortado del Guayabo",
        "El Guayabo"
    ],
    "wof:name":"El Guayabo",
    "wof:placetype":"locality"
},
  "geometry": {"coordinates":[-66.93333,10.35],"type":"Point"}
}