{
  "type": "Feature",
  "properties": {
    "gn:admin1_code":"23",
    "gn:asciiname":"El Manilla",
    "gn:cc2":"VE",
    "gn:country_code":"VE",
    "gn:dem":18,
    "gn:feature_class":"P",
    "gn:feature_code":"PPL",
    "gn:name":"El Manilla",
    "gn:population":0,
    "gn:timezone":"America/Caracas",
    "iso:country":"VE",
    "name:und_x_variant":[
        "La Manilla",
        "El Manila",
        "El Manilla"
    ],
    "wof:name":"El Manilla",
    "wof:placetype":"locality"
},
  "geometry": {"coordinates":[-71.61667,10.58333],"type":"Point"}
}