{
  "type": "Feature",
  "properties": {
    "gn:admin1_code":"05",
    "gn:asciiname":"Rondonero",
    "gn:country_code":"VE",
    "gn:dem":491,
    "gn:feature_class":"P",
    "gn:feature_code":"PPLL",
    "gn:name":"Rondonero",
    "gn:population":0,
    "gn:timezone":"America/Caracas",
    "iso:country":"VE",
    "wof:name":"Rondonero",
    "wof:placetype":"locality"
},
  "geometry": {"coordinates":[-70.15243000000001,8.76481],"type":"Point"}
}