{
  "type": "Feature",
  "properties": {
    "gn:admin1_code":"19.0",
    "gn:asciiname":"Baltasara",
    "gn:country_code":"VE",
    "gn:dem":291,
    "gn:feature_class":"P",
    "gn:feature_code":"PPLL",
    "gn:name":"Baltasara",
    "gn:population":0,
    "gn:timezone":"America/Caracas",
    "iso:country":"VE",
    "wof:name":"Baltasara",
    "wof:placetype":"locality"
},
  "geometry": {"coordinates":[-64.13698000000001,10.32324],"type":"Point"}
}