{
  "type": "Feature",
  "properties": {
    "gn:admin1_code":"15",
    "gn:asciiname":"Onoto",
    "gn:country_code":"VE",
    "gn:dem":366,
    "gn:feature_class":"P",
    "gn:feature_code":"PPL",
    "gn:name":"Onoto",
    "gn:population":0,
    "gn:timezone":"America/Caracas",
    "iso:country":"VE",
    "name:ceb_x_preferred":[
        "Onoto"
    ],
    "name:fra_x_preferred":[
        "Onoto"
    ],
    "name:por_x_preferred":[
        "Onoto"
    ],
    "name:rus_x_preferred":[
        "\u041e\u043d\u043e\u0442\u043e"
    ],
    "name:spa_x_preferred":[
        "Onoto"
    ],
    "name:zho_x_preferred":[
        "\u5967\u8afe\u6258"
    ],
    "wof:name":"Onoto",
    "wof:placetype":"locality"
},
  "geometry": {"coordinates":[-66.46666999999999,10.33333],"type":"Point"}
}