{
  "type": "Feature",
  "properties": {
    "gn:admin1_code":"23.0",
    "gn:asciiname":"Mata de Coco",
    "gn:country_code":"VE",
    "gn:dem":10,
    "gn:feature_class":"P",
    "gn:feature_code":"PPLL",
    "gn:name":"Mata de Coco",
    "gn:population":0,
    "gn:timezone":"America/Caracas",
    "iso:country":"VE",
    "wof:name":"Mata de Coco",
    "wof:placetype":"locality"
},
  "geometry": {"coordinates":[-71.59756999999998,8.9351],"type":"Point"}
}