{
  "type": "Feature",
  "properties": {
    "gn:admin1_code":"12",
    "gn:asciiname":"El Gallego",
    "gn:country_code":"VE",
    "gn:dem":222,
    "gn:feature_class":"P",
    "gn:feature_code":"PPL",
    "gn:name":"El Gallego",
    "gn:population":0,
    "gn:timezone":"America/Caracas",
    "iso:country":"VE",
    "wof:name":"El Gallego",
    "wof:placetype":"locality"
},
  "geometry": {"coordinates":[-66.28326,9.63375],"type":"Point"}
}