{
  "type": "Feature",
  "properties": {
    "gn:admin1_code":"9",
    "gn:asciiname":"Las Hermanas",
    "gn:cc2":"VE",
    "gn:country_code":"VE",
    "gn:dem":62,
    "gn:feature_class":"P",
    "gn:feature_code":"PPL",
    "gn:name":"Las Hermanas",
    "gn:population":0,
    "gn:timezone":"America/Caracas",
    "iso:country":"VE",
    "name:und_x_variant":[
        "Hermanas",
        "Las Hermanas"
    ],
    "wof:name":"Las Hermanas",
    "wof:placetype":"locality"
},
  "geometry": {"coordinates":[-61.69333,8.44444],"type":"Point"}
}