{
  "type": "Feature",
  "properties": {
    "gn:country":"VE",
    "iso:country":"VE",
    "qs_pg:aaroncc":"VE",
    "qs_pg:gn_country":"VE",
    "qs_pg:name":"Lecherias",
    "qs_pg:name_adm0":"Venezuela",
    "qs_pg:name_adm1":"Anzoategui",
    "qs_pg:photos":188,
    "qs_pg:photos_1k":38,
    "qs_pg:photos_9k":5,
    "qs_pg:photos_9r":7,
    "qs_pg:photos_all":1059,
    "qs_pg:photos_sr":4,
    "qs_pg:pop_sr":0,
    "qs_pg:qs_pg_placetype":"localadmin",
    "qs_pg:qs_pg_placetype_gp":"LocalAdmin",
    "qs_pg:woe_adm0":23424982,
    "woe:adm0_id":23424982,
    "woe:name_adm0":"Venezuela",
    "woe:name_adm1":"Anzoategui",
    "woe:placetype":"LocalAdmin",
    "wof:name":"Lecherias",
    "wof:placetype":"localadmin"
},
  "geometry": {"coordinates":[-64.68423799999999,10.189242],"type":"Point"}
}