{
  "type": "Feature",
  "properties": {
    "gn:admin1_code":"5",
    "gn:asciiname":"Espiritu",
    "gn:country_code":"VE",
    "gn:dem":91,
    "gn:feature_class":"P",
    "gn:feature_code":"PPL",
    "gn:name":"Esp\u00edritu",
    "gn:population":0,
    "gn:timezone":"America/Caracas",
    "iso:country":"VE",
    "wof:name":"Espiritu",
    "wof:placetype":"locality"
},
  "geometry": {"coordinates":[-69.41667,8.33333],"type":"Point"}
}