{
  "type": "Feature",
  "properties": {
    "gn:admin1_code":"6.0",
    "gn:asciiname":"Mantecal",
    "gn:country_code":"VE",
    "gn:dem":326,
    "gn:feature_class":"P",
    "gn:feature_code":"PPL",
    "gn:name":"Mantecal",
    "gn:population":0,
    "gn:timezone":"America/Caracas",
    "iso:country":"VE",
    "wof:name":"Mantecal",
    "wof:placetype":"locality"
},
  "geometry": {"coordinates":[-61.87056,7.99556],"type":"Point"}
}