{
  "type": "Feature",
  "properties": {
    "gn:admin1_code":"11.0",
    "gn:asciiname":"Hierva Brava",
    "gn:country_code":"VE",
    "gn:dem":120,
    "gn:feature_class":"P",
    "gn:feature_code":"PPLL",
    "gn:name":"Hierva Brava",
    "gn:population":0,
    "gn:timezone":"America/Caracas",
    "iso:country":"VE",
    "wof:name":"Hierva Brava",
    "wof:placetype":"locality"
},
  "geometry": {"coordinates":[-70.68895000000001,10.88437],"type":"Point"}
}