{
  "type": "Feature",
  "properties": {
    "gn:admin1_code":"11",
    "gn:asciiname":"La Boca",
    "gn:country_code":"VE",
    "gn:dem":2,
    "gn:feature_class":"P",
    "gn:feature_code":"PPL",
    "gn:name":"La Boca",
    "gn:population":0,
    "gn:timezone":"America/Caracas",
    "iso:country":"VE",
    "name:cat_x_preferred":[
        "La Boca"
    ],
    "name:ces_x_preferred":[
        "La Boca"
    ],
    "name:deu_x_preferred":[
        "La Boca"
    ],
    "name:eus_x_preferred":[
        "La Boca"
    ],
    "name:fas_x_preferred":[
        "\u0644\u0627 \u0628\u0648\u06a9\u0627"
    ],
    "name:fra_x_preferred":[
        "La Boca"
    ],
    "name:heb_x_preferred":[
        "\u05dc\u05d4 \u05d1\u05d5\u05e7\u05d4"
    ],
    "name:hun_x_preferred":[
        "La Boca"
    ],
    "name:hye_x_preferred":[
        "\u053c\u0561 \u0532\u0578\u056f\u0561"
    ],
    "name:ita_x_preferred":[
        "La Boca"
    ],
    "name:jpn_x_preferred":[
        "\u30e9\u30fb\u30dc\u30ab"
    ],
    "name:lat_x_preferred":[
        "La Boca"
    ],
    "name:lij_x_preferred":[
        "A Bocca"
    ],
    "name:lit_x_preferred":[
        "La Boka"
    ],
    "name:msa_x_preferred":[
        "La Boca"
    ],
    "name:nld_x_preferred":[
        "La Boca"
    ],
    "name:nor_x_preferred":[
        "La Boca"
    ],
    "name:oci_x_preferred":[
        "La Boca"
    ],
    "name:oss_x_preferred":[
        "\u041b\u0430-\u0411\u043e\u043a\u00e6"
    ],
    "name:pol_x_preferred":[
        "La Boca"
    ],
    "name:por_x_preferred":[
        "La Boca"
    ],
    "name:rus_x_preferred":[
        "\u041b\u0430-\u0411\u043e\u043a\u0430"
    ],
    "name:slk_x_preferred":[
        "La Boca"
    ],
    "name:spa_x_preferred":[
        "La Boca"
    ],
    "name:swe_x_preferred":[
        "La Boca"
    ],
    "name:tur_x_preferred":[
        "La Boca"
    ],
    "name:ukr_x_preferred":[
        "\u041b\u0430 \u0411\u043e\u043a\u0430"
    ],
    "name:urd_x_preferred":[
        "\u0644\u0627 \u0628\u0648\u06a9\u0627"
    ],
    "name:zho_x_preferred":[
        "\u62c9\u535a\u5361"
    ],
    "wof:name":"La Boca",
    "wof:placetype":"locality"
},
  "geometry": {"coordinates":[-70.13333,12.11667],"type":"Point"}
}