{
  "type": "Feature",
  "properties": {
    "gn:admin1_code":"11",
    "gn:asciiname":"La Boca",
    "gn:country_code":"VE",
    "gn:dem":2,
    "gn:feature_class":"P",
    "gn:feature_code":"PPL",
    "gn:name":"La Boca",
    "gn:population":0,
    "gn:timezone":"America/Caracas",
    "iso:country":"VE",
    "wof:name":"La Boca",
    "wof:placetype":"locality"
},
  "geometry": {"coordinates":[-70.13333,12.11667],"type":"Point"}
}