{
  "type": "Feature",
  "properties": {
    "gn:admin1_code":"6.0",
    "gn:asciiname":"Guaimare",
    "gn:country_code":"VE",
    "gn:dem":148,
    "gn:feature_class":"P",
    "gn:feature_code":"PPL",
    "gn:name":"Guaimare",
    "gn:population":0,
    "gn:timezone":"America/Caracas",
    "iso:country":"VE",
    "wof:name":"Guaimare",
    "wof:placetype":"locality"
},
  "geometry": {"coordinates":[-63.27505,8.08916],"type":"Point"}
}