{
  "type": "Feature",
  "properties": {
    "gn:admin1_code":"18.0",
    "gn:asciiname":"Agua Viva",
    "gn:country_code":"VE",
    "gn:dem":110,
    "gn:feature_class":"P",
    "gn:feature_code":"PPL",
    "gn:name":"Agua Viva",
    "gn:population":0,
    "gn:timezone":"America/Caracas",
    "iso:country":"VE",
    "name:spa_x_preferred":[
        "Agua Viva"
    ],
    "wof:name":"Agua Viva",
    "wof:placetype":"locality"
},
  "geometry": {"coordinates":[-69.20379,9.15527],"type":"Point"}
}