{
  "type": "Feature",
  "properties": {
    "gn:admin1_code":"22",
    "gn:asciiname":"El Portachuelo",
    "gn:country_code":"VE",
    "gn:dem":687,
    "gn:feature_class":"P",
    "gn:feature_code":"PPL",
    "gn:name":"El Portachuelo",
    "gn:population":0,
    "gn:timezone":"America/Caracas",
    "iso:country":"VE",
    "wof:name":"El Portachuelo",
    "wof:placetype":"locality"
},
  "geometry": {"coordinates":[-69.43399000000001,10.10385],"type":"Point"}
}