{
  "type": "Feature",
  "properties": {
    "gn:admin1_code":"13.0",
    "gn:asciiname":"Campo Lindo",
    "gn:country_code":"VE",
    "gn:dem":1336,
    "gn:feature_class":"P",
    "gn:feature_code":"PPL",
    "gn:name":"Campo Lindo",
    "gn:population":0,
    "gn:timezone":"America/Caracas",
    "iso:country":"VE",
    "wof:name":"Campo Lindo",
    "wof:placetype":"locality"
},
  "geometry": {"coordinates":[-70.06147,9.89157],"type":"Point"}
}