{
  "type": "Feature",
  "properties": {
    "iso:country":"VE",
    "name:chi_x_preferred":[
        "\u79d1\u9686"
    ],
    "name:dut_x_preferred":[
        "Col\u00f3n"
    ],
    "name:eng_x_colloquial":[
        "San Juan De Colon"
    ],
    "name:eng_x_preferred":[
        "San Juan De Colon"
    ],
    "name:eng_x_variant":[
        "San Juan de Col\u00f3n",
        "Col\u00f3n"
    ],
    "name:fra_x_preferred":[
        "San Juan de Col\u00f3n"
    ],
    "name:fre_x_preferred":[
        "San Juan de Col\u00f3n"
    ],
    "name:pol_x_preferred":[
        "San Juan de Col\u00f3n"
    ],
    "name:por_x_colloquial":[
        "San Juan De Colon"
    ],
    "name:por_x_preferred":[
        "Col\u00f3n"
    ],
    "name:por_x_variant":[
        "San Juan De Colon",
        "San Juan de Col\u00f3n"
    ],
    "name:spa_x_colloquial":[
        "San Juan De Colon"
    ],
    "name:spa_x_preferred":[
        "San Juan de Col\u00f3n"
    ],
    "name:spa_x_variant":[
        "Col\u00f3n",
        "San Juan De Colon"
    ],
    "name:zho_x_preferred":[
        "\u79d1\u9686"
    ],
    "qs:gn_country":"VE",
    "qs:gn_fcode":"PPL",
    "qs:gn_pop":38233,
    "qs:name":"San Juan de Col\u00f3n",
    "qs:name_adm0":"Venezuela",
    "qs:name_adm1":"Tachira",
    "qs:photos":62,
    "qs:photos_1k":13,
    "qs:photos_9k":1,
    "qs:photos_9r":2,
    "qs:photos_all":62,
    "qs:photos_sr":2,
    "qs:placetype":"Town",
    "qs:pop_sr":"7",
    "qs:woe_adm0":23424982,
    "wof:name":"San Juan de Col\u00f3n",
    "wof:placetype":"locality",
    "wof:population":38233
},
  "geometry": {"coordinates":[-72.26053,8.03125],"type":"Point"}
}