{
  "type": "Feature",
  "properties": {
    "iso:country":"VE",
    "qs:gn_pop":0,
    "qs:name":"Calabozo",
    "qs:name_adm0":"Venezuela",
    "qs:name_adm1":"Guarico",
    "qs:photos":4,
    "qs:photos_1k":1,
    "qs:photos_9k":1,
    "qs:photos_9r":2,
    "qs:photos_all":54,
    "qs:photos_sr":1,
    "qs:placetype":"LocalAdmin",
    "qs:pop_sr":"0",
    "qs:woe_adm0":23424982,
    "wof:name":"Calabozo",
    "wof:placetype":"localadmin"
},
  "geometry": {"coordinates":[-67.428421,8.922189],"type":"Point"}
}