{
  "type": "Feature",
  "properties": {
    "iso:country":"VE",
    "name:ceb_x_preferred":[
        "Calabozo"
    ],
    "name:deu_x_preferred":[
        "Calabozo"
    ],
    "name:epo_x_preferred":[
        "Calabozo"
    ],
    "name:fra_x_preferred":[
        "Calabozo"
    ],
    "name:heb_x_preferred":[
        "\u05e7\u05dc\u05d1\u05d5\u05d6\u05d5"
    ],
    "name:hun_x_preferred":[
        "Calabozo"
    ],
    "name:ita_x_preferred":[
        "Calabozo"
    ],
    "name:jpn_x_preferred":[
        "\u30ab\u30e9\u30dc\u30bd"
    ],
    "name:kat_x_preferred":[
        "\u10d9\u10d0\u10da\u10d0\u10d1\u10dd\u10e1\u10dd"
    ],
    "name:lit_x_preferred":[
        "Kalabosas"
    ],
    "name:pol_x_preferred":[
        "Calabozo"
    ],
    "name:por_x_preferred":[
        "Calabozo"
    ],
    "name:spa_x_preferred":[
        "Calabozo"
    ],
    "name:tat_x_preferred":[
        "\u041a\u0430\u043b\u0430\u0431\u043e\u0441\u043e"
    ],
    "name:vol_x_preferred":[
        "Calabozo"
    ],
    "name:zho_x_preferred":[
        "\u5361\u62c9\u6c83\u7d22"
    ],
    "qs:gn_pop":0,
    "qs:name":"Calabozo",
    "qs:name_adm0":"Venezuela",
    "qs:name_adm1":"Guarico",
    "qs:photos":4,
    "qs:photos_1k":1,
    "qs:photos_9k":1,
    "qs:photos_9r":2,
    "qs:photos_all":54,
    "qs:photos_sr":1,
    "qs:placetype":"LocalAdmin",
    "qs:pop_sr":"0",
    "qs:woe_adm0":23424982,
    "wof:name":"Calabozo",
    "wof:placetype":"localadmin"
},
  "geometry": {"coordinates":[-67.428421,8.922189],"type":"Point"}
}