{
  "type": "Feature",
  "properties": {
    "gn:admin1_code":"05",
    "gn:asciiname":"San Juan Bautista",
    "gn:country_code":"VE",
    "gn:dem":2532,
    "gn:feature_class":"P",
    "gn:feature_code":"PPL",
    "gn:name":"San Juan Bautista",
    "gn:population":0,
    "gn:timezone":"America/Caracas",
    "iso:country":"VE",
    "wof:name":"San Juan Bautista",
    "wof:placetype":"locality"
},
  "geometry": {"coordinates":[-71.03333000000001,8.36667],"type":"Point"}
}