{
  "type": "Feature",
  "properties": {
    "gn:admin1_code":"8",
    "gn:asciiname":"Barreto",
    "gn:cc2":"VE",
    "gn:country_code":"VE",
    "gn:dem":101,
    "gn:feature_class":"P",
    "gn:feature_code":"PPL",
    "gn:name":"Barreto",
    "gn:population":0,
    "gn:timezone":"America/Caracas",
    "iso:country":"VE",
    "name:und_x_variant":[
        "Barrito",
        "Barreto"
    ],
    "wof:name":"Barreto",
    "wof:placetype":"locality"
},
  "geometry": {"coordinates":[-68.71666999999999,9.45],"type":"Point"}
}