{
  "type": "Feature",
  "properties": {
    "gn:admin1_code":"6.0",
    "gn:asciiname":"Guajillal",
    "gn:country_code":"VE",
    "gn:dem":334,
    "gn:feature_class":"P",
    "gn:feature_code":"PPL",
    "gn:name":"Guajillal",
    "gn:population":0,
    "gn:timezone":"America/Caracas",
    "iso:country":"VE",
    "wof:name":"Guajillal",
    "wof:placetype":"locality"
},
  "geometry": {"coordinates":[-63.21556,7.455],"type":"Point"}
}