{
  "type": "Feature",
  "properties": {
    "gn:admin1_code":"11",
    "gn:asciiname":"La Costa",
    "gn:country_code":"VE",
    "gn:dem":39,
    "gn:feature_class":"P",
    "gn:feature_code":"PPL",
    "gn:name":"La Costa",
    "gn:population":0,
    "gn:timezone":"America/Caracas",
    "iso:country":"VE",
    "name:ara_x_preferred":[
        "\u0644\u0627 \u0643\u0648\u0633\u062a\u0627"
    ],
    "wof:name":"La Costa",
    "wof:placetype":"locality"
},
  "geometry": {"coordinates":[-68.83333,11.43333],"type":"Point"}
}