{
  "type": "Feature",
  "properties": {
    "gn:admin1_code":"5",
    "gn:asciiname":"Guamito",
    "gn:country_code":"VE",
    "gn:dem":130,
    "gn:feature_class":"P",
    "gn:feature_code":"PPL",
    "gn:name":"Guamito",
    "gn:population":0,
    "gn:timezone":"America/Caracas",
    "iso:country":"VE",
    "wof:name":"Guamito",
    "wof:placetype":"locality"
},
  "geometry": {"coordinates":[-69.98331999999999,8.42729],"type":"Point"}
}