{
  "type": "Feature",
  "properties": {
    "gn:admin1_code":"20.0",
    "gn:asciiname":"Los Angelitos",
    "gn:country_code":"VE",
    "gn:dem":1094,
    "gn:feature_class":"P",
    "gn:feature_code":"PPLL",
    "gn:name":"Los Angelitos",
    "gn:population":0,
    "gn:timezone":"America/Caracas",
    "iso:country":"VE",
    "wof:name":"Los Angelitos",
    "wof:placetype":"locality"
},
  "geometry": {"coordinates":[-71.5724,7.92865],"type":"Point"}
}