{
  "type": "Feature",
  "properties": {
    "gn:admin1_code":"05",
    "gn:asciiname":"La Yuca",
    "gn:country_code":"VE",
    "gn:dem":813,
    "gn:feature_class":"P",
    "gn:feature_code":"PPL",
    "gn:name":"La Yuca",
    "gn:population":0,
    "gn:timezone":"America/Caracas",
    "iso:country":"VE",
    "wof:name":"La Yuca",
    "wof:placetype":"locality"
},
  "geometry": {"coordinates":[-70.49486999999998,8.80874],"type":"Point"}
}