{
  "type": "Feature",
  "properties": {
    "gn:admin1_code":"17",
    "gn:asciiname":"Puerto Moreno",
    "gn:country_code":"VE",
    "gn:dem":6,
    "gn:feature_class":"P",
    "gn:feature_code":"PPL",
    "gn:name":"Puerto Moreno",
    "gn:population":0,
    "gn:timezone":"America/Caracas",
    "iso:country":"VE",
    "wof:name":"Puerto Moreno",
    "wof:placetype":"locality"
},
  "geometry": {"coordinates":[-63.81137,10.98261],"type":"Point"}
}