{
  "type": "Feature",
  "properties": {
    "gn:admin1_code":"20",
    "gn:asciiname":"Santa Ana del Tachira",
    "gn:country_code":"VE",
    "gn:dem":810,
    "gn:feature_class":"P",
    "gn:feature_code":"PPL",
    "gn:name":"Santa Ana del Tachira",
    "gn:population":0,
    "gn:timezone":"America/Caracas",
    "iso:country":"VE",
    "name:spa_x_preferred":[
        "Santa Ana del T\u00e1chira"
    ],
    "name:und_x_variant":[
        "Santa Ana",
        "Santa Ana del Tachira"
    ],
    "wof:name":"Santa Ana del Tachira",
    "wof:placetype":"locality"
},
  "geometry": {"coordinates":[-72.27798,7.64175],"type":"Point"}
}