{
  "type": "Feature",
  "properties": {
    "gn:admin1_code":"20",
    "gn:asciiname":"La Morita",
    "gn:country_code":"VE",
    "gn:dem":478,
    "gn:feature_class":"P",
    "gn:feature_code":"PPL",
    "gn:name":"La Morita",
    "gn:population":0,
    "gn:timezone":"America/Caracas",
    "iso:country":"VE",
    "wof:name":"La Morita",
    "wof:placetype":"locality"
},
  "geometry": {"coordinates":[-72.02041,7.66583],"type":"Point"}
}