{
  "type": "Feature",
  "properties": {
    "gn:admin1_code":"6.0",
    "gn:asciiname":"Las Cuevas",
    "gn:country_code":"VE",
    "gn:dem":73,
    "gn:feature_class":"P",
    "gn:feature_code":"PPL",
    "gn:name":"Las Cuevas",
    "gn:population":0,
    "gn:timezone":"America/Caracas",
    "iso:country":"VE",
    "wof:name":"Las Cuevas",
    "wof:placetype":"locality"
},
  "geometry": {"coordinates":[-65.36431999999999,7.3894],"type":"Point"}
}