{
  "type": "Feature",
  "properties": {
    "gn:admin1_code":"07",
    "gn:asciiname":"Morrocoy",
    "gn:country_code":"VE",
    "gn:dem":454,
    "gn:feature_class":"P",
    "gn:feature_code":"PPL",
    "gn:name":"Morrocoy",
    "gn:population":0,
    "gn:timezone":"America/Caracas",
    "iso:country":"VE",
    "wof:name":"Morrocoy",
    "wof:placetype":"locality"
},
  "geometry": {"coordinates":[-67.96297,9.83901],"type":"Point"}
}