{
  "type": "Feature",
  "properties": {
    "gn:admin1_code":"19.0",
    "gn:asciiname":"Campo Libre",
    "gn:country_code":"VE",
    "gn:dem":906,
    "gn:feature_class":"P",
    "gn:feature_code":"PPLL",
    "gn:name":"Campo Libre",
    "gn:population":0,
    "gn:timezone":"America/Caracas",
    "iso:country":"VE",
    "wof:name":"Campo Libre",
    "wof:placetype":"locality"
},
  "geometry": {"coordinates":[-64.43895999999999,10.19276],"type":"Point"}
}