{
  "type": "Feature",
  "properties": {
    "gn:admin1_code":"16",
    "gn:asciiname":"La Alegria",
    "gn:country_code":"VE",
    "gn:dem":110,
    "gn:feature_class":"P",
    "gn:feature_code":"PPL",
    "gn:name":"La Alegr\u00eda",
    "gn:population":0,
    "gn:timezone":"America/Caracas",
    "iso:country":"VE",
    "wof:name":"La Alegria",
    "wof:placetype":"locality"
},
  "geometry": {"coordinates":[-63.34016999999999,9.20127],"type":"Point"}
}