{
  "type": "Feature",
  "properties": {
    "gn:admin1_code":"12",
    "gn:asciiname":"Corral Viejo",
    "gn:country_code":"VE",
    "gn:dem":184,
    "gn:feature_class":"P",
    "gn:feature_code":"PPL",
    "gn:name":"Corral Viejo",
    "gn:population":0,
    "gn:timezone":"America/Caracas",
    "iso:country":"VE",
    "wof:name":"Corral Viejo",
    "wof:placetype":"locality"
},
  "geometry": {"coordinates":[-67.02396,9.28294],"type":"Point"}
}