{
  "type": "Feature",
  "properties": {
    "gn:admin1_code":"6.0",
    "gn:asciiname":"Panadero",
    "gn:country_code":"VE",
    "gn:dem":141,
    "gn:feature_class":"P",
    "gn:feature_code":"PPL",
    "gn:name":"Panadero",
    "gn:population":0,
    "gn:timezone":"America/Caracas",
    "iso:country":"VE",
    "wof:name":"Panadero",
    "wof:placetype":"locality"
},
  "geometry": {"coordinates":[-63.82662,7.7831],"type":"Point"}
}