{
  "type": "Feature",
  "properties": {
    "gn:admin1_code":"4.0",
    "gn:asciiname":"Pozo Azul",
    "gn:country_code":"VE",
    "gn:dem":628,
    "gn:feature_class":"P",
    "gn:feature_code":"PPL",
    "gn:name":"Pozo Azul",
    "gn:population":0,
    "gn:timezone":"America/Caracas",
    "iso:country":"VE",
    "wof:name":"Pozo Azul",
    "wof:placetype":"locality"
},
  "geometry": {"coordinates":[-67.38197,10.10628],"type":"Point"}
}