{
  "type": "Feature",
  "properties": {
    "gn:admin1_code":"5",
    "gn:asciiname":"Curito",
    "gn:country_code":"VE",
    "gn:dem":228,
    "gn:feature_class":"P",
    "gn:feature_code":"PPL",
    "gn:name":"Curito",
    "gn:population":0,
    "gn:timezone":"America/Caracas",
    "iso:country":"VE",
    "name:und_x_variant":[
        "El Curito",
        "Curito"
    ],
    "wof:name":"Curito",
    "wof:placetype":"locality"
},
  "geometry": {"coordinates":[-71.02703000000002,7.97091],"type":"Point"}
}