{
  "type": "Feature",
  "properties": {
    "gn:country":"VE",
    "gn:fcode":"PPLA2",
    "gn:pop":364684,
    "iso:country":"VE",
    "name:ara_x_preferred":[
        "\u0628\u064a\u062a\u0627\u0631\u064a"
    ],
    "name:ben_x_preferred":[
        "\u09aa\u09cd\u09b2\u09be\u09a4\u09be\u09b0\u09c7"
    ],
    "name:bul_x_preferred":[
        "\u041f\u0435\u0442\u0430\u0440\u0435"
    ],
    "name:chi_x_preferred":[
        "\u4f69\u5854\u96f7"
    ],
    "name:dan_x_preferred":[
        "Petare"
    ],
    "name:dut_x_preferred":[
        "Petare"
    ],
    "name:eng_x_preferred":[
        "Petare"
    ],
    "name:epo_x_preferred":[
        "Petare"
    ],
    "name:fin_x_preferred":[
        "Petare"
    ],
    "name:fre_x_preferred":[
        "Petare"
    ],
    "name:geo_x_preferred":[
        "\u10de\u10d4\u10e2\u10d0\u10e0\u10d4"
    ],
    "name:ger_x_preferred":[
        "Petare"
    ],
    "name:gre_x_preferred":[
        "\u03a0\u03b5\u03c4\u03ac\u03c1\u03b5"
    ],
    "name:guj_x_preferred":[
        "\u0aaa\u0ac7\u0a9f\u0ab0\u0ac7"
    ],
    "name:hin_x_preferred":[
        "\u092a\u0947\u091f\u093e\u0930\u0947"
    ],
    "name:ind_x_preferred":[
        "Petare"
    ],
    "name:ita_x_preferred":[
        "Petare"
    ],
    "name:jpn_x_preferred":[
        "\u30da\u30bf\u30ec"
    ],
    "name:kan_x_preferred":[
        "\u0caa\u0cc6\u0c9f\u0cb0\u0cc6"
    ],
    "name:kat_x_preferred":[
        "\u10de\u10d4\u10e2\u10d0\u10e0\u10d4"
    ],
    "name:kor_x_preferred":[
        "\ud398\ud0c0\ub808"
    ],
    "name:lav_x_preferred":[
        "Petare"
    ],
    "name:lit_x_preferred":[
        "Petar\u0117"
    ],
    "name:mar_x_preferred":[
        "\u092a\u0947\u091f\u093e\u0930\u0947"
    ],
    "name:may_x_preferred":[
        "Petare"
    ],
    "name:nob_x_preferred":[
        "Petare"
    ],
    "name:pol_x_preferred":[
        "Petare"
    ],
    "name:por_x_preferred":[
        "Petare"
    ],
    "name:rus_x_preferred":[
        "\u041f\u0435\u0442\u0430\u0440\u0435"
    ],
    "name:sin_x_preferred":[
        "\u0db4\u0dd9\u0da7\u0dbb\u0dda"
    ],
    "name:spa_x_preferred":[
        "Petare"
    ],
    "name:swe_x_preferred":[
        "Petare"
    ],
    "name:tam_x_preferred":[
        "\u0baa\u0bc6\u0b9f\u0bcd\u0b9f\u0bbe\u0bb0\u0bc7"
    ],
    "name:tel_x_preferred":[
        "\u0c2a\u0c47\u0c1f\u0c30\u0c47"
    ],
    "name:tha_x_preferred":[
        "\u0e1e\u0e35\u0e17\u0e32\u0e40\u0e23\u0e48"
    ],
    "name:tur_x_preferred":[
        "Petare"
    ],
    "name:ukr_x_preferred":[
        "\u041f\u0435\u0442\u0430\u0440\u0435"
    ],
    "name:urd_x_preferred":[
        "\u067e\u06cc\u062a\u0627\u0631\u06cc"
    ],
    "name:vie_x_preferred":[
        "Petare"
    ],
    "name:war_x_preferred":[
        "Petare"
    ],
    "name:zho_x_preferred":[
        "\u4f69\u5854\u96f7"
    ],
    "qs:name":"Petare",
    "qs:photos_9r":0,
    "qs:photos_sr":0,
    "qs:pop_sr":"10",
    "wd:wordcount":138,
    "wof:name":"Petare",
    "wof:placetype":"locality",
    "wof:population":364684
},
  "geometry": {"coordinates":[-66.80155000000001,10.47226],"type":"Point"}
}