{
  "type": "Feature",
  "properties": {
    "gn:admin1_code":"13.0",
    "gn:asciiname":"Las Tres Marias",
    "gn:country_code":"VE",
    "gn:dem":1087,
    "gn:feature_class":"P",
    "gn:feature_code":"PPL",
    "gn:name":"Las Tres Mar\u00edas",
    "gn:population":0,
    "gn:timezone":"America/Caracas",
    "iso:country":"VE",
    "name:ceb_x_preferred":[
        "Las Tres Marias"
    ],
    "name:swe_x_preferred":[
        "Las Tres Marias"
    ],
    "wof:name":"Las Tres Marias",
    "wof:placetype":"locality"
},
  "geometry": {"coordinates":[-70.60611,10.37444],"type":"Point"}
}