{
  "type": "Feature",
  "properties": {
    "gn:admin1_code":"12",
    "gn:asciiname":"El Perro",
    "gn:cc2":"VE",
    "gn:country_code":"VE",
    "gn:dem":105,
    "gn:feature_class":"P",
    "gn:feature_code":"PPL",
    "gn:name":"El Perro",
    "gn:population":0,
    "gn:timezone":"America/Caracas",
    "iso:country":"VE",
    "name:und_x_variant":[
        "El Perio",
        "El Perro"
    ],
    "wof:name":"El Perro",
    "wof:placetype":"locality"
},
  "geometry": {"coordinates":[-67.40222,8.89444],"type":"Point"}
}