{
  "type": "Feature",
  "properties": {
    "gn:admin1_code":"9",
    "gn:asciiname":"Boca de Araguao",
    "gn:country_code":"VE",
    "gn:dem":12,
    "gn:feature_class":"P",
    "gn:feature_code":"PPL",
    "gn:name":"Boca de Araguao",
    "gn:population":0,
    "gn:timezone":"America/Caracas",
    "iso:country":"VE",
    "wof:name":"Boca de Araguao",
    "wof:placetype":"locality"
},
  "geometry": {"coordinates":[-61.71278,8.62389],"type":"Point"}
}