{
  "type": "Feature",
  "properties": {
    "gn:admin1_code":"18.0",
    "gn:asciiname":"Los Playones",
    "gn:country_code":"VE",
    "gn:dem":149,
    "gn:feature_class":"P",
    "gn:feature_code":"PPL",
    "gn:name":"Los Playones",
    "gn:population":0,
    "gn:timezone":"America/Caracas",
    "iso:country":"VE",
    "wof:name":"Los Playones",
    "wof:placetype":"locality"
},
  "geometry": {"coordinates":[-69.77226,8.97344],"type":"Point"}
}