{
  "type": "Feature",
  "properties": {
    "gn:admin1_code":"21",
    "gn:asciiname":"Alto de Piedra",
    "gn:country_code":"VE",
    "gn:dem":1111,
    "gn:feature_class":"P",
    "gn:feature_code":"PPL",
    "gn:name":"Alto de Piedra",
    "gn:population":0,
    "gn:timezone":"America/Caracas",
    "iso:country":"VE",
    "wof:name":"Alto de Piedra",
    "wof:placetype":"locality"
},
  "geometry": {"coordinates":[-70.1332,9.16172],"type":"Point"}
}