{
  "type": "Feature",
  "properties": {
    "gn:admin1_code":"23",
    "gn:asciiname":"Las Dolores",
    "gn:country_code":"VE",
    "gn:dem":5,
    "gn:feature_class":"P",
    "gn:feature_code":"PPL",
    "gn:name":"Las Dolores",
    "gn:population":0,
    "gn:timezone":"America/Caracas",
    "iso:country":"VE",
    "wof:name":"Las Dolores",
    "wof:placetype":"locality"
},
  "geometry": {"coordinates":[-71.16466,9.22153],"type":"Point"}
}