{
  "type": "Feature",
  "properties": {
    "gn:admin1_code":"2",
    "gn:asciiname":"Merecure",
    "gn:country_code":"VE",
    "gn:dem":175,
    "gn:feature_class":"P",
    "gn:feature_code":"PPL",
    "gn:name":"Merecure",
    "gn:population":0,
    "gn:timezone":"America/Caracas",
    "iso:country":"VE",
    "wof:name":"Merecure",
    "wof:placetype":"locality"
},
  "geometry": {"coordinates":[-64.732,9.58375],"type":"Point"}
}