{
  "type": "Feature",
  "properties": {
    "gn:admin1_code":"20",
    "gn:asciiname":"Tabor",
    "gn:country_code":"VE",
    "gn:dem":1751,
    "gn:feature_class":"P",
    "gn:feature_code":"PPL",
    "gn:name":"Tabor",
    "gn:population":0,
    "gn:timezone":"America/Caracas",
    "iso:country":"VE",
    "name:bos_x_preferred":[
        "Tabor"
    ],
    "name:bul_x_preferred":[
        "\u0422\u0430\u0431\u043e\u0440"
    ],
    "name:cat_x_preferred":[
        "Tabor"
    ],
    "name:ceb_x_preferred":[
        "Tabor"
    ],
    "name:ces_x_preferred":[
        "Tabor"
    ],
    "name:chv_x_preferred":[
        "\u0422\u0430\u0431\u043e\u0440"
    ],
    "name:deu_x_preferred":[
        "Tabor"
    ],
    "name:fin_x_preferred":[
        "Taabor"
    ],
    "name:heb_x_preferred":[
        "\u05ea\u05d1\u05d5\u05e8"
    ],
    "name:hrv_x_preferred":[
        "Tabor"
    ],
    "name:hye_x_preferred":[
        "\u054f\u0561\u0562\u0578\u0580"
    ],
    "name:ita_x_preferred":[
        "Tabor"
    ],
    "name:jpn_x_preferred":[
        "\u30bf\u30fc\u30dc\u30eb"
    ],
    "name:kor_x_preferred":[
        "\ud0c0\ubcf4\ub974"
    ],
    "name:lit_x_preferred":[
        "Taboras"
    ],
    "name:nld_x_preferred":[
        "Tabor"
    ],
    "name:pol_x_preferred":[
        "Tabor"
    ],
    "name:por_x_preferred":[
        "Tabor"
    ],
    "name:ron_x_preferred":[
        "Tabor"
    ],
    "name:rus_x_preferred":[
        "\u0422\u0430\u0431\u043e\u0440"
    ],
    "name:slv_x_preferred":[
        "Tabor"
    ],
    "name:spa_x_preferred":[
        "Tabor"
    ],
    "name:swe_x_preferred":[
        "Tabor"
    ],
    "name:ukr_x_preferred":[
        "\u0422\u0430\u0431\u043e\u0440"
    ],
    "name:uzb_x_preferred":[
        "Tabor"
    ],
    "name:vie_x_preferred":[
        "Tabor"
    ],
    "name:vol_x_preferred":[
        "Tabor"
    ],
    "wof:name":"Tabor",
    "wof:placetype":"locality"
},
  "geometry": {"coordinates":[-72.47020000000001,7.51554],"type":"Point"}
}