{
  "type": "Feature",
  "properties": {
    "gn:admin1_code":"20",
    "gn:asciiname":"Tabor",
    "gn:country_code":"VE",
    "gn:dem":1751,
    "gn:feature_class":"P",
    "gn:feature_code":"PPL",
    "gn:name":"Tabor",
    "gn:population":0,
    "gn:timezone":"America/Caracas",
    "iso:country":"VE",
    "wof:name":"Tabor",
    "wof:placetype":"locality"
},
  "geometry": {"coordinates":[-72.47020000000001,7.51554],"type":"Point"}
}