{
  "type": "Feature",
  "properties": {
    "gn:admin1_code":"23",
    "gn:asciiname":"Pele el Ojo",
    "gn:country_code":"VE",
    "gn:dem":5,
    "gn:feature_class":"P",
    "gn:feature_code":"PPL",
    "gn:name":"Pele el Ojo",
    "gn:population":0,
    "gn:timezone":"America/Caracas",
    "iso:country":"VE",
    "wof:name":"Pele el Ojo",
    "wof:placetype":"locality"
},
  "geometry": {"coordinates":[-71.53333000000001,10.55],"type":"Point"}
}