{
  "type": "Feature",
  "properties": {
    "gn:admin1_code":"6",
    "gn:asciiname":"Cucurital",
    "gn:cc2":"VE",
    "gn:country_code":"VE",
    "gn:dem":455,
    "gn:feature_class":"P",
    "gn:feature_code":"PPL",
    "gn:name":"Cucurital",
    "gn:population":0,
    "gn:timezone":"America/Caracas",
    "iso:country":"VE",
    "name:und_x_variant":[
        "Rurua\u00f1a",
        "Cucurital"
    ],
    "wof:name":"Cucurital",
    "wof:placetype":"locality"
},
  "geometry": {"coordinates":[-64.71666999999999,4.73333],"type":"Point"}
}