{
  "type": "Feature",
  "properties": {
    "gn:admin1_code":"18.0",
    "gn:asciiname":"Vega del Brazo",
    "gn:country_code":"VE",
    "gn:dem":144,
    "gn:feature_class":"P",
    "gn:feature_code":"PPL",
    "gn:name":"Vega del Brazo",
    "gn:population":0,
    "gn:timezone":"America/Caracas",
    "iso:country":"VE",
    "name:spa_x_preferred":[
        "Vega del Brazo"
    ],
    "wof:name":"Vega del Brazo",
    "wof:placetype":"locality"
},
  "geometry": {"coordinates":[-69.77244,8.94966],"type":"Point"}
}