{
  "type": "Feature",
  "properties": {
    "gn:admin1_code":"26",
    "gn:asciiname":"El Zapatero",
    "gn:country_code":"VE",
    "gn:dem":57,
    "gn:feature_class":"P",
    "gn:feature_code":"PPLL",
    "gn:name":"El Zapatero",
    "gn:population":0,
    "gn:timezone":"America/Caracas",
    "iso:country":"VE",
    "wof:name":"El Zapatero",
    "wof:placetype":"locality"
},
  "geometry": {"coordinates":[-66.76666,10.61381],"type":"Point"}
}