{
  "type": "Feature",
  "properties": {
    "gn:admin1_code":"16",
    "gn:asciiname":"La Dominga",
    "gn:country_code":"VE",
    "gn:dem":31,
    "gn:feature_class":"P",
    "gn:feature_code":"PPL",
    "gn:name":"La Dominga",
    "gn:population":0,
    "gn:timezone":"America/Caracas",
    "iso:country":"VE",
    "wof:name":"La Dominga",
    "wof:placetype":"locality"
},
  "geometry": {"coordinates":[-62.475,8.63417],"type":"Point"}
}