{
  "type": "Feature",
  "properties": {
    "gn:admin1_code":"8.0",
    "gn:asciiname":"El Guafal",
    "gn:country_code":"VE",
    "gn:dem":545,
    "gn:feature_class":"P",
    "gn:feature_code":"PPL",
    "gn:name":"El Guafal",
    "gn:population":0,
    "gn:timezone":"America/Caracas",
    "iso:country":"VE",
    "wof:name":"El Guafal",
    "wof:placetype":"locality"
},
  "geometry": {"coordinates":[-68.02083,9.81671],"type":"Point"}
}