{
  "type": "Feature",
  "properties": {
    "gn:admin1_code":"19.0",
    "gn:asciiname":"Quebrada El Sordo",
    "gn:country_code":"VE",
    "gn:dem":136,
    "gn:feature_class":"P",
    "gn:feature_code":"PPL",
    "gn:name":"Quebrada El Sordo",
    "gn:population":0,
    "gn:timezone":"America/Caracas",
    "iso:country":"VE",
    "wof:name":"Quebrada El Sordo",
    "wof:placetype":"locality"
},
  "geometry": {"coordinates":[-64.05389,10.41222],"type":"Point"}
}