{
  "type": "Feature",
  "properties": {
    "gn:admin1_code":"11",
    "gn:asciiname":"Capadare",
    "gn:country_code":"VE",
    "gn:dem":129,
    "gn:feature_class":"P",
    "gn:feature_code":"PPL",
    "gn:name":"Capadare",
    "gn:population":0,
    "gn:timezone":"America/Caracas",
    "iso:country":"VE",
    "wof:name":"Capadare",
    "wof:placetype":"locality"
},
  "geometry": {"coordinates":[-68.57393,11.15769],"type":"Point"}
}