{
  "type": "Feature",
  "properties": {
    "gn:admin1_code":"20",
    "gn:admin2_code":"2008.0",
    "gn:asciiname":"San Jose de Bolivar",
    "gn:country_code":"VE",
    "gn:dem":1437,
    "gn:feature_class":"P",
    "gn:feature_code":"PPLA2",
    "gn:name":"San Jos\u00e9 de Bol\u00edvar",
    "gn:population":0,
    "gn:timezone":"America/Caracas",
    "iso:country":"VE",
    "name:spa_x_preferred":[
        "San Jos\u00e9 de Bol\u00edvar"
    ],
    "wof:name":"San Jose de Bolivar",
    "wof:placetype":"locality"
},
  "geometry": {"coordinates":[-71.97194,7.91139],"type":"Point"}
}