{
  "type": "Feature",
  "properties": {
    "gn:admin1_code":"23",
    "gn:asciiname":"El Trancador",
    "gn:country_code":"VE",
    "gn:dem":2,
    "gn:feature_class":"P",
    "gn:feature_code":"PPL",
    "gn:name":"El Trancador",
    "gn:population":0,
    "gn:timezone":"America/Caracas",
    "iso:country":"VE",
    "wof:name":"El Trancador",
    "wof:placetype":"locality"
},
  "geometry": {"coordinates":[-72.01805999999998,11.10523],"type":"Point"}
}