{
  "type": "Feature",
  "properties": {
    "gn:admin1_code":"12",
    "gn:asciiname":"El Jabillo",
    "gn:country_code":"VE",
    "gn:dem":155,
    "gn:feature_class":"P",
    "gn:feature_code":"PPL",
    "gn:name":"El Jabillo",
    "gn:population":0,
    "gn:timezone":"America/Caracas",
    "iso:country":"VE",
    "wof:name":"El Jabillo",
    "wof:placetype":"locality"
},
  "geometry": {"coordinates":[-65.86759000000001,9.1588],"type":"Point"}
}