{
  "type": "Feature",
  "properties": {
    "gn:admin1_code":"11.0",
    "gn:asciiname":"Los Paraguaneros",
    "gn:country_code":"VE",
    "gn:dem":1005,
    "gn:feature_class":"P",
    "gn:feature_code":"PPL",
    "gn:name":"Los Paraguaneros",
    "gn:population":0,
    "gn:timezone":"America/Caracas",
    "iso:country":"VE",
    "wof:name":"Los Paraguaneros",
    "wof:placetype":"locality"
},
  "geometry": {"coordinates":[-69.79523,11.17033],"type":"Point"}
}