{
  "type": "Feature",
  "properties": {
    "gn:admin1_code":"13",
    "gn:asciiname":"Agua Viva",
    "gn:country_code":"VE",
    "gn:dem":380,
    "gn:feature_class":"P",
    "gn:feature_code":"PPLL",
    "gn:name":"Agua Viva",
    "gn:population":0,
    "gn:timezone":"America/Caracas",
    "iso:country":"VE",
    "wof:name":"Agua Viva",
    "wof:placetype":"locality"
},
  "geometry": {"coordinates":[-69.50899,10.43129],"type":"Point"}
}