{
  "type": "Feature",
  "properties": {
    "gn:admin1_code":"16",
    "gn:asciiname":"Voladero",
    "gn:country_code":"VE",
    "gn:dem":512,
    "gn:feature_class":"P",
    "gn:feature_code":"PPL",
    "gn:name":"Voladero",
    "gn:population":0,
    "gn:timezone":"America/Caracas",
    "iso:country":"VE",
    "wof:name":"Voladero",
    "wof:placetype":"locality"
},
  "geometry": {"coordinates":[-63.82836,9.95837],"type":"Point"}
}