{
  "type": "Feature",
  "properties": {
    "gn:admin1_code":"5.0",
    "gn:asciiname":"El Dragal",
    "gn:country_code":"VE",
    "gn:dem":66,
    "gn:feature_class":"P",
    "gn:feature_code":"PPL",
    "gn:name":"El Dragal",
    "gn:population":0,
    "gn:timezone":"America/Caracas",
    "iso:country":"VE",
    "wof:name":"El Dragal",
    "wof:placetype":"locality"
},
  "geometry": {"coordinates":[-67.85110999999999,8.21583],"type":"Point"}
}