{
  "type": "Feature",
  "properties": {
    "iso:country":"VE",
    "name:eng_x_preferred":[
        "Ezequiel Zamora Airport"
    ],
    "name:eng_x_variant":[
        "SVCJ"
    ],
    "name:fas_x_preferred":[
        "\u0641\u0631\u0648\u062f\u06af\u0627\u0647 \u0633\u0646 \u06a9\u0627\u0631\u0644\u0648\u0633"
    ],
    "name:jpn_x_preferred":[
        "\u30b5\u30f3\u30fb\u30ab\u30eb\u30ed\u30b9\u7a7a\u6e2f"
    ],
    "name:msa_x_preferred":[
        "Lapangan Terbang San Carlos"
    ],
    "name:ron_x_preferred":[
        "Aeroportul Ezequiel Zamora"
    ],
    "name:sco_x_preferred":[
        "San Carlos Airport"
    ],
    "name:spa_x_preferred":[
        "Aeropuerto de San Carlos"
    ],
    "name:spa_x_variant":[
        "Aeropuerto Nacional Ezequiel Zamora"
    ],
    "oa:elevation_ft":"512",
    "oa:type":"small_airport",
    "wd:wordcount":46,
    "woe:hierarchy":{
        "country_id":23424982,
        "county_id":26804509,
        "localadmin_id":26805509,
        "planet_id":1,
        "state_id":2347684
    },
    "wof:name":"San Carlos Airport",
    "wof:placetype":"campus"
},
  "geometry": {"coordinates":[-68.57470000000001,9.64778],"type":"Point"}
}