{
  "type": "Feature",
  "properties": {
    "gn:admin1_code":"12",
    "gn:asciiname":"Camoruquito",
    "gn:country_code":"VE",
    "gn:dem":440,
    "gn:feature_class":"P",
    "gn:feature_code":"PPL",
    "gn:name":"Camoruquito",
    "gn:population":0,
    "gn:timezone":"America/Caracas",
    "iso:country":"VE",
    "wof:name":"Camoruquito",
    "wof:placetype":"locality"
},
  "geometry": {"coordinates":[-67.35639,9.90011],"type":"Point"}
}