{
  "type": "Feature",
  "properties": {
    "gn:admin1_code":"18",
    "gn:asciiname":"Los Gualjes",
    "gn:country_code":"VE",
    "gn:dem":518,
    "gn:feature_class":"P",
    "gn:feature_code":"PPL",
    "gn:name":"Los Gualjes",
    "gn:population":0,
    "gn:timezone":"America/Caracas",
    "iso:country":"VE",
    "wof:name":"Los Gualjes",
    "wof:placetype":"locality"
},
  "geometry": {"coordinates":[-69.93333,9.21667],"type":"Point"}
}