{
  "type": "Feature",
  "properties": {
    "gn:admin1_code":"02",
    "gn:asciiname":"San Luis",
    "gn:country_code":"VE",
    "gn:dem":131,
    "gn:feature_class":"P",
    "gn:feature_code":"PPL",
    "gn:name":"San Luis",
    "gn:population":0,
    "gn:timezone":"America/Caracas",
    "iso:country":"VE",
    "wof:name":"San Luis",
    "wof:placetype":"locality"
},
  "geometry": {"coordinates":[-64.86917,9.20285],"type":"Point"}
}