{
  "type": "Feature",
  "properties": {
    "gn:admin1_code":"19",
    "gn:asciiname":"La Cumbre de San Antonio",
    "gn:country_code":"VE",
    "gn:dem":474,
    "gn:feature_class":"P",
    "gn:feature_code":"PPL",
    "gn:name":"La Cumbre de San Antonio",
    "gn:population":0,
    "gn:timezone":"America/Caracas",
    "iso:country":"VE",
    "wof:name":"La Cumbre de San Antonio",
    "wof:placetype":"locality"
},
  "geometry": {"coordinates":[-63.09218000000001,10.61143],"type":"Point"}
}