{
  "type": "Feature",
  "properties": {
    "gn:admin1_code":"20.0",
    "gn:asciiname":"Laguna de Garcia",
    "gn:country_code":"VE",
    "gn:dem":2054,
    "gn:feature_class":"P",
    "gn:feature_code":"PPL",
    "gn:name":"Laguna de Garcia",
    "gn:population":0,
    "gn:timezone":"America/Caracas",
    "iso:country":"VE",
    "wof:name":"Laguna de Garcia",
    "wof:placetype":"locality"
},
  "geometry": {"coordinates":[-71.85675000000001,8.03556],"type":"Point"}
}