{
  "type": "Feature",
  "properties": {
    "gn:admin1_code":"11",
    "gn:asciiname":"Sabana Libre",
    "gn:country_code":"VE",
    "gn:dem":1230,
    "gn:feature_class":"P",
    "gn:feature_code":"PPL",
    "gn:name":"Sabana Libre",
    "gn:population":0,
    "gn:timezone":"America/Caracas",
    "iso:country":"VE",
    "wof:name":"Sabana Libre",
    "wof:placetype":"locality"
},
  "geometry": {"coordinates":[-70.55096999999998,10.33929],"type":"Point"}
}