{
  "type": "Feature",
  "properties": {
    "gn:admin1_code":"11",
    "gn:asciiname":"Cauca",
    "gn:country_code":"VE",
    "gn:dem":13,
    "gn:feature_class":"P",
    "gn:feature_code":"PPL",
    "gn:name":"Cauca",
    "gn:population":0,
    "gn:timezone":"America/Caracas",
    "iso:country":"VE",
    "name:bre_x_preferred":[
        "Cauca"
    ],
    "name:cat_x_preferred":[
        "Cauca"
    ],
    "name:deu_x_preferred":[
        "Cauca"
    ],
    "name:fra_x_preferred":[
        "Cauca"
    ],
    "name:heb_x_preferred":[
        "\u05e7\u05d0\u05d5\u05e7\u05d4"
    ],
    "name:hun_x_preferred":[
        "Cauca"
    ],
    "name:nld_x_preferred":[
        "Cauca"
    ],
    "name:pol_x_preferred":[
        "Cauca"
    ],
    "name:ron_x_preferred":[
        "Cauca"
    ],
    "name:sco_x_preferred":[
        "Cauca"
    ],
    "name:spa_x_preferred":[
        "Cauca"
    ],
    "name:vie_x_preferred":[
        "Cauca"
    ],
    "wof:name":"Cauca",
    "wof:placetype":"locality"
},
  "geometry": {"coordinates":[-70.30806,11.31014],"type":"Point"}
}