{
  "type": "Feature",
  "properties": {
    "gn:admin1_code":"11",
    "gn:asciiname":"Cauca",
    "gn:country_code":"VE",
    "gn:dem":13,
    "gn:feature_class":"P",
    "gn:feature_code":"PPL",
    "gn:name":"Cauca",
    "gn:population":0,
    "gn:timezone":"America/Caracas",
    "iso:country":"VE",
    "wof:name":"Cauca",
    "wof:placetype":"locality"
},
  "geometry": {"coordinates":[-70.30806,11.31014],"type":"Point"}
}