{
  "type": "Feature",
  "properties": {
    "gn:admin1_code":"14",
    "gn:asciiname":"Pico de Piedra",
    "gn:country_code":"VE",
    "gn:dem":1839,
    "gn:feature_class":"P",
    "gn:feature_code":"PPL",
    "gn:name":"Pico de Piedra",
    "gn:population":0,
    "gn:timezone":"America/Caracas",
    "iso:country":"VE",
    "wof:name":"Pico de Piedra",
    "wof:placetype":"locality"
},
  "geometry": {"coordinates":[-71.42,8.21361],"type":"Point"}
}