{
  "type": "Feature",
  "properties": {
    "gn:admin1_code":"7",
    "gn:asciiname":"Las Acacias",
    "gn:country_code":"VE",
    "gn:dem":492,
    "gn:feature_class":"P",
    "gn:feature_code":"PPL",
    "gn:name":"Las Acacias",
    "gn:population":0,
    "gn:timezone":"America/Caracas",
    "iso:country":"VE",
    "wof:name":"Las Acacias",
    "wof:placetype":"locality"
},
  "geometry": {"coordinates":[-67.99807,10.20354],"type":"Point"}
}