{
  "type": "Feature",
  "properties": {
    "gn:admin1_code":"2",
    "gn:asciiname":"La Pascualita",
    "gn:country_code":"VE",
    "gn:dem":266,
    "gn:feature_class":"P",
    "gn:feature_code":"PPL",
    "gn:name":"La Pascualita",
    "gn:population":0,
    "gn:timezone":"America/Caracas",
    "iso:country":"VE",
    "name:und_x_variant":[
        "Pascualita",
        "La Pascualita"
    ],
    "wof:name":"La Pascualita",
    "wof:placetype":"locality"
},
  "geometry": {"coordinates":[-64.28943000000001,9.2431],"type":"Point"}
}