{
  "type": "Feature",
  "properties": {
    "gn:admin1_code":"08",
    "gn:asciiname":"Santa Ines",
    "gn:country_code":"VE",
    "gn:dem":735,
    "gn:feature_class":"P",
    "gn:feature_code":"PPL",
    "gn:name":"Santa In\u00e9s",
    "gn:population":0,
    "gn:timezone":"America/Caracas",
    "iso:country":"VE",
    "wof:name":"Santa Ines",
    "wof:placetype":"locality"
},
  "geometry": {"coordinates":[-68.65000000000001,9.86667],"type":"Point"}
}