{
  "type": "Feature",
  "properties": {
    "gn:admin1_code":"8",
    "gn:asciiname":"Cartanal",
    "gn:country_code":"VE",
    "gn:dem":421,
    "gn:feature_class":"P",
    "gn:feature_code":"PPL",
    "gn:name":"Cartanal",
    "gn:population":0,
    "gn:timezone":"America/Caracas",
    "iso:country":"VE",
    "name:fra_x_preferred":[
        "Cartanal"
    ],
    "name:pol_x_preferred":[
        "El Cartanal"
    ],
    "wof:name":"Cartanal",
    "wof:placetype":"locality"
},
  "geometry": {"coordinates":[-68.43333,9.78333],"type":"Point"}
}