{
  "type": "Feature",
  "properties": {
    "gn:admin1_code":"13",
    "gn:asciiname":"La Morita",
    "gn:country_code":"VE",
    "gn:dem":471,
    "gn:feature_class":"P",
    "gn:feature_code":"PPL",
    "gn:name":"La Morita",
    "gn:population":0,
    "gn:timezone":"America/Caracas",
    "iso:country":"VE",
    "wof:name":"La Morita",
    "wof:placetype":"locality"
},
  "geometry": {"coordinates":[-69.21313000000001,9.94441],"type":"Point"}
}