{
  "type": "Feature",
  "properties": {
    "gn:admin1_code":"5",
    "gn:asciiname":"Las Mayitas",
    "gn:country_code":"VE",
    "gn:dem":119,
    "gn:feature_class":"P",
    "gn:feature_code":"PPL",
    "gn:name":"Las Mayitas",
    "gn:population":0,
    "gn:timezone":"America/Caracas",
    "iso:country":"VE",
    "wof:name":"Las Mayitas",
    "wof:placetype":"locality"
},
  "geometry": {"coordinates":[-70.09786,8.19298],"type":"Point"}
}