{
  "type": "Feature",
  "properties": {
    "gn:admin1_code":"6.0",
    "gn:asciiname":"San Juan de Lucio",
    "gn:country_code":"VE",
    "gn:dem":190,
    "gn:feature_class":"P",
    "gn:feature_code":"PPL",
    "gn:name":"San Juan de Lucio",
    "gn:population":0,
    "gn:timezone":"America/Caracas",
    "iso:country":"VE",
    "wof:name":"San Juan de Lucio",
    "wof:placetype":"locality"
},
  "geometry": {"coordinates":[-61.86556,7.34389],"type":"Point"}
}