{
  "type": "Feature",
  "properties": {
    "gn:admin1_code":"16.0",
    "gn:asciiname":"Caricari",
    "gn:country_code":"VE",
    "gn:dem":158,
    "gn:feature_class":"P",
    "gn:feature_code":"PPL",
    "gn:name":"Caricari",
    "gn:population":0,
    "gn:timezone":"America/Caracas",
    "iso:country":"VE",
    "wof:name":"Caricari",
    "wof:placetype":"locality"
},
  "geometry": {"coordinates":[-63.64093,9.36581],"type":"Point"}
}