{
  "type": "Feature",
  "properties": {
    "gn:admin1_code":"15",
    "gn:asciiname":"La Carbonera",
    "gn:country_code":"VE",
    "gn:dem":306,
    "gn:feature_class":"P",
    "gn:feature_code":"PPL",
    "gn:name":"La Carbonera",
    "gn:population":0,
    "gn:timezone":"America/Caracas",
    "iso:country":"VE",
    "wof:name":"La Carbonera",
    "wof:placetype":"locality"
},
  "geometry": {"coordinates":[-66.53333000000001,10.46667],"type":"Point"}
}