{
  "type": "Feature",
  "properties": {
    "gn:admin1_code":"15.0",
    "gn:asciiname":"Sabaneta Arriba",
    "gn:country_code":"VE",
    "gn:dem":844,
    "gn:feature_class":"P",
    "gn:feature_code":"PPL",
    "gn:name":"Sabaneta Arriba",
    "gn:population":0,
    "gn:timezone":"America/Caracas",
    "iso:country":"VE",
    "wof:name":"Sabaneta Arriba",
    "wof:placetype":"locality"
},
  "geometry": {"coordinates":[-66.80072,10.39815],"type":"Point"}
}