{
  "type": "Feature",
  "properties": {
    "gn:admin1_code":"2",
    "gn:asciiname":"Las Corobas",
    "gn:country_code":"VE",
    "gn:dem":105,
    "gn:feature_class":"P",
    "gn:feature_code":"PPL",
    "gn:name":"Las Corobas",
    "gn:population":0,
    "gn:timezone":"America/Caracas",
    "iso:country":"VE",
    "wof:name":"Las Corobas",
    "wof:placetype":"locality"
},
  "geometry": {"coordinates":[-63.97792,8.56073],"type":"Point"}
}