{
  "type": "Feature",
  "properties": {
    "iso:country":"VE",
    "name:und_x_variant":[
        "Judivana"
    ],
    "qs:gn_country":"VE",
    "qs:gn_fcode":"PPL",
    "qs:gn_pop":0,
    "qs:name":"Judibana",
    "qs:name_adm0":"Venezuela",
    "qs:name_adm1":"Falcon",
    "qs:photos":43,
    "qs:photos_1k":9,
    "qs:photos_9k":1,
    "qs:photos_9r":2,
    "qs:photos_all":43,
    "qs:photos_sr":2,
    "qs:placetype":"Town",
    "qs:pop_sr":"0",
    "qs:woe_adm0":23424982,
    "wof:name":"Judibana",
    "wof:placetype":"locality"
},
  "geometry": {"coordinates":[-70.19355,11.75054],"type":"Point"}
}