{
  "type": "Feature",
  "properties": {
    "gn:admin1_code":"16.0",
    "gn:asciiname":"El Maneto",
    "gn:country_code":"VE",
    "gn:dem":206,
    "gn:feature_class":"P",
    "gn:feature_code":"PPL",
    "gn:name":"El Maneto",
    "gn:population":0,
    "gn:timezone":"America/Caracas",
    "iso:country":"VE",
    "wof:name":"El Maneto",
    "wof:placetype":"locality"
},
  "geometry": {"coordinates":[-63.67556,9.27278],"type":"Point"}
}