{
  "type": "Feature",
  "properties": {
    "gn:admin1_code":"18.0",
    "gn:asciiname":"Agua Sucia",
    "gn:country_code":"VE",
    "gn:dem":1132,
    "gn:feature_class":"P",
    "gn:feature_code":"PPL",
    "gn:name":"Agua Sucia",
    "gn:population":0,
    "gn:timezone":"America/Caracas",
    "iso:country":"VE",
    "name:spa_x_preferred":[
        "Agua Sucia"
    ],
    "wof:name":"Agua Sucia",
    "wof:placetype":"locality"
},
  "geometry": {"coordinates":[-69.40517,9.64148],"type":"Point"}
}