{
  "type": "Feature",
  "properties": {
    "gn:admin1_code":"22",
    "gn:asciiname":"Talla Arriba",
    "gn:country_code":"VE",
    "gn:dem":908,
    "gn:feature_class":"P",
    "gn:feature_code":"PPL",
    "gn:name":"Talla Arriba",
    "gn:population":0,
    "gn:timezone":"America/Caracas",
    "iso:country":"VE",
    "wof:name":"Talla Arriba",
    "wof:placetype":"locality"
},
  "geometry": {"coordinates":[-68.46666999999999,10.15],"type":"Point"}
}