{
  "type": "Feature",
  "properties": {
    "gn:admin1_code":"14",
    "gn:asciiname":"El Saisay",
    "gn:country_code":"VE",
    "gn:dem":1644,
    "gn:feature_class":"P",
    "gn:feature_code":"PPL",
    "gn:name":"El Saisay",
    "gn:population":0,
    "gn:timezone":"America/Caracas",
    "iso:country":"VE",
    "wof:name":"El Saisay",
    "wof:placetype":"locality"
},
  "geometry": {"coordinates":[-71.7349,8.18379],"type":"Point"}
}