{
  "type": "Feature",
  "properties": {
    "gn:admin1_code":"15.0",
    "gn:asciiname":"Mi Chiquita",
    "gn:country_code":"VE",
    "gn:dem":1188,
    "gn:feature_class":"P",
    "gn:feature_code":"PPLL",
    "gn:name":"Mi Chiquita",
    "gn:population":0,
    "gn:timezone":"America/Caracas",
    "iso:country":"VE",
    "wof:name":"Mi Chiquita",
    "wof:placetype":"locality"
},
  "geometry": {"coordinates":[-66.79172,10.42522],"type":"Point"}
}