{
  "type": "Feature",
  "properties": {
    "gn:admin1_code":"12",
    "gn:asciiname":"El Silgaito",
    "gn:country_code":"VE",
    "gn:dem":368,
    "gn:feature_class":"P",
    "gn:feature_code":"PPL",
    "gn:name":"El Silga\u00edto",
    "gn:population":0,
    "gn:timezone":"America/Caracas",
    "iso:country":"VE",
    "wof:name":"El Silgaito",
    "wof:placetype":"locality"
},
  "geometry": {"coordinates":[-67.46666999999999,9.78333],"type":"Point"}
}