{
  "type": "Feature",
  "properties": {
    "gn:admin1_code":"6",
    "gn:asciiname":"Luciri",
    "gn:cc2":"VE",
    "gn:country_code":"VE",
    "gn:dem":344,
    "gn:feature_class":"P",
    "gn:feature_code":"PPL",
    "gn:name":"Luciri",
    "gn:population":0,
    "gn:timezone":"America/Caracas",
    "iso:country":"VE",
    "name:und_x_variant":[
        "Lusiri",
        "Luciri"
    ],
    "wof:name":"Luciri",
    "wof:placetype":"locality"
},
  "geometry": {"coordinates":[-62.66667,6.63333],"type":"Point"}
}