{
  "type": "Feature",
  "properties": {
    "gn:admin1_code":"19.0",
    "gn:asciiname":"El Manglillo",
    "gn:country_code":"VE",
    "gn:dem":1,
    "gn:feature_class":"P",
    "gn:feature_code":"PPL",
    "gn:name":"El Manglillo",
    "gn:population":0,
    "gn:timezone":"America/Caracas",
    "iso:country":"VE",
    "wof:name":"El Manglillo",
    "wof:placetype":"locality"
},
  "geometry": {"coordinates":[-64.21841999999999,10.64092],"type":"Point"}
}