{
  "type": "Feature",
  "properties": {
    "gn:admin1_code":"11",
    "gn:asciiname":"Las Adjuntas",
    "gn:country_code":"VE",
    "gn:dem":353,
    "gn:feature_class":"P",
    "gn:feature_code":"PPL",
    "gn:name":"Las Adjuntas",
    "gn:population":0,
    "gn:timezone":"America/Caracas",
    "iso:country":"VE",
    "wof:name":"Las Adjuntas",
    "wof:placetype":"locality"
},
  "geometry": {"coordinates":[-69.96666999999999,10.91667],"type":"Point"}
}