{
  "type": "Feature",
  "properties": {
    "gn:admin1_code":"19",
    "gn:admin2_code":"1913.0",
    "gn:asciiname":"Catuaro",
    "gn:country_code":"VE",
    "gn:dem":434,
    "gn:feature_class":"P",
    "gn:feature_code":"PPL",
    "gn:name":"Catuaro",
    "gn:population":0,
    "gn:timezone":"America/Caracas",
    "iso:country":"VE",
    "wof:name":"Catuaro",
    "wof:placetype":"locality"
},
  "geometry": {"coordinates":[-63.50153,10.3961],"type":"Point"}
}