{
  "type": "Feature",
  "properties": {
    "gn:admin1_code":"18.0",
    "gn:asciiname":"Chiriguare",
    "gn:country_code":"VE",
    "gn:dem":73,
    "gn:feature_class":"P",
    "gn:feature_code":"PPL",
    "gn:name":"Chiriguare",
    "gn:population":0,
    "gn:timezone":"America/Caracas",
    "iso:country":"VE",
    "name:spa_x_preferred":[
        "Chiriguare"
    ],
    "wof:name":"Chiriguare",
    "wof:placetype":"locality"
},
  "geometry": {"coordinates":[-68.71828000000001,8.62254],"type":"Point"}
}