{
  "type": "Feature",
  "properties": {
    "gn:admin1_code":"4",
    "gn:asciiname":"La Ceiba",
    "gn:country_code":"VE",
    "gn:dem":546,
    "gn:feature_class":"P",
    "gn:feature_code":"PPL",
    "gn:name":"La Ceiba",
    "gn:population":0,
    "gn:timezone":"America/Caracas",
    "iso:country":"VE",
    "wof:name":"La Ceiba",
    "wof:placetype":"locality"
},
  "geometry": {"coordinates":[-67.37976999999999,10.17904],"type":"Point"}
}