{
  "type": "Feature",
  "properties": {
    "gn:admin1_code":"12",
    "gn:asciiname":"Herrera",
    "gn:country_code":"VE",
    "gn:dem":64,
    "gn:feature_class":"P",
    "gn:feature_code":"PPL",
    "gn:name":"Herrera",
    "gn:population":0,
    "gn:timezone":"America/Caracas",
    "iso:country":"VE",
    "name:cat_x_preferred":[
        "Herrera"
    ],
    "name:ceb_x_preferred":[
        "Herrera"
    ],
    "name:ces_x_preferred":[
        "Herrera"
    ],
    "name:deu_x_preferred":[
        "Herrera"
    ],
    "name:epo_x_preferred":[
        "Herrera"
    ],
    "name:eus_x_preferred":[
        "Herrera"
    ],
    "name:fin_x_preferred":[
        "Herrera"
    ],
    "name:fra_x_preferred":[
        "Herrera"
    ],
    "name:glg_x_preferred":[
        "Herrera"
    ],
    "name:heb_x_preferred":[
        "\u05d4\u05e8\u05e8\u05d4"
    ],
    "name:hun_x_preferred":[
        "Herrera"
    ],
    "name:ita_x_preferred":[
        "Herrera"
    ],
    "name:jpn_x_preferred":[
        "\u30a8\u30ec\u30fc\u30e9"
    ],
    "name:kor_x_preferred":[
        "\uc5d0\ub808\ub77c"
    ],
    "name:nld_x_preferred":[
        "Herrera"
    ],
    "name:pol_x_preferred":[
        "Herrera"
    ],
    "name:por_x_preferred":[
        "Herrera"
    ],
    "name:ron_x_preferred":[
        "Herrera"
    ],
    "name:rus_x_preferred":[
        "\u042d\u0440\u0440\u0435\u0440\u0430"
    ],
    "name:slk_x_preferred":[
        "Herrera"
    ],
    "name:spa_x_preferred":[
        "Herrera"
    ],
    "name:swe_x_preferred":[
        "Herrera"
    ],
    "name:ukr_x_preferred":[
        "\u0415\u0440\u0440\u0435\u0440\u0430"
    ],
    "wof:name":"Herrera",
    "wof:placetype":"locality"
},
  "geometry": {"coordinates":[-67.21095,8.52902],"type":"Point"}
}