{
  "type": "Feature",
  "properties": {
    "gn:admin1_code":"21",
    "gn:asciiname":"El Calembe",
    "gn:country_code":"VE",
    "gn:dem":1245,
    "gn:feature_class":"P",
    "gn:feature_code":"PPL",
    "gn:name":"El Calembe",
    "gn:population":0,
    "gn:timezone":"America/Caracas",
    "iso:country":"VE",
    "wof:name":"El Calembe",
    "wof:placetype":"locality"
},
  "geometry": {"coordinates":[-70.64746,9.24001],"type":"Point"}
}