{
  "type": "Feature",
  "properties": {
    "gn:admin1_code":"5",
    "gn:asciiname":"Los Canaverales",
    "gn:country_code":"VE",
    "gn:dem":88,
    "gn:feature_class":"P",
    "gn:feature_code":"PPL",
    "gn:name":"Los Ca\u00f1averales",
    "gn:population":0,
    "gn:timezone":"America/Caracas",
    "iso:country":"VE",
    "name:und_x_variant":[
        "Ca\u00f1averales",
        "Los Ca\u00f1averales"
    ],
    "wof:name":"Los Canaverales",
    "wof:placetype":"locality"
},
  "geometry": {"coordinates":[-69.38231999999999,8.19422],"type":"Point"}
}