{
  "type": "Feature",
  "properties": {
    "gn:admin1_code":"2",
    "gn:asciiname":"Guapa",
    "gn:country_code":"VE",
    "gn:dem":29,
    "gn:feature_class":"P",
    "gn:feature_code":"PPL",
    "gn:name":"Guapa",
    "gn:population":0,
    "gn:timezone":"America/Caracas",
    "iso:country":"VE",
    "wof:name":"Guapa",
    "wof:placetype":"locality"
},
  "geometry": {"coordinates":[-65.25,9.91667],"type":"Point"}
}