{
  "type": "Feature",
  "properties": {
    "gn:admin1_code":"14.0",
    "gn:asciiname":"Playones",
    "gn:country_code":"VE",
    "gn:dem":116,
    "gn:feature_class":"P",
    "gn:feature_code":"PPL",
    "gn:name":"Playones",
    "gn:population":0,
    "gn:timezone":"America/Caracas",
    "iso:country":"VE",
    "wof:name":"Playones",
    "wof:placetype":"locality"
},
  "geometry": {"coordinates":[-71.5423,8.77716],"type":"Point"}
}