{
  "type": "Feature",
  "properties": {
    "gn:admin1_code":"8",
    "gn:asciiname":"Cariaquito",
    "gn:country_code":"VE",
    "gn:dem":391,
    "gn:feature_class":"P",
    "gn:feature_code":"PPL",
    "gn:name":"Cariaquito",
    "gn:population":0,
    "gn:timezone":"America/Caracas",
    "iso:country":"VE",
    "wof:name":"Cariaquito",
    "wof:placetype":"locality"
},
  "geometry": {"coordinates":[-68.51306,9.78675],"type":"Point"}
}