{
  "type": "Feature",
  "properties": {
    "gn:admin1_code":"2",
    "gn:asciiname":"Aribi",
    "gn:country_code":"VE",
    "gn:dem":199,
    "gn:feature_class":"P",
    "gn:feature_code":"PPL",
    "gn:name":"Arib\u00ed",
    "gn:population":0,
    "gn:timezone":"America/Caracas",
    "iso:country":"VE",
    "wof:name":"Aribi",
    "wof:placetype":"locality"
},
  "geometry": {"coordinates":[-64.77795,8.57539],"type":"Point"}
}