{
  "type": "Feature",
  "properties": {
    "gn:admin1_code":"3",
    "gn:asciiname":"Tapa Santera",
    "gn:country_code":"VE",
    "gn:dem":129,
    "gn:feature_class":"P",
    "gn:feature_code":"PPL",
    "gn:name":"Tapa Santera",
    "gn:population":0,
    "gn:timezone":"America/Caracas",
    "iso:country":"VE",
    "wof:name":"Tapa Santera",
    "wof:placetype":"locality"
},
  "geometry": {"coordinates":[-70.62054999999999,7.22649],"type":"Point"}
}