{
  "type": "Feature",
  "properties": {
    "gn:admin1_code":"4",
    "gn:asciiname":"Mucura",
    "gn:country_code":"VE",
    "gn:dem":364,
    "gn:feature_class":"P",
    "gn:feature_code":"PPL",
    "gn:name":"M\u00facura",
    "gn:population":0,
    "gn:timezone":"America/Caracas",
    "iso:country":"VE",
    "wof:name":"Mucura",
    "wof:placetype":"locality"
},
  "geometry": {"coordinates":[-67.04074,9.91143],"type":"Point"}
}