{
  "type": "Feature",
  "properties": {
    "gn:admin1_code":"22",
    "gn:asciiname":"Sol y Sombra",
    "gn:country_code":"VE",
    "gn:dem":367,
    "gn:feature_class":"P",
    "gn:feature_code":"PPL",
    "gn:name":"Sol y Sombra",
    "gn:population":0,
    "gn:timezone":"America/Caracas",
    "iso:country":"VE",
    "name:spa_x_preferred":[
        "Sol y sombra"
    ],
    "wof:name":"Sol y Sombra",
    "wof:placetype":"locality"
},
  "geometry": {"coordinates":[-69.01396,10.40483],"type":"Point"}
}