{
  "type": "Feature",
  "properties": {
    "gn:admin1_code":"5",
    "gn:asciiname":"El Brilero",
    "gn:country_code":"VE",
    "gn:dem":93,
    "gn:feature_class":"P",
    "gn:feature_code":"PPL",
    "gn:name":"El Brilero",
    "gn:population":0,
    "gn:timezone":"America/Caracas",
    "iso:country":"VE",
    "wof:name":"El Brilero",
    "wof:placetype":"locality"
},
  "geometry": {"coordinates":[-69.59999999999999,8.18333],"type":"Point"}
}