{
  "type": "Feature",
  "properties": {
    "iso:country":"VE",
    "qs_pg:aaroncc":"VE",
    "qs_pg:name":"La Laguna de Tacarigua",
    "qs_pg:name_adm0":"Venezuela",
    "qs_pg:name_adm1":"Miranda",
    "qs_pg:photos":1,
    "qs_pg:photos_1k":1,
    "qs_pg:photos_9k":1,
    "qs_pg:photos_9r":2,
    "qs_pg:photos_all":67,
    "qs_pg:photos_sr":1,
    "qs_pg:pop_sr":0,
    "qs_pg:qs_pg_placetype":"localadmin",
    "qs_pg:qs_pg_placetype_gp":"LocalAdmin",
    "qs_pg:woe_adm0":23424982,
    "woe:adm0_id":23424982,
    "woe:name_adm0":"Venezuela",
    "woe:name_adm1":"Miranda",
    "woe:placetype":"LocalAdmin",
    "wof:name":"La Laguna de Tacarigua",
    "wof:placetype":"localadmin"
},
  "geometry": {"coordinates":[-65.876598,10.3054025],"type":"Point"}
}