{
  "type": "Feature",
  "properties": {
    "gn:admin1_code":"20",
    "gn:asciiname":"Los Teques",
    "gn:country_code":"VE",
    "gn:dem":949,
    "gn:feature_class":"P",
    "gn:feature_code":"PPL",
    "gn:name":"Los Teques",
    "gn:population":0,
    "gn:timezone":"America/Caracas",
    "iso:country":"VE",
    "name:arg_x_preferred":[
        "Los Teques"
    ],
    "name:bar_x_preferred":[
        "Los Teques"
    ],
    "name:ben_x_preferred":[
        "\u09b2\u09b8 \u099f\u09c7\u0995\u09bf\u0989\u09b8"
    ],
    "name:bul_x_preferred":[
        "\u041b\u043e\u0441 \u0422\u0435\u043a\u0435\u0441"
    ],
    "name:cat_x_preferred":[
        "Los Teques"
    ],
    "name:ceb_x_preferred":[
        "Los Teques"
    ],
    "name:dan_x_preferred":[
        "Los Teques"
    ],
    "name:deu_x_preferred":[
        "Los Teques"
    ],
    "name:ell_x_preferred":[
        "\u039b\u03bf\u03c2 \u03a4\u03ad\u03ba\u03b5\u03c2"
    ],
    "name:epo_x_preferred":[
        "Los Teques"
    ],
    "name:eus_x_preferred":[
        "Los Teques"
    ],
    "name:fas_x_preferred":[
        "\u0644\u0627\u0633 \u062a\u06a9\u0648\u0633"
    ],
    "name:fin_x_preferred":[
        "Los Teques"
    ],
    "name:fra_x_preferred":[
        "Los Teques"
    ],
    "name:heb_x_preferred":[
        "\u05dc\u05d5\u05e1 \u05d8\u05e7\u05e1"
    ],
    "name:hin_x_preferred":[
        "\u0932\u0949\u0938 \u091f\u0947\u0915\u0947\u0938"
    ],
    "name:hun_x_preferred":[
        "Los Teques"
    ],
    "name:ind_x_preferred":[
        "Los Teques"
    ],
    "name:ita_x_preferred":[
        "Los Teques"
    ],
    "name:jpn_x_preferred":[
        "\u30ed\u30b9\u30fb\u30c6\u30b1\u30b9"
    ],
    "name:kat_x_preferred":[
        "\u10da\u10dd\u10e1-\u10e2\u10d4\u10d9\u10d4\u10e1\u10d8"
    ],
    "name:kor_x_preferred":[
        "\ub85c\uc2a4\ud14c\ucf00\uc2a4"
    ],
    "name:lit_x_preferred":[
        "Los Tekesas"
    ],
    "name:mwl_x_preferred":[
        "Los Teques"
    ],
    "name:nld_x_preferred":[
        "Los Teques"
    ],
    "name:nno_x_preferred":[
        "Los Teques"
    ],
    "name:nor_x_preferred":[
        "Los Teques"
    ],
    "name:oci_x_preferred":[
        "Los Teques"
    ],
    "name:pol_x_preferred":[
        "Los Teques"
    ],
    "name:por_x_preferred":[
        "Los Teques"
    ],
    "name:que_x_preferred":[
        "Los Teques"
    ],
    "name:ron_x_preferred":[
        "Los Teques"
    ],
    "name:rus_x_preferred":[
        "\u041b\u043e\u0441-\u0422\u0435\u043a\u0435\u0441"
    ],
    "name:spa_x_preferred":[
        "Los Teques"
    ],
    "name:swe_x_preferred":[
        "Los Teques"
    ],
    "name:tur_x_preferred":[
        "Los Teques"
    ],
    "name:ukr_x_preferred":[
        "\u041b\u043e\u0441-\u0422\u0435\u043a\u0435\u0441"
    ],
    "name:urd_x_preferred":[
        "\u0644\u0648\u0633 \u062a\u06cc\u06a9\u06cc\u0633"
    ],
    "name:vie_x_preferred":[
        "Los Teques"
    ],
    "name:vol_x_preferred":[
        "Los Teques"
    ],
    "name:war_x_preferred":[
        "Los Teques"
    ],
    "name:wuu_x_preferred":[
        "\u6d1b\u65af\u7279\u514b\u65af"
    ],
    "name:zho_x_preferred":[
        "\u6d1b\u65af\u7279\u514b\u65af"
    ],
    "wof:name":"Los Teques",
    "wof:placetype":"locality"
},
  "geometry": {"coordinates":[-72.21666999999999,7.78333],"type":"Point"}
}