{
  "type": "Feature",
  "properties": {
    "gn:admin1_code":"20",
    "gn:asciiname":"Los Teques",
    "gn:country_code":"VE",
    "gn:dem":949,
    "gn:feature_class":"P",
    "gn:feature_code":"PPL",
    "gn:name":"Los Teques",
    "gn:population":0,
    "gn:timezone":"America/Caracas",
    "iso:country":"VE",
    "wof:name":"Los Teques",
    "wof:placetype":"locality"
},
  "geometry": {"coordinates":[-72.21666999999999,7.78333],"type":"Point"}
}