{
  "type": "Feature",
  "properties": {
    "gn:admin1_code":"13",
    "gn:asciiname":"Moyetones",
    "gn:country_code":"VE",
    "gn:dem":613,
    "gn:feature_class":"P",
    "gn:feature_code":"PPL",
    "gn:name":"Moyetones",
    "gn:population":0,
    "gn:timezone":"America/Caracas",
    "iso:country":"VE",
    "name:und_x_variant":[
        "Molletones",
        "Moyetones"
    ],
    "wof:name":"Moyetones",
    "wof:placetype":"locality"
},
  "geometry": {"coordinates":[-69.38807,10.07532],"type":"Point"}
}