{
  "type": "Feature",
  "properties": {
    "gn:admin1_code":"19.0",
    "gn:asciiname":"Macanillal",
    "gn:country_code":"VE",
    "gn:dem":505,
    "gn:feature_class":"P",
    "gn:feature_code":"PPL",
    "gn:name":"Macanillal",
    "gn:population":0,
    "gn:timezone":"America/Caracas",
    "iso:country":"VE",
    "wof:name":"Macanillal",
    "wof:placetype":"locality"
},
  "geometry": {"coordinates":[-62.74947,10.70592],"type":"Point"}
}