{
  "type": "Feature",
  "properties": {
    "gn:admin1_code":"5",
    "gn:asciiname":"Buena Vista",
    "gn:country_code":"VE",
    "gn:dem":108,
    "gn:feature_class":"P",
    "gn:feature_code":"PPL",
    "gn:name":"Buena Vista",
    "gn:population":0,
    "gn:timezone":"America/Caracas",
    "iso:country":"VE",
    "wof:name":"Buena Vista",
    "wof:placetype":"locality"
},
  "geometry": {"coordinates":[-70.02419999999999,8.05641],"type":"Point"}
}