{
  "type": "Feature",
  "properties": {
    "gn:admin1_code":"16.0",
    "gn:asciiname":"La Carata",
    "gn:country_code":"VE",
    "gn:dem":388,
    "gn:feature_class":"P",
    "gn:feature_code":"PPL",
    "gn:name":"La Carata",
    "gn:population":0,
    "gn:timezone":"America/Caracas",
    "iso:country":"VE",
    "wof:name":"La Carata",
    "wof:placetype":"locality"
},
  "geometry": {"coordinates":[-63.19278000000001,10.115],"type":"Point"}
}