{
  "type": "Feature",
  "properties": {
    "gn:admin1_code":"19.0",
    "gn:asciiname":"La Recta",
    "gn:country_code":"VE",
    "gn:dem":25,
    "gn:feature_class":"P",
    "gn:feature_code":"PPLL",
    "gn:name":"La Recta",
    "gn:population":0,
    "gn:timezone":"America/Caracas",
    "iso:country":"VE",
    "wof:name":"La Recta",
    "wof:placetype":"locality"
},
  "geometry": {"coordinates":[-63.34104,10.65308],"type":"Point"}
}