{
  "type": "Feature",
  "properties": {
    "gn:admin1_code":"9",
    "gn:asciiname":"Araguao",
    "gn:country_code":"VE",
    "gn:dem":15,
    "gn:feature_class":"P",
    "gn:feature_code":"PPL",
    "gn:name":"Araguao",
    "gn:population":0,
    "gn:timezone":"America/Caracas",
    "iso:country":"VE",
    "wof:name":"Araguao",
    "wof:placetype":"locality"
},
  "geometry": {"coordinates":[-61.08333,9.16667],"type":"Point"}
}