{
  "type": "Feature",
  "properties": {
    "gn:admin1_code":"6",
    "gn:asciiname":"La Cantina",
    "gn:cc2":"VE",
    "gn:country_code":"VE",
    "gn:dem":270,
    "gn:feature_class":"P",
    "gn:feature_code":"PPL",
    "gn:name":"La Cantina",
    "gn:population":0,
    "gn:timezone":"America/Caracas",
    "iso:country":"VE",
    "name:und_x_variant":[
        "Cantina",
        "La Cantina"
    ],
    "wof:name":"La Cantina",
    "wof:placetype":"locality"
},
  "geometry": {"coordinates":[-62.75,7.53333],"type":"Point"}
}