{
  "type": "Feature",
  "properties": {
    "gn:admin1_code":"6",
    "gn:asciiname":"La Arenosa",
    "gn:country_code":"VE",
    "gn:dem":67,
    "gn:feature_class":"P",
    "gn:feature_code":"PPL",
    "gn:name":"La Arenosa",
    "gn:population":0,
    "gn:timezone":"America/Caracas",
    "iso:country":"VE",
    "name:und_x_variant":[
        "Arenas",
        "La Arenosa"
    ],
    "wof:name":"La Arenosa",
    "wof:placetype":"locality"
},
  "geometry": {"coordinates":[-66.71258,6.72623],"type":"Point"}
}