{
  "type": "Feature",
  "properties": {
    "iso:country":"VE",
    "qs:gn_country":"VE",
    "qs:gn_fcode":"PPL",
    "qs:gn_pop":0,
    "qs:name":"San Juan",
    "qs:name_adm0":"Venezuela",
    "qs:name_adm1":"M\u00e9rida",
    "qs:photos":39,
    "qs:photos_1k":8,
    "qs:photos_9k":1,
    "qs:photos_9r":2,
    "qs:photos_all":39,
    "qs:photos_sr":2,
    "qs:placetype":"Town",
    "qs:pop_sr":"0",
    "qs:woe_adm0":23424982,
    "wof:name":"San Juan",
    "wof:placetype":"locality"
},
  "geometry": {"coordinates":[-71.34958,8.51239],"type":"Point"}
}