{
  "type": "Feature",
  "properties": {
    "gn:admin1_code":"14",
    "gn:asciiname":"Mucusuru",
    "gn:country_code":"VE",
    "gn:dem":2264,
    "gn:feature_class":"P",
    "gn:feature_code":"PPL",
    "gn:name":"Mucusur\u00fa",
    "gn:population":0,
    "gn:timezone":"America/Caracas",
    "iso:country":"VE",
    "wof:name":"Mucusuru",
    "wof:placetype":"locality"
},
  "geometry": {"coordinates":[-71.17929000000002,8.37744],"type":"Point"}
}