{
  "type": "Feature",
  "properties": {
    "gn:admin1_code":"16",
    "gn:asciiname":"Alto de La Iguana",
    "gn:country_code":"VE",
    "gn:dem":242,
    "gn:feature_class":"P",
    "gn:feature_code":"PPL",
    "gn:name":"Alto de La Iguana",
    "gn:population":0,
    "gn:timezone":"America/Caracas",
    "iso:country":"VE",
    "wof:name":"Alto de La Iguana",
    "wof:placetype":"locality"
},
  "geometry": {"coordinates":[-63.3551,9.96547],"type":"Point"}
}