{
  "type": "Feature",
  "properties": {
    "gn:admin1_code":"11.0",
    "gn:asciiname":"Miramar",
    "gn:country_code":"VE",
    "gn:dem":111,
    "gn:feature_class":"P",
    "gn:feature_code":"PPL",
    "gn:name":"Miramar",
    "gn:population":0,
    "gn:timezone":"America/Caracas",
    "iso:country":"VE",
    "wof:name":"Miramar",
    "wof:placetype":"locality"
},
  "geometry": {"coordinates":[-69.92121999999999,12.01594],"type":"Point"}
}