{
  "type": "Feature",
  "properties": {
    "gn:admin1_code":"12",
    "gn:asciiname":"Uverito",
    "gn:country_code":"VE",
    "gn:dem":132,
    "gn:feature_class":"P",
    "gn:feature_code":"PPL",
    "gn:name":"Uverito",
    "gn:population":0,
    "gn:timezone":"America/Caracas",
    "iso:country":"VE",
    "wof:name":"Uverito",
    "wof:placetype":"locality"
},
  "geometry": {"coordinates":[-65.01123,8.94641],"type":"Point"}
}