{
  "type": "Feature",
  "properties": {
    "gn:admin1_code":"15",
    "gn:asciiname":"El Macho",
    "gn:country_code":"VE",
    "gn:dem":395,
    "gn:feature_class":"P",
    "gn:feature_code":"PPL",
    "gn:name":"El Macho",
    "gn:population":0,
    "gn:timezone":"America/Caracas",
    "iso:country":"VE",
    "name:deu_x_preferred":[
        "El Macho"
    ],
    "name:ita_x_preferred":[
        "El macho"
    ],
    "wof:name":"El Macho",
    "wof:placetype":"locality"
},
  "geometry": {"coordinates":[-66.16249999999999,10.0475],"type":"Point"}
}