{
  "type": "Feature",
  "properties": {
    "gn:admin1_code":"15.0",
    "gn:asciiname":"Tucupe",
    "gn:country_code":"VE",
    "gn:dem":1007,
    "gn:feature_class":"P",
    "gn:feature_code":"PPLL",
    "gn:name":"Tucupe",
    "gn:population":0,
    "gn:timezone":"America/Caracas",
    "iso:country":"VE",
    "wof:name":"Tucupe",
    "wof:placetype":"locality"
},
  "geometry": {"coordinates":[-66.92721999999999,10.41157],"type":"Point"}
}