{
  "type": "Feature",
  "properties": {
    "gn:admin1_code":"17",
    "gn:asciiname":"La Chica",
    "gn:country_code":"VE",
    "gn:dem":28,
    "gn:feature_class":"P",
    "gn:feature_code":"PPL",
    "gn:name":"La Chica",
    "gn:population":0,
    "gn:timezone":"America/Caracas",
    "iso:country":"VE",
    "wof:name":"La Chica",
    "wof:placetype":"locality"
},
  "geometry": {"coordinates":[-64.01666999999999,10.93333],"type":"Point"}
}