{
  "type": "Feature",
  "properties": {
    "gn:admin1_code":"13",
    "gn:asciiname":"El Tintorero",
    "gn:country_code":"VE",
    "gn:dem":661,
    "gn:feature_class":"P",
    "gn:feature_code":"PPL",
    "gn:name":"El Tintorero",
    "gn:population":0,
    "gn:timezone":"America/Caracas",
    "iso:country":"VE",
    "wof:name":"El Tintorero",
    "wof:placetype":"locality"
},
  "geometry": {"coordinates":[-69.56788,9.98657],"type":"Point"}
}