{
  "type": "Feature",
  "properties": {
    "gn:admin1_code":"3",
    "gn:asciiname":"Mata del Medio",
    "gn:cc2":"VE",
    "gn:country_code":"VE",
    "gn:dem":68,
    "gn:feature_class":"P",
    "gn:feature_code":"PPL",
    "gn:name":"Mata del Medio",
    "gn:population":0,
    "gn:timezone":"America/Caracas",
    "iso:country":"VE",
    "name:und_x_variant":[
        "Meta del Medio",
        "Mata del Medio"
    ],
    "wof:name":"Mata del Medio",
    "wof:placetype":"locality"
},
  "geometry": {"coordinates":[-68.75,7.73333],"type":"Point"}
}