{
  "type": "Feature",
  "properties": {
    "gn:admin1_code":"9",
    "gn:admin2_code":"1002.0",
    "gn:asciiname":"Sierra Imataca",
    "gn:country_code":"VE",
    "gn:dem":107,
    "gn:feature_class":"P",
    "gn:feature_code":"PPLA2",
    "gn:name":"Sierra Imataca",
    "gn:population":0,
    "gn:timezone":"America/Caracas",
    "iso:country":"VE",
    "name:spa_x_preferred":[
        "Sierra Imataca"
    ],
    "wof:name":"Sierra Imataca",
    "wof:placetype":"locality"
},
  "geometry": {"coordinates":[-62.42891,8.4555],"type":"Point"}
}