{
  "type": "Feature",
  "properties": {
    "gn:admin1_code":"02",
    "gn:asciiname":"Los Manantiales",
    "gn:country_code":"VE",
    "gn:dem":955,
    "gn:feature_class":"P",
    "gn:feature_code":"PPLL",
    "gn:name":"Los Manantiales",
    "gn:population":0,
    "gn:timezone":"America/Caracas",
    "iso:country":"VE",
    "wof:name":"Los Manantiales",
    "wof:placetype":"locality"
},
  "geometry": {"coordinates":[-64.19167,10.01444],"type":"Point"}
}