{
  "type": "Feature",
  "properties": {
    "gn:admin1_code":"23",
    "gn:asciiname":"Sarria",
    "gn:country_code":"VE",
    "gn:dem":77,
    "gn:feature_class":"P",
    "gn:feature_code":"PPL",
    "gn:name":"Sarr\u00eda",
    "gn:population":0,
    "gn:timezone":"America/Caracas",
    "iso:country":"VE",
    "name:und_x_variant":[
        "Sarr\u00eda"
    ],
    "wof:name":"Sarria",
    "wof:placetype":"locality"
},
  "geometry": {"coordinates":[-71.31928000000001,10.41887],"type":"Point"}
}