{
  "type": "Feature",
  "properties": {
    "gn:admin1_code":"23",
    "gn:asciiname":"Sarria",
    "gn:country_code":"VE",
    "gn:dem":77,
    "gn:feature_class":"P",
    "gn:feature_code":"PPL",
    "gn:name":"Sarr\u00eda",
    "gn:population":0,
    "gn:timezone":"America/Caracas",
    "iso:country":"VE",
    "name:arg_x_preferred":[
        "Sarria"
    ],
    "name:azb_x_preferred":[
        "\u0633\u0627\u0631\u06cc\u0627"
    ],
    "name:bre_x_preferred":[
        "Sarria"
    ],
    "name:cat_x_preferred":[
        "Sarria"
    ],
    "name:ceb_x_preferred":[
        "Sarria"
    ],
    "name:ces_x_preferred":[
        "Sarria"
    ],
    "name:deu_x_preferred":[
        "Sarria"
    ],
    "name:eus_x_preferred":[
        "Sarria"
    ],
    "name:fas_x_preferred":[
        "\u0633\u0627\u0631\u06cc\u0627"
    ],
    "name:glg_x_preferred":[
        "Sarria"
    ],
    "name:hun_x_preferred":[
        "Sarria"
    ],
    "name:ita_x_preferred":[
        "Sarria"
    ],
    "name:jpn_x_preferred":[
        "\u30b5\u30ea\u30a2"
    ],
    "name:kaz_x_preferred":[
        "\u0421\u0430\u0440\u0440\u0438\u0430"
    ],
    "name:lmo_x_preferred":[
        "Sarria"
    ],
    "name:msa_x_preferred":[
        "Sarria"
    ],
    "name:nld_x_preferred":[
        "Sarria"
    ],
    "name:oci_x_preferred":[
        "Sarria"
    ],
    "name:pol_x_preferred":[
        "Sarria"
    ],
    "name:por_x_preferred":[
        "Sarria"
    ],
    "name:rus_x_preferred":[
        "\u0421\u0430\u0440\u0440\u0438\u044f"
    ],
    "name:spa_x_preferred":[
        "Sarria"
    ],
    "name:swe_x_preferred":[
        "Sarria"
    ],
    "name:tur_x_preferred":[
        "Sarria"
    ],
    "name:ukr_x_preferred":[
        "\u0421\u0430\u0440\u0440\u0456\u044f"
    ],
    "name:und_x_variant":[
        "Sarr\u00eda"
    ],
    "name:uzb_x_preferred":[
        "Sarria"
    ],
    "name:vie_x_preferred":[
        "Sarria"
    ],
    "name:war_x_preferred":[
        "Sarria"
    ],
    "name:zho_x_preferred":[
        "\u8428\u91cc\u4e9a"
    ],
    "wof:name":"Sarria",
    "wof:placetype":"locality"
},
  "geometry": {"coordinates":[-71.31928000000001,10.41887],"type":"Point"}
}