{
  "type": "Feature",
  "properties": {
    "gn:admin1_code":"20.0",
    "gn:asciiname":"El Tesoro",
    "gn:country_code":"VE",
    "gn:dem":188,
    "gn:feature_class":"P",
    "gn:feature_code":"PPLL",
    "gn:name":"El Tesoro",
    "gn:population":0,
    "gn:timezone":"America/Caracas",
    "iso:country":"VE",
    "wof:name":"El Tesoro",
    "wof:placetype":"locality"
},
  "geometry": {"coordinates":[-71.69564,7.63152],"type":"Point"}
}