{
  "type": "Feature",
  "properties": {
    "gn:admin1_code":"7",
    "gn:asciiname":"El Cambur",
    "gn:country_code":"VE",
    "gn:dem":65,
    "gn:feature_class":"P",
    "gn:feature_code":"PPL",
    "gn:name":"El Cambur",
    "gn:population":0,
    "gn:timezone":"America/Caracas",
    "iso:country":"VE",
    "wof:name":"El Cambur",
    "wof:placetype":"locality"
},
  "geometry": {"coordinates":[-68.10741,10.40296],"type":"Point"}
}