{
  "type": "Feature",
  "properties": {
    "gn:admin1_code":"13.0",
    "gn:asciiname":"Catalina",
    "gn:country_code":"VE",
    "gn:dem":1101,
    "gn:feature_class":"P",
    "gn:feature_code":"PPL",
    "gn:name":"Catalina",
    "gn:population":0,
    "gn:timezone":"America/Caracas",
    "iso:country":"VE",
    "wof:name":"Catalina",
    "wof:placetype":"locality"
},
  "geometry": {"coordinates":[-70.15326,9.80409],"type":"Point"}
}