{
  "type": "Feature",
  "properties": {
    "gn:admin1_code":"18.0",
    "gn:asciiname":"El Acequion",
    "gn:country_code":"VE",
    "gn:dem":121,
    "gn:feature_class":"P",
    "gn:feature_code":"PPL",
    "gn:name":"El Acequi\u00f3n",
    "gn:population":0,
    "gn:timezone":"America/Caracas",
    "iso:country":"VE",
    "name:spa_x_preferred":[
        "El Acequi\u00f3n"
    ],
    "wof:name":"El Acequion",
    "wof:placetype":"locality"
},
  "geometry": {"coordinates":[-69.03662,9.31564],"type":"Point"}
}