{
  "type": "Feature",
  "properties": {
    "gn:admin1_code":"12",
    "gn:asciiname":"Jabillal",
    "gn:country_code":"VE",
    "gn:dem":487,
    "gn:feature_class":"P",
    "gn:feature_code":"PPL",
    "gn:name":"Jabillal",
    "gn:population":0,
    "gn:timezone":"America/Caracas",
    "iso:country":"VE",
    "name:und_x_variant":[
        "Paso Javillal",
        "Jubillal",
        "Javillal",
        "Jabillal"
    ],
    "wof:name":"Jabillal",
    "wof:placetype":"locality"
},
  "geometry": {"coordinates":[-66.3456,9.90066],"type":"Point"}
}