{
  "type": "Feature",
  "properties": {
    "gn:admin1_code":"18",
    "gn:asciiname":"Punta Brava",
    "gn:country_code":"VE",
    "gn:dem":148,
    "gn:feature_class":"P",
    "gn:feature_code":"PPL",
    "gn:name":"Punta Brava",
    "gn:population":0,
    "gn:timezone":"America/Caracas",
    "iso:country":"VE",
    "wof:name":"Punta Brava",
    "wof:placetype":"locality"
},
  "geometry": {"coordinates":[-69.14263000000001,9.37802],"type":"Point"}
}