{
  "type": "Feature",
  "properties": {
    "gn:admin1_code":"16",
    "gn:asciiname":"El Hueco",
    "gn:country_code":"VE",
    "gn:dem":92,
    "gn:feature_class":"P",
    "gn:feature_code":"PPL",
    "gn:name":"El Hueco",
    "gn:population":0,
    "gn:timezone":"America/Caracas",
    "iso:country":"VE",
    "name:spa_x_preferred":[
        "El Hueco"
    ],
    "wof:name":"El Hueco",
    "wof:placetype":"locality"
},
  "geometry": {"coordinates":[-63.14504,10.14636],"type":"Point"}
}