{
  "type": "Feature",
  "properties": {
    "gn:admin1_code":"16",
    "gn:asciiname":"El Ristero",
    "gn:country_code":"VE",
    "gn:dem":293,
    "gn:feature_class":"P",
    "gn:feature_code":"PPL",
    "gn:name":"El Ristero",
    "gn:population":0,
    "gn:timezone":"America/Caracas",
    "iso:country":"VE",
    "wof:name":"El Ristero",
    "wof:placetype":"locality"
},
  "geometry": {"coordinates":[-63.72968,9.96698],"type":"Point"}
}