{
  "type": "Feature",
  "properties": {
    "gn:admin1_code":"13",
    "gn:asciiname":"Riecito",
    "gn:country_code":"VE",
    "gn:dem":398,
    "gn:feature_class":"P",
    "gn:feature_code":"PPL",
    "gn:name":"Riecito",
    "gn:population":0,
    "gn:timezone":"America/Caracas",
    "iso:country":"VE",
    "wof:name":"Riecito",
    "wof:placetype":"locality"
},
  "geometry": {"coordinates":[-70.77278000000003,9.98611],"type":"Point"}
}