{
  "type": "Feature",
  "properties": {
    "gn:admin1_code":"15",
    "gn:asciiname":"Aramina",
    "gn:cc2":"VE",
    "gn:country_code":"VE",
    "gn:dem":115,
    "gn:feature_class":"P",
    "gn:feature_code":"PPL",
    "gn:name":"Aramina",
    "gn:population":0,
    "gn:timezone":"America/Caracas",
    "iso:country":"VE",
    "name:bpy_x_preferred":[
        "\u09f1\u09be\u09b0\u09be\u09ae\u09bf\u09a8\u09be"
    ],
    "name:ceb_x_preferred":[
        "Aramina"
    ],
    "name:epo_x_preferred":[
        "Aramina"
    ],
    "name:eus_x_preferred":[
        "Aramina"
    ],
    "name:fra_x_preferred":[
        "Aramina"
    ],
    "name:ita_x_preferred":[
        "Aramina"
    ],
    "name:kaz_x_preferred":[
        "\u0410\u0440\u0430\u043c\u0438\u043d\u0430"
    ],
    "name:mlg_x_preferred":[
        "Aramina"
    ],
    "name:nld_x_preferred":[
        "Aramina"
    ],
    "name:nor_x_preferred":[
        "Aramina"
    ],
    "name:pol_x_preferred":[
        "Aramina"
    ],
    "name:por_x_preferred":[
        "Aramina"
    ],
    "name:ron_x_preferred":[
        "Aramina"
    ],
    "name:rus_x_preferred":[
        "\u0410\u0440\u0430\u043c\u0438\u043d\u0430"
    ],
    "name:spa_x_preferred":[
        "Aramina"
    ],
    "name:swe_x_preferred":[
        "Aramina"
    ],
    "name:und_x_variant":[
        "Aranima"
    ],
    "name:vie_x_preferred":[
        "Aramina"
    ],
    "name:vol_x_preferred":[
        "Aramina"
    ],
    "name:war_x_preferred":[
        "Aramina"
    ],
    "name:zho_x_preferred":[
        "\u963f\u62c9\u7c73\u7eb3"
    ],
    "wof:name":"Aramina",
    "wof:placetype":"locality"
},
  "geometry": {"coordinates":[-66.28333000000001,10.38333],"type":"Point"}
}