{
  "type": "Feature",
  "properties": {
    "gn:admin1_code":"15",
    "gn:asciiname":"Aramina",
    "gn:cc2":"VE",
    "gn:country_code":"VE",
    "gn:dem":115,
    "gn:feature_class":"P",
    "gn:feature_code":"PPL",
    "gn:name":"Aramina",
    "gn:population":0,
    "gn:timezone":"America/Caracas",
    "iso:country":"VE",
    "name:und_x_variant":[
        "Aranima",
        "Aramina"
    ],
    "wof:name":"Aramina",
    "wof:placetype":"locality"
},
  "geometry": {"coordinates":[-66.28333000000001,10.38333],"type":"Point"}
}