{
  "type": "Feature",
  "properties": {
    "gn:admin1_code":"18.0",
    "gn:asciiname":"La Coromoto",
    "gn:country_code":"VE",
    "gn:dem":213,
    "gn:feature_class":"P",
    "gn:feature_code":"PPL",
    "gn:name":"La Coromoto",
    "gn:population":0,
    "gn:timezone":"America/Caracas",
    "iso:country":"VE",
    "wof:name":"La Coromoto",
    "wof:placetype":"locality"
},
  "geometry": {"coordinates":[-69.40714,9.37152],"type":"Point"}
}