{
  "type": "Feature",
  "properties": {
    "gn:admin1_code":"11.0",
    "gn:asciiname":"El Olivito",
    "gn:country_code":"VE",
    "gn:dem":66,
    "gn:feature_class":"P",
    "gn:feature_code":"PPLL",
    "gn:name":"El Olivito",
    "gn:population":0,
    "gn:timezone":"America/Caracas",
    "iso:country":"VE",
    "wof:name":"El Olivito",
    "wof:placetype":"locality"
},
  "geometry": {"coordinates":[-70.72498,11.03944],"type":"Point"}
}