{
  "type": "Feature",
  "properties": {
    "gn:admin1_code":"22",
    "gn:asciiname":"Cocorotico",
    "gn:country_code":"VE",
    "gn:dem":148,
    "gn:feature_class":"P",
    "gn:feature_code":"PPL",
    "gn:name":"Cocorotico",
    "gn:population":0,
    "gn:timezone":"America/Caracas",
    "iso:country":"VE",
    "wof:name":"Cocorotico",
    "wof:placetype":"locality"
},
  "geometry": {"coordinates":[-68.6844,10.377],"type":"Point"}
}