{
  "type": "Feature",
  "properties": {
    "gn:admin1_code":"3",
    "gn:asciiname":"Macanillita",
    "gn:cc2":"VE",
    "gn:country_code":"VE",
    "gn:dem":45,
    "gn:feature_class":"P",
    "gn:feature_code":"PPL",
    "gn:name":"Macanillita",
    "gn:population":0,
    "gn:timezone":"America/Caracas",
    "iso:country":"VE",
    "name:und_x_variant":[
        "Macarillita",
        "Macanillita"
    ],
    "wof:name":"Macanillita",
    "wof:placetype":"locality"
},
  "geometry": {"coordinates":[-67.11667,7.33333],"type":"Point"}
}