{
  "type": "Feature",
  "properties": {
    "gn:admin1_code":"15",
    "gn:asciiname":"Tacata",
    "gn:country_code":"VE",
    "gn:dem":336,
    "gn:feature_class":"P",
    "gn:feature_code":"PPL",
    "gn:name":"T\u00e1cata",
    "gn:population":0,
    "gn:timezone":"America/Caracas",
    "iso:country":"VE",
    "name:fra_x_preferred":[
        "T\u00e1cata"
    ],
    "name:jpn_x_preferred":[
        "\u30bf\u30ab\u30bf"
    ],
    "name:spa_x_preferred":[
        "Parroquia T\u00e1cata"
    ],
    "name:und_x_variant":[
        "T\u00e1cata"
    ],
    "wof:name":"Tacata",
    "wof:placetype":"locality"
},
  "geometry": {"coordinates":[-67.00587,10.20905],"type":"Point"}
}