{
  "type": "Feature",
  "properties": {
    "gn:admin1_code":"6",
    "gn:asciiname":"Puerto Hormigo",
    "gn:country_code":"VE",
    "gn:dem":458,
    "gn:feature_class":"P",
    "gn:feature_code":"PPL",
    "gn:name":"Puerto Hormigo",
    "gn:population":0,
    "gn:timezone":"America/Caracas",
    "iso:country":"VE",
    "wof:name":"Puerto Hormigo",
    "wof:placetype":"locality"
},
  "geometry": {"coordinates":[-62.63333000000001,6.41667],"type":"Point"}
}