{
  "type": "Feature",
  "properties": {
    "gn:admin1_code":"02",
    "gn:asciiname":"El Falucho",
    "gn:country_code":"VE",
    "gn:dem":-9999,
    "gn:feature_class":"P",
    "gn:feature_code":"PPLL",
    "gn:name":"El Falucho",
    "gn:population":0,
    "gn:timezone":"America/Caracas",
    "iso:country":"VE",
    "wof:name":"El Falucho",
    "wof:placetype":"locality"
},
  "geometry": {"coordinates":[-65.15056,10.08389],"type":"Point"}
}