{
  "type": "Feature",
  "properties": {
    "gn:admin1_code":"5",
    "gn:asciiname":"Domingo Garrido",
    "gn:country_code":"VE",
    "gn:dem":98,
    "gn:feature_class":"P",
    "gn:feature_code":"PPL",
    "gn:name":"Domingo Garrido",
    "gn:population":0,
    "gn:timezone":"America/Caracas",
    "iso:country":"VE",
    "wof:name":"Domingo Garrido",
    "wof:placetype":"locality"
},
  "geometry": {"coordinates":[-69.55,8.36667],"type":"Point"}
}