{
  "type": "Feature",
  "properties": {
    "gn:admin1_code":"12",
    "gn:asciiname":"Pueblo Nuevo",
    "gn:country_code":"VE",
    "gn:dem":318,
    "gn:feature_class":"P",
    "gn:feature_code":"PPL",
    "gn:name":"Pueblo Nuevo",
    "gn:population":0,
    "gn:timezone":"America/Caracas",
    "iso:country":"VE",
    "name:ceb_x_preferred":[
        "Pueblo Nuevo"
    ],
    "name:deu_x_preferred":[
        "Pueblo Nuevo"
    ],
    "name:epo_x_preferred":[
        "Pueblo Nuevo"
    ],
    "name:fra_x_preferred":[
        "Pueblo Nuevo"
    ],
    "name:ita_x_preferred":[
        "Pueblo Nuevo"
    ],
    "name:nds_x_preferred":[
        "Pueblo Nuevo"
    ],
    "name:nld_x_preferred":[
        "Pueblo Nuevo"
    ],
    "name:pol_x_preferred":[
        "Pueblo Nuevo"
    ],
    "name:por_x_preferred":[
        "Pueblo Nuevo"
    ],
    "name:rus_x_preferred":[
        "\u041f\u0443\u044d\u0431\u043b\u043e-\u041d\u0443\u044d\u0432\u043e"
    ],
    "name:sco_x_preferred":[
        "Pueblo Nuevo"
    ],
    "name:spa_x_preferred":[
        "Pueblo Nuevo"
    ],
    "name:srp_x_preferred":[
        "\u041f\u0443\u0435\u0431\u043b\u043e \u041d\u0443\u0435\u0432\u043e"
    ],
    "name:swe_x_preferred":[
        "Pueblo Nuevo"
    ],
    "name:vie_x_preferred":[
        "Pueblo Nuevo"
    ],
    "wof:name":"Pueblo Nuevo",
    "wof:placetype":"locality"
},
  "geometry": {"coordinates":[-67.60921999999999,9.7668],"type":"Point"}
}