{
  "type": "Feature",
  "properties": {
    "gn:admin1_code":"7",
    "gn:asciiname":"El Escondido",
    "gn:country_code":"VE",
    "gn:dem":544,
    "gn:feature_class":"P",
    "gn:feature_code":"PPL",
    "gn:name":"El Escondido",
    "gn:population":0,
    "gn:timezone":"America/Caracas",
    "iso:country":"VE",
    "name:spa_x_preferred":[
        "Volc\u00e1n El Escondido"
    ],
    "name:zho_x_preferred":[
        "\u57c3\u723e\u57c3\u65af\u5b54\u8fea\u591a\u706b\u5c71"
    ],
    "wof:name":"El Escondido",
    "wof:placetype":"locality"
},
  "geometry": {"coordinates":[-68.16701999999999,10.04832],"type":"Point"}
}