{
  "type": "Feature",
  "properties": {
    "gn:admin1_code":"11.0",
    "gn:asciiname":"El Concilio",
    "gn:country_code":"VE",
    "gn:dem":290,
    "gn:feature_class":"P",
    "gn:feature_code":"PPL",
    "gn:name":"El Concilio",
    "gn:population":0,
    "gn:timezone":"America/Caracas",
    "iso:country":"VE",
    "wof:name":"El Concilio",
    "wof:placetype":"locality"
},
  "geometry": {"coordinates":[-70.05400999999999,10.91943],"type":"Point"}
}