{
  "type": "Feature",
  "properties": {
    "gn:admin1_code":"14",
    "gn:asciiname":"Belen",
    "gn:country_code":"VE",
    "gn:dem":1667,
    "gn:feature_class":"P",
    "gn:feature_code":"PPL",
    "gn:name":"Bel\u00e9n",
    "gn:population":0,
    "gn:timezone":"America/Caracas",
    "iso:country":"VE",
    "wof:name":"Belen",
    "wof:placetype":"locality"
},
  "geometry": {"coordinates":[-71.47310999999998,8.53369],"type":"Point"}
}