{
  "type": "Feature",
  "properties": {
    "gn:admin1_code":"14",
    "gn:asciiname":"Belen",
    "gn:country_code":"VE",
    "gn:dem":1667,
    "gn:feature_class":"P",
    "gn:feature_code":"PPL",
    "gn:name":"Bel\u00e9n",
    "gn:population":0,
    "gn:timezone":"America/Caracas",
    "iso:country":"VE",
    "name:ara_x_preferred":[
        "\u0628\u064a\u0644\u064a\u0646"
    ],
    "name:ben_x_preferred":[
        "\u09ac\u09c7\u09b2\u09c7\u09a8"
    ],
    "name:bul_x_preferred":[
        "\u0411\u0435\u043b\u0435\u043d"
    ],
    "name:ceb_x_preferred":[
        "Belen"
    ],
    "name:ell_x_preferred":[
        "\u039c\u03c0\u03b5\u03bb\u03ad\u03bd"
    ],
    "name:hin_x_preferred":[
        "\u092c\u0947\u0932\u0947\u0928"
    ],
    "name:hun_x_preferred":[
        "Belen"
    ],
    "name:hye_x_preferred":[
        "\u0532\u0565\u056c\u0565\u0576"
    ],
    "name:ind_x_preferred":[
        "Belen"
    ],
    "name:jpn_x_preferred":[
        "\u30d9\u30ec\u30f3"
    ],
    "name:kaz_x_preferred":[
        "\u0411\u0435\u043b\u0435\u043d"
    ],
    "name:kor_x_preferred":[
        "\ubca8\ub80c"
    ],
    "name:min_x_preferred":[
        "Belen"
    ],
    "name:nld_x_preferred":[
        "Belen"
    ],
    "name:rus_x_preferred":[
        "\u0411\u0435\u043b\u0435\u043d"
    ],
    "name:sco_x_preferred":[
        "Belen"
    ],
    "name:srp_x_preferred":[
        "\u0411\u0435\u043b\u0435\u043d"
    ],
    "name:swe_x_preferred":[
        "Belen"
    ],
    "name:tur_x_preferred":[
        "Belen"
    ],
    "name:ukr_x_preferred":[
        "\u0411\u0435\u043b\u0435\u043d"
    ],
    "name:urd_x_preferred":[
        "\u0628\u06cc\u0644\u06cc\u0646"
    ],
    "name:vie_x_preferred":[
        "Belen"
    ],
    "wof:name":"Belen",
    "wof:placetype":"locality"
},
  "geometry": {"coordinates":[-71.47311000000001,8.53369],"type":"Point"}
}