{
  "type": "Feature",
  "properties": {
    "gn:admin1_code":"02",
    "gn:asciiname":"Campanario",
    "gn:country_code":"VE",
    "gn:dem":69,
    "gn:feature_class":"P",
    "gn:feature_code":"PPL",
    "gn:name":"Campanario",
    "gn:population":0,
    "gn:timezone":"America/Caracas",
    "iso:country":"VE",
    "name:ceb_x_preferred":[
        "Campanario"
    ],
    "name:epo_x_preferred":[
        "Campanario"
    ],
    "name:nld_x_preferred":[
        "Campanario"
    ],
    "name:spa_x_preferred":[
        "Campanario"
    ],
    "name:swe_x_preferred":[
        "Campanario"
    ],
    "wof:name":"Campanario",
    "wof:placetype":"locality"
},
  "geometry": {"coordinates":[-65.35231999999999,9.92778],"type":"Point"}
}