{
  "type": "Feature",
  "properties": {
    "gn:admin1_code":"12",
    "gn:asciiname":"El Caribote",
    "gn:country_code":"VE",
    "gn:dem":338,
    "gn:feature_class":"P",
    "gn:feature_code":"PPL",
    "gn:name":"El Caribote",
    "gn:population":0,
    "gn:timezone":"America/Caracas",
    "iso:country":"VE",
    "wof:name":"El Caribote",
    "wof:placetype":"locality"
},
  "geometry": {"coordinates":[-65.81667,9.91667],"type":"Point"}
}