{
  "type": "Feature",
  "properties": {
    "iso:country":"VE",
    "qs:gn_pop":0,
    "qs:name":"Rafael Urdaneta",
    "qs:name_adm0":"Venezuela",
    "qs:name_adm1":"Carabobo",
    "qs:photos":190,
    "qs:photos_1k":39,
    "qs:photos_9k":1,
    "qs:photos_9r":5,
    "qs:photos_all":334,
    "qs:photos_sr":4,
    "qs:placetype":"LocalAdmin",
    "qs:pop_sr":"0",
    "qs:woe_adm0":23424982,
    "wof:name":"Rafael Urdaneta",
    "wof:placetype":"localadmin"
},
  "geometry": {"coordinates":[-67.95961200000001,10.234429],"type":"Point"}
}