{
  "type": "Feature",
  "properties": {
    "iso:country":"VE",
    "name:ara_x_preferred":[
        "\u0631\u0627\u0641\u0627\u0626\u064a\u0644 \u0623\u0648\u0631\u062f\u0627\u0646\u064a\u062a\u0627"
    ],
    "name:cat_x_preferred":[
        "Rafael Urdaneta"
    ],
    "name:deu_x_preferred":[
        "Rafael Urdaneta"
    ],
    "name:epo_x_preferred":[
        "Rafael Urdaneta"
    ],
    "name:fra_x_preferred":[
        "Rafael Urdaneta"
    ],
    "name:gla_x_preferred":[
        "Rafael Urdaneta"
    ],
    "name:glg_x_preferred":[
        "Rafael Urdaneta"
    ],
    "name:ido_x_preferred":[
        "Rafael Urdaneta"
    ],
    "name:ita_x_preferred":[
        "Rafael Urdaneta"
    ],
    "name:jpn_x_preferred":[
        "\u30e9\u30d5\u30a1\u30a8\u30eb\u30fb\u30a6\u30eb\u30c0\u30cd\u30bf"
    ],
    "name:kor_x_preferred":[
        "\ub77c\ud30c\uc5d8 \uc6b0\ub974\ub2e4\ub124\ud0c0"
    ],
    "name:oci_x_preferred":[
        "Rafael Urdaneta"
    ],
    "name:por_x_preferred":[
        "Rafael Urdaneta"
    ],
    "name:rus_x_preferred":[
        "\u0423\u0440\u0434\u0430\u043d\u0435\u0442\u0430"
    ],
    "name:spa_x_preferred":[
        "Rafael Urdaneta"
    ],
    "name:ukr_x_preferred":[
        "\u0420\u0430\u0444\u0430\u0435\u043b\u044c \u0423\u0440\u0434\u0430\u043d\u0435\u0442\u0430"
    ],
    "name:vie_x_preferred":[
        "Rafael Urdaneta"
    ],
    "name:yor_x_preferred":[
        "Rafael Urdaneta"
    ],
    "qs:gn_pop":0,
    "qs:name":"Rafael Urdaneta",
    "qs:name_adm0":"Venezuela",
    "qs:name_adm1":"Carabobo",
    "qs:photos":190,
    "qs:photos_1k":39,
    "qs:photos_9k":1,
    "qs:photos_9r":5,
    "qs:photos_all":334,
    "qs:photos_sr":4,
    "qs:placetype":"LocalAdmin",
    "qs:pop_sr":"0",
    "qs:woe_adm0":23424982,
    "wof:name":"Rafael Urdaneta",
    "wof:placetype":"localadmin"
},
  "geometry": {"coordinates":[-67.95961200000001,10.234429],"type":"Point"}
}