{
  "type": "Feature",
  "properties": {
    "gn:admin1_code":"3",
    "gn:asciiname":"Costa de Anaru",
    "gn:country_code":"VE",
    "gn:dem":123,
    "gn:feature_class":"P",
    "gn:feature_code":"PPLL",
    "gn:name":"Costa de Anar\u00fa",
    "gn:population":0,
    "gn:timezone":"America/Caracas",
    "iso:country":"VE",
    "wof:name":"Costa de Anaru",
    "wof:placetype":"locality"
},
  "geometry": {"coordinates":[-70.53917,7.41028],"type":"Point"}
}