{
  "type": "Feature",
  "properties": {
    "gn:admin1_code":"23",
    "gn:asciiname":"Puerto del Hacha",
    "gn:country_code":"VE",
    "gn:dem":68,
    "gn:feature_class":"P",
    "gn:feature_code":"PPL",
    "gn:name":"Puerto del Hacha",
    "gn:population":0,
    "gn:timezone":"America/Caracas",
    "iso:country":"VE",
    "wof:name":"Puerto del Hacha",
    "wof:placetype":"locality"
},
  "geometry": {"coordinates":[-72.17959999999999,11.18581],"type":"Point"}
}