{
  "type": "Feature",
  "properties": {
    "gn:admin1_code":"11.0",
    "gn:asciiname":"Cueva de los Indios",
    "gn:country_code":"VE",
    "gn:dem":14,
    "gn:feature_class":"P",
    "gn:feature_code":"PPLL",
    "gn:name":"Cueva de los Indios",
    "gn:population":0,
    "gn:timezone":"America/Caracas",
    "iso:country":"VE",
    "wof:name":"Cueva de los Indios",
    "wof:placetype":"locality"
},
  "geometry": {"coordinates":[-68.32666999999999,10.91222],"type":"Point"}
}