{
  "type": "Feature",
  "properties": {
    "gn:admin1_code":"11",
    "gn:asciiname":"La Cercada",
    "gn:cc2":"VE",
    "gn:country_code":"VE",
    "gn:dem":43,
    "gn:feature_class":"P",
    "gn:feature_code":"PPL",
    "gn:name":"La Cercada",
    "gn:population":0,
    "gn:timezone":"America/Caracas",
    "iso:country":"VE",
    "name:und_x_variant":[
        "El Cercado",
        "La Cercada"
    ],
    "wof:name":"La Cercada",
    "wof:placetype":"locality"
},
  "geometry": {"coordinates":[-70.90000000000001,10.96667],"type":"Point"}
}