{
  "type": "Feature",
  "properties": {
    "gn:admin1_code":"23",
    "gn:asciiname":"Los Haticos del Sur",
    "gn:country_code":"VE",
    "gn:dem":10,
    "gn:feature_class":"P",
    "gn:feature_code":"PPL",
    "gn:name":"Los Haticos del Sur",
    "gn:population":0,
    "gn:timezone":"America/Caracas",
    "iso:country":"VE",
    "name:und_x_variant":[
        "Haticos del Sur",
        "Los Haticos del Sur"
    ],
    "wof:name":"Los Haticos del Sur",
    "wof:placetype":"locality"
},
  "geometry": {"coordinates":[-71.5219,10.68905],"type":"Point"}
}