{
  "type": "Feature",
  "properties": {
    "gn:admin1_code":"16",
    "gn:asciiname":"La Viuda",
    "gn:country_code":"VE",
    "gn:dem":13,
    "gn:feature_class":"P",
    "gn:feature_code":"PPL",
    "gn:name":"La Viuda",
    "gn:population":0,
    "gn:timezone":"America/Caracas",
    "iso:country":"VE",
    "wof:name":"La Viuda",
    "wof:placetype":"locality"
},
  "geometry": {"coordinates":[-62.77618,9.91913],"type":"Point"}
}