{
  "type": "Feature",
  "properties": {
    "gn:admin1_code":"11.0",
    "gn:asciiname":"Campo Amor",
    "gn:country_code":"VE",
    "gn:dem":23,
    "gn:feature_class":"P",
    "gn:feature_code":"PPL",
    "gn:name":"Campo Amor",
    "gn:population":0,
    "gn:timezone":"America/Caracas",
    "iso:country":"VE",
    "wof:name":"Campo Amor",
    "wof:placetype":"locality"
},
  "geometry": {"coordinates":[-70.82451999999998,11.14456],"type":"Point"}
}