{
  "type": "Feature",
  "properties": {
    "gn:admin1_code":"22",
    "gn:admin2_code":"2206.0",
    "gn:asciiname":"Sabana de Parra",
    "gn:country_code":"VE",
    "gn:dem":416,
    "gn:feature_class":"P",
    "gn:feature_code":"PPLA2",
    "gn:name":"Sabana de Parra",
    "gn:population":0,
    "gn:timezone":"America/Caracas",
    "iso:country":"VE",
    "name:spa_x_preferred":[
        "Sabana de Parra"
    ],
    "wof:name":"Sabana de Parra",
    "wof:placetype":"locality"
},
  "geometry": {"coordinates":[-69.03639,10.12111],"type":"Point"}
}