{
  "type": "Feature",
  "properties": {
    "gn:admin1_code":"20.0",
    "gn:asciiname":"El Salado",
    "gn:country_code":"VE",
    "gn:dem":563,
    "gn:feature_class":"P",
    "gn:feature_code":"PPLL",
    "gn:name":"El Salado",
    "gn:population":0,
    "gn:timezone":"America/Caracas",
    "iso:country":"VE",
    "wof:name":"El Salado",
    "wof:placetype":"locality"
},
  "geometry": {"coordinates":[-71.93714,8.37627],"type":"Point"}
}