{
  "type": "Feature",
  "properties": {
    "gn:admin1_code":"23",
    "gn:asciiname":"La Paja",
    "gn:country_code":"VE",
    "gn:dem":97,
    "gn:feature_class":"P",
    "gn:feature_code":"PPL",
    "gn:name":"La Paja",
    "gn:population":0,
    "gn:timezone":"America/Caracas",
    "iso:country":"VE",
    "wof:name":"La Paja",
    "wof:placetype":"locality"
},
  "geometry": {"coordinates":[-72.51666999999998,10.05],"type":"Point"}
}