{
  "type": "Feature",
  "properties": {
    "gn:admin1_code":"7",
    "gn:asciiname":"La Paradena",
    "gn:country_code":"VE",
    "gn:dem":683,
    "gn:feature_class":"P",
    "gn:feature_code":"PPL",
    "gn:name":"La Parade\u00f1a",
    "gn:population":0,
    "gn:timezone":"America/Caracas",
    "iso:country":"VE",
    "wof:name":"La Paradena",
    "wof:placetype":"locality"
},
  "geometry": {"coordinates":[-68.17528,10.19024],"type":"Point"}
}