{
  "type": "Feature",
  "properties": {
    "gn:admin1_code":"16.0",
    "gn:asciiname":"El Rincon del Yabo",
    "gn:country_code":"VE",
    "gn:dem":211,
    "gn:feature_class":"P",
    "gn:feature_code":"PPL",
    "gn:name":"El Rinc\u00f3n del Yabo",
    "gn:population":0,
    "gn:timezone":"America/Caracas",
    "iso:country":"VE",
    "wof:name":"El Rincon del Yabo",
    "wof:placetype":"locality"
},
  "geometry": {"coordinates":[-63.80333,9.07444],"type":"Point"}
}