{
  "type": "Feature",
  "properties": {
    "gn:admin1_code":"07",
    "gn:asciiname":"Santa Ines",
    "gn:country_code":"VE",
    "gn:dem":680,
    "gn:feature_class":"P",
    "gn:feature_code":"PPL",
    "gn:name":"Santa In\u00e9s",
    "gn:population":0,
    "gn:timezone":"America/Caracas",
    "iso:country":"VE",
    "name:ceb_x_preferred":[
        "Santa Ines"
    ],
    "name:nld_x_preferred":[
        "Santa Ines"
    ],
    "name:sco_x_preferred":[
        "Santa Ines"
    ],
    "name:srp_x_preferred":[
        "\u0421\u0430\u043d\u0442\u0430 \u0418\u043d\u0435\u0441"
    ],
    "name:swe_x_preferred":[
        "Santa Ines"
    ],
    "name:war_x_preferred":[
        "Santa Ines"
    ],
    "wof:name":"Santa Ines",
    "wof:placetype":"locality"
},
  "geometry": {"coordinates":[-67.83499999999999,9.96111],"type":"Point"}
}