{
  "type": "Feature",
  "properties": {
    "gn:admin1_code":"19.0",
    "gn:asciiname":"San Basilio",
    "gn:country_code":"VE",
    "gn:dem":85,
    "gn:feature_class":"P",
    "gn:feature_code":"PPLL",
    "gn:name":"San Basilio",
    "gn:population":0,
    "gn:timezone":"America/Caracas",
    "iso:country":"VE",
    "wof:name":"San Basilio",
    "wof:placetype":"locality"
},
  "geometry": {"coordinates":[-63.20538000000001,10.574],"type":"Point"}
}