{
  "type": "Feature",
  "properties": {
    "gn:admin1_code":"08",
    "gn:asciiname":"Santoyero",
    "gn:country_code":"VE",
    "gn:dem":71,
    "gn:feature_class":"P",
    "gn:feature_code":"PPL",
    "gn:name":"Santoyero",
    "gn:population":0,
    "gn:timezone":"America/Caracas",
    "iso:country":"VE",
    "wof:name":"Santoyero",
    "wof:placetype":"locality"
},
  "geometry": {"coordinates":[-68.63333,8.33333],"type":"Point"}
}