{
  "type": "Feature",
  "properties": {
    "gn:admin1_code":"2",
    "gn:asciiname":"Los Tigres",
    "gn:country_code":"VE",
    "gn:dem":98,
    "gn:feature_class":"P",
    "gn:feature_code":"PPL",
    "gn:name":"Los Tigres",
    "gn:population":0,
    "gn:timezone":"America/Caracas",
    "iso:country":"VE",
    "wof:name":"Los Tigres",
    "wof:placetype":"locality"
},
  "geometry": {"coordinates":[-65.06347,8.24957],"type":"Point"}
}