{
  "type": "Feature",
  "properties": {
    "gn:admin1_code":"26",
    "gn:asciiname":"El Infiernito",
    "gn:country_code":"VE",
    "gn:dem":1638,
    "gn:feature_class":"P",
    "gn:feature_code":"PPLL",
    "gn:name":"El Infiernito",
    "gn:population":0,
    "gn:timezone":"America/Caracas",
    "iso:country":"VE",
    "wof:name":"El Infiernito",
    "wof:placetype":"locality"
},
  "geometry": {"coordinates":[-66.91667,10.56222],"type":"Point"}
}