{
  "type": "Feature",
  "properties": {
    "gn:admin1_code":"14",
    "gn:asciiname":"Chachopo",
    "gn:country_code":"VE",
    "gn:dem":2625,
    "gn:feature_class":"P",
    "gn:feature_code":"PPL",
    "gn:name":"Chachopo",
    "gn:population":0,
    "gn:timezone":"America/Caracas",
    "iso:country":"VE",
    "name:und_x_variant":[
        "Chachopa",
        "Chachopo"
    ],
    "wof:name":"Chachopo",
    "wof:placetype":"locality"
},
  "geometry": {"coordinates":[-70.76943,8.93505],"type":"Point"}
}