{
  "type": "Feature",
  "properties": {
    "gn:admin1_code":"04",
    "gn:asciiname":"Santa Apolonia",
    "gn:country_code":"VE",
    "gn:dem":126,
    "gn:feature_class":"P",
    "gn:feature_code":"PPL",
    "gn:name":"Santa Apolonia",
    "gn:population":0,
    "gn:timezone":"America/Caracas",
    "iso:country":"VE",
    "wof:name":"Santa Apolonia",
    "wof:placetype":"locality"
},
  "geometry": {"coordinates":[-67.60149,10.4773],"type":"Point"}
}