{
  "type": "Feature",
  "properties": {
    "iso:country":"VE",
    "name:ceb_x_preferred":[
        "R\u00edo Caribe"
    ],
    "name:eng_x_preferred":[
        "R\u00edo Caribe"
    ],
    "name:fra_x_preferred":[
        "R\u00edo Caribe"
    ],
    "name:jpn_x_preferred":[
        "\u30ea\u30aa\u30fb\u30ab\u30ea\u30d9"
    ],
    "name:nld_x_preferred":[
        "R\u00edo Caribe"
    ],
    "name:pol_x_preferred":[
        "R\u00edo Caribe"
    ],
    "name:por_x_preferred":[
        "R\u00edo Caribe"
    ],
    "name:rus_x_preferred":[
        "\u0420\u0438\u043e-\u041a\u0430\u0440\u0438\u0431\u0435"
    ],
    "name:spa_x_preferred":[
        "R\u00edo Caribe"
    ],
    "name:yrl_x_preferred":[
        "negro simoney"
    ],
    "name:zho_x_preferred":[
        "\u91cc\u5967\u5361\u91cc\u97cb"
    ],
    "qs:gn_pop":0,
    "qs:name":"R\u00edo Caribe",
    "qs:name_adm0":"Venezuela",
    "qs:name_adm1":"Sucre",
    "qs:photos":124,
    "qs:photos_1k":25,
    "qs:photos_9k":1,
    "qs:photos_9r":3,
    "qs:photos_all":124,
    "qs:photos_sr":3,
    "qs:placetype":"Town",
    "qs:pop_sr":"0",
    "qs:woe_adm0":23424982,
    "wd:wordcount":348,
    "wof:name":"R\u00edo Caribe",
    "wof:placetype":"locality"
},
  "geometry": {"coordinates":[-63.113003,10.699445],"type":"Point"}
}