{
  "type": "Feature",
  "properties": {
    "gn:admin1_code":"14",
    "gn:asciiname":"Mucusun",
    "gn:country_code":"VE",
    "gn:dem":2247,
    "gn:feature_class":"P",
    "gn:feature_code":"PPL",
    "gn:name":"Mucus\u00fan",
    "gn:population":0,
    "gn:timezone":"America/Caracas",
    "iso:country":"VE",
    "name:und_x_variant":[
        "Mucusm",
        "Mucus\u00fan"
    ],
    "wof:name":"Mucusun",
    "wof:placetype":"locality"
},
  "geometry": {"coordinates":[-71.31981,8.41164],"type":"Point"}
}