{
  "type": "Feature",
  "properties": {
    "gn:admin1_code":"15",
    "gn:asciiname":"Bejaranito",
    "gn:country_code":"VE",
    "gn:dem":1448,
    "gn:feature_class":"P",
    "gn:feature_code":"PPL",
    "gn:name":"Bejaranito",
    "gn:population":0,
    "gn:timezone":"America/Caracas",
    "iso:country":"VE",
    "wof:name":"Bejaranito",
    "wof:placetype":"locality"
},
  "geometry": {"coordinates":[-66.95,10.38333],"type":"Point"}
}