{
  "type": "Feature",
  "properties": {
    "gn:admin1_code":"3",
    "gn:asciiname":"El Chiguire",
    "gn:cc2":"VE",
    "gn:country_code":"VE",
    "gn:dem":51,
    "gn:feature_class":"P",
    "gn:feature_code":"PPL",
    "gn:name":"El Chig\u00fcire",
    "gn:population":0,
    "gn:timezone":"America/Caracas",
    "iso:country":"VE",
    "name:und_x_variant":[
        "El Chiquire",
        "El Chig\u00fcire"
    ],
    "wof:name":"El Chiguire",
    "wof:placetype":"locality"
},
  "geometry": {"coordinates":[-67.59999999999999,7.71667],"type":"Point"}
}