{
  "type": "Feature",
  "properties": {
    "gn:admin1_code":"15",
    "gn:asciiname":"La Peraza",
    "gn:country_code":"VE",
    "gn:dem":1176,
    "gn:feature_class":"P",
    "gn:feature_code":"PPL",
    "gn:name":"La Peraza",
    "gn:population":0,
    "gn:timezone":"America/Caracas",
    "iso:country":"VE",
    "name:und_x_variant":[
        "Peraza",
        "La Peraza"
    ],
    "wof:name":"La Peraza",
    "wof:placetype":"locality"
},
  "geometry": {"coordinates":[-66.74648000000001,10.44419],"type":"Point"}
}