{
  "type": "Feature",
  "properties": {
    "gn:admin1_code":"5",
    "gn:asciiname":"La Acequia",
    "gn:country_code":"VE",
    "gn:dem":220,
    "gn:feature_class":"P",
    "gn:feature_code":"PPL",
    "gn:name":"La Acequia",
    "gn:population":0,
    "gn:timezone":"America/Caracas",
    "iso:country":"VE",
    "name:deu_x_preferred":[
        "La Acequia"
    ],
    "name:fra_x_preferred":[
        "La Acequia"
    ],
    "name:ita_x_preferred":[
        "La Acequia"
    ],
    "name:por_x_preferred":[
        "La Acequia"
    ],
    "name:spa_x_preferred":[
        "La Acequia"
    ],
    "wof:name":"La Acequia",
    "wof:placetype":"locality"
},
  "geometry": {"coordinates":[-70.67454000000002,8.37965],"type":"Point"}
}