{
  "type": "Feature",
  "properties": {
    "gn:admin1_code":"3",
    "gn:asciiname":"Leche de Miel",
    "gn:country_code":"VE",
    "gn:dem":102,
    "gn:feature_class":"P",
    "gn:feature_code":"PPL",
    "gn:name":"Leche de Miel",
    "gn:population":0,
    "gn:timezone":"America/Caracas",
    "iso:country":"VE",
    "wof:name":"Leche de Miel",
    "wof:placetype":"locality"
},
  "geometry": {"coordinates":[-70.00583,6.99833],"type":"Point"}
}