{
  "type": "Feature",
  "properties": {
    "gn:admin1_code":"2",
    "gn:asciiname":"Higuerote",
    "gn:country_code":"VE",
    "gn:dem":116,
    "gn:feature_class":"P",
    "gn:feature_code":"PPL",
    "gn:name":"Higuerote",
    "gn:population":0,
    "gn:timezone":"America/Caracas",
    "iso:country":"VE",
    "name:ceb_x_preferred":[
        "Higuerote"
    ],
    "name:fra_x_preferred":[
        "Higuerote"
    ],
    "name:ita_x_preferred":[
        "Higuerote"
    ],
    "name:jpn_x_preferred":[
        "\u30a4\u30b2\u30ed\u30fc\u30c6"
    ],
    "name:kor_x_preferred":[
        "\uc774\uac8c\ub85c\ud14c"
    ],
    "name:por_x_preferred":[
        "Higuerote"
    ],
    "name:spa_x_preferred":[
        "Higuerote"
    ],
    "name:zho_x_preferred":[
        "\u4f0a\u683c\u7f85\u7279"
    ],
    "wof:name":"Higuerote",
    "wof:placetype":"locality"
},
  "geometry": {"coordinates":[-64.61064,8.23188],"type":"Point"}
}