{
  "type": "Feature",
  "properties": {
    "gn:admin1_code":"1",
    "gn:asciiname":"Arubap",
    "gn:cc2":"VE",
    "gn:country_code":"VE",
    "gn:dem":98,
    "gn:feature_class":"P",
    "gn:feature_code":"PPL",
    "gn:name":"Arubap",
    "gn:population":0,
    "gn:timezone":"America/Caracas",
    "iso:country":"VE",
    "name:und_x_variant":[
        "Arubapi",
        "Arubap"
    ],
    "wof:name":"Arubap",
    "wof:placetype":"locality"
},
  "geometry": {"coordinates":[-66.6075,1.9225],"type":"Point"}
}