{
  "type": "Feature",
  "properties": {
    "gn:admin1_code":"8",
    "gn:asciiname":"Las Hermanitas",
    "gn:country_code":"VE",
    "gn:dem":94,
    "gn:feature_class":"P",
    "gn:feature_code":"PPL",
    "gn:name":"Las Hermanitas",
    "gn:population":0,
    "gn:timezone":"America/Caracas",
    "iso:country":"VE",
    "wof:name":"Las Hermanitas",
    "wof:placetype":"locality"
},
  "geometry": {"coordinates":[-67.90000000000001,9.28333],"type":"Point"}
}