{
  "type": "Feature",
  "properties": {
    "gn:admin1_code":"21",
    "gn:asciiname":"Piedra Gorda",
    "gn:country_code":"VE",
    "gn:dem":2125,
    "gn:feature_class":"P",
    "gn:feature_code":"PPL",
    "gn:name":"Piedra Gorda",
    "gn:population":0,
    "gn:timezone":"America/Caracas",
    "iso:country":"VE",
    "wof:name":"Piedra Gorda",
    "wof:placetype":"locality"
},
  "geometry": {"coordinates":[-70.2389,9.38626],"type":"Point"}
}