{
  "type": "Feature",
  "properties": {
    "iso:country":"VE",
    "qs:gn_pop":0,
    "qs:name":"Monsenor Jauregui",
    "qs:name_adm0":"Venezuela",
    "qs:name_adm1":"Trujillo",
    "qs:photos":1,
    "qs:photos_1k":1,
    "qs:photos_9k":1,
    "qs:photos_9r":3,
    "qs:photos_all":102,
    "qs:photos_sr":1,
    "qs:placetype":"LocalAdmin",
    "qs:pop_sr":"0",
    "qs:woe_adm0":23424982,
    "wof:name":"Monsenor Jauregui",
    "wof:placetype":"localadmin"
},
  "geometry": {"coordinates":[-70.40296499999999,9.110861],"type":"Point"}
}