{
  "type": "Feature",
  "properties": {
    "gn:admin1_code":"18.0",
    "gn:asciiname":"Fila de Oro",
    "gn:country_code":"VE",
    "gn:dem":892,
    "gn:feature_class":"P",
    "gn:feature_code":"PPL",
    "gn:name":"Fila de Oro",
    "gn:population":0,
    "gn:timezone":"America/Caracas",
    "iso:country":"VE",
    "name:spa_x_preferred":[
        "Fila de Oro"
    ],
    "wof:name":"Fila de Oro",
    "wof:placetype":"locality"
},
  "geometry": {"coordinates":[-69.81,9.26556],"type":"Point"}
}