{
  "type": "Feature",
  "properties": {
    "gn:admin1_code":"15",
    "gn:asciiname":"Sixta",
    "gn:country_code":"VE",
    "gn:dem":175,
    "gn:feature_class":"P",
    "gn:feature_code":"PPL",
    "gn:name":"Sixta",
    "gn:population":0,
    "gn:timezone":"America/Caracas",
    "iso:country":"VE",
    "wof:name":"Sixta",
    "wof:placetype":"locality"
},
  "geometry": {"coordinates":[-65.63590000000001,10.04757],"type":"Point"}
}