{
  "type": "Feature",
  "properties": {
    "gn:admin1_code":"21",
    "gn:asciiname":"Carmona",
    "gn:country_code":"VE",
    "gn:dem":936,
    "gn:feature_class":"P",
    "gn:feature_code":"PPLL",
    "gn:name":"Carmona",
    "gn:population":0,
    "gn:timezone":"America/Caracas",
    "iso:country":"VE",
    "name:ceb_x_preferred":[
        "Carmona"
    ],
    "name:deu_x_preferred":[
        "Carmona"
    ],
    "name:fra_x_preferred":[
        "Carmona"
    ],
    "name:ita_x_preferred":[
        "Carmona"
    ],
    "name:jpn_x_preferred":[
        "\u30ab\u30eb\u30e2\u30ca"
    ],
    "name:nld_x_preferred":[
        "Carmona"
    ],
    "name:pol_x_preferred":[
        "Carmona"
    ],
    "name:por_x_preferred":[
        "Carmona"
    ],
    "name:rus_x_preferred":[
        "\u041a\u0430\u0440\u043c\u043e\u043d\u0430"
    ],
    "name:sco_x_preferred":[
        "Carmona"
    ],
    "name:spa_x_preferred":[
        "Carmona"
    ],
    "name:srp_x_preferred":[
        "\u041a\u0430\u0440\u043c\u043e\u043d\u0430"
    ],
    "name:swe_x_preferred":[
        "Carmona"
    ],
    "name:war_x_preferred":[
        "Carmona"
    ],
    "wof:name":"Carmona",
    "wof:placetype":"locality"
},
  "geometry": {"coordinates":[-70.44815,9.35775],"type":"Point"}
}