{
  "type": "Feature",
  "properties": {
    "gn:admin1_code":"3",
    "gn:asciiname":"Pedraza",
    "gn:country_code":"VE",
    "gn:dem":262,
    "gn:feature_class":"P",
    "gn:feature_code":"PPL",
    "gn:name":"Pedraza",
    "gn:population":0,
    "gn:timezone":"America/Caracas",
    "iso:country":"VE",
    "wof:name":"Pedraza",
    "wof:placetype":"locality"
},
  "geometry": {"coordinates":[-72.00554,7.06848],"type":"Point"}
}