{
  "type": "Feature",
  "properties": {
    "gn:admin1_code":"18.0",
    "gn:asciiname":"El Torito",
    "gn:country_code":"VE",
    "gn:dem":1149,
    "gn:feature_class":"P",
    "gn:feature_code":"PPL",
    "gn:name":"El Torito",
    "gn:population":0,
    "gn:timezone":"America/Caracas",
    "iso:country":"VE",
    "name:dan_x_preferred":[
        "El Torito"
    ],
    "name:pol_x_preferred":[
        "El Torito"
    ],
    "name:por_x_preferred":[
        "El Torito"
    ],
    "name:spa_x_preferred":[
        "El Torito"
    ],
    "wof:name":"El Torito",
    "wof:placetype":"locality"
},
  "geometry": {"coordinates":[-69.76355,9.37095],"type":"Point"}
}