{
  "type": "Feature",
  "properties": {
    "gn:admin1_code":"18.0",
    "gn:asciiname":"Cambi",
    "gn:country_code":"VE",
    "gn:dem":259,
    "gn:feature_class":"P",
    "gn:feature_code":"PPL",
    "gn:name":"Cambi",
    "gn:population":0,
    "gn:timezone":"America/Caracas",
    "iso:country":"VE",
    "wof:name":"Cambi",
    "wof:placetype":"locality"
},
  "geometry": {"coordinates":[-70.03667,8.92056],"type":"Point"}
}