{
  "type": "Feature",
  "properties": {
    "gn:admin1_code":"17",
    "gn:asciiname":"Sulica",
    "gn:country_code":"VE",
    "gn:dem":3,
    "gn:feature_class":"P",
    "gn:feature_code":"PPL",
    "gn:name":"Sulica",
    "gn:population":0,
    "gn:timezone":"America/Caracas",
    "iso:country":"VE",
    "name:und_x_variant":[
        "Zulica",
        "Suplica",
        "Sulica"
    ],
    "wof:name":"Sulica",
    "wof:placetype":"locality"
},
  "geometry": {"coordinates":[-63.88951,10.75605],"type":"Point"}
}