{
  "type": "Feature",
  "properties": {
    "gn:admin1_code":"13",
    "gn:asciiname":"San Juan",
    "gn:country_code":"VE",
    "gn:dem":776,
    "gn:feature_class":"P",
    "gn:feature_code":"PPL",
    "gn:name":"San Juan",
    "gn:population":0,
    "gn:timezone":"America/Caracas",
    "iso:country":"VE",
    "wof:name":"San Juan",
    "wof:placetype":"locality"
},
  "geometry": {"coordinates":[-70.21214000000001,10.43434],"type":"Point"}
}