{
  "type": "Feature",
  "properties": {
    "gn:admin1_code":"19",
    "gn:asciiname":"Buena Esperanza",
    "gn:country_code":"VE",
    "gn:dem":64,
    "gn:feature_class":"P",
    "gn:feature_code":"PPL",
    "gn:name":"Buena Esperanza",
    "gn:population":0,
    "gn:timezone":"America/Caracas",
    "iso:country":"VE",
    "name:ceb_x_preferred":[
        "Buena Esperanza"
    ],
    "name:deu_x_preferred":[
        "Buena Esperanza"
    ],
    "name:fra_x_preferred":[
        "Buena Esperanza"
    ],
    "name:nld_x_preferred":[
        "Buena Esperanza"
    ],
    "name:por_x_preferred":[
        "Buena Esperanza"
    ],
    "name:spa_x_preferred":[
        "Buena Esperanza"
    ],
    "name:swe_x_preferred":[
        "Buena Esperanza"
    ],
    "name:zho_x_preferred":[
        "\u5e03\u57c3\u7d0d\u57c3\u65af\u4f69\u862d\u85a9"
    ],
    "wof:name":"Buena Esperanza",
    "wof:placetype":"locality"
},
  "geometry": {"coordinates":[-63.1626,10.17608],"type":"Point"}
}