{
  "type": "Feature",
  "properties": {
    "gn:admin1_code":"19",
    "gn:asciiname":"Cangua",
    "gn:country_code":"VE",
    "gn:dem":466,
    "gn:feature_class":"P",
    "gn:feature_code":"PPL",
    "gn:name":"Cangua",
    "gn:population":0,
    "gn:timezone":"America/Caracas",
    "iso:country":"VE",
    "wof:name":"Cangua",
    "wof:placetype":"locality"
},
  "geometry": {"coordinates":[-63.28672,10.48637],"type":"Point"}
}