{
  "type": "Feature",
  "properties": {
    "gn:admin1_code":"19.0",
    "gn:asciiname":"Las Misiones",
    "gn:country_code":"VE",
    "gn:dem":426,
    "gn:feature_class":"P",
    "gn:feature_code":"PPLL",
    "gn:name":"Las Misiones",
    "gn:population":0,
    "gn:timezone":"America/Caracas",
    "iso:country":"VE",
    "wof:name":"Las Misiones",
    "wof:placetype":"locality"
},
  "geometry": {"coordinates":[-64.30166,10.19712],"type":"Point"}
}