{
  "type": "Feature",
  "properties": {
    "gn:admin1_code":"12",
    "gn:asciiname":"Coral Viejo",
    "gn:country_code":"VE",
    "gn:dem":49,
    "gn:feature_class":"P",
    "gn:feature_code":"PPL",
    "gn:name":"Coral Viejo",
    "gn:population":0,
    "gn:timezone":"America/Caracas",
    "iso:country":"VE",
    "wof:name":"Coral Viejo",
    "wof:placetype":"locality"
},
  "geometry": {"coordinates":[-67.1341,8.26156],"type":"Point"}
}