{
  "type": "Feature",
  "properties": {
    "gn:admin1_code":"12",
    "gn:asciiname":"La Guasimita",
    "gn:cc2":"VE",
    "gn:country_code":"VE",
    "gn:dem":77,
    "gn:feature_class":"P",
    "gn:feature_code":"PPL",
    "gn:name":"La Guasimita",
    "gn:population":0,
    "gn:timezone":"America/Caracas",
    "iso:country":"VE",
    "name:und_x_variant":[
        "Guasimita",
        "La Guasimata",
        "La Guasimita"
    ],
    "wof:name":"La Guasimita",
    "wof:placetype":"locality"
},
  "geometry": {"coordinates":[-67.78333000000001,8.91667],"type":"Point"}
}