{
  "type": "Feature",
  "properties": {
    "gn:admin1_code":"6",
    "gn:asciiname":"Icabaru",
    "gn:cc2":"VE",
    "gn:country_code":"VE",
    "gn:dem":481,
    "gn:feature_class":"P",
    "gn:feature_code":"PPL",
    "gn:name":"Icabar\u00fa",
    "gn:population":0,
    "gn:timezone":"America/Caracas",
    "iso:country":"VE",
    "name:eng_x_preferred":[
        "Icabar\u00fa"
    ],
    "name:und_x_variant":[
        "Icabaro",
        "Ikabar\u00fa",
        "Icapar\u00fa"
    ],
    "wof:name":"Icabaru",
    "wof:placetype":"locality"
},
  "geometry": {"coordinates":[-61.7358,4.33077],"type":"Point"}
}