{
  "type": "Feature",
  "properties": {
    "gn:admin1_code":"20.0",
    "gn:asciiname":"La Urbina",
    "gn:country_code":"VE",
    "gn:dem":1593,
    "gn:feature_class":"P",
    "gn:feature_code":"PPLL",
    "gn:name":"La Urbina",
    "gn:population":0,
    "gn:timezone":"America/Caracas",
    "iso:country":"VE",
    "wof:name":"La Urbina",
    "wof:placetype":"locality"
},
  "geometry": {"coordinates":[-71.7084,7.91216],"type":"Point"}
}