{
  "type": "Feature",
  "properties": {
    "gn:admin1_code":"6",
    "gn:asciiname":"Parupa",
    "gn:country_code":"VE",
    "gn:dem":1266,
    "gn:feature_class":"P",
    "gn:feature_code":"PPL",
    "gn:name":"Parup\u00e1",
    "gn:population":0,
    "gn:timezone":"America/Caracas",
    "iso:country":"VE",
    "wof:name":"Parupa",
    "wof:placetype":"locality"
},
  "geometry": {"coordinates":[-61.58333,5.68333],"type":"Point"}
}