{
  "type": "Feature",
  "properties": {
    "gn:admin1_code":"23",
    "gn:asciiname":"La Mision",
    "gn:country_code":"VE",
    "gn:dem":9,
    "gn:feature_class":"P",
    "gn:feature_code":"PPL",
    "gn:name":"La Misi\u00f3n",
    "gn:population":0,
    "gn:timezone":"America/Caracas",
    "iso:country":"VE",
    "wof:name":"La Mision",
    "wof:placetype":"locality"
},
  "geometry": {"coordinates":[-71.46389000000001,10.42671],"type":"Point"}
}