{
  "type": "Feature",
  "properties": {
    "gn:admin1_code":"11.0",
    "gn:asciiname":"Cuara",
    "gn:country_code":"VE",
    "gn:dem":4,
    "gn:feature_class":"P",
    "gn:feature_code":"PPLL",
    "gn:name":"Cuara",
    "gn:population":0,
    "gn:timezone":"America/Caracas",
    "iso:country":"VE",
    "name:und_x_variant":[
        "Guada",
        "Guara",
        "Cuara"
    ],
    "wof:name":"Cuara",
    "wof:placetype":"locality"
},
  "geometry": {"coordinates":[-69.92536,11.68295],"type":"Point"}
}