{
  "type": "Feature",
  "properties": {
    "gn:admin1_code":"20",
    "gn:asciiname":"Llano de Jorge",
    "gn:country_code":"VE",
    "gn:dem":543,
    "gn:feature_class":"P",
    "gn:feature_code":"PPL",
    "gn:name":"Llano de Jorge",
    "gn:population":0,
    "gn:timezone":"America/Caracas",
    "iso:country":"VE",
    "wof:name":"Llano de Jorge",
    "wof:placetype":"locality"
},
  "geometry": {"coordinates":[-72.45622,7.78339],"type":"Point"}
}