{
  "type": "Feature",
  "properties": {
    "gn:admin1_code":"12.0",
    "gn:asciiname":"Ramonero",
    "gn:country_code":"VE",
    "gn:dem":72,
    "gn:feature_class":"P",
    "gn:feature_code":"PPL",
    "gn:name":"Ramonero",
    "gn:population":0,
    "gn:timezone":"America/Caracas",
    "iso:country":"VE",
    "wof:name":"Ramonero",
    "wof:placetype":"locality"
},
  "geometry": {"coordinates":[-67.80778000000001,8.83944],"type":"Point"}
}