{
  "type": "Feature",
  "properties": {
    "gn:admin1_code":"11.0",
    "gn:asciiname":"Aviagua",
    "gn:country_code":"VE",
    "gn:dem":111,
    "gn:feature_class":"P",
    "gn:feature_code":"PPLL",
    "gn:name":"Aviagua",
    "gn:population":0,
    "gn:timezone":"America/Caracas",
    "iso:country":"VE",
    "wof:name":"Aviagua",
    "wof:placetype":"locality"
},
  "geometry": {"coordinates":[-70.54243000000002,11.01286],"type":"Point"}
}