{
  "type": "Feature",
  "properties": {
    "gn:admin1_code":"07",
    "gn:asciiname":"Monte Esperanza",
    "gn:country_code":"VE",
    "gn:dem":756,
    "gn:feature_class":"P",
    "gn:feature_code":"PPLL",
    "gn:name":"Monte Esperanza",
    "gn:population":0,
    "gn:timezone":"America/Caracas",
    "iso:country":"VE",
    "wof:name":"Monte Esperanza",
    "wof:placetype":"locality"
},
  "geometry": {"coordinates":[-67.80025999999999,9.97417],"type":"Point"}
}