{
  "type": "Feature",
  "properties": {
    "gn:admin1_code":"12.0",
    "gn:asciiname":"Los Caricares",
    "gn:country_code":"VE",
    "gn:dem":36,
    "gn:feature_class":"P",
    "gn:feature_code":"PPLL",
    "gn:name":"Los Caricares",
    "gn:population":0,
    "gn:timezone":"America/Caracas",
    "iso:country":"VE",
    "wof:name":"Los Caricares",
    "wof:placetype":"locality"
},
  "geometry": {"coordinates":[-66.57579,7.84969],"type":"Point"}
}