{
  "type": "Feature",
  "properties": {
    "iso:country":"VE",
    "name:cym_x_preferred":[
        "Santa Rita"
    ],
    "name:eng_x_preferred":[
        "Santa Rita"
    ],
    "name:epo_x_preferred":[
        "Santa Rita"
    ],
    "name:pol_x_preferred":[
        "Santa Rita"
    ],
    "name:por_x_preferred":[
        "Santa Rita"
    ],
    "name:spa_x_preferred":[
        "Santa Rita"
    ],
    "name:swe_x_preferred":[
        "Lagunillas"
    ],
    "name:zho_x_preferred":[
        "\u8056\u91cc\u5854"
    ],
    "ne:ADM0CAP":0.0,
    "ne:ADM0NAME":"Venezuela",
    "ne:ADM0_A3":"VEN",
    "ne:ADM1NAME":"Trujillo",
    "ne:ADMIN1_COD":23,
    "ne:CAPALT":0,
    "ne:CHANGED":4,
    "ne:CHECKME":0,
    "ne:COMPARE":0,
    "ne:DIFFASCII":0,
    "ne:DIFFNOTE":"Location adjusted.",
    "ne:ELEVATION":0.0,
    "ne:FEATURECLA":"Populated place",
    "ne:FEATURE_CL":"P",
    "ne:FEATURE_CO":"PPL",
    "ne:GEONAMEID":3627186,
    "ne:GEONAMESNO":"Geonames ascii name + lat.d + long.d matching.",
    "ne:GN_ASCII":"Santa Rita",
    "ne:GN_POP":31810,
    "ne:GTOPO30":1.0,
    "ne:ISO_A2":"VE",
    "ne:LABELRANK":6,
    "ne:LATITUDE":10.531827,
    "ne:LONGITUDE":-71.503949,
    "ne:LS_MATCH":1,
    "ne:LS_NAME":"Santa Rita",
    "ne:MAX_AREAKM":3.0,
    "ne:MAX_AREAMI":1.0,
    "ne:MAX_BBXMAX":-71.508333,
    "ne:MAX_BBXMIN":-71.525,
    "ne:MAX_BBYMAX":10.541667,
    "ne:MAX_BBYMIN":10.525,
    "ne:MAX_NATSCA":20.0,
    "ne:MAX_PERKM":7.0,
    "ne:MAX_PERMI":5.0,
    "ne:MAX_POP10":10380,
    "ne:MAX_POP20":10380,
    "ne:MAX_POP300":0,
    "ne:MAX_POP310":0,
    "ne:MAX_POP50":0,
    "ne:MEAN_BBXC":-71.516667,
    "ne:MEAN_BBYC":10.533333,
    "ne:MEGACITY":0,
    "ne:MIN_AREAKM":3.0,
    "ne:MIN_AREAMI":1.0,
    "ne:MIN_BBXMAX":-71.508333,
    "ne:MIN_BBXMIN":-71.525,
    "ne:MIN_BBYMAX":10.541667,
    "ne:MIN_BBYMIN":10.525,
    "ne:MIN_PERKM":7.0,
    "ne:MIN_PERMI":5.0,
    "ne:NAME":"Santa Rita",
    "ne:NAMEASCII":"Santa Rita",
    "ne:NAMEDIFF":0,
    "ne:NATSCALE":20,
    "ne:POP1950":0,
    "ne:POP1955":0,
    "ne:POP1960":0,
    "ne:POP1965":0,
    "ne:POP1970":0,
    "ne:POP1975":0,
    "ne:POP1980":0,
    "ne:POP1985":0,
    "ne:POP1990":0,
    "ne:POP1995":0,
    "ne:POP2000":0,
    "ne:POP2005":0,
    "ne:POP2010":0,
    "ne:POP2015":0,
    "ne:POP2020":0,
    "ne:POP2025":0,
    "ne:POP2050":0,
    "ne:POP_MAX":31810,
    "ne:POP_MIN":10380,
    "ne:POP_OTHER":293777,
    "ne:RANK_MAX":7,
    "ne:RANK_MIN":6,
    "ne:SCALERANK":7,
    "ne:SOV0NAME":"Venezuela",
    "ne:SOV_A3":"VEN",
    "ne:TIMEZONE":"America/Caracas",
    "ne:UN_FID":0,
    "ne:UN_LAT":0.0,
    "ne:UN_LONG":0.0,
    "ne:WORLDCITY":0,
    "qs:gn_country":"VE",
    "qs:gn_fcode":"PPLA2",
    "qs:gn_pop":31810,
    "qs:name":"Santa Rita",
    "qs:name_adm0":"Venezuela",
    "qs:name_adm1":"Zulia",
    "qs:photos":0,
    "qs:photos_1k":0,
    "qs:photos_9k":1,
    "qs:photos_9r":2,
    "qs:photos_all":36,
    "qs:photos_sr":0,
    "qs:placetype":"Town",
    "qs:pop_sr":"7",
    "qs:woe_adm0":23424982,
    "wof:name":"Santa Rita",
    "wof:placetype":"locality",
    "wof:population":31810
},
  "geometry": {"coordinates":[-71.51103999999999,10.53642],"type":"Point"}
}