{
  "type": "Feature",
  "properties": {
    "gn:admin1_code":"11.0",
    "gn:asciiname":"El Bucaral",
    "gn:country_code":"VE",
    "gn:dem":783,
    "gn:feature_class":"P",
    "gn:feature_code":"PPL",
    "gn:name":"El Bucaral",
    "gn:population":0,
    "gn:timezone":"America/Caracas",
    "iso:country":"VE",
    "wof:name":"El Bucaral",
    "wof:placetype":"locality"
},
  "geometry": {"coordinates":[-69.62385999999999,11.15205],"type":"Point"}
}