{
  "type": "Feature",
  "properties": {
    "gn:admin1_code":"16",
    "gn:asciiname":"Azagua",
    "gn:country_code":"VE",
    "gn:dem":30,
    "gn:feature_class":"P",
    "gn:feature_code":"PPL",
    "gn:name":"Azagua",
    "gn:population":0,
    "gn:timezone":"America/Caracas",
    "iso:country":"VE",
    "wof:name":"Azagua",
    "wof:placetype":"locality"
},
  "geometry": {"coordinates":[-63.1029,10.03744],"type":"Point"}
}