{
  "type": "Feature",
  "properties": {
    "gn:admin1_code":"4.0",
    "gn:asciiname":"El Rebollero",
    "gn:country_code":"VE",
    "gn:dem":169,
    "gn:feature_class":"P",
    "gn:feature_code":"PPL",
    "gn:name":"El Rebollero",
    "gn:population":0,
    "gn:timezone":"America/Caracas",
    "iso:country":"VE",
    "wof:name":"El Rebollero",
    "wof:placetype":"locality"
},
  "geometry": {"coordinates":[-66.71359,9.37203],"type":"Point"}
}