{
  "type": "Feature",
  "properties": {
    "gn:admin1_code":"13",
    "gn:asciiname":"Sogore",
    "gn:country_code":"VE",
    "gn:dem":485,
    "gn:feature_class":"P",
    "gn:feature_code":"PPL",
    "gn:name":"Sogore",
    "gn:population":0,
    "gn:timezone":"America/Caracas",
    "iso:country":"VE",
    "wof:name":"Sogore",
    "wof:placetype":"locality"
},
  "geometry": {"coordinates":[-69.90805,10.11046],"type":"Point"}
}