{
  "type": "Feature",
  "properties": {
    "gn:admin1_code":"19",
    "gn:asciiname":"Los Carrizales",
    "gn:country_code":"VE",
    "gn:dem":311,
    "gn:feature_class":"P",
    "gn:feature_code":"PPL",
    "gn:name":"Los Carrizales",
    "gn:population":0,
    "gn:timezone":"America/Caracas",
    "iso:country":"VE",
    "wof:name":"Los Carrizales",
    "wof:placetype":"locality"
},
  "geometry": {"coordinates":[-63.62006,10.36026],"type":"Point"}
}