{
  "type": "Feature",
  "properties": {
    "gn:admin1_code":"20",
    "gn:asciiname":"Potosi",
    "gn:country_code":"VE",
    "gn:dem":1098,
    "gn:feature_class":"P",
    "gn:feature_code":"PPL",
    "gn:name":"Potos\u00ed",
    "gn:population":0,
    "gn:timezone":"America/Caracas",
    "iso:country":"VE",
    "name:pol_x_preferred":[
        "Potos\u00ed"
    ],
    "name:spa_x_preferred":[
        "Potos\u00ed"
    ],
    "name:und_x_variant":[
        "El Potos\u00ed",
        "El Plan de Potosi"
    ],
    "wof:name":"Potosi",
    "wof:placetype":"locality"
},
  "geometry": {"coordinates":[-71.65394000000001,7.95106],"type":"Point"}
}