{
  "type": "Feature",
  "properties": {
    "gn:admin1_code":"6.0",
    "gn:asciiname":"El Alambre",
    "gn:country_code":"VE",
    "gn:dem":313,
    "gn:feature_class":"P",
    "gn:feature_code":"PPL",
    "gn:name":"El Alambre",
    "gn:population":0,
    "gn:timezone":"America/Caracas",
    "iso:country":"VE",
    "wof:name":"El Alambre",
    "wof:placetype":"locality"
},
  "geometry": {"coordinates":[-61.885,7.98833],"type":"Point"}
}