{
  "type": "Feature",
  "properties": {
    "gn:admin1_code":"5",
    "gn:asciiname":"Mata de Leon",
    "gn:country_code":"VE",
    "gn:dem":124,
    "gn:feature_class":"P",
    "gn:feature_code":"PPL",
    "gn:name":"Mata de Le\u00f3n",
    "gn:population":0,
    "gn:timezone":"America/Caracas",
    "iso:country":"VE",
    "wof:name":"Mata de Leon",
    "wof:placetype":"locality"
},
  "geometry": {"coordinates":[-70.36419000000001,8.06139],"type":"Point"}
}