{
  "type": "Feature",
  "properties": {
    "gn:admin1_code":"09",
    "gn:asciiname":"Santa Catalina",
    "gn:country_code":"VE",
    "gn:dem":5,
    "gn:feature_class":"P",
    "gn:feature_code":"PPL",
    "gn:name":"Santa Catalina",
    "gn:population":0,
    "gn:timezone":"America/Caracas",
    "iso:country":"VE",
    "wof:name":"Santa Catalina",
    "wof:placetype":"locality"
},
  "geometry": {"coordinates":[-61.82471999999999,8.56278],"type":"Point"}
}