{
  "type": "Feature",
  "properties": {
    "gn:admin1_code":"19.0",
    "gn:asciiname":"El Coco",
    "gn:country_code":"VE",
    "gn:dem":8,
    "gn:feature_class":"P",
    "gn:feature_code":"PPL",
    "gn:name":"El Coco",
    "gn:population":0,
    "gn:timezone":"America/Caracas",
    "iso:country":"VE",
    "wof:name":"El Coco",
    "wof:placetype":"locality"
},
  "geometry": {"coordinates":[-63.11916,10.53217],"type":"Point"}
}