{
  "type": "Feature",
  "properties": {
    "gn:admin1_code":"13",
    "gn:asciiname":"La Yagua",
    "gn:country_code":"VE",
    "gn:dem":582,
    "gn:feature_class":"P",
    "gn:feature_code":"PPL",
    "gn:name":"La Yagua",
    "gn:population":0,
    "gn:timezone":"America/Caracas",
    "iso:country":"VE",
    "wof:name":"La Yagua",
    "wof:placetype":"locality"
},
  "geometry": {"coordinates":[-70.52060999999998,10.0688],"type":"Point"}
}