{
  "type": "Feature",
  "properties": {
    "gn:admin1_code":"3",
    "gn:asciiname":"El Perro",
    "gn:country_code":"VE",
    "gn:dem":37,
    "gn:feature_class":"P",
    "gn:feature_code":"PPL",
    "gn:name":"El Perro",
    "gn:population":0,
    "gn:timezone":"America/Caracas",
    "iso:country":"VE",
    "wof:name":"El Perro",
    "wof:placetype":"locality"
},
  "geometry": {"coordinates":[-66.46422,7.66122],"type":"Point"}
}