{
  "type": "Feature",
  "properties": {
    "gn:admin1_code":"15.0",
    "gn:asciiname":"Quebrada de Guayas",
    "gn:country_code":"VE",
    "gn:dem":729,
    "gn:feature_class":"P",
    "gn:feature_code":"PPL",
    "gn:name":"Quebrada de Guayas",
    "gn:population":0,
    "gn:timezone":"America/Caracas",
    "iso:country":"VE",
    "wof:name":"Quebrada de Guayas",
    "wof:placetype":"locality"
},
  "geometry": {"coordinates":[-67.09444000000001,10.28278],"type":"Point"}
}