{
  "type": "Feature",
  "properties": {
    "gn:admin1_code":"19.0",
    "gn:asciiname":"El Corozo",
    "gn:country_code":"VE",
    "gn:dem":382,
    "gn:feature_class":"P",
    "gn:feature_code":"PPLL",
    "gn:name":"El Corozo",
    "gn:population":0,
    "gn:timezone":"America/Caracas",
    "iso:country":"VE",
    "wof:name":"El Corozo",
    "wof:placetype":"locality"
},
  "geometry": {"coordinates":[-63.6185,10.29948],"type":"Point"}
}