{
  "type": "Feature",
  "properties": {
    "gn:admin1_code":"3",
    "gn:asciiname":"Cano del Medio",
    "gn:country_code":"VE",
    "gn:dem":70,
    "gn:feature_class":"P",
    "gn:feature_code":"PPL",
    "gn:name":"Ca\u00f1o del Medio",
    "gn:population":0,
    "gn:timezone":"America/Caracas",
    "iso:country":"VE",
    "wof:name":"Cano del Medio",
    "wof:placetype":"locality"
},
  "geometry": {"coordinates":[-68.73333000000001,7.86667],"type":"Point"}
}