{
  "type": "Feature",
  "properties": {
    "gn:admin1_code":"14.0",
    "gn:asciiname":"El Brillante",
    "gn:country_code":"VE",
    "gn:dem":104,
    "gn:feature_class":"P",
    "gn:feature_code":"PPL",
    "gn:name":"El Brillante",
    "gn:population":0,
    "gn:timezone":"America/Caracas",
    "iso:country":"VE",
    "wof:name":"El Brillante",
    "wof:placetype":"locality"
},
  "geometry": {"coordinates":[-71.01770999999999,9.1761],"type":"Point"}
}