{
  "type": "Feature",
  "properties": {
    "iso:country":"VE",
    "qs:gn_pop":0,
    "qs:name":"Urbana Tocuyito",
    "qs:name_adm0":"Venezuela",
    "qs:name_adm1":"Carabobo",
    "qs:photos":1,
    "qs:photos_1k":1,
    "qs:photos_9k":1,
    "qs:photos_9r":3,
    "qs:photos_all":112,
    "qs:photos_sr":1,
    "qs:placetype":"LocalAdmin",
    "qs:pop_sr":"0",
    "qs:woe_adm0":23424982,
    "wof:name":"Urbana Tocuyito",
    "wof:placetype":"localadmin"
},
  "geometry": {"coordinates":[-68.09010000000001,10.086417],"type":"Point"}
}