{
  "type": "Feature",
  "properties": {
    "gn:admin1_code":"13",
    "gn:asciiname":"Los Aymanes de San Miguel",
    "gn:cc2":"VE",
    "gn:country_code":"VE",
    "gn:dem":576,
    "gn:feature_class":"P",
    "gn:feature_code":"PPL",
    "gn:name":"Los Aymanes de San Miguel",
    "gn:population":0,
    "gn:timezone":"America/Caracas",
    "iso:country":"VE",
    "name:und_x_variant":[
        "San Miguel de Los Ayamanes",
        "Los Aymanes de San Miguel"
    ],
    "wof:name":"Los Aymanes de San Miguel",
    "wof:placetype":"locality"
},
  "geometry": {"coordinates":[-69.51222,10.55],"type":"Point"}
}