{
  "type": "Feature",
  "properties": {
    "gn:admin1_code":"14.0",
    "gn:asciiname":"Cordoba",
    "gn:country_code":"VE",
    "gn:dem":1418,
    "gn:feature_class":"P",
    "gn:feature_code":"PPLL",
    "gn:name":"Cordoba",
    "gn:population":0,
    "gn:timezone":"America/Caracas",
    "iso:country":"VE",
    "wof:name":"Cordoba",
    "wof:placetype":"locality"
},
  "geometry": {"coordinates":[-71.68963000000002,8.04607],"type":"Point"}
}