{
  "type": "Feature",
  "properties": {
    "gn:admin1_code":"15.0",
    "gn:asciiname":"Las Gonzalez",
    "gn:country_code":"VE",
    "gn:dem":38,
    "gn:feature_class":"P",
    "gn:feature_code":"PPL",
    "gn:name":"Las Gonzalez",
    "gn:population":0,
    "gn:timezone":"America/Caracas",
    "iso:country":"VE",
    "wof:name":"Las Gonzalez",
    "wof:placetype":"locality"
},
  "geometry": {"coordinates":[-66.18524000000001,10.4038],"type":"Point"}
}