{
  "type": "Feature",
  "properties": {
    "gn:admin1_code":"11",
    "gn:asciiname":"Campo Alegre",
    "gn:country_code":"VE",
    "gn:dem":141,
    "gn:feature_class":"P",
    "gn:feature_code":"PPL",
    "gn:name":"Campo Alegre",
    "gn:population":0,
    "gn:timezone":"America/Caracas",
    "iso:country":"VE",
    "wof:name":"Campo Alegre",
    "wof:placetype":"locality"
},
  "geometry": {"coordinates":[-68.73090999999999,11.12633],"type":"Point"}
}