{
  "type": "Feature",
  "properties": {
    "gn:admin1_code":"23",
    "gn:asciiname":"Kilometro Veintidos",
    "gn:country_code":"VE",
    "gn:dem":39,
    "gn:feature_class":"P",
    "gn:feature_code":"PPL",
    "gn:name":"Kil\u00f3metro Veintidos",
    "gn:population":0,
    "gn:timezone":"America/Caracas",
    "iso:country":"VE",
    "name:und_x_variant":[
        "Kil\u00f3metro 22",
        "Kilometro 22",
        "Kil\u00f3metro Veintidos"
    ],
    "wof:name":"Kilometro Veintidos",
    "wof:placetype":"locality"
},
  "geometry": {"coordinates":[-71.29507,10.45139],"type":"Point"}
}