{
  "type": "Feature",
  "properties": {
    "gn:admin1_code":"2",
    "gn:asciiname":"La Peluda",
    "gn:country_code":"VE",
    "gn:dem":2019,
    "gn:feature_class":"P",
    "gn:feature_code":"PPL",
    "gn:name":"La Peluda",
    "gn:population":0,
    "gn:timezone":"America/Caracas",
    "iso:country":"VE",
    "wof:name":"La Peluda",
    "wof:placetype":"locality"
},
  "geometry": {"coordinates":[-63.96666999999999,10.06667],"type":"Point"}
}