{
  "type": "Feature",
  "properties": {
    "iso:country":"VE",
    "name:unk_x_variant":[
        "Perai-tepu\u00ed"
    ],
    "qs:gn_country":"VE",
    "qs:gn_fcode":"PPL",
    "qs:gn_pop":0,
    "qs:name":"Parai-tepu\u00ed",
    "qs:name_adm0":"Venezuela",
    "qs:name_adm1":"Bol\u00edvar",
    "qs:photos":6,
    "qs:photos_1k":1,
    "qs:photos_9k":1,
    "qs:photos_9r":1,
    "qs:photos_all":6,
    "qs:photos_sr":1,
    "qs:placetype":"Town",
    "qs:pop_sr":"3",
    "qs:woe_adm0":23424982,
    "wof:name":"Parai-tepu\u00ed",
    "wof:placetype":"locality"
},
  "geometry": {"coordinates":[-60.93333,5.01667],"type":"Point"}
}