{
  "type": "Feature",
  "properties": {
    "gn:admin1_code":"2",
    "gn:asciiname":"Gato Negro",
    "gn:country_code":"VE",
    "gn:dem":93,
    "gn:feature_class":"P",
    "gn:feature_code":"PPL",
    "gn:name":"Gato Negro",
    "gn:population":0,
    "gn:timezone":"America/Caracas",
    "iso:country":"VE",
    "name:ell_x_preferred":[
        "Gato Negro"
    ],
    "name:pol_x_preferred":[
        "Gato Negro"
    ],
    "wof:name":"Gato Negro",
    "wof:placetype":"locality"
},
  "geometry": {"coordinates":[-64.85366999999999,9.42829],"type":"Point"}
}