{
  "type": "Feature",
  "properties": {
    "gn:admin1_code":"12.0",
    "gn:asciiname":"Galeras del Mamon",
    "gn:country_code":"VE",
    "gn:dem":431,
    "gn:feature_class":"P",
    "gn:feature_code":"PPLL",
    "gn:name":"Galeras del Mam\u00f3n",
    "gn:population":0,
    "gn:timezone":"America/Caracas",
    "iso:country":"VE",
    "wof:name":"Galeras del Mamon",
    "wof:placetype":"locality"
},
  "geometry": {"coordinates":[-67.5945,9.81153],"type":"Point"}
}