{
  "type": "Feature",
  "properties": {
    "gn:admin1_code":"2",
    "gn:asciiname":"El Olivo",
    "gn:country_code":"VE",
    "gn:dem":117,
    "gn:feature_class":"P",
    "gn:feature_code":"PPL",
    "gn:name":"El Olivo",
    "gn:population":0,
    "gn:timezone":"America/Caracas",
    "iso:country":"VE",
    "wof:name":"El Olivo",
    "wof:placetype":"locality"
},
  "geometry": {"coordinates":[-64.78333000000001,9.26667],"type":"Point"}
}