{
  "type": "Feature",
  "properties": {
    "gn:admin1_code":"23",
    "gn:asciiname":"Las Yayas",
    "gn:cc2":"VE",
    "gn:country_code":"VE",
    "gn:dem":-9999,
    "gn:feature_class":"P",
    "gn:feature_code":"PPL",
    "gn:name":"Las Yayas",
    "gn:population":0,
    "gn:timezone":"America/Caracas",
    "iso:country":"VE",
    "name:und_x_variant":[
        "El Juval",
        "El Javal",
        "El Jayal",
        "El Jabal",
        "Las Yayas"
    ],
    "wof:name":"Las Yayas",
    "wof:placetype":"locality"
},
  "geometry": {"coordinates":[-72.11667,9.81667],"type":"Point"}
}