{
  "type": "Feature",
  "properties": {
    "iso:country":"VE",
    "name:deu_x_preferred":[
        "Bocon\u00f3"
    ],
    "name:fra_x_preferred":[
        "Bocon\u00f3"
    ],
    "name:ita_x_preferred":[
        "Bocon\u00f3"
    ],
    "name:nld_x_preferred":[
        "Bocon\u00f3"
    ],
    "name:pol_x_preferred":[
        "Bocon\u00f3"
    ],
    "name:por_x_preferred":[
        "Bocon\u00f3"
    ],
    "name:spa_x_preferred":[
        "Bocon\u00f3"
    ],
    "name:zho_x_preferred":[
        "\u535a\u79d1\u8afe"
    ],
    "qs:gn_pop":0,
    "qs:name":"Bocon\u00f3",
    "qs:name_adm0":"Venezuela",
    "qs:name_adm1":"Trujillo",
    "qs:photos":50,
    "qs:photos_1k":10,
    "qs:photos_9k":1,
    "qs:photos_9r":2,
    "qs:photos_all":50,
    "qs:photos_sr":2,
    "qs:placetype":"Town",
    "qs:pop_sr":"0",
    "qs:woe_adm0":23424982,
    "wof:name":"Bocon\u00f3",
    "wof:placetype":"locality"
},
  "geometry": {"coordinates":[-70.27037799999999,9.244647],"type":"Point"}
}