{
  "type": "Feature",
  "properties": {
    "gn:admin1_code":"4.0",
    "gn:asciiname":"Los Rastrojos",
    "gn:country_code":"VE",
    "gn:dem":1142,
    "gn:feature_class":"P",
    "gn:feature_code":"PPL",
    "gn:name":"Los Rastrojos",
    "gn:population":0,
    "gn:timezone":"America/Caracas",
    "iso:country":"VE",
    "name:und_x_variant":[
        "Los Rastrojones",
        "Los Rastrojos"
    ],
    "wof:name":"Los Rastrojos",
    "wof:placetype":"locality"
},
  "geometry": {"coordinates":[-67.56912,10.44855],"type":"Point"}
}