{
  "type": "Feature",
  "properties": {
    "gn:admin1_code":"23",
    "gn:asciiname":"Gavilanes",
    "gn:country_code":"VE",
    "gn:dem":16,
    "gn:feature_class":"P",
    "gn:feature_code":"PPL",
    "gn:name":"Gavilanes",
    "gn:population":0,
    "gn:timezone":"America/Caracas",
    "iso:country":"VE",
    "name:und_x_variant":[
        "Los Gavilanes",
        "Gavilanes"
    ],
    "wof:name":"Gavilanes",
    "wof:placetype":"locality"
},
  "geometry": {"coordinates":[-71.47643000000002,8.89256],"type":"Point"}
}