{
  "type": "Feature",
  "properties": {
    "gn:admin1_code":"18",
    "gn:asciiname":"Playa del Medio",
    "gn:country_code":"VE",
    "gn:dem":119,
    "gn:feature_class":"P",
    "gn:feature_code":"PPL",
    "gn:name":"Playa del Medio",
    "gn:population":0,
    "gn:timezone":"America/Caracas",
    "iso:country":"VE",
    "wof:name":"Playa del Medio",
    "wof:placetype":"locality"
},
  "geometry": {"coordinates":[-69.71755,8.72095],"type":"Point"}
}