{
  "type": "Feature",
  "properties": {
    "gn:admin1_code":"14",
    "gn:asciiname":"San Miguel",
    "gn:country_code":"VE",
    "gn:dem":955,
    "gn:feature_class":"P",
    "gn:feature_code":"PPL",
    "gn:name":"San Miguel",
    "gn:population":0,
    "gn:timezone":"America/Caracas",
    "iso:country":"VE",
    "wof:name":"San Miguel",
    "wof:placetype":"locality"
},
  "geometry": {"coordinates":[-71.77158,8.39699],"type":"Point"}
}