{
  "type": "Feature",
  "properties": {
    "gn:admin1_code":"02",
    "gn:asciiname":"La Cabecera",
    "gn:country_code":"VE",
    "gn:dem":1994,
    "gn:feature_class":"P",
    "gn:feature_code":"PPLL",
    "gn:name":"La Cabecera",
    "gn:population":0,
    "gn:timezone":"America/Caracas",
    "iso:country":"VE",
    "wof:name":"La Cabecera",
    "wof:placetype":"locality"
},
  "geometry": {"coordinates":[-63.96757,10.09612],"type":"Point"}
}