{
  "type": "Feature",
  "properties": {
    "gn:admin1_code":"19.0",
    "gn:asciiname":"Los Cerritos",
    "gn:country_code":"VE",
    "gn:dem":249,
    "gn:feature_class":"P",
    "gn:feature_code":"PPL",
    "gn:name":"Los Cerritos",
    "gn:population":0,
    "gn:timezone":"America/Caracas",
    "iso:country":"VE",
    "wof:name":"Los Cerritos",
    "wof:placetype":"locality"
},
  "geometry": {"coordinates":[-63.34405,10.50596],"type":"Point"}
}