{
  "type": "Feature",
  "properties": {
    "gn:admin1_code":"8",
    "gn:asciiname":"Los Canos",
    "gn:country_code":"VE",
    "gn:dem":74,
    "gn:feature_class":"P",
    "gn:feature_code":"PPL",
    "gn:name":"Los Ca\u00f1os",
    "gn:population":0,
    "gn:timezone":"America/Caracas",
    "iso:country":"VE",
    "wof:name":"Los Canos",
    "wof:placetype":"locality"
},
  "geometry": {"coordinates":[-68.33558000000001,8.90859],"type":"Point"}
}