{
  "type": "Feature",
  "properties": {
    "gn:admin1_code":"8.0",
    "gn:asciiname":"El Topo",
    "gn:country_code":"VE",
    "gn:dem":176,
    "gn:feature_class":"P",
    "gn:feature_code":"PPL",
    "gn:name":"El Topo",
    "gn:population":0,
    "gn:timezone":"America/Caracas",
    "iso:country":"VE",
    "name:ces_x_preferred":[
        "El Topo"
    ],
    "name:deu_x_preferred":[
        "El Topo"
    ],
    "name:epo_x_preferred":[
        "El Topo"
    ],
    "name:fas_x_preferred":[
        "\u0627\u0644 \u062a\u0648\u067e\u0648"
    ],
    "name:fra_x_preferred":[
        "El Topo"
    ],
    "name:hun_x_preferred":[
        "A vakond"
    ],
    "name:hye_x_preferred":[
        "\u053d\u056c\u0578\u0582\u0580\u0564\u0568"
    ],
    "name:ita_x_preferred":[
        "El Topo"
    ],
    "name:jpn_x_preferred":[
        "\u30a8\u30eb\u30fb\u30c8\u30dd"
    ],
    "name:nld_x_preferred":[
        "El Topo"
    ],
    "name:por_x_preferred":[
        "El topo"
    ],
    "wof:name":"El Topo",
    "wof:placetype":"locality"
},
  "geometry": {"coordinates":[-68.41818000000001,9.72923],"type":"Point"}
}