{
  "type": "Feature",
  "properties": {
    "gn:admin1_code":"8.0",
    "gn:asciiname":"El Topo",
    "gn:country_code":"VE",
    "gn:dem":176,
    "gn:feature_class":"P",
    "gn:feature_code":"PPL",
    "gn:name":"El Topo",
    "gn:population":0,
    "gn:timezone":"America/Caracas",
    "iso:country":"VE",
    "wof:name":"El Topo",
    "wof:placetype":"locality"
},
  "geometry": {"coordinates":[-68.41818000000001,9.72923],"type":"Point"}
}