{
  "type": "Feature",
  "properties": {
    "gn:admin1_code":"19.0",
    "gn:asciiname":"Contador",
    "gn:country_code":"VE",
    "gn:dem":392,
    "gn:feature_class":"P",
    "gn:feature_code":"PPL",
    "gn:name":"Contador",
    "gn:population":0,
    "gn:timezone":"America/Caracas",
    "iso:country":"VE",
    "name:deu_x_preferred":[
        "Contador"
    ],
    "name:nds_x_preferred":[
        "Contador"
    ],
    "name:por_x_preferred":[
        "Contador"
    ],
    "name:spa_x_preferred":[
        "Contador"
    ],
    "wof:name":"Contador",
    "wof:placetype":"locality"
},
  "geometry": {"coordinates":[-63.85916,10.28756],"type":"Point"}
}