{
  "type": "Feature",
  "properties": {
    "gn:admin1_code":"19",
    "gn:asciiname":"Rio Macho",
    "gn:country_code":"VE",
    "gn:dem":853,
    "gn:feature_class":"P",
    "gn:feature_code":"PPL",
    "gn:name":"R\u00edo Macho",
    "gn:population":0,
    "gn:timezone":"America/Caracas",
    "iso:country":"VE",
    "name:und_x_variant":[
        "R\u00edo Macha",
        "R\u00edo Macho"
    ],
    "wof:name":"Rio Macho",
    "wof:placetype":"locality"
},
  "geometry": {"coordinates":[-63.62083000000001,10.25468],"type":"Point"}
}