{
  "type": "Feature",
  "properties": {
    "gn:admin1_code":"12.0",
    "gn:asciiname":"Padre Ruiz",
    "gn:country_code":"VE",
    "gn:dem":106,
    "gn:feature_class":"P",
    "gn:feature_code":"PPL",
    "gn:name":"Padre Ruiz",
    "gn:population":0,
    "gn:timezone":"America/Caracas",
    "iso:country":"VE",
    "wof:name":"Padre Ruiz",
    "wof:placetype":"locality"
},
  "geometry": {"coordinates":[-65.02561999999999,9.08191],"type":"Point"}
}