{
  "type": "Feature",
  "properties": {
    "gn:admin1_code":"2",
    "gn:asciiname":"Mara",
    "gn:country_code":"VE",
    "gn:dem":286,
    "gn:feature_class":"P",
    "gn:feature_code":"PPL",
    "gn:name":"Mara",
    "gn:population":0,
    "gn:timezone":"America/Caracas",
    "iso:country":"VE",
    "wof:name":"Mara",
    "wof:placetype":"locality"
},
  "geometry": {"coordinates":[-64.33280000000001,9.49194],"type":"Point"}
}