{
  "type": "Feature",
  "properties": {
    "gn:admin1_code":"2",
    "gn:asciiname":"Mara",
    "gn:country_code":"VE",
    "gn:dem":286,
    "gn:feature_class":"P",
    "gn:feature_code":"PPL",
    "gn:name":"Mara",
    "gn:population":0,
    "gn:timezone":"America/Caracas",
    "iso:country":"VE",
    "name:arg_x_preferred":[
        "Mara"
    ],
    "name:bul_x_preferred":[
        "\u041c\u0430\u0440\u0430"
    ],
    "name:cat_x_preferred":[
        "Mara"
    ],
    "name:ceb_x_preferred":[
        "Mara"
    ],
    "name:ces_x_preferred":[
        "Mara"
    ],
    "name:dan_x_preferred":[
        "Mara"
    ],
    "name:deu_x_preferred":[
        "Mara"
    ],
    "name:epo_x_preferred":[
        "Mara"
    ],
    "name:eus_x_preferred":[
        "Mara"
    ],
    "name:fas_x_preferred":[
        "\u0645\u0627\u0631\u0627"
    ],
    "name:fin_x_preferred":[
        "Mara"
    ],
    "name:fra_x_preferred":[
        "Mara"
    ],
    "name:glg_x_preferred":[
        "Mara"
    ],
    "name:heb_x_preferred":[
        "\u05de\u05e8\u05d4"
    ],
    "name:hun_x_preferred":[
        "Mara"
    ],
    "name:ita_x_preferred":[
        "Mara"
    ],
    "name:jpn_x_preferred":[
        "\u30de\u30fc\u30e9"
    ],
    "name:krc_x_preferred":[
        "\u041c\u0430\u0440\u0430"
    ],
    "name:lav_x_preferred":[
        "Mara"
    ],
    "name:lit_x_preferred":[
        "Mara"
    ],
    "name:msa_x_preferred":[
        "Mara"
    ],
    "name:nld_x_preferred":[
        "Mara"
    ],
    "name:nno_x_preferred":[
        "Mara"
    ],
    "name:nor_x_preferred":[
        "Mara"
    ],
    "name:oci_x_preferred":[
        "Mara"
    ],
    "name:pol_x_preferred":[
        "Mara"
    ],
    "name:por_x_preferred":[
        "Mara"
    ],
    "name:ron_x_preferred":[
        "Mara"
    ],
    "name:rus_x_preferred":[
        "\u041c\u0430\u0440\u0430"
    ],
    "name:slk_x_preferred":[
        "Mara"
    ],
    "name:slv_x_preferred":[
        "Mara"
    ],
    "name:spa_x_preferred":[
        "Mara"
    ],
    "name:srp_x_preferred":[
        "\u041c\u0430\u0440\u0430"
    ],
    "name:swa_x_preferred":[
        "Mara"
    ],
    "name:swe_x_preferred":[
        "Mara"
    ],
    "name:ukr_x_preferred":[
        "\u041c\u0430\u0440\u0430"
    ],
    "name:vie_x_preferred":[
        "Mara"
    ],
    "name:war_x_preferred":[
        "Mara"
    ],
    "wof:name":"Mara",
    "wof:placetype":"locality"
},
  "geometry": {"coordinates":[-64.33280000000001,9.49194],"type":"Point"}
}