{
  "type": "Feature",
  "properties": {
    "gn:admin1_code":"8.0",
    "gn:asciiname":"Los Pocitos",
    "gn:country_code":"VE",
    "gn:dem":199,
    "gn:feature_class":"P",
    "gn:feature_code":"PPL",
    "gn:name":"Los Pocitos",
    "gn:population":0,
    "gn:timezone":"America/Caracas",
    "iso:country":"VE",
    "wof:name":"Los Pocitos",
    "wof:placetype":"locality"
},
  "geometry": {"coordinates":[-68.27138000000001,9.73238],"type":"Point"}
}