{
  "type": "Feature",
  "properties": {
    "gn:admin1_code":"6",
    "gn:asciiname":"Castillejo",
    "gn:country_code":"VE",
    "gn:dem":144,
    "gn:feature_class":"P",
    "gn:feature_code":"PPL",
    "gn:name":"Castillejo",
    "gn:population":0,
    "gn:timezone":"America/Caracas",
    "iso:country":"VE",
    "wof:name":"Castillejo",
    "wof:placetype":"locality"
},
  "geometry": {"coordinates":[-61.21666999999999,6.81667],"type":"Point"}
}