{
  "type": "Feature",
  "properties": {
    "gn:admin1_code":"26",
    "gn:asciiname":"Las Canoas",
    "gn:country_code":"VE",
    "gn:dem":1626,
    "gn:feature_class":"P",
    "gn:feature_code":"PPLL",
    "gn:name":"Las Canoas",
    "gn:population":0,
    "gn:timezone":"America/Caracas",
    "iso:country":"VE",
    "wof:name":"Las Canoas",
    "wof:placetype":"locality"
},
  "geometry": {"coordinates":[-66.93122,10.54807],"type":"Point"}
}