{
  "type": "Feature",
  "properties": {
    "gn:admin1_code":"6.0",
    "gn:asciiname":"Boca de Yumena",
    "gn:country_code":"VE",
    "gn:dem":69,
    "gn:feature_class":"P",
    "gn:feature_code":"PPL",
    "gn:name":"Boca de Yumena",
    "gn:population":0,
    "gn:timezone":"America/Caracas",
    "iso:country":"VE",
    "wof:name":"Boca de Yumena",
    "wof:placetype":"locality"
},
  "geometry": {"coordinates":[-67.06214,6.07338],"type":"Point"}
}