{
  "type": "Feature",
  "properties": {
    "gn:admin1_code":"6.0",
    "gn:asciiname":"Botamano de Abbati",
    "gn:country_code":"VE",
    "gn:dem":153,
    "gn:feature_class":"P",
    "gn:feature_code":"PPL",
    "gn:name":"Botamano de Abbati",
    "gn:population":0,
    "gn:timezone":"America/Caracas",
    "iso:country":"VE",
    "wof:name":"Botamano de Abbati",
    "wof:placetype":"locality"
},
  "geometry": {"coordinates":[-61.25056,7.23222],"type":"Point"}
}