{
  "type": "Feature",
  "properties": {
    "gn:admin1_code":"19",
    "gn:asciiname":"Boca de Loro",
    "gn:country_code":"VE",
    "gn:dem":99,
    "gn:feature_class":"P",
    "gn:feature_code":"PPL",
    "gn:name":"Boca de Loro",
    "gn:population":0,
    "gn:timezone":"America/Caracas",
    "iso:country":"VE",
    "wof:name":"Boca de Loro",
    "wof:placetype":"locality"
},
  "geometry": {"coordinates":[-64.43471,10.36771],"type":"Point"}
}