{
  "type": "Feature",
  "properties": {
    "gn:admin1_code":"19.0",
    "gn:asciiname":"La Montana",
    "gn:country_code":"VE",
    "gn:dem":317,
    "gn:feature_class":"P",
    "gn:feature_code":"PPL",
    "gn:name":"La Monta\u00f1a",
    "gn:population":0,
    "gn:timezone":"America/Caracas",
    "iso:country":"VE",
    "wof:name":"La Montana",
    "wof:placetype":"locality"
},
  "geometry": {"coordinates":[-64.21883000000001,10.36124],"type":"Point"}
}