{
  "type": "Feature",
  "properties": {
    "gn:admin1_code":"14",
    "gn:asciiname":"Mocaz",
    "gn:country_code":"VE",
    "gn:dem":2410,
    "gn:feature_class":"P",
    "gn:feature_code":"PPL",
    "gn:name":"Mocaz",
    "gn:population":0,
    "gn:timezone":"America/Caracas",
    "iso:country":"VE",
    "wof:name":"Mocaz",
    "wof:placetype":"locality"
},
  "geometry": {"coordinates":[-71.14404,8.46167],"type":"Point"}
}