{
  "type": "Feature",
  "properties": {
    "gn:admin1_code":"19",
    "gn:asciiname":"Sabana Larga",
    "gn:country_code":"VE",
    "gn:dem":490,
    "gn:feature_class":"P",
    "gn:feature_code":"PPL",
    "gn:name":"Sabana Larga",
    "gn:population":0,
    "gn:timezone":"America/Caracas",
    "iso:country":"VE",
    "name:ceb_x_preferred":[
        "Sabana Larga"
    ],
    "name:ita_x_preferred":[
        "Sabana Larga"
    ],
    "name:por_x_preferred":[
        "Sabana Larga"
    ],
    "name:spa_x_preferred":[
        "Sabana Larga"
    ],
    "name:swe_x_preferred":[
        "Sabana Larga"
    ],
    "name:urd_x_preferred":[
        "\u0633\u0628\u0627\u0646\u06c1 \u0644\u0627\u0631\u06af\u0627"
    ],
    "name:zho_x_preferred":[
        "\u85a9\u74e6\u7d0d\u62c9\u723e\u52a0"
    ],
    "wof:name":"Sabana Larga",
    "wof:placetype":"locality"
},
  "geometry": {"coordinates":[-63.65932,10.42755],"type":"Point"}
}