{
  "type": "Feature",
  "properties": {
    "gn:admin1_code":"19",
    "gn:asciiname":"Sabana Larga",
    "gn:country_code":"VE",
    "gn:dem":490,
    "gn:feature_class":"P",
    "gn:feature_code":"PPL",
    "gn:name":"Sabana Larga",
    "gn:population":0,
    "gn:timezone":"America/Caracas",
    "iso:country":"VE",
    "wof:name":"Sabana Larga",
    "wof:placetype":"locality"
},
  "geometry": {"coordinates":[-63.65932,10.42755],"type":"Point"}
}