{
  "type": "Feature",
  "properties": {
    "gn:admin1_code":"23",
    "gn:asciiname":"El Guanabano",
    "gn:country_code":"VE",
    "gn:dem":70,
    "gn:feature_class":"P",
    "gn:feature_code":"PPL",
    "gn:name":"El Guan\u00e1bano",
    "gn:population":0,
    "gn:timezone":"America/Caracas",
    "iso:country":"VE",
    "name:und_x_variant":[
        "El Guan\u00e1bano",
        "Guan\u00e1bano"
    ],
    "wof:name":"El Guanabano",
    "wof:placetype":"locality"
},
  "geometry": {"coordinates":[-71.25395999999998,10.50276],"type":"Point"}
}