{
  "type": "Feature",
  "properties": {
    "gn:admin1_code":"12.0",
    "gn:asciiname":"La Yagua",
    "gn:country_code":"VE",
    "gn:dem":51,
    "gn:feature_class":"P",
    "gn:feature_code":"PPL",
    "gn:name":"La Yagua",
    "gn:population":0,
    "gn:timezone":"America/Caracas",
    "iso:country":"VE",
    "wof:name":"La Yagua",
    "wof:placetype":"locality"
},
  "geometry": {"coordinates":[-67.34778,7.95944],"type":"Point"}
}