{
  "type": "Feature",
  "properties": {
    "gn:admin1_code":"12",
    "gn:asciiname":"El Chiguire",
    "gn:country_code":"VE",
    "gn:dem":929,
    "gn:feature_class":"P",
    "gn:feature_code":"PPL",
    "gn:name":"El Chig\u00fcire",
    "gn:population":0,
    "gn:timezone":"America/Caracas",
    "iso:country":"VE",
    "wof:name":"El Chiguire",
    "wof:placetype":"locality"
},
  "geometry": {"coordinates":[-67.60833000000001,9.84944],"type":"Point"}
}