{
  "type": "Feature",
  "properties": {
    "iso:country":"VE",
    "name:eng_x_preferred":[
        "Santa Rosa De Guanare Airport"
    ],
    "name:eng_x_variant":[
        "SVQU"
    ],
    "name:msa_x_preferred":[
        "Lapangan Terbang Santa Rosa De Guanare"
    ],
    "name:ron_x_preferred":[
        "Aeroportul Santa Rosa De Guanare"
    ],
    "oa:elevation_ft":"429",
    "oa:type":"small_airport",
    "woe:hierarchy":{
        "country_id":23424982,
        "county_id":26804747,
        "localadmin_id":26805615,
        "planet_id":1,
        "state_id":2347681
    },
    "wof:name":"Santa Rosa de Guanare Airport",
    "wof:placetype":"campus"
},
  "geometry": {"coordinates":[-69.72222499999999,8.749132],"type":"Point"}
}