{
  "type": "Feature",
  "properties": {
    "gn:admin1_code":"13",
    "gn:asciiname":"La Represa",
    "gn:country_code":"VE",
    "gn:dem":668,
    "gn:feature_class":"P",
    "gn:feature_code":"PPL",
    "gn:name":"La Represa",
    "gn:population":0,
    "gn:timezone":"America/Caracas",
    "iso:country":"VE",
    "name:ita_x_preferred":[
        "La Represa"
    ],
    "name:spa_x_preferred":[
        "La Represa"
    ],
    "name:zho_x_preferred":[
        "\u62c9\u96f7\u666e\u96f7\u85a9"
    ],
    "wof:name":"La Represa",
    "wof:placetype":"locality"
},
  "geometry": {"coordinates":[-69.70093,9.85503],"type":"Point"}
}