{
  "type": "Feature",
  "properties": {
    "gn:admin1_code":"19",
    "gn:asciiname":"Bejuquero",
    "gn:country_code":"VE",
    "gn:dem":314,
    "gn:feature_class":"P",
    "gn:feature_code":"PPL",
    "gn:name":"Bejuquero",
    "gn:population":0,
    "gn:timezone":"America/Caracas",
    "iso:country":"VE",
    "wof:name":"Bejuquero",
    "wof:placetype":"locality"
},
  "geometry": {"coordinates":[-64.15254,10.26494],"type":"Point"}
}