{
  "type": "Feature",
  "properties": {
    "gn:admin1_code":"13",
    "gn:asciiname":"El Bubal",
    "gn:country_code":"VE",
    "gn:dem":650,
    "gn:feature_class":"P",
    "gn:feature_code":"PPLL",
    "gn:name":"El Bubal",
    "gn:population":0,
    "gn:timezone":"America/Caracas",
    "iso:country":"VE",
    "wof:name":"El Bubal",
    "wof:placetype":"locality"
},
  "geometry": {"coordinates":[-69.77231999999999,10.41648],"type":"Point"}
}