{
  "type": "Feature",
  "properties": {
    "gn:admin1_code":"02",
    "gn:asciiname":"Unare",
    "gn:country_code":"VE",
    "gn:dem":3,
    "gn:feature_class":"P",
    "gn:feature_code":"PPL",
    "gn:name":"Unare",
    "gn:population":0,
    "gn:timezone":"America/Caracas",
    "iso:country":"VE",
    "name:und_x_variant":[
        "Puerto Unare",
        "Unare"
    ],
    "wof:name":"Unare",
    "wof:placetype":"locality"
},
  "geometry": {"coordinates":[-65.20522,10.07982],"type":"Point"}
}