{
  "type": "Feature",
  "properties": {
    "gn:admin1_code":"6.0",
    "gn:asciiname":"Tagroima",
    "gn:country_code":"VE",
    "gn:dem":261,
    "gn:feature_class":"P",
    "gn:feature_code":"PPL",
    "gn:name":"Tagroima",
    "gn:population":0,
    "gn:timezone":"America/Caracas",
    "iso:country":"VE",
    "wof:name":"Tagroima",
    "wof:placetype":"locality"
},
  "geometry": {"coordinates":[-62.53333000000001,7.61],"type":"Point"}
}