{
  "type": "Feature",
  "properties": {
    "gn:admin1_code":"18",
    "gn:asciiname":"La Pica",
    "gn:country_code":"VE",
    "gn:dem":836,
    "gn:feature_class":"P",
    "gn:feature_code":"PPL",
    "gn:name":"La Pica",
    "gn:population":0,
    "gn:timezone":"America/Caracas",
    "iso:country":"VE",
    "wof:name":"La Pica",
    "wof:placetype":"locality"
},
  "geometry": {"coordinates":[-69.93833000000001,9.41778],"type":"Point"}
}