{
  "type": "Feature",
  "properties": {
    "gn:admin1_code":"12.0",
    "gn:asciiname":"La Guasima",
    "gn:country_code":"VE",
    "gn:dem":80,
    "gn:feature_class":"P",
    "gn:feature_code":"PPL",
    "gn:name":"La Gu\u00e1sima",
    "gn:population":0,
    "gn:timezone":"America/Caracas",
    "iso:country":"VE",
    "wof:name":"La Guasima",
    "wof:placetype":"locality"
},
  "geometry": {"coordinates":[-67.46583000000001,8.75556],"type":"Point"}
}