{
  "type": "Feature",
  "properties": {
    "gn:admin1_code":"23",
    "gn:asciiname":"El Quijote",
    "gn:country_code":"VE",
    "gn:dem":227,
    "gn:feature_class":"P",
    "gn:feature_code":"PPL",
    "gn:name":"El Quijote",
    "gn:population":0,
    "gn:timezone":"America/Caracas",
    "iso:country":"VE",
    "wof:name":"El Quijote",
    "wof:placetype":"locality"
},
  "geometry": {"coordinates":[-72.51666999999998,8.56667],"type":"Point"}
}