{
  "type": "Feature",
  "properties": {
    "gn:admin1_code":"14.0",
    "gn:asciiname":"Las Veritas",
    "gn:country_code":"VE",
    "gn:dem":14,
    "gn:feature_class":"P",
    "gn:feature_code":"PPL",
    "gn:name":"Las Veritas",
    "gn:population":0,
    "gn:timezone":"America/Caracas",
    "iso:country":"VE",
    "wof:name":"Las Veritas",
    "wof:placetype":"locality"
},
  "geometry": {"coordinates":[-71.04034,9.27901],"type":"Point"}
}