{
  "type": "Feature",
  "properties": {
    "gn:admin1_code":"11",
    "gn:admin2_code":"1108.0",
    "gn:asciiname":"Pedregal",
    "gn:country_code":"VE",
    "gn:dem":178,
    "gn:feature_class":"P",
    "gn:feature_code":"PPLA2",
    "gn:name":"Pedregal",
    "gn:population":0,
    "gn:timezone":"America/Caracas",
    "iso:country":"VE",
    "name:spa_x_preferred":[
        "Pedregal"
    ],
    "wof:name":"Pedregal",
    "wof:placetype":"locality"
},
  "geometry": {"coordinates":[-70.12059000000001,11.02037],"type":"Point"}
}