{
  "type": "Feature",
  "properties": {
    "gn:admin1_code":"15",
    "gn:asciiname":"Gamelotal",
    "gn:country_code":"VE",
    "gn:dem":73,
    "gn:feature_class":"P",
    "gn:feature_code":"PPL",
    "gn:name":"Gamelotal",
    "gn:population":0,
    "gn:timezone":"America/Caracas",
    "iso:country":"VE",
    "name:und_x_variant":[
        "Gamerota",
        "Gamerotal",
        "Gamelotal"
    ],
    "wof:name":"Gamelotal",
    "wof:placetype":"locality"
},
  "geometry": {"coordinates":[-66.21354000000001,10.40315],"type":"Point"}
}