{
  "type": "Feature",
  "properties": {
    "gn:admin1_code":"19",
    "gn:asciiname":"La Cabana",
    "gn:country_code":"VE",
    "gn:dem":158,
    "gn:feature_class":"P",
    "gn:feature_code":"PPL",
    "gn:name":"La Caba\u00f1a",
    "gn:population":0,
    "gn:timezone":"America/Caracas",
    "iso:country":"VE",
    "wof:name":"La Cabana",
    "wof:placetype":"locality"
},
  "geometry": {"coordinates":[-64.18459,10.37838],"type":"Point"}
}