{
  "type": "Feature",
  "properties": {
    "gn:admin1_code":"15",
    "gn:asciiname":"Mendoza",
    "gn:country_code":"VE",
    "gn:dem":211,
    "gn:feature_class":"P",
    "gn:feature_code":"PPL",
    "gn:name":"Mendoza",
    "gn:population":0,
    "gn:timezone":"America/Caracas",
    "iso:country":"VE",
    "name:bre_x_preferred":[
        "Mendoza"
    ],
    "name:cat_x_preferred":[
        "Mendoza"
    ],
    "name:ceb_x_preferred":[
        "Mendoza"
    ],
    "name:ces_x_preferred":[
        "Mendoza"
    ],
    "name:deu_x_preferred":[
        "Mendoza"
    ],
    "name:fra_x_preferred":[
        "Mendoza"
    ],
    "name:glg_x_preferred":[
        "Mendoza"
    ],
    "name:heb_x_preferred":[
        "\u05de\u05e0\u05d3\u05d5\u05e1\u05d4"
    ],
    "name:hin_x_preferred":[
        "\u092e\u0947\u0928\u094d\u0926\u094b\u091c\u093c\u093e"
    ],
    "name:hye_x_preferred":[
        "\u0544\u0565\u0576\u0564\u0578\u057d\u0561"
    ],
    "name:ita_x_preferred":[
        "Mendoza"
    ],
    "name:jpn_x_preferred":[
        "\u30e1\u30f3\u30c9\u30fc\u30b5"
    ],
    "name:kor_x_preferred":[
        "\uba58\ub3c4\uc790"
    ],
    "name:kor_x_variant":[
        "\uba58\ub3c4\uc0ac"
    ],
    "name:lit_x_preferred":[
        "Mendosa"
    ],
    "name:nld_x_preferred":[
        "Mendoza"
    ],
    "name:oci_x_preferred":[
        "Mendoza"
    ],
    "name:pol_x_preferred":[
        "Mendoza"
    ],
    "name:por_x_preferred":[
        "Mendoza"
    ],
    "name:rus_x_preferred":[
        "\u041c\u0435\u043d\u0434\u043e\u0441\u0430"
    ],
    "name:sco_x_preferred":[
        "Mendoza"
    ],
    "name:slk_x_preferred":[
        "Mendoza"
    ],
    "name:slv_x_preferred":[
        "Mendoza"
    ],
    "name:spa_x_preferred":[
        "Mendoza"
    ],
    "name:swe_x_preferred":[
        "Mendoza"
    ],
    "name:ukr_x_preferred":[
        "\u041c\u0435\u043d\u0434\u043e\u0441\u0430"
    ],
    "name:urd_x_preferred":[
        "\u0645\u06cc\u0646\u0688\u0648\u0632\u0627"
    ],
    "name:vie_x_preferred":[
        "S\u00f4ng Mendoza"
    ],
    "name:vie_x_variant":[
        "Mendoza"
    ],
    "wof:name":"Mendoza",
    "wof:placetype":"locality"
},
  "geometry": {"coordinates":[-66.83240000000001,10.12402],"type":"Point"}
}