{
  "type": "Feature",
  "properties": {
    "gn:admin1_code":"9",
    "gn:asciiname":"San Francisco de Guayo",
    "gn:country_code":"VE",
    "gn:dem":8,
    "gn:feature_class":"P",
    "gn:feature_code":"PPL",
    "gn:name":"San Francisco de Guayo",
    "gn:population":0,
    "gn:timezone":"America/Caracas",
    "iso:country":"VE",
    "name:eng_x_preferred":[
        "San Francisco de Guayo"
    ],
    "name:por_x_preferred":[
        "San Francisco de Guayo"
    ],
    "name:spa_x_colloquial":[
        "Misi\u00f3n San Francisco de Guayo"
    ],
    "name:spa_x_preferred":[
        "San Francisco de Guayo"
    ],
    "name:spa_x_variant":[
        "Misi\u00f3n San Francisco de Guayo"
    ],
    "wof:name":"San Francisco de Guayo",
    "wof:placetype":"locality"
},
  "geometry": {"coordinates":[-60.8869,9.02377],"type":"Point"}
}