{
  "type": "Feature",
  "properties": {
    "gn:admin1_code":"6.0",
    "gn:asciiname":"Deriba",
    "gn:country_code":"VE",
    "gn:dem":656,
    "gn:feature_class":"P",
    "gn:feature_code":"PPL",
    "gn:name":"Der\u00edba",
    "gn:population":0,
    "gn:timezone":"America/Caracas",
    "iso:country":"VE",
    "wof:name":"Deriba",
    "wof:placetype":"locality"
},
  "geometry": {"coordinates":[-66.54778,6.11417],"type":"Point"}
}