{
  "type": "Feature",
  "properties": {
    "gn:admin1_code":"19",
    "gn:asciiname":"Cerro de Piedra",
    "gn:country_code":"VE",
    "gn:dem":465,
    "gn:feature_class":"P",
    "gn:feature_code":"PPL",
    "gn:name":"Cerro de Piedra",
    "gn:population":0,
    "gn:timezone":"America/Caracas",
    "iso:country":"VE",
    "wof:name":"Cerro de Piedra",
    "wof:placetype":"locality"
},
  "geometry": {"coordinates":[-63.21666999999999,10.45],"type":"Point"}
}