{
  "type": "Feature",
  "properties": {
    "gn:admin1_code":"6",
    "gn:asciiname":"Maparuta",
    "gn:country_code":"VE",
    "gn:dem":1017,
    "gn:feature_class":"P",
    "gn:feature_code":"PPL",
    "gn:name":"Maparuta",
    "gn:population":0,
    "gn:timezone":"America/Caracas",
    "iso:country":"VE",
    "wof:name":"Maparuta",
    "wof:placetype":"locality"
},
  "geometry": {"coordinates":[-61.78333000000001,5.58333],"type":"Point"}
}