{
  "type": "Feature",
  "properties": {
    "gn:admin1_code":"5",
    "gn:asciiname":"Rafaeleno",
    "gn:cc2":"VE",
    "gn:country_code":"VE",
    "gn:dem":397,
    "gn:feature_class":"P",
    "gn:feature_code":"PPL",
    "gn:name":"Rafaele\u00f1o",
    "gn:population":0,
    "gn:timezone":"America/Caracas",
    "iso:country":"VE",
    "name:und_x_variant":[
        "Ca\u00f1o Rafade\u00f1o",
        "Ca\u00f1o Rafaele\u00f1o",
        "Rafaele\u00f1o"
    ],
    "wof:name":"Rafaeleno",
    "wof:placetype":"locality"
},
  "geometry": {"coordinates":[-71.23333000000002,7.88333],"type":"Point"}
}