{
  "type": "Feature",
  "properties": {
    "gn:admin1_code":"11",
    "gn:asciiname":"El Vesubio",
    "gn:country_code":"VE",
    "gn:dem":632,
    "gn:feature_class":"P",
    "gn:feature_code":"PPL",
    "gn:name":"El Vesubio",
    "gn:population":0,
    "gn:timezone":"America/Caracas",
    "iso:country":"VE",
    "wof:name":"El Vesubio",
    "wof:placetype":"locality"
},
  "geometry": {"coordinates":[-69.22402,10.78596],"type":"Point"}
}