{
  "type": "Feature",
  "properties": {
    "gn:admin1_code":"11.0",
    "gn:asciiname":"Carrizalito",
    "gn:country_code":"VE",
    "gn:dem":1166,
    "gn:feature_class":"P",
    "gn:feature_code":"PPL",
    "gn:name":"Carrizalito",
    "gn:population":0,
    "gn:timezone":"America/Caracas",
    "iso:country":"VE",
    "wof:name":"Carrizalito",
    "wof:placetype":"locality"
},
  "geometry": {"coordinates":[-69.75295,11.13335],"type":"Point"}
}