{
  "type": "Feature",
  "properties": {
    "gn:admin1_code":"3.0",
    "gn:asciiname":"Voca El Cerezo",
    "gn:country_code":"VE",
    "gn:dem":166,
    "gn:feature_class":"P",
    "gn:feature_code":"PPLL",
    "gn:name":"Voca El Cerezo",
    "gn:population":0,
    "gn:timezone":"America/Caracas",
    "iso:country":"VE",
    "wof:name":"Voca El Cerezo",
    "wof:placetype":"locality"
},
  "geometry": {"coordinates":[-71.45358,7.28919],"type":"Point"}
}