{
  "type": "Feature",
  "properties": {
    "gn:admin1_code":"15.0",
    "gn:asciiname":"Loma Larga",
    "gn:country_code":"VE",
    "gn:dem":1048,
    "gn:feature_class":"P",
    "gn:feature_code":"PPLL",
    "gn:name":"Loma Larga",
    "gn:population":0,
    "gn:timezone":"America/Caracas",
    "iso:country":"VE",
    "wof:name":"Loma Larga",
    "wof:placetype":"locality"
},
  "geometry": {"coordinates":[-66.70458000000001,10.4132],"type":"Point"}
}