{
  "type": "Feature",
  "properties": {
    "gn:admin1_code":"16",
    "gn:asciiname":"La Cruz Blanca",
    "gn:country_code":"VE",
    "gn:dem":52,
    "gn:feature_class":"P",
    "gn:feature_code":"PPL",
    "gn:name":"La Cruz Blanca",
    "gn:population":0,
    "gn:timezone":"America/Caracas",
    "iso:country":"VE",
    "name:spa_x_preferred":[
        "Cruz Blanca Neutral"
    ],
    "wof:name":"La Cruz Blanca",
    "wof:placetype":"locality"
},
  "geometry": {"coordinates":[-63.24994,9.96871],"type":"Point"}
}