{
  "type": "Feature",
  "properties": {
    "gn:admin1_code":"26",
    "gn:asciiname":"Los Rios",
    "gn:country_code":"VE",
    "gn:dem":521,
    "gn:feature_class":"P",
    "gn:feature_code":"PPL",
    "gn:name":"Los Rios",
    "gn:population":0,
    "gn:timezone":"America/Caracas",
    "iso:country":"VE",
    "wof:name":"Los Rios",
    "wof:placetype":"locality"
},
  "geometry": {"coordinates":[-67.30722,10.475],"type":"Point"}
}