{
  "type": "Feature",
  "properties": {
    "gn:admin1_code":"3",
    "gn:asciiname":"La Orurita",
    "gn:country_code":"VE",
    "gn:dem":129,
    "gn:feature_class":"P",
    "gn:feature_code":"PPL",
    "gn:name":"La Orurita",
    "gn:population":0,
    "gn:timezone":"America/Caracas",
    "iso:country":"VE",
    "wof:name":"La Orurita",
    "wof:placetype":"locality"
},
  "geometry": {"coordinates":[-70.64485999999999,7.32848],"type":"Point"}
}