{
  "type": "Feature",
  "properties": {
    "gn:admin1_code":"16",
    "gn:asciiname":"El Bagre",
    "gn:country_code":"VE",
    "gn:dem":30,
    "gn:feature_class":"P",
    "gn:feature_code":"PPL",
    "gn:name":"El Bagre",
    "gn:population":0,
    "gn:timezone":"America/Caracas",
    "iso:country":"VE",
    "wof:name":"El Bagre",
    "wof:placetype":"locality"
},
  "geometry": {"coordinates":[-63.09905,9.9218],"type":"Point"}
}