{
  "type": "Feature",
  "properties": {
    "gn:admin1_code":"16",
    "gn:asciiname":"El Bagre",
    "gn:country_code":"VE",
    "gn:dem":30,
    "gn:feature_class":"P",
    "gn:feature_code":"PPL",
    "gn:name":"El Bagre",
    "gn:population":0,
    "gn:timezone":"America/Caracas",
    "iso:country":"VE",
    "name:cat_x_preferred":[
        "El Bagre"
    ],
    "name:ceb_x_preferred":[
        "El Bagre"
    ],
    "name:deu_x_preferred":[
        "El Bagre"
    ],
    "name:fas_x_preferred":[
        "\u0627\u0644 \u0628\u0627\u06af\u0631\u0647"
    ],
    "name:fra_x_preferred":[
        "El Bagre"
    ],
    "name:ile_x_preferred":[
        "El Bagre"
    ],
    "name:ilo_x_preferred":[
        "El Bagre"
    ],
    "name:ita_x_preferred":[
        "El Bagre"
    ],
    "name:kat_x_preferred":[
        "\u10d4\u10da-\u10d1\u10d0\u10d2\u10e0\u10d4"
    ],
    "name:msa_x_preferred":[
        "El Bagre"
    ],
    "name:nld_x_preferred":[
        "El Bagre"
    ],
    "name:por_x_preferred":[
        "El Bagre"
    ],
    "name:ron_x_preferred":[
        "El Bagre"
    ],
    "name:rus_x_preferred":[
        "\u042d\u043b\u044c-\u0411\u0430\u0433\u0440\u0435"
    ],
    "name:spa_x_preferred":[
        "El Bagre"
    ],
    "name:swe_x_preferred":[
        "El Bagre"
    ],
    "name:tgl_x_preferred":[
        "El Bagre"
    ],
    "name:vie_x_preferred":[
        "El Bagre"
    ],
    "name:war_x_preferred":[
        "El Bagre"
    ],
    "name:zho_x_preferred":[
        "\u57c3\u723e\u5df4\u683c\u840a"
    ],
    "wof:name":"El Bagre",
    "wof:placetype":"locality"
},
  "geometry": {"coordinates":[-63.09905,9.9218],"type":"Point"}
}