{
  "type": "Feature",
  "properties": {
    "gn:admin1_code":"6.0",
    "gn:asciiname":"El Machete",
    "gn:country_code":"VE",
    "gn:dem":101,
    "gn:feature_class":"P",
    "gn:feature_code":"PPL",
    "gn:name":"El Machete",
    "gn:population":0,
    "gn:timezone":"America/Caracas",
    "iso:country":"VE",
    "wof:name":"El Machete",
    "wof:placetype":"locality"
},
  "geometry": {"coordinates":[-66.73765999999999,6.54668],"type":"Point"}
}