{
  "type": "Feature",
  "properties": {
    "gn:admin1_code":"12",
    "gn:asciiname":"Cueva de Tigre",
    "gn:country_code":"VE",
    "gn:dem":406,
    "gn:feature_class":"P",
    "gn:feature_code":"PPL",
    "gn:name":"Cueva de Tigre",
    "gn:population":0,
    "gn:timezone":"America/Caracas",
    "iso:country":"VE",
    "wof:name":"Cueva de Tigre",
    "wof:placetype":"locality"
},
  "geometry": {"coordinates":[-67.37165999999999,9.86342],"type":"Point"}
}