{
  "type": "Feature",
  "properties": {
    "gn:admin1_code":"15",
    "gn:asciiname":"Tovarito",
    "gn:country_code":"VE",
    "gn:dem":34,
    "gn:feature_class":"P",
    "gn:feature_code":"PPL",
    "gn:name":"Tovarito",
    "gn:population":0,
    "gn:timezone":"America/Caracas",
    "iso:country":"VE",
    "wof:name":"Tovarito",
    "wof:placetype":"locality"
},
  "geometry": {"coordinates":[-66.30698000000001,10.21722],"type":"Point"}
}