{
  "type": "Feature",
  "properties": {
    "gn:admin1_code":"5",
    "gn:asciiname":"Bocas Las Doradas",
    "gn:cc2":"VE",
    "gn:country_code":"VE",
    "gn:dem":156,
    "gn:feature_class":"P",
    "gn:feature_code":"PPL",
    "gn:name":"Bocas Las Doradas",
    "gn:population":0,
    "gn:timezone":"America/Caracas",
    "iso:country":"VE",
    "name:und_x_variant":[
        "Boca de Doradar",
        "Boca de Doradas",
        "Bocas Las Doradas"
    ],
    "wof:name":"Bocas Las Doradas",
    "wof:placetype":"locality"
},
  "geometry": {"coordinates":[-71.31667,7.48333],"type":"Point"}
}