{
  "type": "Feature",
  "properties": {
    "gn:admin1_code":"11",
    "gn:asciiname":"Machuruca",
    "gn:country_code":"VE",
    "gn:dem":78,
    "gn:feature_class":"P",
    "gn:feature_code":"PPL",
    "gn:name":"Machuruca",
    "gn:population":0,
    "gn:timezone":"America/Caracas",
    "iso:country":"VE",
    "wof:name":"Machuruca",
    "wof:placetype":"locality"
},
  "geometry": {"coordinates":[-69.91053000000001,11.80909],"type":"Point"}
}