{
  "type": "Feature",
  "properties": {
    "gn:admin1_code":"11.0",
    "gn:asciiname":"Virgen del Valle",
    "gn:country_code":"VE",
    "gn:dem":1,
    "gn:feature_class":"P",
    "gn:feature_code":"PPL",
    "gn:name":"Virgen del Valle",
    "gn:population":0,
    "gn:timezone":"America/Caracas",
    "iso:country":"VE",
    "wof:name":"Virgen del Valle",
    "wof:placetype":"locality"
},
  "geometry": {"coordinates":[-68.27944000000001,10.91667],"type":"Point"}
}