{
  "type": "Feature",
  "properties": {
    "gn:admin1_code":"20",
    "gn:asciiname":"El Altico",
    "gn:country_code":"VE",
    "gn:dem":1552,
    "gn:feature_class":"P",
    "gn:feature_code":"PPLL",
    "gn:name":"El Altico",
    "gn:population":0,
    "gn:timezone":"America/Caracas",
    "iso:country":"VE",
    "wof:name":"El Altico",
    "wof:placetype":"locality"
},
  "geometry": {"coordinates":[-71.98648,7.90103],"type":"Point"}
}