{
  "type": "Feature",
  "properties": {
    "gn:admin1_code":"6.0",
    "gn:asciiname":"Las Cocuizas",
    "gn:country_code":"VE",
    "gn:dem":99,
    "gn:feature_class":"P",
    "gn:feature_code":"PPL",
    "gn:name":"Las Cocuizas",
    "gn:population":0,
    "gn:timezone":"America/Caracas",
    "iso:country":"VE",
    "wof:name":"Las Cocuizas",
    "wof:placetype":"locality"
},
  "geometry": {"coordinates":[-63.76935,7.9457],"type":"Point"}
}