{
  "type": "Feature",
  "properties": {
    "gn:admin1_code":"11",
    "gn:asciiname":"Caidie Abajo",
    "gn:country_code":"VE",
    "gn:dem":58,
    "gn:feature_class":"P",
    "gn:feature_code":"PPL",
    "gn:name":"Caidie Abajo",
    "gn:population":0,
    "gn:timezone":"America/Caracas",
    "iso:country":"VE",
    "wof:name":"Caidie Abajo",
    "wof:placetype":"locality"
},
  "geometry": {"coordinates":[-68.79093,11.18247],"type":"Point"}
}