{
  "type": "Feature",
  "properties": {
    "gn:admin1_code":"3.0",
    "gn:asciiname":"Mata Larga",
    "gn:country_code":"VE",
    "gn:dem":54,
    "gn:feature_class":"P",
    "gn:feature_code":"PPLL",
    "gn:name":"Mata Larga",
    "gn:population":0,
    "gn:timezone":"America/Caracas",
    "iso:country":"VE",
    "wof:name":"Mata Larga",
    "wof:placetype":"locality"
},
  "geometry": {"coordinates":[-67.25511999999999,7.03552],"type":"Point"}
}