{
  "type": "Feature",
  "properties": {
    "gn:admin1_code":"6.0",
    "gn:asciiname":"Mapares",
    "gn:country_code":"VE",
    "gn:dem":135,
    "gn:feature_class":"P",
    "gn:feature_code":"PPL",
    "gn:name":"Mapares",
    "gn:population":0,
    "gn:timezone":"America/Caracas",
    "iso:country":"VE",
    "wof:name":"Mapares",
    "wof:placetype":"locality"
},
  "geometry": {"coordinates":[-64.06833,7.63333],"type":"Point"}
}