{
  "type": "Feature",
  "properties": {
    "gn:admin1_code":"20.0",
    "gn:asciiname":"Hernandez",
    "gn:country_code":"VE",
    "gn:dem":902,
    "gn:feature_class":"P",
    "gn:feature_code":"PPL",
    "gn:name":"Hernandez",
    "gn:population":0,
    "gn:timezone":"America/Caracas",
    "iso:country":"VE",
    "wof:name":"Hernandez",
    "wof:placetype":"locality"
},
  "geometry": {"coordinates":[-71.84024000000002,8.3873],"type":"Point"}
}