{
  "type": "Feature",
  "properties": {
    "gn:admin1_code":"21",
    "gn:asciiname":"Marajabu",
    "gn:country_code":"VE",
    "gn:dem":2237,
    "gn:feature_class":"P",
    "gn:feature_code":"PPL",
    "gn:name":"Marajab\u00fa",
    "gn:population":0,
    "gn:timezone":"America/Caracas",
    "iso:country":"VE",
    "wof:name":"Marajabu",
    "wof:placetype":"locality"
},
  "geometry": {"coordinates":[-70.49556,9.22833],"type":"Point"}
}