{
  "type": "Feature",
  "properties": {
    "gn:admin1_code":"20",
    "gn:asciiname":"La Laja",
    "gn:country_code":"VE",
    "gn:dem":1423,
    "gn:feature_class":"P",
    "gn:feature_code":"PPL",
    "gn:name":"La Laja",
    "gn:population":0,
    "gn:timezone":"America/Caracas",
    "iso:country":"VE",
    "name:ita_x_preferred":[
        "La Laja"
    ],
    "name:spa_x_preferred":[
        "La Laja"
    ],
    "name:zho_x_preferred":[
        "\u62c9\u62c9\u54c8"
    ],
    "wof:name":"La Laja",
    "wof:placetype":"locality"
},
  "geometry": {"coordinates":[-72.18139000000002,7.88515],"type":"Point"}
}