{
  "type": "Feature",
  "properties": {
    "gn:admin1_code":"13",
    "gn:asciiname":"Copa de Oro",
    "gn:country_code":"VE",
    "gn:dem":472,
    "gn:feature_class":"P",
    "gn:feature_code":"PPL",
    "gn:name":"Copa de Oro",
    "gn:population":0,
    "gn:timezone":"America/Caracas",
    "iso:country":"VE",
    "name:jpn_x_preferred":[
        "\u30b3\u30d1\u30fb\u30aa\u30fc\u30ed"
    ],
    "name:kor_x_preferred":[
        "\ucf54\ud30c \ub370 \uc624\ub85c"
    ],
    "name:por_x_preferred":[
        "Copa Ouro"
    ],
    "name:rus_x_preferred":[
        "\u0417\u043e\u043b\u043e\u0442\u043e\u0439 \u041a\u0443\u0431\u043e\u043a"
    ],
    "name:ukr_x_preferred":[
        "\u0417\u043e\u043b\u043e\u0442\u0438\u0439 \u041a\u0443\u0431\u043e\u043a"
    ],
    "wof:name":"Copa de Oro",
    "wof:placetype":"locality"
},
  "geometry": {"coordinates":[-69.78192,10.5396],"type":"Point"}
}