{
  "type": "Feature",
  "properties": {
    "gn:admin1_code":"13",
    "gn:asciiname":"Copa de Oro",
    "gn:country_code":"VE",
    "gn:dem":472,
    "gn:feature_class":"P",
    "gn:feature_code":"PPL",
    "gn:name":"Copa de Oro",
    "gn:population":0,
    "gn:timezone":"America/Caracas",
    "iso:country":"VE",
    "wof:name":"Copa de Oro",
    "wof:placetype":"locality"
},
  "geometry": {"coordinates":[-69.78192,10.5396],"type":"Point"}
}