{
  "type": "Feature",
  "properties": {
    "gn:admin1_code":"20.0",
    "gn:asciiname":"El Moral",
    "gn:country_code":"VE",
    "gn:dem":1826,
    "gn:feature_class":"P",
    "gn:feature_code":"PPL",
    "gn:name":"El Moral",
    "gn:population":0,
    "gn:timezone":"America/Caracas",
    "iso:country":"VE",
    "wof:name":"El Moral",
    "wof:placetype":"locality"
},
  "geometry": {"coordinates":[-71.94355,7.82119],"type":"Point"}
}