{
  "type": "Feature",
  "properties": {
    "gn:admin1_code":"15.0",
    "gn:asciiname":"Silma",
    "gn:country_code":"VE",
    "gn:dem":610,
    "gn:feature_class":"P",
    "gn:feature_code":"PPLL",
    "gn:name":"Silma",
    "gn:population":0,
    "gn:timezone":"America/Caracas",
    "iso:country":"VE",
    "wof:name":"Silma",
    "wof:placetype":"locality"
},
  "geometry": {"coordinates":[-66.52500000000001,10.50278],"type":"Point"}
}