{
  "type": "Feature",
  "properties": {
    "gn:admin1_code":"6",
    "gn:asciiname":"Buena Esperanza",
    "gn:country_code":"VE",
    "gn:dem":74,
    "gn:feature_class":"P",
    "gn:feature_code":"PPL",
    "gn:name":"Buena Esperanza",
    "gn:population":0,
    "gn:timezone":"America/Caracas",
    "iso:country":"VE",
    "wof:name":"Buena Esperanza",
    "wof:placetype":"locality"
},
  "geometry": {"coordinates":[-65.58333,7.51667],"type":"Point"}
}