{
  "type": "Feature",
  "properties": {
    "gn:admin1_code":"11",
    "gn:asciiname":"La Montanita",
    "gn:country_code":"VE",
    "gn:dem":44,
    "gn:feature_class":"P",
    "gn:feature_code":"PPL",
    "gn:name":"La Monta\u00f1ita",
    "gn:population":0,
    "gn:timezone":"America/Caracas",
    "iso:country":"VE",
    "wof:name":"La Montanita",
    "wof:placetype":"locality"
},
  "geometry": {"coordinates":[-70.96372,10.9031],"type":"Point"}
}