{
  "type": "Feature",
  "properties": {
    "gn:admin1_code":"9",
    "gn:asciiname":"Dinamita",
    "gn:country_code":"VE",
    "gn:dem":21,
    "gn:feature_class":"P",
    "gn:feature_code":"PPL",
    "gn:name":"Dinamita",
    "gn:population":0,
    "gn:timezone":"America/Caracas",
    "iso:country":"VE",
    "wof:name":"Dinamita",
    "wof:placetype":"locality"
},
  "geometry": {"coordinates":[-62.52306,8.46861],"type":"Point"}
}