{
  "type": "Feature",
  "properties": {
    "gn:admin1_code":"11.0",
    "gn:asciiname":"Barigua Arriba",
    "gn:country_code":"VE",
    "gn:dem":330,
    "gn:feature_class":"P",
    "gn:feature_code":"PPL",
    "gn:name":"Barigua Arriba",
    "gn:population":0,
    "gn:timezone":"America/Caracas",
    "iso:country":"VE",
    "wof:name":"Barigua Arriba",
    "wof:placetype":"locality"
},
  "geometry": {"coordinates":[-69.49755999999999,11.39059],"type":"Point"}
}