{
  "type": "Feature",
  "properties": {
    "gn:admin1_code":"25",
    "gn:asciiname":"Conejo Blanco",
    "gn:country_code":"VE",
    "gn:dem":928,
    "gn:feature_class":"P",
    "gn:feature_code":"PPL",
    "gn:name":"Conejo Blanco",
    "gn:population":0,
    "gn:timezone":"America/Caracas",
    "iso:country":"VE",
    "wof:name":"Conejo Blanco",
    "wof:placetype":"locality"
},
  "geometry": {"coordinates":[-66.9068,10.44614],"type":"Point"}
}