{
  "type": "Feature",
  "properties": {
    "gn:admin1_code":"15",
    "gn:asciiname":"Los Aguacates",
    "gn:country_code":"VE",
    "gn:dem":937,
    "gn:feature_class":"P",
    "gn:feature_code":"PPL",
    "gn:name":"Los Aguacates",
    "gn:population":0,
    "gn:timezone":"America/Caracas",
    "iso:country":"VE",
    "wof:name":"Los Aguacates",
    "wof:placetype":"locality"
},
  "geometry": {"coordinates":[-66.58665999999999,10.40809],"type":"Point"}
}