{
  "type": "Feature",
  "properties": {
    "gn:admin1_code":"15",
    "gn:asciiname":"El Secreto",
    "gn:country_code":"VE",
    "gn:dem":837,
    "gn:feature_class":"P",
    "gn:feature_code":"PPL",
    "gn:name":"El Secreto",
    "gn:population":0,
    "gn:timezone":"America/Caracas",
    "iso:country":"VE",
    "wof:name":"El Secreto",
    "wof:placetype":"locality"
},
  "geometry": {"coordinates":[-66.65000000000001,10.13333],"type":"Point"}
}