{
  "type": "Feature",
  "properties": {
    "gn:admin1_code":"3",
    "gn:asciiname":"El Ripial",
    "gn:country_code":"VE",
    "gn:dem":159,
    "gn:feature_class":"P",
    "gn:feature_code":"PPL",
    "gn:name":"El Ripial",
    "gn:population":0,
    "gn:timezone":"America/Caracas",
    "iso:country":"VE",
    "wof:name":"El Ripial",
    "wof:placetype":"locality"
},
  "geometry": {"coordinates":[-71.41658000000002,7.03746],"type":"Point"}
}