{
  "type": "Feature",
  "properties": {
    "gn:admin1_code":"6.0",
    "gn:asciiname":"El Alcornoque",
    "gn:country_code":"VE",
    "gn:dem":85,
    "gn:feature_class":"P",
    "gn:feature_code":"PPL",
    "gn:name":"El Alcornoque",
    "gn:population":0,
    "gn:timezone":"America/Caracas",
    "iso:country":"VE",
    "wof:name":"El Alcornoque",
    "wof:placetype":"locality"
},
  "geometry": {"coordinates":[-65.13833000000001,7.39],"type":"Point"}
}