{
  "type": "Feature",
  "properties": {
    "iso:country":"VE",
    "name:und_x_variant":[
        "La Lecher\u00eda"
    ],
    "qs:gn_country":"VE",
    "qs:gn_fcode":"PPL",
    "qs:gn_pop":0,
    "qs:name":"El Morro de Barcelona",
    "qs:name_adm0":"Venezuela",
    "qs:name_adm1":"Anzoategui",
    "qs:photos":2,
    "qs:photos_1k":1,
    "qs:photos_9k":1,
    "qs:photos_9r":1,
    "qs:photos_all":2,
    "qs:photos_sr":1,
    "qs:placetype":"Town",
    "qs:pop_sr":"0",
    "qs:woe_adm0":23424982,
    "wof:name":"El Morro de Barcelona",
    "wof:placetype":"locality"
},
  "geometry": {"coordinates":[-64.69284,10.19825],"type":"Point"}
}