{
  "type": "Feature",
  "properties": {
    "gn:admin1_code":"2",
    "gn:asciiname":"El Bayito",
    "gn:country_code":"VE",
    "gn:dem":109,
    "gn:feature_class":"P",
    "gn:feature_code":"PPL",
    "gn:name":"El Bayito",
    "gn:population":0,
    "gn:timezone":"America/Caracas",
    "iso:country":"VE",
    "wof:name":"El Bayito",
    "wof:placetype":"locality"
},
  "geometry": {"coordinates":[-64.77639000000001,9.4575],"type":"Point"}
}