{
  "type": "Feature",
  "properties": {
    "gn:admin1_code":"1",
    "gn:asciiname":"Piedra Merey",
    "gn:cc2":"VE",
    "gn:country_code":"VE",
    "gn:dem":90,
    "gn:feature_class":"P",
    "gn:feature_code":"PPL",
    "gn:name":"Piedra Merey",
    "gn:population":0,
    "gn:timezone":"America/Caracas",
    "iso:country":"VE",
    "name:und_x_variant":[
        "Caser\u00edo Merey",
        "Merey",
        "Piedra Merey"
    ],
    "wof:name":"Piedra Merey",
    "wof:placetype":"locality"
},
  "geometry": {"coordinates":[-67.30778000000001,3.39278],"type":"Point"}
}