{
  "type": "Feature",
  "properties": {
    "gn:admin1_code":"11.0",
    "gn:asciiname":"El Vallito",
    "gn:country_code":"VE",
    "gn:dem":70,
    "gn:feature_class":"P",
    "gn:feature_code":"PPL",
    "gn:name":"El Vallito",
    "gn:population":0,
    "gn:timezone":"America/Caracas",
    "iso:country":"VE",
    "wof:name":"El Vallito",
    "wof:placetype":"locality"
},
  "geometry": {"coordinates":[-70.87229000000001,10.88725],"type":"Point"}
}