{
  "type": "Feature",
  "properties": {
    "gn:admin1_code":"13",
    "gn:asciiname":"Agua Santa",
    "gn:country_code":"VE",
    "gn:dem":708,
    "gn:feature_class":"P",
    "gn:feature_code":"PPL",
    "gn:name":"Agua Santa",
    "gn:population":0,
    "gn:timezone":"America/Caracas",
    "iso:country":"VE",
    "wof:name":"Agua Santa",
    "wof:placetype":"locality"
},
  "geometry": {"coordinates":[-69.28556999999999,10.29227],"type":"Point"}
}