{
  "type": "Feature",
  "properties": {
    "gn:admin1_code":"9",
    "gn:asciiname":"La Margarita",
    "gn:cc2":"VE",
    "gn:country_code":"VE",
    "gn:dem":90,
    "gn:feature_class":"P",
    "gn:feature_code":"PPL",
    "gn:name":"La Margarita",
    "gn:population":0,
    "gn:timezone":"America/Caracas",
    "iso:country":"VE",
    "name:und_x_variant":[
        "Las Margaritas",
        "La Margarita"
    ],
    "wof:name":"La Margarita",
    "wof:placetype":"locality"
},
  "geometry": {"coordinates":[-60.98333,8.08333],"type":"Point"}
}