{
  "type": "Feature",
  "properties": {
    "gn:admin1_code":"8.0",
    "gn:asciiname":"Macuaya",
    "gn:country_code":"VE",
    "gn:dem":430,
    "gn:feature_class":"P",
    "gn:feature_code":"PPL",
    "gn:name":"Macuaya",
    "gn:population":0,
    "gn:timezone":"America/Caracas",
    "iso:country":"VE",
    "wof:name":"Macuaya",
    "wof:placetype":"locality"
},
  "geometry": {"coordinates":[-68.04741,9.82024],"type":"Point"}
}