{
  "type": "Feature",
  "properties": {
    "gn:admin1_code":"02",
    "gn:asciiname":"El Destino",
    "gn:country_code":"VE",
    "gn:dem":1,
    "gn:feature_class":"P",
    "gn:feature_code":"PPLL",
    "gn:name":"El Destino",
    "gn:population":0,
    "gn:timezone":"America/Caracas",
    "iso:country":"VE",
    "name:srp_x_preferred":[
        "\u0415\u043b \u0414\u0435\u0441\u0442\u0438\u043d\u043e"
    ],
    "wof:name":"El Destino",
    "wof:placetype":"locality"
},
  "geometry": {"coordinates":[-65.34090999999999,10.06586],"type":"Point"}
}