{
  "type": "Feature",
  "properties": {
    "gn:admin1_code":"19.0",
    "gn:asciiname":"Los Conoricos",
    "gn:country_code":"VE",
    "gn:dem":692,
    "gn:feature_class":"P",
    "gn:feature_code":"PPL",
    "gn:name":"Los Conoricos",
    "gn:population":0,
    "gn:timezone":"America/Caracas",
    "iso:country":"VE",
    "wof:name":"Los Conoricos",
    "wof:placetype":"locality"
},
  "geometry": {"coordinates":[-64.13521999999999,10.16886],"type":"Point"}
}