{
  "type": "Feature",
  "properties": {
    "gn:admin1_code":"23",
    "gn:asciiname":"El Bejucal",
    "gn:country_code":"VE",
    "gn:dem":55,
    "gn:feature_class":"P",
    "gn:feature_code":"PPL",
    "gn:name":"El Bejucal",
    "gn:population":0,
    "gn:timezone":"America/Caracas",
    "iso:country":"VE",
    "wof:name":"El Bejucal",
    "wof:placetype":"locality"
},
  "geometry": {"coordinates":[-71.26666999999998,10.48333],"type":"Point"}
}