{
  "type": "Feature",
  "properties": {
    "gn:admin1_code":"11.0",
    "gn:asciiname":"San Antonio de Acaboa",
    "gn:country_code":"VE",
    "gn:dem":62,
    "gn:feature_class":"P",
    "gn:feature_code":"PPLL",
    "gn:name":"San Antonio de Acaboa",
    "gn:population":0,
    "gn:timezone":"America/Caracas",
    "iso:country":"VE",
    "wof:name":"San Antonio de Acaboa",
    "wof:placetype":"locality"
},
  "geometry": {"coordinates":[-70.06809,11.99431],"type":"Point"}
}