{
  "type": "Feature",
  "properties": {
    "gn:admin1_code":"02",
    "gn:asciiname":"Chiguarcara",
    "gn:country_code":"VE",
    "gn:dem":78,
    "gn:feature_class":"P",
    "gn:feature_code":"PPL",
    "gn:name":"Chiguarcara",
    "gn:population":0,
    "gn:timezone":"America/Caracas",
    "iso:country":"VE",
    "wof:name":"Chiguarcara",
    "wof:placetype":"locality"
},
  "geometry": {"coordinates":[-65.172,9.32207],"type":"Point"}
}