{
  "type": "Feature",
  "properties": {
    "gn:admin1_code":"12",
    "gn:asciiname":"Lezama",
    "gn:country_code":"VE",
    "gn:dem":270,
    "gn:feature_class":"P",
    "gn:feature_code":"PPL",
    "gn:name":"Lezama",
    "gn:population":0,
    "gn:timezone":"America/Caracas",
    "iso:country":"VE",
    "name:ara_x_preferred":[
        "\u0644\u064a\u0632\u0627\u0645\u0627"
    ],
    "name:arg_x_preferred":[
        "Lezama"
    ],
    "name:bre_x_preferred":[
        "Lezama"
    ],
    "name:cat_x_preferred":[
        "Lezama"
    ],
    "name:eus_x_preferred":[
        "Lezama"
    ],
    "name:fra_x_preferred":[
        "Lezama"
    ],
    "name:glg_x_preferred":[
        "Lezama"
    ],
    "name:hun_x_preferred":[
        "Lezama"
    ],
    "name:ita_x_preferred":[
        "Lezama"
    ],
    "name:lat_x_preferred":[
        "Lezama"
    ],
    "name:msa_x_preferred":[
        "Lezama"
    ],
    "name:nld_x_preferred":[
        "Lezama"
    ],
    "name:oci_x_preferred":[
        "Lezama"
    ],
    "name:pol_x_preferred":[
        "Lezama"
    ],
    "name:por_x_preferred":[
        "Lezama"
    ],
    "name:rus_x_preferred":[
        "\u041b\u0435\u0441\u0430\u043c\u0430"
    ],
    "name:sco_x_preferred":[
        "Lezama"
    ],
    "name:spa_x_preferred":[
        "Lezama"
    ],
    "name:sqi_x_preferred":[
        "Lezama"
    ],
    "name:ukr_x_preferred":[
        "\u041b\u0435\u0441\u0430\u043c\u0430"
    ],
    "name:uzb_x_preferred":[
        "Lezama"
    ],
    "name:war_x_preferred":[
        "Lezama"
    ],
    "name:zho_x_preferred":[
        "\u83b1\u8428\u9a6c"
    ],
    "wof:name":"Lezama",
    "wof:placetype":"locality"
},
  "geometry": {"coordinates":[-66.39556,9.71778],"type":"Point"}
}