{
  "type": "Feature",
  "properties": {
    "gn:admin1_code":"12",
    "gn:asciiname":"Lezama",
    "gn:country_code":"VE",
    "gn:dem":270,
    "gn:feature_class":"P",
    "gn:feature_code":"PPL",
    "gn:name":"Lezama",
    "gn:population":0,
    "gn:timezone":"America/Caracas",
    "iso:country":"VE",
    "wof:name":"Lezama",
    "wof:placetype":"locality"
},
  "geometry": {"coordinates":[-66.39556,9.71778],"type":"Point"}
}