{
  "type": "Feature",
  "properties": {
    "gn:admin1_code":"22",
    "gn:asciiname":"Cobalongo",
    "gn:country_code":"VE",
    "gn:dem":788,
    "gn:feature_class":"P",
    "gn:feature_code":"PPL",
    "gn:name":"Cobalongo",
    "gn:population":0,
    "gn:timezone":"America/Caracas",
    "iso:country":"VE",
    "wof:name":"Cobalongo",
    "wof:placetype":"locality"
},
  "geometry": {"coordinates":[-68.69824,10.0564],"type":"Point"}
}