{
  "type": "Feature",
  "properties": {
    "gn:admin1_code":"7",
    "gn:asciiname":"Avinca",
    "gn:country_code":"VE",
    "gn:dem":437,
    "gn:feature_class":"P",
    "gn:feature_code":"PPL",
    "gn:name":"Avinca",
    "gn:population":0,
    "gn:timezone":"America/Caracas",
    "iso:country":"VE",
    "wof:name":"Avinca",
    "wof:placetype":"locality"
},
  "geometry": {"coordinates":[-67.89765,10.20467],"type":"Point"}
}