{
  "type": "Feature",
  "properties": {
    "gn:admin1_code":"13.0",
    "gn:asciiname":"Palo Negro",
    "gn:country_code":"VE",
    "gn:dem":732,
    "gn:feature_class":"P",
    "gn:feature_code":"PPL",
    "gn:name":"Palo Negro",
    "gn:population":0,
    "gn:timezone":"America/Caracas",
    "iso:country":"VE",
    "wof:name":"Palo Negro",
    "wof:placetype":"locality"
},
  "geometry": {"coordinates":[-70.80389,10.08226],"type":"Point"}
}