{
  "type": "Feature",
  "properties": {
    "gn:admin1_code":"13",
    "gn:asciiname":"El Pauji",
    "gn:country_code":"VE",
    "gn:dem":221,
    "gn:feature_class":"P",
    "gn:feature_code":"PPL",
    "gn:name":"El Pauj\u00ed",
    "gn:population":0,
    "gn:timezone":"America/Caracas",
    "iso:country":"VE",
    "name:und_x_variant":[
        "Pauj\u00ed",
        "El Pauj\u00ed"
    ],
    "wof:name":"El Pauji",
    "wof:placetype":"locality"
},
  "geometry": {"coordinates":[-69.36774,10.55841],"type":"Point"}
}