{
  "type": "Feature",
  "properties": {
    "gn:admin1_code":"20.0",
    "gn:asciiname":"La Isla",
    "gn:country_code":"VE",
    "gn:dem":232,
    "gn:feature_class":"P",
    "gn:feature_code":"PPLL",
    "gn:name":"La Isla",
    "gn:population":0,
    "gn:timezone":"America/Caracas",
    "iso:country":"VE",
    "wof:name":"La Isla",
    "wof:placetype":"locality"
},
  "geometry": {"coordinates":[-71.93221,7.50097],"type":"Point"}
}