{
  "type": "Feature",
  "properties": {
    "gn:admin1_code":"20.0",
    "gn:asciiname":"La Isla",
    "gn:country_code":"VE",
    "gn:dem":232,
    "gn:feature_class":"P",
    "gn:feature_code":"PPLL",
    "gn:name":"La Isla",
    "gn:population":0,
    "gn:timezone":"America/Caracas",
    "iso:country":"VE",
    "name:ceb_x_preferred":[
        "La Isla"
    ],
    "name:spa_x_preferred":[
        "La isla"
    ],
    "name:srp_x_preferred":[
        "\u041b\u0430 \u0418\u0441\u043b\u0430"
    ],
    "name:swe_x_preferred":[
        "La Isla"
    ],
    "wof:name":"La Isla",
    "wof:placetype":"locality"
},
  "geometry": {"coordinates":[-71.93221,7.50097],"type":"Point"}
}