{
  "type": "Feature",
  "properties": {
    "gn:admin1_code":"17",
    "gn:asciiname":"Las Villarroel",
    "gn:country_code":"VE",
    "gn:dem":35,
    "gn:feature_class":"P",
    "gn:feature_code":"PPL",
    "gn:name":"Las Villarroel",
    "gn:population":0,
    "gn:timezone":"America/Caracas",
    "iso:country":"VE",
    "wof:name":"Las Villarroel",
    "wof:placetype":"locality"
},
  "geometry": {"coordinates":[-63.98177,10.98437],"type":"Point"}
}