{
  "type": "Feature",
  "properties": {
    "gn:admin1_code":"11.0",
    "gn:asciiname":"Balsamar",
    "gn:country_code":"VE",
    "gn:dem":55,
    "gn:feature_class":"P",
    "gn:feature_code":"PPLL",
    "gn:name":"Balsamar",
    "gn:population":0,
    "gn:timezone":"America/Caracas",
    "iso:country":"VE",
    "wof:name":"Balsamar",
    "wof:placetype":"locality"
},
  "geometry": {"coordinates":[-68.4708,10.78385],"type":"Point"}
}