{
  "type": "Feature",
  "properties": {
    "gn:admin1_code":"6.0",
    "gn:asciiname":"Chaguaramal",
    "gn:country_code":"VE",
    "gn:dem":324,
    "gn:feature_class":"P",
    "gn:feature_code":"PPL",
    "gn:name":"Chaguaramal",
    "gn:population":0,
    "gn:timezone":"America/Caracas",
    "iso:country":"VE",
    "wof:name":"Chaguaramal",
    "wof:placetype":"locality"
},
  "geometry": {"coordinates":[-61.90389,7.96833],"type":"Point"}
}