{
  "type": "Feature",
  "properties": {
    "gn:admin1_code":"13",
    "gn:asciiname":"Maya",
    "gn:country_code":"VE",
    "gn:dem":242,
    "gn:feature_class":"P",
    "gn:feature_code":"PPL",
    "gn:name":"Maya",
    "gn:population":0,
    "gn:timezone":"America/Caracas",
    "iso:country":"VE",
    "wof:name":"Maya",
    "wof:placetype":"locality"
},
  "geometry": {"coordinates":[-69.57576,10.67001],"type":"Point"}
}