{
  "type": "Feature",
  "properties": {
    "gn:admin1_code":"13.0",
    "gn:asciiname":"La Encrucijada",
    "gn:country_code":"VE",
    "gn:dem":565,
    "gn:feature_class":"P",
    "gn:feature_code":"PPL",
    "gn:name":"La Encrucijada",
    "gn:population":0,
    "gn:timezone":"America/Caracas",
    "iso:country":"VE",
    "wof:name":"La Encrucijada",
    "wof:placetype":"locality"
},
  "geometry": {"coordinates":[-70.51993,10.24827],"type":"Point"}
}