{
  "type": "Feature",
  "properties": {
    "gn:admin1_code":"2",
    "gn:asciiname":"Mamonal",
    "gn:country_code":"VE",
    "gn:dem":195,
    "gn:feature_class":"P",
    "gn:feature_code":"PPL",
    "gn:name":"Mamonal",
    "gn:population":0,
    "gn:timezone":"America/Caracas",
    "iso:country":"VE",
    "wof:name":"Mamonal",
    "wof:placetype":"locality"
},
  "geometry": {"coordinates":[-65.61528,9.8465],"type":"Point"}
}