{
  "type": "Feature",
  "properties": {
    "gn:admin1_code":"4",
    "gn:asciiname":"Las Palmitas",
    "gn:country_code":"VE",
    "gn:dem":50,
    "gn:feature_class":"P",
    "gn:feature_code":"PPL",
    "gn:name":"Las Palmitas",
    "gn:population":0,
    "gn:timezone":"America/Caracas",
    "iso:country":"VE",
    "name:ceb_x_preferred":[
        "Las Palmitas"
    ],
    "name:ita_x_preferred":[
        "Las Palmitas"
    ],
    "name:spa_x_preferred":[
        "Las Palmitas"
    ],
    "name:srp_x_preferred":[
        "\u041b\u0430\u0441 \u041f\u0430\u043b\u043c\u0438\u0442\u0430\u0441"
    ],
    "name:swe_x_preferred":[
        "Las Palmitas"
    ],
    "wof:name":"Las Palmitas",
    "wof:placetype":"locality"
},
  "geometry": {"coordinates":[-67.79000000000001,10.40722],"type":"Point"}
}