{
  "type": "Feature",
  "properties": {
    "gn:admin1_code":"15.0",
    "gn:asciiname":"Los Cerros",
    "gn:country_code":"VE",
    "gn:dem":28,
    "gn:feature_class":"P",
    "gn:feature_code":"PPL",
    "gn:name":"Los Cerros",
    "gn:population":0,
    "gn:timezone":"America/Caracas",
    "iso:country":"VE",
    "wof:name":"Los Cerros",
    "wof:placetype":"locality"
},
  "geometry": {"coordinates":[-65.91023,10.2077],"type":"Point"}
}