{
  "type": "Feature",
  "properties": {
    "gn:admin1_code":"12.0",
    "gn:asciiname":"Los Caros",
    "gn:country_code":"VE",
    "gn:dem":180,
    "gn:feature_class":"P",
    "gn:feature_code":"PPLL",
    "gn:name":"Los Caros",
    "gn:population":0,
    "gn:timezone":"America/Caracas",
    "iso:country":"VE",
    "wof:name":"Los Caros",
    "wof:placetype":"locality"
},
  "geometry": {"coordinates":[-64.91109,8.79917],"type":"Point"}
}