{
  "type": "Feature",
  "properties": {
    "gn:admin1_code":"15.0",
    "gn:asciiname":"Arenaza",
    "gn:country_code":"VE",
    "gn:dem":266,
    "gn:feature_class":"P",
    "gn:feature_code":"PPL",
    "gn:name":"Arenaza",
    "gn:population":0,
    "gn:timezone":"America/Caracas",
    "iso:country":"VE",
    "wof:name":"Arenaza",
    "wof:placetype":"locality"
},
  "geometry": {"coordinates":[-66.64755,10.36853],"type":"Point"}
}