{
  "type": "Feature",
  "properties": {
    "gn:admin1_code":"02",
    "gn:asciiname":"La Guanota",
    "gn:country_code":"VE",
    "gn:dem":852,
    "gn:feature_class":"P",
    "gn:feature_code":"PPLL",
    "gn:name":"La Guanota",
    "gn:population":0,
    "gn:timezone":"America/Caracas",
    "iso:country":"VE",
    "wof:name":"La Guanota",
    "wof:placetype":"locality"
},
  "geometry": {"coordinates":[-64.39246999999999,10.09692],"type":"Point"}
}