{
  "type": "Feature",
  "properties": {
    "gn:admin1_code":"12",
    "gn:asciiname":"El Raton",
    "gn:country_code":"VE",
    "gn:dem":205,
    "gn:feature_class":"P",
    "gn:feature_code":"PPL",
    "gn:name":"El Rat\u00f3n",
    "gn:population":0,
    "gn:timezone":"America/Caracas",
    "iso:country":"VE",
    "wof:name":"El Raton",
    "wof:placetype":"locality"
},
  "geometry": {"coordinates":[-66.95,9.35],"type":"Point"}
}