{
  "type": "Feature",
  "properties": {
    "gn:admin1_code":"13.0",
    "gn:asciiname":"El Combate",
    "gn:country_code":"VE",
    "gn:dem":483,
    "gn:feature_class":"P",
    "gn:feature_code":"PPL",
    "gn:name":"El Combate",
    "gn:population":0,
    "gn:timezone":"America/Caracas",
    "iso:country":"VE",
    "wof:name":"El Combate",
    "wof:placetype":"locality"
},
  "geometry": {"coordinates":[-70.36792,10.2352],"type":"Point"}
}