{
  "type": "Feature",
  "properties": {
    "gn:admin1_code":"6.0",
    "gn:asciiname":"Las Delicias",
    "gn:country_code":"VE",
    "gn:dem":58,
    "gn:feature_class":"P",
    "gn:feature_code":"PPL",
    "gn:name":"Las Delicias",
    "gn:population":0,
    "gn:timezone":"America/Caracas",
    "iso:country":"VE",
    "name:ceb_x_preferred":[
        "Las Delicias"
    ],
    "name:ita_x_preferred":[
        "Las Delicias"
    ],
    "name:swe_x_preferred":[
        "Las Delicias"
    ],
    "wof:name":"Las Delicias",
    "wof:placetype":"locality"
},
  "geometry": {"coordinates":[-67.40563,6.21659],"type":"Point"}
}