{
  "type": "Feature",
  "properties": {
    "gn:admin1_code":"19.0",
    "gn:asciiname":"Catuaro Abajo",
    "gn:country_code":"VE",
    "gn:dem":40,
    "gn:feature_class":"P",
    "gn:feature_code":"PPL",
    "gn:name":"Catuaro Abajo",
    "gn:population":0,
    "gn:timezone":"America/Caracas",
    "iso:country":"VE",
    "wof:name":"Catuaro Abajo",
    "wof:placetype":"locality"
},
  "geometry": {"coordinates":[-63.07978000000001,10.57748],"type":"Point"}
}