{
  "type": "Feature",
  "properties": {
    "gn:admin1_code":"11.0",
    "gn:asciiname":"El Correo",
    "gn:country_code":"VE",
    "gn:dem":23,
    "gn:feature_class":"P",
    "gn:feature_code":"PPLL",
    "gn:name":"El Correo",
    "gn:population":0,
    "gn:timezone":"America/Caracas",
    "iso:country":"VE",
    "name:ast_x_preferred":[
        "El Correo"
    ],
    "name:cat_x_preferred":[
        "El Correo"
    ],
    "name:deu_x_preferred":[
        "El Correo"
    ],
    "name:eus_x_preferred":[
        "El Correo"
    ],
    "name:fra_x_preferred":[
        "El Correo"
    ],
    "name:jpn_x_preferred":[
        "\u30a8\u30eb\u30fb\u30b3\u30ec\u30aa"
    ],
    "name:spa_x_preferred":[
        "El Correo"
    ],
    "wof:name":"El Correo",
    "wof:placetype":"locality"
},
  "geometry": {"coordinates":[-68.65924,11.31905],"type":"Point"}
}