{
  "type": "Feature",
  "properties": {
    "gn:admin1_code":"3",
    "gn:asciiname":"Mata de Novillo",
    "gn:cc2":"VE",
    "gn:country_code":"VE",
    "gn:dem":51,
    "gn:feature_class":"P",
    "gn:feature_code":"PPL",
    "gn:name":"Mata de Novillo",
    "gn:population":0,
    "gn:timezone":"America/Caracas",
    "iso:country":"VE",
    "name:und_x_variant":[
        "Mata del Novillo",
        "Mata de Novillo"
    ],
    "wof:name":"Mata de Novillo",
    "wof:placetype":"locality"
},
  "geometry": {"coordinates":[-67.46666999999999,7.85],"type":"Point"}
}