{
  "type": "Feature",
  "properties": {
    "gn:admin1_code":"17",
    "gn:asciiname":"Espinola",
    "gn:cc2":"VE",
    "gn:country_code":"VE",
    "gn:dem":43,
    "gn:feature_class":"P",
    "gn:feature_code":"PPL",
    "gn:name":"Espinola",
    "gn:population":0,
    "gn:timezone":"America/Caracas",
    "iso:country":"VE",
    "name:und_x_variant":[
        "Espin\u00f3lo",
        "Espinola"
    ],
    "wof:name":"Espinola",
    "wof:placetype":"locality"
},
  "geometry": {"coordinates":[-63.81667,11.01667],"type":"Point"}
}