{
  "type": "Feature",
  "properties": {
    "gn:admin1_code":"8",
    "gn:asciiname":"Sabana Larga",
    "gn:country_code":"VE",
    "gn:dem":135,
    "gn:feature_class":"P",
    "gn:feature_code":"PPL",
    "gn:name":"Sabana Larga",
    "gn:population":0,
    "gn:timezone":"America/Caracas",
    "iso:country":"VE",
    "wof:name":"Sabana Larga",
    "wof:placetype":"locality"
},
  "geometry": {"coordinates":[-68.18333,9.63333],"type":"Point"}
}