{
  "type": "Feature",
  "properties": {
    "gn:admin1_code":"22.0",
    "gn:asciiname":"Baquira",
    "gn:country_code":"VE",
    "gn:dem":394,
    "gn:feature_class":"P",
    "gn:feature_code":"PPL",
    "gn:name":"B\u00e1quira",
    "gn:population":0,
    "gn:timezone":"America/Caracas",
    "iso:country":"VE",
    "wof:name":"Baquira",
    "wof:placetype":"locality"
},
  "geometry": {"coordinates":[-68.73820000000001,10.16088],"type":"Point"}
}