{
  "type": "Feature",
  "properties": {
    "gn:admin1_code":"11",
    "gn:asciiname":"San Nicolas de Quibure",
    "gn:country_code":"VE",
    "gn:dem":45,
    "gn:feature_class":"P",
    "gn:feature_code":"PPL",
    "gn:name":"San Nicol\u00e1s de Quibure",
    "gn:population":0,
    "gn:timezone":"America/Caracas",
    "iso:country":"VE",
    "wof:name":"San Nicolas de Quibure",
    "wof:placetype":"locality"
},
  "geometry": {"coordinates":[-70.60420000000001,11.10857],"type":"Point"}
}