{
  "type": "Feature",
  "properties": {
    "gn:admin1_code":"12",
    "gn:asciiname":"Agua Verde",
    "gn:country_code":"VE",
    "gn:dem":46,
    "gn:feature_class":"P",
    "gn:feature_code":"PPL",
    "gn:name":"Agua Verde",
    "gn:population":0,
    "gn:timezone":"America/Caracas",
    "iso:country":"VE",
    "wof:name":"Agua Verde",
    "wof:placetype":"locality"
},
  "geometry": {"coordinates":[-67.19203,7.90535],"type":"Point"}
}