{
  "type": "Feature",
  "properties": {
    "gn:admin1_code":"5",
    "gn:asciiname":"Matacandela",
    "gn:cc2":"VE",
    "gn:country_code":"VE",
    "gn:dem":57,
    "gn:feature_class":"P",
    "gn:feature_code":"PPL",
    "gn:name":"Matacandela",
    "gn:population":0,
    "gn:timezone":"America/Caracas",
    "iso:country":"VE",
    "name:und_x_variant":[
        "Mata de Candela",
        "Matacandela"
    ],
    "wof:name":"Matacandela",
    "wof:placetype":"locality"
},
  "geometry": {"coordinates":[-68.03333000000001,8.38333],"type":"Point"}
}