{
  "type": "Feature",
  "properties": {
    "gn:admin1_code":"21",
    "gn:asciiname":"La Pedregosa",
    "gn:country_code":"VE",
    "gn:dem":135,
    "gn:feature_class":"P",
    "gn:feature_code":"PPL",
    "gn:name":"La Pedregosa",
    "gn:population":0,
    "gn:timezone":"America/Caracas",
    "iso:country":"VE",
    "wof:name":"La Pedregosa",
    "wof:placetype":"locality"
},
  "geometry": {"coordinates":[-70.70833,9.66867],"type":"Point"}
}