{
  "type": "Feature",
  "properties": {
    "gn:admin1_code":"11",
    "gn:asciiname":"Polanco",
    "gn:country_code":"VE",
    "gn:dem":248,
    "gn:feature_class":"P",
    "gn:feature_code":"PPL",
    "gn:name":"Polanco",
    "gn:population":0,
    "gn:timezone":"America/Caracas",
    "iso:country":"VE",
    "wof:name":"Polanco",
    "wof:placetype":"locality"
},
  "geometry": {"coordinates":[-69.09999999999999,11.36667],"type":"Point"}
}