{
  "type": "Feature",
  "properties": {
    "gn:admin1_code":"18.0",
    "gn:asciiname":"Boca de La Laguna",
    "gn:country_code":"VE",
    "gn:dem":90,
    "gn:feature_class":"P",
    "gn:feature_code":"PPL",
    "gn:name":"Boca de La Laguna",
    "gn:population":0,
    "gn:timezone":"America/Caracas",
    "iso:country":"VE",
    "wof:name":"Boca de La Laguna",
    "wof:placetype":"locality"
},
  "geometry": {"coordinates":[-69.1361,8.66833],"type":"Point"}
}