{
  "type": "Feature",
  "properties": {
    "gn:admin1_code":"25",
    "gn:asciiname":"Carapa",
    "gn:country_code":"VE",
    "gn:dem":1031,
    "gn:feature_class":"P",
    "gn:feature_code":"PPL",
    "gn:name":"Carapa",
    "gn:population":0,
    "gn:timezone":"America/Caracas",
    "iso:country":"VE",
    "name:cat_x_preferred":[
        "Carapa"
    ],
    "name:ceb_x_preferred":[
        "Carapa"
    ],
    "name:fra_x_preferred":[
        "Carapa"
    ],
    "name:hye_x_preferred":[
        "\u053f\u0561\u0580\u0561\u057a\u0565\u0576\u056b"
    ],
    "name:nld_x_preferred":[
        "Carapa"
    ],
    "name:nor_x_preferred":[
        "Carapa"
    ],
    "name:por_x_preferred":[
        "Carapa"
    ],
    "name:spa_x_preferred":[
        "Carapa"
    ],
    "name:swe_x_preferred":[
        "Carapa"
    ],
    "name:war_x_preferred":[
        "Carapa"
    ],
    "wof:name":"Carapa",
    "wof:placetype":"locality"
},
  "geometry": {"coordinates":[-66.96666999999999,10.48333],"type":"Point"}
}