{
  "type": "Feature",
  "properties": {
    "gn:admin1_code":"12",
    "gn:asciiname":"Melaito",
    "gn:country_code":"VE",
    "gn:dem":139,
    "gn:feature_class":"P",
    "gn:feature_code":"PPL",
    "gn:name":"Mela\u00edto",
    "gn:population":0,
    "gn:timezone":"America/Caracas",
    "iso:country":"VE",
    "wof:name":"Melaito",
    "wof:placetype":"locality"
},
  "geometry": {"coordinates":[-66.05920999999999,9.04216],"type":"Point"}
}