{
  "type": "Feature",
  "properties": {
    "gn:admin1_code":"15.0",
    "gn:asciiname":"Margarita",
    "gn:country_code":"VE",
    "gn:dem":925,
    "gn:feature_class":"P",
    "gn:feature_code":"PPLL",
    "gn:name":"Margarita",
    "gn:population":0,
    "gn:timezone":"America/Caracas",
    "iso:country":"VE",
    "name:ara_x_preferred":[
        "\u0645\u0627\u0631\u063a\u0631\u064a\u062a\u0627"
    ],
    "name:ben_x_preferred":[
        "\u09ae\u09be\u09b0\u0997\u09be\u09b0\u09bf\u09a4\u09be"
    ],
    "name:bos_x_preferred":[
        "Margarita"
    ],
    "name:bul_x_preferred":[
        "\u041c\u0430\u0440\u0433\u0430\u0440\u0438\u0442\u0430"
    ],
    "name:cat_x_preferred":[
        "Margarita"
    ],
    "name:ces_x_preferred":[
        "Margarita"
    ],
    "name:deu_x_preferred":[
        "Margarita"
    ],
    "name:fas_x_preferred":[
        "\u0645\u0627\u0631\u06af\u0627\u0631\u06cc\u062a\u0627"
    ],
    "name:fin_x_preferred":[
        "Margarita"
    ],
    "name:fra_x_preferred":[
        "Margarita"
    ],
    "name:glg_x_preferred":[
        "Margarita"
    ],
    "name:heb_x_preferred":[
        "\u05de\u05e8\u05d2\u05e8\u05d9\u05d8\u05d4"
    ],
    "name:hin_x_preferred":[
        "\u092e\u093e\u0930\u094d\u0917\u0930\u0940\u091f\u093e"
    ],
    "name:hye_x_preferred":[
        "\u0544\u0561\u0580\u0563\u0561\u0580\u056b\u057f\u0561"
    ],
    "name:ita_x_preferred":[
        "Margarita"
    ],
    "name:jpn_x_preferred":[
        "\u30de\u30eb\u30ac\u30ea\u30fc\u30bf"
    ],
    "name:kor_x_preferred":[
        "\ub9c8\ub974\uac00\ub9ac\ud0c0"
    ],
    "name:lav_x_preferred":[
        "Margarita"
    ],
    "name:nld_x_preferred":[
        "Margarita"
    ],
    "name:nno_x_preferred":[
        "Margarita"
    ],
    "name:nor_x_preferred":[
        "Margarita"
    ],
    "name:pol_x_preferred":[
        "Margarita"
    ],
    "name:por_x_preferred":[
        "Margarita"
    ],
    "name:ron_x_preferred":[
        "Margarita"
    ],
    "name:rus_x_preferred":[
        "\u041c\u0430\u0440\u0433\u0430\u0440\u0438\u0442\u0430"
    ],
    "name:slv_x_preferred":[
        "Margarita"
    ],
    "name:spa_x_preferred":[
        "Margarita"
    ],
    "name:swe_x_preferred":[
        "Margarita"
    ],
    "name:tur_x_preferred":[
        "Margarita"
    ],
    "name:ukr_x_preferred":[
        "\u041c\u0430\u0440\u0433\u0430\u0440\u0438\u0442\u0430"
    ],
    "name:urd_x_preferred":[
        "\u0645\u0627\u0631\u06af\u0631\u06cc\u0679\u0627"
    ],
    "name:vie_x_preferred":[
        "\u0110\u1ea3o Margarita"
    ],
    "name:zho_x_preferred":[
        "\u739b\u683c\u4e3d\u5854"
    ],
    "wof:name":"Margarita",
    "wof:placetype":"locality"
},
  "geometry": {"coordinates":[-66.79818,10.40377],"type":"Point"}
}