{
  "type": "Feature",
  "properties": {
    "gn:admin1_code":"15.0",
    "gn:asciiname":"Margarita",
    "gn:country_code":"VE",
    "gn:dem":925,
    "gn:feature_class":"P",
    "gn:feature_code":"PPLL",
    "gn:name":"Margarita",
    "gn:population":0,
    "gn:timezone":"America/Caracas",
    "iso:country":"VE",
    "wof:name":"Margarita",
    "wof:placetype":"locality"
},
  "geometry": {"coordinates":[-66.79818,10.40377],"type":"Point"}
}