{
  "type": "Feature",
  "properties": {
    "gn:admin1_code":"4",
    "gn:asciiname":"La Quesera",
    "gn:country_code":"VE",
    "gn:dem":436,
    "gn:feature_class":"P",
    "gn:feature_code":"PPL",
    "gn:name":"La Quesera",
    "gn:population":0,
    "gn:timezone":"America/Caracas",
    "iso:country":"VE",
    "wof:name":"La Quesera",
    "wof:placetype":"locality"
},
  "geometry": {"coordinates":[-67.58194,10.10611],"type":"Point"}
}