{
  "type": "Feature",
  "properties": {
    "gn:admin1_code":"12",
    "gn:asciiname":"Guariquito",
    "gn:country_code":"VE",
    "gn:dem":82,
    "gn:feature_class":"P",
    "gn:feature_code":"PPL",
    "gn:name":"Guariquito",
    "gn:population":0,
    "gn:timezone":"America/Caracas",
    "iso:country":"VE",
    "wof:name":"Guariquito",
    "wof:placetype":"locality"
},
  "geometry": {"coordinates":[-67.21666999999999,8.71667],"type":"Point"}
}