{
  "type": "Feature",
  "properties": {
    "gn:admin1_code":"18.0",
    "gn:asciiname":"Boqueron",
    "gn:country_code":"VE",
    "gn:dem":176,
    "gn:feature_class":"P",
    "gn:feature_code":"PPL",
    "gn:name":"Boquer\u00f3n",
    "gn:population":0,
    "gn:timezone":"America/Caracas",
    "iso:country":"VE",
    "name:spa_x_preferred":[
        "Boquer\u00f3n"
    ],
    "wof:name":"Boqueron",
    "wof:placetype":"locality"
},
  "geometry": {"coordinates":[-69.71576,9.09553],"type":"Point"}
}