{
  "type": "Feature",
  "properties": {
    "gn:admin1_code":"02",
    "gn:asciiname":"La Pradera",
    "gn:country_code":"VE",
    "gn:dem":92,
    "gn:feature_class":"P",
    "gn:feature_code":"PPLL",
    "gn:name":"La Pradera",
    "gn:population":0,
    "gn:timezone":"America/Caracas",
    "iso:country":"VE",
    "wof:name":"La Pradera",
    "wof:placetype":"locality"
},
  "geometry": {"coordinates":[-64.62142,8.11903],"type":"Point"}
}