{
  "type": "Feature",
  "properties": {
    "gn:admin1_code":"15",
    "gn:asciiname":"Borges",
    "gn:country_code":"VE",
    "gn:dem":11,
    "gn:feature_class":"P",
    "gn:feature_code":"PPL",
    "gn:name":"Borges",
    "gn:population":0,
    "gn:timezone":"America/Caracas",
    "iso:country":"VE",
    "wof:name":"Borges",
    "wof:placetype":"locality"
},
  "geometry": {"coordinates":[-65.96666999999999,10.28333],"type":"Point"}
}