{
  "type": "Feature",
  "properties": {
    "gn:admin1_code":"18.0",
    "gn:asciiname":"El Dividive",
    "gn:country_code":"VE",
    "gn:dem":110,
    "gn:feature_class":"P",
    "gn:feature_code":"PPLL",
    "gn:name":"El Dividive",
    "gn:population":0,
    "gn:timezone":"America/Caracas",
    "iso:country":"VE",
    "name:spa_x_preferred":[
        "El Dividive"
    ],
    "wof:name":"El Dividive",
    "wof:placetype":"locality"
},
  "geometry": {"coordinates":[-69.40658000000001,9.0747],"type":"Point"}
}