{
  "type": "Feature",
  "properties": {
    "gn:admin1_code":"15.0",
    "gn:asciiname":"El Mijao",
    "gn:country_code":"VE",
    "gn:dem":1097,
    "gn:feature_class":"P",
    "gn:feature_code":"PPLL",
    "gn:name":"El Mijao",
    "gn:population":0,
    "gn:timezone":"America/Caracas",
    "iso:country":"VE",
    "wof:name":"El Mijao",
    "wof:placetype":"locality"
},
  "geometry": {"coordinates":[-66.83322,10.38723],"type":"Point"}
}