{
  "type": "Feature",
  "properties": {
    "iso:country":"VE",
    "qs:gn_pop":0,
    "qs:name":"Montalban",
    "qs:name_adm0":"Venezuela",
    "qs:name_adm1":"M\u00e9rida",
    "qs:photos":1,
    "qs:photos_1k":1,
    "qs:photos_9k":2,
    "qs:photos_9r":5,
    "qs:photos_all":374,
    "qs:photos_sr":1,
    "qs:placetype":"LocalAdmin",
    "qs:pop_sr":"0",
    "qs:woe_adm0":23424982,
    "wof:name":"Montalban",
    "wof:placetype":"localadmin"
},
  "geometry": {"coordinates":[-71.15501399999999,8.590865],"type":"Point"}
}