{
  "type": "Feature",
  "properties": {
    "gn:admin1_code":"11",
    "gn:asciiname":"Yesquin",
    "gn:country_code":"VE",
    "gn:dem":232,
    "gn:feature_class":"P",
    "gn:feature_code":"PPL",
    "gn:name":"Yesquin",
    "gn:population":0,
    "gn:timezone":"America/Caracas",
    "iso:country":"VE",
    "wof:name":"Yesquin",
    "wof:placetype":"locality"
},
  "geometry": {"coordinates":[-69.4515,10.91111],"type":"Point"}
}