{
  "type": "Feature",
  "properties": {
    "gn:admin1_code":"5",
    "gn:asciiname":"Cano Morroncito",
    "gn:country_code":"VE",
    "gn:dem":90,
    "gn:feature_class":"P",
    "gn:feature_code":"PPL",
    "gn:name":"Ca\u00f1o Morroncito",
    "gn:population":0,
    "gn:timezone":"America/Caracas",
    "iso:country":"VE",
    "wof:name":"Cano Morroncito",
    "wof:placetype":"locality"
},
  "geometry": {"coordinates":[-69.13333,8.41667],"type":"Point"}
}