{
  "type": "Feature",
  "properties": {
    "gn:admin1_code":"20.0",
    "gn:asciiname":"La Arabia",
    "gn:country_code":"VE",
    "gn:dem":904,
    "gn:feature_class":"P",
    "gn:feature_code":"PPL",
    "gn:name":"La Arabia",
    "gn:population":0,
    "gn:timezone":"America/Caracas",
    "iso:country":"VE",
    "wof:name":"La Arabia",
    "wof:placetype":"locality"
},
  "geometry": {"coordinates":[-72.36516999999998,7.73314],"type":"Point"}
}