{
  "type": "Feature",
  "properties": {
    "gn:admin1_code":"2",
    "gn:asciiname":"El Alto",
    "gn:country_code":"VE",
    "gn:dem":397,
    "gn:feature_class":"P",
    "gn:feature_code":"PPL",
    "gn:name":"El Alto",
    "gn:population":0,
    "gn:timezone":"America/Caracas",
    "iso:country":"VE",
    "name:afr_x_preferred":[
        "El Alto"
    ],
    "name:ara_x_preferred":[
        "\u0625\u0644 \u0623\u0644\u062a\u0648"
    ],
    "name:aym_x_preferred":[
        "Altu pata"
    ],
    "name:bul_x_preferred":[
        "\u0415\u043b \u0410\u043b\u0442\u043e"
    ],
    "name:ces_x_preferred":[
        "El Alto"
    ],
    "name:dan_x_preferred":[
        "El Alto"
    ],
    "name:deu_x_preferred":[
        "El Alto"
    ],
    "name:ell_x_preferred":[
        "\u0395\u03bb \u0386\u03bb\u03c4\u03bf"
    ],
    "name:epo_x_preferred":[
        "El Alto"
    ],
    "name:eus_x_preferred":[
        "El Alto"
    ],
    "name:fas_x_preferred":[
        "\u0627\u0644 \u0622\u0644\u062a\u0648"
    ],
    "name:fin_x_preferred":[
        "El Alto"
    ],
    "name:fra_x_preferred":[
        "El Alto"
    ],
    "name:heb_x_preferred":[
        "\u05d0\u05dc \u05d0\u05dc\u05d8\u05d5"
    ],
    "name:hun_x_preferred":[
        "El Alto"
    ],
    "name:ita_x_preferred":[
        "El Alto"
    ],
    "name:jpn_x_preferred":[
        "\u30a8\u30eb\u30fb\u30a2\u30eb\u30c8"
    ],
    "name:kat_x_preferred":[
        "\u10d4\u10da-\u10d0\u10da\u10e2\u10dd"
    ],
    "name:kor_x_preferred":[
        "\uc5d8\uc54c\ud1a0"
    ],
    "name:lit_x_preferred":[
        "El Altas"
    ],
    "name:mkd_x_preferred":[
        "\u0415\u043b \u0410\u043b\u0442\u043e"
    ],
    "name:nau_x_preferred":[
        "El Alto"
    ],
    "name:nld_x_preferred":[
        "El Alto"
    ],
    "name:nor_x_preferred":[
        "El Alto"
    ],
    "name:pol_x_preferred":[
        "El Alto"
    ],
    "name:por_x_preferred":[
        "El Alto"
    ],
    "name:que_x_preferred":[
        "Altu llaqta"
    ],
    "name:ron_x_preferred":[
        "El Alto"
    ],
    "name:rus_x_preferred":[
        "\u042d\u043b\u044c-\u0410\u043b\u044c\u0442\u043e"
    ],
    "name:sco_x_preferred":[
        "El Alto"
    ],
    "name:spa_x_preferred":[
        "El Alto"
    ],
    "name:swe_x_preferred":[
        "El Alto"
    ],
    "name:tat_x_preferred":[
        "\u042d\u043b-\u0410\u043b\u044c\u0442\u043e"
    ],
    "name:tur_x_preferred":[
        "El Alto"
    ],
    "name:ukr_x_preferred":[
        "\u0415\u043b\u044c-\u0410\u043b\u044c\u0442\u043e"
    ],
    "name:urd_x_preferred":[
        "\u0627\u06cc\u0644 \u0622\u0644\u062a\u0648"
    ],
    "name:vep_x_preferred":[
        "El' Al'to"
    ],
    "name:vie_x_preferred":[
        "El Alto"
    ],
    "name:vol_x_preferred":[
        "El Alto"
    ],
    "name:war_x_preferred":[
        "El Alto"
    ],
    "name:zho_x_preferred":[
        "\u57c3\u723e\u963f\u723e\u6258"
    ],
    "wof:name":"El Alto",
    "wof:placetype":"locality"
},
  "geometry": {"coordinates":[-64.72129,9.95187],"type":"Point"}
}