{
  "type": "Feature",
  "properties": {
    "gn:admin1_code":"15",
    "gn:asciiname":"Quita Calzon",
    "gn:cc2":"VE",
    "gn:country_code":"VE",
    "gn:dem":459,
    "gn:feature_class":"P",
    "gn:feature_code":"PPL",
    "gn:name":"Quita Calz\u00f3n",
    "gn:population":0,
    "gn:timezone":"America/Caracas",
    "iso:country":"VE",
    "name:und_x_variant":[
        "Quita Cals\u00f3n",
        "Quita Calz\u00f3n"
    ],
    "wof:name":"Quita Calzon",
    "wof:placetype":"locality"
},
  "geometry": {"coordinates":[-66.90000000000001,10.08333],"type":"Point"}
}