{
  "type": "Feature",
  "properties": {
    "gn:admin1_code":"6",
    "gn:asciiname":"Conejo",
    "gn:country_code":"VE",
    "gn:dem":270,
    "gn:feature_class":"P",
    "gn:feature_code":"PPL",
    "gn:name":"Conejo",
    "gn:population":0,
    "gn:timezone":"America/Caracas",
    "iso:country":"VE",
    "name:ceb_x_preferred":[
        "Conejo"
    ],
    "name:nds_x_preferred":[
        "Conejo"
    ],
    "name:spa_x_preferred":[
        "Conejo"
    ],
    "name:swe_x_preferred":[
        "Conejo"
    ],
    "wof:name":"Conejo",
    "wof:placetype":"locality"
},
  "geometry": {"coordinates":[-63.08333,6.81667],"type":"Point"}
}