{
  "type": "Feature",
  "properties": {
    "gn:admin1_code":"13",
    "gn:asciiname":"Los Robles",
    "gn:country_code":"VE",
    "gn:dem":660,
    "gn:feature_class":"P",
    "gn:feature_code":"PPL",
    "gn:name":"Los Robles",
    "gn:population":0,
    "gn:timezone":"America/Caracas",
    "iso:country":"VE",
    "name:ceb_x_preferred":[
        "Los Robles"
    ],
    "name:srp_x_preferred":[
        "\u041b\u043e\u0441 \u0420\u043e\u0431\u043b\u0435\u0441"
    ],
    "name:swe_x_preferred":[
        "Los Robles"
    ],
    "wof:name":"Los Robles",
    "wof:placetype":"locality"
},
  "geometry": {"coordinates":[-69.6031,10.3204],"type":"Point"}
}