{
  "type": "Feature",
  "properties": {
    "gn:admin1_code":"06",
    "gn:asciiname":"Suruacri",
    "gn:country_code":"VE",
    "gn:dem":854,
    "gn:feature_class":"P",
    "gn:feature_code":"PPL",
    "gn:name":"Suruacri",
    "gn:population":0,
    "gn:timezone":"America/Caracas",
    "iso:country":"VE",
    "wof:name":"Suruacri",
    "wof:placetype":"locality"
},
  "geometry": {"coordinates":[-61.08333,4.76667],"type":"Point"}
}