{
  "type": "Feature",
  "properties": {
    "gn:admin1_code":"19.0",
    "gn:asciiname":"Cumbre de Tigrillo",
    "gn:country_code":"VE",
    "gn:dem":331,
    "gn:feature_class":"P",
    "gn:feature_code":"PPL",
    "gn:name":"Cumbre de Tigrillo",
    "gn:population":0,
    "gn:timezone":"America/Caracas",
    "iso:country":"VE",
    "wof:name":"Cumbre de Tigrillo",
    "wof:placetype":"locality"
},
  "geometry": {"coordinates":[-62.77844,10.72296],"type":"Point"}
}