{
  "type": "Feature",
  "properties": {
    "gn:admin1_code":"20",
    "gn:asciiname":"Los Picachitos",
    "gn:country_code":"VE",
    "gn:dem":1622,
    "gn:feature_class":"P",
    "gn:feature_code":"PPL",
    "gn:name":"Los Picachitos",
    "gn:population":0,
    "gn:timezone":"America/Caracas",
    "iso:country":"VE",
    "wof:name":"Los Picachitos",
    "wof:placetype":"locality"
},
  "geometry": {"coordinates":[-72.35183000000001,7.89914],"type":"Point"}
}