{
  "type": "Feature",
  "properties": {
    "gn:admin1_code":"14.0",
    "gn:asciiname":"Las Cruces",
    "gn:country_code":"VE",
    "gn:dem":1416,
    "gn:feature_class":"P",
    "gn:feature_code":"PPLL",
    "gn:name":"Las Cruces",
    "gn:population":0,
    "gn:timezone":"America/Caracas",
    "iso:country":"VE",
    "wof:name":"Las Cruces",
    "wof:placetype":"locality"
},
  "geometry": {"coordinates":[-71.76306,8.35202],"type":"Point"}
}