{
  "type": "Feature",
  "properties": {
    "gn:admin1_code":"14",
    "gn:asciiname":"Cucuchica",
    "gn:country_code":"VE",
    "gn:dem":989,
    "gn:feature_class":"P",
    "gn:feature_code":"PPL",
    "gn:name":"Cucuchica",
    "gn:population":0,
    "gn:timezone":"America/Caracas",
    "iso:country":"VE",
    "wof:name":"Cucuchica",
    "wof:placetype":"locality"
},
  "geometry": {"coordinates":[-71.69769000000002,8.3373],"type":"Point"}
}