{
  "type": "Feature",
  "properties": {
    "gn:admin1_code":"7",
    "gn:asciiname":"Santa Efigenia",
    "gn:country_code":"VE",
    "gn:dem":919,
    "gn:feature_class":"P",
    "gn:feature_code":"PPL",
    "gn:name":"Santa Efigenia",
    "gn:population":0,
    "gn:timezone":"America/Caracas",
    "iso:country":"VE",
    "wof:name":"Santa Efigenia",
    "wof:placetype":"locality"
},
  "geometry": {"coordinates":[-67.79730000000001,10.00302],"type":"Point"}
}