{
  "type": "Feature",
  "properties": {
    "gn:admin1_code":"20.0",
    "gn:asciiname":"Los Picachos",
    "gn:country_code":"VE",
    "gn:dem":1362,
    "gn:feature_class":"P",
    "gn:feature_code":"PPL",
    "gn:name":"Los Picachos",
    "gn:population":0,
    "gn:timezone":"America/Caracas",
    "iso:country":"VE",
    "wof:name":"Los Picachos",
    "wof:placetype":"locality"
},
  "geometry": {"coordinates":[-71.98181,7.81552],"type":"Point"}
}