{
  "type": "Feature",
  "properties": {
    "gn:admin1_code":"13",
    "gn:asciiname":"Turturia",
    "gn:country_code":"VE",
    "gn:dem":706,
    "gn:feature_class":"P",
    "gn:feature_code":"PPL",
    "gn:name":"Turturia",
    "gn:population":0,
    "gn:timezone":"America/Caracas",
    "iso:country":"VE",
    "wof:name":"Turturia",
    "wof:placetype":"locality"
},
  "geometry": {"coordinates":[-69.72247,10.13543],"type":"Point"}
}