{
  "type": "Feature",
  "properties": {
    "gn:admin1_code":"12.0",
    "gn:asciiname":"Mohomal",
    "gn:country_code":"VE",
    "gn:dem":173,
    "gn:feature_class":"P",
    "gn:feature_code":"PPL",
    "gn:name":"Mohomal",
    "gn:population":0,
    "gn:timezone":"America/Caracas",
    "iso:country":"VE",
    "wof:name":"Mohomal",
    "wof:placetype":"locality"
},
  "geometry": {"coordinates":[-65.87274000000001,8.95692],"type":"Point"}
}