{
  "type": "Feature",
  "properties": {
    "gn:admin1_code":"20",
    "gn:asciiname":"La Honda",
    "gn:country_code":"VE",
    "gn:dem":1249,
    "gn:feature_class":"P",
    "gn:feature_code":"PPL",
    "gn:name":"La Honda",
    "gn:population":0,
    "gn:timezone":"America/Caracas",
    "iso:country":"VE",
    "wof:name":"La Honda",
    "wof:placetype":"locality"
},
  "geometry": {"coordinates":[-72.24417,7.9825],"type":"Point"}
}