{
  "type": "Feature",
  "properties": {
    "gn:admin1_code":"3",
    "gn:asciiname":"Mata de Turagua",
    "gn:cc2":"VE",
    "gn:country_code":"VE",
    "gn:dem":86,
    "gn:feature_class":"P",
    "gn:feature_code":"PPL",
    "gn:name":"Mata de Turagua",
    "gn:population":0,
    "gn:timezone":"America/Caracas",
    "iso:country":"VE",
    "name:und_x_variant":[
        "Mata de Torugua",
        "Mata de Turagua"
    ],
    "wof:name":"Mata de Turagua",
    "wof:placetype":"locality"
},
  "geometry": {"coordinates":[-69.59999999999999,7.63333],"type":"Point"}
}