{
  "type": "Feature",
  "properties": {
    "gn:admin1_code":"2",
    "gn:asciiname":"La Encantada",
    "gn:country_code":"VE",
    "gn:dem":27,
    "gn:feature_class":"P",
    "gn:feature_code":"PPL",
    "gn:name":"La Encantada",
    "gn:population":0,
    "gn:timezone":"America/Caracas",
    "iso:country":"VE",
    "name:ceb_x_preferred":[
        "La Encantada"
    ],
    "name:spa_x_preferred":[
        "La Encantada"
    ],
    "name:swe_x_preferred":[
        "La Encantada"
    ],
    "name:und_x_variant":[
        "Cede\u00f1o",
        "La Encantada"
    ],
    "wof:name":"La Encantada",
    "wof:placetype":"locality"
},
  "geometry": {"coordinates":[-65.16884,9.69736],"type":"Point"}
}