{
  "type": "Feature",
  "properties": {
    "gn:admin1_code":"12",
    "gn:asciiname":"Las Pitahayas",
    "gn:country_code":"VE",
    "gn:dem":98,
    "gn:feature_class":"P",
    "gn:feature_code":"PPL",
    "gn:name":"Las Pitahayas",
    "gn:population":0,
    "gn:timezone":"America/Caracas",
    "iso:country":"VE",
    "name:und_x_variant":[
        "Los Pitahayas",
        "Las Pitahayas"
    ],
    "wof:name":"Las Pitahayas",
    "wof:placetype":"locality"
},
  "geometry": {"coordinates":[-65.46887,9.19016],"type":"Point"}
}