{
  "type": "Feature",
  "properties": {
    "gn:admin1_code":"4.0",
    "gn:asciiname":"El Portachuelo",
    "gn:country_code":"VE",
    "gn:dem":986,
    "gn:feature_class":"P",
    "gn:feature_code":"PPL",
    "gn:name":"El Portachuelo",
    "gn:population":0,
    "gn:timezone":"America/Caracas",
    "iso:country":"VE",
    "wof:name":"El Portachuelo",
    "wof:placetype":"locality"
},
  "geometry": {"coordinates":[-67.24056,10.20709],"type":"Point"}
}