{
  "type": "Feature",
  "properties": {
    "gn:admin1_code":"23",
    "gn:asciiname":"Jaguey de la Entrada",
    "gn:country_code":"VE",
    "gn:dem":78,
    "gn:feature_class":"P",
    "gn:feature_code":"PPL",
    "gn:name":"Jag\u00fcey de la Entrada",
    "gn:population":0,
    "gn:timezone":"America/Caracas",
    "iso:country":"VE",
    "name:und_x_variant":[
        "La Entrada",
        "Jag\u00fcey de la Entrada"
    ],
    "wof:name":"Jaguey de la Entrada",
    "wof:placetype":"locality"
},
  "geometry": {"coordinates":[-71.35109,10.72127],"type":"Point"}
}