{
  "type": "Feature",
  "properties": {
    "gn:admin1_code":"21",
    "gn:asciiname":"Los Pajones",
    "gn:country_code":"VE",
    "gn:dem":241,
    "gn:feature_class":"P",
    "gn:feature_code":"PPL",
    "gn:name":"Los Pajones",
    "gn:population":0,
    "gn:timezone":"America/Caracas",
    "iso:country":"VE",
    "wof:name":"Los Pajones",
    "wof:placetype":"locality"
},
  "geometry": {"coordinates":[-70.54883000000002,9.49697],"type":"Point"}
}