{
  "type": "Feature",
  "properties": {
    "gn:admin1_code":"13",
    "gn:asciiname":"El Manzanal",
    "gn:country_code":"VE",
    "gn:dem":1302,
    "gn:feature_class":"P",
    "gn:feature_code":"PPL",
    "gn:name":"El Manzanal",
    "gn:population":0,
    "gn:timezone":"America/Caracas",
    "iso:country":"VE",
    "wof:name":"El Manzanal",
    "wof:placetype":"locality"
},
  "geometry": {"coordinates":[-69.51806999999999,9.79807],"type":"Point"}
}