{
  "type": "Feature",
  "properties": {
    "gn:admin1_code":"14",
    "gn:asciiname":"El Salado",
    "gn:country_code":"VE",
    "gn:dem":1569,
    "gn:feature_class":"P",
    "gn:feature_code":"PPL",
    "gn:name":"El Salado",
    "gn:population":0,
    "gn:timezone":"America/Caracas",
    "iso:country":"VE",
    "wof:name":"El Salado",
    "wof:placetype":"locality"
},
  "geometry": {"coordinates":[-71.43456,8.45094],"type":"Point"}
}