{
  "type": "Feature",
  "properties": {
    "gn:admin1_code":"22",
    "gn:asciiname":"Tamanavare",
    "gn:country_code":"VE",
    "gn:dem":161,
    "gn:feature_class":"P",
    "gn:feature_code":"PPL",
    "gn:name":"Tamanavare",
    "gn:population":0,
    "gn:timezone":"America/Caracas",
    "iso:country":"VE",
    "wof:name":"Tamanavare",
    "wof:placetype":"locality"
},
  "geometry": {"coordinates":[-68.7175,10.27924],"type":"Point"}
}