{
  "type": "Feature",
  "properties": {
    "gn:admin1_code":"16",
    "gn:asciiname":"Los Pozotes",
    "gn:country_code":"VE",
    "gn:dem":428,
    "gn:feature_class":"P",
    "gn:feature_code":"PPL",
    "gn:name":"Los Pozotes",
    "gn:population":0,
    "gn:timezone":"America/Caracas",
    "iso:country":"VE",
    "wof:name":"Los Pozotes",
    "wof:placetype":"locality"
},
  "geometry": {"coordinates":[-63.83076,9.94779],"type":"Point"}
}