{
  "type": "Feature",
  "properties": {
    "gn:admin1_code":"23",
    "gn:asciiname":"Ipica",
    "gn:country_code":"VE",
    "gn:dem":699,
    "gn:feature_class":"P",
    "gn:feature_code":"PPL",
    "gn:name":"Ipica",
    "gn:population":0,
    "gn:timezone":"America/Caracas",
    "iso:country":"VE",
    "wof:name":"Ipica",
    "wof:placetype":"locality"
},
  "geometry": {"coordinates":[-72.83601,9.87712],"type":"Point"}
}