{
  "type": "Feature",
  "properties": {
    "iso:country":"VE",
    "qs:gn_pop":0,
    "qs:name":"Capital Bejuma",
    "qs:name_adm0":"Venezuela",
    "qs:name_adm1":"Carabobo",
    "qs:photos":21,
    "qs:photos_1k":4,
    "qs:photos_9k":1,
    "qs:photos_9r":2,
    "qs:photos_all":36,
    "qs:photos_sr":1,
    "qs:placetype":"LocalAdmin",
    "qs:pop_sr":"0",
    "qs:woe_adm0":23424982,
    "wof:name":"Capital Bejuma",
    "wof:placetype":"localadmin"
},
  "geometry": {"coordinates":[-68.260246,10.1688],"type":"Point"}
}