{
  "type": "Feature",
  "properties": {
    "gn:admin1_code":"5",
    "gn:asciiname":"Hato Mata de Conuco",
    "gn:country_code":"VE",
    "gn:dem":120,
    "gn:feature_class":"P",
    "gn:feature_code":"PPLL",
    "gn:name":"Hato Mata de Conuco",
    "gn:population":0,
    "gn:timezone":"America/Caracas",
    "iso:country":"VE",
    "wof:name":"Hato Mata de Conuco",
    "wof:placetype":"locality"
},
  "geometry": {"coordinates":[-70.53139,7.6575],"type":"Point"}
}