{
  "type": "Feature",
  "properties": {
    "gn:admin1_code":"14",
    "gn:asciiname":"Montoya",
    "gn:country_code":"VE",
    "gn:dem":1477,
    "gn:feature_class":"P",
    "gn:feature_code":"PPL",
    "gn:name":"Montoya",
    "gn:population":0,
    "gn:timezone":"America/Caracas",
    "iso:country":"VE",
    "wof:name":"Montoya",
    "wof:placetype":"locality"
},
  "geometry": {"coordinates":[-71.48926999999998,8.50091],"type":"Point"}
}