{
  "type": "Feature",
  "properties": {
    "gn:admin1_code":"12",
    "gn:asciiname":"El Pauji",
    "gn:country_code":"VE",
    "gn:dem":157,
    "gn:feature_class":"P",
    "gn:feature_code":"PPL",
    "gn:name":"El Pauj\u00ed",
    "gn:population":0,
    "gn:timezone":"America/Caracas",
    "iso:country":"VE",
    "wof:name":"El Pauji",
    "wof:placetype":"locality"
},
  "geometry": {"coordinates":[-66.18333,8.95],"type":"Point"}
}