{
  "type": "Feature",
  "properties": {
    "iso:country":"VE",
    "qs:gn_pop":0,
    "qs:name":"Juan B. Rodriguez",
    "qs:name_adm0":"Venezuela",
    "qs:name_adm1":"Lara",
    "qs:photos":93,
    "qs:photos_1k":19,
    "qs:photos_9k":1,
    "qs:photos_9r":3,
    "qs:photos_all":129,
    "qs:photos_sr":3,
    "qs:placetype":"LocalAdmin",
    "qs:pop_sr":"0",
    "qs:woe_adm0":23424982,
    "wof:name":"Juan B. Rodriguez",
    "wof:placetype":"localadmin"
},
  "geometry": {"coordinates":[-69.625167,9.92472],"type":"Point"}
}