{
  "type": "Feature",
  "properties": {
    "gn:admin1_code":"1",
    "gn:asciiname":"Galipero",
    "gn:country_code":"VE",
    "gn:dem":67,
    "gn:feature_class":"P",
    "gn:feature_code":"PPL",
    "gn:name":"Galipero",
    "gn:population":0,
    "gn:timezone":"America/Caracas",
    "iso:country":"VE",
    "wof:name":"Galipero",
    "wof:placetype":"locality"
},
  "geometry": {"coordinates":[-67.52889,5.82806],"type":"Point"}
}