{
  "type": "Feature",
  "properties": {
    "gn:admin1_code":"21",
    "gn:asciiname":"Visnaja",
    "gn:country_code":"VE",
    "gn:dem":2046,
    "gn:feature_class":"P",
    "gn:feature_code":"PPL",
    "gn:name":"Visnaja",
    "gn:population":0,
    "gn:timezone":"America/Caracas",
    "iso:country":"VE",
    "wof:name":"Visnaja",
    "wof:placetype":"locality"
},
  "geometry": {"coordinates":[-70.23611,9.42667],"type":"Point"}
}