{
  "type": "Feature",
  "properties": {
    "gn:admin1_code":"13",
    "gn:asciiname":"Cogollalito",
    "gn:country_code":"VE",
    "gn:dem":797,
    "gn:feature_class":"P",
    "gn:feature_code":"PPL",
    "gn:name":"Cogollalito",
    "gn:population":0,
    "gn:timezone":"America/Caracas",
    "iso:country":"VE",
    "wof:name":"Cogollalito",
    "wof:placetype":"locality"
},
  "geometry": {"coordinates":[-69.56341999999999,10.51244],"type":"Point"}
}