{
  "type": "Feature",
  "properties": {
    "gn:admin1_code":"12.0",
    "gn:asciiname":"Las Narices",
    "gn:country_code":"VE",
    "gn:dem":193,
    "gn:feature_class":"P",
    "gn:feature_code":"PPLL",
    "gn:name":"Las Narices",
    "gn:population":0,
    "gn:timezone":"America/Caracas",
    "iso:country":"VE",
    "wof:name":"Las Narices",
    "wof:placetype":"locality"
},
  "geometry": {"coordinates":[-65.77641,9.79895],"type":"Point"}
}