{
  "type": "Feature",
  "properties": {
    "gn:admin1_code":"11",
    "gn:asciiname":"Manaure",
    "gn:country_code":"VE",
    "gn:dem":30,
    "gn:feature_class":"P",
    "gn:feature_code":"PPL",
    "gn:name":"Manaure",
    "gn:population":0,
    "gn:timezone":"America/Caracas",
    "iso:country":"VE",
    "name:und_x_variant":[
        "Urbanizaci\u00f3n Manaure",
        "Manaure"
    ],
    "wof:name":"Manaure",
    "wof:placetype":"locality"
},
  "geometry": {"coordinates":[-70.19722,11.65342],"type":"Point"}
}