{
  "type": "Feature",
  "properties": {
    "gn:admin1_code":"15",
    "gn:asciiname":"Santa Cruz de Agua Blanca",
    "gn:country_code":"VE",
    "gn:dem":459,
    "gn:feature_class":"P",
    "gn:feature_code":"PPL",
    "gn:name":"Santa Cruz de Agua Blanca",
    "gn:population":0,
    "gn:timezone":"America/Caracas",
    "iso:country":"VE",
    "wof:name":"Santa Cruz de Agua Blanca",
    "wof:placetype":"locality"
},
  "geometry": {"coordinates":[-66.46167,10.05139],"type":"Point"}
}