{
  "type": "Feature",
  "properties": {
    "gn:admin1_code":"8.0",
    "gn:asciiname":"Tapa de La Iguana",
    "gn:country_code":"VE",
    "gn:dem":67,
    "gn:feature_class":"P",
    "gn:feature_code":"PPL",
    "gn:name":"Tapa de La Iguana",
    "gn:population":0,
    "gn:timezone":"America/Caracas",
    "iso:country":"VE",
    "wof:name":"Tapa de La Iguana",
    "wof:placetype":"locality"
},
  "geometry": {"coordinates":[-68.07795,8.86527],"type":"Point"}
}