{
  "type": "Feature",
  "properties": {
    "gn:admin1_code":"15",
    "gn:asciiname":"El Canaote",
    "gn:country_code":"VE",
    "gn:dem":1638,
    "gn:feature_class":"P",
    "gn:feature_code":"PPL",
    "gn:name":"El Ca\u00f1aote",
    "gn:population":0,
    "gn:timezone":"America/Caracas",
    "iso:country":"VE",
    "wof:name":"El Canaote",
    "wof:placetype":"locality"
},
  "geometry": {"coordinates":[-67.12694999999999,10.38141],"type":"Point"}
}