{
  "type": "Feature",
  "properties": {
    "gn:admin1_code":"6",
    "gn:asciiname":"La Reforma",
    "gn:country_code":"VE",
    "gn:dem":55,
    "gn:feature_class":"P",
    "gn:feature_code":"PPL",
    "gn:name":"La Reforma",
    "gn:population":0,
    "gn:timezone":"America/Caracas",
    "iso:country":"VE",
    "wof:name":"La Reforma",
    "wof:placetype":"locality"
},
  "geometry": {"coordinates":[-66.09487,7.338],"type":"Point"}
}