{
  "type": "Feature",
  "properties": {
    "gn:admin1_code":"18.0",
    "gn:asciiname":"Cerro de Paja",
    "gn:country_code":"VE",
    "gn:dem":252,
    "gn:feature_class":"P",
    "gn:feature_code":"PPL",
    "gn:name":"Cerro de Paja",
    "gn:population":0,
    "gn:timezone":"America/Caracas",
    "iso:country":"VE",
    "name:spa_x_preferred":[
        "Cerro de Paja"
    ],
    "wof:name":"Cerro de Paja",
    "wof:placetype":"locality"
},
  "geometry": {"coordinates":[-69.88001,9.1336],"type":"Point"}
}