{
  "type": "Feature",
  "properties": {
    "gn:admin1_code":"12",
    "gn:asciiname":"Tejeria",
    "gn:country_code":"VE",
    "gn:dem":75,
    "gn:feature_class":"P",
    "gn:feature_code":"PPL",
    "gn:name":"Tejer\u00eda",
    "gn:population":0,
    "gn:timezone":"America/Caracas",
    "iso:country":"VE",
    "wof:name":"Tejeria",
    "wof:placetype":"locality"
},
  "geometry": {"coordinates":[-67.53333000000001,8.63333],"type":"Point"}
}