{
  "type": "Feature",
  "properties": {
    "gn:admin1_code":"1.0",
    "gn:asciiname":"Ironasiteri",
    "gn:country_code":"VE",
    "gn:dem":275,
    "gn:feature_class":"P",
    "gn:feature_code":"PPL",
    "gn:name":"Ironasiteri",
    "gn:population":0,
    "gn:timezone":"America/Caracas",
    "iso:country":"VE",
    "wof:name":"Ironasiteri",
    "wof:placetype":"locality"
},
  "geometry": {"coordinates":[-65.28617,1.59426],"type":"Point"}
}