{
  "type": "Feature",
  "properties": {
    "gn:admin1_code":"12",
    "gn:asciiname":"El Alto del Roble",
    "gn:country_code":"VE",
    "gn:dem":82,
    "gn:feature_class":"P",
    "gn:feature_code":"PPL",
    "gn:name":"El Alto del Roble",
    "gn:population":0,
    "gn:timezone":"America/Caracas",
    "iso:country":"VE",
    "name:und_x_variant":[
        "El Alto",
        "El Alto del Roble"
    ],
    "wof:name":"El Alto del Roble",
    "wof:placetype":"locality"
},
  "geometry": {"coordinates":[-65.29543000000001,8.96833],"type":"Point"}
}