{
  "type": "Feature",
  "properties": {
    "gn:admin1_code":"25",
    "gn:asciiname":"El Banqueo",
    "gn:country_code":"VE",
    "gn:dem":880,
    "gn:feature_class":"P",
    "gn:feature_code":"PPLL",
    "gn:name":"El Banqueo",
    "gn:population":0,
    "gn:timezone":"America/Caracas",
    "iso:country":"VE",
    "wof:name":"El Banqueo",
    "wof:placetype":"locality"
},
  "geometry": {"coordinates":[-67.04444000000001,10.52889],"type":"Point"}
}