{
  "type": "Feature",
  "properties": {
    "gn:admin1_code":"5",
    "gn:asciiname":"Chaparral",
    "gn:country_code":"VE",
    "gn:dem":117,
    "gn:feature_class":"P",
    "gn:feature_code":"PPL",
    "gn:name":"Chaparral",
    "gn:population":0,
    "gn:timezone":"America/Caracas",
    "iso:country":"VE",
    "name:ara_x_preferred":[
        "\u063a\u0627\u0628\u0629 \u062d\u0631\u0634\u064a\u0629"
    ],
    "name:bel_x_preferred":[
        "\u0427\u0430\u043f\u0430\u0440\u0430\u043b\u044c"
    ],
    "name:cat_x_preferred":[
        "Chaparral"
    ],
    "name:cym_x_preferred":[
        "Chaparral"
    ],
    "name:deu_x_preferred":[
        "Chaparral"
    ],
    "name:epo_x_preferred":[
        "\u0108aparalo"
    ],
    "name:eus_x_preferred":[
        "Txaparral"
    ],
    "name:fas_x_preferred":[
        "\u0628\u06cc\u0634\u0647\u200c\u0632\u0627\u0631\u0647\u0627\u06cc \u06a9\u0627\u0644\u06cc\u0641\u0631\u0646\u06cc\u0627"
    ],
    "name:fra_x_preferred":[
        "Chaparral"
    ],
    "name:ita_x_preferred":[
        "Chaparral"
    ],
    "name:kat_x_preferred":[
        "\u10e9\u10d0\u10de\u10d0\u10e0\u10d0\u10da\u10d8"
    ],
    "name:kaz_x_preferred":[
        "\u0427\u0430\u043f\u0430\u0440\u0430\u043b\u044c"
    ],
    "name:lim_x_preferred":[
        "Chaparral"
    ],
    "name:lit_x_preferred":[
        "\u010ciaparal\u0117"
    ],
    "name:nld_x_preferred":[
        "Chaparral"
    ],
    "name:nno_x_preferred":[
        "Chaparral"
    ],
    "name:nor_x_preferred":[
        "Chaparral"
    ],
    "name:oci_x_preferred":[
        "Chaparral"
    ],
    "name:pol_x_preferred":[
        "Chaparral"
    ],
    "name:por_x_preferred":[
        "Chaparral"
    ],
    "name:rus_x_preferred":[
        "\u0427\u0430\u043f\u0430\u0440\u0430\u043b\u044c"
    ],
    "name:sin_x_preferred":[
        "\u0daf\u0dd8\u0daa\u0db4\u0dad\u0dca\u200d\u0dbb\u0dd3 \u0d85\u0dbb\u0db9"
    ],
    "name:spa_x_preferred":[
        "Chaparral"
    ],
    "name:srp_x_preferred":[
        "\u0427\u0430\u043f\u0430\u0440\u0430\u043b"
    ],
    "name:swe_x_preferred":[
        "Chaparral"
    ],
    "name:ukr_x_preferred":[
        "\u0427\u0430\u043f\u0430\u0440\u0430\u043b\u044c"
    ],
    "name:zho_x_preferred":[
        "\u6d53\u5bc6\u5e38\u7eff\u9614\u53f6\u704c\u4e1b"
    ],
    "wof:name":"Chaparral",
    "wof:placetype":"locality"
},
  "geometry": {"coordinates":[-69.79345000000001,8.3931],"type":"Point"}
}