{
  "type": "Feature",
  "properties": {
    "gn:admin1_code":"5",
    "gn:asciiname":"Chaparral",
    "gn:country_code":"VE",
    "gn:dem":117,
    "gn:feature_class":"P",
    "gn:feature_code":"PPL",
    "gn:name":"Chaparral",
    "gn:population":0,
    "gn:timezone":"America/Caracas",
    "iso:country":"VE",
    "wof:name":"Chaparral",
    "wof:placetype":"locality"
},
  "geometry": {"coordinates":[-69.79345000000001,8.3931],"type":"Point"}
}