{
  "type": "Feature",
  "properties": {
    "gn:admin1_code":"19.0",
    "gn:asciiname":"Las Cuevas",
    "gn:country_code":"VE",
    "gn:dem":838,
    "gn:feature_class":"P",
    "gn:feature_code":"PPLL",
    "gn:name":"Las Cuevas",
    "gn:population":0,
    "gn:timezone":"America/Caracas",
    "iso:country":"VE",
    "wof:name":"Las Cuevas",
    "wof:placetype":"locality"
},
  "geometry": {"coordinates":[-64.09408000000001,10.2124],"type":"Point"}
}