{
  "type": "Feature",
  "properties": {
    "gn:admin1_code":"22.0",
    "gn:admin2_code":"2205.0",
    "gn:asciiname":"Independencia",
    "gn:country_code":"VE",
    "gn:dem":335,
    "gn:feature_class":"P",
    "gn:feature_code":"PPLA2",
    "gn:name":"Independencia",
    "gn:population":0,
    "gn:timezone":"America/Caracas",
    "iso:country":"VE",
    "wof:name":"Independencia",
    "wof:placetype":"locality"
},
  "geometry": {"coordinates":[-68.75511999999999,10.33432],"type":"Point"}
}