{
  "type": "Feature",
  "properties": {
    "gn:admin1_code":"22.0",
    "gn:admin2_code":"2205.0",
    "gn:asciiname":"Independencia",
    "gn:country_code":"VE",
    "gn:dem":335,
    "gn:feature_class":"P",
    "gn:feature_code":"PPLA2",
    "gn:name":"Independencia",
    "gn:population":0,
    "gn:timezone":"America/Caracas",
    "iso:country":"VE",
    "name:fra_x_preferred":[
        "Independencia"
    ],
    "name:ita_x_preferred":[
        "Independencia"
    ],
    "name:nld_x_preferred":[
        "Independencia"
    ],
    "name:por_x_preferred":[
        "Independencia"
    ],
    "name:spa_x_preferred":[
        "Municipio Independencia"
    ],
    "name:zho_x_preferred":[
        "\u56e0\u5fb7\u5f6d\u767b\u897f\u4e9e\u5e02"
    ],
    "wof:name":"Independencia",
    "wof:placetype":"locality"
},
  "geometry": {"coordinates":[-68.75511999999999,10.33432],"type":"Point"}
}