{
  "type": "Feature",
  "properties": {
    "gn:admin1_code":"23",
    "gn:asciiname":"Wayamuliser",
    "gn:country_code":"VE",
    "gn:dem":7,
    "gn:feature_class":"P",
    "gn:feature_code":"PPL",
    "gn:name":"Wayamuliser",
    "gn:population":0,
    "gn:timezone":"America/Caracas",
    "iso:country":"VE",
    "name:und_x_variant":[
        "Guayamulisira",
        "Guayamuricira",
        "Guayamulicira",
        "Wayamuliser"
    ],
    "wof:name":"Wayamuliser",
    "wof:placetype":"locality"
},
  "geometry": {"coordinates":[-71.97150000000001,11.46409],"type":"Point"}
}