{
  "type": "Feature",
  "properties": {
    "gn:admin1_code":"20",
    "gn:asciiname":"El Palenque",
    "gn:country_code":"VE",
    "gn:dem":2401,
    "gn:feature_class":"P",
    "gn:feature_code":"PPL",
    "gn:name":"El Palenque",
    "gn:population":0,
    "gn:timezone":"America/Caracas",
    "iso:country":"VE",
    "wof:name":"El Palenque",
    "wof:placetype":"locality"
},
  "geometry": {"coordinates":[-71.98813,8.07734],"type":"Point"}
}