{
  "type": "Feature",
  "properties": {
    "gn:admin1_code":"20",
    "gn:asciiname":"Seco Morro",
    "gn:country_code":"VE",
    "gn:dem":1145,
    "gn:feature_class":"P",
    "gn:feature_code":"PPL",
    "gn:name":"Seco Morro",
    "gn:population":0,
    "gn:timezone":"America/Caracas",
    "iso:country":"VE",
    "wof:name":"Seco Morro",
    "wof:placetype":"locality"
},
  "geometry": {"coordinates":[-72.33311999999999,8.03534],"type":"Point"}
}