{
  "type": "Feature",
  "properties": {
    "gn:admin1_code":"21",
    "gn:asciiname":"Mucuche",
    "gn:country_code":"VE",
    "gn:dem":1368,
    "gn:feature_class":"P",
    "gn:feature_code":"PPL",
    "gn:name":"Mucuche",
    "gn:population":0,
    "gn:timezone":"America/Caracas",
    "iso:country":"VE",
    "wof:name":"Mucuche",
    "wof:placetype":"locality"
},
  "geometry": {"coordinates":[-70.22055999999999,9.605],"type":"Point"}
}