{
  "type": "Feature",
  "properties": {
    "iso:country":"VE",
    "qs:gn_pop":0,
    "qs:name":"Alto de Los Godos",
    "qs:name_adm0":"Venezuela",
    "qs:name_adm1":"Monagas",
    "qs:photos":4,
    "qs:photos_1k":1,
    "qs:photos_9k":1,
    "qs:photos_9r":4,
    "qs:photos_all":288,
    "qs:photos_sr":1,
    "qs:placetype":"LocalAdmin",
    "qs:pop_sr":"0",
    "qs:woe_adm0":23424982,
    "wof:name":"Alto de Los Godos",
    "wof:placetype":"localadmin"
},
  "geometry": {"coordinates":[-63.176536,9.743657],"type":"Point"}
}