{
  "type": "Feature",
  "properties": {
    "gn:admin1_code":"12.0",
    "gn:asciiname":"El Alonsero",
    "gn:country_code":"VE",
    "gn:dem":181,
    "gn:feature_class":"P",
    "gn:feature_code":"PPLL",
    "gn:name":"El Alonsero",
    "gn:population":0,
    "gn:timezone":"America/Caracas",
    "iso:country":"VE",
    "wof:name":"El Alonsero",
    "wof:placetype":"locality"
},
  "geometry": {"coordinates":[-65.60665999999999,8.79121],"type":"Point"}
}