{
  "type": "Feature",
  "properties": {
    "gn:admin1_code":"21",
    "gn:asciiname":"Las Pavas",
    "gn:country_code":"VE",
    "gn:dem":385,
    "gn:feature_class":"P",
    "gn:feature_code":"PPL",
    "gn:name":"Las Pavas",
    "gn:population":0,
    "gn:timezone":"America/Caracas",
    "iso:country":"VE",
    "wof:name":"Las Pavas",
    "wof:placetype":"locality"
},
  "geometry": {"coordinates":[-70.80385,9.25935],"type":"Point"}
}