{
  "type": "Feature",
  "properties": {
    "gn:admin1_code":"16",
    "gn:asciiname":"La Guanota",
    "gn:country_code":"VE",
    "gn:dem":1135,
    "gn:feature_class":"P",
    "gn:feature_code":"PPL",
    "gn:name":"La Guanota",
    "gn:population":0,
    "gn:timezone":"America/Caracas",
    "iso:country":"VE",
    "name:und_x_variant":[
        "La Guanda",
        "La Guanota"
    ],
    "wof:name":"La Guanota",
    "wof:placetype":"locality"
},
  "geometry": {"coordinates":[-63.52367,10.21482],"type":"Point"}
}