{
  "type": "Feature",
  "properties": {
    "gn:admin1_code":"14",
    "gn:asciiname":"Mucujepe",
    "gn:country_code":"VE",
    "gn:dem":123,
    "gn:feature_class":"P",
    "gn:feature_code":"PPL",
    "gn:name":"Mucujepe",
    "gn:population":0,
    "gn:timezone":"America/Caracas",
    "iso:country":"VE",
    "wof:name":"Mucujepe",
    "wof:placetype":"locality"
},
  "geometry": {"coordinates":[-71.58610999999998,8.66611],"type":"Point"}
}