{
  "type": "Feature",
  "properties": {
    "gn:admin1_code":"02",
    "gn:asciiname":"Cascaron",
    "gn:country_code":"VE",
    "gn:dem":162,
    "gn:feature_class":"P",
    "gn:feature_code":"PPLL",
    "gn:name":"Cascar\u00f3n",
    "gn:population":0,
    "gn:timezone":"America/Caracas",
    "iso:country":"VE",
    "wof:name":"Cascaron",
    "wof:placetype":"locality"
},
  "geometry": {"coordinates":[-64.61247,9.32639],"type":"Point"}
}