{
  "type": "Feature",
  "properties": {
    "gn:admin1_code":"16.0",
    "gn:asciiname":"El Cambur",
    "gn:country_code":"VE",
    "gn:dem":1074,
    "gn:feature_class":"P",
    "gn:feature_code":"PPL",
    "gn:name":"El Cambur",
    "gn:population":0,
    "gn:timezone":"America/Caracas",
    "iso:country":"VE",
    "wof:name":"El Cambur",
    "wof:placetype":"locality"
},
  "geometry": {"coordinates":[-63.71665,10.19139],"type":"Point"}
}