{
  "type": "Feature",
  "properties": {
    "gn:admin1_code":"16.0",
    "gn:asciiname":"Los Horconcitos",
    "gn:country_code":"VE",
    "gn:dem":728,
    "gn:feature_class":"P",
    "gn:feature_code":"PPL",
    "gn:name":"Los Horconcitos",
    "gn:population":0,
    "gn:timezone":"America/Caracas",
    "iso:country":"VE",
    "wof:name":"Los Horconcitos",
    "wof:placetype":"locality"
},
  "geometry": {"coordinates":[-63.80941,10.01344],"type":"Point"}
}