{
  "type": "Feature",
  "properties": {
    "gn:admin1_code":"03",
    "gn:asciiname":"Santa Amelia",
    "gn:country_code":"VE",
    "gn:dem":93,
    "gn:feature_class":"P",
    "gn:feature_code":"PPL",
    "gn:name":"Santa Amelia",
    "gn:population":0,
    "gn:timezone":"America/Caracas",
    "iso:country":"VE",
    "wof:name":"Santa Amelia",
    "wof:placetype":"locality"
},
  "geometry": {"coordinates":[-69.56560999999999,7.17709],"type":"Point"}
}