{
  "type": "Feature",
  "properties": {
    "gn:admin1_code":"18.0",
    "gn:asciiname":"La Hoyada",
    "gn:country_code":"VE",
    "gn:dem":186,
    "gn:feature_class":"P",
    "gn:feature_code":"PPL",
    "gn:name":"La Hoyada",
    "gn:population":0,
    "gn:timezone":"America/Caracas",
    "iso:country":"VE",
    "name:ceb_x_preferred":[
        "La Hoyada"
    ],
    "name:spa_x_preferred":[
        "La Hoyada"
    ],
    "name:swe_x_preferred":[
        "La Hoyada"
    ],
    "name:urd_x_preferred":[
        "\u0644\u0627 \u06c1\u0648\u06cc\u0627\u0688\u0627"
    ],
    "wof:name":"La Hoyada",
    "wof:placetype":"locality"
},
  "geometry": {"coordinates":[-69.54924,9.25205],"type":"Point"}
}