{
  "type": "Feature",
  "properties": {
    "gn:admin1_code":"11",
    "gn:asciiname":"Los Cardones",
    "gn:country_code":"VE",
    "gn:dem":745,
    "gn:feature_class":"P",
    "gn:feature_code":"PPL",
    "gn:name":"Los Cardones",
    "gn:population":0,
    "gn:timezone":"America/Caracas",
    "iso:country":"VE",
    "wof:name":"Los Cardones",
    "wof:placetype":"locality"
},
  "geometry": {"coordinates":[-69.30249999999999,10.85809],"type":"Point"}
}