{
  "type": "Feature",
  "properties": {
    "gn:admin1_code":"2",
    "gn:asciiname":"El Penado",
    "gn:country_code":"VE",
    "gn:dem":158,
    "gn:feature_class":"P",
    "gn:feature_code":"PPL",
    "gn:name":"El Penado",
    "gn:population":0,
    "gn:timezone":"America/Caracas",
    "iso:country":"VE",
    "wof:name":"El Penado",
    "wof:placetype":"locality"
},
  "geometry": {"coordinates":[-64.59999999999999,9.36667],"type":"Point"}
}