{
  "type": "Feature",
  "properties": {
    "gn:admin1_code":"2",
    "gn:asciiname":"Cabeza de Tigre",
    "gn:country_code":"VE",
    "gn:dem":174,
    "gn:feature_class":"P",
    "gn:feature_code":"PPL",
    "gn:name":"Cabeza de Tigre",
    "gn:population":0,
    "gn:timezone":"America/Caracas",
    "iso:country":"VE",
    "wof:name":"Cabeza de Tigre",
    "wof:placetype":"locality"
},
  "geometry": {"coordinates":[-64.64751,9.57269],"type":"Point"}
}