{
  "type": "Feature",
  "properties": {
    "gn:admin1_code":"6.0",
    "gn:asciiname":"Los Arrendajos",
    "gn:country_code":"VE",
    "gn:dem":39,
    "gn:feature_class":"P",
    "gn:feature_code":"PPL",
    "gn:name":"Los Arrendajos",
    "gn:population":0,
    "gn:timezone":"America/Caracas",
    "iso:country":"VE",
    "wof:name":"Los Arrendajos",
    "wof:placetype":"locality"
},
  "geometry": {"coordinates":[-66.07935999999999,7.65226],"type":"Point"}
}