{
  "type": "Feature",
  "properties": {
    "gn:admin1_code":"11",
    "gn:asciiname":"Pilancon",
    "gn:cc2":"VE",
    "gn:country_code":"VE",
    "gn:dem":165,
    "gn:feature_class":"P",
    "gn:feature_code":"PPL",
    "gn:name":"Pilanc\u00f3n",
    "gn:population":0,
    "gn:timezone":"America/Caracas",
    "iso:country":"VE",
    "name:und_x_variant":[
        "Filancones",
        "Pilancones",
        "Pilanc\u00f3n"
    ],
    "wof:name":"Pilancon",
    "wof:placetype":"locality"
},
  "geometry": {"coordinates":[-69.13333,11.35],"type":"Point"}
}