{
  "type": "Feature",
  "properties": {
    "gn:admin1_code":"2",
    "gn:asciiname":"El Pinal",
    "gn:country_code":"VE",
    "gn:dem":212,
    "gn:feature_class":"P",
    "gn:feature_code":"PPL",
    "gn:name":"El Pi\u00f1al",
    "gn:population":0,
    "gn:timezone":"America/Caracas",
    "iso:country":"VE",
    "wof:name":"El Pinal",
    "wof:placetype":"locality"
},
  "geometry": {"coordinates":[-63.98111,8.85194],"type":"Point"}
}