{
  "type": "Feature",
  "properties": {
    "gn:admin1_code":"2",
    "gn:asciiname":"Morenero",
    "gn:cc2":"VE",
    "gn:country_code":"VE",
    "gn:dem":48,
    "gn:feature_class":"P",
    "gn:feature_code":"PPL",
    "gn:name":"Morenero",
    "gn:population":0,
    "gn:timezone":"America/Caracas",
    "iso:country":"VE",
    "name:und_x_variant":[
        "Moreno",
        "Morenero"
    ],
    "wof:name":"Morenero",
    "wof:placetype":"locality"
},
  "geometry": {"coordinates":[-62.93333000000001,8.78333],"type":"Point"}
}