{
  "type": "Feature",
  "properties": {
    "gn:admin1_code":"1",
    "gn:asciiname":"Barranco Blanco",
    "gn:country_code":"VE",
    "gn:dem":95,
    "gn:feature_class":"P",
    "gn:feature_code":"PPL",
    "gn:name":"Barranco Blanco",
    "gn:population":0,
    "gn:timezone":"America/Caracas",
    "iso:country":"VE",
    "wof:name":"Barranco Blanco",
    "wof:placetype":"locality"
},
  "geometry": {"coordinates":[-67.67685999999999,4.92479],"type":"Point"}
}