{
  "type": "Feature",
  "properties": {
    "gn:admin1_code":"4",
    "gn:asciiname":"Macuayita",
    "gn:country_code":"VE",
    "gn:dem":591,
    "gn:feature_class":"P",
    "gn:feature_code":"PPL",
    "gn:name":"Macuayita",
    "gn:population":0,
    "gn:timezone":"America/Caracas",
    "iso:country":"VE",
    "wof:name":"Macuayita",
    "wof:placetype":"locality"
},
  "geometry": {"coordinates":[-67.29784000000001,10.23678],"type":"Point"}
}