{
  "type": "Feature",
  "properties": {
    "gn:admin1_code":"23.0",
    "gn:asciiname":"Ave Maria",
    "gn:country_code":"VE",
    "gn:dem":82,
    "gn:feature_class":"P",
    "gn:feature_code":"PPLL",
    "gn:name":"Ave Maria",
    "gn:population":0,
    "gn:timezone":"America/Caracas",
    "iso:country":"VE",
    "wof:name":"Ave Maria",
    "wof:placetype":"locality"
},
  "geometry": {"coordinates":[-71.86312,10.62944],"type":"Point"}
}