{
  "type": "Feature",
  "properties": {
    "gn:admin1_code":"13",
    "gn:asciiname":"Las Veras",
    "gn:country_code":"VE",
    "gn:dem":728,
    "gn:feature_class":"P",
    "gn:feature_code":"PPL",
    "gn:name":"Las Veras",
    "gn:population":0,
    "gn:timezone":"America/Caracas",
    "iso:country":"VE",
    "wof:name":"Las Veras",
    "wof:placetype":"locality"
},
  "geometry": {"coordinates":[-69.47790000000001,10.13183],"type":"Point"}
}