{
  "type": "Feature",
  "properties": {
    "gn:admin1_code":"13",
    "gn:asciiname":"Copeyal",
    "gn:country_code":"VE",
    "gn:dem":667,
    "gn:feature_class":"P",
    "gn:feature_code":"PPL",
    "gn:name":"Copeyal",
    "gn:population":0,
    "gn:timezone":"America/Caracas",
    "iso:country":"VE",
    "wof:name":"Copeyal",
    "wof:placetype":"locality"
},
  "geometry": {"coordinates":[-69.44988000000001,10.43909],"type":"Point"}
}