{
  "type": "Feature",
  "properties": {
    "gn:admin1_code":"6.0",
    "gn:asciiname":"Aceitico",
    "gn:country_code":"VE",
    "gn:dem":60,
    "gn:feature_class":"P",
    "gn:feature_code":"PPL",
    "gn:name":"Aceitico",
    "gn:population":0,
    "gn:timezone":"America/Caracas",
    "iso:country":"VE",
    "wof:name":"Aceitico",
    "wof:placetype":"locality"
},
  "geometry": {"coordinates":[-66.98154,6.56738],"type":"Point"}
}