{
  "type": "Feature",
  "properties": {
    "gn:admin1_code":"16.0",
    "gn:asciiname":"Pardillar Abajo",
    "gn:country_code":"VE",
    "gn:dem":830,
    "gn:feature_class":"P",
    "gn:feature_code":"PPL",
    "gn:name":"Pardillar Abajo",
    "gn:population":0,
    "gn:timezone":"America/Caracas",
    "iso:country":"VE",
    "wof:name":"Pardillar Abajo",
    "wof:placetype":"locality"
},
  "geometry": {"coordinates":[-63.63618,10.05867],"type":"Point"}
}