{
  "type": "Feature",
  "properties": {
    "gn:admin1_code":"19",
    "gn:asciiname":"Las Puertas",
    "gn:country_code":"VE",
    "gn:dem":678,
    "gn:feature_class":"P",
    "gn:feature_code":"PPL",
    "gn:name":"Las Puertas",
    "gn:population":0,
    "gn:timezone":"America/Caracas",
    "iso:country":"VE",
    "wof:name":"Las Puertas",
    "wof:placetype":"locality"
},
  "geometry": {"coordinates":[-64.51666999999999,10.21667],"type":"Point"}
}