{
  "type": "Feature",
  "properties": {
    "gn:admin1_code":"19.0",
    "gn:asciiname":"La Guaima",
    "gn:country_code":"VE",
    "gn:dem":401,
    "gn:feature_class":"P",
    "gn:feature_code":"PPL",
    "gn:name":"La Guaima",
    "gn:population":0,
    "gn:timezone":"America/Caracas",
    "iso:country":"VE",
    "wof:name":"La Guaima",
    "wof:placetype":"locality"
},
  "geometry": {"coordinates":[-63.13056,10.63611],"type":"Point"}
}