{
  "type": "Feature",
  "properties": {
    "gn:admin1_code":"23.0",
    "gn:asciiname":"Totumito",
    "gn:country_code":"VE",
    "gn:dem":9,
    "gn:feature_class":"P",
    "gn:feature_code":"PPLL",
    "gn:name":"Totumito",
    "gn:population":0,
    "gn:timezone":"America/Caracas",
    "iso:country":"VE",
    "wof:name":"Totumito",
    "wof:placetype":"locality"
},
  "geometry": {"coordinates":[-71.77128,10.4037],"type":"Point"}
}