{
  "type": "Feature",
  "properties": {
    "gn:admin1_code":"21",
    "gn:asciiname":"Media Loma",
    "gn:country_code":"VE",
    "gn:dem":2441,
    "gn:feature_class":"P",
    "gn:feature_code":"PPL",
    "gn:name":"Media Loma",
    "gn:population":0,
    "gn:timezone":"America/Caracas",
    "iso:country":"VE",
    "wof:name":"Media Loma",
    "wof:placetype":"locality"
},
  "geometry": {"coordinates":[-70.73831,9.10826],"type":"Point"}
}