{
  "type": "Feature",
  "properties": {
    "gn:admin1_code":"2",
    "gn:asciiname":"El Tigre",
    "gn:country_code":"VE",
    "gn:dem":43,
    "gn:feature_class":"P",
    "gn:feature_code":"PPL",
    "gn:name":"El Tigre",
    "gn:population":0,
    "gn:timezone":"America/Caracas",
    "iso:country":"VE",
    "wof:name":"El Tigre",
    "wof:placetype":"locality"
},
  "geometry": {"coordinates":[-65.08875,9.92508],"type":"Point"}
}