{
  "type": "Feature",
  "properties": {
    "gn:admin1_code":"5.0",
    "gn:asciiname":"Agua",
    "gn:country_code":"VE",
    "gn:dem":383,
    "gn:feature_class":"P",
    "gn:feature_code":"PPL",
    "gn:name":"Agua",
    "gn:population":0,
    "gn:timezone":"America/Caracas",
    "iso:country":"VE",
    "wof:name":"Agua",
    "wof:placetype":"locality"
},
  "geometry": {"coordinates":[-70.34576,8.73551],"type":"Point"}
}