{
  "type": "Feature",
  "properties": {
    "gn:admin1_code":"13",
    "gn:asciiname":"Copaya",
    "gn:cc2":"VE",
    "gn:country_code":"VE",
    "gn:dem":280,
    "gn:feature_class":"P",
    "gn:feature_code":"PPL",
    "gn:name":"Copaya",
    "gn:population":0,
    "gn:timezone":"America/Caracas",
    "iso:country":"VE",
    "name:und_x_variant":[
        "Capaya",
        "Copama",
        "Copaya"
    ],
    "wof:name":"Copaya",
    "wof:placetype":"locality"
},
  "geometry": {"coordinates":[-69.75,10.56667],"type":"Point"}
}