{
  "type": "Feature",
  "properties": {
    "gn:admin1_code":"13",
    "gn:asciiname":"Tierra Negra",
    "gn:country_code":"VE",
    "gn:dem":773,
    "gn:feature_class":"P",
    "gn:feature_code":"PPL",
    "gn:name":"Tierra Negra",
    "gn:population":0,
    "gn:timezone":"America/Caracas",
    "iso:country":"VE",
    "wof:name":"Tierra Negra",
    "wof:placetype":"locality"
},
  "geometry": {"coordinates":[-69.36948000000001,10.39988],"type":"Point"}
}