{
  "type": "Feature",
  "properties": {
    "gn:admin1_code":"5",
    "gn:asciiname":"Pena Larga",
    "gn:country_code":"VE",
    "gn:dem":259,
    "gn:feature_class":"P",
    "gn:feature_code":"PPL",
    "gn:name":"Pe\u00f1a Larga",
    "gn:population":0,
    "gn:timezone":"America/Caracas",
    "iso:country":"VE",
    "wof:name":"Pena Larga",
    "wof:placetype":"locality"
},
  "geometry": {"coordinates":[-70.04665,8.89341],"type":"Point"}
}