{
  "type": "Feature",
  "properties": {
    "gn:admin1_code":"15",
    "gn:asciiname":"Perdomo",
    "gn:country_code":"VE",
    "gn:dem":11,
    "gn:feature_class":"P",
    "gn:feature_code":"PPL",
    "gn:name":"Perdomo",
    "gn:population":0,
    "gn:timezone":"America/Caracas",
    "iso:country":"VE",
    "name:deu_x_preferred":[
        "Perdomo"
    ],
    "name:fra_x_preferred":[
        "Perdomo"
    ],
    "name:nds_x_preferred":[
        "Perdomo"
    ],
    "name:pol_x_preferred":[
        "Perdomo"
    ],
    "name:rus_x_preferred":[
        "\u041f\u0435\u0440\u0434\u043e\u043c\u043e"
    ],
    "wof:name":"Perdomo",
    "wof:placetype":"locality"
},
  "geometry": {"coordinates":[-65.98419,10.27109],"type":"Point"}
}