{
  "type": "Feature",
  "properties": {
    "gn:admin1_code":"2",
    "gn:asciiname":"Limoncito",
    "gn:country_code":"VE",
    "gn:dem":121,
    "gn:feature_class":"P",
    "gn:feature_code":"PPL",
    "gn:name":"Limoncito",
    "gn:population":0,
    "gn:timezone":"America/Caracas",
    "iso:country":"VE",
    "wof:name":"Limoncito",
    "wof:placetype":"locality"
},
  "geometry": {"coordinates":[-64.82666999999999,9.5412],"type":"Point"}
}