{
  "type": "Feature",
  "properties": {
    "gn:admin1_code":"22",
    "gn:asciiname":"Pueblo Nuevo",
    "gn:country_code":"VE",
    "gn:dem":38,
    "gn:feature_class":"P",
    "gn:feature_code":"PPL",
    "gn:name":"Pueblo Nuevo",
    "gn:population":0,
    "gn:timezone":"America/Caracas",
    "iso:country":"VE",
    "wof:name":"Pueblo Nuevo",
    "wof:placetype":"locality"
},
  "geometry": {"coordinates":[-68.51328000000001,10.4232],"type":"Point"}
}