{
  "type": "Feature",
  "properties": {
    "gn:admin1_code":"3.0",
    "gn:asciiname":"Vuelta Mala",
    "gn:country_code":"VE",
    "gn:dem":60,
    "gn:feature_class":"P",
    "gn:feature_code":"PPL",
    "gn:name":"Vuelta Mala",
    "gn:population":0,
    "gn:timezone":"America/Caracas",
    "iso:country":"VE",
    "wof:name":"Vuelta Mala",
    "wof:placetype":"locality"
},
  "geometry": {"coordinates":[-67.91167,7.85611],"type":"Point"}
}