{
  "type": "Feature",
  "properties": {
    "gn:admin1_code":"5",
    "gn:asciiname":"Gavilan",
    "gn:country_code":"VE",
    "gn:dem":61,
    "gn:feature_class":"P",
    "gn:feature_code":"PPL",
    "gn:name":"Gavil\u00e1n",
    "gn:population":0,
    "gn:timezone":"America/Caracas",
    "iso:country":"VE",
    "name:ceb_x_preferred":[
        "Gavilan"
    ],
    "name:ita_x_preferred":[
        "Gavilan"
    ],
    "name:swe_x_preferred":[
        "Gavilan"
    ],
    "wof:name":"Gavilan",
    "wof:placetype":"locality"
},
  "geometry": {"coordinates":[-68.16667,8.48333],"type":"Point"}
}