{
  "type": "Feature",
  "properties": {
    "gn:admin1_code":"16",
    "gn:asciiname":"La Vigia",
    "gn:country_code":"VE",
    "gn:dem":91,
    "gn:feature_class":"P",
    "gn:feature_code":"PPL",
    "gn:name":"La Vig\u00eda",
    "gn:population":0,
    "gn:timezone":"America/Caracas",
    "iso:country":"VE",
    "wof:name":"La Vigia",
    "wof:placetype":"locality"
},
  "geometry": {"coordinates":[-63.32106,8.98139],"type":"Point"}
}