{
  "type": "Feature",
  "properties": {
    "gn:admin1_code":"19.0",
    "gn:asciiname":"Potrerito",
    "gn:country_code":"VE",
    "gn:dem":370,
    "gn:feature_class":"P",
    "gn:feature_code":"PPL",
    "gn:name":"Potrerito",
    "gn:population":0,
    "gn:timezone":"America/Caracas",
    "iso:country":"VE",
    "wof:name":"Potrerito",
    "wof:placetype":"locality"
},
  "geometry": {"coordinates":[-63.58121,10.31766],"type":"Point"}
}