{
  "type": "Feature",
  "properties": {
    "gn:admin1_code":"14",
    "gn:asciiname":"Mocotone",
    "gn:country_code":"VE",
    "gn:dem":2357,
    "gn:feature_class":"P",
    "gn:feature_code":"PPL",
    "gn:name":"Mocotone",
    "gn:population":0,
    "gn:timezone":"America/Caracas",
    "iso:country":"VE",
    "wof:name":"Mocotone",
    "wof:placetype":"locality"
},
  "geometry": {"coordinates":[-71.20836,8.48581],"type":"Point"}
}