{
  "type": "Feature",
  "properties": {
    "gn:admin1_code":"2",
    "gn:asciiname":"Montero",
    "gn:country_code":"VE",
    "gn:dem":56,
    "gn:feature_class":"P",
    "gn:feature_code":"PPL",
    "gn:name":"Montero",
    "gn:population":0,
    "gn:timezone":"America/Caracas",
    "iso:country":"VE",
    "wof:name":"Montero",
    "wof:placetype":"locality"
},
  "geometry": {"coordinates":[-65.20228,9.36545],"type":"Point"}
}