{
  "type": "Feature",
  "properties": {
    "gn:admin1_code":"03",
    "gn:asciiname":"San Felipe",
    "gn:country_code":"VE",
    "gn:dem":95,
    "gn:feature_class":"P",
    "gn:feature_code":"PPL",
    "gn:name":"San Felipe",
    "gn:population":0,
    "gn:timezone":"America/Caracas",
    "iso:country":"VE",
    "wof:name":"San Felipe",
    "wof:placetype":"locality"
},
  "geometry": {"coordinates":[-69.71666999999999,6.88333],"type":"Point"}
}