{
  "type": "Feature",
  "properties": {
    "gn:admin1_code":"12.0",
    "gn:asciiname":"Alto Los Barbascos",
    "gn:country_code":"VE",
    "gn:dem":124,
    "gn:feature_class":"P",
    "gn:feature_code":"PPLL",
    "gn:name":"Alto Los Barbascos",
    "gn:population":0,
    "gn:timezone":"America/Caracas",
    "iso:country":"VE",
    "wof:name":"Alto Los Barbascos",
    "wof:placetype":"locality"
},
  "geometry": {"coordinates":[-65.67449999999999,8.89733],"type":"Point"}
}