{
  "type": "Feature",
  "properties": {
    "gn:admin1_code":"19.0",
    "gn:asciiname":"El Trancadero",
    "gn:country_code":"VE",
    "gn:dem":672,
    "gn:feature_class":"P",
    "gn:feature_code":"PPLL",
    "gn:name":"El Trancadero",
    "gn:population":0,
    "gn:timezone":"America/Caracas",
    "iso:country":"VE",
    "wof:name":"El Trancadero",
    "wof:placetype":"locality"
},
  "geometry": {"coordinates":[-63.57104,10.27195],"type":"Point"}
}