{
  "type": "Feature",
  "properties": {
    "gn:admin1_code":"2",
    "gn:asciiname":"Cantarrana",
    "gn:country_code":"VE",
    "gn:dem":185,
    "gn:feature_class":"P",
    "gn:feature_code":"PPL",
    "gn:name":"Cantarrana",
    "gn:population":0,
    "gn:timezone":"America/Caracas",
    "iso:country":"VE",
    "wof:name":"Cantarrana",
    "wof:placetype":"locality"
},
  "geometry": {"coordinates":[-64.64754000000001,9.14033],"type":"Point"}
}