{
  "type": "Feature",
  "properties": {
    "gn:admin1_code":"12",
    "gn:asciiname":"La Fila",
    "gn:country_code":"VE",
    "gn:dem":189,
    "gn:feature_class":"P",
    "gn:feature_code":"PPL",
    "gn:name":"La Fila",
    "gn:population":0,
    "gn:timezone":"America/Caracas",
    "iso:country":"VE",
    "wof:name":"La Fila",
    "wof:placetype":"locality"
},
  "geometry": {"coordinates":[-65.83426999999999,8.87079],"type":"Point"}
}