{
  "type": "Feature",
  "properties": {
    "gn:admin1_code":"11",
    "gn:asciiname":"Tocomoro",
    "gn:country_code":"VE",
    "gn:dem":215,
    "gn:feature_class":"P",
    "gn:feature_code":"PPL",
    "gn:name":"Tocomoro",
    "gn:population":0,
    "gn:timezone":"America/Caracas",
    "iso:country":"VE",
    "wof:name":"Tocomoro",
    "wof:placetype":"locality"
},
  "geometry": {"coordinates":[-69.47444,10.98389],"type":"Point"}
}