{
  "type": "Feature",
  "properties": {
    "gn:admin1_code":"13",
    "gn:asciiname":"Rio Arriba",
    "gn:country_code":"VE",
    "gn:dem":884,
    "gn:feature_class":"P",
    "gn:feature_code":"PPL",
    "gn:name":"R\u00edo Arriba",
    "gn:population":0,
    "gn:timezone":"America/Caracas",
    "iso:country":"VE",
    "wof:name":"Rio Arriba",
    "wof:placetype":"locality"
},
  "geometry": {"coordinates":[-69.03055999999999,10.21361],"type":"Point"}
}