{
  "type": "Feature",
  "properties": {
    "gn:admin1_code":"11.0",
    "gn:asciiname":"Conejalito",
    "gn:country_code":"VE",
    "gn:dem":66,
    "gn:feature_class":"P",
    "gn:feature_code":"PPL",
    "gn:name":"Conejalito",
    "gn:population":0,
    "gn:timezone":"America/Caracas",
    "iso:country":"VE",
    "wof:name":"Conejalito",
    "wof:placetype":"locality"
},
  "geometry": {"coordinates":[-69.93136,12.03901],"type":"Point"}
}