{
  "type": "Feature",
  "properties": {
    "gn:admin1_code":"11.0",
    "gn:asciiname":"Matividiro",
    "gn:country_code":"VE",
    "gn:dem":112,
    "gn:feature_class":"P",
    "gn:feature_code":"PPL",
    "gn:name":"Matividiro",
    "gn:population":0,
    "gn:timezone":"America/Caracas",
    "iso:country":"VE",
    "wof:name":"Matividiro",
    "wof:placetype":"locality"
},
  "geometry": {"coordinates":[-69.90496,11.85541],"type":"Point"}
}