{
  "type": "Feature",
  "properties": {
    "gn:admin1_code":"9",
    "gn:asciiname":"Palmito",
    "gn:country_code":"VE",
    "gn:dem":12,
    "gn:feature_class":"P",
    "gn:feature_code":"PPL",
    "gn:name":"Palmito",
    "gn:population":0,
    "gn:timezone":"America/Caracas",
    "iso:country":"VE",
    "wof:name":"Palmito",
    "wof:placetype":"locality"
},
  "geometry": {"coordinates":[-60.90583,8.7425],"type":"Point"}
}