{
  "type": "Feature",
  "properties": {
    "gn:admin1_code":"6.0",
    "gn:asciiname":"La Leona",
    "gn:country_code":"VE",
    "gn:dem":53,
    "gn:feature_class":"P",
    "gn:feature_code":"PPL",
    "gn:name":"La Leona",
    "gn:population":0,
    "gn:timezone":"America/Caracas",
    "iso:country":"VE",
    "name:ceb_x_preferred":[
        "La Leona"
    ],
    "name:spa_x_preferred":[
        "La leona"
    ],
    "name:srp_x_preferred":[
        "\u041b\u0430 \u041b\u0435\u043e\u043d\u0430"
    ],
    "name:swe_x_preferred":[
        "La Leona"
    ],
    "wof:name":"La Leona",
    "wof:placetype":"locality"
},
  "geometry": {"coordinates":[-65.69020999999999,7.59276],"type":"Point"}
}