{
  "type": "Feature",
  "properties": {
    "gn:admin1_code":"2",
    "gn:asciiname":"Zambrano",
    "gn:country_code":"VE",
    "gn:dem":275,
    "gn:feature_class":"P",
    "gn:feature_code":"PPL",
    "gn:name":"Zambrano",
    "gn:population":0,
    "gn:timezone":"America/Caracas",
    "iso:country":"VE",
    "name:srp_x_preferred":[
        "\u0417\u0430\u043c\u0431\u0440\u0430\u043d\u043e"
    ],
    "name:ukr_x_preferred":[
        "\u0421\u0430\u043c\u0431\u0440\u0430\u043d\u043e"
    ],
    "wof:name":"Zambrano",
    "wof:placetype":"locality"
},
  "geometry": {"coordinates":[-63.98737,9.58154],"type":"Point"}
}