{
  "type": "Feature",
  "properties": {
    "gn:admin1_code":"12",
    "gn:asciiname":"Parapara",
    "gn:country_code":"VE",
    "gn:dem":225,
    "gn:feature_class":"P",
    "gn:feature_code":"PPL",
    "gn:name":"Parapara",
    "gn:population":0,
    "gn:timezone":"America/Caracas",
    "iso:country":"VE",
    "name:ceb_x_preferred":[
        "Parapara"
    ],
    "name:deu_x_preferred":[
        "Parapara"
    ],
    "name:fra_x_preferred":[
        "Parapara"
    ],
    "wof:name":"Parapara",
    "wof:placetype":"locality"
},
  "geometry": {"coordinates":[-67.29151,9.70304],"type":"Point"}
}