{
  "type": "Feature",
  "properties": {
    "gn:admin1_code":"15.0",
    "gn:asciiname":"Los Flores",
    "gn:country_code":"VE",
    "gn:dem":358,
    "gn:feature_class":"P",
    "gn:feature_code":"PPLL",
    "gn:name":"Los Flores",
    "gn:population":0,
    "gn:timezone":"America/Caracas",
    "iso:country":"VE",
    "wof:name":"Los Flores",
    "wof:placetype":"locality"
},
  "geometry": {"coordinates":[-66.56668000000001,10.47061],"type":"Point"}
}