{
  "type": "Feature",
  "properties": {
    "gn:admin1_code":"11",
    "gn:asciiname":"Bocaina",
    "gn:country_code":"VE",
    "gn:dem":185,
    "gn:feature_class":"P",
    "gn:feature_code":"PPL",
    "gn:name":"Bocaina",
    "gn:population":0,
    "gn:timezone":"America/Caracas",
    "iso:country":"VE",
    "name:bpy_x_preferred":[
        "\u09ac\u09cb\u0995\u09be\u0987\u09a8\u09be"
    ],
    "name:ceb_x_preferred":[
        "Bocaina"
    ],
    "name:epo_x_preferred":[
        "Bocaina"
    ],
    "name:eus_x_preferred":[
        "Bocaina"
    ],
    "name:fra_x_preferred":[
        "Bocaina"
    ],
    "name:ita_x_preferred":[
        "Bocaina"
    ],
    "name:kaz_x_preferred":[
        "\u0411\u043e\u043a\u0430\u0439\u043d\u0430"
    ],
    "name:mlg_x_preferred":[
        "Bocaina"
    ],
    "name:nld_x_preferred":[
        "Bocaina"
    ],
    "name:nor_x_preferred":[
        "Bocaina"
    ],
    "name:pol_x_preferred":[
        "Bocaina"
    ],
    "name:por_x_preferred":[
        "Bocaina"
    ],
    "name:ron_x_preferred":[
        "Bocaina"
    ],
    "name:rus_x_preferred":[
        "\u0411\u043e\u043a\u0430\u0439\u043d\u0430"
    ],
    "name:vie_x_preferred":[
        "Bocaina"
    ],
    "name:vol_x_preferred":[
        "Bocaina"
    ],
    "name:war_x_preferred":[
        "Bocaina"
    ],
    "name:zho_x_preferred":[
        "\u535a\u51f1\u7d0d"
    ],
    "wof:name":"Bocaina",
    "wof:placetype":"locality"
},
  "geometry": {"coordinates":[-69.84350000000001,10.97495],"type":"Point"}
}