{
  "type": "Feature",
  "properties": {
    "gn:admin1_code":"11",
    "gn:asciiname":"Bocaina",
    "gn:country_code":"VE",
    "gn:dem":185,
    "gn:feature_class":"P",
    "gn:feature_code":"PPL",
    "gn:name":"Bocaina",
    "gn:population":0,
    "gn:timezone":"America/Caracas",
    "iso:country":"VE",
    "wof:name":"Bocaina",
    "wof:placetype":"locality"
},
  "geometry": {"coordinates":[-69.84350000000001,10.97495],"type":"Point"}
}