{
  "type": "Feature",
  "properties": {
    "gn:admin1_code":"19.0",
    "gn:asciiname":"Maturincito",
    "gn:country_code":"VE",
    "gn:dem":475,
    "gn:feature_class":"P",
    "gn:feature_code":"PPLL",
    "gn:name":"Maturincito",
    "gn:population":0,
    "gn:timezone":"America/Caracas",
    "iso:country":"VE",
    "wof:name":"Maturincito",
    "wof:placetype":"locality"
},
  "geometry": {"coordinates":[-64.35035999999999,10.26467],"type":"Point"}
}