{
  "type": "Feature",
  "properties": {
    "gn:admin1_code":"02",
    "gn:asciiname":"El Vasquero",
    "gn:country_code":"VE",
    "gn:dem":33,
    "gn:feature_class":"P",
    "gn:feature_code":"PPL",
    "gn:name":"El Vasquero",
    "gn:population":0,
    "gn:timezone":"America/Caracas",
    "iso:country":"VE",
    "wof:name":"El Vasquero",
    "wof:placetype":"locality"
},
  "geometry": {"coordinates":[-65.06078000000001,9.75653],"type":"Point"}
}