{
  "type": "Feature",
  "properties": {
    "gn:admin1_code":"11",
    "gn:admin2_code":"1103.0",
    "gn:asciiname":"Canape Capatarida",
    "gn:country_code":"VE",
    "gn:dem":32,
    "gn:feature_class":"P",
    "gn:feature_code":"PPLA2",
    "gn:name":"Canape Capat\u00e1rida",
    "gn:population":0,
    "gn:timezone":"America/Caracas",
    "iso:country":"VE",
    "wof:name":"Canape Capatarida",
    "wof:placetype":"locality"
},
  "geometry": {"coordinates":[-70.62071999999998,11.1755],"type":"Point"}
}