{
  "type": "Feature",
  "properties": {
    "gn:admin1_code":"12",
    "gn:asciiname":"Piritu",
    "gn:cc2":"VE",
    "gn:country_code":"VE",
    "gn:dem":81,
    "gn:feature_class":"P",
    "gn:feature_code":"PPL",
    "gn:name":"P\u00edritu",
    "gn:population":0,
    "gn:timezone":"America/Caracas",
    "iso:country":"VE",
    "name:und_x_variant":[
        "Hato Pirito",
        "P\u00edritu"
    ],
    "wof:name":"Piritu",
    "wof:placetype":"locality"
},
  "geometry": {"coordinates":[-67.38333,8.75],"type":"Point"}
}