{
  "type": "Feature",
  "properties": {
    "gn:admin1_code":"11",
    "gn:asciiname":"Cabeceras",
    "gn:country_code":"VE",
    "gn:dem":88,
    "gn:feature_class":"P",
    "gn:feature_code":"PPL",
    "gn:name":"Cabeceras",
    "gn:population":0,
    "gn:timezone":"America/Caracas",
    "iso:country":"VE",
    "name:fas_x_preferred":[
        "\u06a9\u0627\u0628\u062b\u0631\u0627\u0633"
    ],
    "name:sco_x_preferred":[
        "Cabeceras"
    ],
    "wof:name":"Cabeceras",
    "wof:placetype":"locality"
},
  "geometry": {"coordinates":[-70.15623000000001,11.24699],"type":"Point"}
}