{
  "type": "Feature",
  "properties": {
    "iso:country":"VE",
    "name:eng_x_preferred":[
        "El Dorado"
    ],
    "name:jpn_x_preferred":[
        "\u30a8\u30eb\u30fb\u30c9\u30e9\u30c9"
    ],
    "name:lit_x_preferred":[
        "El Doradas"
    ],
    "name:spa_x_preferred":[
        "El Dorado"
    ],
    "name:zho_x_preferred":[
        "\u57c3\u723e\u591a\u62c9\u591a"
    ],
    "ne:ADM0CAP":0.0,
    "ne:ADM0NAME":"Venezuela",
    "ne:ADM0_A3":"VEN",
    "ne:ADM1NAME":"Bol",
    "ne:ADMIN1_COD":0,
    "ne:CAPALT":0,
    "ne:CHANGED":1,
    "ne:CHECKME":0,
    "ne:COMPARE":0,
    "ne:DIFFASCII":0,
    "ne:DIFFNOTE":"Changed scale rank.",
    "ne:ELEVATION":0.0,
    "ne:FEATURECLA":"Populated place",
    "ne:GEONAMEID":-1,
    "ne:GEONAMESNO":"No GeoNames match due to small population, not in GeoNames, or poor NEV placement.",
    "ne:GN_POP":0,
    "ne:GTOPO30":0.0,
    "ne:ISO_A2":"VE",
    "ne:LABELRANK":6,
    "ne:LATITUDE":6.733296,
    "ne:LONGITUDE":-61.633329,
    "ne:LS_MATCH":1,
    "ne:LS_NAME":"El Dorado2",
    "ne:MAX_AREAKM":3.0,
    "ne:MAX_AREAMI":1.0,
    "ne:MAX_BBXMAX":-61.625,
    "ne:MAX_BBXMIN":-61.641667,
    "ne:MAX_BBYMAX":6.725,
    "ne:MAX_BBYMIN":6.708333,
    "ne:MAX_NATSCA":20.0,
    "ne:MAX_PERKM":7.0,
    "ne:MAX_PERMI":5.0,
    "ne:MAX_POP10":2383,
    "ne:MAX_POP20":2383,
    "ne:MAX_POP300":0,
    "ne:MAX_POP310":0,
    "ne:MAX_POP50":0,
    "ne:MEAN_BBXC":-61.634722,
    "ne:MEAN_BBYC":6.715278,
    "ne:MEGACITY":0,
    "ne:MIN_AREAKM":3.0,
    "ne:MIN_AREAMI":1.0,
    "ne:MIN_BBXMAX":-61.625,
    "ne:MIN_BBXMIN":-61.641667,
    "ne:MIN_BBYMAX":6.725,
    "ne:MIN_BBYMIN":6.708333,
    "ne:MIN_PERKM":7.0,
    "ne:MIN_PERMI":5.0,
    "ne:NAME":"El Dorado",
    "ne:NAMEASCII":"El Dorado",
    "ne:NAMEDIFF":0,
    "ne:NATSCALE":30,
    "ne:POP1950":0,
    "ne:POP1955":0,
    "ne:POP1960":0,
    "ne:POP1965":0,
    "ne:POP1970":0,
    "ne:POP1975":0,
    "ne:POP1980":0,
    "ne:POP1985":0,
    "ne:POP1990":0,
    "ne:POP1995":0,
    "ne:POP2000":0,
    "ne:POP2005":0,
    "ne:POP2010":0,
    "ne:POP2015":0,
    "ne:POP2020":0,
    "ne:POP2025":0,
    "ne:POP2050":0,
    "ne:POP_MAX":2383,
    "ne:POP_MIN":2383,
    "ne:POP_OTHER":22262,
    "ne:RANK_MAX":4,
    "ne:RANK_MIN":4,
    "ne:SCALERANK":6,
    "ne:SOV0NAME":"Venezuela",
    "ne:SOV_A3":"VEN",
    "ne:UN_FID":0,
    "ne:UN_LAT":0.0,
    "ne:UN_LONG":0.0,
    "ne:WORLDCITY":0,
    "ne:min_zoom":6.0,
    "wof:name":"El Dorado",
    "wof:placetype":"locality"
},
  "geometry": {"coordinates":[-61.63332869632262,6.73329571423614],"type":"Point"}
}