{
  "type": "Feature",
  "properties": {
    "gn:admin1_code":"19",
    "gn:asciiname":"La Parisma",
    "gn:country_code":"VE",
    "gn:dem":273,
    "gn:feature_class":"P",
    "gn:feature_code":"PPL",
    "gn:name":"La Parisma",
    "gn:population":0,
    "gn:timezone":"America/Caracas",
    "iso:country":"VE",
    "wof:name":"La Parisma",
    "wof:placetype":"locality"
},
  "geometry": {"coordinates":[-63.98396999999999,10.3766],"type":"Point"}
}