{
  "type": "Feature",
  "properties": {
    "gn:admin1_code":"6",
    "gn:asciiname":"Los Garzones",
    "gn:country_code":"VE",
    "gn:dem":47,
    "gn:feature_class":"P",
    "gn:feature_code":"PPL",
    "gn:name":"Los Garzones",
    "gn:population":0,
    "gn:timezone":"America/Caracas",
    "iso:country":"VE",
    "name:und_x_variant":[
        "Los Carzones",
        "Los Corazonas",
        "Los Corazones",
        "Los Garzones"
    ],
    "wof:name":"Los Garzones",
    "wof:placetype":"locality"
},
  "geometry": {"coordinates":[-67.00071,6.80773],"type":"Point"}
}