{
  "type": "Feature",
  "properties": {
    "gn:admin1_code":"12.0",
    "gn:asciiname":"Santa Ines",
    "gn:country_code":"VE",
    "gn:dem":114,
    "gn:feature_class":"P",
    "gn:feature_code":"PPLL",
    "gn:name":"Santa In\u00e9s",
    "gn:population":0,
    "gn:timezone":"America/Caracas",
    "iso:country":"VE",
    "wof:name":"Santa Ines",
    "wof:placetype":"locality"
},
  "geometry": {"coordinates":[-65.90713000000001,9.37457],"type":"Point"}
}