{
  "type": "Feature",
  "properties": {
    "gn:admin1_code":"11",
    "gn:asciiname":"La Jagua",
    "gn:country_code":"VE",
    "gn:dem":77,
    "gn:feature_class":"P",
    "gn:feature_code":"PPL",
    "gn:name":"La Jagua",
    "gn:population":0,
    "gn:timezone":"America/Caracas",
    "iso:country":"VE",
    "wof:name":"La Jagua",
    "wof:placetype":"locality"
},
  "geometry": {"coordinates":[-70.72234,11.00709],"type":"Point"}
}