{
  "type": "Feature",
  "properties": {
    "gn:admin1_code":"19.0",
    "gn:asciiname":"Bucaral",
    "gn:country_code":"VE",
    "gn:dem":940,
    "gn:feature_class":"P",
    "gn:feature_code":"PPL",
    "gn:name":"Bucaral",
    "gn:population":0,
    "gn:timezone":"America/Caracas",
    "iso:country":"VE",
    "wof:name":"Bucaral",
    "wof:placetype":"locality"
},
  "geometry": {"coordinates":[-64.0543,10.1811],"type":"Point"}
}