{
  "type": "Feature",
  "properties": {
    "gn:admin1_code":"23",
    "gn:asciiname":"Bocachico",
    "gn:country_code":"VE",
    "gn:dem":103,
    "gn:feature_class":"P",
    "gn:feature_code":"PPL",
    "gn:name":"Bocachico",
    "gn:population":0,
    "gn:timezone":"America/Caracas",
    "iso:country":"VE",
    "wof:name":"Bocachico",
    "wof:placetype":"locality"
},
  "geometry": {"coordinates":[-72.515,10.0475],"type":"Point"}
}