{
  "type": "Feature",
  "properties": {
    "gn:admin1_code":"6",
    "gn:asciiname":"Kamarata",
    "gn:country_code":"VE",
    "gn:dem":472,
    "gn:feature_class":"P",
    "gn:feature_code":"PPL",
    "gn:name":"Kamarata",
    "gn:population":0,
    "gn:timezone":"America/Caracas",
    "iso:country":"VE",
    "name:eng_x_preferred":[
        "Kamarata"
    ],
    "name:spa_x_preferred":[
        "Kamarata"
    ],
    "wof:name":"Kamarata",
    "wof:placetype":"locality"
},
  "geometry": {"coordinates":[-62.34551999999999,5.71818],"type":"Point"}
}