{
  "type": "Feature",
  "properties": {
    "gn:admin1_code":"20",
    "gn:asciiname":"La Rochela",
    "gn:country_code":"VE",
    "gn:dem":1922,
    "gn:feature_class":"P",
    "gn:feature_code":"PPL",
    "gn:name":"La Rochela",
    "gn:population":0,
    "gn:timezone":"America/Caracas",
    "iso:country":"VE",
    "wof:name":"La Rochela",
    "wof:placetype":"locality"
},
  "geometry": {"coordinates":[-72.4363,7.57141],"type":"Point"}
}