{
  "type": "Feature",
  "properties": {
    "gn:admin1_code":"12",
    "gn:asciiname":"El Tabaco",
    "gn:country_code":"VE",
    "gn:dem":64,
    "gn:feature_class":"P",
    "gn:feature_code":"PPL",
    "gn:name":"El Tabaco",
    "gn:population":0,
    "gn:timezone":"America/Caracas",
    "iso:country":"VE",
    "wof:name":"El Tabaco",
    "wof:placetype":"locality"
},
  "geometry": {"coordinates":[-66.19764000000001,8.10677],"type":"Point"}
}