{
  "type": "Feature",
  "properties": {
    "gn:admin1_code":"11",
    "gn:asciiname":"La Goya",
    "gn:country_code":"VE",
    "gn:dem":480,
    "gn:feature_class":"P",
    "gn:feature_code":"PPL",
    "gn:name":"La Goya",
    "gn:population":0,
    "gn:timezone":"America/Caracas",
    "iso:country":"VE",
    "wof:name":"La Goya",
    "wof:placetype":"locality"
},
  "geometry": {"coordinates":[-69.70726999999999,10.99437],"type":"Point"}
}