{
  "type": "Feature",
  "properties": {
    "iso:country":"VE",
    "oa:elevation_ft":"804",
    "oa:type":"small_airport",
    "woe:hierarchy":{
        "country_id":23424982,
        "county_id":26804657,
        "localadmin_id":26805147,
        "planet_id":1,
        "state_id":2347692
    },
    "wof:name":"Santa Barbara de Monagas Airport",
    "wof:placetype":"campus"
},
  "geometry": {"coordinates":[-63.625322,9.702263],"type":"Point"}
}