{
  "type": "Feature",
  "properties": {
    "gn:admin1_code":"25",
    "gn:asciiname":"Palo Negro",
    "gn:country_code":"VE",
    "gn:dem":1097,
    "gn:feature_class":"P",
    "gn:feature_code":"PPL",
    "gn:name":"Palo Negro",
    "gn:population":0,
    "gn:timezone":"America/Caracas",
    "iso:country":"VE",
    "name:ceb_x_preferred":[
        "Palo Negro"
    ],
    "name:fra_x_preferred":[
        "Palo Negro"
    ],
    "name:swe_x_preferred":[
        "Palo Negro"
    ],
    "wof:name":"Palo Negro",
    "wof:placetype":"locality"
},
  "geometry": {"coordinates":[-67.06667,10.41667],"type":"Point"}
}