{
  "type": "Feature",
  "properties": {
    "gn:admin1_code":"13",
    "gn:asciiname":"El Mamoncito",
    "gn:country_code":"VE",
    "gn:dem":521,
    "gn:feature_class":"P",
    "gn:feature_code":"PPL",
    "gn:name":"El Mamoncito",
    "gn:population":0,
    "gn:timezone":"America/Caracas",
    "iso:country":"VE",
    "wof:name":"El Mamoncito",
    "wof:placetype":"locality"
},
  "geometry": {"coordinates":[-69.93791,10.65797],"type":"Point"}
}