{
  "type": "Feature",
  "properties": {
    "gn:admin1_code":"19",
    "gn:asciiname":"Guacarapo",
    "gn:country_code":"VE",
    "gn:dem":28,
    "gn:feature_class":"P",
    "gn:feature_code":"PPL",
    "gn:name":"Guacarapo",
    "gn:population":0,
    "gn:timezone":"America/Caracas",
    "iso:country":"VE",
    "wof:name":"Guacarapo",
    "wof:placetype":"locality"
},
  "geometry": {"coordinates":[-63.09836,10.30478],"type":"Point"}
}