{
  "type": "Feature",
  "properties": {
    "gn:admin1_code":"21",
    "gn:asciiname":"Las Delicias",
    "gn:country_code":"VE",
    "gn:dem":1498,
    "gn:feature_class":"P",
    "gn:feature_code":"PPLL",
    "gn:name":"Las Delicias",
    "gn:population":0,
    "gn:timezone":"America/Caracas",
    "iso:country":"VE",
    "name:ceb_x_preferred":[
        "Las Delicias"
    ],
    "name:ita_x_preferred":[
        "Las Delicias"
    ],
    "name:swe_x_preferred":[
        "Las Delicias"
    ],
    "wof:name":"Las Delicias",
    "wof:placetype":"locality"
},
  "geometry": {"coordinates":[-70.68810000000001,9.16264],"type":"Point"}
}