{
  "type": "Feature",
  "properties": {
    "gn:admin1_code":"6",
    "gn:asciiname":"Putari-paru-ta",
    "gn:country_code":"VE",
    "gn:dem":1016,
    "gn:feature_class":"P",
    "gn:feature_code":"PPL",
    "gn:name":"Putari-par\u00fa-ta",
    "gn:population":0,
    "gn:timezone":"America/Caracas",
    "iso:country":"VE",
    "wof:name":"Putari-paru-ta",
    "wof:placetype":"locality"
},
  "geometry": {"coordinates":[-61.01667,4.96667],"type":"Point"}
}