{
  "type": "Feature",
  "properties": {
    "gn:admin1_code":"6.0",
    "gn:asciiname":"Lucianera",
    "gn:country_code":"VE",
    "gn:dem":110,
    "gn:feature_class":"P",
    "gn:feature_code":"PPL",
    "gn:name":"Lucianera",
    "gn:population":0,
    "gn:timezone":"America/Caracas",
    "iso:country":"VE",
    "wof:name":"Lucianera",
    "wof:placetype":"locality"
},
  "geometry": {"coordinates":[-66.35974,7.26829],"type":"Point"}
}