{
  "type": "Feature",
  "properties": {
    "gn:admin1_code":"7",
    "gn:asciiname":"La Bartolera",
    "gn:country_code":"VE",
    "gn:dem":736,
    "gn:feature_class":"P",
    "gn:feature_code":"PPL",
    "gn:name":"La Bartolera",
    "gn:population":0,
    "gn:timezone":"America/Caracas",
    "iso:country":"VE",
    "wof:name":"La Bartolera",
    "wof:placetype":"locality"
},
  "geometry": {"coordinates":[-68.34014999999999,10.06937],"type":"Point"}
}