{
  "type": "Feature",
  "properties": {
    "gn:admin1_code":"12",
    "gn:asciiname":"Los Viborales",
    "gn:country_code":"VE",
    "gn:dem":147,
    "gn:feature_class":"P",
    "gn:feature_code":"PPL",
    "gn:name":"Los Viborales",
    "gn:population":0,
    "gn:timezone":"America/Caracas",
    "iso:country":"VE",
    "wof:name":"Los Viborales",
    "wof:placetype":"locality"
},
  "geometry": {"coordinates":[-66.1448,9.04046],"type":"Point"}
}