{
  "type": "Feature",
  "properties": {
    "gn:admin1_code":"13",
    "gn:asciiname":"El Portachuelo",
    "gn:country_code":"VE",
    "gn:dem":767,
    "gn:feature_class":"P",
    "gn:feature_code":"PPLL",
    "gn:name":"El Portachuelo",
    "gn:population":0,
    "gn:timezone":"America/Caracas",
    "iso:country":"VE",
    "wof:name":"El Portachuelo",
    "wof:placetype":"locality"
},
  "geometry": {"coordinates":[-69.73531,10.37187],"type":"Point"}
}