{
  "type": "Feature",
  "properties": {
    "gn:admin1_code":"12",
    "gn:asciiname":"La Torcida",
    "gn:country_code":"VE",
    "gn:dem":139,
    "gn:feature_class":"P",
    "gn:feature_code":"PPL",
    "gn:name":"La Torcida",
    "gn:population":0,
    "gn:timezone":"America/Caracas",
    "iso:country":"VE",
    "wof:name":"La Torcida",
    "wof:placetype":"locality"
},
  "geometry": {"coordinates":[-65.46861,8.62389],"type":"Point"}
}