{
  "type": "Feature",
  "properties": {
    "iso:country":"VE",
    "qs:gn_pop":0,
    "qs:name":"Matasiete",
    "qs:name_adm0":"Venezuela",
    "qs:name_adm1":"Nueva Esparta",
    "qs:photos":6,
    "qs:photos_1k":1,
    "qs:photos_9k":2,
    "qs:photos_9r":5,
    "qs:photos_all":442,
    "qs:photos_sr":1,
    "qs:placetype":"LocalAdmin",
    "qs:pop_sr":"0",
    "qs:woe_adm0":23424982,
    "wof:name":"Matasiete",
    "wof:placetype":"localadmin"
},
  "geometry": {"coordinates":[-63.939056,11.119083],"type":"Point"}
}