{
  "type": "Feature",
  "properties": {
    "gn:admin1_code":"11.0",
    "gn:asciiname":"Villa Marina",
    "gn:country_code":"VE",
    "gn:dem":4,
    "gn:feature_class":"P",
    "gn:feature_code":"PPL",
    "gn:name":"Villa Marina",
    "gn:population":0,
    "gn:timezone":"America/Caracas",
    "iso:country":"VE",
    "wof:name":"Villa Marina",
    "wof:placetype":"locality"
},
  "geometry": {"coordinates":[-70.27306,11.82528],"type":"Point"}
}