{
  "type": "Feature",
  "properties": {
    "gn:admin1_code":"3",
    "gn:asciiname":"Mata Azul de Tierra",
    "gn:country_code":"VE",
    "gn:dem":108,
    "gn:feature_class":"P",
    "gn:feature_code":"PPL",
    "gn:name":"Mata Azul de Tierra",
    "gn:population":0,
    "gn:timezone":"America/Caracas",
    "iso:country":"VE",
    "name:und_x_variant":[
        "Mata Azul",
        "Mata Azul de Tierra"
    ],
    "wof:name":"Mata Azul de Tierra",
    "wof:placetype":"locality"
},
  "geometry": {"coordinates":[-69.93473,7.00102],"type":"Point"}
}