{
  "type": "Feature",
  "properties": {
    "gn:admin1_code":"02",
    "gn:asciiname":"Boca de Cogollar",
    "gn:country_code":"VE",
    "gn:dem":70,
    "gn:feature_class":"P",
    "gn:feature_code":"PPLL",
    "gn:name":"Boca de Cogollar",
    "gn:population":0,
    "gn:timezone":"America/Caracas",
    "iso:country":"VE",
    "wof:name":"Boca de Cogollar",
    "wof:placetype":"locality"
},
  "geometry": {"coordinates":[-63.15301,8.63501],"type":"Point"}
}