{
  "type": "Feature",
  "properties": {
    "gn:country":"VE",
    "gn:fcode":"PPLA2",
    "gn:pop":89662,
    "iso:country":"VE",
    "name:ara_x_preferred":[
        "\u064a\u0627\u0631\u064a\u062a\u0627\u063a\u0648\u0627"
    ],
    "name:ben_x_preferred":[
        "\u0987\u09af\u09bc\u09be\u09b0\u09bf\u09a4\u09be\u0997\u09cb\u09af\u09bc\u09be"
    ],
    "name:chi_x_preferred":[
        "\u4e9e\u91cc\u5854\u74dc"
    ],
    "name:dan_x_preferred":[
        "Yaritagua"
    ],
    "name:dut_x_preferred":[
        "Yaritagua"
    ],
    "name:eng_x_preferred":[
        "Yaritagua"
    ],
    "name:fin_x_preferred":[
        "Yaritagua"
    ],
    "name:fre_x_preferred":[
        "Yaritagua"
    ],
    "name:ger_x_preferred":[
        "Yaritagua"
    ],
    "name:gre_x_preferred":[
        "\u0393\u03b9\u03b1\u03c1\u03b9\u03c4\u03ac\u03b3\u03ba\u03bf\u03c5\u03b1"
    ],
    "name:guj_x_preferred":[
        "\u0aaf\u0ab0\u0abf\u0a9f\u0abe\u0a97\u0ac1\u0a86"
    ],
    "name:hin_x_preferred":[
        "\u092f\u093e\u0930\u093f\u0924\u0917\u0941\u0906"
    ],
    "name:ind_x_preferred":[
        "Yaritagua"
    ],
    "name:ita_x_preferred":[
        "Yaritagua"
    ],
    "name:jpn_x_preferred":[
        "\u30e4\u30ea\u30bf\u30b0\u30a2"
    ],
    "name:kan_x_preferred":[
        "\u0caf\u0cb0\u0cbf\u0c9f\u0cbe\u0c97\u0cc1\u0cb5\u0cbe"
    ],
    "name:kor_x_preferred":[
        "\uc57c\ub9ac\ud0c0\uacfc"
    ],
    "name:lav_x_preferred":[
        "Jaritagva"
    ],
    "name:lit_x_preferred":[
        "Jaritagva"
    ],
    "name:mar_x_preferred":[
        "\u092f\u0947\u0930\u093f\u091f\u093e\u0917\u0941\u0906"
    ],
    "name:may_x_preferred":[
        "Yaritagua"
    ],
    "name:nob_x_preferred":[
        "Yaritagua"
    ],
    "name:pol_x_preferred":[
        "Yaritagua"
    ],
    "name:por_x_preferred":[
        "Yaritagua"
    ],
    "name:rus_x_preferred":[
        "\u042f\u0440\u0438\u0442\u0430\u0433\u0443\u0430"
    ],
    "name:sin_x_preferred":[
        "\u0dba\u0dbb\u0dd2\u0da7\u0d9c\u0dd4\u0d86"
    ],
    "name:spa_x_preferred":[
        "Yaritagua"
    ],
    "name:swe_x_preferred":[
        "Yaritagua"
    ],
    "name:tam_x_preferred":[
        "\u0baf\u0bb1\u0bbf\u0ba4\u0b95\u0bc1\u0b86"
    ],
    "name:tel_x_preferred":[
        "\u0c2f\u0c3e\u0c30\u0c3f\u0c1f\u0c17\u0c4d\u0c35\u0c3e"
    ],
    "name:tha_x_preferred":[
        "\u0e22\u0e32\u0e23\u0e34\u0e15\u0e32\u0e01\u0e31\u0e27"
    ],
    "name:tur_x_preferred":[
        "Yaritagua"
    ],
    "name:ukr_x_preferred":[
        "\u042f\u0440\u0456\u0442\u0430\u0433\u0443\u0430"
    ],
    "name:urd_x_preferred":[
        "\u06cc\u0627\u0631\u06cc\u062a\u0627\u06af\u0648\u0627"
    ],
    "name:vie_x_preferred":[
        "Yaritagua"
    ],
    "qs:name":"Yaritagua",
    "qs:photos_9r":0,
    "qs:photos_sr":0,
    "qs:pop_sr":"8",
    "wd:wordcount":114,
    "wof:name":"Yaritagua",
    "wof:placetype":"locality",
    "wof:population":89662
},
  "geometry": {"coordinates":[-69.12611,10.08],"type":"Point"}
}