{
  "type": "Feature",
  "properties": {
    "gn:admin1_code":"12",
    "gn:asciiname":"La Porfia",
    "gn:country_code":"VE",
    "gn:dem":69,
    "gn:feature_class":"P",
    "gn:feature_code":"PPL",
    "gn:name":"La Porf\u00eda",
    "gn:population":0,
    "gn:timezone":"America/Caracas",
    "iso:country":"VE",
    "wof:name":"La Porfia",
    "wof:placetype":"locality"
},
  "geometry": {"coordinates":[-65.39067,9.33415],"type":"Point"}
}