{
  "type": "Feature",
  "properties": {
    "gn:admin1_code":"02",
    "gn:asciiname":"Guatacaro",
    "gn:country_code":"VE",
    "gn:dem":133,
    "gn:feature_class":"P",
    "gn:feature_code":"PPL",
    "gn:name":"Guatacaro",
    "gn:population":0,
    "gn:timezone":"America/Caracas",
    "iso:country":"VE",
    "wof:name":"Guatacaro",
    "wof:placetype":"locality"
},
  "geometry": {"coordinates":[-64.95241,9.23582],"type":"Point"}
}