{
  "type": "Feature",
  "properties": {
    "gn:admin1_code":"6.0",
    "gn:asciiname":"Sampay",
    "gn:country_code":"VE",
    "gn:dem":862,
    "gn:feature_class":"P",
    "gn:feature_code":"PPL",
    "gn:name":"Sampay",
    "gn:population":0,
    "gn:timezone":"America/Caracas",
    "iso:country":"VE",
    "wof:name":"Sampay",
    "wof:placetype":"locality"
},
  "geometry": {"coordinates":[-61.08833000000001,4.61222],"type":"Point"}
}