{
  "type": "Feature",
  "properties": {
    "gn:admin1_code":"16",
    "gn:asciiname":"La Chaguarama",
    "gn:cc2":"VE",
    "gn:country_code":"VE",
    "gn:dem":241,
    "gn:feature_class":"P",
    "gn:feature_code":"PPL",
    "gn:name":"La Chaguarama",
    "gn:population":0,
    "gn:timezone":"America/Caracas",
    "iso:country":"VE",
    "name:und_x_variant":[
        "Chaguaramal",
        "La Chaguarama"
    ],
    "wof:name":"La Chaguarama",
    "wof:placetype":"locality"
},
  "geometry": {"coordinates":[-63.88333000000001,9.71667],"type":"Point"}
}