{
  "type": "Feature",
  "properties": {
    "gn:admin1_code":"25",
    "gn:asciiname":"Las Peonias",
    "gn:country_code":"VE",
    "gn:dem":984,
    "gn:feature_class":"P",
    "gn:feature_code":"PPL",
    "gn:name":"Las Peon\u00edas",
    "gn:population":0,
    "gn:timezone":"America/Caracas",
    "iso:country":"VE",
    "wof:name":"Las Peonias",
    "wof:placetype":"locality"
},
  "geometry": {"coordinates":[-67.05,10.51667],"type":"Point"}
}