{
  "type": "Feature",
  "properties": {
    "gn:admin1_code":"02",
    "gn:asciiname":"Santa Juana",
    "gn:country_code":"VE",
    "gn:dem":338,
    "gn:feature_class":"P",
    "gn:feature_code":"PPL",
    "gn:name":"Santa Juana",
    "gn:population":0,
    "gn:timezone":"America/Caracas",
    "iso:country":"VE",
    "wof:name":"Santa Juana",
    "wof:placetype":"locality"
},
  "geometry": {"coordinates":[-64.45755,10.07661],"type":"Point"}
}