{
  "type": "Feature",
  "properties": {
    "gn:admin1_code":"20",
    "gn:asciiname":"El Guardijo",
    "gn:country_code":"VE",
    "gn:dem":1604,
    "gn:feature_class":"P",
    "gn:feature_code":"PPLL",
    "gn:name":"El Guardijo",
    "gn:population":0,
    "gn:timezone":"America/Caracas",
    "iso:country":"VE",
    "wof:name":"El Guardijo",
    "wof:placetype":"locality"
},
  "geometry": {"coordinates":[-71.79961,7.91585],"type":"Point"}
}