{
  "type": "Feature",
  "properties": {
    "gn:admin1_code":"11.0",
    "gn:asciiname":"Montana de Los Indios",
    "gn:country_code":"VE",
    "gn:dem":273,
    "gn:feature_class":"P",
    "gn:feature_code":"PPL",
    "gn:name":"Monta\u00f1a de Los Indios",
    "gn:population":0,
    "gn:timezone":"America/Caracas",
    "iso:country":"VE",
    "wof:name":"Montana de Los Indios",
    "wof:placetype":"locality"
},
  "geometry": {"coordinates":[-69.32080000000001,11.45197],"type":"Point"}
}