{
  "type": "Feature",
  "properties": {
    "gn:admin1_code":"20",
    "gn:asciiname":"Quinimari",
    "gn:country_code":"VE",
    "gn:dem":677,
    "gn:feature_class":"P",
    "gn:feature_code":"PPL",
    "gn:name":"Quinimar\u00ed",
    "gn:population":0,
    "gn:timezone":"America/Caracas",
    "iso:country":"VE",
    "wof:name":"Quinimari",
    "wof:placetype":"locality"
},
  "geometry": {"coordinates":[-72.28118000000001,7.65481],"type":"Point"}
}