{
  "type": "Feature",
  "properties": {
    "gn:admin1_code":"8",
    "gn:asciiname":"Lagunita",
    "gn:country_code":"VE",
    "gn:dem":352,
    "gn:feature_class":"P",
    "gn:feature_code":"PPL",
    "gn:name":"Lagunita",
    "gn:population":0,
    "gn:timezone":"America/Caracas",
    "iso:country":"VE",
    "name:nld_x_preferred":[
        "Lagunita"
    ],
    "name:spa_x_preferred":[
        "Lagunita"
    ],
    "name:swe_x_preferred":[
        "Lagunita"
    ],
    "wof:name":"Lagunita",
    "wof:placetype":"locality"
},
  "geometry": {"coordinates":[-68.07773,9.81373],"type":"Point"}
}