{
  "type": "Feature",
  "properties": {
    "gn:admin1_code":"11",
    "gn:asciiname":"Guaibacoa",
    "gn:country_code":"VE",
    "gn:dem":257,
    "gn:feature_class":"P",
    "gn:feature_code":"PPL",
    "gn:name":"Guaibacoa",
    "gn:population":0,
    "gn:timezone":"America/Caracas",
    "iso:country":"VE",
    "name:und_x_variant":[
        "Guayabacoa",
        "Guaibacoa"
    ],
    "wof:name":"Guaibacoa",
    "wof:placetype":"locality"
},
  "geometry": {"coordinates":[-69.47909,11.4157],"type":"Point"}
}