{
  "type": "Feature",
  "properties": {
    "gn:admin1_code":"23.0",
    "gn:asciiname":"Juan de Los Rios",
    "gn:country_code":"VE",
    "gn:dem":25,
    "gn:feature_class":"P",
    "gn:feature_code":"PPL",
    "gn:name":"Juan de Los R\u00edos",
    "gn:population":0,
    "gn:timezone":"America/Caracas",
    "iso:country":"VE",
    "wof:name":"Juan de Los Rios",
    "wof:placetype":"locality"
},
  "geometry": {"coordinates":[-71.1357,9.15477],"type":"Point"}
}