{
  "type": "Feature",
  "properties": {
    "gn:admin1_code":"4.0",
    "gn:asciiname":"San Salvador",
    "gn:country_code":"VE",
    "gn:dem":1086,
    "gn:feature_class":"P",
    "gn:feature_code":"PPL",
    "gn:name":"San Salvador",
    "gn:population":0,
    "gn:timezone":"America/Caracas",
    "iso:country":"VE",
    "wof:name":"San Salvador",
    "wof:placetype":"locality"
},
  "geometry": {"coordinates":[-67.06437,10.04862],"type":"Point"}
}