{
  "type": "Feature",
  "properties": {
    "gn:admin1_code":"12",
    "gn:asciiname":"Gamelotal",
    "gn:country_code":"VE",
    "gn:dem":179,
    "gn:feature_class":"P",
    "gn:feature_code":"PPL",
    "gn:name":"Gamelotal",
    "gn:population":0,
    "gn:timezone":"America/Caracas",
    "iso:country":"VE",
    "name:und_x_variant":[
        "Gamelota",
        "Gamelotal"
    ],
    "wof:name":"Gamelotal",
    "wof:placetype":"locality"
},
  "geometry": {"coordinates":[-65.86816999999999,9.207],"type":"Point"}
}