{
  "type": "Feature",
  "properties": {
    "gn:admin1_code":"4",
    "gn:asciiname":"Veintitres de Enero",
    "gn:country_code":"VE",
    "gn:dem":438,
    "gn:feature_class":"P",
    "gn:feature_code":"PPL",
    "gn:name":"Veintitr\u00e9s de Enero",
    "gn:population":0,
    "gn:timezone":"America/Caracas",
    "iso:country":"VE",
    "wof:name":"Veintitres de Enero",
    "wof:placetype":"locality"
},
  "geometry": {"coordinates":[-67.61901999999999,10.24709],"type":"Point"}
}