{
  "type": "Feature",
  "properties": {
    "gn:admin1_code":"02",
    "gn:asciiname":"La Palmita",
    "gn:country_code":"VE",
    "gn:dem":208,
    "gn:feature_class":"P",
    "gn:feature_code":"PPLL",
    "gn:name":"La Palmita",
    "gn:population":0,
    "gn:timezone":"America/Caracas",
    "iso:country":"VE",
    "wof:name":"La Palmita",
    "wof:placetype":"locality"
},
  "geometry": {"coordinates":[-64.7664,8.92164],"type":"Point"}
}