{
  "type": "Feature",
  "properties": {
    "gn:admin1_code":"6",
    "gn:asciiname":"Euana",
    "gn:country_code":"VE",
    "gn:dem":340,
    "gn:feature_class":"P",
    "gn:feature_code":"PPL",
    "gn:name":"Eua\u00f1a",
    "gn:population":0,
    "gn:timezone":"America/Caracas",
    "iso:country":"VE",
    "wof:name":"Euana",
    "wof:placetype":"locality"
},
  "geometry": {"coordinates":[-64.66667,5.36667],"type":"Point"}
}