{
  "type": "Feature",
  "properties": {
    "iso:country":"VE",
    "qs:gn_country":"VE",
    "qs:gn_fcode":"PPL",
    "qs:gn_pop":0,
    "qs:name":"Vista Alegre",
    "qs:name_adm0":"Venezuela",
    "qs:name_adm1":"Distrito Federal",
    "qs:photos":105,
    "qs:photos_1k":21,
    "qs:photos_9k":1,
    "qs:photos_9r":3,
    "qs:photos_all":105,
    "qs:photos_sr":3,
    "qs:placetype":"Town",
    "qs:pop_sr":"0",
    "qs:woe_adm0":23424982,
    "wof:name":"Vista Alegre",
    "wof:placetype":"locality"
},
  "geometry": {"coordinates":[-67.69593,10.29174],"type":"Point"}
}