{
  "type": "Feature",
  "properties": {
    "iso:country":"VE",
    "name:cat_x_preferred":[
        "Vista Alegre"
    ],
    "name:ceb_x_preferred":[
        "Vista Alegre"
    ],
    "name:deu_x_preferred":[
        "Vista Alegre"
    ],
    "name:epo_x_preferred":[
        "Vista Alegre"
    ],
    "name:eus_x_preferred":[
        "Vista Alegre"
    ],
    "name:fra_x_preferred":[
        "Vista Alegre"
    ],
    "name:glg_x_preferred":[
        "Vista Alegre"
    ],
    "name:ita_x_preferred":[
        "Vista Alegre"
    ],
    "name:nld_x_preferred":[
        "Vista Alegre"
    ],
    "name:nor_x_preferred":[
        "Vista Alegre"
    ],
    "name:por_x_preferred":[
        "Vista Alegre"
    ],
    "name:spa_x_preferred":[
        "Vista Alegre"
    ],
    "name:srp_x_preferred":[
        "\u0412\u0438\u0441\u0442\u0430 \u0410\u043b\u0435\u0433\u0440\u0435"
    ],
    "name:swe_x_preferred":[
        "Vista Alegre"
    ],
    "qs:gn_country":"VE",
    "qs:gn_fcode":"PPL",
    "qs:gn_pop":0,
    "qs:name":"Vista Alegre",
    "qs:name_adm0":"Venezuela",
    "qs:name_adm1":"Distrito Federal",
    "qs:photos":105,
    "qs:photos_1k":21,
    "qs:photos_9k":1,
    "qs:photos_9r":3,
    "qs:photos_all":105,
    "qs:photos_sr":3,
    "qs:placetype":"Town",
    "qs:pop_sr":"0",
    "qs:woe_adm0":23424982,
    "wof:name":"Vista Alegre",
    "wof:placetype":"locality"
},
  "geometry": {"coordinates":[-67.69593,10.29174],"type":"Point"}
}