{
  "type": "Feature",
  "properties": {
    "gn:admin1_code":"18",
    "gn:asciiname":"El Bajio",
    "gn:country_code":"VE",
    "gn:dem":321,
    "gn:feature_class":"P",
    "gn:feature_code":"PPL",
    "gn:name":"El Baj\u00edo",
    "gn:population":0,
    "gn:timezone":"America/Caracas",
    "iso:country":"VE",
    "wof:name":"El Bajio",
    "wof:placetype":"locality"
},
  "geometry": {"coordinates":[-69.3245,9.54178],"type":"Point"}
}