{
  "type": "Feature",
  "properties": {
    "gn:country":"VE",
    "gn:fcode":"PPLA2",
    "gn:pop":182558,
    "iso:country":"VE",
    "name:ara_x_preferred":[
        "\u0643\u0648\u0627"
    ],
    "name:ast_x_preferred":[
        "C\u00faa"
    ],
    "name:ben_x_preferred":[
        "\u0995\u09cb\u09af\u09bc\u09be"
    ],
    "name:bul_x_preferred":[
        "\u041a\u0443\u0430"
    ],
    "name:cat_x_preferred":[
        "C\u00faa"
    ],
    "name:ceb_x_preferred":[
        "C\u00faa"
    ],
    "name:dan_x_preferred":[
        "C\u00faa"
    ],
    "name:deu_x_preferred":[
        "C\u00faa"
    ],
    "name:ell_x_preferred":[
        "\u039a\u03bf\u03cd\u03b1"
    ],
    "name:eng_x_preferred":[
        "C\u00faa"
    ],
    "name:epo_x_preferred":[
        "C\u00faa"
    ],
    "name:fin_x_preferred":[
        "C\u00faa"
    ],
    "name:fra_x_preferred":[
        "C\u00faa"
    ],
    "name:guj_x_preferred":[
        "\u0a95\u0ac1\u0a86"
    ],
    "name:hin_x_preferred":[
        "\u091a\u0941\u0906"
    ],
    "name:ind_x_preferred":[
        "C\u00faa"
    ],
    "name:ita_x_preferred":[
        "C\u00faa"
    ],
    "name:jpn_x_preferred":[
        "\u30af\u30a2"
    ],
    "name:kan_x_preferred":[
        "\u0c95\u0cc1\u0cb5\u0cbe"
    ],
    "name:kat_x_preferred":[
        "\u10d9\u10e3\u10d0"
    ],
    "name:kor_x_preferred":[
        "\uafb8\uc544"
    ],
    "name:lav_x_preferred":[
        "Kua"
    ],
    "name:lit_x_preferred":[
        "Kua"
    ],
    "name:mar_x_preferred":[
        "\u0915\u0942\u0906"
    ],
    "name:msa_x_preferred":[
        "Cua"
    ],
    "name:nld_x_preferred":[
        "C\u00faa"
    ],
    "name:nob_x_preferred":[
        "Cua"
    ],
    "name:pol_x_preferred":[
        "C\u00faa"
    ],
    "name:por_x_preferred":[
        "C\u00faa"
    ],
    "name:rus_x_preferred":[
        "\u041a\u0443\u0430"
    ],
    "name:sin_x_preferred":[
        "\u0d9a\u0dd6\u0d86"
    ],
    "name:spa_x_preferred":[
        "C\u00faa"
    ],
    "name:swe_x_preferred":[
        "C\u00faa"
    ],
    "name:tam_x_preferred":[
        "\u0b9a\u0bc1\u0baf"
    ],
    "name:tel_x_preferred":[
        "\u0c1a\u0c41\u0c35\u0c3e"
    ],
    "name:tha_x_preferred":[
        "\u0e01\u0e31\u0e27 \u0e25\u0e31\u0e1a"
    ],
    "name:tur_x_preferred":[
        "C\u00faa"
    ],
    "name:ukr_x_preferred":[
        "\u041a\u0443\u0430"
    ],
    "name:urd_x_preferred":[
        "\u06a9\u0648\u0627"
    ],
    "name:vie_x_preferred":[
        "C\u00faa"
    ],
    "name:zho_x_preferred":[
        "\u5eab\u963f"
    ],
    "qs:name":"C\u00faa",
    "qs:photos_9r":0,
    "qs:photos_sr":0,
    "qs:pop_sr":"9",
    "wd:elevation":490.0,
    "wd:wordcount":748,
    "wof:name":"C\u00faa",
    "wof:placetype":"locality",
    "wof:population":182558
},
  "geometry": {"coordinates":[-66.88575,10.15892],"type":"Point"}
}