{
  "type": "Feature",
  "properties": {
    "gn:admin1_code":"18.0",
    "gn:asciiname":"Villa Araure Dos",
    "gn:country_code":"VE",
    "gn:dem":242,
    "gn:feature_class":"P",
    "gn:feature_code":"PPL",
    "gn:name":"Villa Araure Dos",
    "gn:population":0,
    "gn:timezone":"America/Caracas",
    "iso:country":"VE",
    "wof:name":"Villa Araure Dos",
    "wof:placetype":"locality"
},
  "geometry": {"coordinates":[-69.22832,9.59002],"type":"Point"}
}