{
  "type": "Feature",
  "properties": {
    "gn:admin1_code":"6.0",
    "gn:asciiname":"El Guarapo",
    "gn:country_code":"VE",
    "gn:dem":295,
    "gn:feature_class":"P",
    "gn:feature_code":"PPL",
    "gn:name":"El Guarapo",
    "gn:population":0,
    "gn:timezone":"America/Caracas",
    "iso:country":"VE",
    "wof:name":"El Guarapo",
    "wof:placetype":"locality"
},
  "geometry": {"coordinates":[-63.09889,7.46556],"type":"Point"}
}