{
  "type": "Feature",
  "properties": {
    "gn:admin1_code":"23.0",
    "gn:asciiname":"San Jose",
    "gn:country_code":"VE",
    "gn:dem":78,
    "gn:feature_class":"P",
    "gn:feature_code":"PPLL",
    "gn:name":"San Jos\u00e9",
    "gn:population":0,
    "gn:timezone":"America/Caracas",
    "iso:country":"VE",
    "wof:name":"San Jose",
    "wof:placetype":"locality"
},
  "geometry": {"coordinates":[-72.04259,10.71102],"type":"Point"}
}