{
  "type": "Feature",
  "properties": {
    "gn:admin1_code":"18",
    "gn:asciiname":"La Aduana",
    "gn:country_code":"VE",
    "gn:dem":100,
    "gn:feature_class":"P",
    "gn:feature_code":"PPL",
    "gn:name":"La Aduana",
    "gn:population":0,
    "gn:timezone":"America/Caracas",
    "iso:country":"VE",
    "wof:name":"La Aduana",
    "wof:placetype":"locality"
},
  "geometry": {"coordinates":[-69.2073,8.92004],"type":"Point"}
}