{
  "type": "Feature",
  "properties": {
    "gn:admin1_code":"20.0",
    "gn:asciiname":"Las Blancas",
    "gn:country_code":"VE",
    "gn:dem":849,
    "gn:feature_class":"P",
    "gn:feature_code":"PPL",
    "gn:name":"Las Blancas",
    "gn:population":0,
    "gn:timezone":"America/Caracas",
    "iso:country":"VE",
    "wof:name":"Las Blancas",
    "wof:placetype":"locality"
},
  "geometry": {"coordinates":[-72.22389,8.07389],"type":"Point"}
}