{
  "type": "Feature",
  "properties": {
    "gn:admin1_code":"01",
    "gn:admin2_code":"0207",
    "gn:asciiname":"San Carlos de Rio Negro",
    "gn:cc2":"VE",
    "gn:country_code":"VE",
    "gn:dem":92,
    "gn:feature_class":"P",
    "gn:feature_code":"PPLA2",
    "gn:name":"San Carlos de R\u00edo Negro",
    "gn:population":0,
    "gn:timezone":"America/Caracas",
    "iso:country":"VE",
    "name:und_x_variant":[
        "San Carlos",
        "San Carlos de R\u00edo Negro"
    ],
    "wof:name":"San Carlos de Rio Negro",
    "wof:placetype":"locality"
},
  "geometry": {"coordinates":[-67.06089,1.92027],"type":"Point"}
}