{
  "type": "Feature",
  "properties": {
    "gn:admin1_code":"23",
    "gn:asciiname":"Villa Vieja",
    "gn:country_code":"VE",
    "gn:dem":59,
    "gn:feature_class":"P",
    "gn:feature_code":"PPL",
    "gn:name":"Villa Vieja",
    "gn:population":0,
    "gn:timezone":"America/Caracas",
    "iso:country":"VE",
    "name:und_x_variant":[
        "La Villa Vieja",
        "La Villa Viejo",
        "Villa Vieja"
    ],
    "wof:name":"Villa Vieja",
    "wof:placetype":"locality"
},
  "geometry": {"coordinates":[-72.36448,10.12515],"type":"Point"}
}