{
  "type": "Feature",
  "properties": {
    "gn:admin1_code":"11.0",
    "gn:asciiname":"Buruica",
    "gn:country_code":"VE",
    "gn:dem":457,
    "gn:feature_class":"P",
    "gn:feature_code":"PPL",
    "gn:name":"Buruica",
    "gn:population":0,
    "gn:timezone":"America/Caracas",
    "iso:country":"VE",
    "wof:name":"Buruica",
    "wof:placetype":"locality"
},
  "geometry": {"coordinates":[-70.30603000000001,10.86964],"type":"Point"}
}