{
  "type": "Feature",
  "properties": {
    "gn:admin1_code":"3.0",
    "gn:asciiname":"Las Bonitas",
    "gn:country_code":"VE",
    "gn:dem":48,
    "gn:feature_class":"P",
    "gn:feature_code":"PPLL",
    "gn:name":"Las Bonitas",
    "gn:population":0,
    "gn:timezone":"America/Caracas",
    "iso:country":"VE",
    "wof:name":"Las Bonitas",
    "wof:placetype":"locality"
},
  "geometry": {"coordinates":[-67.67253000000001,7.50459],"type":"Point"}
}