{
  "type": "Feature",
  "properties": {
    "gn:admin1_code":"11.0",
    "gn:asciiname":"Tarica",
    "gn:country_code":"VE",
    "gn:dem":31,
    "gn:feature_class":"P",
    "gn:feature_code":"PPL",
    "gn:name":"Tarica",
    "gn:population":0,
    "gn:timezone":"America/Caracas",
    "iso:country":"VE",
    "wof:name":"Tarica",
    "wof:placetype":"locality"
},
  "geometry": {"coordinates":[-70.92014,11.02036],"type":"Point"}
}