{
  "type": "Feature",
  "properties": {
    "gn:admin1_code":"12.0",
    "gn:asciiname":"Cotoperiz",
    "gn:country_code":"VE",
    "gn:dem":137,
    "gn:feature_class":"P",
    "gn:feature_code":"PPLL",
    "gn:name":"Cotoperiz",
    "gn:population":0,
    "gn:timezone":"America/Caracas",
    "iso:country":"VE",
    "wof:name":"Cotoperiz",
    "wof:placetype":"locality"
},
  "geometry": {"coordinates":[-65.34557,8.8134],"type":"Point"}
}