{
  "type": "Feature",
  "properties": {
    "gn:admin1_code":"11.0",
    "gn:asciiname":"Jajatal",
    "gn:country_code":"VE",
    "gn:dem":7,
    "gn:feature_class":"P",
    "gn:feature_code":"PPL",
    "gn:name":"Jajatal",
    "gn:population":0,
    "gn:timezone":"America/Caracas",
    "iso:country":"VE",
    "wof:name":"Jajatal",
    "wof:placetype":"locality"
},
  "geometry": {"coordinates":[-68.33333,10.98889],"type":"Point"}
}