{
  "type": "Feature",
  "properties": {
    "gn:admin1_code":"23",
    "gn:asciiname":"El Guayabo",
    "gn:country_code":"VE",
    "gn:dem":27,
    "gn:feature_class":"P",
    "gn:feature_code":"PPL",
    "gn:name":"El Guayabo",
    "gn:population":0,
    "gn:timezone":"America/Caracas",
    "iso:country":"VE",
    "wof:name":"El Guayabo",
    "wof:placetype":"locality"
},
  "geometry": {"coordinates":[-72.3389,8.62443],"type":"Point"}
}