{
  "type": "Feature",
  "properties": {
    "gn:admin1_code":"16.0",
    "gn:asciiname":"La Chaguarama",
    "gn:country_code":"VE",
    "gn:dem":641,
    "gn:feature_class":"P",
    "gn:feature_code":"PPL",
    "gn:name":"La Chaguarama",
    "gn:population":0,
    "gn:timezone":"America/Caracas",
    "iso:country":"VE",
    "wof:name":"La Chaguarama",
    "wof:placetype":"locality"
},
  "geometry": {"coordinates":[-63.76739,10.09838],"type":"Point"}
}