{
  "type": "Feature",
  "properties": {
    "gn:admin1_code":"15",
    "gn:asciiname":"La Comunidad",
    "gn:country_code":"VE",
    "gn:dem":379,
    "gn:feature_class":"P",
    "gn:feature_code":"PPL",
    "gn:name":"La Comunidad",
    "gn:population":0,
    "gn:timezone":"America/Caracas",
    "iso:country":"VE",
    "wof:name":"La Comunidad",
    "wof:placetype":"locality"
},
  "geometry": {"coordinates":[-66.63266,10.47447],"type":"Point"}
}