{
  "type": "Feature",
  "properties": {
    "gn:admin1_code":"13.0",
    "gn:asciiname":"La Niguita",
    "gn:country_code":"VE",
    "gn:dem":584,
    "gn:feature_class":"P",
    "gn:feature_code":"PPL",
    "gn:name":"La Niguita",
    "gn:population":0,
    "gn:timezone":"America/Caracas",
    "iso:country":"VE",
    "wof:name":"La Niguita",
    "wof:placetype":"locality"
},
  "geometry": {"coordinates":[-69.68918000000001,10.06704],"type":"Point"}
}