{
  "type": "Feature",
  "properties": {
    "gn:admin1_code":"02",
    "gn:asciiname":"El Totumo",
    "gn:country_code":"VE",
    "gn:dem":113,
    "gn:feature_class":"P",
    "gn:feature_code":"PPLL",
    "gn:name":"El Totumo",
    "gn:population":0,
    "gn:timezone":"America/Caracas",
    "iso:country":"VE",
    "name:ces_x_preferred":[
        "El Totumo"
    ],
    "name:fas_x_preferred":[
        "\u0627\u0644 \u062a\u0648\u062a\u0648\u0645\u0648"
    ],
    "name:kor_x_preferred":[
        "\uc5d8\ud1a0\ud22c\ubaa8\uc0b0"
    ],
    "name:nld_x_preferred":[
        "El Totumo"
    ],
    "name:por_x_preferred":[
        "El Totumo"
    ],
    "name:spa_x_preferred":[
        "Volc\u00e1n del Totumo"
    ],
    "name:zho_x_preferred":[
        "\u57c3\u723e\u6258\u5716\u83ab\u706b\u5c71"
    ],
    "wof:name":"El Totumo",
    "wof:placetype":"locality"
},
  "geometry": {"coordinates":[-64.75603000000001,8.10498],"type":"Point"}
}