{
  "type": "Feature",
  "properties": {
    "gn:admin1_code":"11",
    "gn:asciiname":"Cieneguita",
    "gn:country_code":"VE",
    "gn:dem":104,
    "gn:feature_class":"P",
    "gn:feature_code":"PPL",
    "gn:name":"Cieneguita",
    "gn:population":0,
    "gn:timezone":"America/Caracas",
    "iso:country":"VE",
    "wof:name":"Cieneguita",
    "wof:placetype":"locality"
},
  "geometry": {"coordinates":[-69.96284,11.12274],"type":"Point"}
}