{
  "type": "Feature",
  "properties": {
    "gn:admin1_code":"19.0",
    "gn:asciiname":"Cerro Grande",
    "gn:country_code":"VE",
    "gn:dem":316,
    "gn:feature_class":"P",
    "gn:feature_code":"PPL",
    "gn:name":"Cerro Grande",
    "gn:population":0,
    "gn:timezone":"America/Caracas",
    "iso:country":"VE",
    "name:ceb_x_preferred":[
        "Cerro Grande"
    ],
    "name:deu_x_preferred":[
        "Cerro Grande"
    ],
    "name:spa_x_preferred":[
        "Cerro Grande"
    ],
    "name:swe_x_preferred":[
        "Cerro Grande"
    ],
    "wof:name":"Cerro Grande",
    "wof:placetype":"locality"
},
  "geometry": {"coordinates":[-63.88889,10.59222],"type":"Point"}
}