{
  "type": "Feature",
  "properties": {
    "gn:admin1_code":"12.0",
    "gn:asciiname":"Estacion de Bombeo",
    "gn:country_code":"VE",
    "gn:dem":164,
    "gn:feature_class":"P",
    "gn:feature_code":"PPLL",
    "gn:name":"Estaci\u00f3n de Bombeo",
    "gn:population":0,
    "gn:timezone":"America/Caracas",
    "iso:country":"VE",
    "wof:name":"Estacion de Bombeo",
    "wof:placetype":"locality"
},
  "geometry": {"coordinates":[-66.68289,9.29481],"type":"Point"}
}