{
  "type": "Feature",
  "properties": {
    "gn:admin1_code":"23",
    "gn:asciiname":"Singapur",
    "gn:country_code":"VE",
    "gn:dem":65,
    "gn:feature_class":"P",
    "gn:feature_code":"PPL",
    "gn:name":"Singapur",
    "gn:population":0,
    "gn:timezone":"America/Caracas",
    "iso:country":"VE",
    "wof:name":"Singapur",
    "wof:placetype":"locality"
},
  "geometry": {"coordinates":[-71.04441,10.18313],"type":"Point"}
}