{
  "type": "Feature",
  "properties": {
    "gn:admin1_code":"02",
    "gn:asciiname":"Alto Clarindero",
    "gn:country_code":"VE",
    "gn:dem":111,
    "gn:feature_class":"P",
    "gn:feature_code":"PPLL",
    "gn:name":"Alto Clarindero",
    "gn:population":0,
    "gn:timezone":"America/Caracas",
    "iso:country":"VE",
    "wof:name":"Alto Clarindero",
    "wof:placetype":"locality"
},
  "geometry": {"coordinates":[-64.70791,9.6672],"type":"Point"}
}