{
  "type": "Feature",
  "properties": {
    "iso:country":"VE",
    "qs:gn_country":"VE",
    "qs:gn_fcode":"PPL",
    "qs:gn_pop":0,
    "qs:name":"El M\u00e1caro",
    "qs:name_adm0":"Venezuela",
    "qs:name_adm1":"Aragua",
    "qs:photos":97,
    "qs:photos_1k":20,
    "qs:photos_9k":1,
    "qs:photos_9r":3,
    "qs:photos_all":97,
    "qs:photos_sr":3,
    "qs:placetype":"Town",
    "qs:pop_sr":"0",
    "qs:woe_adm0":23424982,
    "wof:name":"El M\u00e1caro",
    "wof:placetype":"locality"
},
  "geometry": {"coordinates":[-67.49281000000001,10.22875],"type":"Point"}
}