{
  "type": "Feature",
  "properties": {
    "gn:admin1_code":"11.0",
    "gn:asciiname":"Pacheco",
    "gn:country_code":"VE",
    "gn:dem":28,
    "gn:feature_class":"P",
    "gn:feature_code":"PPL",
    "gn:name":"Pacheco",
    "gn:population":0,
    "gn:timezone":"America/Caracas",
    "iso:country":"VE",
    "name:kor_x_preferred":[
        "\ud30c\uccb4\ucf54"
    ],
    "wof:name":"Pacheco",
    "wof:placetype":"locality"
},
  "geometry": {"coordinates":[-70.9847,10.94335],"type":"Point"}
}