{
  "type": "Feature",
  "properties": {
    "gn:admin1_code":"16",
    "gn:asciiname":"Los Pozos",
    "gn:country_code":"VE",
    "gn:dem":376,
    "gn:feature_class":"P",
    "gn:feature_code":"PPL",
    "gn:name":"Los Pozos",
    "gn:population":0,
    "gn:timezone":"America/Caracas",
    "iso:country":"VE",
    "wof:name":"Los Pozos",
    "wof:placetype":"locality"
},
  "geometry": {"coordinates":[-63.53436,9.93809],"type":"Point"}
}