{
  "type": "Feature",
  "properties": {
    "gn:admin1_code":"18",
    "gn:asciiname":"Catuche",
    "gn:country_code":"VE",
    "gn:dem":86,
    "gn:feature_class":"P",
    "gn:feature_code":"PPL",
    "gn:name":"Catuche",
    "gn:population":0,
    "gn:timezone":"America/Caracas",
    "iso:country":"VE",
    "wof:name":"Catuche",
    "wof:placetype":"locality"
},
  "geometry": {"coordinates":[-69.08981,8.82697],"type":"Point"}
}