{
  "type": "Feature",
  "properties": {
    "gn:admin1_code":"20",
    "gn:asciiname":"Vuelta del Mono",
    "gn:country_code":"VE",
    "gn:dem":43,
    "gn:feature_class":"P",
    "gn:feature_code":"PPL",
    "gn:name":"Vuelta del Mono",
    "gn:population":0,
    "gn:timezone":"America/Caracas",
    "iso:country":"VE",
    "wof:name":"Vuelta del Mono",
    "wof:placetype":"locality"
},
  "geometry": {"coordinates":[-72.36740999999998,8.41426],"type":"Point"}
}