{
  "type": "Feature",
  "properties": {
    "gn:admin1_code":"7.0",
    "gn:asciiname":"Urbanizacion Guataparo",
    "gn:country_code":"VE",
    "gn:dem":573,
    "gn:feature_class":"P",
    "gn:feature_code":"PPL",
    "gn:name":"Urbanizaci\u00f3n Guataparo",
    "gn:population":0,
    "gn:timezone":"America/Caracas",
    "iso:country":"VE",
    "wof:name":"Urbanizacion Guataparo",
    "wof:placetype":"locality"
},
  "geometry": {"coordinates":[-68.05110999999999,10.19361],"type":"Point"}
}