{
  "type": "Feature",
  "properties": {
    "gn:admin1_code":"7",
    "gn:asciiname":"Flor Amarilla",
    "gn:country_code":"VE",
    "gn:dem":434,
    "gn:feature_class":"P",
    "gn:feature_code":"PPL",
    "gn:name":"Flor Amarilla",
    "gn:population":0,
    "gn:timezone":"America/Caracas",
    "iso:country":"VE",
    "wof:name":"Flor Amarilla",
    "wof:placetype":"locality"
},
  "geometry": {"coordinates":[-67.93608,10.13972],"type":"Point"}
}