{
  "type": "Feature",
  "properties": {
    "gn:admin1_code":"23.0",
    "gn:asciiname":"Los Canamos",
    "gn:country_code":"VE",
    "gn:dem":35,
    "gn:feature_class":"P",
    "gn:feature_code":"PPLL",
    "gn:name":"Los Ca\u00f1amos",
    "gn:population":0,
    "gn:timezone":"America/Caracas",
    "iso:country":"VE",
    "wof:name":"Los Canamos",
    "wof:placetype":"locality"
},
  "geometry": {"coordinates":[-71.956,10.82992],"type":"Point"}
}