{
  "type": "Feature",
  "properties": {
    "gn:country":"VE",
    "gn:fcode":"PPLX",
    "gn:population":0,
    "iso:country":"VE",
    "name:bre_x_preferred":[
        "San F\u00e9lix"
    ],
    "name:ceb_x_preferred":[
        "San F\u00e9lix"
    ],
    "name:eng_x_preferred":[
        "San F\u00e9lix"
    ],
    "name:fra_x_preferred":[
        "San F\u00e9lix"
    ],
    "name:slk_x_preferred":[
        "San F\u00e9lix"
    ],
    "name:spa_x_colloquial":[
        "S. Felix",
        "S Felix",
        "San Felix"
    ],
    "name:spa_x_preferred":[
        "San F\u00e9lix"
    ],
    "name:spa_x_variant":[
        "S. F\u00e9lix",
        "Seccion S Felix",
        "Pto Tablas",
        "San Felis",
        "Puerto Tablas",
        "Seccion San Felix",
        "S F\u00e9lix",
        "S Felis",
        "Las Tablas",
        "S. Felis",
        "Seccion S. Felix"
    ],
    "name:swe_x_preferred":[
        "San F\u00e9lix"
    ],
    "qs:gn_fcode":"PPLX",
    "qs:gn_local":0,
    "qs:gn_namadm1":"06",
    "qs:gn_name":"San F\u00e9lix",
    "qs:local_max":133,
    "qs:local_sum":133,
    "qs:localhoods":1,
    "qs:name":"San F\u00e9lix",
    "qs:name_adm0":"Venezuela",
    "qs:name_adm1":"Bol\u00edvar",
    "qs:name_adm2":"Caroni",
    "qs:name_lau":"Caroni",
    "qs:name_local":"Ciudad Guayana",
    "qs:photo_max":37,
    "qs:photo_sum":133,
    "qs:placetype":"Suburb",
    "qs:quad_count":15,
    "qs:woe_adm0":23424982,
    "qs:woe_adm1":2347682,
    "qs:woe_adm2":26804581,
    "qs:woe_lau":26805585,
    "qs:woe_local":395275,
    "qs:woe_ver":"7.10.0",
    "qs_pg:aaroncc":"VE",
    "qs_pg:gn_country":"VE",
    "qs_pg:gn_fcode":"PPLX",
    "qs_pg:gn_pop":0,
    "qs_pg:name":"San F\u00e9lix",
    "qs_pg:name_adm0":"Venezuela",
    "qs_pg:name_adm1":"Bol\u00edvar",
    "qs_pg:photos":133,
    "qs_pg:photos_1k":27,
    "qs_pg:photos_9k":1,
    "qs_pg:photos_9r":3,
    "qs_pg:photos_all":133,
    "qs_pg:photos_sr":3,
    "qs_pg:pop_sr":0,
    "qs_pg:qs_pg_placetype":"neighbourhood",
    "qs_pg:qs_pg_placetype_gp":"Suburb",
    "qs_pg:woe_adm0":23424982,
    "wof:lang":[
        "spa"
    ],
    "wof:name":"San F\u00e9lix",
    "wof:placetype":"neighbourhood"
},
  "geometry": {"coordinates":[-62.650268,8.37257],"type":"Point"}
}