{
  "type": "Feature",
  "properties": {
    "gn:admin1_code":"12",
    "gn:asciiname":"El Perro",
    "gn:country_code":"VE",
    "gn:dem":119,
    "gn:feature_class":"P",
    "gn:feature_code":"PPL",
    "gn:name":"El Perro",
    "gn:population":0,
    "gn:timezone":"America/Caracas",
    "iso:country":"VE",
    "wof:name":"El Perro",
    "wof:placetype":"locality"
},
  "geometry": {"coordinates":[-66.30078,8.32212],"type":"Point"}
}