{
  "type": "Feature",
  "properties": {
    "gn:admin1_code":"6.0",
    "gn:asciiname":"La Yagua",
    "gn:country_code":"VE",
    "gn:dem":307,
    "gn:feature_class":"P",
    "gn:feature_code":"PPL",
    "gn:name":"La Yagua",
    "gn:population":0,
    "gn:timezone":"America/Caracas",
    "iso:country":"VE",
    "wof:name":"La Yagua",
    "wof:placetype":"locality"
},
  "geometry": {"coordinates":[-61.89333000000001,7.89778],"type":"Point"}
}