{
  "type": "Feature",
  "properties": {
    "gn:admin1_code":"2",
    "gn:asciiname":"Caracol",
    "gn:country_code":"VE",
    "gn:dem":238,
    "gn:feature_class":"P",
    "gn:feature_code":"PPL",
    "gn:name":"Caracol",
    "gn:population":0,
    "gn:timezone":"America/Caracas",
    "iso:country":"VE",
    "wof:name":"Caracol",
    "wof:placetype":"locality"
},
  "geometry": {"coordinates":[-64.63462,8.85737],"type":"Point"}
}