{
  "type": "Feature",
  "properties": {
    "iso:country":"VE",
    "qs:gn_pop":0,
    "qs:name":"San Simon",
    "qs:name_adm0":"Venezuela",
    "qs:name_adm1":"Monagas",
    "qs:photos":2,
    "qs:photos_1k":1,
    "qs:photos_9k":1,
    "qs:photos_9r":1,
    "qs:photos_all":2,
    "qs:photos_sr":1,
    "qs:placetype":"LocalAdmin",
    "qs:pop_sr":"0",
    "qs:woe_adm0":23424982,
    "wof:name":"San Simon",
    "wof:placetype":"localadmin"
},
  "geometry": {"coordinates":[-63.183746,9.780114],"type":"Point"}
}