{
  "type": "Feature",
  "properties": {
    "iso:country":"VE",
    "name:ceb_x_preferred":[
        "San Simon"
    ],
    "name:ces_x_preferred":[
        "San Simon"
    ],
    "name:deu_x_preferred":[
        "San Simon"
    ],
    "name:fra_x_preferred":[
        "San Simon"
    ],
    "name:nld_x_preferred":[
        "San Simon"
    ],
    "name:sco_x_preferred":[
        "San Simon"
    ],
    "name:srp_x_preferred":[
        "\u0421\u0430\u043d \u0421\u0438\u043c\u043e\u043d"
    ],
    "name:swe_x_preferred":[
        "San Simon"
    ],
    "name:ukr_x_preferred":[
        "\u0421\u0430\u043d-\u0421\u0456\u043c\u043e\u043d"
    ],
    "name:war_x_preferred":[
        "San Sim\u00f3n"
    ],
    "qs:gn_pop":0,
    "qs:name":"San Simon",
    "qs:name_adm0":"Venezuela",
    "qs:name_adm1":"Monagas",
    "qs:photos":2,
    "qs:photos_1k":1,
    "qs:photos_9k":1,
    "qs:photos_9r":1,
    "qs:photos_all":2,
    "qs:photos_sr":1,
    "qs:placetype":"LocalAdmin",
    "qs:pop_sr":"0",
    "qs:woe_adm0":23424982,
    "wof:name":"San Simon",
    "wof:placetype":"localadmin"
},
  "geometry": {"coordinates":[-63.183746,9.780114],"type":"Point"}
}