{
  "type": "Feature",
  "properties": {
    "gn:admin1_code":"11",
    "gn:asciiname":"Matacara",
    "gn:country_code":"VE",
    "gn:dem":177,
    "gn:feature_class":"P",
    "gn:feature_code":"PPL",
    "gn:name":"Matacara",
    "gn:population":0,
    "gn:timezone":"America/Caracas",
    "iso:country":"VE",
    "wof:name":"Matacara",
    "wof:placetype":"locality"
},
  "geometry": {"coordinates":[-70.10177,11.01249],"type":"Point"}
}