{
  "type": "Feature",
  "properties": {
    "gn:admin1_code":"11.0",
    "gn:asciiname":"Montana Fria",
    "gn:country_code":"VE",
    "gn:dem":830,
    "gn:feature_class":"P",
    "gn:feature_code":"PPL",
    "gn:name":"Monta\u00f1a Fr\u00eda",
    "gn:population":0,
    "gn:timezone":"America/Caracas",
    "iso:country":"VE",
    "wof:name":"Montana Fria",
    "wof:placetype":"locality"
},
  "geometry": {"coordinates":[-69.28579000000001,10.78451],"type":"Point"}
}