{
  "type": "Feature",
  "properties": {
    "gn:admin1_code":"16",
    "gn:asciiname":"Bajo Areo",
    "gn:country_code":"VE",
    "gn:dem":363,
    "gn:feature_class":"P",
    "gn:feature_code":"PPL",
    "gn:name":"Bajo Areo",
    "gn:population":0,
    "gn:timezone":"America/Caracas",
    "iso:country":"VE",
    "wof:name":"Bajo Areo",
    "wof:placetype":"locality"
},
  "geometry": {"coordinates":[-63.91583000000001,9.91833],"type":"Point"}
}