{
  "type": "Feature",
  "properties": {
    "gn:country":"VE",
    "gn:fcode":"PPL",
    "gn:pop":34636,
    "iso:country":"VE",
    "name:unk_x_variant":[
        "Rastrojo"
    ],
    "qs:name":"Los Rastrojos",
    "qs:photos_9r":0,
    "qs:photos_sr":0,
    "qs:pop_sr":"7",
    "wd:wordcount":978,
    "wof:name":"Los Rastrojos",
    "wof:placetype":"locality",
    "wof:population":34636
},
  "geometry": {"coordinates":[-69.24166,10.02588],"type":"Point"}
}