{
  "type": "Feature",
  "properties": {
    "gn:country":"VE",
    "gn:fcode":"PPL",
    "gn:population":34636,
    "iso:country":"VE",
    "name:eng_x_preferred":[
        "Los Rastrojos"
    ],
    "name:jpn_x_preferred":[
        "\u30ed\u30b9\u30fb\u30e9\u30b9\u30c8\u30ed\u30db\u30b9"
    ],
    "name:por_x_preferred":[
        "Los Rastrojos"
    ],
    "name:rus_x_preferred":[
        "\u041b\u043e\u0441 \u0420\u0430\u0441\u0442\u0440\u043e\u0445\u043e\u0441"
    ],
    "name:sco_x_preferred":[
        "Los Rastrojos"
    ],
    "name:spa_x_preferred":[
        "Rondas Campesinas Populares"
    ],
    "name:und_x_variant":[
        "Rastrojo"
    ],
    "qs:name":"Los Rastrojos",
    "qs:photos_9r":0,
    "qs:photos_sr":0,
    "qs:pop_sr":"7",
    "wd:wordcount":978,
    "wof:name":"Los Rastrojos",
    "wof:placetype":"locality",
    "wof:population":34636
},
  "geometry": {"coordinates":[-69.24166,10.02588],"type":"Point"}
}