{
  "type": "Feature",
  "properties": {
    "gn:admin1_code":"13",
    "gn:asciiname":"Malecon",
    "gn:country_code":"VE",
    "gn:dem":634,
    "gn:feature_class":"P",
    "gn:feature_code":"PPL",
    "gn:name":"Malec\u00f3n",
    "gn:population":0,
    "gn:timezone":"America/Caracas",
    "iso:country":"VE",
    "wof:name":"Malecon",
    "wof:placetype":"locality"
},
  "geometry": {"coordinates":[-69.25296,10.23985],"type":"Point"}
}