{
  "type": "Feature",
  "properties": {
    "gn:admin1_code":"5",
    "gn:asciiname":"Los Arrecifes",
    "gn:country_code":"VE",
    "gn:dem":132,
    "gn:feature_class":"P",
    "gn:feature_code":"PPLL",
    "gn:name":"Los Arrecifes",
    "gn:population":0,
    "gn:timezone":"America/Caracas",
    "iso:country":"VE",
    "wof:name":"Los Arrecifes",
    "wof:placetype":"locality"
},
  "geometry": {"coordinates":[-70.71436,7.3071],"type":"Point"}
}