{
  "type": "Feature",
  "properties": {
    "gn:admin1_code":"5",
    "gn:asciiname":"Cuchinilla",
    "gn:country_code":"VE",
    "gn:dem":467,
    "gn:feature_class":"P",
    "gn:feature_code":"PPL",
    "gn:name":"Cuchinilla",
    "gn:population":0,
    "gn:timezone":"America/Caracas",
    "iso:country":"VE",
    "wof:name":"Cuchinilla",
    "wof:placetype":"locality"
},
  "geometry": {"coordinates":[-70.43333,8.78333],"type":"Point"}
}