{
  "type": "Feature",
  "properties": {
    "gn:country":"VE",
    "gn:fcode":"PPLA2",
    "gn:population":27432,
    "iso:country":"VE",
    "name:ara_x_preferred":[
        "\u062a\u0627\u0631\u064a\u0628\u0627\u060c \u0641\u0646\u0632\u0648\u064a\u0644\u0627"
    ],
    "name:ara_x_variant":[
        "\u062a\u0627\u0631\u064a\u0628\u0627"
    ],
    "name:arz_x_preferred":[
        "\u062a\u0627\u0631\u064a\u0628\u0627"
    ],
    "name:ast_x_preferred":[
        "Car\u00fapano"
    ],
    "name:ben_x_preferred":[
        "\u09a4\u09be\u09b0\u09bf\u09ac\u09be"
    ],
    "name:cat_x_preferred":[
        "T\u00e1riba"
    ],
    "name:ceb_x_preferred":[
        "T\u00e1riba"
    ],
    "name:dan_x_preferred":[
        "T\u00e1riba"
    ],
    "name:deu_x_preferred":[
        "T\u00e1riba"
    ],
    "name:ell_x_preferred":[
        "\u03a4\u03ac\u03c1\u03b9\u03bc\u03c0\u03b1"
    ],
    "name:eng_x_preferred":[
        "T\u00e1riba"
    ],
    "name:fas_x_preferred":[
        "\u062a\u0627\u0631\u06cc\u0628\u0627"
    ],
    "name:fin_x_preferred":[
        "T\u00e1riba"
    ],
    "name:fra_x_preferred":[
        "T\u00e1riba"
    ],
    "name:gle_x_preferred":[
        "T\u00e1riba"
    ],
    "name:guj_x_preferred":[
        "\u0aa4\u0abe\u0ab0\u0abf\u0aac\u0abe"
    ],
    "name:hin_x_preferred":[
        "\u091f\u0948\u0930\u0940\u092c\u093e"
    ],
    "name:ind_x_preferred":[
        "T\u00e1riba"
    ],
    "name:ita_x_preferred":[
        "T\u00e1riba"
    ],
    "name:jpn_x_preferred":[
        "\u30bf\u30ea\u30d0"
    ],
    "name:kan_x_preferred":[
        "\u0c9f\u0cbe\u0cb0\u0cbf\u0cac\u0cbe"
    ],
    "name:kor_x_preferred":[
        "\ud0c0\ub9ac\ubc14"
    ],
    "name:lav_x_preferred":[
        "Tariba"
    ],
    "name:lit_x_preferred":[
        "Tariba"
    ],
    "name:mar_x_preferred":[
        "\u0924\u093e\u0930\u093f\u092c\u093e"
    ],
    "name:msa_x_preferred":[
        "Tariba"
    ],
    "name:nld_x_preferred":[
        "T\u00e1riba"
    ],
    "name:nob_x_preferred":[
        "Tariba"
    ],
    "name:pol_x_preferred":[
        "T\u00e1riba"
    ],
    "name:por_x_preferred":[
        "T\u00e1riba"
    ],
    "name:rus_x_preferred":[
        "\u0422\u0430\u0440\u0438\u0431\u0430"
    ],
    "name:sin_x_preferred":[
        "\u0da7\u0dcf\u0dbb\u0dd2\u0db6\u0dcf"
    ],
    "name:spa_x_preferred":[
        "T\u00e1riba"
    ],
    "name:swe_x_preferred":[
        "T\u00e1riba"
    ],
    "name:tam_x_preferred":[
        "\u0b9f\u0bb0\u0bbf\u0baa\u0bbe"
    ],
    "name:tat_x_preferred":[
        "\u0422\u0430\u0440\u0438\u0431\u0430"
    ],
    "name:tel_x_preferred":[
        "\u0c24\u0c30\u0c3f\u0c2c\u0c3e"
    ],
    "name:tha_x_preferred":[
        "\u0e15\u0e32\u0e23\u0e34\u0e01\u0e32"
    ],
    "name:tur_x_preferred":[
        "Tariba"
    ],
    "name:ukr_x_preferred":[
        "\u0422\u0430\u0440\u0456\u0431\u0430"
    ],
    "name:urd_x_preferred":[
        "\u062a\u0627\u0631\u06cc\u0628\u0627"
    ],
    "name:vec_x_preferred":[
        "T\u00e1riba"
    ],
    "name:vie_x_preferred":[
        "Tariba"
    ],
    "name:zho_x_preferred":[
        "\u5854\u91cc\u74e6"
    ],
    "qs:name":"T\u00e1riba",
    "qs:photos_9r":0,
    "qs:photos_sr":0,
    "qs:pop_sr":"7",
    "wd:wordcount":34,
    "wof:name":"T\u00e1riba",
    "wof:placetype":"locality",
    "wof:population":27432
},
  "geometry": {"coordinates":[-72.22427,7.8188],"type":"Point"}
}