{
  "type": "Feature",
  "properties": {
    "gn:admin1_code":"11",
    "gn:asciiname":"Los Taques",
    "gn:country_code":"VE",
    "gn:dem":96,
    "gn:feature_class":"P",
    "gn:feature_code":"PPL",
    "gn:name":"Los Taques",
    "gn:population":0,
    "gn:timezone":"America/Caracas",
    "iso:country":"VE",
    "wof:name":"Los Taques",
    "wof:placetype":"locality"
},
  "geometry": {"coordinates":[-70.24893,11.14449],"type":"Point"}
}