{
  "type": "Feature",
  "properties": {
    "gn:admin1_code":"19.0",
    "gn:asciiname":"Rio Chiquito Abajo",
    "gn:country_code":"VE",
    "gn:dem":114,
    "gn:feature_class":"P",
    "gn:feature_code":"PPL",
    "gn:name":"R\u00edo Chiquito Abajo",
    "gn:population":0,
    "gn:timezone":"America/Caracas",
    "iso:country":"VE",
    "wof:name":"Rio Chiquito Abajo",
    "wof:placetype":"locality"
},
  "geometry": {"coordinates":[-63.05178000000001,10.6477],"type":"Point"}
}