{
  "type": "Feature",
  "properties": {
    "gn:admin1_code":"6",
    "gn:asciiname":"La Pena",
    "gn:country_code":"VE",
    "gn:dem":8,
    "gn:feature_class":"P",
    "gn:feature_code":"PPL",
    "gn:name":"La Pe\u00f1a",
    "gn:population":0,
    "gn:timezone":"America/Caracas",
    "iso:country":"VE",
    "wof:name":"La Pena",
    "wof:placetype":"locality"
},
  "geometry": {"coordinates":[-63.53333000000001,8.15],"type":"Point"}
}