{
  "type": "Feature",
  "properties": {
    "gn:admin1_code":"23.0",
    "gn:asciiname":"Lambedero",
    "gn:country_code":"VE",
    "gn:dem":83,
    "gn:feature_class":"P",
    "gn:feature_code":"PPLL",
    "gn:name":"Lambedero",
    "gn:population":0,
    "gn:timezone":"America/Caracas",
    "iso:country":"VE",
    "wof:name":"Lambedero",
    "wof:placetype":"locality"
},
  "geometry": {"coordinates":[-71.77878,10.60371],"type":"Point"}
}