{
  "type": "Feature",
  "properties": {
    "gn:admin1_code":"4",
    "gn:asciiname":"Monte Oscuro",
    "gn:country_code":"VE",
    "gn:dem":186,
    "gn:feature_class":"P",
    "gn:feature_code":"PPL",
    "gn:name":"Monte Oscuro",
    "gn:population":0,
    "gn:timezone":"America/Caracas",
    "iso:country":"VE",
    "wof:name":"Monte Oscuro",
    "wof:placetype":"locality"
},
  "geometry": {"coordinates":[-66.91169000000001,9.52022],"type":"Point"}
}