{
  "type": "Feature",
  "properties": {
    "gn:admin1_code":"12",
    "gn:asciiname":"El Caracol",
    "gn:country_code":"VE",
    "gn:dem":145,
    "gn:feature_class":"P",
    "gn:feature_code":"PPL",
    "gn:name":"El Caracol",
    "gn:population":0,
    "gn:timezone":"America/Caracas",
    "iso:country":"VE",
    "wof:name":"El Caracol",
    "wof:placetype":"locality"
},
  "geometry": {"coordinates":[-65.90011,9.38483],"type":"Point"}
}