{
  "type": "Feature",
  "properties": {
    "gn:admin1_code":"99",
    "gn:asciiname":"Venevision",
    "gn:country_code":"VE",
    "gn:dem":1173,
    "gn:feature_class":"P",
    "gn:feature_code":"PPL",
    "gn:name":"Venevisi\u00f3n",
    "gn:population":0,
    "gn:timezone":"America/Caracas",
    "iso:country":"VE",
    "wof:name":"Venevision",
    "wof:placetype":"locality"
},
  "geometry": {"coordinates":[-70.71666999999999,10.15],"type":"Point"}
}