{
  "type": "Feature",
  "properties": {
    "gn:admin1_code":"4",
    "gn:asciiname":"Conofe",
    "gn:country_code":"VE",
    "gn:dem":959,
    "gn:feature_class":"P",
    "gn:feature_code":"PPL",
    "gn:name":"Conofe",
    "gn:population":0,
    "gn:timezone":"America/Caracas",
    "iso:country":"VE",
    "wof:name":"Conofe",
    "wof:placetype":"locality"
},
  "geometry": {"coordinates":[-67.16667,10.21667],"type":"Point"}
}