{
  "type": "Feature",
  "properties": {
    "gn:admin1_code":"11",
    "gn:asciiname":"El Cauca",
    "gn:country_code":"VE",
    "gn:dem":16,
    "gn:feature_class":"P",
    "gn:feature_code":"PPL",
    "gn:name":"El Cauca",
    "gn:population":0,
    "gn:timezone":"America/Caracas",
    "iso:country":"VE",
    "wof:name":"El Cauca",
    "wof:placetype":"locality"
},
  "geometry": {"coordinates":[-70.30844999999999,11.31917],"type":"Point"}
}