{
  "type": "Feature",
  "properties": {
    "gn:admin1_code":"20",
    "gn:asciiname":"La Union",
    "gn:country_code":"VE",
    "gn:dem":1490,
    "gn:feature_class":"P",
    "gn:feature_code":"PPL",
    "gn:name":"La Uni\u00f3n",
    "gn:population":0,
    "gn:timezone":"America/Caracas",
    "iso:country":"VE",
    "wof:name":"La Union",
    "wof:placetype":"locality"
},
  "geometry": {"coordinates":[-72.34364000000002,7.78327],"type":"Point"}
}