{
  "type": "Feature",
  "properties": {
    "gn:admin1_code":"23",
    "gn:asciiname":"Corea",
    "gn:country_code":"VE",
    "gn:dem":-4,
    "gn:feature_class":"P",
    "gn:feature_code":"PPL",
    "gn:name":"Corea",
    "gn:population":0,
    "gn:timezone":"America/Caracas",
    "iso:country":"VE",
    "name:cat_x_preferred":[
        "Corea"
    ],
    "name:ceb_x_preferred":[
        "Corea"
    ],
    "name:deu_x_preferred":[
        "Corea"
    ],
    "name:ita_x_preferred":[
        "Corea"
    ],
    "name:spa_x_preferred":[
        "Corea"
    ],
    "name:swe_x_preferred":[
        "Corea"
    ],
    "wof:name":"Corea",
    "wof:placetype":"locality"
},
  "geometry": {"coordinates":[-71.24196999999999,10.1001],"type":"Point"}
}