{
  "type": "Feature",
  "properties": {
    "gn:admin1_code":"23.0",
    "gn:asciiname":"La Entrada",
    "gn:country_code":"VE",
    "gn:dem":65,
    "gn:feature_class":"P",
    "gn:feature_code":"PPLL",
    "gn:name":"La Entrada",
    "gn:population":0,
    "gn:timezone":"America/Caracas",
    "iso:country":"VE",
    "name:bul_x_preferred":[
        "\u041b\u0430 \u0415\u043d\u0442\u0440\u0430\u0434\u0430"
    ],
    "name:ceb_x_preferred":[
        "La Entrada"
    ],
    "name:fra_x_preferred":[
        "La Entrada"
    ],
    "name:por_x_preferred":[
        "La Entrada"
    ],
    "name:spa_x_preferred":[
        "La Entrada"
    ],
    "name:urd_x_preferred":[
        "\u0644\u0627 \u06cc\u0646\u0679\u0631\u0627\u0688\u0627"
    ],
    "wof:name":"La Entrada",
    "wof:placetype":"locality"
},
  "geometry": {"coordinates":[-72.15827,10.43098],"type":"Point"}
}