{
  "type": "Feature",
  "properties": {
    "gn:admin1_code":"05",
    "gn:asciiname":"El Charal",
    "gn:country_code":"VE",
    "gn:dem":293,
    "gn:feature_class":"P",
    "gn:feature_code":"PPL",
    "gn:name":"El Charal",
    "gn:population":0,
    "gn:timezone":"America/Caracas",
    "iso:country":"VE",
    "wof:name":"El Charal",
    "wof:placetype":"locality"
},
  "geometry": {"coordinates":[-70.30063,8.73461],"type":"Point"}
}