{
  "type": "Feature",
  "properties": {
    "gn:admin1_code":"23.0",
    "gn:asciiname":"Casa de Tabla",
    "gn:country_code":"VE",
    "gn:dem":4,
    "gn:feature_class":"P",
    "gn:feature_code":"PPLL",
    "gn:name":"Casa de Tabla",
    "gn:population":0,
    "gn:timezone":"America/Caracas",
    "iso:country":"VE",
    "wof:name":"Casa de Tabla",
    "wof:placetype":"locality"
},
  "geometry": {"coordinates":[-72.09347,9.04035],"type":"Point"}
}