{
  "type": "Feature",
  "properties": {
    "gn:admin1_code":"20.0",
    "gn:asciiname":"Las Dantas",
    "gn:country_code":"VE",
    "gn:dem":919,
    "gn:feature_class":"P",
    "gn:feature_code":"PPL",
    "gn:name":"Las Dantas",
    "gn:population":0,
    "gn:timezone":"America/Caracas",
    "iso:country":"VE",
    "wof:name":"Las Dantas",
    "wof:placetype":"locality"
},
  "geometry": {"coordinates":[-72.41944000000002,7.69167],"type":"Point"}
}