{
  "type": "Feature",
  "properties": {
    "gn:admin1_code":"02",
    "gn:asciiname":"Peladero Picapica",
    "gn:country_code":"VE",
    "gn:dem":115,
    "gn:feature_class":"P",
    "gn:feature_code":"PPLL",
    "gn:name":"Peladero Picapica",
    "gn:population":0,
    "gn:timezone":"America/Caracas",
    "iso:country":"VE",
    "wof:name":"Peladero Picapica",
    "wof:placetype":"locality"
},
  "geometry": {"coordinates":[-64.70742,9.69399],"type":"Point"}
}