{
  "type": "Feature",
  "properties": {
    "gn:admin1_code":"4.0",
    "gn:asciiname":"El Palmar",
    "gn:country_code":"VE",
    "gn:dem":198,
    "gn:feature_class":"P",
    "gn:feature_code":"PPL",
    "gn:name":"El Palmar",
    "gn:population":0,
    "gn:timezone":"America/Caracas",
    "iso:country":"VE",
    "wof:name":"El Palmar",
    "wof:placetype":"locality"
},
  "geometry": {"coordinates":[-66.78652,9.38927],"type":"Point"}
}