{
  "type": "Feature",
  "properties": {
    "gn:admin1_code":"26",
    "gn:asciiname":"Templon",
    "gn:country_code":"VE",
    "gn:dem":876,
    "gn:feature_class":"P",
    "gn:feature_code":"PPL",
    "gn:name":"Templ\u00f3n",
    "gn:population":0,
    "gn:timezone":"America/Caracas",
    "iso:country":"VE",
    "wof:name":"Templon",
    "wof:placetype":"locality"
},
  "geometry": {"coordinates":[-67.15000000000001,10.51667],"type":"Point"}
}