{
  "type": "Feature",
  "properties": {
    "gn:admin1_code":"26",
    "gn:asciiname":"Templon",
    "gn:country_code":"VE",
    "gn:dem":876,
    "gn:feature_class":"P",
    "gn:feature_code":"PPL",
    "gn:name":"Templ\u00f3n",
    "gn:population":0,
    "gn:timezone":"America/Caracas",
    "iso:country":"VE",
    "name:deu_x_preferred":[
        "Templon"
    ],
    "name:fra_x_preferred":[
        "Templon"
    ],
    "name:ido_x_preferred":[
        "Templono"
    ],
    "name:ita_x_preferred":[
        "Templon"
    ],
    "name:pol_x_preferred":[
        "Templon"
    ],
    "name:rus_x_preferred":[
        "\u0422\u044f\u0431\u043b\u043e"
    ],
    "name:spa_x_preferred":[
        "Templ\u00f3n"
    ],
    "name:tur_x_preferred":[
        "Templon"
    ],
    "wof:name":"Templon",
    "wof:placetype":"locality"
},
  "geometry": {"coordinates":[-67.15000000000001,10.51667],"type":"Point"}
}