{
  "type": "Feature",
  "properties": {
    "gn:admin1_code":"4",
    "gn:asciiname":"Pantin",
    "gn:country_code":"VE",
    "gn:dem":1686,
    "gn:feature_class":"P",
    "gn:feature_code":"PPL",
    "gn:name":"Pantin",
    "gn:population":0,
    "gn:timezone":"America/Caracas",
    "iso:country":"VE",
    "name:ara_x_preferred":[
        "\u0628\u0627\u0646\u062a\u0627\u0646"
    ],
    "name:azb_x_preferred":[
        "\u067e\u0627\u0646\u062a\u0646"
    ],
    "name:bre_x_preferred":[
        "Pantin"
    ],
    "name:cat_x_preferred":[
        "Pantin"
    ],
    "name:ceb_x_preferred":[
        "Pantin"
    ],
    "name:ces_x_preferred":[
        "Pantin"
    ],
    "name:dan_x_preferred":[
        "Pantin"
    ],
    "name:deu_x_preferred":[
        "Pantin"
    ],
    "name:epo_x_preferred":[
        "Pantin"
    ],
    "name:eus_x_preferred":[
        "Pantin"
    ],
    "name:fas_x_preferred":[
        "\u067e\u0627\u0646\u062a\u0646"
    ],
    "name:fra_x_preferred":[
        "Pantin"
    ],
    "name:hun_x_preferred":[
        "Pantin"
    ],
    "name:ind_x_preferred":[
        "Pantin"
    ],
    "name:ita_x_preferred":[
        "Pantin"
    ],
    "name:jpn_x_preferred":[
        "\u30d1\u30f3\u30bf\u30f3"
    ],
    "name:kaz_x_preferred":[
        "\u041f\u0430\u043d\u0442\u0435\u043d"
    ],
    "name:lat_x_preferred":[
        "Pantin"
    ],
    "name:msa_x_preferred":[
        "Pantin"
    ],
    "name:mzn_x_preferred":[
        "\u067e\u0627\u0646\u062a\u0646"
    ],
    "name:nld_x_preferred":[
        "Pantin"
    ],
    "name:nno_x_preferred":[
        "Pantin"
    ],
    "name:nor_x_preferred":[
        "Pantin"
    ],
    "name:oci_x_preferred":[
        "Pantin"
    ],
    "name:pol_x_preferred":[
        "Pantin"
    ],
    "name:por_x_preferred":[
        "Pantin"
    ],
    "name:ron_x_preferred":[
        "Pantin"
    ],
    "name:slk_x_preferred":[
        "Pantin"
    ],
    "name:slv_x_preferred":[
        "Pantin"
    ],
    "name:spa_x_preferred":[
        "Pantin"
    ],
    "name:srp_x_preferred":[
        "\u041f\u0430\u043d\u0442\u0435\u043d"
    ],
    "name:swa_x_preferred":[
        "Pantin"
    ],
    "name:swe_x_preferred":[
        "Pantin"
    ],
    "name:tat_x_preferred":[
        "\u041f\u0430\u043d\u0442\u0435\u043d"
    ],
    "name:tur_x_preferred":[
        "Pantin"
    ],
    "name:ukr_x_preferred":[
        "\u041f\u0430\u043d\u0442\u0435\u043d"
    ],
    "name:vie_x_preferred":[
        "Pantin"
    ],
    "name:vol_x_preferred":[
        "Pantin"
    ],
    "name:war_x_preferred":[
        "Pantin"
    ],
    "wof:name":"Pantin",
    "wof:placetype":"locality"
},
  "geometry": {"coordinates":[-67.43333,10.35],"type":"Point"}
}