{
  "type": "Feature",
  "properties": {
    "gn:admin1_code":"4",
    "gn:asciiname":"Pantin",
    "gn:country_code":"VE",
    "gn:dem":1686,
    "gn:feature_class":"P",
    "gn:feature_code":"PPL",
    "gn:name":"Pantin",
    "gn:population":0,
    "gn:timezone":"America/Caracas",
    "iso:country":"VE",
    "wof:name":"Pantin",
    "wof:placetype":"locality"
},
  "geometry": {"coordinates":[-67.43333,10.35],"type":"Point"}
}