{
  "type": "Feature",
  "properties": {
    "gn:admin1_code":"07",
    "gn:asciiname":"Santa Cecilia",
    "gn:country_code":"VE",
    "gn:dem":488,
    "gn:feature_class":"P",
    "gn:feature_code":"PPLL",
    "gn:name":"Santa Cecilia",
    "gn:population":0,
    "gn:timezone":"America/Caracas",
    "iso:country":"VE",
    "wof:name":"Santa Cecilia",
    "wof:placetype":"locality"
},
  "geometry": {"coordinates":[-68.00596,10.18882],"type":"Point"}
}