{
  "type": "Feature",
  "properties": {
    "gn:admin1_code":"7",
    "gn:asciiname":"Los Samanes",
    "gn:country_code":"VE",
    "gn:dem":455,
    "gn:feature_class":"P",
    "gn:feature_code":"PPL",
    "gn:name":"Los Samanes",
    "gn:population":0,
    "gn:timezone":"America/Caracas",
    "iso:country":"VE",
    "wof:name":"Los Samanes",
    "wof:placetype":"locality"
},
  "geometry": {"coordinates":[-67.97809000000001,10.16704],"type":"Point"}
}