{
  "type": "Feature",
  "properties": {
    "iso:country":"VE",
    "qs:gn_pop":0,
    "qs:name":"Altagracia",
    "qs:name_adm0":"Venezuela",
    "qs:name_adm1":"Zulia",
    "qs:photos":18,
    "qs:photos_1k":4,
    "qs:photos_9k":1,
    "qs:photos_9r":3,
    "qs:photos_all":100,
    "qs:photos_sr":1,
    "qs:placetype":"LocalAdmin",
    "qs:pop_sr":"0",
    "qs:woe_adm0":23424982,
    "wof:name":"Altagracia",
    "wof:placetype":"localadmin"
},
  "geometry": {"coordinates":[-71.52815200000001,10.709763],"type":"Point"}
}