{
  "type": "Feature",
  "properties": {
    "iso:country":"VE",
    "name:cat_x_preferred":[
        "Altagracia"
    ],
    "name:fas_x_preferred":[
        "\u0627\u0644\u062a\u0627\u06af\u0631\u0627\u0634\u06cc\u0627"
    ],
    "name:fra_x_preferred":[
        "Altagracia"
    ],
    "name:ita_x_preferred":[
        "Altagracia"
    ],
    "name:spa_x_preferred":[
        "Altagracia"
    ],
    "name:swe_x_preferred":[
        "Altagracia"
    ],
    "name:urd_x_preferred":[
        "\u0627\u0644\u062a\u0627\u06af\u0631\u0627\u0633\u06cc\u0627"
    ],
    "name:vie_x_preferred":[
        "Altagracia"
    ],
    "name:zho_x_preferred":[
        "\u963f\u723e\u5854\u683c\u62c9\u897f\u4e9e"
    ],
    "qs:gn_pop":0,
    "qs:name":"Altagracia",
    "qs:name_adm0":"Venezuela",
    "qs:name_adm1":"Zulia",
    "qs:photos":18,
    "qs:photos_1k":4,
    "qs:photos_9k":1,
    "qs:photos_9r":3,
    "qs:photos_all":100,
    "qs:photos_sr":1,
    "qs:placetype":"LocalAdmin",
    "qs:pop_sr":"0",
    "qs:woe_adm0":23424982,
    "wof:name":"Altagracia",
    "wof:placetype":"localadmin"
},
  "geometry": {"coordinates":[-71.52815200000001,10.709763],"type":"Point"}
}