{
  "type": "Feature",
  "properties": {
    "iso:country":"VE",
    "qs:gn_country":"VE",
    "qs:gn_fcode":"PPL",
    "qs:gn_pop":0,
    "qs:name":"La Urbina",
    "qs:name_adm0":"Venezuela",
    "qs:name_adm1":"Miranda",
    "qs:photos":258,
    "qs:photos_1k":52,
    "qs:photos_9k":1,
    "qs:photos_9r":4,
    "qs:photos_all":258,
    "qs:photos_sr":5,
    "qs:placetype":"Town",
    "qs:pop_sr":"0",
    "qs:woe_adm0":23424982,
    "wof:name":"La Urbina",
    "wof:placetype":"locality"
},
  "geometry": {"coordinates":[-66.07444,10.22639],"type":"Point"}
}