{
  "type": "Feature",
  "properties": {
    "gn:admin1_code":"05",
    "gn:asciiname":"Mata de Mango",
    "gn:country_code":"VE",
    "gn:dem":316,
    "gn:feature_class":"P",
    "gn:feature_code":"PPL",
    "gn:name":"Mata de Mango",
    "gn:population":0,
    "gn:timezone":"America/Caracas",
    "iso:country":"VE",
    "wof:name":"Mata de Mango",
    "wof:placetype":"locality"
},
  "geometry": {"coordinates":[-70.15528,8.81195],"type":"Point"}
}