{
  "type": "Feature",
  "properties": {
    "gn:admin1_code":"11.0",
    "gn:asciiname":"Tacalito",
    "gn:country_code":"VE",
    "gn:dem":138,
    "gn:feature_class":"P",
    "gn:feature_code":"PPL",
    "gn:name":"Tacalito",
    "gn:population":0,
    "gn:timezone":"America/Caracas",
    "iso:country":"VE",
    "wof:name":"Tacalito",
    "wof:placetype":"locality"
},
  "geometry": {"coordinates":[-69.47125,11.48798],"type":"Point"}
}