{
  "type": "Feature",
  "properties": {
    "gn:admin1_code":"20",
    "gn:asciiname":"Rio Arriba",
    "gn:country_code":"VE",
    "gn:dem":2181,
    "gn:feature_class":"P",
    "gn:feature_code":"PPL",
    "gn:name":"R\u00edo Arriba",
    "gn:population":0,
    "gn:timezone":"America/Caracas",
    "iso:country":"VE",
    "wof:name":"Rio Arriba",
    "wof:placetype":"locality"
},
  "geometry": {"coordinates":[-72.06494000000001,8.00382],"type":"Point"}
}