{
  "type": "Feature",
  "properties": {
    "gn:admin1_code":"15.0",
    "gn:asciiname":"Barrialito",
    "gn:country_code":"VE",
    "gn:dem":1493,
    "gn:feature_class":"P",
    "gn:feature_code":"PPL",
    "gn:name":"Barrialito",
    "gn:population":0,
    "gn:timezone":"America/Caracas",
    "iso:country":"VE",
    "wof:name":"Barrialito",
    "wof:placetype":"locality"
},
  "geometry": {"coordinates":[-66.97471,10.35882],"type":"Point"}
}