{
  "type": "Feature",
  "properties": {
    "gn:admin1_code":"12",
    "gn:asciiname":"Chaguaramira",
    "gn:cc2":"VE",
    "gn:country_code":"VE",
    "gn:dem":167,
    "gn:feature_class":"P",
    "gn:feature_code":"PPL",
    "gn:name":"Chaguaramira",
    "gn:population":0,
    "gn:timezone":"America/Caracas",
    "iso:country":"VE",
    "name:und_x_variant":[
        "La Chaguaramita",
        "Chaguaramira"
    ],
    "wof:name":"Chaguaramira",
    "wof:placetype":"locality"
},
  "geometry": {"coordinates":[-65.91667,8.98333],"type":"Point"}
}