{
  "type": "Feature",
  "properties": {
    "gn:admin1_code":"8",
    "gn:asciiname":"Las Babas",
    "gn:country_code":"VE",
    "gn:dem":95,
    "gn:feature_class":"P",
    "gn:feature_code":"PPL",
    "gn:name":"Las Babas",
    "gn:population":0,
    "gn:timezone":"America/Caracas",
    "iso:country":"VE",
    "wof:name":"Las Babas",
    "wof:placetype":"locality"
},
  "geometry": {"coordinates":[-68.44333,9.48618],"type":"Point"}
}