{
  "type": "Feature",
  "properties": {
    "gn:admin1_code":"11",
    "gn:asciiname":"Zazarida",
    "gn:country_code":"VE",
    "gn:dem":778,
    "gn:feature_class":"P",
    "gn:feature_code":"PPL",
    "gn:name":"Zaz\u00e1rida",
    "gn:population":0,
    "gn:timezone":"America/Caracas",
    "iso:country":"VE",
    "wof:name":"Zazarida",
    "wof:placetype":"locality"
},
  "geometry": {"coordinates":[-69.64286,11.14244],"type":"Point"}
}