{
  "type": "Feature",
  "properties": {
    "gn:admin1_code":"8",
    "gn:asciiname":"Camoruco",
    "gn:country_code":"VE",
    "gn:dem":295,
    "gn:feature_class":"P",
    "gn:feature_code":"PPL",
    "gn:name":"Camoruco",
    "gn:population":0,
    "gn:timezone":"America/Caracas",
    "iso:country":"VE",
    "wof:name":"Camoruco",
    "wof:placetype":"locality"
},
  "geometry": {"coordinates":[-67.7834,9.70346],"type":"Point"}
}