{
  "type": "Feature",
  "properties": {
    "gn:admin1_code":"6",
    "gn:asciiname":"El Rosario",
    "gn:country_code":"VE",
    "gn:dem":73,
    "gn:feature_class":"P",
    "gn:feature_code":"PPL",
    "gn:name":"El Rosario",
    "gn:population":0,
    "gn:timezone":"America/Caracas",
    "iso:country":"VE",
    "wof:name":"El Rosario",
    "wof:placetype":"locality"
},
  "geometry": {"coordinates":[-65.57993,7.74788],"type":"Point"}
}