{
  "type": "Feature",
  "properties": {
    "gn:admin1_code":"6",
    "gn:asciiname":"Caraqueno",
    "gn:country_code":"VE",
    "gn:dem":273,
    "gn:feature_class":"P",
    "gn:feature_code":"PPL",
    "gn:name":"Caraque\u00f1o",
    "gn:population":0,
    "gn:timezone":"America/Caracas",
    "iso:country":"VE",
    "wof:name":"Caraqueno",
    "wof:placetype":"locality"
},
  "geometry": {"coordinates":[-63.23333,7.55],"type":"Point"}
}