{
  "type": "Feature",
  "properties": {
    "gn:admin1_code":"3.0",
    "gn:asciiname":"Macanilla",
    "gn:country_code":"VE",
    "gn:dem":69,
    "gn:feature_class":"P",
    "gn:feature_code":"PPLL",
    "gn:name":"Macanilla",
    "gn:population":0,
    "gn:timezone":"America/Caracas",
    "iso:country":"VE",
    "wof:name":"Macanilla",
    "wof:placetype":"locality"
},
  "geometry": {"coordinates":[-67.62889,6.01111],"type":"Point"}
}