{
  "type": "Feature",
  "properties": {
    "gn:admin1_code":"23",
    "gn:asciiname":"Los Haticos",
    "gn:country_code":"VE",
    "gn:dem":3,
    "gn:feature_class":"P",
    "gn:feature_code":"PPL",
    "gn:name":"Los Haticos",
    "gn:population":0,
    "gn:timezone":"America/Caracas",
    "iso:country":"VE",
    "name:spa_x_preferred":[
        "Los Haticos"
    ],
    "wof:name":"Los Haticos",
    "wof:placetype":"locality"
},
  "geometry": {"coordinates":[-71.61667,10.63333],"type":"Point"}
}