{
  "type": "Feature",
  "properties": {
    "gn:admin1_code":"3",
    "gn:asciiname":"La Florena",
    "gn:country_code":"VE",
    "gn:dem":96,
    "gn:feature_class":"P",
    "gn:feature_code":"PPL",
    "gn:name":"La Flore\u00f1a",
    "gn:population":0,
    "gn:timezone":"America/Caracas",
    "iso:country":"VE",
    "wof:name":"La Florena",
    "wof:placetype":"locality"
},
  "geometry": {"coordinates":[-69.63715000000001,7.87774],"type":"Point"}
}