{
  "type": "Feature",
  "properties": {
    "gn:admin1_code":"14",
    "gn:asciiname":"El Chamita",
    "gn:country_code":"VE",
    "gn:dem":1217,
    "gn:feature_class":"P",
    "gn:feature_code":"PPL",
    "gn:name":"El Chamita",
    "gn:population":0,
    "gn:timezone":"America/Caracas",
    "iso:country":"VE",
    "wof:name":"El Chamita",
    "wof:placetype":"locality"
},
  "geometry": {"coordinates":[-71.17856,8.55886],"type":"Point"}
}