{
  "type": "Feature",
  "properties": {
    "gn:admin1_code":"5.0",
    "gn:asciiname":"El Orozquero",
    "gn:country_code":"VE",
    "gn:dem":61,
    "gn:feature_class":"P",
    "gn:feature_code":"PPL",
    "gn:name":"El Orozquero",
    "gn:population":0,
    "gn:timezone":"America/Caracas",
    "iso:country":"VE",
    "wof:name":"El Orozquero",
    "wof:placetype":"locality"
},
  "geometry": {"coordinates":[-67.83750000000001,8.09028],"type":"Point"}
}