{
  "type": "Feature",
  "properties": {
    "gn:admin1_code":"6.0",
    "gn:asciiname":"Moriche",
    "gn:country_code":"VE",
    "gn:dem":151,
    "gn:feature_class":"P",
    "gn:feature_code":"PPL",
    "gn:name":"Moriche",
    "gn:population":0,
    "gn:timezone":"America/Caracas",
    "iso:country":"VE",
    "wof:name":"Moriche",
    "wof:placetype":"locality"
},
  "geometry": {"coordinates":[-61.31833,7.21444],"type":"Point"}
}