{
  "type": "Feature",
  "properties": {
    "gn:admin1_code":"6",
    "gn:asciiname":"Amurug",
    "gn:cc2":"VE",
    "gn:country_code":"VE",
    "gn:dem":910,
    "gn:feature_class":"P",
    "gn:feature_code":"PPL",
    "gn:name":"Amurug",
    "gn:population":0,
    "gn:timezone":"America/Caracas",
    "iso:country":"VE",
    "name:und_x_variant":[
        "Amauruc",
        "Amurug"
    ],
    "wof:name":"Amurug",
    "wof:placetype":"locality"
},
  "geometry": {"coordinates":[-61.68333000000001,5.23333],"type":"Point"}
}