{
  "type": "Feature",
  "properties": {
    "gn:admin1_code":"26",
    "gn:asciiname":"La Cortada",
    "gn:country_code":"VE",
    "gn:dem":669,
    "gn:feature_class":"P",
    "gn:feature_code":"PPLL",
    "gn:name":"La Cortada",
    "gn:population":0,
    "gn:timezone":"America/Caracas",
    "iso:country":"VE",
    "wof:name":"La Cortada",
    "wof:placetype":"locality"
},
  "geometry": {"coordinates":[-66.66761,10.58534],"type":"Point"}
}