{
  "type": "Feature",
  "properties": {
    "gn:admin1_code":"13",
    "gn:asciiname":"El Roble",
    "gn:country_code":"VE",
    "gn:dem":302,
    "gn:feature_class":"P",
    "gn:feature_code":"PPL",
    "gn:name":"El Roble",
    "gn:population":0,
    "gn:timezone":"America/Caracas",
    "iso:country":"VE",
    "wof:name":"El Roble",
    "wof:placetype":"locality"
},
  "geometry": {"coordinates":[-69.13774000000001,9.80962],"type":"Point"}
}