{
  "type": "Feature",
  "properties": {
    "gn:admin1_code":"11.0",
    "gn:asciiname":"Mucaro",
    "gn:country_code":"VE",
    "gn:dem":248,
    "gn:feature_class":"P",
    "gn:feature_code":"PPL",
    "gn:name":"Mucaro",
    "gn:population":0,
    "gn:timezone":"America/Caracas",
    "iso:country":"VE",
    "wof:name":"Mucaro",
    "wof:placetype":"locality"
},
  "geometry": {"coordinates":[-70.34514,10.95929],"type":"Point"}
}