{
  "type": "Feature",
  "properties": {
    "gn:admin1_code":"8",
    "gn:asciiname":"Las Sardinas",
    "gn:country_code":"VE",
    "gn:dem":407,
    "gn:feature_class":"P",
    "gn:feature_code":"PPL",
    "gn:name":"Las Sardinas",
    "gn:population":0,
    "gn:timezone":"America/Caracas",
    "iso:country":"VE",
    "name:und_x_variant":[
        "Sardinas",
        "Sardina",
        "Sardinata",
        "Las Sardinas"
    ],
    "wof:name":"Las Sardinas",
    "wof:placetype":"locality"
},
  "geometry": {"coordinates":[-67.90354000000001,9.78695],"type":"Point"}
}