{
  "type": "Feature",
  "properties": {
    "gn:admin1_code":"3.0",
    "gn:asciiname":"Mata de Yuca",
    "gn:country_code":"VE",
    "gn:dem":53,
    "gn:feature_class":"P",
    "gn:feature_code":"PPLL",
    "gn:name":"Mata de Yuca",
    "gn:population":0,
    "gn:timezone":"America/Caracas",
    "iso:country":"VE",
    "wof:name":"Mata de Yuca",
    "wof:placetype":"locality"
},
  "geometry": {"coordinates":[-67.15106999999999,7.12849],"type":"Point"}
}