{
  "type": "Feature",
  "properties": {
    "gn:admin1_code":"18.0",
    "gn:asciiname":"El Tigre",
    "gn:country_code":"VE",
    "gn:dem":79,
    "gn:feature_class":"P",
    "gn:feature_code":"PPLL",
    "gn:name":"El Tigre",
    "gn:population":0,
    "gn:timezone":"America/Caracas",
    "iso:country":"VE",
    "name:spa_x_preferred":[
        "El Tigre"
    ],
    "wof:name":"El Tigre",
    "wof:placetype":"locality"
},
  "geometry": {"coordinates":[-68.84173,8.65702],"type":"Point"}
}