{
  "type": "Feature",
  "properties": {
    "gn:admin1_code":"3",
    "gn:asciiname":"Jobal",
    "gn:country_code":"VE",
    "gn:dem":107,
    "gn:feature_class":"P",
    "gn:feature_code":"PPL",
    "gn:name":"Jobal",
    "gn:population":0,
    "gn:timezone":"America/Caracas",
    "iso:country":"VE",
    "wof:name":"Jobal",
    "wof:placetype":"locality"
},
  "geometry": {"coordinates":[-70.14886,7.43435],"type":"Point"}
}