{
  "type": "Feature",
  "properties": {
    "gn:admin1_code":"11",
    "gn:asciiname":"Jusal",
    "gn:country_code":"VE",
    "gn:dem":657,
    "gn:feature_class":"P",
    "gn:feature_code":"PPL",
    "gn:name":"Jusal",
    "gn:population":0,
    "gn:timezone":"America/Caracas",
    "iso:country":"VE",
    "wof:name":"Jusal",
    "wof:placetype":"locality"
},
  "geometry": {"coordinates":[-69.47081999999999,10.72228],"type":"Point"}
}