{
  "type": "Feature",
  "properties": {
    "gn:admin1_code":"12",
    "gn:asciiname":"Las Lagunitas",
    "gn:country_code":"VE",
    "gn:dem":157,
    "gn:feature_class":"P",
    "gn:feature_code":"PPL",
    "gn:name":"Las Lagunitas",
    "gn:population":0,
    "gn:timezone":"America/Caracas",
    "iso:country":"VE",
    "wof:name":"Las Lagunitas",
    "wof:placetype":"locality"
},
  "geometry": {"coordinates":[-65.98683,9.13175],"type":"Point"}
}