{
  "type": "Feature",
  "properties": {
    "gn:admin1_code":"20",
    "gn:asciiname":"El Pabellon",
    "gn:country_code":"VE",
    "gn:dem":1517,
    "gn:feature_class":"P",
    "gn:feature_code":"PPL",
    "gn:name":"El Pabell\u00f3n",
    "gn:population":0,
    "gn:timezone":"America/Caracas",
    "iso:country":"VE",
    "wof:name":"El Pabellon",
    "wof:placetype":"locality"
},
  "geometry": {"coordinates":[-72.43042,7.64823],"type":"Point"}
}