{
  "type": "Feature",
  "properties": {
    "gn:admin1_code":"6.0",
    "gn:asciiname":"El Mosquito",
    "gn:country_code":"VE",
    "gn:dem":268,
    "gn:feature_class":"P",
    "gn:feature_code":"PPL",
    "gn:name":"El Mosquito",
    "gn:population":0,
    "gn:timezone":"America/Caracas",
    "iso:country":"VE",
    "wof:name":"El Mosquito",
    "wof:placetype":"locality"
},
  "geometry": {"coordinates":[-62.23944,7.85167],"type":"Point"}
}