{
  "type": "Feature",
  "properties": {
    "gn:admin1_code":"02",
    "gn:asciiname":"Cerro Negro",
    "gn:country_code":"VE",
    "gn:dem":1161,
    "gn:feature_class":"P",
    "gn:feature_code":"PPL",
    "gn:name":"Cerro Negro",
    "gn:population":0,
    "gn:timezone":"America/Caracas",
    "iso:country":"VE",
    "wof:name":"Cerro Negro",
    "wof:placetype":"locality"
},
  "geometry": {"coordinates":[-64.24619,10.03211],"type":"Point"}
}