{
  "type": "Feature",
  "properties": {
    "gn:admin1_code":"11.0",
    "gn:asciiname":"La Veguita",
    "gn:country_code":"VE",
    "gn:dem":797,
    "gn:feature_class":"P",
    "gn:feature_code":"PPL",
    "gn:name":"La Veguita",
    "gn:population":0,
    "gn:timezone":"America/Caracas",
    "iso:country":"VE",
    "wof:name":"La Veguita",
    "wof:placetype":"locality"
},
  "geometry": {"coordinates":[-69.48687,10.7737],"type":"Point"}
}