{
  "type": "Feature",
  "properties": {
    "gn:admin1_code":"02",
    "gn:asciiname":"Saquimare",
    "gn:country_code":"VE",
    "gn:dem":121,
    "gn:feature_class":"P",
    "gn:feature_code":"PPLL",
    "gn:name":"Saquimare",
    "gn:population":0,
    "gn:timezone":"America/Caracas",
    "iso:country":"VE",
    "wof:name":"Saquimare",
    "wof:placetype":"locality"
},
  "geometry": {"coordinates":[-64.36735999999999,8.46035],"type":"Point"}
}