{
  "type": "Feature",
  "properties": {
    "gn:admin1_code":"16",
    "gn:asciiname":"Los Caracoles",
    "gn:country_code":"VE",
    "gn:dem":585,
    "gn:feature_class":"P",
    "gn:feature_code":"PPL",
    "gn:name":"Los Caracoles",
    "gn:population":0,
    "gn:timezone":"America/Caracas",
    "iso:country":"VE",
    "name:und_x_variant":[
        "Los Caracales",
        "Los Caracoles"
    ],
    "wof:name":"Los Caracoles",
    "wof:placetype":"locality"
},
  "geometry": {"coordinates":[-63.38539,10.05322],"type":"Point"}
}