{
  "type": "Feature",
  "properties": {
    "gn:admin1_code":"15",
    "gn:asciiname":"Laguneta",
    "gn:country_code":"VE",
    "gn:dem":1505,
    "gn:feature_class":"P",
    "gn:feature_code":"PPL",
    "gn:name":"Laguneta",
    "gn:population":0,
    "gn:timezone":"America/Caracas",
    "iso:country":"VE",
    "wof:name":"Laguneta",
    "wof:placetype":"locality"
},
  "geometry": {"coordinates":[-67.13333,10.33333],"type":"Point"}
}