{
  "type": "Feature",
  "properties": {
    "iso:country":"VE",
    "qs:gn_pop":0,
    "qs:name":"Tocopero",
    "qs:name_adm0":"Venezuela",
    "qs:name_adm1":"Falcon",
    "qs:photos":1,
    "qs:photos_1k":1,
    "qs:photos_9k":1,
    "qs:photos_9r":1,
    "qs:photos_all":1,
    "qs:photos_sr":1,
    "qs:placetype":"LocalAdmin",
    "qs:pop_sr":"0",
    "qs:woe_adm0":23424982,
    "wof:name":"Tocopero",
    "wof:placetype":"localadmin"
},
  "geometry": {"coordinates":[-69.25892,11.49897],"type":"Point"}
}