{
  "type": "Feature",
  "properties": {
    "gn:admin1_code":"12.0",
    "gn:asciiname":"Los Islenos",
    "gn:country_code":"VE",
    "gn:dem":176,
    "gn:feature_class":"P",
    "gn:feature_code":"PPL",
    "gn:name":"Los Isle\u00f1os",
    "gn:population":0,
    "gn:timezone":"America/Caracas",
    "iso:country":"VE",
    "wof:name":"Los Islenos",
    "wof:placetype":"locality"
},
  "geometry": {"coordinates":[-66.06115,9.20839],"type":"Point"}
}