{
  "type": "Feature",
  "properties": {
    "gn:admin1_code":"2",
    "gn:asciiname":"Medanito",
    "gn:country_code":"VE",
    "gn:dem":139,
    "gn:feature_class":"P",
    "gn:feature_code":"PPL",
    "gn:name":"Medanito",
    "gn:population":0,
    "gn:timezone":"America/Caracas",
    "iso:country":"VE",
    "wof:name":"Medanito",
    "wof:placetype":"locality"
},
  "geometry": {"coordinates":[-64.99892,8.57064],"type":"Point"}
}