{
  "type": "Feature",
  "properties": {
    "gn:admin1_code":"20.0",
    "gn:asciiname":"La Mesa del Rio",
    "gn:country_code":"VE",
    "gn:dem":606,
    "gn:feature_class":"P",
    "gn:feature_code":"PPL",
    "gn:name":"La Mesa del R\u00edo",
    "gn:population":0,
    "gn:timezone":"America/Caracas",
    "iso:country":"VE",
    "wof:name":"La Mesa del Rio",
    "wof:placetype":"locality"
},
  "geometry": {"coordinates":[-71.87246,8.40856],"type":"Point"}
}