{
  "type": "Feature",
  "properties": {
    "gn:admin1_code":"02",
    "gn:asciiname":"Los Pajaritos",
    "gn:country_code":"VE",
    "gn:dem":1326,
    "gn:feature_class":"P",
    "gn:feature_code":"PPL",
    "gn:name":"Los Pajaritos",
    "gn:population":0,
    "gn:timezone":"America/Caracas",
    "iso:country":"VE",
    "wof:name":"Los Pajaritos",
    "wof:placetype":"locality"
},
  "geometry": {"coordinates":[-64.10133,10.06317],"type":"Point"}
}