{
  "type": "Feature",
  "properties": {
    "iso:country":"VE",
    "name:ast_x_preferred":[
        "Propatria"
    ],
    "name:bul_x_preferred":[
        "Propatria"
    ],
    "name:deu_x_preferred":[
        "Propatria"
    ],
    "name:eng_x_preferred":[
        "Propatria"
    ],
    "name:fra_x_preferred":[
        "Propatria"
    ],
    "name:ita_x_preferred":[
        "Propatria"
    ],
    "name:lat_x_preferred":[
        "Propatria"
    ],
    "name:nld_x_preferred":[
        "Propatria"
    ],
    "name:rus_x_preferred":[
        "Propatria"
    ],
    "name:spa_x_preferred":[
        "Propatria"
    ],
    "name:ukr_x_preferred":[
        "Propatria"
    ],
    "name:vie_x_preferred":[
        "Propatria"
    ],
    "qs:gn_pop":0,
    "qs:name":"Propatria",
    "qs:name_adm0":"Venezuela",
    "qs:name_adm1":"Distrito Federal",
    "qs:photos":37,
    "qs:photos_1k":7,
    "qs:photos_9k":1,
    "qs:photos_9r":2,
    "qs:photos_all":37,
    "qs:photos_sr":2,
    "qs:placetype":"Town",
    "qs:pop_sr":"0",
    "qs:woe_adm0":23424982,
    "wd:wordcount":16,
    "wof:name":"Propatria",
    "wof:placetype":"locality"
},
  "geometry": {"coordinates":[-66.95272,10.509585],"type":"Point"}
}