{
  "type": "Feature",
  "properties": {
    "gn:admin1_code":"13",
    "gn:asciiname":"Los Quimbombos",
    "gn:country_code":"VE",
    "gn:dem":928,
    "gn:feature_class":"P",
    "gn:feature_code":"PPLL",
    "gn:name":"Los Quimbombos",
    "gn:population":0,
    "gn:timezone":"America/Caracas",
    "iso:country":"VE",
    "wof:name":"Los Quimbombos",
    "wof:placetype":"locality"
},
  "geometry": {"coordinates":[-69.9089,10.52095],"type":"Point"}
}