{
  "type": "Feature",
  "properties": {
    "gn:admin1_code":"1.0",
    "gn:asciiname":"Laja Negra",
    "gn:country_code":"VE",
    "gn:dem":77,
    "gn:feature_class":"P",
    "gn:feature_code":"PPLL",
    "gn:name":"Laja Negra",
    "gn:population":0,
    "gn:timezone":"America/Caracas",
    "iso:country":"VE",
    "wof:name":"Laja Negra",
    "wof:placetype":"locality"
},
  "geometry": {"coordinates":[-67.68833000000001,4.735],"type":"Point"}
}