{
  "type": "Feature",
  "properties": {
    "gn:admin1_code":"07",
    "gn:asciiname":"El Placer",
    "gn:country_code":"VE",
    "gn:dem":985,
    "gn:feature_class":"P",
    "gn:feature_code":"PPLL",
    "gn:name":"El Placer",
    "gn:population":0,
    "gn:timezone":"America/Caracas",
    "iso:country":"VE",
    "wof:name":"El Placer",
    "wof:placetype":"locality"
},
  "geometry": {"coordinates":[-67.72609,9.97091],"type":"Point"}
}