{
  "type": "Feature",
  "properties": {
    "gn:admin1_code":"11",
    "gn:asciiname":"Yuquique",
    "gn:country_code":"VE",
    "gn:dem":17,
    "gn:feature_class":"P",
    "gn:feature_code":"PPL",
    "gn:name":"Yuquique",
    "gn:population":0,
    "gn:timezone":"America/Caracas",
    "iso:country":"VE",
    "wof:name":"Yuquique",
    "wof:placetype":"locality"
},
  "geometry": {"coordinates":[-70.75833,11.16877],"type":"Point"}
}