{
  "type": "Feature",
  "properties": {
    "gn:admin1_code":"12",
    "gn:asciiname":"El Palenque",
    "gn:cc2":"VE",
    "gn:country_code":"VE",
    "gn:dem":63,
    "gn:feature_class":"P",
    "gn:feature_code":"PPL",
    "gn:name":"El Palenque",
    "gn:population":0,
    "gn:timezone":"America/Caracas",
    "iso:country":"VE",
    "name:und_x_variant":[
        "Palenque",
        "Palenqui",
        "El Palenque"
    ],
    "wof:name":"El Palenque",
    "wof:placetype":"locality"
},
  "geometry": {"coordinates":[-67.78333000000001,8.51667],"type":"Point"}
}