{
  "type": "Feature",
  "properties": {
    "gn:admin1_code":"19.0",
    "gn:asciiname":"Mana Hambre",
    "gn:country_code":"VE",
    "gn:dem":1059,
    "gn:feature_class":"P",
    "gn:feature_code":"PPLL",
    "gn:name":"Mana Hambre",
    "gn:population":0,
    "gn:timezone":"America/Caracas",
    "iso:country":"VE",
    "wof:name":"Mana Hambre",
    "wof:placetype":"locality"
},
  "geometry": {"coordinates":[-63.86794,10.16861],"type":"Point"}
}