{
  "type": "Feature",
  "properties": {
    "gn:admin1_code":"14.0",
    "gn:asciiname":"La Providencia",
    "gn:country_code":"VE",
    "gn:dem":465,
    "gn:feature_class":"P",
    "gn:feature_code":"PPLL",
    "gn:name":"La Providencia",
    "gn:population":0,
    "gn:timezone":"America/Caracas",
    "iso:country":"VE",
    "wof:name":"La Providencia",
    "wof:placetype":"locality"
},
  "geometry": {"coordinates":[-71.58889000000001,8.49519],"type":"Point"}
}