{
  "type": "Feature",
  "properties": {
    "gn:admin1_code":"2",
    "gn:asciiname":"Garrapata",
    "gn:country_code":"VE",
    "gn:dem":277,
    "gn:feature_class":"P",
    "gn:feature_code":"PPL",
    "gn:name":"Garrapata",
    "gn:population":0,
    "gn:timezone":"America/Caracas",
    "iso:country":"VE",
    "wof:name":"Garrapata",
    "wof:placetype":"locality"
},
  "geometry": {"coordinates":[-64.55401999999999,9.03028],"type":"Point"}
}