{
  "type": "Feature",
  "properties": {
    "gn:admin1_code":"22",
    "gn:asciiname":"Kilometro Cincuentiocho",
    "gn:country_code":"VE",
    "gn:dem":132,
    "gn:feature_class":"P",
    "gn:feature_code":"PPL",
    "gn:name":"Kil\u00f3metro Cincuentiocho",
    "gn:population":0,
    "gn:timezone":"America/Caracas",
    "iso:country":"VE",
    "name:und_x_variant":[
        "Kil\u00f3metro 58",
        "Kil\u00f3metro Cincuentiocho"
    ],
    "wof:name":"Kilometro Cincuentiocho",
    "wof:placetype":"locality"
},
  "geometry": {"coordinates":[-68.84143,10.52295],"type":"Point"}
}