{
  "type": "Feature",
  "properties": {
    "iso:country":"VE",
    "name:ceb_x_preferred":[
        "Palmarejo"
    ],
    "name:pol_x_preferred":[
        "Palmarejo"
    ],
    "name:swe_x_preferred":[
        "Palmarejo"
    ],
    "qs:gn_country":"VE",
    "qs:gn_fcode":"PPL",
    "qs:gn_pop":0,
    "qs:name":"Palmarejo",
    "qs:name_adm0":"Venezuela",
    "qs:name_adm1":"Zulia",
    "qs:photos":42,
    "qs:photos_1k":9,
    "qs:photos_9k":1,
    "qs:photos_9r":2,
    "qs:photos_all":42,
    "qs:photos_sr":2,
    "qs:placetype":"Town",
    "qs:pop_sr":"0",
    "qs:woe_adm0":23424982,
    "wof:name":"Palmarejo",
    "wof:placetype":"locality"
},
  "geometry": {"coordinates":[-71.52179,10.59256],"type":"Point"}
}