{
  "type": "Feature",
  "properties": {
    "gn:admin1_code":"11",
    "gn:asciiname":"Cayudar",
    "gn:country_code":"VE",
    "gn:dem":170,
    "gn:feature_class":"P",
    "gn:feature_code":"PPL",
    "gn:name":"Cayudar",
    "gn:population":0,
    "gn:timezone":"America/Caracas",
    "iso:country":"VE",
    "wof:name":"Cayudar",
    "wof:placetype":"locality"
},
  "geometry": {"coordinates":[-69.55266999999999,11.39084],"type":"Point"}
}