{
  "type": "Feature",
  "properties": {
    "gn:admin1_code":"12",
    "gn:asciiname":"El Palmito",
    "gn:country_code":"VE",
    "gn:dem":205,
    "gn:feature_class":"P",
    "gn:feature_code":"PPL",
    "gn:name":"El Palmito",
    "gn:population":0,
    "gn:timezone":"America/Caracas",
    "iso:country":"VE",
    "wof:name":"El Palmito",
    "wof:placetype":"locality"
},
  "geometry": {"coordinates":[-66.91667,9.63333],"type":"Point"}
}