{
  "type": "Feature",
  "properties": {
    "gn:admin1_code":"07",
    "gn:asciiname":"Majaguito",
    "gn:country_code":"VE",
    "gn:dem":539,
    "gn:feature_class":"P",
    "gn:feature_code":"PPL",
    "gn:name":"Majaguito",
    "gn:population":0,
    "gn:timezone":"America/Caracas",
    "iso:country":"VE",
    "wof:name":"Majaguito",
    "wof:placetype":"locality"
},
  "geometry": {"coordinates":[-67.92864,9.89349],"type":"Point"}
}