{
  "type": "Feature",
  "properties": {
    "gn:admin1_code":"8.0",
    "gn:asciiname":"Santa Ana",
    "gn:country_code":"VE",
    "gn:dem":1293,
    "gn:feature_class":"P",
    "gn:feature_code":"PPL",
    "gn:name":"Santa Ana",
    "gn:population":0,
    "gn:timezone":"America/Caracas",
    "iso:country":"VE",
    "wof:name":"Santa Ana",
    "wof:placetype":"locality"
},
  "geometry": {"coordinates":[-68.70798000000001,9.94665],"type":"Point"}
}