{
  "type": "Feature",
  "properties": {
    "gn:admin1_code":"16.0",
    "gn:asciiname":"La Oroquera de La Soledad",
    "gn:country_code":"VE",
    "gn:dem":127,
    "gn:feature_class":"P",
    "gn:feature_code":"PPL",
    "gn:name":"La Oroquera de La Soledad",
    "gn:population":0,
    "gn:timezone":"America/Caracas",
    "iso:country":"VE",
    "wof:name":"La Oroquera de La Soledad",
    "wof:placetype":"locality"
},
  "geometry": {"coordinates":[-63.40221999999999,9.58611],"type":"Point"}
}