{
  "type": "Feature",
  "properties": {
    "gn:admin1_code":"11",
    "gn:asciiname":"Curimagua",
    "gn:country_code":"VE",
    "gn:dem":1115,
    "gn:feature_class":"P",
    "gn:feature_code":"PPL",
    "gn:name":"Curimagua",
    "gn:population":0,
    "gn:timezone":"America/Caracas",
    "iso:country":"VE",
    "wof:name":"Curimagua",
    "wof:placetype":"locality"
},
  "geometry": {"coordinates":[-69.67679,11.16985],"type":"Point"}
}