{
  "type": "Feature",
  "properties": {
    "gn:admin1_code":"05",
    "gn:asciiname":"Orticero",
    "gn:country_code":"VE",
    "gn:dem":104,
    "gn:feature_class":"P",
    "gn:feature_code":"PPLL",
    "gn:name":"Orticero",
    "gn:population":0,
    "gn:timezone":"America/Caracas",
    "iso:country":"VE",
    "wof:name":"Orticero",
    "wof:placetype":"locality"
},
  "geometry": {"coordinates":[-70.10715,7.90711],"type":"Point"}
}