{
  "type": "Feature",
  "properties": {
    "gn:admin1_code":"14.0",
    "gn:asciiname":"Los Toritos",
    "gn:country_code":"VE",
    "gn:dem":1492,
    "gn:feature_class":"P",
    "gn:feature_code":"PPLL",
    "gn:name":"Los Toritos",
    "gn:population":0,
    "gn:timezone":"America/Caracas",
    "iso:country":"VE",
    "wof:name":"Los Toritos",
    "wof:placetype":"locality"
},
  "geometry": {"coordinates":[-71.00721999999998,9.00167],"type":"Point"}
}