{
  "type": "Feature",
  "properties": {
    "gn:admin1_code":"12",
    "gn:asciiname":"El Carrizal",
    "gn:cc2":"VE",
    "gn:country_code":"VE",
    "gn:dem":176,
    "gn:feature_class":"P",
    "gn:feature_code":"PPL",
    "gn:name":"El Carrizal",
    "gn:population":0,
    "gn:timezone":"America/Caracas",
    "iso:country":"VE",
    "name:und_x_variant":[
        "Carrizal",
        "El Carrizal"
    ],
    "wof:name":"El Carrizal",
    "wof:placetype":"locality"
},
  "geometry": {"coordinates":[-66.93333,9.33333],"type":"Point"}
}