{
  "type": "Feature",
  "properties": {
    "iso:country":"VE",
    "qs:gn_pop":0,
    "qs:name":"Urbana Aguas Calientes",
    "qs:name_adm0":"Venezuela",
    "qs:name_adm1":"Carabobo",
    "qs:photos":30,
    "qs:photos_1k":6,
    "qs:photos_9k":1,
    "qs:photos_9r":4,
    "qs:photos_all":156,
    "qs:photos_sr":2,
    "qs:placetype":"LocalAdmin",
    "qs:pop_sr":"0",
    "qs:woe_adm0":23424982,
    "wof:name":"Urbana Aguas Calientes",
    "wof:placetype":"localadmin"
},
  "geometry": {"coordinates":[-67.685222,10.349708],"type":"Point"}
}