{
  "type": "Feature",
  "properties": {
    "gn:admin1_code":"07",
    "gn:asciiname":"Verdun",
    "gn:country_code":"VE",
    "gn:dem":436,
    "gn:feature_class":"P",
    "gn:feature_code":"PPL",
    "gn:name":"Verd\u00fan",
    "gn:population":0,
    "gn:timezone":"America/Caracas",
    "iso:country":"VE",
    "wof:name":"Verdun",
    "wof:placetype":"locality"
},
  "geometry": {"coordinates":[-67.89378000000001,10.08418],"type":"Point"}
}