{
  "type": "Feature",
  "properties": {
    "gn:admin1_code":"19",
    "gn:asciiname":"La Restinga",
    "gn:country_code":"VE",
    "gn:dem":3,
    "gn:feature_class":"P",
    "gn:feature_code":"PPL",
    "gn:name":"La Restinga",
    "gn:population":0,
    "gn:timezone":"America/Caracas",
    "iso:country":"VE",
    "name:deu_x_preferred":[
        "La Restinga"
    ],
    "name:fra_x_preferred":[
        "La Restinga"
    ],
    "name:spa_x_preferred":[
        "La Restinga"
    ],
    "name:und_x_variant":[
        "La Arestinga",
        "La Restinga"
    ],
    "wof:name":"La Restinga",
    "wof:placetype":"locality"
},
  "geometry": {"coordinates":[-63.15841999999999,10.71979],"type":"Point"}
}