{
  "type": "Feature",
  "properties": {
    "gn:admin1_code":"11.0",
    "gn:asciiname":"La Meseta",
    "gn:country_code":"VE",
    "gn:dem":561,
    "gn:feature_class":"P",
    "gn:feature_code":"PPL",
    "gn:name":"La Meseta",
    "gn:population":0,
    "gn:timezone":"America/Caracas",
    "iso:country":"VE",
    "wof:name":"La Meseta",
    "wof:placetype":"locality"
},
  "geometry": {"coordinates":[-69.65611,11.12111],"type":"Point"}
}