{
  "type": "Feature",
  "properties": {
    "gn:admin1_code":"19",
    "gn:asciiname":"Paradero",
    "gn:country_code":"VE",
    "gn:dem":34,
    "gn:feature_class":"P",
    "gn:feature_code":"PPL",
    "gn:name":"Paradero",
    "gn:population":0,
    "gn:timezone":"America/Caracas",
    "iso:country":"VE",
    "name:deu_x_preferred":[
        "Paradero"
    ],
    "name:zho_x_preferred":[
        "\u5e15\u62c9\u5fb7\u7f85"
    ],
    "wof:name":"Paradero",
    "wof:placetype":"locality"
},
  "geometry": {"coordinates":[-63.10079,10.25245],"type":"Point"}
}