{
  "type": "Feature",
  "properties": {
    "gn:admin1_code":"16",
    "gn:asciiname":"El Blanquero",
    "gn:country_code":"VE",
    "gn:dem":34,
    "gn:feature_class":"P",
    "gn:feature_code":"PPL",
    "gn:name":"El Blanquero",
    "gn:population":0,
    "gn:timezone":"America/Caracas",
    "iso:country":"VE",
    "wof:name":"El Blanquero",
    "wof:placetype":"locality"
},
  "geometry": {"coordinates":[-63.01201999999999,9.37865],"type":"Point"}
}