{
  "type": "Feature",
  "properties": {
    "gn:admin1_code":"20.0",
    "gn:asciiname":"Mesa de Guerrero",
    "gn:country_code":"VE",
    "gn:dem":1677,
    "gn:feature_class":"P",
    "gn:feature_code":"PPL",
    "gn:name":"Mesa de Guerrero",
    "gn:population":0,
    "gn:timezone":"America/Caracas",
    "iso:country":"VE",
    "wof:name":"Mesa de Guerrero",
    "wof:placetype":"locality"
},
  "geometry": {"coordinates":[-71.93419,7.90159],"type":"Point"}
}