{
  "type": "Feature",
  "properties": {
    "gn:admin1_code":"11",
    "gn:asciiname":"El Cayude",
    "gn:country_code":"VE",
    "gn:dem":6,
    "gn:feature_class":"P",
    "gn:feature_code":"PPL",
    "gn:name":"El Cayude",
    "gn:population":0,
    "gn:timezone":"America/Caracas",
    "iso:country":"VE",
    "name:und_x_variant":[
        "Cayude",
        "El Cayude"
    ],
    "wof:name":"El Cayude",
    "wof:placetype":"locality"
},
  "geometry": {"coordinates":[-69.9877,11.66201],"type":"Point"}
}