{
  "type": "Feature",
  "properties": {
    "gn:admin1_code":"02",
    "gn:asciiname":"Palital",
    "gn:country_code":"VE",
    "gn:dem":15,
    "gn:feature_class":"P",
    "gn:feature_code":"PPLL",
    "gn:name":"Palital",
    "gn:population":0,
    "gn:timezone":"America/Caracas",
    "iso:country":"VE",
    "wof:name":"Palital",
    "wof:placetype":"locality"
},
  "geometry": {"coordinates":[-64.11756,8.00876],"type":"Point"}
}