{
  "type": "Feature",
  "properties": {
    "gn:admin1_code":"16",
    "gn:asciiname":"La Boca de La Mata",
    "gn:country_code":"VE",
    "gn:dem":143,
    "gn:feature_class":"P",
    "gn:feature_code":"PPL",
    "gn:name":"La Boca de La Mata",
    "gn:population":0,
    "gn:timezone":"America/Caracas",
    "iso:country":"VE",
    "wof:name":"La Boca de La Mata",
    "wof:placetype":"locality"
},
  "geometry": {"coordinates":[-63.69237,9.40351],"type":"Point"}
}