{
  "type": "Feature",
  "properties": {
    "gn:admin1_code":"13.0",
    "gn:asciiname":"Chiparito",
    "gn:country_code":"VE",
    "gn:dem":591,
    "gn:feature_class":"P",
    "gn:feature_code":"PPL",
    "gn:name":"Chiparito",
    "gn:population":0,
    "gn:timezone":"America/Caracas",
    "iso:country":"VE",
    "wof:name":"Chiparito",
    "wof:placetype":"locality"
},
  "geometry": {"coordinates":[-70.58633,10.50894],"type":"Point"}
}