{
  "type": "Feature",
  "properties": {
    "gn:admin1_code":"22.0",
    "gn:asciiname":"Las Quisandas",
    "gn:country_code":"VE",
    "gn:dem":498,
    "gn:feature_class":"P",
    "gn:feature_code":"PPL",
    "gn:name":"Las Quisandas",
    "gn:population":0,
    "gn:timezone":"America/Caracas",
    "iso:country":"VE",
    "wof:name":"Las Quisandas",
    "wof:placetype":"locality"
},
  "geometry": {"coordinates":[-68.93092,10.20268],"type":"Point"}
}