{
  "type": "Feature",
  "properties": {
    "gn:admin1_code":"23",
    "gn:asciiname":"Chimborazo",
    "gn:country_code":"VE",
    "gn:dem":194,
    "gn:feature_class":"P",
    "gn:feature_code":"PPL",
    "gn:name":"Chimborazo",
    "gn:population":0,
    "gn:timezone":"America/Caracas",
    "iso:country":"VE",
    "wof:name":"Chimborazo",
    "wof:placetype":"locality"
},
  "geometry": {"coordinates":[-72.63333,10.06667],"type":"Point"}
}