{
  "type": "Feature",
  "properties": {
    "gn:admin1_code":"23.0",
    "gn:asciiname":"Los Naranjos del Chama",
    "gn:country_code":"VE",
    "gn:dem":45,
    "gn:feature_class":"P",
    "gn:feature_code":"PPL",
    "gn:name":"Los Naranjos del Chama",
    "gn:population":0,
    "gn:timezone":"America/Caracas",
    "iso:country":"VE",
    "wof:name":"Los Naranjos del Chama",
    "wof:placetype":"locality"
},
  "geometry": {"coordinates":[-71.68179000000001,8.74746],"type":"Point"}
}