{
  "type": "Feature",
  "properties": {
    "gn:admin1_code":"05",
    "gn:asciiname":"El Pueblito",
    "gn:country_code":"VE",
    "gn:dem":458,
    "gn:feature_class":"P",
    "gn:feature_code":"PPLL",
    "gn:name":"El Pueblito",
    "gn:population":0,
    "gn:timezone":"America/Caracas",
    "iso:country":"VE",
    "wof:name":"El Pueblito",
    "wof:placetype":"locality"
},
  "geometry": {"coordinates":[-70.39889000000002,8.785],"type":"Point"}
}