{
  "type": "Feature",
  "properties": {
    "gn:admin1_code":"3",
    "gn:asciiname":"La Trinidad de Orichuna",
    "gn:country_code":"VE",
    "gn:dem":103,
    "gn:feature_class":"P",
    "gn:feature_code":"PPL",
    "gn:name":"La Trinidad de Orichuna",
    "gn:population":0,
    "gn:timezone":"America/Caracas",
    "iso:country":"VE",
    "name:und_x_variant":[
        "La Trinidad",
        "La Trinidad de Orichuna"
    ],
    "wof:name":"La Trinidad de Orichuna",
    "wof:placetype":"locality"
},
  "geometry": {"coordinates":[-69.78403,7.11358],"type":"Point"}
}