{
  "type": "Feature",
  "properties": {
    "gn:admin1_code":"14.0",
    "gn:asciiname":"Agua Colorada",
    "gn:country_code":"VE",
    "gn:dem":24,
    "gn:feature_class":"P",
    "gn:feature_code":"PPL",
    "gn:name":"Agua Colorada",
    "gn:population":0,
    "gn:timezone":"America/Caracas",
    "iso:country":"VE",
    "wof:name":"Agua Colorada",
    "wof:placetype":"locality"
},
  "geometry": {"coordinates":[-71.23849,9.06159],"type":"Point"}
}