{
  "type": "Feature",
  "properties": {
    "gn:admin1_code":"13",
    "gn:asciiname":"Uribana",
    "gn:country_code":"VE",
    "gn:dem":685,
    "gn:feature_class":"P",
    "gn:feature_code":"PPL",
    "gn:name":"Uribana",
    "gn:population":0,
    "gn:timezone":"America/Caracas",
    "iso:country":"VE",
    "name:und_x_variant":[
        "Oribana",
        "Uribana"
    ],
    "wof:name":"Uribana",
    "wof:placetype":"locality"
},
  "geometry": {"coordinates":[-69.34966,10.18981],"type":"Point"}
}