{
  "type": "Feature",
  "properties": {
    "gn:admin1_code":"15",
    "gn:asciiname":"San Daniel",
    "gn:country_code":"VE",
    "gn:dem":576,
    "gn:feature_class":"P",
    "gn:feature_code":"PPL",
    "gn:name":"San Daniel",
    "gn:population":0,
    "gn:timezone":"America/Caracas",
    "iso:country":"VE",
    "wof:name":"San Daniel",
    "wof:placetype":"locality"
},
  "geometry": {"coordinates":[-67.04535,10.09489],"type":"Point"}
}