{
  "type": "Feature",
  "properties": {
    "gn:admin1_code":"20",
    "gn:asciiname":"La Palestina",
    "gn:country_code":"VE",
    "gn:dem":876,
    "gn:feature_class":"P",
    "gn:feature_code":"PPL",
    "gn:name":"La Palestina",
    "gn:population":0,
    "gn:timezone":"America/Caracas",
    "iso:country":"VE",
    "wof:name":"La Palestina",
    "wof:placetype":"locality"
},
  "geometry": {"coordinates":[-72.04994000000001,7.46005],"type":"Point"}
}