{
  "type": "Feature",
  "properties": {
    "gn:admin1_code":"8",
    "gn:asciiname":"La Galera",
    "gn:country_code":"VE",
    "gn:dem":125,
    "gn:feature_class":"P",
    "gn:feature_code":"PPL",
    "gn:name":"La Galera",
    "gn:population":0,
    "gn:timezone":"America/Caracas",
    "iso:country":"VE",
    "name:arg_x_preferred":[
        "La Galera"
    ],
    "name:ast_x_preferred":[
        "La Galera"
    ],
    "name:azb_x_preferred":[
        "\u0644\u0627 \u0642\u0627\u0644\u0631\u0627"
    ],
    "name:cat_x_preferred":[
        "La Galera"
    ],
    "name:ceb_x_preferred":[
        "La Galera"
    ],
    "name:eus_x_preferred":[
        "La Galera"
    ],
    "name:fas_x_preferred":[
        "\u0644\u0627 \u06af\u0627\u0644\u0631\u0627"
    ],
    "name:fra_x_preferred":[
        "La Galera"
    ],
    "name:glg_x_preferred":[
        "La Galera"
    ],
    "name:hun_x_preferred":[
        "La Galera"
    ],
    "name:hye_x_preferred":[
        "\u053c\u0561 \u0533\u0561\u056c\u0565\u0580\u0561"
    ],
    "name:ita_x_preferred":[
        "La Galera"
    ],
    "name:lat_x_preferred":[
        "La Galera"
    ],
    "name:msa_x_preferred":[
        "La Galera"
    ],
    "name:nld_x_preferred":[
        "La Galera"
    ],
    "name:oci_x_preferred":[
        "La Galera"
    ],
    "name:pol_x_preferred":[
        "La Galera"
    ],
    "name:por_x_preferred":[
        "La Galera"
    ],
    "name:rus_x_preferred":[
        "\u041b\u0430-\u0413\u0430\u043b\u0435\u0440\u0430"
    ],
    "name:spa_x_preferred":[
        "La Galera"
    ],
    "name:sqi_x_preferred":[
        "La Galera"
    ],
    "name:swe_x_preferred":[
        "La Galera"
    ],
    "name:urd_x_preferred":[
        "\u0644\u0627 \u06af\u0627\u0644\u06cc\u0631\u0627"
    ],
    "name:war_x_preferred":[
        "La Galera"
    ],
    "name:zho_x_preferred":[
        "\u62c9\u52a0\u83b1\u62c9"
    ],
    "wof:name":"La Galera",
    "wof:placetype":"locality"
},
  "geometry": {"coordinates":[-68.17265,9.56382],"type":"Point"}
}