{
  "type": "Feature",
  "properties": {
    "gn:admin1_code":"8",
    "gn:asciiname":"La Galera",
    "gn:country_code":"VE",
    "gn:dem":125,
    "gn:feature_class":"P",
    "gn:feature_code":"PPL",
    "gn:name":"La Galera",
    "gn:population":0,
    "gn:timezone":"America/Caracas",
    "iso:country":"VE",
    "wof:name":"La Galera",
    "wof:placetype":"locality"
},
  "geometry": {"coordinates":[-68.17265,9.56382],"type":"Point"}
}