{
  "type": "Feature",
  "properties": {
    "gn:admin1_code":"21",
    "gn:asciiname":"El Araguaney",
    "gn:country_code":"VE",
    "gn:dem":567,
    "gn:feature_class":"P",
    "gn:feature_code":"PPLL",
    "gn:name":"El Araguaney",
    "gn:population":0,
    "gn:timezone":"America/Caracas",
    "iso:country":"VE",
    "wof:name":"El Araguaney",
    "wof:placetype":"locality"
},
  "geometry": {"coordinates":[-70.22336999999999,9.76955],"type":"Point"}
}