{
  "type": "Feature",
  "properties": {
    "gn:admin1_code":"12.0",
    "gn:asciiname":"Las Garzas",
    "gn:country_code":"VE",
    "gn:dem":151,
    "gn:feature_class":"P",
    "gn:feature_code":"PPLL",
    "gn:name":"Las Garzas",
    "gn:population":0,
    "gn:timezone":"America/Caracas",
    "iso:country":"VE",
    "name:spa_x_preferred":[
        "Las Garzas"
    ],
    "wof:name":"Las Garzas",
    "wof:placetype":"locality"
},
  "geometry": {"coordinates":[-66.92667,9.24667],"type":"Point"}
}