{
  "type": "Feature",
  "properties": {
    "gn:country":"VE",
    "gn:fcode":"PPLA",
    "gn:population":112286,
    "iso:country":"VE",
    "name:arg_x_preferred":[
        "Guanare"
    ],
    "name:ceb_x_preferred":[
        "Guanare"
    ],
    "name:deu_x_preferred":[
        "Guanare"
    ],
    "name:eng_x_preferred":[
        "Guanare"
    ],
    "name:epo_x_preferred":[
        "Guanare"
    ],
    "name:fas_x_preferred":[
        "\u06af\u0648\u0627\u0646\u0627\u0631\u0647"
    ],
    "name:fra_x_preferred":[
        "Guanare"
    ],
    "name:hun_x_preferred":[
        "Guanare"
    ],
    "name:ita_x_preferred":[
        "Guanare"
    ],
    "name:jpn_x_preferred":[
        "\u30b0\u30a2\u30ca\u30ec"
    ],
    "name:kat_x_preferred":[
        "\u10d2\u10e3\u10d0\u10dc\u10d0\u10e0\u10d4"
    ],
    "name:kor_x_preferred":[
        "\uacfc\ub098\ub808"
    ],
    "name:lit_x_preferred":[
        "Gvanar\u0117"
    ],
    "name:nld_x_preferred":[
        "Guanare"
    ],
    "name:pol_x_preferred":[
        "Guanare"
    ],
    "name:por_x_preferred":[
        "Guanare"
    ],
    "name:que_x_preferred":[
        "Guanare"
    ],
    "name:ron_x_preferred":[
        "Guanare"
    ],
    "name:rus_x_preferred":[
        "\u0413\u0443\u0430\u043d\u0430\u0440\u0435"
    ],
    "name:spa_x_preferred":[
        "Guanare"
    ],
    "name:swe_x_preferred":[
        "Guanare"
    ],
    "name:ukr_x_preferred":[
        "\u0413\u0443\u0430\u043d\u0430\u0440\u0435"
    ],
    "name:urd_x_preferred":[
        "\u06af\u0648\u0627\u0646\u0627\u0631\u06d2"
    ],
    "name:vol_x_preferred":[
        "Guanare"
    ],
    "name:war_x_preferred":[
        "Guanare"
    ],
    "name:zho_x_preferred":[
        "\u74dc\u7d0d\u96f7"
    ],
    "qs_pg:aaroncc":"VE",
    "qs_pg:gn_country":"VE",
    "qs_pg:gn_fcode":"PPLA",
    "qs_pg:gn_pop":112286,
    "qs_pg:name":"Guanare",
    "qs_pg:photos_9r":0,
    "qs_pg:photos_sr":0,
    "qs_pg:pop_sr":9,
    "qs_pg:qs_pg_placetype":"locality",
    "wof:name":"Guanare",
    "wof:placetype":"locality",
    "wof:population":112286
},
  "geometry": {"coordinates":[-69.74206,9.04183],"type":"Point"}
}