{
  "type": "Feature",
  "properties": {
    "iso:country":"VE",
    "qs:gn_pop":0,
    "qs:name":"Gonzalo Picon Febres",
    "qs:name_adm0":"Venezuela",
    "qs:name_adm1":"M\u00e9rida",
    "qs:photos":13,
    "qs:photos_1k":3,
    "qs:photos_9k":1,
    "qs:photos_9r":3,
    "qs:photos_all":98,
    "qs:photos_sr":1,
    "qs:placetype":"LocalAdmin",
    "qs:pop_sr":"0",
    "qs:woe_adm0":23424982,
    "wof:name":"Gonzalo Picon Febres",
    "wof:placetype":"localadmin"
},
  "geometry": {"coordinates":[-70.879,8.77176],"type":"Point"}
}