{
  "type": "Feature",
  "properties": {
    "gn:admin1_code":"2",
    "gn:asciiname":"Merecure",
    "gn:country_code":"VE",
    "gn:dem":118,
    "gn:feature_class":"P",
    "gn:feature_code":"PPL",
    "gn:name":"Merecure",
    "gn:population":0,
    "gn:timezone":"America/Caracas",
    "iso:country":"VE",
    "wof:name":"Merecure",
    "wof:placetype":"locality"
},
  "geometry": {"coordinates":[-64.90728,9.08562],"type":"Point"}
}