{
  "type": "Feature",
  "properties": {
    "gn:admin1_code":"12",
    "gn:asciiname":"Ipare",
    "gn:country_code":"VE",
    "gn:dem":357,
    "gn:feature_class":"P",
    "gn:feature_code":"PPL",
    "gn:name":"Ipare",
    "gn:population":0,
    "gn:timezone":"America/Caracas",
    "iso:country":"VE",
    "wof:name":"Ipare",
    "wof:placetype":"locality"
},
  "geometry": {"coordinates":[-66.32253,9.867],"type":"Point"}
}