{
  "type": "Feature",
  "properties": {
    "gn:admin1_code":"15",
    "gn:asciiname":"Barrialito",
    "gn:country_code":"VE",
    "gn:dem":358,
    "gn:feature_class":"P",
    "gn:feature_code":"PPL",
    "gn:name":"Barrialito",
    "gn:population":0,
    "gn:timezone":"America/Caracas",
    "iso:country":"VE",
    "wof:name":"Barrialito",
    "wof:placetype":"locality"
},
  "geometry": {"coordinates":[-66.81544,10.10252],"type":"Point"}
}