{
  "type": "Feature",
  "properties": {
    "gn:admin1_code":"22.0",
    "gn:asciiname":"Casa de Teja",
    "gn:country_code":"VE",
    "gn:dem":593,
    "gn:feature_class":"P",
    "gn:feature_code":"PPL",
    "gn:name":"Casa de Teja",
    "gn:population":0,
    "gn:timezone":"America/Caracas",
    "iso:country":"VE",
    "wof:name":"Casa de Teja",
    "wof:placetype":"locality"
},
  "geometry": {"coordinates":[-69.89389,10.09389],"type":"Point"}
}