{
  "type": "Feature",
  "properties": {
    "gn:admin1_code":"5",
    "gn:asciiname":"Paso de San Vicente",
    "gn:country_code":"VE",
    "gn:dem":71,
    "gn:feature_class":"P",
    "gn:feature_code":"PPL",
    "gn:name":"Paso de San Vicente",
    "gn:population":0,
    "gn:timezone":"America/Caracas",
    "iso:country":"VE",
    "wof:name":"Paso de San Vicente",
    "wof:placetype":"locality"
},
  "geometry": {"coordinates":[-68.45411999999999,8.25157],"type":"Point"}
}