{
  "type": "Feature",
  "properties": {
    "gn:admin1_code":"7",
    "gn:asciiname":"El Barrial",
    "gn:country_code":"VE",
    "gn:dem":538,
    "gn:feature_class":"P",
    "gn:feature_code":"PPL",
    "gn:name":"El Barrial",
    "gn:population":0,
    "gn:timezone":"America/Caracas",
    "iso:country":"VE",
    "name:spa_x_preferred":[
        "El Barrial"
    ],
    "wof:name":"El Barrial",
    "wof:placetype":"locality"
},
  "geometry": {"coordinates":[-67.89931,9.8552],"type":"Point"}
}