{
  "type": "Feature",
  "properties": {
    "gn:admin1_code":"99",
    "gn:asciiname":"San Pablo",
    "gn:country_code":"VE",
    "gn:dem":578,
    "gn:feature_class":"P",
    "gn:feature_code":"PPL",
    "gn:name":"San Pablo",
    "gn:population":0,
    "gn:timezone":"America/Caracas",
    "iso:country":"VE",
    "wof:name":"San Pablo",
    "wof:placetype":"locality"
},
  "geometry": {"coordinates":[-70.63333,10.15],"type":"Point"}
}