{
  "type": "Feature",
  "properties": {
    "gn:admin1_code":"12.0",
    "gn:asciiname":"La Centella",
    "gn:country_code":"VE",
    "gn:dem":133,
    "gn:feature_class":"P",
    "gn:feature_code":"PPLL",
    "gn:name":"La Centella",
    "gn:population":0,
    "gn:timezone":"America/Caracas",
    "iso:country":"VE",
    "wof:name":"La Centella",
    "wof:placetype":"locality"
},
  "geometry": {"coordinates":[-65.69403,8.82681],"type":"Point"}
}