{
  "type": "Feature",
  "properties": {
    "gn:admin1_code":"07",
    "gn:asciiname":"Casupito",
    "gn:country_code":"VE",
    "gn:dem":677,
    "gn:feature_class":"P",
    "gn:feature_code":"PPL",
    "gn:name":"Casupito",
    "gn:population":0,
    "gn:timezone":"America/Caracas",
    "iso:country":"VE",
    "wof:name":"Casupito",
    "wof:placetype":"locality"
},
  "geometry": {"coordinates":[-67.59456,9.9573],"type":"Point"}
}