{
  "type": "Feature",
  "properties": {
    "gn:admin1_code":"23.0",
    "gn:asciiname":"Tampico",
    "gn:country_code":"VE",
    "gn:dem":19,
    "gn:feature_class":"P",
    "gn:feature_code":"PPLL",
    "gn:name":"Tampico",
    "gn:population":0,
    "gn:timezone":"America/Caracas",
    "iso:country":"VE",
    "name:ara_x_preferred":[
        "\u062a\u0627\u0645\u0628\u064a\u0643\u0648"
    ],
    "name:bel_x_preferred":[
        "\u0422\u0430\u043c\u043f\u0456\u043a\u0430"
    ],
    "name:bre_x_preferred":[
        "Tampico"
    ],
    "name:bul_x_preferred":[
        "\u0422\u0430\u043c\u043f\u0438\u043a\u043e"
    ],
    "name:cat_x_preferred":[
        "Tampico"
    ],
    "name:deu_x_preferred":[
        "Tampico"
    ],
    "name:epo_x_preferred":[
        "Tampico"
    ],
    "name:eus_x_preferred":[
        "Tampico"
    ],
    "name:fas_x_preferred":[
        "\u062a\u0627\u0645\u067e\u06cc\u06a9\u0648"
    ],
    "name:fin_x_preferred":[
        "Tampico"
    ],
    "name:fra_x_preferred":[
        "Tampico"
    ],
    "name:heb_x_preferred":[
        "\u05d8\u05de\u05e4\u05d9\u05e7\u05d5"
    ],
    "name:hun_x_preferred":[
        "Tampico"
    ],
    "name:hye_x_preferred":[
        "\u054f\u0561\u0574\u057a\u056b\u056f\u0578"
    ],
    "name:ita_x_preferred":[
        "Tampico"
    ],
    "name:jpn_x_preferred":[
        "\u30bf\u30f3\u30d4\u30b3"
    ],
    "name:kor_x_preferred":[
        "\ud0d0\ud53c\ucf54"
    ],
    "name:lad_x_preferred":[
        "Tampico"
    ],
    "name:lat_x_preferred":[
        "Tampico"
    ],
    "name:lit_x_preferred":[
        "Tampikas"
    ],
    "name:lmo_x_preferred":[
        "Tampico"
    ],
    "name:mar_x_preferred":[
        "\u091f\u0945\u092e\u094d\u092a\u093f\u0915\u094b"
    ],
    "name:nld_x_preferred":[
        "Tampico"
    ],
    "name:nno_x_preferred":[
        "Tampico"
    ],
    "name:nor_x_preferred":[
        "Tampico"
    ],
    "name:pol_x_preferred":[
        "Tampico"
    ],
    "name:por_x_preferred":[
        "Tampico"
    ],
    "name:rus_x_preferred":[
        "\u0422\u0430\u043c\u043f\u0438\u043a\u043e"
    ],
    "name:spa_x_preferred":[
        "Tampico"
    ],
    "name:srp_x_preferred":[
        "\u0422\u0430\u043c\u043f\u0438\u043a\u043e"
    ],
    "name:swe_x_preferred":[
        "Tampico"
    ],
    "name:szl_x_preferred":[
        "Tampico"
    ],
    "name:tgl_x_preferred":[
        "Tampico"
    ],
    "name:tha_x_preferred":[
        "\u0e15\u0e31\u0e21\u0e1b\u0e34\u0e42\u0e01"
    ],
    "name:tur_x_preferred":[
        "Tampico"
    ],
    "name:ukr_x_preferred":[
        "\u0422\u0430\u043c\u043f\u0456\u043a\u043e"
    ],
    "name:urd_x_preferred":[
        "\u062a\u0627\u0645\u067e\u06cc\u06a9\u0648"
    ],
    "name:uzb_x_preferred":[
        "Tampiko"
    ],
    "name:war_x_preferred":[
        "Tampico"
    ],
    "name:zho_x_preferred":[
        "\u5766\u76ae\u79d1"
    ],
    "wof:name":"Tampico",
    "wof:placetype":"locality"
},
  "geometry": {"coordinates":[-72.27678,9.91286],"type":"Point"}
}