{
  "type": "Feature",
  "properties": {
    "gn:admin1_code":"02",
    "gn:asciiname":"Paraguatey",
    "gn:country_code":"VE",
    "gn:dem":49,
    "gn:feature_class":"P",
    "gn:feature_code":"PPL",
    "gn:name":"Paraguatey",
    "gn:population":0,
    "gn:timezone":"America/Caracas",
    "iso:country":"VE",
    "wof:name":"Paraguatey",
    "wof:placetype":"locality"
},
  "geometry": {"coordinates":[-64.67716999999999,9.97222],"type":"Point"}
}