{
  "type": "Feature",
  "properties": {
    "gn:admin1_code":"11",
    "gn:asciiname":"Quebrada Honda",
    "gn:country_code":"VE",
    "gn:dem":875,
    "gn:feature_class":"P",
    "gn:feature_code":"PPL",
    "gn:name":"Quebrada Honda",
    "gn:population":0,
    "gn:timezone":"America/Caracas",
    "iso:country":"VE",
    "wof:name":"Quebrada Honda",
    "wof:placetype":"locality"
},
  "geometry": {"coordinates":[-69.51205,10.76411],"type":"Point"}
}