{
  "type": "Feature",
  "properties": {
    "gn:admin1_code":"15.0",
    "gn:asciiname":"Jerico",
    "gn:country_code":"VE",
    "gn:dem":781,
    "gn:feature_class":"P",
    "gn:feature_code":"PPL",
    "gn:name":"Jeric\u00f3",
    "gn:population":0,
    "gn:timezone":"America/Caracas",
    "iso:country":"VE",
    "wof:name":"Jerico",
    "wof:placetype":"locality"
},
  "geometry": {"coordinates":[-66.55100999999999,10.42127],"type":"Point"}
}