{
  "type": "Feature",
  "properties": {
    "gn:admin1_code":"3",
    "gn:asciiname":"Las Guasduitas",
    "gn:cc2":"VE",
    "gn:country_code":"VE",
    "gn:dem":72,
    "gn:feature_class":"P",
    "gn:feature_code":"PPL",
    "gn:name":"Las Guasduitas",
    "gn:population":0,
    "gn:timezone":"America/Caracas",
    "iso:country":"VE",
    "name:und_x_variant":[
        "Guasduita",
        "Las Guasduitas"
    ],
    "wof:name":"Las Guasduitas",
    "wof:placetype":"locality"
},
  "geometry": {"coordinates":[-68.86667,7.31667],"type":"Point"}
}