{
  "type": "Feature",
  "properties": {
    "gn:admin1_code":"05",
    "gn:asciiname":"Boca de Uribante",
    "gn:country_code":"VE",
    "gn:dem":129,
    "gn:feature_class":"P",
    "gn:feature_code":"PPL",
    "gn:name":"Boca de Uribante",
    "gn:population":0,
    "gn:timezone":"America/Caracas",
    "iso:country":"VE",
    "wof:name":"Boca de Uribante",
    "wof:placetype":"locality"
},
  "geometry": {"coordinates":[-70.69816999999998,7.29885],"type":"Point"}
}