{
  "type": "Feature",
  "properties": {
    "gn:admin1_code":"19.0",
    "gn:asciiname":"Cacahual",
    "gn:country_code":"VE",
    "gn:dem":386,
    "gn:feature_class":"P",
    "gn:feature_code":"PPLL",
    "gn:name":"Cacahual",
    "gn:population":0,
    "gn:timezone":"America/Caracas",
    "iso:country":"VE",
    "wof:name":"Cacahual",
    "wof:placetype":"locality"
},
  "geometry": {"coordinates":[-63.37167,10.56778],"type":"Point"}
}