{
  "type": "Feature",
  "properties": {
    "gn:admin1_code":"19.0",
    "gn:asciiname":"Cacahual",
    "gn:country_code":"VE",
    "gn:dem":386,
    "gn:feature_class":"P",
    "gn:feature_code":"PPLL",
    "gn:name":"Cacahual",
    "gn:population":0,
    "gn:timezone":"America/Caracas",
    "iso:country":"VE",
    "name:ceb_x_preferred":[
        "Cacahual"
    ],
    "name:fra_x_preferred":[
        "Cacahual"
    ],
    "name:ita_x_preferred":[
        "Cacahual"
    ],
    "name:kat_x_preferred":[
        "\u10d9\u10d0\u10d9\u10d0\u10e3\u10d0\u10da\u10d8"
    ],
    "name:msa_x_preferred":[
        "Cacahual"
    ],
    "name:nld_x_preferred":[
        "Cacahual"
    ],
    "name:sco_x_preferred":[
        "Cacahual"
    ],
    "name:spa_x_preferred":[
        "Cacahual"
    ],
    "name:swe_x_preferred":[
        "Cacahual"
    ],
    "name:tgl_x_preferred":[
        "Cacahual"
    ],
    "name:vie_x_preferred":[
        "Cacahual"
    ],
    "name:war_x_preferred":[
        "Cacahual"
    ],
    "name:zho_x_preferred":[
        "\u5361\u5361\u74e6\u723e"
    ],
    "wof:name":"Cacahual",
    "wof:placetype":"locality"
},
  "geometry": {"coordinates":[-63.37167,10.56778],"type":"Point"}
}