{
  "type": "Feature",
  "properties": {
    "gn:admin1_code":"11",
    "gn:asciiname":"Barrio Miramar",
    "gn:country_code":"VE",
    "gn:dem":9,
    "gn:feature_class":"P",
    "gn:feature_code":"PPL",
    "gn:name":"Barrio Miramar",
    "gn:population":0,
    "gn:timezone":"America/Caracas",
    "iso:country":"VE",
    "name:und_x_variant":[
        "Barrio Nuevo",
        "Barrio Miramara",
        "Barrio Miramar"
    ],
    "wof:name":"Barrio Miramar",
    "wof:placetype":"locality"
},
  "geometry": {"coordinates":[-70.22051999999999,11.71821],"type":"Point"}
}