{
  "type": "Feature",
  "properties": {
    "gn:admin1_code":"21",
    "gn:asciiname":"Esnacuao",
    "gn:country_code":"VE",
    "gn:dem":2960,
    "gn:feature_class":"P",
    "gn:feature_code":"PPL",
    "gn:name":"Esnacuao",
    "gn:population":0,
    "gn:timezone":"America/Caracas",
    "iso:country":"VE",
    "wof:name":"Esnacuao",
    "wof:placetype":"locality"
},
  "geometry": {"coordinates":[-70.49556,9.17389],"type":"Point"}
}