{
  "type": "Feature",
  "properties": {
    "gn:admin1_code":"21",
    "gn:asciiname":"Loma Arriba",
    "gn:country_code":"VE",
    "gn:dem":1428,
    "gn:feature_class":"P",
    "gn:feature_code":"PPL",
    "gn:name":"Loma Arriba",
    "gn:population":0,
    "gn:timezone":"America/Caracas",
    "iso:country":"VE",
    "wof:name":"Loma Arriba",
    "wof:placetype":"locality"
},
  "geometry": {"coordinates":[-70.32445,9.18211],"type":"Point"}
}