{
  "type": "Feature",
  "properties": {
    "gn:admin1_code":"13",
    "gn:asciiname":"El Charito",
    "gn:country_code":"VE",
    "gn:dem":172,
    "gn:feature_class":"P",
    "gn:feature_code":"PPL",
    "gn:name":"El Charito",
    "gn:population":0,
    "gn:timezone":"America/Caracas",
    "iso:country":"VE",
    "wof:name":"El Charito",
    "wof:placetype":"locality"
},
  "geometry": {"coordinates":[-69.20571,10.64996],"type":"Point"}
}