{
  "type": "Feature",
  "properties": {
    "gn:admin1_code":"02",
    "gn:asciiname":"La Torta",
    "gn:country_code":"VE",
    "gn:dem":142,
    "gn:feature_class":"P",
    "gn:feature_code":"PPLL",
    "gn:name":"La Torta",
    "gn:population":0,
    "gn:timezone":"America/Caracas",
    "iso:country":"VE",
    "wof:name":"La Torta",
    "wof:placetype":"locality"
},
  "geometry": {"coordinates":[-64.51333000000001,9.675],"type":"Point"}
}