{
  "type": "Feature",
  "properties": {
    "gn:admin1_code":"21",
    "gn:asciiname":"Santa Rita",
    "gn:country_code":"VE",
    "gn:dem":1137,
    "gn:feature_class":"P",
    "gn:feature_code":"PPL",
    "gn:name":"Santa Rita",
    "gn:population":0,
    "gn:timezone":"America/Caracas",
    "iso:country":"VE",
    "wof:name":"Santa Rita",
    "wof:placetype":"locality"
},
  "geometry": {"coordinates":[-70.48997,9.35107],"type":"Point"}
}