{
  "type": "Feature",
  "properties": {
    "gn:admin1_code":"23",
    "gn:asciiname":"La Horqueta",
    "gn:country_code":"VE",
    "gn:dem":-1,
    "gn:feature_class":"P",
    "gn:feature_code":"PPL",
    "gn:name":"La Horqueta",
    "gn:population":0,
    "gn:timezone":"America/Caracas",
    "iso:country":"VE",
    "wof:name":"La Horqueta",
    "wof:placetype":"locality"
},
  "geometry": {"coordinates":[-71.76666999999998,9.33333],"type":"Point"}
}