{
  "type": "Feature",
  "properties": {
    "gn:admin1_code":"21",
    "gn:asciiname":"La Cuchilla",
    "gn:country_code":"VE",
    "gn:dem":1069,
    "gn:feature_class":"P",
    "gn:feature_code":"PPL",
    "gn:name":"La Cuchilla",
    "gn:population":0,
    "gn:timezone":"America/Caracas",
    "iso:country":"VE",
    "wof:name":"La Cuchilla",
    "wof:placetype":"locality"
},
  "geometry": {"coordinates":[-70.05145,9.42005],"type":"Point"}
}