{
  "type": "Feature",
  "properties": {
    "gn:admin1_code":"6.0",
    "gn:asciiname":"Villacoa",
    "gn:country_code":"VE",
    "gn:dem":51,
    "gn:feature_class":"P",
    "gn:feature_code":"PPL",
    "gn:name":"Villacoa",
    "gn:population":0,
    "gn:timezone":"America/Caracas",
    "iso:country":"VE",
    "wof:name":"Villacoa",
    "wof:placetype":"locality"
},
  "geometry": {"coordinates":[-67.08079000000001,6.48036],"type":"Point"}
}