{
  "type": "Feature",
  "properties": {
    "gn:admin1_code":"15",
    "gn:asciiname":"La Horqueta",
    "gn:cc2":"VE",
    "gn:country_code":"VE",
    "gn:dem":377,
    "gn:feature_class":"P",
    "gn:feature_code":"PPL",
    "gn:name":"La Horqueta",
    "gn:population":0,
    "gn:timezone":"America/Caracas",
    "iso:country":"VE",
    "name:cat_x_preferred":[
        "Horqueta"
    ],
    "name:fra_x_preferred":[
        "La Horqueta"
    ],
    "name:spa_x_preferred":[
        "La Horqueta"
    ],
    "name:und_x_variant":[
        "La Horgueta"
    ],
    "name:urd_x_preferred":[
        "\u0644\u0627 \u06c1\u0648\u0631\u06a9\u0648\u06cc\u062a\u0627"
    ],
    "wof:name":"La Horqueta",
    "wof:placetype":"locality"
},
  "geometry": {"coordinates":[-66.03333000000001,10.03333],"type":"Point"}
}