{
  "type": "Feature",
  "properties": {
    "gn:admin1_code":"12.0",
    "gn:asciiname":"Guanare",
    "gn:country_code":"VE",
    "gn:dem":129,
    "gn:feature_class":"P",
    "gn:feature_code":"PPL",
    "gn:name":"Guanare",
    "gn:population":0,
    "gn:timezone":"America/Caracas",
    "iso:country":"VE",
    "name:arg_x_preferred":[
        "Guanare"
    ],
    "name:ceb_x_preferred":[
        "Guanare"
    ],
    "name:deu_x_preferred":[
        "Guanare"
    ],
    "name:epo_x_preferred":[
        "Guanare"
    ],
    "name:fas_x_preferred":[
        "\u06af\u0648\u0627\u0646\u0627\u0631\u0647"
    ],
    "name:fra_x_preferred":[
        "Guanare"
    ],
    "name:heb_x_preferred":[
        "\u05d2\u05d5\u05d5\u05d0\u05e0\u05d0\u05e8\u05d4"
    ],
    "name:hun_x_preferred":[
        "Guanare"
    ],
    "name:ita_x_preferred":[
        "Guanare"
    ],
    "name:jpn_x_preferred":[
        "\u30b0\u30a2\u30ca\u30ec"
    ],
    "name:kat_x_preferred":[
        "\u10d2\u10e3\u10d0\u10dc\u10d0\u10e0\u10d4"
    ],
    "name:kor_x_preferred":[
        "\uacfc\ub098\ub808"
    ],
    "name:lit_x_preferred":[
        "Gvanar\u0117"
    ],
    "name:nld_x_preferred":[
        "Guanare"
    ],
    "name:pol_x_preferred":[
        "Guanare"
    ],
    "name:por_x_preferred":[
        "Guanare"
    ],
    "name:que_x_preferred":[
        "Guanare"
    ],
    "name:ron_x_preferred":[
        "Guanare"
    ],
    "name:rus_x_preferred":[
        "\u0413\u0443\u0430\u043d\u0430\u0440\u0435"
    ],
    "name:spa_x_preferred":[
        "Guanare"
    ],
    "name:swe_x_preferred":[
        "Guanare"
    ],
    "name:ukr_x_preferred":[
        "\u0413\u0443\u0430\u043d\u0430\u0440\u0435"
    ],
    "name:urd_x_preferred":[
        "\u06af\u0648\u0627\u0646\u0627\u0631\u06d2"
    ],
    "name:vol_x_preferred":[
        "Guanare"
    ],
    "name:war_x_preferred":[
        "Guanare"
    ],
    "name:zho_x_preferred":[
        "\u74dc\u7d0d\u96f7"
    ],
    "wof:name":"Guanare",
    "wof:placetype":"locality"
},
  "geometry": {"coordinates":[-65.83949,8.99878],"type":"Point"}
}