{
  "type": "Feature",
  "properties": {
    "gn:admin1_code":"12.0",
    "gn:asciiname":"Guanare",
    "gn:country_code":"VE",
    "gn:dem":129,
    "gn:feature_class":"P",
    "gn:feature_code":"PPL",
    "gn:name":"Guanare",
    "gn:population":0,
    "gn:timezone":"America/Caracas",
    "iso:country":"VE",
    "wof:name":"Guanare",
    "wof:placetype":"locality"
},
  "geometry": {"coordinates":[-65.83949,8.99878],"type":"Point"}
}