{
  "type": "Feature",
  "properties": {
    "gn:admin1_code":"22",
    "gn:asciiname":"El Copey",
    "gn:country_code":"VE",
    "gn:dem":1144,
    "gn:feature_class":"P",
    "gn:feature_code":"PPL",
    "gn:name":"El Copey",
    "gn:population":0,
    "gn:timezone":"America/Caracas",
    "iso:country":"VE",
    "wof:name":"El Copey",
    "wof:placetype":"locality"
},
  "geometry": {"coordinates":[-69.01244,10.2871],"type":"Point"}
}