{
  "type": "Feature",
  "properties": {
    "gn:admin1_code":"18",
    "gn:asciiname":"Tucupido",
    "gn:country_code":"VE",
    "gn:dem":165,
    "gn:feature_class":"P",
    "gn:feature_code":"PPL",
    "gn:name":"Tucupido",
    "gn:population":0,
    "gn:timezone":"America/Caracas",
    "iso:country":"VE",
    "wof:name":"Tucupido",
    "wof:placetype":"locality"
},
  "geometry": {"coordinates":[-69.84567,8.9518],"type":"Point"}
}