{
  "type": "Feature",
  "properties": {
    "gn:admin1_code":"16",
    "gn:asciiname":"Temblador",
    "gn:cc2":"VE",
    "gn:country_code":"VE",
    "gn:dem":45,
    "gn:feature_class":"P",
    "gn:feature_code":"PPL",
    "gn:name":"Temblador",
    "gn:population":0,
    "gn:timezone":"America/Caracas",
    "iso:country":"VE",
    "name:und_x_variant":[
        "El Temblador",
        "Morichal Temblador",
        "Temblador"
    ],
    "wof:name":"Temblador",
    "wof:placetype":"locality"
},
  "geometry": {"coordinates":[-62.73333,8.98333],"type":"Point"}
}