{
  "type": "Feature",
  "properties": {
    "gn:admin1_code":"20.0",
    "gn:asciiname":"La Blanquita",
    "gn:country_code":"VE",
    "gn:dem":248,
    "gn:feature_class":"P",
    "gn:feature_code":"PPL",
    "gn:name":"La Blanquita",
    "gn:population":0,
    "gn:timezone":"America/Caracas",
    "iso:country":"VE",
    "wof:name":"La Blanquita",
    "wof:placetype":"locality"
},
  "geometry": {"coordinates":[-71.67504,7.72474],"type":"Point"}
}