{
  "type": "Feature",
  "properties": {
    "gn:admin1_code":"3.0",
    "gn:asciiname":"Mata de Pilon",
    "gn:country_code":"VE",
    "gn:dem":91,
    "gn:feature_class":"P",
    "gn:feature_code":"PPLL",
    "gn:name":"Mata de Pil\u00f3n",
    "gn:population":0,
    "gn:timezone":"America/Caracas",
    "iso:country":"VE",
    "wof:name":"Mata de Pilon",
    "wof:placetype":"locality"
},
  "geometry": {"coordinates":[-69.60389000000001,7.54444],"type":"Point"}
}