{
  "type": "Feature",
  "properties": {
    "gn:admin1_code":"21",
    "gn:asciiname":"El Hatico",
    "gn:country_code":"VE",
    "gn:dem":605,
    "gn:feature_class":"P",
    "gn:feature_code":"PPL",
    "gn:name":"El Hatico",
    "gn:population":0,
    "gn:timezone":"America/Caracas",
    "iso:country":"VE",
    "wof:name":"El Hatico",
    "wof:placetype":"locality"
},
  "geometry": {"coordinates":[-70.43000000000001,9.39167],"type":"Point"}
}