{
  "type": "Feature",
  "properties": {
    "gn:admin1_code":"11",
    "gn:asciiname":"Piedra Honda",
    "gn:country_code":"VE",
    "gn:dem":177,
    "gn:feature_class":"P",
    "gn:feature_code":"PPL",
    "gn:name":"Piedra Honda",
    "gn:population":0,
    "gn:timezone":"America/Caracas",
    "iso:country":"VE",
    "wof:name":"Piedra Honda",
    "wof:placetype":"locality"
},
  "geometry": {"coordinates":[-70.00994,11.94124],"type":"Point"}
}