{
  "type": "Feature",
  "properties": {
    "gn:admin1_code":"13",
    "gn:asciiname":"La Izquierda",
    "gn:country_code":"VE",
    "gn:dem":809,
    "gn:feature_class":"P",
    "gn:feature_code":"PPL",
    "gn:name":"La Izquierda",
    "gn:population":0,
    "gn:timezone":"America/Caracas",
    "iso:country":"VE",
    "wof:name":"La Izquierda",
    "wof:placetype":"locality"
},
  "geometry": {"coordinates":[-70.11536,10.39963],"type":"Point"}
}