{
  "type": "Feature",
  "properties": {
    "gn:admin1_code":"1",
    "gn:asciiname":"Macanilla",
    "gn:country_code":"VE",
    "gn:dem":116,
    "gn:feature_class":"P",
    "gn:feature_code":"PPL",
    "gn:name":"Macanilla",
    "gn:population":0,
    "gn:timezone":"America/Caracas",
    "iso:country":"VE",
    "wof:name":"Macanilla",
    "wof:placetype":"locality"
},
  "geometry": {"coordinates":[-66.98333000000001,1.71667],"type":"Point"}
}