{
  "type": "Feature",
  "properties": {
    "gn:admin1_code":"12",
    "gn:asciiname":"Boca Mahomito",
    "gn:country_code":"VE",
    "gn:dem":109,
    "gn:feature_class":"P",
    "gn:feature_code":"PPL",
    "gn:name":"Boca Mahomito",
    "gn:population":0,
    "gn:timezone":"America/Caracas",
    "iso:country":"VE",
    "wof:name":"Boca Mahomito",
    "wof:placetype":"locality"
},
  "geometry": {"coordinates":[-65.40000000000001,8.55],"type":"Point"}
}