{
  "type": "Feature",
  "properties": {
    "gn:admin1_code":"4",
    "gn:asciiname":"Los Algodones",
    "gn:country_code":"VE",
    "gn:dem":187,
    "gn:feature_class":"P",
    "gn:feature_code":"PPL",
    "gn:name":"Los Algodones",
    "gn:population":0,
    "gn:timezone":"America/Caracas",
    "iso:country":"VE",
    "wof:name":"Los Algodones",
    "wof:placetype":"locality"
},
  "geometry": {"coordinates":[-66.74571,9.39261],"type":"Point"}
}