{
  "type": "Feature",
  "properties": {
    "gn:admin1_code":"13",
    "gn:asciiname":"Los Corrales",
    "gn:country_code":"VE",
    "gn:dem":753,
    "gn:feature_class":"P",
    "gn:feature_code":"PPL",
    "gn:name":"Los Corrales",
    "gn:population":0,
    "gn:timezone":"America/Caracas",
    "iso:country":"VE",
    "wof:name":"Los Corrales",
    "wof:placetype":"locality"
},
  "geometry": {"coordinates":[-69.94444,9.93],"type":"Point"}
}