{
  "type": "Feature",
  "properties": {
    "gn:admin1_code":"19",
    "gn:asciiname":"El Chispero",
    "gn:country_code":"VE",
    "gn:dem":239,
    "gn:feature_class":"P",
    "gn:feature_code":"PPL",
    "gn:name":"El Chispero",
    "gn:population":0,
    "gn:timezone":"America/Caracas",
    "iso:country":"VE",
    "wof:name":"El Chispero",
    "wof:placetype":"locality"
},
  "geometry": {"coordinates":[-63.63755,10.43697],"type":"Point"}
}