{
  "type": "Feature",
  "properties": {
    "gn:admin1_code":"4",
    "gn:asciiname":"La Conopia",
    "gn:country_code":"VE",
    "gn:dem":670,
    "gn:feature_class":"P",
    "gn:feature_code":"PPL",
    "gn:name":"La Conopia",
    "gn:population":0,
    "gn:timezone":"America/Caracas",
    "iso:country":"VE",
    "wof:name":"La Conopia",
    "wof:placetype":"locality"
},
  "geometry": {"coordinates":[-67.37092,10.01468],"type":"Point"}
}