{
  "type": "Feature",
  "properties": {
    "gn:admin1_code":"13",
    "gn:asciiname":"Los Morochos",
    "gn:country_code":"VE",
    "gn:dem":253,
    "gn:feature_class":"P",
    "gn:feature_code":"PPL",
    "gn:name":"Los Morochos",
    "gn:population":0,
    "gn:timezone":"America/Caracas",
    "iso:country":"VE",
    "wof:name":"Los Morochos",
    "wof:placetype":"locality"
},
  "geometry": {"coordinates":[-69.02806,9.92139],"type":"Point"}
}