{
  "type": "Feature",
  "properties": {
    "gn:admin1_code":"6.0",
    "gn:asciiname":"Lapo",
    "gn:country_code":"VE",
    "gn:dem":346,
    "gn:feature_class":"P",
    "gn:feature_code":"PPL",
    "gn:name":"Lapo",
    "gn:population":0,
    "gn:timezone":"America/Caracas",
    "iso:country":"VE",
    "wof:name":"Lapo",
    "wof:placetype":"locality"
},
  "geometry": {"coordinates":[-63.76722,6.07167],"type":"Point"}
}