{
  "type": "Feature",
  "properties": {
    "gn:admin1_code":"13.0",
    "gn:asciiname":"El Castillo",
    "gn:country_code":"VE",
    "gn:dem":513,
    "gn:feature_class":"P",
    "gn:feature_code":"PPL",
    "gn:name":"El Castillo",
    "gn:population":0,
    "gn:timezone":"America/Caracas",
    "iso:country":"VE",
    "name:ceb_x_preferred":[
        "El Castillo"
    ],
    "name:deu_x_preferred":[
        "El Castillo"
    ],
    "name:ita_x_preferred":[
        "El Castillo"
    ],
    "name:nld_x_preferred":[
        "El Castillo"
    ],
    "name:pol_x_preferred":[
        "El Castillo"
    ],
    "name:spa_x_preferred":[
        "El Castillo"
    ],
    "name:swe_x_preferred":[
        "El Castillo"
    ],
    "name:vie_x_preferred":[
        "El Castillo"
    ],
    "wof:name":"El Castillo",
    "wof:placetype":"locality"
},
  "geometry": {"coordinates":[-70.24320999999999,9.83503],"type":"Point"}
}