{
  "type": "Feature",
  "properties": {
    "gn:admin1_code":"18.0",
    "gn:asciiname":"Mata de Mijagua",
    "gn:country_code":"VE",
    "gn:dem":158,
    "gn:feature_class":"P",
    "gn:feature_code":"PPLL",
    "gn:name":"Mata de Mijagua",
    "gn:population":0,
    "gn:timezone":"America/Caracas",
    "iso:country":"VE",
    "name:spa_x_preferred":[
        "Mata de Mijagua"
    ],
    "wof:name":"Mata de Mijagua",
    "wof:placetype":"locality"
},
  "geometry": {"coordinates":[-69.25778000000001,9.32556],"type":"Point"}
}