{
  "type": "Feature",
  "properties": {
    "gn:admin1_code":"20",
    "gn:admin2_code":"2026.0",
    "gn:asciiname":"Queniquea",
    "gn:country_code":"VE",
    "gn:dem":1626,
    "gn:feature_class":"P",
    "gn:feature_code":"PPLA2",
    "gn:name":"Queniquea",
    "gn:population":0,
    "gn:timezone":"America/Caracas",
    "iso:country":"VE",
    "name:zho_x_preferred":[
        "\u514b\u5c3c\u514b\u963f"
    ],
    "wof:name":"Queniquea",
    "wof:placetype":"locality"
},
  "geometry": {"coordinates":[-72.01557,7.91717],"type":"Point"}
}