{
  "type": "Feature",
  "properties": {
    "gn:admin1_code":"21",
    "gn:asciiname":"El Golfo",
    "gn:country_code":"VE",
    "gn:dem":30,
    "gn:feature_class":"P",
    "gn:feature_code":"PPL",
    "gn:name":"El Golfo",
    "gn:population":0,
    "gn:timezone":"America/Caracas",
    "iso:country":"VE",
    "wof:name":"El Golfo",
    "wof:placetype":"locality"
},
  "geometry": {"coordinates":[-70.78928000000001,9.67267],"type":"Point"}
}