{
  "type": "Feature",
  "properties": {
    "gn:admin1_code":"3.0",
    "gn:asciiname":"Montes de Oca",
    "gn:country_code":"VE",
    "gn:dem":71,
    "gn:feature_class":"P",
    "gn:feature_code":"PPLL",
    "gn:name":"Montes de Oca",
    "gn:population":0,
    "gn:timezone":"America/Caracas",
    "iso:country":"VE",
    "wof:name":"Montes de Oca",
    "wof:placetype":"locality"
},
  "geometry": {"coordinates":[-68.59703,7.38346],"type":"Point"}
}