{
  "type": "Feature",
  "properties": {
    "gn:admin1_code":"2",
    "gn:asciiname":"Manirito",
    "gn:country_code":"VE",
    "gn:dem":211,
    "gn:feature_class":"P",
    "gn:feature_code":"PPL",
    "gn:name":"Manirito",
    "gn:population":0,
    "gn:timezone":"America/Caracas",
    "iso:country":"VE",
    "name:und_x_variant":[
        "Manipito",
        "Manirito"
    ],
    "wof:name":"Manirito",
    "wof:placetype":"locality"
},
  "geometry": {"coordinates":[-64.95534000000001,9.97824],"type":"Point"}
}