{
  "type": "Feature",
  "properties": {
    "gn:admin1_code":"25",
    "gn:asciiname":"El Gallo",
    "gn:country_code":"VE",
    "gn:dem":1140,
    "gn:feature_class":"P",
    "gn:feature_code":"PPLL",
    "gn:name":"El Gallo",
    "gn:population":0,
    "gn:timezone":"America/Caracas",
    "iso:country":"VE",
    "wof:name":"El Gallo",
    "wof:placetype":"locality"
},
  "geometry": {"coordinates":[-66.97785999999999,10.49734],"type":"Point"}
}