{
  "type": "Feature",
  "properties": {
    "iso:country":"VE",
    "qs:gn_pop":0,
    "qs:name":"Sucre",
    "qs:name_adm0":"Venezuela",
    "qs:name_adm1":"Distrito Federal",
    "qs:photos":1,
    "qs:photos_1k":1,
    "qs:photos_9k":1,
    "qs:photos_9r":2,
    "qs:photos_all":38,
    "qs:photos_sr":1,
    "qs:placetype":"LocalAdmin",
    "qs:pop_sr":"0",
    "qs:woe_adm0":23424982,
    "wof:name":"Sucre",
    "wof:placetype":"localadmin"
},
  "geometry": {"coordinates":[-66.954666,10.521906],"type":"Point"}
}