{
  "type": "Feature",
  "properties": {
    "gn:admin1_code":"12",
    "gn:asciiname":"Casirey",
    "gn:cc2":"VE",
    "gn:country_code":"VE",
    "gn:dem":168,
    "gn:feature_class":"P",
    "gn:feature_code":"PPL",
    "gn:name":"Casirey",
    "gn:population":0,
    "gn:timezone":"America/Caracas",
    "iso:country":"VE",
    "name:und_x_variant":[
        "Caserey",
        "Casirey"
    ],
    "wof:name":"Casirey",
    "wof:placetype":"locality"
},
  "geometry": {"coordinates":[-66.26666999999999,9.26667],"type":"Point"}
}