{
  "type": "Feature",
  "properties": {
    "gn:admin1_code":"16",
    "gn:asciiname":"La Guacharaca",
    "gn:country_code":"VE",
    "gn:dem":143,
    "gn:feature_class":"P",
    "gn:feature_code":"PPL",
    "gn:name":"La Guacharaca",
    "gn:population":0,
    "gn:timezone":"America/Caracas",
    "iso:country":"VE",
    "wof:name":"La Guacharaca",
    "wof:placetype":"locality"
},
  "geometry": {"coordinates":[-63.52231999999999,9.37796],"type":"Point"}
}