{
  "type": "Feature",
  "properties": {
    "gn:admin1_code":"22",
    "gn:asciiname":"Campo Nuevo",
    "gn:country_code":"VE",
    "gn:dem":216,
    "gn:feature_class":"P",
    "gn:feature_code":"PPL",
    "gn:name":"Campo Nuevo",
    "gn:population":0,
    "gn:timezone":"America/Caracas",
    "iso:country":"VE",
    "wof:name":"Campo Nuevo",
    "wof:placetype":"locality"
},
  "geometry": {"coordinates":[-68.80158,10.21716],"type":"Point"}
}