{
  "type": "Feature",
  "properties": {
    "gn:admin1_code":"6.0",
    "gn:asciiname":"El Cruce",
    "gn:country_code":"VE",
    "gn:dem":362,
    "gn:feature_class":"P",
    "gn:feature_code":"PPL",
    "gn:name":"El Cruce",
    "gn:population":0,
    "gn:timezone":"America/Caracas",
    "iso:country":"VE",
    "wof:name":"El Cruce",
    "wof:placetype":"locality"
},
  "geometry": {"coordinates":[-63.30722,7.36944],"type":"Point"}
}