{
  "type": "Feature",
  "properties": {
    "gn:admin1_code":"15",
    "gn:asciiname":"El Pauji",
    "gn:country_code":"VE",
    "gn:dem":483,
    "gn:feature_class":"P",
    "gn:feature_code":"PPL",
    "gn:name":"El Pauj\u00ed",
    "gn:population":0,
    "gn:timezone":"America/Caracas",
    "iso:country":"VE",
    "wof:name":"El Pauji",
    "wof:placetype":"locality"
},
  "geometry": {"coordinates":[-66.49743000000001,10.3801],"type":"Point"}
}