{
  "type": "Feature",
  "properties": {
    "gn:admin1_code":"5",
    "gn:asciiname":"Penitas",
    "gn:country_code":"VE",
    "gn:dem":154,
    "gn:feature_class":"P",
    "gn:feature_code":"PPL",
    "gn:name":"Pe\u00f1itas",
    "gn:population":0,
    "gn:timezone":"America/Caracas",
    "iso:country":"VE",
    "name:und_x_variant":[
        "Pel\u00f1itas",
        "Pe\u00f1itas"
    ],
    "wof:name":"Penitas",
    "wof:placetype":"locality"
},
  "geometry": {"coordinates":[-69.95684,8.77066],"type":"Point"}
}