{
  "type": "Feature",
  "properties": {
    "gn:admin1_code":"12.0",
    "gn:asciiname":"Tigrera",
    "gn:country_code":"VE",
    "gn:dem":184,
    "gn:feature_class":"P",
    "gn:feature_code":"PPLL",
    "gn:name":"Tigrera",
    "gn:population":0,
    "gn:timezone":"America/Caracas",
    "iso:country":"VE",
    "wof:name":"Tigrera",
    "wof:placetype":"locality"
},
  "geometry": {"coordinates":[-66.16328,9.29669],"type":"Point"}
}