{
  "type": "Feature",
  "properties": {
    "gn:admin1_code":"15",
    "gn:asciiname":"La Bolica",
    "gn:country_code":"VE",
    "gn:dem":160,
    "gn:feature_class":"P",
    "gn:feature_code":"PPL",
    "gn:name":"La Bolica",
    "gn:population":0,
    "gn:timezone":"America/Caracas",
    "iso:country":"VE",
    "wof:name":"La Bolica",
    "wof:placetype":"locality"
},
  "geometry": {"coordinates":[-66.55851,10.20705],"type":"Point"}
}