{
  "type": "Feature",
  "properties": {
    "gn:admin1_code":"25",
    "gn:asciiname":"Sabanetica",
    "gn:country_code":"VE",
    "gn:dem":1307,
    "gn:feature_class":"P",
    "gn:feature_code":"PPL",
    "gn:name":"Sabanetica",
    "gn:population":0,
    "gn:timezone":"America/Caracas",
    "iso:country":"VE",
    "wof:name":"Sabanetica",
    "wof:placetype":"locality"
},
  "geometry": {"coordinates":[-67.05,10.48333],"type":"Point"}
}