{
  "type": "Feature",
  "properties": {
    "gn:admin1_code":"22",
    "gn:asciiname":"Palo Grande",
    "gn:country_code":"VE",
    "gn:dem":465,
    "gn:feature_class":"P",
    "gn:feature_code":"PPL",
    "gn:name":"Palo Grande",
    "gn:population":0,
    "gn:timezone":"America/Caracas",
    "iso:country":"VE",
    "name:ita_x_preferred":[
        "Palo Grande"
    ],
    "name:spa_x_preferred":[
        "Palo Grande"
    ],
    "name:zho_x_preferred":[
        "\u5e15\u6d1b\u683c\u5170\u5fb7"
    ],
    "wof:name":"Palo Grande",
    "wof:placetype":"locality"
},
  "geometry": {"coordinates":[-68.89275000000001,10.24082],"type":"Point"}
}