{
  "type": "Feature",
  "properties": {
    "gn:admin1_code":"12",
    "gn:asciiname":"El Danto",
    "gn:country_code":"VE",
    "gn:dem":166,
    "gn:feature_class":"P",
    "gn:feature_code":"PPL",
    "gn:name":"El Danto",
    "gn:population":0,
    "gn:timezone":"America/Caracas",
    "iso:country":"VE",
    "wof:name":"El Danto",
    "wof:placetype":"locality"
},
  "geometry": {"coordinates":[-65.76002,9.67523],"type":"Point"}
}