{
  "type": "Feature",
  "properties": {
    "gn:admin1_code":"16",
    "gn:asciiname":"Corozal",
    "gn:country_code":"VE",
    "gn:dem":8,
    "gn:feature_class":"P",
    "gn:feature_code":"PPL",
    "gn:name":"Corozal",
    "gn:population":0,
    "gn:timezone":"America/Caracas",
    "iso:country":"VE",
    "wof:name":"Corozal",
    "wof:placetype":"locality"
},
  "geometry": {"coordinates":[-62.36681,9.13434],"type":"Point"}
}