{
  "type": "Feature",
  "properties": {
    "gn:admin1_code":"16",
    "gn:asciiname":"Corozal",
    "gn:country_code":"VE",
    "gn:dem":8,
    "gn:feature_class":"P",
    "gn:feature_code":"PPL",
    "gn:name":"Corozal",
    "gn:population":0,
    "gn:timezone":"America/Caracas",
    "iso:country":"VE",
    "name:ben_x_preferred":[
        "\u0995\u09cb\u09b0\u09cb\u099c\u09be\u09b2"
    ],
    "name:ceb_x_preferred":[
        "Corozal"
    ],
    "name:deu_x_preferred":[
        "Corozal"
    ],
    "name:ell_x_preferred":[
        "\u039a\u03bf\u03c1\u03bf\u03b6\u03ac\u03bb"
    ],
    "name:fas_x_preferred":[
        "\u06a9\u0648\u0631\u0648\u0632\u0627\u0644"
    ],
    "name:fra_x_preferred":[
        "Corozal"
    ],
    "name:heb_x_preferred":[
        "\u05e7\u05d5\u05e8\u05d5\u05d6\u05d0\u05dc"
    ],
    "name:hin_x_preferred":[
        "\u0915\u094b\u0930\u094b\u091c\u093c\u093e\u0932"
    ],
    "name:hun_x_preferred":[
        "Corozal"
    ],
    "name:ind_x_preferred":[
        "Corozal"
    ],
    "name:ita_x_preferred":[
        "Corozal"
    ],
    "name:kor_x_preferred":[
        "\ucf54\ub85c\uc798"
    ],
    "name:nds_x_preferred":[
        "Corozal"
    ],
    "name:nld_x_preferred":[
        "Corozal"
    ],
    "name:pol_x_preferred":[
        "Corozal"
    ],
    "name:por_x_preferred":[
        "Corozal"
    ],
    "name:rus_x_preferred":[
        "\u041a\u043e\u0440\u043e\u0441\u0430\u043b\u044c"
    ],
    "name:spa_x_preferred":[
        "Corozal"
    ],
    "name:swe_x_preferred":[
        "Corozal"
    ],
    "name:tur_x_preferred":[
        "Corozal"
    ],
    "name:ukr_x_preferred":[
        "\u041a\u043e\u0440\u043e\u0441\u0430\u043b\u044c"
    ],
    "name:vie_x_preferred":[
        "Corozal"
    ],
    "wof:name":"Corozal",
    "wof:placetype":"locality"
},
  "geometry": {"coordinates":[-62.36681,9.13434],"type":"Point"}
}