{
  "type": "Feature",
  "properties": {
    "gn:admin1_code":"16.0",
    "gn:asciiname":"Paila Chinga",
    "gn:country_code":"VE",
    "gn:dem":153,
    "gn:feature_class":"P",
    "gn:feature_code":"PPL",
    "gn:name":"Paila Chinga",
    "gn:population":0,
    "gn:timezone":"America/Caracas",
    "iso:country":"VE",
    "wof:name":"Paila Chinga",
    "wof:placetype":"locality"
},
  "geometry": {"coordinates":[-63.44531,9.80535],"type":"Point"}
}