{
  "type": "Feature",
  "properties": {
    "gn:admin1_code":"13",
    "gn:asciiname":"Los Ejidos",
    "gn:country_code":"VE",
    "gn:dem":691,
    "gn:feature_class":"P",
    "gn:feature_code":"PPL",
    "gn:name":"Los Ejidos",
    "gn:population":0,
    "gn:timezone":"America/Caracas",
    "iso:country":"VE",
    "wof:name":"Los Ejidos",
    "wof:placetype":"locality"
},
  "geometry": {"coordinates":[-69.64393000000001,9.89346],"type":"Point"}
}