{
  "type": "Feature",
  "properties": {
    "gn:admin1_code":"6.0",
    "gn:asciiname":"La Emilia",
    "gn:country_code":"VE",
    "gn:dem":59,
    "gn:feature_class":"P",
    "gn:feature_code":"PPL",
    "gn:name":"La Emilia",
    "gn:population":0,
    "gn:timezone":"America/Caracas",
    "iso:country":"VE",
    "name:ceb_x_preferred":[
        "La Emilia"
    ],
    "name:pol_x_preferred":[
        "La Emilia San Nicolas"
    ],
    "name:sco_x_preferred":[
        "La Emilia"
    ],
    "name:spa_x_preferred":[
        "La Emilia"
    ],
    "name:swe_x_preferred":[
        "La Emilia"
    ],
    "wof:name":"La Emilia",
    "wof:placetype":"locality"
},
  "geometry": {"coordinates":[-66.53364999999999,7.00985],"type":"Point"}
}