{
  "type": "Feature",
  "properties": {
    "gn:admin1_code":"12.0",
    "gn:asciiname":"Jerusalen",
    "gn:country_code":"VE",
    "gn:dem":105,
    "gn:feature_class":"P",
    "gn:feature_code":"PPL",
    "gn:name":"Jerusal\u00e9n",
    "gn:population":0,
    "gn:timezone":"America/Caracas",
    "iso:country":"VE",
    "wof:name":"Jerusalen",
    "wof:placetype":"locality"
},
  "geometry": {"coordinates":[-65.74245999999999,9.12284],"type":"Point"}
}