{
  "type": "Feature",
  "properties": {
    "gn:admin1_code":"18",
    "gn:asciiname":"Buchi",
    "gn:country_code":"VE",
    "gn:dem":236,
    "gn:feature_class":"P",
    "gn:feature_code":"PPL",
    "gn:name":"Buchi",
    "gn:population":0,
    "gn:timezone":"America/Caracas",
    "iso:country":"VE",
    "name:ceb_x_preferred":[
        "Buchi"
    ],
    "name:swe_x_preferred":[
        "Buchi"
    ],
    "wof:name":"Buchi",
    "wof:placetype":"locality"
},
  "geometry": {"coordinates":[-69.31845,9.47552],"type":"Point"}
}