{
  "type": "Feature",
  "properties": {
    "gn:admin1_code":"6.0",
    "gn:asciiname":"Surucun",
    "gn:country_code":"VE",
    "gn:dem":875,
    "gn:feature_class":"P",
    "gn:feature_code":"PPL",
    "gn:name":"Surucun",
    "gn:population":0,
    "gn:timezone":"America/Caracas",
    "iso:country":"VE",
    "wof:name":"Surucun",
    "wof:placetype":"locality"
},
  "geometry": {"coordinates":[-61.41667,4.60389],"type":"Point"}
}