{
  "type": "Feature",
  "properties": {
    "gn:admin1_code":"16",
    "gn:asciiname":"El Potrero",
    "gn:country_code":"VE",
    "gn:dem":222,
    "gn:feature_class":"P",
    "gn:feature_code":"PPL",
    "gn:name":"El Potrero",
    "gn:population":0,
    "gn:timezone":"America/Caracas",
    "iso:country":"VE",
    "wof:name":"El Potrero",
    "wof:placetype":"locality"
},
  "geometry": {"coordinates":[-63.63891,9.69154],"type":"Point"}
}