{
  "type": "Feature",
  "properties": {
    "gn:admin1_code":"12",
    "gn:asciiname":"La Ceiba",
    "gn:country_code":"VE",
    "gn:dem":99,
    "gn:feature_class":"P",
    "gn:feature_code":"PPL",
    "gn:name":"La Ceiba",
    "gn:population":0,
    "gn:timezone":"America/Caracas",
    "iso:country":"VE",
    "wof:name":"La Ceiba",
    "wof:placetype":"locality"
},
  "geometry": {"coordinates":[-66.32413000000001,8.66228],"type":"Point"}
}