{
  "type": "Feature",
  "properties": {
    "gn:admin1_code":"13",
    "gn:asciiname":"El Mamonal",
    "gn:country_code":"VE",
    "gn:dem":792,
    "gn:feature_class":"P",
    "gn:feature_code":"PPL",
    "gn:name":"El Mamonal",
    "gn:population":0,
    "gn:timezone":"America/Caracas",
    "iso:country":"VE",
    "wof:name":"El Mamonal",
    "wof:placetype":"locality"
},
  "geometry": {"coordinates":[-69.81194000000001,9.7076],"type":"Point"}
}