{
  "type": "Feature",
  "properties": {
    "gn:admin1_code":"11",
    "gn:asciiname":"Derramadero",
    "gn:country_code":"VE",
    "gn:dem":41,
    "gn:feature_class":"P",
    "gn:feature_code":"PPL",
    "gn:name":"Derramadero",
    "gn:population":0,
    "gn:timezone":"America/Caracas",
    "iso:country":"VE",
    "wof:name":"Derramadero",
    "wof:placetype":"locality"
},
  "geometry": {"coordinates":[-69.9658,11.33493],"type":"Point"}
}