{
  "type": "Feature",
  "properties": {
    "gn:admin1_code":"6",
    "gn:asciiname":"El Yagual",
    "gn:cc2":"VE",
    "gn:country_code":"VE",
    "gn:dem":239,
    "gn:feature_class":"P",
    "gn:feature_code":"PPL",
    "gn:name":"El Yagual",
    "gn:population":0,
    "gn:timezone":"America/Caracas",
    "iso:country":"VE",
    "name:und_x_variant":[
        "Yagual",
        "El Yagual"
    ],
    "wof:name":"El Yagual",
    "wof:placetype":"locality"
},
  "geometry": {"coordinates":[-62.48333,7.21667],"type":"Point"}
}