{
  "type": "Feature",
  "properties": {
    "gn:admin1_code":"12.0",
    "gn:asciiname":"Kilometro 132",
    "gn:country_code":"VE",
    "gn:dem":194,
    "gn:feature_class":"P",
    "gn:feature_code":"PPL",
    "gn:name":"Kil\u00f3metro 132",
    "gn:population":0,
    "gn:timezone":"America/Caracas",
    "iso:country":"VE",
    "wof:name":"Kilometro 132",
    "wof:placetype":"locality"
},
  "geometry": {"coordinates":[-65.63093000000001,9.57946],"type":"Point"}
}