{
  "type": "Feature",
  "properties": {
    "gn:admin1_code":"11.0",
    "gn:asciiname":"Las Yeritas",
    "gn:country_code":"VE",
    "gn:dem":72,
    "gn:feature_class":"P",
    "gn:feature_code":"PPL",
    "gn:name":"Las Yeritas",
    "gn:population":0,
    "gn:timezone":"America/Caracas",
    "iso:country":"VE",
    "wof:name":"Las Yeritas",
    "wof:placetype":"locality"
},
  "geometry": {"coordinates":[-70.68267,11.09593],"type":"Point"}
}