{
  "type": "Feature",
  "properties": {
    "gn:admin1_code":"23",
    "gn:asciiname":"La Trinidad",
    "gn:country_code":"VE",
    "gn:dem":80,
    "gn:feature_class":"P",
    "gn:feature_code":"PPL",
    "gn:name":"La Trinidad",
    "gn:population":0,
    "gn:timezone":"America/Caracas",
    "iso:country":"VE",
    "name:ceb_x_preferred":[
        "La Trinidad"
    ],
    "name:deu_x_preferred":[
        "La Trinidad"
    ],
    "name:ita_x_preferred":[
        "La Trinidad"
    ],
    "name:nld_x_preferred":[
        "La Trinidad"
    ],
    "name:srp_x_preferred":[
        "\u041b\u0430 \u0422\u0440\u0438\u043d\u0438\u0434\u0430\u0434"
    ],
    "name:swe_x_preferred":[
        "La Trinidad"
    ],
    "name:vie_x_preferred":[
        "La Trinidad"
    ],
    "wof:name":"La Trinidad",
    "wof:placetype":"locality"
},
  "geometry": {"coordinates":[-71.97391999999998,10.67192],"type":"Point"}
}