{
  "type": "Feature",
  "properties": {
    "gn:admin1_code":"8",
    "gn:asciiname":"El Angulo",
    "gn:country_code":"VE",
    "gn:dem":96,
    "gn:feature_class":"P",
    "gn:feature_code":"PPL",
    "gn:name":"El \u00c1ngulo",
    "gn:population":0,
    "gn:timezone":"America/Caracas",
    "iso:country":"VE",
    "wof:name":"El Angulo",
    "wof:placetype":"locality"
},
  "geometry": {"coordinates":[-68.63002,9.32352],"type":"Point"}
}