{
  "type": "Feature",
  "properties": {
    "gn:admin1_code":"11",
    "gn:asciiname":"El Colorado",
    "gn:country_code":"VE",
    "gn:dem":41,
    "gn:feature_class":"P",
    "gn:feature_code":"PPL",
    "gn:name":"El Colorado",
    "gn:population":0,
    "gn:timezone":"America/Caracas",
    "iso:country":"VE",
    "name:deu_x_preferred":[
        "El Colorado"
    ],
    "name:fra_x_preferred":[
        "El Colorado"
    ],
    "name:nld_x_preferred":[
        "El Colorado"
    ],
    "name:pol_x_preferred":[
        "El Colorado"
    ],
    "name:por_x_preferred":[
        "El Colorado"
    ],
    "name:spa_x_preferred":[
        "El Colorado"
    ],
    "wof:name":"El Colorado",
    "wof:placetype":"locality"
},
  "geometry": {"coordinates":[-68.61667,11.23333],"type":"Point"}
}