{
  "type": "Feature",
  "properties": {
    "gn:admin1_code":"13.0",
    "gn:asciiname":"Nueva Segovia",
    "gn:country_code":"VE",
    "gn:dem":524,
    "gn:feature_class":"P",
    "gn:feature_code":"PPL",
    "gn:name":"Nueva Segovia",
    "gn:population":0,
    "gn:timezone":"America/Caracas",
    "iso:country":"VE",
    "name:heb_x_preferred":[
        "\u05e0\u05d5\u05d0\u05d1\u05d4 \u05e1\u05d2\u05d5\u05d1\u05d9\u05d4"
    ],
    "name:por_x_preferred":[
        "Nueva Segovia"
    ],
    "wof:name":"Nueva Segovia",
    "wof:placetype":"locality"
},
  "geometry": {"coordinates":[-69.28428,10.05682],"type":"Point"}
}