{
  "type": "Feature",
  "properties": {
    "gn:admin1_code":"13.0",
    "gn:asciiname":"Nueva Segovia",
    "gn:country_code":"VE",
    "gn:dem":524,
    "gn:feature_class":"P",
    "gn:feature_code":"PPL",
    "gn:name":"Nueva Segovia",
    "gn:population":0,
    "gn:timezone":"America/Caracas",
    "iso:country":"VE",
    "wof:name":"Nueva Segovia",
    "wof:placetype":"locality"
},
  "geometry": {"coordinates":[-69.28428000000001,10.05682],"type":"Point"}
}