{
  "type": "Feature",
  "properties": {
    "gn:admin1_code":"19.0",
    "gn:asciiname":"Puerto Soro",
    "gn:country_code":"VE",
    "gn:dem":8,
    "gn:feature_class":"P",
    "gn:feature_code":"PPL",
    "gn:name":"Puerto Soro",
    "gn:population":0,
    "gn:timezone":"America/Caracas",
    "iso:country":"VE",
    "wof:name":"Puerto Soro",
    "wof:placetype":"locality"
},
  "geometry": {"coordinates":[-62.45303000000001,10.54439],"type":"Point"}
}