{
  "type": "Feature",
  "properties": {
    "gn:admin1_code":"15",
    "gn:asciiname":"Nisperal",
    "gn:country_code":"VE",
    "gn:dem":353,
    "gn:feature_class":"P",
    "gn:feature_code":"PPL",
    "gn:name":"Nisperal",
    "gn:population":0,
    "gn:timezone":"America/Caracas",
    "iso:country":"VE",
    "wof:name":"Nisperal",
    "wof:placetype":"locality"
},
  "geometry": {"coordinates":[-65.596,10.06681],"type":"Point"}
}