{
  "type": "Feature",
  "properties": {
    "gn:admin1_code":"15",
    "gn:asciiname":"La Bocaina",
    "gn:country_code":"VE",
    "gn:dem":613,
    "gn:feature_class":"P",
    "gn:feature_code":"PPL",
    "gn:name":"La Bocaina",
    "gn:population":0,
    "gn:timezone":"America/Caracas",
    "iso:country":"VE",
    "wof:name":"La Bocaina",
    "wof:placetype":"locality"
},
  "geometry": {"coordinates":[-66.53333000000001,9.98333],"type":"Point"}
}