{
  "type": "Feature",
  "properties": {
    "gn:admin1_code":"21",
    "gn:asciiname":"Horcon Sur",
    "gn:country_code":"VE",
    "gn:dem":21,
    "gn:feature_class":"P",
    "gn:feature_code":"PPL",
    "gn:name":"Horcon Sur",
    "gn:population":0,
    "gn:timezone":"America/Caracas",
    "iso:country":"VE",
    "wof:name":"Horcon Sur",
    "wof:placetype":"locality"
},
  "geometry": {"coordinates":[-70.87347,9.51134],"type":"Point"}
}