{
  "type": "Feature",
  "properties": {
    "gn:admin1_code":"19.0",
    "gn:asciiname":"El Canton",
    "gn:country_code":"VE",
    "gn:dem":173,
    "gn:feature_class":"P",
    "gn:feature_code":"PPL",
    "gn:name":"El Cant\u00f3n",
    "gn:population":0,
    "gn:timezone":"America/Caracas",
    "iso:country":"VE",
    "wof:name":"El Canton",
    "wof:placetype":"locality"
},
  "geometry": {"coordinates":[-63.41889000000001,10.41778],"type":"Point"}
}