{
  "type": "Feature",
  "properties": {
    "gn:admin1_code":"22",
    "gn:asciiname":"Tamboral",
    "gn:country_code":"VE",
    "gn:dem":553,
    "gn:feature_class":"P",
    "gn:feature_code":"PPL",
    "gn:name":"Tamboral",
    "gn:population":0,
    "gn:timezone":"America/Caracas",
    "iso:country":"VE",
    "wof:name":"Tamboral",
    "wof:placetype":"locality"
},
  "geometry": {"coordinates":[-68.8338,10.02201],"type":"Point"}
}