{
  "type": "Feature",
  "properties": {
    "gn:admin1_code":"12",
    "gn:asciiname":"Monterola",
    "gn:country_code":"VE",
    "gn:dem":183,
    "gn:feature_class":"P",
    "gn:feature_code":"PPL",
    "gn:name":"Monterola",
    "gn:population":0,
    "gn:timezone":"America/Caracas",
    "iso:country":"VE",
    "wof:name":"Monterola",
    "wof:placetype":"locality"
},
  "geometry": {"coordinates":[-67.35947,9.50178],"type":"Point"}
}