{
  "type": "Feature",
  "properties": {
    "gn:admin1_code":"23.0",
    "gn:asciiname":"Pozo Largo",
    "gn:country_code":"VE",
    "gn:dem":20,
    "gn:feature_class":"P",
    "gn:feature_code":"PPLL",
    "gn:name":"Pozo Largo",
    "gn:population":0,
    "gn:timezone":"America/Caracas",
    "iso:country":"VE",
    "wof:name":"Pozo Largo",
    "wof:placetype":"locality"
},
  "geometry": {"coordinates":[-71.9987,10.31822],"type":"Point"}
}