{
  "type": "Feature",
  "properties": {
    "gn:admin1_code":"13",
    "gn:asciiname":"San Pedro",
    "gn:country_code":"VE",
    "gn:dem":1479,
    "gn:feature_class":"P",
    "gn:feature_code":"PPL",
    "gn:name":"San Pedro",
    "gn:population":0,
    "gn:timezone":"America/Caracas",
    "iso:country":"VE",
    "name:eng_x_preferred":[
        "San Pedro"
    ],
    "name:por_x_preferred":[
        "San Pedro"
    ],
    "name:spa_x_preferred":[
        "San Pedro"
    ],
    "wof:name":"San Pedro",
    "wof:placetype":"locality"
},
  "geometry": {"coordinates":[-70.08181999999999,9.86333],"type":"Point"}
}