{
  "type": "Feature",
  "properties": {
    "gn:admin1_code":"5",
    "gn:asciiname":"La Sabaneta",
    "gn:country_code":"VE",
    "gn:dem":137,
    "gn:feature_class":"P",
    "gn:feature_code":"PPL",
    "gn:name":"La Sabaneta",
    "gn:population":0,
    "gn:timezone":"America/Caracas",
    "iso:country":"VE",
    "wof:name":"La Sabaneta",
    "wof:placetype":"locality"
},
  "geometry": {"coordinates":[-70.09999999999999,8.48333],"type":"Point"}
}