{
  "type": "Feature",
  "properties": {
    "gn:admin1_code":"14",
    "gn:asciiname":"Mucubaji",
    "gn:country_code":"VE",
    "gn:dem":2649,
    "gn:feature_class":"P",
    "gn:feature_code":"PPL",
    "gn:name":"Mucubaj\u00ed",
    "gn:population":0,
    "gn:timezone":"America/Caracas",
    "iso:country":"VE",
    "wof:name":"Mucubaji",
    "wof:placetype":"locality"
},
  "geometry": {"coordinates":[-71.08333,8.46667],"type":"Point"}
}