{
  "type": "Feature",
  "properties": {
    "gn:admin1_code":"12.0",
    "gn:asciiname":"Camachero",
    "gn:country_code":"VE",
    "gn:dem":47,
    "gn:feature_class":"P",
    "gn:feature_code":"PPL",
    "gn:name":"Camachero",
    "gn:population":0,
    "gn:timezone":"America/Caracas",
    "iso:country":"VE",
    "wof:name":"Camachero",
    "wof:placetype":"locality"
},
  "geometry": {"coordinates":[-67.19556,7.78167],"type":"Point"}
}