{
  "type": "Feature",
  "properties": {
    "gn:admin1_code":"11.0",
    "gn:asciiname":"La Guarabita",
    "gn:country_code":"VE",
    "gn:dem":661,
    "gn:feature_class":"P",
    "gn:feature_code":"PPL",
    "gn:name":"La Guarabita",
    "gn:population":0,
    "gn:timezone":"America/Caracas",
    "iso:country":"VE",
    "wof:name":"La Guarabita",
    "wof:placetype":"locality"
},
  "geometry": {"coordinates":[-69.71318000000001,11.10657],"type":"Point"}
}