{
  "type": "Feature",
  "properties": {
    "gn:admin1_code":"23",
    "gn:asciiname":"La Paz",
    "gn:country_code":"VE",
    "gn:dem":5,
    "gn:feature_class":"P",
    "gn:feature_code":"PPL",
    "gn:name":"La Paz",
    "gn:population":0,
    "gn:timezone":"America/Caracas",
    "iso:country":"VE",
    "wof:name":"La Paz",
    "wof:placetype":"locality"
},
  "geometry": {"coordinates":[-71.91809000000001,9.04644],"type":"Point"}
}