{
  "type": "Feature",
  "properties": {
    "gn:admin1_code":"3.0",
    "gn:asciiname":"Sabana Los Blancos",
    "gn:country_code":"VE",
    "gn:dem":145,
    "gn:feature_class":"P",
    "gn:feature_code":"PPLL",
    "gn:name":"Sabana Los Blancos",
    "gn:population":0,
    "gn:timezone":"America/Caracas",
    "iso:country":"VE",
    "wof:name":"Sabana Los Blancos",
    "wof:placetype":"locality"
},
  "geometry": {"coordinates":[-71.22333,7.32889],"type":"Point"}
}