{
  "type": "Feature",
  "properties": {
    "gn:admin1_code":"21",
    "gn:asciiname":"El Pie",
    "gn:country_code":"VE",
    "gn:dem":1528,
    "gn:feature_class":"P",
    "gn:feature_code":"PPL",
    "gn:name":"El Pi\u00e9",
    "gn:population":0,
    "gn:timezone":"America/Caracas",
    "iso:country":"VE",
    "wof:name":"El Pie",
    "wof:placetype":"locality"
},
  "geometry": {"coordinates":[-70.34799,9.50851],"type":"Point"}
}