{
  "type": "Feature",
  "properties": {
    "gn:admin1_code":"11",
    "gn:asciiname":"Las Farias",
    "gn:country_code":"VE",
    "gn:dem":18,
    "gn:feature_class":"P",
    "gn:feature_code":"PPL",
    "gn:name":"Las Farias",
    "gn:population":0,
    "gn:timezone":"America/Caracas",
    "iso:country":"VE",
    "wof:name":"Las Farias",
    "wof:placetype":"locality"
},
  "geometry": {"coordinates":[-71.1409,10.90903],"type":"Point"}
}