{
  "type": "Feature",
  "properties": {
    "gn:admin1_code":"22",
    "gn:asciiname":"Los Horcones",
    "gn:country_code":"VE",
    "gn:dem":231,
    "gn:feature_class":"P",
    "gn:feature_code":"PPL",
    "gn:name":"Los Horcones",
    "gn:population":0,
    "gn:timezone":"America/Caracas",
    "iso:country":"VE",
    "wof:name":"Los Horcones",
    "wof:placetype":"locality"
},
  "geometry": {"coordinates":[-68.83815,10.16542],"type":"Point"}
}