{
  "type": "Feature",
  "properties": {
    "gn:admin1_code":"13",
    "gn:asciiname":"Rincon Hondo",
    "gn:country_code":"VE",
    "gn:dem":1005,
    "gn:feature_class":"P",
    "gn:feature_code":"PPL",
    "gn:name":"Rinc\u00f3n Hondo",
    "gn:population":0,
    "gn:timezone":"America/Caracas",
    "iso:country":"VE",
    "wof:name":"Rincon Hondo",
    "wof:placetype":"locality"
},
  "geometry": {"coordinates":[-69.12430000000001,10.21044],"type":"Point"}
}