{
  "type": "Feature",
  "properties": {
    "gn:admin1_code":"15.0",
    "gn:asciiname":"La Madre Vieja",
    "gn:country_code":"VE",
    "gn:dem":13,
    "gn:feature_class":"P",
    "gn:feature_code":"PPL",
    "gn:name":"La Madre Vieja",
    "gn:population":0,
    "gn:timezone":"America/Caracas",
    "iso:country":"VE",
    "wof:name":"La Madre Vieja",
    "wof:placetype":"locality"
},
  "geometry": {"coordinates":[-66.02167,10.30833],"type":"Point"}
}