{
  "type": "Feature",
  "properties": {
    "gn:admin1_code":"4.0",
    "gn:asciiname":"Guasdual",
    "gn:country_code":"VE",
    "gn:dem":916,
    "gn:feature_class":"P",
    "gn:feature_code":"PPL",
    "gn:name":"Guasdual",
    "gn:population":0,
    "gn:timezone":"America/Caracas",
    "iso:country":"VE",
    "wof:name":"Guasdual",
    "wof:placetype":"locality"
},
  "geometry": {"coordinates":[-67.05141,10.0099],"type":"Point"}
}