{
  "type": "Feature",
  "properties": {
    "gn:admin1_code":"3",
    "gn:asciiname":"Platanales",
    "gn:country_code":"VE",
    "gn:dem":55,
    "gn:feature_class":"P",
    "gn:feature_code":"PPL",
    "gn:name":"Platanales",
    "gn:population":0,
    "gn:timezone":"America/Caracas",
    "iso:country":"VE",
    "wof:name":"Platanales",
    "wof:placetype":"locality"
},
  "geometry": {"coordinates":[-68.11667,7.55],"type":"Point"}
}