{
  "type": "Feature",
  "properties": {
    "iso:country":"VE",
    "qs:gn_pop":0,
    "qs:name":"Delicias",
    "qs:name_adm0":"Venezuela",
    "qs:name_adm1":"Tachira",
    "qs:photos":7,
    "qs:photos_1k":1,
    "qs:photos_9k":1,
    "qs:photos_9r":2,
    "qs:photos_all":32,
    "qs:photos_sr":1,
    "qs:placetype":"LocalAdmin",
    "qs:pop_sr":"0",
    "qs:woe_adm0":23424982,
    "wof:name":"Delicias",
    "wof:placetype":"localadmin"
},
  "geometry": {"coordinates":[-72.344455,7.456432],"type":"Point"}
}