{
  "type": "Feature",
  "properties": {
    "iso:country":"VE",
    "name:arg_x_preferred":[
        "Delicias"
    ],
    "name:cat_x_preferred":[
        "Delicias"
    ],
    "name:ceb_x_preferred":[
        "Delicias"
    ],
    "name:deu_x_preferred":[
        "Delicias"
    ],
    "name:fra_x_preferred":[
        "Delicias"
    ],
    "name:ita_x_preferred":[
        "Delicias"
    ],
    "name:mlg_x_preferred":[
        "Delicias"
    ],
    "name:nld_x_preferred":[
        "Delicias"
    ],
    "name:rus_x_preferred":[
        "\u0414\u0435\u043b\u0438\u0441\u044c\u044f\u0441"
    ],
    "name:spa_x_preferred":[
        "Las Delicias"
    ],
    "name:swe_x_preferred":[
        "Delicias"
    ],
    "qs:gn_pop":0,
    "qs:name":"Delicias",
    "qs:name_adm0":"Venezuela",
    "qs:name_adm1":"Tachira",
    "qs:photos":7,
    "qs:photos_1k":1,
    "qs:photos_9k":1,
    "qs:photos_9r":2,
    "qs:photos_all":32,
    "qs:photos_sr":1,
    "qs:placetype":"LocalAdmin",
    "qs:pop_sr":"0",
    "qs:woe_adm0":23424982,
    "wof:name":"Delicias",
    "wof:placetype":"localadmin"
},
  "geometry": {"coordinates":[-72.344455,7.456432],"type":"Point"}
}