{
  "type": "Feature",
  "properties": {
    "gn:admin1_code":"8",
    "gn:asciiname":"Canada Honda",
    "gn:country_code":"VE",
    "gn:dem":201,
    "gn:feature_class":"P",
    "gn:feature_code":"PPL",
    "gn:name":"Ca\u00f1ada Honda",
    "gn:population":0,
    "gn:timezone":"America/Caracas",
    "iso:country":"VE",
    "wof:name":"Canada Honda",
    "wof:placetype":"locality"
},
  "geometry": {"coordinates":[-68.08333,9.75],"type":"Point"}
}