{
  "type": "Feature",
  "properties": {
    "gn:admin1_code":"15",
    "gn:asciiname":"Ocumarito",
    "gn:country_code":"VE",
    "gn:dem":359,
    "gn:feature_class":"P",
    "gn:feature_code":"PPL",
    "gn:name":"Ocumarito",
    "gn:population":0,
    "gn:timezone":"America/Caracas",
    "iso:country":"VE",
    "wof:name":"Ocumarito",
    "wof:placetype":"locality"
},
  "geometry": {"coordinates":[-66.84148,10.05561],"type":"Point"}
}