{
  "type": "Feature",
  "properties": {
    "gn:admin1_code":"02",
    "gn:asciiname":"Orejano",
    "gn:country_code":"VE",
    "gn:dem":148,
    "gn:feature_class":"P",
    "gn:feature_code":"PPLL",
    "gn:name":"Orejano",
    "gn:population":0,
    "gn:timezone":"America/Caracas",
    "iso:country":"VE",
    "wof:name":"Orejano",
    "wof:placetype":"locality"
},
  "geometry": {"coordinates":[-64.78856,8.44092],"type":"Point"}
}