{
  "type": "Feature",
  "properties": {
    "gn:admin1_code":"13.0",
    "gn:asciiname":"Sicarre",
    "gn:country_code":"VE",
    "gn:dem":617,
    "gn:feature_class":"P",
    "gn:feature_code":"PPL",
    "gn:name":"Sicarr\u00e9",
    "gn:population":0,
    "gn:timezone":"America/Caracas",
    "iso:country":"VE",
    "wof:name":"Sicarre",
    "wof:placetype":"locality"
},
  "geometry": {"coordinates":[-70.59244,10.091],"type":"Point"}
}