{
  "type": "Feature",
  "properties": {
    "gn:admin1_code":"3",
    "gn:asciiname":"Los Palotes",
    "gn:country_code":"VE",
    "gn:dem":68,
    "gn:feature_class":"P",
    "gn:feature_code":"PPL",
    "gn:name":"Los Palotes",
    "gn:population":0,
    "gn:timezone":"America/Caracas",
    "iso:country":"VE",
    "wof:name":"Los Palotes",
    "wof:placetype":"locality"
},
  "geometry": {"coordinates":[-68.66667,7.85],"type":"Point"}
}