{
  "type": "Feature",
  "properties": {
    "gn:admin1_code":"14",
    "gn:asciiname":"Los Aposentos",
    "gn:country_code":"VE",
    "gn:dem":3296,
    "gn:feature_class":"P",
    "gn:feature_code":"PPL",
    "gn:name":"Los Aposentos",
    "gn:population":0,
    "gn:timezone":"America/Caracas",
    "iso:country":"VE",
    "name:nor_x_preferred":[
        "Los Aposentos"
    ],
    "name:spa_x_preferred":[
        "Parque nacional Los Aposentos"
    ],
    "wof:name":"Los Aposentos",
    "wof:placetype":"locality"
},
  "geometry": {"coordinates":[-70.9434,8.75236],"type":"Point"}
}