{
  "type": "Feature",
  "properties": {
    "gn:admin1_code":"11",
    "gn:asciiname":"La Rusia",
    "gn:country_code":"VE",
    "gn:dem":75,
    "gn:feature_class":"P",
    "gn:feature_code":"PPL",
    "gn:name":"La Rusia",
    "gn:population":0,
    "gn:timezone":"America/Caracas",
    "iso:country":"VE",
    "wof:name":"La Rusia",
    "wof:placetype":"locality"
},
  "geometry": {"coordinates":[-70.16933,11.25835],"type":"Point"}
}