{
  "type": "Feature",
  "properties": {
    "gn:admin1_code":"20",
    "gn:asciiname":"Perdices",
    "gn:country_code":"VE",
    "gn:dem":1028,
    "gn:feature_class":"P",
    "gn:feature_code":"PPL",
    "gn:name":"Perdices",
    "gn:population":0,
    "gn:timezone":"America/Caracas",
    "iso:country":"VE",
    "wof:name":"Perdices",
    "wof:placetype":"locality"
},
  "geometry": {"coordinates":[-72.47235000000001,7.6389],"type":"Point"}
}