{
  "type": "Feature",
  "properties": {
    "gn:admin1_code":"19.0",
    "gn:asciiname":"Lechozal",
    "gn:country_code":"VE",
    "gn:dem":651,
    "gn:feature_class":"P",
    "gn:feature_code":"PPL",
    "gn:name":"Lechozal",
    "gn:population":0,
    "gn:timezone":"America/Caracas",
    "iso:country":"VE",
    "wof:name":"Lechozal",
    "wof:placetype":"locality"
},
  "geometry": {"coordinates":[-63.28288000000001,10.55595],"type":"Point"}
}