{
  "type": "Feature",
  "properties": {
    "gn:admin1_code":"11.0",
    "gn:asciiname":"El Carmelero",
    "gn:country_code":"VE",
    "gn:dem":26,
    "gn:feature_class":"P",
    "gn:feature_code":"PPL",
    "gn:name":"El Carmelero",
    "gn:population":0,
    "gn:timezone":"America/Caracas",
    "iso:country":"VE",
    "wof:name":"El Carmelero",
    "wof:placetype":"locality"
},
  "geometry": {"coordinates":[-70.02812,12.09338],"type":"Point"}
}