{
  "type": "Feature",
  "properties": {
    "gn:admin1_code":"11",
    "gn:asciiname":"Las Veritas",
    "gn:country_code":"VE",
    "gn:dem":159,
    "gn:feature_class":"P",
    "gn:feature_code":"PPL",
    "gn:name":"Las Veritas",
    "gn:population":0,
    "gn:timezone":"America/Caracas",
    "iso:country":"VE",
    "wof:name":"Las Veritas",
    "wof:placetype":"locality"
},
  "geometry": {"coordinates":[-69.33273,11.21477],"type":"Point"}
}