{
  "type": "Feature",
  "properties": {
    "gn:admin1_code":"23",
    "gn:asciiname":"La Rancheria",
    "gn:cc2":"VE",
    "gn:country_code":"VE",
    "gn:dem":35,
    "gn:feature_class":"P",
    "gn:feature_code":"PPL",
    "gn:name":"La Rancher\u00eda",
    "gn:population":0,
    "gn:timezone":"America/Caracas",
    "iso:country":"VE",
    "name:und_x_variant":[
        "Rancheria",
        "La Rancher\u00eda"
    ],
    "wof:name":"La Rancheria",
    "wof:placetype":"locality"
},
  "geometry": {"coordinates":[-71.61667,10.61667],"type":"Point"}
}