{
  "type": "Feature",
  "properties": {
    "gn:admin1_code":"8",
    "gn:asciiname":"La Palenciera",
    "gn:country_code":"VE",
    "gn:dem":105,
    "gn:feature_class":"P",
    "gn:feature_code":"PPL",
    "gn:name":"La Palenciera",
    "gn:population":0,
    "gn:timezone":"America/Caracas",
    "iso:country":"VE",
    "wof:name":"La Palenciera",
    "wof:placetype":"locality"
},
  "geometry": {"coordinates":[-68.71666999999999,9.46667],"type":"Point"}
}