{
  "type": "Feature",
  "properties": {
    "gn:admin1_code":"18",
    "gn:asciiname":"Cordoba",
    "gn:country_code":"VE",
    "gn:dem":1089,
    "gn:feature_class":"P",
    "gn:feature_code":"PPL",
    "gn:name":"C\u00f3rdoba",
    "gn:population":0,
    "gn:timezone":"America/Caracas",
    "iso:country":"VE",
    "wof:name":"Cordoba",
    "wof:placetype":"locality"
},
  "geometry": {"coordinates":[-69.84999999999999,9.33333],"type":"Point"}
}