{
  "type": "Feature",
  "properties": {
    "gn:admin1_code":"05",
    "gn:asciiname":"Piedras Negras",
    "gn:country_code":"VE",
    "gn:dem":194,
    "gn:feature_class":"P",
    "gn:feature_code":"PPL",
    "gn:name":"Piedras Negras",
    "gn:population":0,
    "gn:timezone":"America/Caracas",
    "iso:country":"VE",
    "name:ceb_x_preferred":[
        "Piedras Negras"
    ],
    "name:deu_x_preferred":[
        "Piedras Negras"
    ],
    "name:fra_x_preferred":[
        "Piedras Negras"
    ],
    "name:ita_x_preferred":[
        "Piedras Negras"
    ],
    "name:nld_x_preferred":[
        "Piedras Negras"
    ],
    "name:spa_x_preferred":[
        "Piedras Negras"
    ],
    "name:swe_x_preferred":[
        "Piedras Negras"
    ],
    "name:vie_x_preferred":[
        "Piedras Negras"
    ],
    "wof:name":"Piedras Negras",
    "wof:placetype":"locality"
},
  "geometry": {"coordinates":[-70.2051,8.67257],"type":"Point"}
}