{
  "type": "Feature",
  "properties": {
    "gn:admin1_code":"23",
    "gn:asciiname":"Gato Rey",
    "gn:country_code":"VE",
    "gn:dem":45,
    "gn:feature_class":"P",
    "gn:feature_code":"PPL",
    "gn:name":"Gato Rey",
    "gn:population":0,
    "gn:timezone":"America/Caracas",
    "iso:country":"VE",
    "wof:name":"Gato Rey",
    "wof:placetype":"locality"
},
  "geometry": {"coordinates":[-71.86823000000003,10.83929],"type":"Point"}
}