{
  "type": "Feature",
  "properties": {
    "gn:admin1_code":"15",
    "gn:asciiname":"Cupo",
    "gn:country_code":"VE",
    "gn:dem":227,
    "gn:feature_class":"P",
    "gn:feature_code":"PPL",
    "gn:name":"Cupo",
    "gn:population":0,
    "gn:timezone":"America/Caracas",
    "iso:country":"VE",
    "wof:name":"Cupo",
    "wof:placetype":"locality"
},
  "geometry": {"coordinates":[-66.47887,10.39426],"type":"Point"}
}