{
  "type": "Feature",
  "properties": {
    "gn:admin1_code":"12.0",
    "gn:asciiname":"Paso Falcon",
    "gn:country_code":"VE",
    "gn:dem":51,
    "gn:feature_class":"P",
    "gn:feature_code":"PPLL",
    "gn:name":"Paso Falc\u00f3n",
    "gn:population":0,
    "gn:timezone":"America/Caracas",
    "iso:country":"VE",
    "wof:name":"Paso Falcon",
    "wof:placetype":"locality"
},
  "geometry": {"coordinates":[-67.60110999999999,8.12462],"type":"Point"}
}