{
  "type": "Feature",
  "properties": {
    "gn:admin1_code":"12.0",
    "gn:asciiname":"El Pegon",
    "gn:country_code":"VE",
    "gn:dem":262,
    "gn:feature_class":"P",
    "gn:feature_code":"PPLL",
    "gn:name":"El Peg\u00f3n",
    "gn:population":0,
    "gn:timezone":"America/Caracas",
    "iso:country":"VE",
    "wof:name":"El Pegon",
    "wof:placetype":"locality"
},
  "geometry": {"coordinates":[-65.84810999999999,9.88786],"type":"Point"}
}