{
  "type": "Feature",
  "properties": {
    "gn:admin1_code":"6.0",
    "gn:asciiname":"Los Indios",
    "gn:country_code":"VE",
    "gn:dem":63,
    "gn:feature_class":"P",
    "gn:feature_code":"PPL",
    "gn:name":"Los Indios",
    "gn:population":0,
    "gn:timezone":"America/Caracas",
    "iso:country":"VE",
    "wof:name":"Los Indios",
    "wof:placetype":"locality"
},
  "geometry": {"coordinates":[-63.86645,7.79556],"type":"Point"}
}