{
  "type": "Feature",
  "properties": {
    "gn:admin1_code":"14",
    "gn:asciiname":"El Potrero",
    "gn:country_code":"VE",
    "gn:dem":1229,
    "gn:feature_class":"P",
    "gn:feature_code":"PPL",
    "gn:name":"El Potrero",
    "gn:population":0,
    "gn:timezone":"America/Caracas",
    "iso:country":"VE",
    "name:ceb_x_preferred":[
        "El Potrero"
    ],
    "name:ita_x_preferred":[
        "El Potrero"
    ],
    "name:srp_x_preferred":[
        "\u0415\u043b \u041f\u043e\u0442\u0440\u0435\u0440\u043e"
    ],
    "name:swe_x_preferred":[
        "El Potrero"
    ],
    "name:und_x_variant":[
        "El Botrero"
    ],
    "wof:name":"El Potrero",
    "wof:placetype":"locality"
},
  "geometry": {"coordinates":[-71.78147,8.30405],"type":"Point"}
}