{
  "type": "Feature",
  "properties": {
    "iso:country":"VE",
    "qs:gn_pop":0,
    "qs:name":"San Cristobal",
    "qs:name_adm0":"Venezuela",
    "qs:name_adm1":"Anzoategui",
    "qs:photos":11,
    "qs:photos_1k":2,
    "qs:photos_9k":1,
    "qs:photos_9r":4,
    "qs:photos_all":242,
    "qs:photos_sr":1,
    "qs:placetype":"LocalAdmin",
    "qs:pop_sr":"0",
    "qs:woe_adm0":23424982,
    "wof:name":"San Cristobal",
    "wof:placetype":"localadmin"
},
  "geometry": {"coordinates":[-64.692001,10.133],"type":"Point"}
}