{
  "type": "Feature",
  "properties": {
    "gn:admin1_code":"05",
    "gn:asciiname":"La Rompia",
    "gn:country_code":"VE",
    "gn:dem":90,
    "gn:feature_class":"P",
    "gn:feature_code":"PPLL",
    "gn:name":"La Rompia",
    "gn:population":0,
    "gn:timezone":"America/Caracas",
    "iso:country":"VE",
    "wof:name":"La Rompia",
    "wof:placetype":"locality"
},
  "geometry": {"coordinates":[-69.53886,8.00307],"type":"Point"}
}