{
  "type": "Feature",
  "properties": {
    "gn:admin1_code":"19.0",
    "gn:asciiname":"Blanco Lugar",
    "gn:country_code":"VE",
    "gn:dem":318,
    "gn:feature_class":"P",
    "gn:feature_code":"PPL",
    "gn:name":"Blanco Lugar",
    "gn:population":0,
    "gn:timezone":"America/Caracas",
    "iso:country":"VE",
    "wof:name":"Blanco Lugar",
    "wof:placetype":"locality"
},
  "geometry": {"coordinates":[-63.36941,10.49912],"type":"Point"}
}