{
  "type": "Feature",
  "properties": {
    "gn:admin1_code":"11",
    "gn:asciiname":"Guanabano",
    "gn:country_code":"VE",
    "gn:dem":342,
    "gn:feature_class":"P",
    "gn:feature_code":"PPL",
    "gn:name":"Guan\u00e1bano",
    "gn:population":0,
    "gn:timezone":"America/Caracas",
    "iso:country":"VE",
    "wof:name":"Guanabano",
    "wof:placetype":"locality"
},
  "geometry": {"coordinates":[-70.68333,10.65],"type":"Point"}
}