{
  "type": "Feature",
  "properties": {
    "iso:country":"VE",
    "name:eng_x_preferred":[
        "Guanta"
    ],
    "name:epo_x_preferred":[
        "Guanta"
    ],
    "name:fra_x_preferred":[
        "Guanta"
    ],
    "name:nld_x_preferred":[
        "Guanta"
    ],
    "name:pol_x_preferred":[
        "Guanta"
    ],
    "name:por_x_preferred":[
        "Guanta"
    ],
    "name:rus_x_preferred":[
        "\u0413\u0443\u0430\u043d\u0442\u0430"
    ],
    "name:spa_x_preferred":[
        "Guanta"
    ],
    "name:zho_x_preferred":[
        "\u95dc\u5854"
    ],
    "qs:gn_country":"VE",
    "qs:gn_fcode":"PPL",
    "qs:gn_pop":0,
    "qs:name":"Guanta",
    "qs:name_adm0":"Venezuela",
    "qs:name_adm1":"Anzoategui",
    "qs:photos":25,
    "qs:photos_1k":5,
    "qs:photos_9k":1,
    "qs:photos_9r":1,
    "qs:photos_all":25,
    "qs:photos_sr":1,
    "qs:placetype":"Town",
    "qs:pop_sr":"0",
    "qs:woe_adm0":23424982,
    "wd:wordcount":72,
    "wof:name":"Guanta",
    "wof:placetype":"locality"
},
  "geometry": {"coordinates":[-65.09941000000001,9.65167],"type":"Point"}
}