{
  "type": "Feature",
  "properties": {
    "gn:admin1_code":"6.0",
    "gn:asciiname":"Puerto San Isidro",
    "gn:country_code":"VE",
    "gn:dem":20,
    "gn:feature_class":"P",
    "gn:feature_code":"PPL",
    "gn:name":"Puerto San Isidro",
    "gn:population":0,
    "gn:timezone":"America/Caracas",
    "iso:country":"VE",
    "wof:name":"Puerto San Isidro",
    "wof:placetype":"locality"
},
  "geometry": {"coordinates":[-65.21833000000001,7.53],"type":"Point"}
}