{
  "type": "Feature",
  "properties": {
    "gn:admin1_code":"19.0",
    "gn:asciiname":"Hondonada Cogollal",
    "gn:country_code":"VE",
    "gn:dem":492,
    "gn:feature_class":"P",
    "gn:feature_code":"PPLL",
    "gn:name":"Hondonada Cogollal",
    "gn:population":0,
    "gn:timezone":"America/Caracas",
    "iso:country":"VE",
    "wof:name":"Hondonada Cogollal",
    "wof:placetype":"locality"
},
  "geometry": {"coordinates":[-64.48765999999999,10.21027],"type":"Point"}
}