{
  "type": "Feature",
  "properties": {
    "gn:admin1_code":"8.0",
    "gn:asciiname":"Manire",
    "gn:cc2":"VE",
    "gn:country_code":"VE",
    "gn:dem":69,
    "gn:feature_class":"P",
    "gn:feature_code":"PPL",
    "gn:name":"Manire",
    "gn:population":0,
    "gn:timezone":"America/Caracas",
    "iso:country":"VE",
    "name:und_x_variant":[
        "El Manire",
        "Manire"
    ],
    "wof:name":"Manire",
    "wof:placetype":"locality"
},
  "geometry": {"coordinates":[-68.31667,8.92167],"type":"Point"}
}