{
  "type": "Feature",
  "properties": {
    "gn:admin1_code":"14",
    "gn:asciiname":"Los Barbechos",
    "gn:country_code":"VE",
    "gn:dem":2356,
    "gn:feature_class":"P",
    "gn:feature_code":"PPL",
    "gn:name":"Los Barbechos",
    "gn:population":0,
    "gn:timezone":"America/Caracas",
    "iso:country":"VE",
    "wof:name":"Los Barbechos",
    "wof:placetype":"locality"
},
  "geometry": {"coordinates":[-71.16611999999998,8.39826],"type":"Point"}
}