{
  "type": "Feature",
  "properties": {
    "gn:admin1_code":"21",
    "gn:asciiname":"La Cabrera",
    "gn:country_code":"VE",
    "gn:dem":2023,
    "gn:feature_class":"P",
    "gn:feature_code":"PPL",
    "gn:name":"La Cabrera",
    "gn:population":0,
    "gn:timezone":"America/Caracas",
    "iso:country":"VE",
    "wof:name":"La Cabrera",
    "wof:placetype":"locality"
},
  "geometry": {"coordinates":[-70.67463000000002,9.05694],"type":"Point"}
}