{
  "type": "Feature",
  "properties": {
    "gn:admin1_code":"2",
    "gn:asciiname":"Mahomal",
    "gn:cc2":"VE",
    "gn:country_code":"VE",
    "gn:dem":105,
    "gn:feature_class":"P",
    "gn:feature_code":"PPL",
    "gn:name":"Mahomal",
    "gn:population":0,
    "gn:timezone":"America/Caracas",
    "iso:country":"VE",
    "name:und_x_variant":[
        "Majomal",
        "Mahomal"
    ],
    "wof:name":"Mahomal",
    "wof:placetype":"locality"
},
  "geometry": {"coordinates":[-64.93333,9.13333],"type":"Point"}
}