{
  "type": "Feature",
  "properties": {
    "gn:admin1_code":"2",
    "gn:asciiname":"Cruz de Topocual",
    "gn:country_code":"VE",
    "gn:dem":102,
    "gn:feature_class":"P",
    "gn:feature_code":"PPL",
    "gn:name":"Cruz de Topocual",
    "gn:population":0,
    "gn:timezone":"America/Caracas",
    "iso:country":"VE",
    "wof:name":"Cruz de Topocual",
    "wof:placetype":"locality"
},
  "geometry": {"coordinates":[-64.90675999999999,9.90282],"type":"Point"}
}