{
  "type": "Feature",
  "properties": {
    "gn:admin1_code":"11",
    "gn:asciiname":"Sarinao",
    "gn:country_code":"VE",
    "gn:dem":26,
    "gn:feature_class":"P",
    "gn:feature_code":"PPL",
    "gn:name":"Sarinao",
    "gn:population":0,
    "gn:timezone":"America/Caracas",
    "iso:country":"VE",
    "wof:name":"Sarinao",
    "wof:placetype":"locality"
},
  "geometry": {"coordinates":[-70.07980000000001,11.74232],"type":"Point"}
}