{
  "type": "Feature",
  "properties": {
    "gn:admin1_code":"5",
    "gn:asciiname":"El Cambur",
    "gn:country_code":"VE",
    "gn:dem":236,
    "gn:feature_class":"P",
    "gn:feature_code":"PPL",
    "gn:name":"El Cambur",
    "gn:population":0,
    "gn:timezone":"America/Caracas",
    "iso:country":"VE",
    "wof:name":"El Cambur",
    "wof:placetype":"locality"
},
  "geometry": {"coordinates":[-71.11083000000001,7.88823],"type":"Point"}
}