{
  "type": "Feature",
  "properties": {
    "gn:admin1_code":"23",
    "gn:asciiname":"Porguera",
    "gn:cc2":"VE",
    "gn:country_code":"VE",
    "gn:dem":-9999,
    "gn:feature_class":"P",
    "gn:feature_code":"PPL",
    "gn:name":"Porguera",
    "gn:population":0,
    "gn:timezone":"America/Caracas",
    "iso:country":"VE",
    "name:und_x_variant":[
        "Porquera",
        "Porguera"
    ],
    "wof:name":"Porguera",
    "wof:placetype":"locality"
},
  "geometry": {"coordinates":[-71.71666999999999,10.38333],"type":"Point"}
}