{
  "type": "Feature",
  "properties": {
    "gn:admin1_code":"05",
    "gn:asciiname":"La Gloria",
    "gn:country_code":"VE",
    "gn:dem":116,
    "gn:feature_class":"P",
    "gn:feature_code":"PPLL",
    "gn:name":"La Gloria",
    "gn:population":0,
    "gn:timezone":"America/Caracas",
    "iso:country":"VE",
    "name:ast_x_preferred":[
        "La Gloria"
    ],
    "name:ceb_x_preferred":[
        "La Gloria"
    ],
    "name:deu_x_preferred":[
        "La Gloria"
    ],
    "name:ita_x_preferred":[
        "La Gloria"
    ],
    "name:nld_x_preferred":[
        "La Gloria"
    ],
    "name:spa_x_preferred":[
        "La Gloria"
    ],
    "name:swe_x_preferred":[
        "La Gloria"
    ],
    "name:vie_x_preferred":[
        "La Gloria"
    ],
    "wof:name":"La Gloria",
    "wof:placetype":"locality"
},
  "geometry": {"coordinates":[-69.82696999999999,8.35735],"type":"Point"}
}