{
  "type": "Feature",
  "properties": {
    "gn:admin1_code":"02",
    "gn:asciiname":"El Rincon",
    "gn:country_code":"VE",
    "gn:dem":130,
    "gn:feature_class":"P",
    "gn:feature_code":"PPL",
    "gn:name":"El Rinc\u00f3n",
    "gn:population":0,
    "gn:timezone":"America/Caracas",
    "iso:country":"VE",
    "wof:name":"El Rincon",
    "wof:placetype":"locality"
},
  "geometry": {"coordinates":[-65.02276999999999,9.96889],"type":"Point"}
}