{
  "type": "Feature",
  "properties": {
    "gn:admin1_code":"2",
    "gn:asciiname":"Moriche Solo",
    "gn:country_code":"VE",
    "gn:dem":257,
    "gn:feature_class":"P",
    "gn:feature_code":"PPL",
    "gn:name":"Moriche Solo",
    "gn:population":0,
    "gn:timezone":"America/Caracas",
    "iso:country":"VE",
    "wof:name":"Moriche Solo",
    "wof:placetype":"locality"
},
  "geometry": {"coordinates":[-64.51666999999999,9.16667],"type":"Point"}
}