{
  "type": "Feature",
  "properties": {
    "gn:admin1_code":"12.0",
    "gn:asciiname":"Castillito",
    "gn:country_code":"VE",
    "gn:dem":33,
    "gn:feature_class":"P",
    "gn:feature_code":"PPLL",
    "gn:name":"Castillito",
    "gn:population":0,
    "gn:timezone":"America/Caracas",
    "iso:country":"VE",
    "wof:name":"Castillito",
    "wof:placetype":"locality"
},
  "geometry": {"coordinates":[-66.47389,7.76056],"type":"Point"}
}