{
  "type": "Feature",
  "properties": {
    "gn:admin1_code":"13",
    "gn:asciiname":"Las Mulas",
    "gn:country_code":"VE",
    "gn:dem":629,
    "gn:feature_class":"P",
    "gn:feature_code":"PPL",
    "gn:name":"Las Mulas",
    "gn:population":0,
    "gn:timezone":"America/Caracas",
    "iso:country":"VE",
    "wof:name":"Las Mulas",
    "wof:placetype":"locality"
},
  "geometry": {"coordinates":[-69.42610999999999,10.30205],"type":"Point"}
}