{
  "type": "Feature",
  "properties": {
    "gn:admin1_code":"12.0",
    "gn:asciiname":"Pueblo Nuevo",
    "gn:country_code":"VE",
    "gn:dem":122,
    "gn:feature_class":"P",
    "gn:feature_code":"PPLL",
    "gn:name":"Pueblo Nuevo",
    "gn:population":0,
    "gn:timezone":"America/Caracas",
    "iso:country":"VE",
    "wof:name":"Pueblo Nuevo",
    "wof:placetype":"locality"
},
  "geometry": {"coordinates":[-65.54833000000001,8.59556],"type":"Point"}
}