{
  "type": "Feature",
  "properties": {
    "gn:admin1_code":"4.0",
    "gn:asciiname":"Carutico",
    "gn:country_code":"VE",
    "gn:dem":813,
    "gn:feature_class":"P",
    "gn:feature_code":"PPL",
    "gn:name":"Carutico",
    "gn:population":0,
    "gn:timezone":"America/Caracas",
    "iso:country":"VE",
    "wof:name":"Carutico",
    "wof:placetype":"locality"
},
  "geometry": {"coordinates":[-67.02248,10.02615],"type":"Point"}
}