{
  "type": "Feature",
  "properties": {
    "gn:admin1_code":"05",
    "gn:asciiname":"El Canito",
    "gn:country_code":"VE",
    "gn:dem":852,
    "gn:feature_class":"P",
    "gn:feature_code":"PPL",
    "gn:name":"El Ca\u00f1ito",
    "gn:population":0,
    "gn:timezone":"America/Caracas",
    "iso:country":"VE",
    "wof:name":"El Canito",
    "wof:placetype":"locality"
},
  "geometry": {"coordinates":[-70.50381999999998,8.83153],"type":"Point"}
}