{
  "type": "Feature",
  "properties": {
    "gn:admin1_code":"23",
    "gn:asciiname":"Pedregalito",
    "gn:country_code":"VE",
    "gn:dem":9,
    "gn:feature_class":"P",
    "gn:feature_code":"PPL",
    "gn:name":"Pedregalito",
    "gn:population":0,
    "gn:timezone":"America/Caracas",
    "iso:country":"VE",
    "name:und_x_variant":[
        "Pedregal",
        "Pedregalito"
    ],
    "wof:name":"Pedregalito",
    "wof:placetype":"locality"
},
  "geometry": {"coordinates":[-71.40246999999999,10.36388],"type":"Point"}
}