{
  "type": "Feature",
  "properties": {
    "gn:admin1_code":"19.0",
    "gn:asciiname":"Manacal",
    "gn:country_code":"VE",
    "gn:dem":345,
    "gn:feature_class":"P",
    "gn:feature_code":"PPL",
    "gn:name":"Manacal",
    "gn:population":0,
    "gn:timezone":"America/Caracas",
    "iso:country":"VE",
    "wof:name":"Manacal",
    "wof:placetype":"locality"
},
  "geometry": {"coordinates":[-63.04367,10.61706],"type":"Point"}
}