{
  "type": "Feature",
  "properties": {
    "gn:admin1_code":"11.0",
    "gn:asciiname":"El Curari",
    "gn:country_code":"VE",
    "gn:dem":83,
    "gn:feature_class":"P",
    "gn:feature_code":"PPL",
    "gn:name":"El Curari",
    "gn:population":0,
    "gn:timezone":"America/Caracas",
    "iso:country":"VE",
    "wof:name":"El Curari",
    "wof:placetype":"locality"
},
  "geometry": {"coordinates":[-70.34222,11.17722],"type":"Point"}
}