{
  "type": "Feature",
  "properties": {
    "gn:admin1_code":"5",
    "gn:admin2_code":"611.0",
    "gn:admin3_code":"61101.0",
    "gn:asciiname":"Ciudad De Nutrias",
    "gn:country_code":"VE",
    "gn:dem":84,
    "gn:feature_class":"P",
    "gn:feature_code":"PPLA3",
    "gn:name":"Ciudad De Nutrias",
    "gn:population":0,
    "gn:timezone":"America/Caracas",
    "iso:country":"VE",
    "name:und_x_variant":[
        "Nutrias",
        "Ciudad De Nutrias"
    ],
    "wof:name":"Ciudad De Nutrias",
    "wof:placetype":"locality"
},
  "geometry": {"coordinates":[-69.30798,8.09535],"type":"Point"}
}