{
  "type": "Feature",
  "properties": {
    "gn:admin1_code":"19.0",
    "gn:asciiname":"Mauraquito",
    "gn:country_code":"VE",
    "gn:dem":149,
    "gn:feature_class":"P",
    "gn:feature_code":"PPL",
    "gn:name":"Mauraquito",
    "gn:population":0,
    "gn:timezone":"America/Caracas",
    "iso:country":"VE",
    "wof:name":"Mauraquito",
    "wof:placetype":"locality"
},
  "geometry": {"coordinates":[-63.12079,10.64696],"type":"Point"}
}