{
  "type": "Feature",
  "properties": {
    "gn:admin1_code":"15",
    "gn:asciiname":"El Trabajo",
    "gn:country_code":"VE",
    "gn:dem":107,
    "gn:feature_class":"P",
    "gn:feature_code":"PPL",
    "gn:name":"El Trabajo",
    "gn:population":0,
    "gn:timezone":"America/Caracas",
    "iso:country":"VE",
    "wof:name":"El Trabajo",
    "wof:placetype":"locality"
},
  "geometry": {"coordinates":[-66.47051999999999,10.25665],"type":"Point"}
}