{
  "type": "Feature",
  "properties": {
    "gn:admin1_code":"20.0",
    "gn:asciiname":"Agua Fria",
    "gn:country_code":"VE",
    "gn:dem":348,
    "gn:feature_class":"P",
    "gn:feature_code":"PPLL",
    "gn:name":"Agua Fr\u00eda",
    "gn:population":0,
    "gn:timezone":"America/Caracas",
    "iso:country":"VE",
    "wof:name":"Agua Fria",
    "wof:placetype":"locality"
},
  "geometry": {"coordinates":[-71.63076,7.76097],"type":"Point"}
}