{
  "type": "Feature",
  "properties": {
    "gn:admin1_code":"13",
    "gn:asciiname":"La Rinconada",
    "gn:country_code":"VE",
    "gn:dem":273,
    "gn:feature_class":"P",
    "gn:feature_code":"PPLL",
    "gn:name":"La Rinconada",
    "gn:population":0,
    "gn:timezone":"America/Caracas",
    "iso:country":"VE",
    "wof:name":"La Rinconada",
    "wof:placetype":"locality"
},
  "geometry": {"coordinates":[-69.68562,10.5574],"type":"Point"}
}