{
  "type": "Feature",
  "properties": {
    "gn:admin1_code":"6.0",
    "gn:asciiname":"La Naranjita",
    "gn:country_code":"VE",
    "gn:dem":246,
    "gn:feature_class":"P",
    "gn:feature_code":"PPL",
    "gn:name":"La Naranjita",
    "gn:population":0,
    "gn:timezone":"America/Caracas",
    "iso:country":"VE",
    "wof:name":"La Naranjita",
    "wof:placetype":"locality"
},
  "geometry": {"coordinates":[-63.18722,7.625],"type":"Point"}
}