{
  "type": "Feature",
  "properties": {
    "gn:admin1_code":"4",
    "gn:asciiname":"Polvorin",
    "gn:country_code":"VE",
    "gn:dem":613,
    "gn:feature_class":"P",
    "gn:feature_code":"PPL",
    "gn:name":"Polvor\u00edn",
    "gn:population":0,
    "gn:timezone":"America/Caracas",
    "iso:country":"VE",
    "wof:name":"Polvorin",
    "wof:placetype":"locality"
},
  "geometry": {"coordinates":[-67.47335,10.29663],"type":"Point"}
}