{
  "type": "Feature",
  "properties": {
    "gn:admin1_code":"17",
    "gn:asciiname":"La Pared",
    "gn:country_code":"VE",
    "gn:dem":22,
    "gn:feature_class":"P",
    "gn:feature_code":"PPL",
    "gn:name":"La Pared",
    "gn:population":0,
    "gn:timezone":"America/Caracas",
    "iso:country":"VE",
    "wof:name":"La Pared",
    "wof:placetype":"locality"
},
  "geometry": {"coordinates":[-64.30722,11.06333],"type":"Point"}
}