{
  "type": "Feature",
  "properties": {
    "gn:admin1_code":"5",
    "gn:asciiname":"La Recta",
    "gn:country_code":"VE",
    "gn:dem":492,
    "gn:feature_class":"P",
    "gn:feature_code":"PPL",
    "gn:name":"La Recta",
    "gn:population":0,
    "gn:timezone":"America/Caracas",
    "iso:country":"VE",
    "wof:name":"La Recta",
    "wof:placetype":"locality"
},
  "geometry": {"coordinates":[-70.40000000000001,8.75],"type":"Point"}
}