{
  "type": "Feature",
  "properties": {
    "gn:admin1_code":"19.0",
    "gn:asciiname":"Quebrada de la Nina",
    "gn:country_code":"VE",
    "gn:dem":24,
    "gn:feature_class":"P",
    "gn:feature_code":"PPL",
    "gn:name":"Quebrada de la Ni\u00f1a",
    "gn:population":0,
    "gn:timezone":"America/Caracas",
    "iso:country":"VE",
    "wof:name":"Quebrada de la Nina",
    "wof:placetype":"locality"
},
  "geometry": {"coordinates":[-62.79336,10.60413],"type":"Point"}
}