{
  "type": "Feature",
  "properties": {
    "gn:admin1_code":"11",
    "gn:asciiname":"La Vigia",
    "gn:country_code":"VE",
    "gn:dem":52,
    "gn:feature_class":"P",
    "gn:feature_code":"PPL",
    "gn:name":"La Vig\u00eda",
    "gn:population":0,
    "gn:timezone":"America/Caracas",
    "iso:country":"VE",
    "name:und_x_variant":[
        "La Vij\u00eda",
        "La Villa",
        "La Vig\u00eda"
    ],
    "wof:name":"La Vigia",
    "wof:placetype":"locality"
},
  "geometry": {"coordinates":[-68.58888,11.22921],"type":"Point"}
}