{
  "type": "Feature",
  "properties": {
    "iso:country":"VE",
    "name:ast_x_preferred":[
        "Higuerote"
    ],
    "name:ceb_x_preferred":[
        "Higuerote"
    ],
    "name:deu_x_preferred":[
        "Higuerote"
    ],
    "name:eng_x_preferred":[
        "Higuerote"
    ],
    "name:fas_x_preferred":[
        "\u0647\u06cc\u06af\u0648\u0631\u0648\u062a\u06cc"
    ],
    "name:fra_x_preferred":[
        "Higuerote"
    ],
    "name:ita_x_preferred":[
        "Higuerote"
    ],
    "name:jpn_x_preferred":[
        "\u30a4\u30b2\u30ed\u30fc\u30c6"
    ],
    "name:kor_x_preferred":[
        "\uc774\uac8c\ub85c\ud14c"
    ],
    "name:nld_x_preferred":[
        "Higuerote"
    ],
    "name:pol_x_preferred":[
        "Higuerote"
    ],
    "name:por_x_preferred":[
        "Higuerote"
    ],
    "name:spa_x_preferred":[
        "Higuerote"
    ],
    "name:ukr_x_preferred":[
        "\u0406\u0433\u0435\u0440\u043e\u0442\u0435"
    ],
    "name:zho_x_preferred":[
        "\u4f0a\u683c\u7f85\u7279"
    ],
    "qs:gn_country":"VE",
    "qs:gn_fcode":"PPL",
    "qs:gn_pop":0,
    "qs:name":"Higuerote",
    "qs:name_adm0":"Venezuela",
    "qs:name_adm1":"Miranda",
    "qs:photos":330,
    "qs:photos_1k":67,
    "qs:photos_9k":1,
    "qs:photos_9r":5,
    "qs:photos_all":330,
    "qs:photos_sr":5,
    "qs:placetype":"Town",
    "qs:pop_sr":"0",
    "qs:woe_adm0":23424982,
    "wd:wordcount":46,
    "wof:name":"Higuerote",
    "wof:placetype":"locality"
},
  "geometry": {"coordinates":[-66.53333000000001,10.0],"type":"Point"}
}