{
  "type": "Feature",
  "properties": {
    "gn:admin1_code":"21",
    "gn:asciiname":"Los Ranchos",
    "gn:country_code":"VE",
    "gn:dem":1246,
    "gn:feature_class":"P",
    "gn:feature_code":"PPL",
    "gn:name":"Los Ranchos",
    "gn:population":0,
    "gn:timezone":"America/Caracas",
    "iso:country":"VE",
    "name:ceb_x_preferred":[
        "Los Ranchos"
    ],
    "name:swe_x_preferred":[
        "Los Ranchos"
    ],
    "wof:name":"Los Ranchos",
    "wof:placetype":"locality"
},
  "geometry": {"coordinates":[-70.72664,9.26161],"type":"Point"}
}