{
  "type": "Feature",
  "properties": {
    "gn:admin1_code":"23.0",
    "gn:asciiname":"Cerro Verde",
    "gn:country_code":"VE",
    "gn:dem":998,
    "gn:feature_class":"P",
    "gn:feature_code":"PPL",
    "gn:name":"Cerro Verde",
    "gn:population":0,
    "gn:timezone":"America/Caracas",
    "iso:country":"VE",
    "name:spa_x_preferred":[
        "Sociedad Minera Cerro Verde"
    ],
    "wof:name":"Cerro Verde",
    "wof:placetype":"locality"
},
  "geometry": {"coordinates":[-70.68055,10.04211],"type":"Point"}
}