{
  "type": "Feature",
  "properties": {
    "gn:admin1_code":"3",
    "gn:asciiname":"La Ceiba",
    "gn:country_code":"VE",
    "gn:dem":103,
    "gn:feature_class":"P",
    "gn:feature_code":"PPL",
    "gn:name":"La Ceiba",
    "gn:population":0,
    "gn:timezone":"America/Caracas",
    "iso:country":"VE",
    "wof:name":"La Ceiba",
    "wof:placetype":"locality"
},
  "geometry": {"coordinates":[-70.01456,6.91725],"type":"Point"}
}