{
  "type": "Feature",
  "properties": {
    "gn:admin1_code":"12",
    "gn:asciiname":"Tamarindito",
    "gn:country_code":"VE",
    "gn:dem":75,
    "gn:feature_class":"P",
    "gn:feature_code":"PPL",
    "gn:name":"Tamarindito",
    "gn:population":0,
    "gn:timezone":"America/Caracas",
    "iso:country":"VE",
    "name:ceb_x_preferred":[
        "Tamarindito"
    ],
    "name:fra_x_preferred":[
        "Tamarindito"
    ],
    "name:ita_x_preferred":[
        "Tamarindito"
    ],
    "name:spa_x_preferred":[
        "Tamarindito"
    ],
    "name:swe_x_preferred":[
        "Tamarindito"
    ],
    "name:ukr_x_preferred":[
        "\u0422\u0430\u043c\u0430\u0440\u0456\u043d\u0434\u0456\u0442\u043e"
    ],
    "wof:name":"Tamarindito",
    "wof:placetype":"locality"
},
  "geometry": {"coordinates":[-67.53333000000001,8.66667],"type":"Point"}
}