{
  "type": "Feature",
  "properties": {
    "gn:admin1_code":"8",
    "gn:asciiname":"Felipero",
    "gn:country_code":"VE",
    "gn:dem":89,
    "gn:feature_class":"P",
    "gn:feature_code":"PPL",
    "gn:name":"Felipero",
    "gn:population":0,
    "gn:timezone":"America/Caracas",
    "iso:country":"VE",
    "wof:name":"Felipero",
    "wof:placetype":"locality"
},
  "geometry": {"coordinates":[-68.53333000000001,9.35],"type":"Point"}
}