{
  "type": "Feature",
  "properties": {
    "gn:admin1_code":"6",
    "gn:asciiname":"Curatabaca",
    "gn:cc2":"VE",
    "gn:country_code":"VE",
    "gn:dem":457,
    "gn:feature_class":"P",
    "gn:feature_code":"PPL",
    "gn:name":"Curatabaca",
    "gn:population":0,
    "gn:timezone":"America/Caracas",
    "iso:country":"VE",
    "name:und_x_variant":[
        "Caratubaca",
        "Curatabaca"
    ],
    "wof:name":"Curatabaca",
    "wof:placetype":"locality"
},
  "geometry": {"coordinates":[-62.85,6.31667],"type":"Point"}
}