{
  "type": "Feature",
  "properties": {
    "gn:admin1_code":"3",
    "gn:asciiname":"Bucaral",
    "gn:country_code":"VE",
    "gn:dem":48,
    "gn:feature_class":"P",
    "gn:feature_code":"PPL",
    "gn:name":"Bucaral",
    "gn:population":0,
    "gn:timezone":"America/Caracas",
    "iso:country":"VE",
    "wof:name":"Bucaral",
    "wof:placetype":"locality"
},
  "geometry": {"coordinates":[-67.47471999999999,7.58222],"type":"Point"}
}