{
  "type": "Feature",
  "properties": {
    "gn:admin1_code":"23",
    "gn:asciiname":"El Menito",
    "gn:country_code":"VE",
    "gn:dem":79,
    "gn:feature_class":"P",
    "gn:feature_code":"PPL",
    "gn:name":"El Menito",
    "gn:population":0,
    "gn:timezone":"America/Caracas",
    "iso:country":"VE",
    "wof:name":"El Menito",
    "wof:placetype":"locality"
},
  "geometry": {"coordinates":[-70.91667,9.86667],"type":"Point"}
}