{
  "type": "Feature",
  "properties": {
    "gn:admin1_code":"19.0",
    "gn:asciiname":"La Soledad",
    "gn:country_code":"VE",
    "gn:dem":325,
    "gn:feature_class":"P",
    "gn:feature_code":"PPL",
    "gn:name":"La Soledad",
    "gn:population":0,
    "gn:timezone":"America/Caracas",
    "iso:country":"VE",
    "wof:name":"La Soledad",
    "wof:placetype":"locality"
},
  "geometry": {"coordinates":[-63.22919,10.56269],"type":"Point"}
}