{
  "type": "Feature",
  "properties": {
    "gn:admin1_code":"8.0",
    "gn:asciiname":"El Urape",
    "gn:country_code":"VE",
    "gn:dem":74,
    "gn:feature_class":"P",
    "gn:feature_code":"PPL",
    "gn:name":"El Urape",
    "gn:population":0,
    "gn:timezone":"America/Caracas",
    "iso:country":"VE",
    "wof:name":"El Urape",
    "wof:placetype":"locality"
},
  "geometry": {"coordinates":[-68.50649,8.71673],"type":"Point"}
}