{
  "type": "Feature",
  "properties": {
    "gn:admin1_code":"15",
    "gn:asciiname":"Aniaguita",
    "gn:country_code":"VE",
    "gn:dem":546,
    "gn:feature_class":"P",
    "gn:feature_code":"PPL",
    "gn:name":"Aniag\u00fcita",
    "gn:population":0,
    "gn:timezone":"America/Caracas",
    "iso:country":"VE",
    "wof:name":"Aniaguita",
    "wof:placetype":"locality"
},
  "geometry": {"coordinates":[-66.97081999999999,10.09463],"type":"Point"}
}