{
  "type": "Feature",
  "properties": {
    "gn:admin1_code":"20.0",
    "gn:asciiname":"Las Tienditas",
    "gn:country_code":"VE",
    "gn:dem":354,
    "gn:feature_class":"P",
    "gn:feature_code":"PPL",
    "gn:name":"Las Tienditas",
    "gn:population":0,
    "gn:timezone":"America/Caracas",
    "iso:country":"VE",
    "wof:name":"Las Tienditas",
    "wof:placetype":"locality"
},
  "geometry": {"coordinates":[-72.44358000000003,7.88679],"type":"Point"}
}