{
  "type": "Feature",
  "properties": {
    "gn:admin1_code":"02",
    "gn:asciiname":"Uverito",
    "gn:country_code":"VE",
    "gn:dem":143,
    "gn:feature_class":"P",
    "gn:feature_code":"PPL",
    "gn:name":"Uverito",
    "gn:population":0,
    "gn:timezone":"America/Caracas",
    "iso:country":"VE",
    "name:und_x_variant":[
        "Uberito",
        "Uverito"
    ],
    "wof:name":"Uverito",
    "wof:placetype":"locality"
},
  "geometry": {"coordinates":[-64.68871,8.11228],"type":"Point"}
}