{
  "type": "Feature",
  "properties": {
    "gn:admin1_code":"11",
    "gn:asciiname":"Curarima",
    "gn:cc2":"VE",
    "gn:country_code":"VE",
    "gn:dem":366,
    "gn:feature_class":"P",
    "gn:feature_code":"PPL",
    "gn:name":"Curarima",
    "gn:population":0,
    "gn:timezone":"America/Caracas",
    "iso:country":"VE",
    "name:und_x_variant":[
        "Curas\u00edma",
        "Curairima",
        "Curarima"
    ],
    "wof:name":"Curarima",
    "wof:placetype":"locality"
},
  "geometry": {"coordinates":[-69.61667,11.08333],"type":"Point"}
}