{
  "type": "Feature",
  "properties": {
    "gn:admin1_code":"13",
    "gn:asciiname":"Terepaima",
    "gn:country_code":"VE",
    "gn:dem":1219,
    "gn:feature_class":"P",
    "gn:feature_code":"PPL",
    "gn:name":"Terepaima",
    "gn:population":0,
    "gn:timezone":"America/Caracas",
    "iso:country":"VE",
    "wof:name":"Terepaima",
    "wof:placetype":"locality"
},
  "geometry": {"coordinates":[-69.28006999999999,9.95114],"type":"Point"}
}