{
  "type": "Feature",
  "properties": {
    "gn:admin1_code":"11.0",
    "gn:asciiname":"La Esperanza",
    "gn:country_code":"VE",
    "gn:dem":442,
    "gn:feature_class":"P",
    "gn:feature_code":"PPLL",
    "gn:name":"La Esperanza",
    "gn:population":0,
    "gn:timezone":"America/Caracas",
    "iso:country":"VE",
    "wof:name":"La Esperanza",
    "wof:placetype":"locality"
},
  "geometry": {"coordinates":[-70.61688000000002,10.59833],"type":"Point"}
}