{
  "type": "Feature",
  "properties": {
    "gn:admin1_code":"20",
    "gn:asciiname":"San Pedro del Rio",
    "gn:country_code":"VE",
    "gn:dem":795,
    "gn:feature_class":"P",
    "gn:feature_code":"PPL",
    "gn:name":"San Pedro del R\u00edo",
    "gn:population":0,
    "gn:timezone":"America/Caracas",
    "iso:country":"VE",
    "name:und_x_variant":[
        "San Pedro",
        "San Pedro del R\u00edo"
    ],
    "wof:name":"San Pedro del Rio",
    "wof:placetype":"locality"
},
  "geometry": {"coordinates":[-72.27373,7.99341],"type":"Point"}
}