{
  "type": "Feature",
  "properties": {
    "gn:admin1_code":"02",
    "gn:asciiname":"Las Raices",
    "gn:country_code":"VE",
    "gn:dem":68,
    "gn:feature_class":"P",
    "gn:feature_code":"PPLL",
    "gn:name":"Las Raices",
    "gn:population":0,
    "gn:timezone":"America/Caracas",
    "iso:country":"VE",
    "wof:name":"Las Raices",
    "wof:placetype":"locality"
},
  "geometry": {"coordinates":[-64.08344,8.05304],"type":"Point"}
}