{
  "type": "Feature",
  "properties": {
    "gn:admin1_code":"1.0",
    "gn:asciiname":"Punimabuiteri",
    "gn:country_code":"VE",
    "gn:dem":675,
    "gn:feature_class":"P",
    "gn:feature_code":"PPL",
    "gn:name":"Punimabuiteri",
    "gn:population":0,
    "gn:timezone":"America/Caracas",
    "iso:country":"VE",
    "wof:name":"Punimabuiteri",
    "wof:placetype":"locality"
},
  "geometry": {"coordinates":[-64.64825999999999,2.01576],"type":"Point"}
}