{
  "type": "Feature",
  "properties": {
    "gn:admin1_code":"11",
    "gn:asciiname":"Taguaqui",
    "gn:country_code":"VE",
    "gn:dem":61,
    "gn:feature_class":"P",
    "gn:feature_code":"PPL",
    "gn:name":"Taguaqui",
    "gn:population":0,
    "gn:timezone":"America/Caracas",
    "iso:country":"VE",
    "wof:name":"Taguaqui",
    "wof:placetype":"locality"
},
  "geometry": {"coordinates":[-69.16261,11.38163],"type":"Point"}
}