{
  "type": "Feature",
  "properties": {
    "gn:gn_country":"VE",
    "iso:country":"VE",
    "qs_pg:aaroncc":"VE",
    "qs_pg:gn_country":"VE",
    "qs_pg:name":"G. Francisco Antonio Vasquez",
    "qs_pg:name_adm0":"Venezuela",
    "qs_pg:name_adm1":"Sucre",
    "qs_pg:photos":3,
    "qs_pg:photos_1k":1,
    "qs_pg:photos_9k":1,
    "qs_pg:photos_9r":1,
    "qs_pg:photos_all":3,
    "qs_pg:photos_sr":1,
    "qs_pg:pop_sr":0,
    "qs_pg:qs_pg_placetype":"localadmin",
    "qs_pg:qs_pg_placetype_gp":"LocalAdmin",
    "qs_pg:woe_adm0":23424982,
    "woe:adm0_id":23424982,
    "woe:name_adm0":"Venezuela",
    "woe:name_adm1":"Sucre",
    "woe:placetype":"LocalAdmin",
    "wof:name":"G. Francisco Antonio Vasquez",
    "wof:placetype":"localadmin"
},
  "geometry": {"coordinates":[-63.900947,10.48798],"type":"Point"}
}