{
  "type": "Feature",
  "properties": {
    "gn:admin1_code":"22",
    "gn:asciiname":"El Mango",
    "gn:country_code":"VE",
    "gn:dem":244,
    "gn:feature_class":"P",
    "gn:feature_code":"PPL",
    "gn:name":"El Mango",
    "gn:population":0,
    "gn:timezone":"America/Caracas",
    "iso:country":"VE",
    "wof:name":"El Mango",
    "wof:placetype":"locality"
},
  "geometry": {"coordinates":[-68.84999999999999,10.16667],"type":"Point"}
}