{
  "type": "Feature",
  "properties": {
    "gn:admin1_code":"13",
    "gn:asciiname":"Cerro Colorado",
    "gn:country_code":"VE",
    "gn:dem":434,
    "gn:feature_class":"P",
    "gn:feature_code":"PPLL",
    "gn:name":"Cerro Colorado",
    "gn:population":0,
    "gn:timezone":"America/Caracas",
    "iso:country":"VE",
    "wof:name":"Cerro Colorado",
    "wof:placetype":"locality"
},
  "geometry": {"coordinates":[-69.83216999999999,10.38925],"type":"Point"}
}