{
  "type": "Feature",
  "properties": {
    "gn:admin1_code":"12.0",
    "gn:asciiname":"Tarrayero",
    "gn:country_code":"VE",
    "gn:dem":21,
    "gn:feature_class":"P",
    "gn:feature_code":"PPL",
    "gn:name":"Tarrayero",
    "gn:population":0,
    "gn:timezone":"America/Caracas",
    "iso:country":"VE",
    "wof:name":"Tarrayero",
    "wof:placetype":"locality"
},
  "geometry": {"coordinates":[-66.02815,7.6971],"type":"Point"}
}