{
  "type": "Feature",
  "properties": {
    "gn:admin1_code":"13.0",
    "gn:asciiname":"Pueblo Nuevo",
    "gn:country_code":"VE",
    "gn:dem":623,
    "gn:feature_class":"P",
    "gn:feature_code":"PPL",
    "gn:name":"Pueblo Nuevo",
    "gn:population":0,
    "gn:timezone":"America/Caracas",
    "iso:country":"VE",
    "wof:name":"Pueblo Nuevo",
    "wof:placetype":"locality"
},
  "geometry": {"coordinates":[-69.36861,10.04399],"type":"Point"}
}