{
  "type": "Feature",
  "properties": {
    "gn:admin1_code":"12",
    "gn:asciiname":"El Machete",
    "gn:country_code":"VE",
    "gn:dem":152,
    "gn:feature_class":"P",
    "gn:feature_code":"PPL",
    "gn:name":"El Machete",
    "gn:population":0,
    "gn:timezone":"America/Caracas",
    "iso:country":"VE",
    "wof:name":"El Machete",
    "wof:placetype":"locality"
},
  "geometry": {"coordinates":[-66.48298,8.57373],"type":"Point"}
}