{
  "type": "Feature",
  "properties": {
    "gn:admin1_code":"23",
    "gn:asciiname":"El Japon",
    "gn:country_code":"VE",
    "gn:dem":112,
    "gn:feature_class":"P",
    "gn:feature_code":"PPL",
    "gn:name":"El Jap\u00f3n",
    "gn:population":0,
    "gn:timezone":"America/Caracas",
    "iso:country":"VE",
    "wof:name":"El Japon",
    "wof:placetype":"locality"
},
  "geometry": {"coordinates":[-72.20699999999999,11.15469],"type":"Point"}
}