{
  "type": "Feature",
  "properties": {
    "gn:admin1_code":"11.0",
    "gn:asciiname":"Codore de la Playa",
    "gn:country_code":"VE",
    "gn:dem":6,
    "gn:feature_class":"P",
    "gn:feature_code":"PPL",
    "gn:name":"Codore de la Playa",
    "gn:population":0,
    "gn:timezone":"America/Caracas",
    "iso:country":"VE",
    "wof:name":"Codore de la Playa",
    "wof:placetype":"locality"
},
  "geometry": {"coordinates":[-70.24095,11.33839],"type":"Point"}
}