{
  "type": "Feature",
  "properties": {
    "gn:admin1_code":"21",
    "gn:asciiname":"Timbis",
    "gn:country_code":"VE",
    "gn:dem":1875,
    "gn:feature_class":"P",
    "gn:feature_code":"PPL",
    "gn:name":"Timbis",
    "gn:population":0,
    "gn:timezone":"America/Caracas",
    "iso:country":"VE",
    "wof:name":"Timbis",
    "wof:placetype":"locality"
},
  "geometry": {"coordinates":[-70.57301,9.17889],"type":"Point"}
}