{
  "type": "Feature",
  "properties": {
    "gn:admin1_code":"4",
    "gn:asciiname":"La Playa",
    "gn:country_code":"VE",
    "gn:dem":122,
    "gn:feature_class":"P",
    "gn:feature_code":"PPL",
    "gn:name":"La Playa",
    "gn:population":0,
    "gn:timezone":"America/Caracas",
    "iso:country":"VE",
    "name:ceb_x_preferred":[
        "La Playa"
    ],
    "name:fra_x_preferred":[
        "La Playa"
    ],
    "name:nld_x_preferred":[
        "La Playa"
    ],
    "name:spa_x_preferred":[
        "La Playa"
    ],
    "name:swe_x_preferred":[
        "La Playa"
    ],
    "wof:name":"La Playa",
    "wof:placetype":"locality"
},
  "geometry": {"coordinates":[-67.83333,10.46667],"type":"Point"}
}