{
  "type": "Feature",
  "properties": {
    "gn:admin1_code":"12.0",
    "gn:asciiname":"Zamurito Nuevo",
    "gn:country_code":"VE",
    "gn:dem":191,
    "gn:feature_class":"P",
    "gn:feature_code":"PPLL",
    "gn:name":"Zamurito Nuevo",
    "gn:population":0,
    "gn:timezone":"America/Caracas",
    "iso:country":"VE",
    "wof:name":"Zamurito Nuevo",
    "wof:placetype":"locality"
},
  "geometry": {"coordinates":[-65.95873,9.58357],"type":"Point"}
}