{
  "type": "Feature",
  "properties": {
    "gn:admin1_code":"13",
    "gn:asciiname":"Sabana de Tigre",
    "gn:country_code":"VE",
    "gn:dem":846,
    "gn:feature_class":"P",
    "gn:feature_code":"PPL",
    "gn:name":"Sabana de Tigre",
    "gn:population":0,
    "gn:timezone":"America/Caracas",
    "iso:country":"VE",
    "wof:name":"Sabana de Tigre",
    "wof:placetype":"locality"
},
  "geometry": {"coordinates":[-70.54746,10.01008],"type":"Point"}
}