{
  "type": "Feature",
  "properties": {
    "gn:admin1_code":"14.0",
    "gn:asciiname":"El Lindero",
    "gn:country_code":"VE",
    "gn:dem":1488,
    "gn:feature_class":"P",
    "gn:feature_code":"PPLL",
    "gn:name":"El Lindero",
    "gn:population":0,
    "gn:timezone":"America/Caracas",
    "iso:country":"VE",
    "name:spa_x_preferred":[
        "El Lindero"
    ],
    "wof:name":"El Lindero",
    "wof:placetype":"locality"
},
  "geometry": {"coordinates":[-71.64514,8.07781],"type":"Point"}
}