{
  "type": "Feature",
  "properties": {
    "gn:admin1_code":"8",
    "gn:asciiname":"El Charal",
    "gn:country_code":"VE",
    "gn:dem":197,
    "gn:feature_class":"P",
    "gn:feature_code":"PPL",
    "gn:name":"El Charal",
    "gn:population":0,
    "gn:timezone":"America/Caracas",
    "iso:country":"VE",
    "wof:name":"El Charal",
    "wof:placetype":"locality"
},
  "geometry": {"coordinates":[-68.58793,9.70616],"type":"Point"}
}