{
  "type": "Feature",
  "properties": {
    "gn:admin1_code":"14.0",
    "gn:asciiname":"Los Limones",
    "gn:country_code":"VE",
    "gn:dem":2719,
    "gn:feature_class":"P",
    "gn:feature_code":"PPLL",
    "gn:name":"Los Limones",
    "gn:population":0,
    "gn:timezone":"America/Caracas",
    "iso:country":"VE",
    "wof:name":"Los Limones",
    "wof:placetype":"locality"
},
  "geometry": {"coordinates":[-70.99179000000002,8.71552],"type":"Point"}
}