{
  "type": "Feature",
  "properties": {
    "gn:admin1_code":"4",
    "gn:asciiname":"Morro la Cruz",
    "gn:country_code":"VE",
    "gn:dem":415,
    "gn:feature_class":"P",
    "gn:feature_code":"PPL",
    "gn:name":"Morro la Cruz",
    "gn:population":0,
    "gn:timezone":"America/Caracas",
    "iso:country":"VE",
    "wof:name":"Morro la Cruz",
    "wof:placetype":"locality"
},
  "geometry": {"coordinates":[-66.98333000000001,9.91667],"type":"Point"}
}