{
  "type": "Feature",
  "properties": {
    "gn:admin1_code":"11",
    "gn:asciiname":"La Sirena",
    "gn:country_code":"VE",
    "gn:dem":107,
    "gn:feature_class":"P",
    "gn:feature_code":"PPL",
    "gn:name":"La Sirena",
    "gn:population":0,
    "gn:timezone":"America/Caracas",
    "iso:country":"VE",
    "wof:name":"La Sirena",
    "wof:placetype":"locality"
},
  "geometry": {"coordinates":[-69.98333000000001,11.98333],"type":"Point"}
}