{
  "type": "Feature",
  "properties": {
    "gn:admin1_code":"09",
    "gn:asciiname":"San Jose de Amacuro",
    "gn:country_code":"VE",
    "gn:dem":14,
    "gn:feature_class":"P",
    "gn:feature_code":"PPL",
    "gn:name":"San Jose de Amacuro",
    "gn:population":0,
    "gn:timezone":"America/Caracas",
    "iso:country":"VE",
    "wof:name":"San Jose de Amacuro",
    "wof:placetype":"locality"
},
  "geometry": {"coordinates":[-59.96666999999999,8.23333],"type":"Point"}
}