{
  "type": "Feature",
  "properties": {
    "gn:admin1_code":"8",
    "gn:asciiname":"Morguito",
    "gn:cc2":"VE",
    "gn:country_code":"VE",
    "gn:dem":125,
    "gn:feature_class":"P",
    "gn:feature_code":"PPL",
    "gn:name":"Morguito",
    "gn:population":0,
    "gn:timezone":"America/Caracas",
    "iso:country":"VE",
    "name:und_x_variant":[
        "Moruguito",
        "Morguito"
    ],
    "wof:name":"Morguito",
    "wof:placetype":"locality"
},
  "geometry": {"coordinates":[-67.98333000000001,9.35],"type":"Point"}
}