{
  "type": "Feature",
  "properties": {
    "gn:admin1_code":"18",
    "gn:asciiname":"Mijaguito",
    "gn:country_code":"VE",
    "gn:dem":173,
    "gn:feature_class":"P",
    "gn:feature_code":"PPL",
    "gn:name":"Mijag\u00fcito",
    "gn:population":0,
    "gn:timezone":"America/Caracas",
    "iso:country":"VE",
    "wof:name":"Mijaguito",
    "wof:placetype":"locality"
},
  "geometry": {"coordinates":[-69.18626,9.45512],"type":"Point"}
}