{
  "type": "Feature",
  "properties": {
    "gn:admin1_code":"23.0",
    "gn:asciiname":"Sabana de Machango",
    "gn:country_code":"VE",
    "gn:dem":24,
    "gn:feature_class":"P",
    "gn:feature_code":"PPL",
    "gn:name":"Sabana de Machango",
    "gn:population":0,
    "gn:timezone":"America/Caracas",
    "iso:country":"VE",
    "wof:name":"Sabana de Machango",
    "wof:placetype":"locality"
},
  "geometry": {"coordinates":[-71.03721999999998,10.045],"type":"Point"}
}