{
  "type": "Feature",
  "properties": {
    "gn:admin1_code":"02",
    "gn:asciiname":"Cedral",
    "gn:country_code":"VE",
    "gn:dem":1560,
    "gn:feature_class":"P",
    "gn:feature_code":"PPL",
    "gn:name":"Cedral",
    "gn:population":0,
    "gn:timezone":"America/Caracas",
    "iso:country":"VE",
    "wof:name":"Cedral",
    "wof:placetype":"locality"
},
  "geometry": {"coordinates":[-64.10059,10.02017],"type":"Point"}
}