{
  "type": "Feature",
  "properties": {
    "gn:admin1_code":"02",
    "gn:asciiname":"Cedral",
    "gn:country_code":"VE",
    "gn:dem":1560,
    "gn:feature_class":"P",
    "gn:feature_code":"PPL",
    "gn:name":"Cedral",
    "gn:population":0,
    "gn:timezone":"America/Caracas",
    "iso:country":"VE",
    "name:bpy_x_preferred":[
        "\u09b8\u09c7\u09a1\u09cd\u09b0\u09be\u09b2"
    ],
    "name:ceb_x_preferred":[
        "Cedral"
    ],
    "name:epo_x_preferred":[
        "Cedral"
    ],
    "name:eus_x_preferred":[
        "Cedral"
    ],
    "name:fra_x_preferred":[
        "Cedral"
    ],
    "name:ita_x_preferred":[
        "Cedral"
    ],
    "name:kaz_x_preferred":[
        "\u0421\u0435\u0434\u0440\u0430\u043b"
    ],
    "name:mlg_x_preferred":[
        "Cedral"
    ],
    "name:nld_x_preferred":[
        "Cedral"
    ],
    "name:nor_x_preferred":[
        "Cedral"
    ],
    "name:pol_x_preferred":[
        "Cedral"
    ],
    "name:por_x_preferred":[
        "Cedral"
    ],
    "name:ron_x_preferred":[
        "Cedral"
    ],
    "name:rus_x_preferred":[
        "\u0421\u0435\u0434\u0440\u0430\u043b"
    ],
    "name:spa_x_preferred":[
        "Cedral"
    ],
    "name:vie_x_preferred":[
        "Cedral"
    ],
    "name:vol_x_preferred":[
        "Cedral"
    ],
    "name:war_x_preferred":[
        "Cedral"
    ],
    "name:zho_x_preferred":[
        "\u585e\u5fb7\u62c9\u723e"
    ],
    "wof:name":"Cedral",
    "wof:placetype":"locality"
},
  "geometry": {"coordinates":[-64.10059,10.02017],"type":"Point"}
}