{
  "type": "Feature",
  "properties": {
    "gn:admin1_code":"6",
    "gn:asciiname":"Morichibi",
    "gn:country_code":"VE",
    "gn:dem":206,
    "gn:feature_class":"P",
    "gn:feature_code":"PPL",
    "gn:name":"Morichibi",
    "gn:population":0,
    "gn:timezone":"America/Caracas",
    "iso:country":"VE",
    "wof:name":"Morichibi",
    "wof:placetype":"locality"
},
  "geometry": {"coordinates":[-62.16667,7.46667],"type":"Point"}
}