{
  "type": "Feature",
  "properties": {
    "gn:admin1_code":"07",
    "gn:asciiname":"La Sorpresa",
    "gn:country_code":"VE",
    "gn:dem":12,
    "gn:feature_class":"P",
    "gn:feature_code":"PPL",
    "gn:name":"La Sorpresa",
    "gn:population":0,
    "gn:timezone":"America/Caracas",
    "iso:country":"VE",
    "wof:name":"La Sorpresa",
    "wof:placetype":"locality"
},
  "geometry": {"coordinates":[-68.06144,10.47228],"type":"Point"}
}