{
  "type": "Feature",
  "properties": {
    "gn:admin1_code":"06",
    "gn:asciiname":"Teicupa",
    "gn:country_code":"VE",
    "gn:dem":495,
    "gn:feature_class":"P",
    "gn:feature_code":"PPL",
    "gn:name":"Teicupa",
    "gn:population":0,
    "gn:timezone":"America/Caracas",
    "iso:country":"VE",
    "wof:name":"Teicupa",
    "wof:placetype":"locality"
},
  "geometry": {"coordinates":[-62.23333,5.98333],"type":"Point"}
}