{
  "type": "Feature",
  "properties": {
    "gn:admin1_code":"8",
    "gn:asciiname":"La Corcoba",
    "gn:cc2":"VE",
    "gn:country_code":"VE",
    "gn:dem":87,
    "gn:feature_class":"P",
    "gn:feature_code":"PPL",
    "gn:name":"La Corcoba",
    "gn:population":0,
    "gn:timezone":"America/Caracas",
    "iso:country":"VE",
    "name:und_x_variant":[
        "La Corcova",
        "La Corcoba"
    ],
    "wof:name":"La Corcoba",
    "wof:placetype":"locality"
},
  "geometry": {"coordinates":[-68.31667,9.25],"type":"Point"}
}