{
  "type": "Feature",
  "properties": {
    "gn:admin1_code":"01",
    "gn:asciiname":"Solano",
    "gn:country_code":"VE",
    "gn:dem":106,
    "gn:feature_class":"P",
    "gn:feature_code":"PPL",
    "gn:name":"Solano",
    "gn:population":0,
    "gn:timezone":"America/Caracas",
    "iso:country":"VE",
    "wof:name":"Solano",
    "wof:placetype":"locality"
},
  "geometry": {"coordinates":[-66.95889,1.97472],"type":"Point"}
}