{
  "type": "Feature",
  "properties": {
    "gn:admin1_code":"11",
    "gn:asciiname":"Camururia",
    "gn:country_code":"VE",
    "gn:dem":209,
    "gn:feature_class":"P",
    "gn:feature_code":"PPL",
    "gn:name":"Camururia",
    "gn:population":0,
    "gn:timezone":"America/Caracas",
    "iso:country":"VE",
    "wof:name":"Camururia",
    "wof:placetype":"locality"
},
  "geometry": {"coordinates":[-68.85258,11.087],"type":"Point"}
}