{
  "type": "Feature",
  "properties": {
    "gn:admin1_code":"23.0",
    "gn:asciiname":"Chamita",
    "gn:country_code":"VE",
    "gn:dem":27,
    "gn:feature_class":"P",
    "gn:feature_code":"PPL",
    "gn:name":"Chamita",
    "gn:population":0,
    "gn:timezone":"America/Caracas",
    "iso:country":"VE",
    "wof:name":"Chamita",
    "wof:placetype":"locality"
},
  "geometry": {"coordinates":[-71.76666999999998,8.80833],"type":"Point"}
}