{
  "type": "Feature",
  "properties": {
    "gn:admin1_code":"15",
    "gn:asciiname":"Lagartijo",
    "gn:country_code":"VE",
    "gn:dem":237,
    "gn:feature_class":"P",
    "gn:feature_code":"PPL",
    "gn:name":"Lagartijo",
    "gn:population":0,
    "gn:timezone":"America/Caracas",
    "iso:country":"VE",
    "wof:name":"Lagartijo",
    "wof:placetype":"locality"
},
  "geometry": {"coordinates":[-66.6996,10.0874],"type":"Point"}
}