{
  "type": "Feature",
  "properties": {
    "gn:admin1_code":"4",
    "gn:asciiname":"Fajardo",
    "gn:country_code":"VE",
    "gn:dem":672,
    "gn:feature_class":"P",
    "gn:feature_code":"PPL",
    "gn:name":"Fajardo",
    "gn:population":0,
    "gn:timezone":"America/Caracas",
    "iso:country":"VE",
    "wof:name":"Fajardo",
    "wof:placetype":"locality"
},
  "geometry": {"coordinates":[-67.60556,10.41],"type":"Point"}
}