{
  "type": "Feature",
  "properties": {
    "gn:admin1_code":"5",
    "gn:admin2_code":"603.0",
    "gn:admin3_code":"60302.0",
    "gn:asciiname":"Guadarrama",
    "gn:country_code":"VE",
    "gn:dem":63,
    "gn:feature_class":"P",
    "gn:feature_code":"PPLA3",
    "gn:name":"Guadarrama",
    "gn:population":0,
    "gn:timezone":"America/Caracas",
    "iso:country":"VE",
    "name:ara_x_preferred":[
        "\u062c\u0648\u0627\u062f\u0627\u0631\u0627\u0645\u0627"
    ],
    "name:azb_x_preferred":[
        "\u0642\u0648\u0627\u062f\u0627\u0631\u0627\u0645\u0627"
    ],
    "name:cat_x_preferred":[
        "Guadarrama"
    ],
    "name:ceb_x_preferred":[
        "Guadarrama"
    ],
    "name:epo_x_preferred":[
        "Gvadaramo"
    ],
    "name:eus_x_preferred":[
        "Guadarrama"
    ],
    "name:fas_x_preferred":[
        "\u06af\u0648\u0627\u062f\u0627\u0631\u0627\u0645\u0627"
    ],
    "name:glg_x_preferred":[
        "Guadarrama"
    ],
    "name:hun_x_preferred":[
        "Guadarrama"
    ],
    "name:hye_x_preferred":[
        "\u0533\u0578\u0582\u0561\u0564\u0561\u057c\u0561\u0574\u0561"
    ],
    "name:ita_x_preferred":[
        "Guadarrama"
    ],
    "name:lad_x_preferred":[
        "Guadarrama"
    ],
    "name:ltz_x_preferred":[
        "Guadarrama"
    ],
    "name:msa_x_preferred":[
        "Guadarrama"
    ],
    "name:nld_x_preferred":[
        "Guadarrama"
    ],
    "name:oci_x_preferred":[
        "Guadarrama"
    ],
    "name:pol_x_preferred":[
        "Guadarrama"
    ],
    "name:por_x_preferred":[
        "Guadarrama"
    ],
    "name:rus_x_preferred":[
        "\u0413\u0432\u0430\u0434\u0430\u0440\u0440\u0430\u043c\u0430"
    ],
    "name:spa_x_preferred":[
        "Guadarrama"
    ],
    "name:swe_x_preferred":[
        "Guadarrama"
    ],
    "name:ukr_x_preferred":[
        "\u0413\u0443\u0430\u0434\u0430\u0440\u0440\u0430\u043c\u0430"
    ],
    "name:uzb_x_preferred":[
        "Guadarrama"
    ],
    "name:vie_x_preferred":[
        "Guadarrama"
    ],
    "name:war_x_preferred":[
        "Guadarrama"
    ],
    "name:zho_x_preferred":[
        "\u74dc\u8fbe\u62c9\u9a6c"
    ],
    "wof:name":"Guadarrama",
    "wof:placetype":"locality"
},
  "geometry": {"coordinates":[-68.04923000000001,8.53508],"type":"Point"}
}