{
  "type": "Feature",
  "properties": {
    "gn:admin1_code":"5",
    "gn:admin2_code":"603.0",
    "gn:admin3_code":"60302.0",
    "gn:asciiname":"Guadarrama",
    "gn:country_code":"VE",
    "gn:dem":63,
    "gn:feature_class":"P",
    "gn:feature_code":"PPLA3",
    "gn:name":"Guadarrama",
    "gn:population":0,
    "gn:timezone":"America/Caracas",
    "iso:country":"VE",
    "wof:name":"Guadarrama",
    "wof:placetype":"locality"
},
  "geometry": {"coordinates":[-68.04923000000001,8.53508],"type":"Point"}
}