{
  "type": "Feature",
  "properties": {
    "gn:admin1_code":"18.0",
    "gn:asciiname":"Palma Sola",
    "gn:country_code":"VE",
    "gn:dem":963,
    "gn:feature_class":"P",
    "gn:feature_code":"PPL",
    "gn:name":"Palma Sola",
    "gn:population":0,
    "gn:timezone":"America/Caracas",
    "iso:country":"VE",
    "name:ceb_x_preferred":[
        "Palma Sola"
    ],
    "name:deu_x_preferred":[
        "Palma Sola"
    ],
    "name:fra_x_preferred":[
        "Palma Sola"
    ],
    "name:spa_x_preferred":[
        "Palma Sola"
    ],
    "name:srp_x_preferred":[
        "\u041f\u0430\u043b\u043c\u0430 \u0421\u043e\u043b\u0430"
    ],
    "name:swe_x_preferred":[
        "Palma Sola"
    ],
    "wof:name":"Palma Sola",
    "wof:placetype":"locality"
},
  "geometry": {"coordinates":[-69.62028000000001,9.40577],"type":"Point"}
}