{
  "type": "Feature",
  "properties": {
    "gn:admin1_code":"02",
    "gn:asciiname":"Santa Juana",
    "gn:country_code":"VE",
    "gn:dem":78,
    "gn:feature_class":"P",
    "gn:feature_code":"PPL",
    "gn:name":"Santa Juana",
    "gn:population":0,
    "gn:timezone":"America/Caracas",
    "iso:country":"VE",
    "name:aze_x_preferred":[
        "Santa Juana"
    ],
    "name:bre_x_preferred":[
        "Santa Juana"
    ],
    "name:deu_x_preferred":[
        "Santa Juana"
    ],
    "name:eus_x_preferred":[
        "Santa Juana"
    ],
    "name:fas_x_preferred":[
        "\u0633\u0627\u0646\u062a\u0627 \u062e\u0648\u0622\u0646\u0627"
    ],
    "name:fra_x_preferred":[
        "Santa Juana"
    ],
    "name:glg_x_preferred":[
        "Santa Juana"
    ],
    "name:hrv_x_preferred":[
        "Santa Juana"
    ],
    "name:ina_x_preferred":[
        "Santa Juana"
    ],
    "name:ita_x_preferred":[
        "Santa Juana"
    ],
    "name:kor_x_preferred":[
        "\uc0b0\ud0c0\ud6c4\uc544\ub098"
    ],
    "name:lat_x_preferred":[
        "Sancta Ioanna"
    ],
    "name:nld_x_preferred":[
        "Santa Juana"
    ],
    "name:oci_x_preferred":[
        "Santa Juana"
    ],
    "name:pol_x_preferred":[
        "Santa Juana"
    ],
    "name:por_x_preferred":[
        "Santa Juana"
    ],
    "name:ron_x_preferred":[
        "Santa Juana"
    ],
    "name:rus_x_preferred":[
        "\u0421\u0430\u043d\u0442\u0430-\u0425\u0443\u0430\u043d\u0430"
    ],
    "name:slv_x_preferred":[
        "Santa Juana"
    ],
    "name:spa_x_preferred":[
        "Santa Juana"
    ],
    "name:tur_x_preferred":[
        "Santa Juana"
    ],
    "name:vol_x_preferred":[
        "Santa Juana"
    ],
    "name:war_x_preferred":[
        "Santa Juana"
    ],
    "name:zho_x_preferred":[
        "\u8056\u80e1\u963f\u7d0d"
    ],
    "wof:name":"Santa Juana",
    "wof:placetype":"locality"
},
  "geometry": {"coordinates":[-64.89053,9.57018],"type":"Point"}
}