{
  "type": "Feature",
  "properties": {
    "gn:admin1_code":"20.0",
    "gn:asciiname":"Las Parcelas",
    "gn:country_code":"VE",
    "gn:dem":156,
    "gn:feature_class":"P",
    "gn:feature_code":"PPL",
    "gn:name":"Las Parcelas",
    "gn:population":0,
    "gn:timezone":"America/Caracas",
    "iso:country":"VE",
    "wof:name":"Las Parcelas",
    "wof:placetype":"locality"
},
  "geometry": {"coordinates":[-71.34555999999998,7.48333],"type":"Point"}
}