{
  "type": "Feature",
  "properties": {
    "gn:admin1_code":"20",
    "gn:asciiname":"Llanetes",
    "gn:country_code":"VE",
    "gn:dem":2165,
    "gn:feature_class":"P",
    "gn:feature_code":"PPL",
    "gn:name":"Llanetes",
    "gn:population":0,
    "gn:timezone":"America/Caracas",
    "iso:country":"VE",
    "wof:name":"Llanetes",
    "wof:placetype":"locality"
},
  "geometry": {"coordinates":[-71.92442,8.25352],"type":"Point"}
}