{
  "type": "Feature",
  "properties": {
    "gn:admin1_code":"13.0",
    "gn:asciiname":"El Uiano",
    "gn:country_code":"VE",
    "gn:dem":520,
    "gn:feature_class":"P",
    "gn:feature_code":"PPL",
    "gn:name":"El Uiano",
    "gn:population":0,
    "gn:timezone":"America/Caracas",
    "iso:country":"VE",
    "wof:name":"El Uiano",
    "wof:placetype":"locality"
},
  "geometry": {"coordinates":[-69.27611,10.09416],"type":"Point"}
}