{
  "type": "Feature",
  "properties": {
    "gn:admin1_code":"14",
    "gn:asciiname":"Otopun",
    "gn:country_code":"VE",
    "gn:dem":1323,
    "gn:feature_class":"P",
    "gn:feature_code":"PPL",
    "gn:name":"Otop\u00fan",
    "gn:population":0,
    "gn:timezone":"America/Caracas",
    "iso:country":"VE",
    "name:und_x_variant":[
        "Otopu\u00edn",
        "Otop\u00fan"
    ],
    "wof:name":"Otopun",
    "wof:placetype":"locality"
},
  "geometry": {"coordinates":[-71.31941999999999,8.13769],"type":"Point"}
}