{
  "type": "Feature",
  "properties": {
    "gn:admin1_code":"02",
    "gn:asciiname":"San Manuel",
    "gn:country_code":"VE",
    "gn:dem":335,
    "gn:feature_class":"P",
    "gn:feature_code":"PPL",
    "gn:name":"San Manuel",
    "gn:population":0,
    "gn:timezone":"America/Caracas",
    "iso:country":"VE",
    "wof:name":"San Manuel",
    "wof:placetype":"locality"
},
  "geometry": {"coordinates":[-64.13661999999999,9.35238],"type":"Point"}
}