{
  "type": "Feature",
  "properties": {
    "gn:admin1_code":"13",
    "gn:asciiname":"Jabillal",
    "gn:country_code":"VE",
    "gn:dem":609,
    "gn:feature_class":"P",
    "gn:feature_code":"PPL",
    "gn:name":"Jabillal",
    "gn:population":0,
    "gn:timezone":"America/Caracas",
    "iso:country":"VE",
    "wof:name":"Jabillal",
    "wof:placetype":"locality"
},
  "geometry": {"coordinates":[-69.66894000000001,10.32348],"type":"Point"}
}