{
  "type": "Feature",
  "properties": {
    "gn:admin1_code":"11.0",
    "gn:asciiname":"Charaima",
    "gn:country_code":"VE",
    "gn:dem":11,
    "gn:feature_class":"P",
    "gn:feature_code":"PPL",
    "gn:name":"Charaima",
    "gn:population":0,
    "gn:timezone":"America/Caracas",
    "iso:country":"VE",
    "wof:name":"Charaima",
    "wof:placetype":"locality"
},
  "geometry": {"coordinates":[-69.85289,11.90788],"type":"Point"}
}