{
  "type": "Feature",
  "properties": {
    "gn:admin1_code":"11",
    "gn:asciiname":"Boca de Mangle",
    "gn:country_code":"VE",
    "gn:dem":5,
    "gn:feature_class":"P",
    "gn:feature_code":"PPL",
    "gn:name":"Boca de Mangle",
    "gn:population":0,
    "gn:timezone":"America/Caracas",
    "iso:country":"VE",
    "name:und_x_variant":[
        "El Mangle",
        "Boca Mangle",
        "El Manglar",
        "Boca de Mangle"
    ],
    "wof:name":"Boca de Mangle",
    "wof:placetype":"locality"
},
  "geometry": {"coordinates":[-68.39747,11.14786],"type":"Point"}
}