{
  "type": "Feature",
  "properties": {
    "gn:admin1_code":"13",
    "gn:asciiname":"Guamuy",
    "gn:country_code":"VE",
    "gn:dem":298,
    "gn:feature_class":"P",
    "gn:feature_code":"PPL",
    "gn:name":"Guamuy",
    "gn:population":0,
    "gn:timezone":"America/Caracas",
    "iso:country":"VE",
    "name:und_x_variant":[
        "Guama",
        "Guamuy"
    ],
    "wof:name":"Guamuy",
    "wof:placetype":"locality"
},
  "geometry": {"coordinates":[-69.69216999999999,10.53631],"type":"Point"}
}