{
  "type": "Feature",
  "properties": {
    "gn:admin1_code":"16.0",
    "gn:asciiname":"Mata La Baquira",
    "gn:country_code":"VE",
    "gn:dem":181,
    "gn:feature_class":"P",
    "gn:feature_code":"PPL",
    "gn:name":"Mata La Baquira",
    "gn:population":0,
    "gn:timezone":"America/Caracas",
    "iso:country":"VE",
    "wof:name":"Mata La Baquira",
    "wof:placetype":"locality"
},
  "geometry": {"coordinates":[-63.74222,9.12611],"type":"Point"}
}