{
  "type": "Feature",
  "properties": {
    "gn:admin1_code":"2",
    "gn:asciiname":"La Gallera",
    "gn:country_code":"VE",
    "gn:dem":134,
    "gn:feature_class":"P",
    "gn:feature_code":"PPL",
    "gn:name":"La Gallera",
    "gn:population":0,
    "gn:timezone":"America/Caracas",
    "iso:country":"VE",
    "wof:name":"La Gallera",
    "wof:placetype":"locality"
},
  "geometry": {"coordinates":[-64.58333,9.73333],"type":"Point"}
}