{
  "type": "Feature",
  "properties": {
    "gn:admin1_code":"15",
    "gn:asciiname":"La Rama",
    "gn:cc2":"VE",
    "gn:country_code":"VE",
    "gn:dem":28,
    "gn:feature_class":"P",
    "gn:feature_code":"PPL",
    "gn:name":"La Rama",
    "gn:population":0,
    "gn:timezone":"America/Caracas",
    "iso:country":"VE",
    "name:und_x_variant":[
        "La Rana",
        "La Rama"
    ],
    "wof:name":"La Rama",
    "wof:placetype":"locality"
},
  "geometry": {"coordinates":[-66.15000000000001,10.21667],"type":"Point"}
}