{
  "type": "Feature",
  "properties": {
    "gn:admin1_code":"15.0",
    "gn:asciiname":"Caipauro",
    "gn:country_code":"VE",
    "gn:dem":909,
    "gn:feature_class":"P",
    "gn:feature_code":"PPLL",
    "gn:name":"Caipauro",
    "gn:population":0,
    "gn:timezone":"America/Caracas",
    "iso:country":"VE",
    "wof:name":"Caipauro",
    "wof:placetype":"locality"
},
  "geometry": {"coordinates":[-66.85316,10.35142],"type":"Point"}
}