{
  "type": "Feature",
  "properties": {
    "gn:admin1_code":"4",
    "gn:asciiname":"La Mesa",
    "gn:country_code":"VE",
    "gn:dem":1108,
    "gn:feature_class":"P",
    "gn:feature_code":"PPL",
    "gn:name":"La Mesa",
    "gn:population":0,
    "gn:timezone":"America/Caracas",
    "iso:country":"VE",
    "wof:name":"La Mesa",
    "wof:placetype":"locality"
},
  "geometry": {"coordinates":[-67.26679,10.16502],"type":"Point"}
}