{
  "type": "Feature",
  "properties": {
    "gn:admin1_code":"3.0",
    "gn:asciiname":"El Deleite",
    "gn:country_code":"VE",
    "gn:dem":51,
    "gn:feature_class":"P",
    "gn:feature_code":"PPL",
    "gn:name":"El Deleite",
    "gn:population":0,
    "gn:timezone":"America/Caracas",
    "iso:country":"VE",
    "wof:name":"El Deleite",
    "wof:placetype":"locality"
},
  "geometry": {"coordinates":[-67.63221999999999,7.87556],"type":"Point"}
}