{
  "type": "Feature",
  "properties": {
    "gn:admin1_code":"03",
    "gn:asciiname":"Turagua",
    "gn:country_code":"VE",
    "gn:dem":83,
    "gn:feature_class":"P",
    "gn:feature_code":"PPL",
    "gn:name":"Turagua",
    "gn:population":0,
    "gn:timezone":"America/Caracas",
    "iso:country":"VE",
    "wof:name":"Turagua",
    "wof:placetype":"locality"
},
  "geometry": {"coordinates":[-69.32358000000001,7.80835],"type":"Point"}
}