{
  "type": "Feature",
  "properties": {
    "gn:admin1_code":"15.0",
    "gn:asciiname":"London",
    "gn:country_code":"VE",
    "gn:dem":811,
    "gn:feature_class":"P",
    "gn:feature_code":"PPLL",
    "gn:name":"London",
    "gn:population":0,
    "gn:timezone":"America/Caracas",
    "iso:country":"VE",
    "wof:name":"London",
    "wof:placetype":"locality"
},
  "geometry": {"coordinates":[-66.73159,10.36093],"type":"Point"}
}