{
  "type": "Feature",
  "properties": {
    "gn:admin1_code":"14",
    "gn:asciiname":"Villa Mercedes",
    "gn:country_code":"VE",
    "gn:dem":1521,
    "gn:feature_class":"P",
    "gn:feature_code":"PPL",
    "gn:name":"Villa Mercedes",
    "gn:population":0,
    "gn:timezone":"America/Caracas",
    "iso:country":"VE",
    "wof:name":"Villa Mercedes",
    "wof:placetype":"locality"
},
  "geometry": {"coordinates":[-70.71794,9.04468],"type":"Point"}
}