{
  "type": "Feature",
  "properties": {
    "gn:admin1_code":"6",
    "gn:asciiname":"Panapana",
    "gn:country_code":"VE",
    "gn:dem":34,
    "gn:feature_class":"P",
    "gn:feature_code":"PPL",
    "gn:name":"Panapana",
    "gn:population":0,
    "gn:timezone":"America/Caracas",
    "iso:country":"VE",
    "wof:name":"Panapana",
    "wof:placetype":"locality"
},
  "geometry": {"coordinates":[-63.25,8.23333],"type":"Point"}
}