{
  "type": "Feature",
  "properties": {
    "gn:admin1_code":"20",
    "gn:asciiname":"La Blanca",
    "gn:country_code":"VE",
    "gn:dem":1107,
    "gn:feature_class":"P",
    "gn:feature_code":"PPL",
    "gn:name":"La Blanca",
    "gn:population":0,
    "gn:timezone":"America/Caracas",
    "iso:country":"VE",
    "wof:name":"La Blanca",
    "wof:placetype":"locality"
},
  "geometry": {"coordinates":[-72.01127,7.83153],"type":"Point"}
}