{
  "type": "Feature",
  "properties": {
    "gn:admin1_code":"4",
    "gn:asciiname":"Guasduas",
    "gn:country_code":"VE",
    "gn:dem":485,
    "gn:feature_class":"P",
    "gn:feature_code":"PPL",
    "gn:name":"Guasduas",
    "gn:population":0,
    "gn:timezone":"America/Caracas",
    "iso:country":"VE",
    "wof:name":"Guasduas",
    "wof:placetype":"locality"
},
  "geometry": {"coordinates":[-67.48333000000001,10.08333],"type":"Point"}
}