{
  "type": "Feature",
  "properties": {
    "gn:admin1_code":"18.0",
    "gn:asciiname":"Las Tortugas",
    "gn:country_code":"VE",
    "gn:dem":144,
    "gn:feature_class":"P",
    "gn:feature_code":"PPLL",
    "gn:name":"Las Tortugas",
    "gn:population":0,
    "gn:timezone":"America/Caracas",
    "iso:country":"VE",
    "name:spa_x_preferred":[
        "Las Tortugas"
    ],
    "wof:name":"Las Tortugas",
    "wof:placetype":"locality"
},
  "geometry": {"coordinates":[-69.29331999999999,9.30324],"type":"Point"}
}