{
  "type": "Feature",
  "properties": {
    "gn:admin1_code":"13",
    "gn:asciiname":"Guayamure",
    "gn:country_code":"VE",
    "gn:dem":954,
    "gn:feature_class":"P",
    "gn:feature_code":"PPL",
    "gn:name":"Guayamure",
    "gn:population":0,
    "gn:timezone":"America/Caracas",
    "iso:country":"VE",
    "wof:name":"Guayamure",
    "wof:placetype":"locality"
},
  "geometry": {"coordinates":[-69.37671999999999,9.90752],"type":"Point"}
}