{
  "type": "Feature",
  "properties": {
    "gn:admin1_code":"6.0",
    "gn:asciiname":"La Busca",
    "gn:country_code":"VE",
    "gn:dem":79,
    "gn:feature_class":"P",
    "gn:feature_code":"PPL",
    "gn:name":"La Busca",
    "gn:population":0,
    "gn:timezone":"America/Caracas",
    "iso:country":"VE",
    "wof:name":"La Busca",
    "wof:placetype":"locality"
},
  "geometry": {"coordinates":[-66.69333,6.67139],"type":"Point"}
}