{
  "type": "Feature",
  "properties": {
    "gn:admin1_code":"15",
    "gn:asciiname":"Cano Morado",
    "gn:country_code":"VE",
    "gn:dem":47,
    "gn:feature_class":"P",
    "gn:feature_code":"PPL",
    "gn:name":"Ca\u00f1o Morado",
    "gn:population":0,
    "gn:timezone":"America/Caracas",
    "iso:country":"VE",
    "wof:name":"Cano Morado",
    "wof:placetype":"locality"
},
  "geometry": {"coordinates":[-66.25932,10.29136],"type":"Point"}
}