{
  "type": "Feature",
  "properties": {
    "gn:admin1_code":"23",
    "gn:asciiname":"San Jeronimo",
    "gn:country_code":"VE",
    "gn:dem":154,
    "gn:feature_class":"P",
    "gn:feature_code":"PPL",
    "gn:name":"San Jer\u00f3nimo",
    "gn:population":0,
    "gn:timezone":"America/Caracas",
    "iso:country":"VE",
    "wof:name":"San Jeronimo",
    "wof:placetype":"locality"
},
  "geometry": {"coordinates":[-71.01461,10.30703],"type":"Point"}
}