{
  "type": "Feature",
  "properties": {
    "gn:admin1_code":"19.0",
    "gn:asciiname":"Galeron",
    "gn:country_code":"VE",
    "gn:dem":305,
    "gn:feature_class":"P",
    "gn:feature_code":"PPL",
    "gn:name":"Galer\u00f3n",
    "gn:population":0,
    "gn:timezone":"America/Caracas",
    "iso:country":"VE",
    "wof:name":"Galeron",
    "wof:placetype":"locality"
},
  "geometry": {"coordinates":[-63.30278000000001,10.50222],"type":"Point"}
}