{
  "type": "Feature",
  "properties": {
    "gn:admin1_code":"3.0",
    "gn:asciiname":"Paso La Manga de Los Indios",
    "gn:country_code":"VE",
    "gn:dem":39,
    "gn:feature_class":"P",
    "gn:feature_code":"PPL",
    "gn:name":"Paso La Manga de Los Indios",
    "gn:population":0,
    "gn:timezone":"America/Caracas",
    "iso:country":"VE",
    "wof:name":"Paso La Manga de Los Indios",
    "wof:placetype":"locality"
},
  "geometry": {"coordinates":[-67.11525999999999,7.26125],"type":"Point"}
}