{
  "type": "Feature",
  "properties": {
    "gn:admin1_code":"08",
    "gn:asciiname":"Vallecito",
    "gn:country_code":"VE",
    "gn:dem":364,
    "gn:feature_class":"P",
    "gn:feature_code":"PPL",
    "gn:name":"Vallecito",
    "gn:population":0,
    "gn:timezone":"America/Caracas",
    "iso:country":"VE",
    "name:ceb_x_preferred":[
        "Vallecito"
    ],
    "name:deu_x_preferred":[
        "Vallecito"
    ],
    "name:swe_x_preferred":[
        "Vallecito"
    ],
    "wof:name":"Vallecito",
    "wof:placetype":"locality"
},
  "geometry": {"coordinates":[-68.01975,9.78042],"type":"Point"}
}