{
  "type": "Feature",
  "properties": {
    "gn:admin1_code":"2",
    "gn:asciiname":"El Huepo",
    "gn:cc2":"VE",
    "gn:country_code":"VE",
    "gn:dem":187,
    "gn:feature_class":"P",
    "gn:feature_code":"PPL",
    "gn:name":"El Huepo",
    "gn:population":0,
    "gn:timezone":"America/Caracas",
    "iso:country":"VE",
    "name:und_x_variant":[
        "El Huepe",
        "El Huepo"
    ],
    "wof:name":"El Huepo",
    "wof:placetype":"locality"
},
  "geometry": {"coordinates":[-63.86666999999999,9.08333],"type":"Point"}
}