{
  "type": "Feature",
  "properties": {
    "gn:admin1_code":"19.0",
    "gn:asciiname":"Rio San Pedro",
    "gn:country_code":"VE",
    "gn:dem":421,
    "gn:feature_class":"P",
    "gn:feature_code":"PPL",
    "gn:name":"R\u00edo San Pedro",
    "gn:population":0,
    "gn:timezone":"America/Caracas",
    "iso:country":"VE",
    "wof:name":"Rio San Pedro",
    "wof:placetype":"locality"
},
  "geometry": {"coordinates":[-64.42301999999999,10.21549],"type":"Point"}
}