{
  "type": "Feature",
  "properties": {
    "gn:admin1_code":"2",
    "gn:asciiname":"El Caro",
    "gn:country_code":"VE",
    "gn:dem":165,
    "gn:feature_class":"P",
    "gn:feature_code":"PPL",
    "gn:name":"El Caro",
    "gn:population":0,
    "gn:timezone":"America/Caracas",
    "iso:country":"VE",
    "wof:name":"El Caro",
    "wof:placetype":"locality"
},
  "geometry": {"coordinates":[-65.64636,9.803],"type":"Point"}
}