{
  "type": "Feature",
  "properties": {
    "gn:admin1_code":"11.0",
    "gn:asciiname":"El Caracoli",
    "gn:country_code":"VE",
    "gn:dem":247,
    "gn:feature_class":"P",
    "gn:feature_code":"PPL",
    "gn:name":"El Caracoli",
    "gn:population":0,
    "gn:timezone":"America/Caracas",
    "iso:country":"VE",
    "wof:name":"El Caracoli",
    "wof:placetype":"locality"
},
  "geometry": {"coordinates":[-70.92166999999998,10.532],"type":"Point"}
}