{
  "type": "Feature",
  "properties": {
    "gn:admin1_code":"02",
    "gn:asciiname":"Moropocual",
    "gn:country_code":"VE",
    "gn:dem":422,
    "gn:feature_class":"P",
    "gn:feature_code":"PPLL",
    "gn:name":"Moropocual",
    "gn:population":0,
    "gn:timezone":"America/Caracas",
    "iso:country":"VE",
    "wof:name":"Moropocual",
    "wof:placetype":"locality"
},
  "geometry": {"coordinates":[-64.56111,10.215],"type":"Point"}
}