{
  "type": "Feature",
  "properties": {
    "gn:admin1_code":"19",
    "gn:asciiname":"Punta Angoleta",
    "gn:country_code":"VE",
    "gn:dem":48,
    "gn:feature_class":"P",
    "gn:feature_code":"PPL",
    "gn:name":"Punta Angoleta",
    "gn:population":0,
    "gn:timezone":"America/Caracas",
    "iso:country":"VE",
    "wof:name":"Punta Angoleta",
    "wof:placetype":"locality"
},
  "geometry": {"coordinates":[-64.11667,10.56667],"type":"Point"}
}