{
  "type": "Feature",
  "properties": {
    "gn:admin1_code":"19.0",
    "gn:asciiname":"La Tigra",
    "gn:country_code":"VE",
    "gn:dem":964,
    "gn:feature_class":"P",
    "gn:feature_code":"PPL",
    "gn:name":"La Tigra",
    "gn:population":0,
    "gn:timezone":"America/Caracas",
    "iso:country":"VE",
    "wof:name":"La Tigra",
    "wof:placetype":"locality"
},
  "geometry": {"coordinates":[-63.8048,10.19628],"type":"Point"}
}