{
  "type": "Feature",
  "properties": {
    "iso:country":"VE",
    "qs:gn_country":"VE",
    "qs:gn_fcode":"PPL",
    "qs:gn_pop":0,
    "qs:name":"El Hatillo",
    "qs:name_adm0":"Venezuela",
    "qs:name_adm1":"Anzoategui",
    "qs:photos":324,
    "qs:photos_1k":66,
    "qs:photos_9k":1,
    "qs:photos_9r":5,
    "qs:photos_all":324,
    "qs:photos_sr":5,
    "qs:placetype":"Town",
    "qs:pop_sr":"0",
    "qs:woe_adm0":23424982,
    "wof:name":"El Hatillo",
    "wof:placetype":"locality"
},
  "geometry": {"coordinates":[-65.23475999999999,10.10295],"type":"Point"}
}