{
  "type": "Feature",
  "properties": {
    "gn:admin1_code":"23",
    "gn:asciiname":"El Cuarente y Cuatro",
    "gn:country_code":"VE",
    "gn:dem":177,
    "gn:feature_class":"P",
    "gn:feature_code":"PPL",
    "gn:name":"El Cuarente y Cuatro",
    "gn:population":0,
    "gn:timezone":"America/Caracas",
    "iso:country":"VE",
    "wof:name":"El Cuarente y Cuatro",
    "wof:placetype":"locality"
},
  "geometry": {"coordinates":[-71.08144,10.43611],"type":"Point"}
}