{
  "type": "Feature",
  "properties": {
    "gn:admin1_code":"02",
    "gn:asciiname":"Zanjonote",
    "gn:country_code":"VE",
    "gn:dem":77,
    "gn:feature_class":"P",
    "gn:feature_code":"PPL",
    "gn:name":"Zanjonote",
    "gn:population":0,
    "gn:timezone":"America/Caracas",
    "iso:country":"VE",
    "name:und_x_variant":[
        "Zanionate",
        "Zanjonote"
    ],
    "wof:name":"Zanjonote",
    "wof:placetype":"locality"
},
  "geometry": {"coordinates":[-64.45196999999999,8.22515],"type":"Point"}
}