{
  "type": "Feature",
  "properties": {
    "gn:admin1_code":"8.0",
    "gn:asciiname":"Rinconote",
    "gn:country_code":"VE",
    "gn:dem":109,
    "gn:feature_class":"P",
    "gn:feature_code":"PPL",
    "gn:name":"Rinconote",
    "gn:population":0,
    "gn:timezone":"America/Caracas",
    "iso:country":"VE",
    "wof:name":"Rinconote",
    "wof:placetype":"locality"
},
  "geometry": {"coordinates":[-68.03975,9.48095],"type":"Point"}
}