{
  "type": "Feature",
  "properties": {
    "gn:admin1_code":"8",
    "gn:asciiname":"Monagas",
    "gn:country_code":"VE",
    "gn:dem":270,
    "gn:feature_class":"P",
    "gn:feature_code":"PPL",
    "gn:name":"Monagas",
    "gn:population":0,
    "gn:timezone":"America/Caracas",
    "iso:country":"VE",
    "wof:name":"Monagas",
    "wof:placetype":"locality"
},
  "geometry": {"coordinates":[-68.40860000000001,9.81392],"type":"Point"}
}