{
  "type": "Feature",
  "properties": {
    "gn:admin1_code":"4",
    "gn:asciiname":"El Buey",
    "gn:country_code":"VE",
    "gn:dem":1079,
    "gn:feature_class":"P",
    "gn:feature_code":"PPL",
    "gn:name":"El Buey",
    "gn:population":0,
    "gn:timezone":"America/Caracas",
    "iso:country":"VE",
    "wof:name":"El Buey",
    "wof:placetype":"locality"
},
  "geometry": {"coordinates":[-67.15000000000001,10.18333],"type":"Point"}
}