{
  "type": "Feature",
  "properties": {
    "gn:admin1_code":"23",
    "gn:asciiname":"Amunol",
    "gn:country_code":"VE",
    "gn:dem":6,
    "gn:feature_class":"P",
    "gn:feature_code":"PPL",
    "gn:name":"Amu\u00f1ol",
    "gn:population":0,
    "gn:timezone":"America/Caracas",
    "iso:country":"VE",
    "name:und_x_variant":[
        "Amunor",
        "Amu\u00f1ol"
    ],
    "wof:name":"Amunol",
    "wof:placetype":"locality"
},
  "geometry": {"coordinates":[-71.99136,11.43847],"type":"Point"}
}