{
  "type": "Feature",
  "properties": {
    "iso:country":"VE",
    "qs:gn_country":"VE",
    "qs:gn_fcode":"PPL",
    "qs:gn_pop":0,
    "qs:name":"Agua de Vaca",
    "qs:name_adm0":"Venezuela",
    "qs:name_adm1":"Nueva Esparta",
    "qs:photos":65,
    "qs:photos_1k":13,
    "qs:photos_9k":1,
    "qs:photos_9r":2,
    "qs:photos_all":65,
    "qs:photos_sr":2,
    "qs:placetype":"Town",
    "qs:pop_sr":"0",
    "qs:woe_adm0":23424982,
    "wof:name":"Agua de Vaca",
    "wof:placetype":"locality"
},
  "geometry": {"coordinates":[-63.81753,11.02712],"type":"Point"}
}