{
  "type": "Feature",
  "properties": {
    "gn:admin1_code":"15",
    "gn:asciiname":"Raiz de Mato",
    "gn:country_code":"VE",
    "gn:dem":320,
    "gn:feature_class":"P",
    "gn:feature_code":"PPL",
    "gn:name":"Ra\u00edz de Mato",
    "gn:population":0,
    "gn:timezone":"America/Caracas",
    "iso:country":"VE",
    "wof:name":"Raiz de Mato",
    "wof:placetype":"locality"
},
  "geometry": {"coordinates":[-66.40000000000001,10.36667],"type":"Point"}
}