{
  "type": "Feature",
  "properties": {
    "gn:admin1_code":"05",
    "gn:asciiname":"Las Sabanetas",
    "gn:country_code":"VE",
    "gn:dem":92,
    "gn:feature_class":"P",
    "gn:feature_code":"PPL",
    "gn:name":"Las Sabanetas",
    "gn:population":0,
    "gn:timezone":"America/Caracas",
    "iso:country":"VE",
    "wof:name":"Las Sabanetas",
    "wof:placetype":"locality"
},
  "geometry": {"coordinates":[-69.34324000000001,8.38191],"type":"Point"}
}