{
  "type": "Feature",
  "properties": {
    "gn:admin1_code":"20",
    "gn:asciiname":"La Arenosa",
    "gn:country_code":"VE",
    "gn:dem":110,
    "gn:feature_class":"P",
    "gn:feature_code":"PPL",
    "gn:name":"La Arenosa",
    "gn:population":0,
    "gn:timezone":"America/Caracas",
    "iso:country":"VE",
    "wof:name":"La Arenosa",
    "wof:placetype":"locality"
},
  "geometry": {"coordinates":[-72.01194,8.41222],"type":"Point"}
}