{
  "type": "Feature",
  "properties": {
    "gn:admin1_code":"13",
    "gn:asciiname":"Matatere",
    "gn:country_code":"VE",
    "gn:dem":472,
    "gn:feature_class":"P",
    "gn:feature_code":"PPL",
    "gn:name":"Matatere",
    "gn:population":0,
    "gn:timezone":"America/Caracas",
    "iso:country":"VE",
    "wof:name":"Matatere",
    "wof:placetype":"locality"
},
  "geometry": {"coordinates":[-69.54730000000001,10.38984],"type":"Point"}
}