{
  "type": "Feature",
  "properties": {
    "gn:admin1_code":"11",
    "gn:asciiname":"Barunu",
    "gn:country_code":"VE",
    "gn:dem":86,
    "gn:feature_class":"P",
    "gn:feature_code":"PPL",
    "gn:name":"Barun\u00fa",
    "gn:population":0,
    "gn:timezone":"America/Caracas",
    "iso:country":"VE",
    "wof:name":"Barunu",
    "wof:placetype":"locality"
},
  "geometry": {"coordinates":[-70.01943,11.85524],"type":"Point"}
}