{
  "type": "Feature",
  "properties": {
    "gn:admin1_code":"03",
    "gn:asciiname":"Simonero",
    "gn:country_code":"VE",
    "gn:dem":74,
    "gn:feature_class":"P",
    "gn:feature_code":"PPL",
    "gn:name":"Simonero",
    "gn:population":0,
    "gn:timezone":"America/Caracas",
    "iso:country":"VE",
    "wof:name":"Simonero",
    "wof:placetype":"locality"
},
  "geometry": {"coordinates":[-68.53333000000001,7.38333],"type":"Point"}
}