{
  "type": "Feature",
  "properties": {
    "gn:admin1_code":"03",
    "gn:asciiname":"Santa Carolina",
    "gn:country_code":"VE",
    "gn:dem":63,
    "gn:feature_class":"P",
    "gn:feature_code":"PPL",
    "gn:name":"Santa Carolina",
    "gn:population":0,
    "gn:timezone":"America/Caracas",
    "iso:country":"VE",
    "name:fra_x_preferred":[
        "Santa Carolina"
    ],
    "name:zho_x_preferred":[
        "\u8056\u5361\u7f85\u91cc\u7d0d\u5cf6"
    ],
    "wof:name":"Santa Carolina",
    "wof:placetype":"locality"
},
  "geometry": {"coordinates":[-68.45,7.23333],"type":"Point"}
}