{
  "type": "Feature",
  "properties": {
    "gn:admin1_code":"21",
    "gn:asciiname":"Capellania",
    "gn:country_code":"VE",
    "gn:dem":1954,
    "gn:feature_class":"P",
    "gn:feature_code":"PPL",
    "gn:name":"Capellania",
    "gn:population":0,
    "gn:timezone":"America/Caracas",
    "iso:country":"VE",
    "wof:name":"Capellania",
    "wof:placetype":"locality"
},
  "geometry": {"coordinates":[-70.32037,9.41527],"type":"Point"}
}