{
  "type": "Feature",
  "properties": {
    "gn:admin1_code":"19.0",
    "gn:asciiname":"Quebrada Honda",
    "gn:country_code":"VE",
    "gn:dem":102,
    "gn:feature_class":"P",
    "gn:feature_code":"PPL",
    "gn:name":"Quebrada Honda",
    "gn:population":0,
    "gn:timezone":"America/Caracas",
    "iso:country":"VE",
    "wof:name":"Quebrada Honda",
    "wof:placetype":"locality"
},
  "geometry": {"coordinates":[-62.99446,10.65236],"type":"Point"}
}