{
  "type": "Feature",
  "properties": {
    "gn:admin1_code":"20",
    "gn:asciiname":"Tucape",
    "gn:country_code":"VE",
    "gn:dem":985,
    "gn:feature_class":"P",
    "gn:feature_code":"PPL",
    "gn:name":"Tucape",
    "gn:population":0,
    "gn:timezone":"America/Caracas",
    "iso:country":"VE",
    "wof:name":"Tucape",
    "wof:placetype":"locality"
},
  "geometry": {"coordinates":[-72.25,7.81278],"type":"Point"}
}