{
  "type": "Feature",
  "properties": {
    "gn:admin1_code":"2",
    "gn:asciiname":"Las Mayitas de Corrientoso",
    "gn:country_code":"VE",
    "gn:dem":16,
    "gn:feature_class":"P",
    "gn:feature_code":"PPL",
    "gn:name":"Las Mayitas de Corrientoso",
    "gn:population":0,
    "gn:timezone":"America/Caracas",
    "iso:country":"VE",
    "wof:name":"Las Mayitas de Corrientoso",
    "wof:placetype":"locality"
},
  "geometry": {"coordinates":[-63.13333000000001,8.36667],"type":"Point"}
}