{
  "type": "Feature",
  "properties": {
    "gn:admin1_code":"19",
    "gn:asciiname":"El Tapon",
    "gn:country_code":"VE",
    "gn:dem":342,
    "gn:feature_class":"P",
    "gn:feature_code":"PPL",
    "gn:name":"El Tap\u00f3n",
    "gn:population":0,
    "gn:timezone":"America/Caracas",
    "iso:country":"VE",
    "wof:name":"El Tapon",
    "wof:placetype":"locality"
},
  "geometry": {"coordinates":[-64.19632,10.19529],"type":"Point"}
}