{
  "type": "Feature",
  "properties": {
    "gn:admin1_code":"12.0",
    "gn:asciiname":"El Chorro",
    "gn:country_code":"VE",
    "gn:dem":51,
    "gn:feature_class":"P",
    "gn:feature_code":"PPLL",
    "gn:name":"El Chorro",
    "gn:population":0,
    "gn:timezone":"America/Caracas",
    "iso:country":"VE",
    "name:ceb_x_preferred":[
        "El Chorro"
    ],
    "name:dan_x_preferred":[
        "El Chorro"
    ],
    "name:epo_x_preferred":[
        "El Chorro"
    ],
    "name:eus_x_preferred":[
        "El Chorro"
    ],
    "name:fra_x_preferred":[
        "El Chorro"
    ],
    "name:glg_x_preferred":[
        "El Chorro"
    ],
    "name:hat_x_preferred":[
        "El Chorro"
    ],
    "name:nld_x_preferred":[
        "El Chorro"
    ],
    "name:pol_x_preferred":[
        "El Chorro"
    ],
    "name:spa_x_preferred":[
        "El Chorro"
    ],
    "name:swe_x_preferred":[
        "El Chorro"
    ],
    "wof:name":"El Chorro",
    "wof:placetype":"locality"
},
  "geometry": {"coordinates":[-65.73611,8.07778],"type":"Point"}
}