{
  "type": "Feature",
  "properties": {
    "gn:admin1_code":"2",
    "gn:asciiname":"La Jarilla",
    "gn:country_code":"VE",
    "gn:dem":147,
    "gn:feature_class":"P",
    "gn:feature_code":"PPL",
    "gn:name":"La Jarilla",
    "gn:population":0,
    "gn:timezone":"America/Caracas",
    "iso:country":"VE",
    "wof:name":"La Jarilla",
    "wof:placetype":"locality"
},
  "geometry": {"coordinates":[-64.90271,8.20776],"type":"Point"}
}