{
  "type": "Feature",
  "properties": {
    "gn:admin1_code":"16",
    "gn:asciiname":"El Periquito",
    "gn:cc2":"VE",
    "gn:country_code":"VE",
    "gn:dem":1061,
    "gn:feature_class":"P",
    "gn:feature_code":"PPL",
    "gn:name":"El Periquito",
    "gn:population":0,
    "gn:timezone":"America/Caracas",
    "iso:country":"VE",
    "name:und_x_variant":[
        "Periquito",
        "El Periquito"
    ],
    "wof:name":"El Periquito",
    "wof:placetype":"locality"
},
  "geometry": {"coordinates":[-63.58333,10.15],"type":"Point"}
}