{
  "type": "Feature",
  "properties": {
    "gn:admin1_code":"2",
    "gn:asciiname":"Las Garzas",
    "gn:country_code":"VE",
    "gn:dem":7,
    "gn:feature_class":"P",
    "gn:feature_code":"PPL",
    "gn:name":"Las Garzas",
    "gn:population":0,
    "gn:timezone":"America/Caracas",
    "iso:country":"VE",
    "name:spa_x_preferred":[
        "Las Garzas"
    ],
    "wof:name":"Las Garzas",
    "wof:placetype":"locality"
},
  "geometry": {"coordinates":[-64.66625000000001,10.18183],"type":"Point"}
}