{
  "type": "Feature",
  "properties": {
    "gn:admin1_code":"06",
    "gn:asciiname":"Suapure",
    "gn:country_code":"VE",
    "gn:dem":54,
    "gn:feature_class":"P",
    "gn:feature_code":"PPL",
    "gn:name":"Suapure",
    "gn:population":0,
    "gn:timezone":"America/Caracas",
    "iso:country":"VE",
    "wof:name":"Suapure",
    "wof:placetype":"locality"
},
  "geometry": {"coordinates":[-65.16667,7.23333],"type":"Point"}
}