{
  "type": "Feature",
  "properties": {
    "gn:admin1_code":"11",
    "gn:asciiname":"Campeche",
    "gn:country_code":"VE",
    "gn:dem":18,
    "gn:feature_class":"P",
    "gn:feature_code":"PPL",
    "gn:name":"Campeche",
    "gn:population":0,
    "gn:timezone":"America/Caracas",
    "iso:country":"VE",
    "wof:name":"Campeche",
    "wof:placetype":"locality"
},
  "geometry": {"coordinates":[-68.46149,10.96236],"type":"Point"}
}