{
  "type": "Feature",
  "properties": {
    "gn:admin1_code":"26",
    "gn:asciiname":"San Juan de Dios",
    "gn:country_code":"VE",
    "gn:dem":609,
    "gn:feature_class":"P",
    "gn:feature_code":"PPLL",
    "gn:name":"San Juan de Dios",
    "gn:population":0,
    "gn:timezone":"America/Caracas",
    "iso:country":"VE",
    "wof:name":"San Juan de Dios",
    "wof:placetype":"locality"
},
  "geometry": {"coordinates":[-66.93333,10.58333],"type":"Point"}
}