{
  "type": "Feature",
  "properties": {
    "gn:admin1_code":"26",
    "gn:asciiname":"San Juan de Dios",
    "gn:country_code":"VE",
    "gn:dem":609,
    "gn:feature_class":"P",
    "gn:feature_code":"PPLL",
    "gn:name":"San Juan de Dios",
    "gn:population":0,
    "gn:timezone":"America/Caracas",
    "iso:country":"VE",
    "name:urd_x_preferred":[
        "\u0633\u0627\u0646 \u062e\u0648\u0622\u0646 \u062f\u06d2 \u062f\u06cc\u0648\u0633"
    ],
    "wof:name":"San Juan de Dios",
    "wof:placetype":"locality"
},
  "geometry": {"coordinates":[-66.93333,10.58333],"type":"Point"}
}