{
  "type": "Feature",
  "properties": {
    "gn:admin1_code":"22",
    "gn:asciiname":"Los Corozos",
    "gn:country_code":"VE",
    "gn:dem":241,
    "gn:feature_class":"P",
    "gn:feature_code":"PPL",
    "gn:name":"Los Corozos",
    "gn:population":0,
    "gn:timezone":"America/Caracas",
    "iso:country":"VE",
    "wof:name":"Los Corozos",
    "wof:placetype":"locality"
},
  "geometry": {"coordinates":[-68.79148000000001,10.13342],"type":"Point"}
}