{
  "type": "Feature",
  "properties": {
    "gn:admin1_code":"11",
    "gn:asciiname":"La Encrucijada",
    "gn:country_code":"VE",
    "gn:dem":397,
    "gn:feature_class":"P",
    "gn:feature_code":"PPL",
    "gn:name":"La Encrucijada",
    "gn:population":0,
    "gn:timezone":"America/Caracas",
    "iso:country":"VE",
    "wof:name":"La Encrucijada",
    "wof:placetype":"locality"
},
  "geometry": {"coordinates":[-69.48867,11.18573],"type":"Point"}
}