{
  "type": "Feature",
  "properties": {
    "gn:admin1_code":"13",
    "gn:asciiname":"Chirino",
    "gn:country_code":"VE",
    "gn:dem":1813,
    "gn:feature_class":"P",
    "gn:feature_code":"PPL",
    "gn:name":"Chirin\u00f3",
    "gn:population":0,
    "gn:timezone":"America/Caracas",
    "iso:country":"VE",
    "wof:name":"Chirino",
    "wof:placetype":"locality"
},
  "geometry": {"coordinates":[-69.97744,9.71731],"type":"Point"}
}