{
  "type": "Feature",
  "properties": {
    "gn:admin1_code":"11",
    "gn:asciiname":"Caracubana",
    "gn:country_code":"VE",
    "gn:dem":15,
    "gn:feature_class":"P",
    "gn:feature_code":"PPL",
    "gn:name":"Caracubana",
    "gn:population":0,
    "gn:timezone":"America/Caracas",
    "iso:country":"VE",
    "wof:name":"Caracubana",
    "wof:placetype":"locality"
},
  "geometry": {"coordinates":[-70.81401,11.17669],"type":"Point"}
}