{
  "type": "Feature",
  "properties": {
    "gn:admin1_code":"23",
    "gn:asciiname":"El Pilar",
    "gn:country_code":"VE",
    "gn:dem":15,
    "gn:feature_class":"P",
    "gn:feature_code":"PPL",
    "gn:name":"El Pilar",
    "gn:population":0,
    "gn:timezone":"America/Caracas",
    "iso:country":"VE",
    "name:deu_x_preferred":[
        "El Pilar"
    ],
    "name:epo_x_preferred":[
        "El Pilar"
    ],
    "name:ita_x_preferred":[
        "El Pilar"
    ],
    "name:lit_x_preferred":[
        "El Pilaras"
    ],
    "name:pol_x_preferred":[
        "El Pilar"
    ],
    "name:spa_x_preferred":[
        "El Pilar"
    ],
    "name:ukr_x_preferred":[
        "\u0415\u043b\u044c-\u041f\u0456\u043b\u0430\u0440"
    ],
    "wof:name":"El Pilar",
    "wof:placetype":"locality"
},
  "geometry": {"coordinates":[-72.49783000000002,9.11691],"type":"Point"}
}