{
  "type": "Feature",
  "properties": {
    "gn:admin1_code":"15.0",
    "gn:asciiname":"El Radio",
    "gn:country_code":"VE",
    "gn:dem":1286,
    "gn:feature_class":"P",
    "gn:feature_code":"PPLL",
    "gn:name":"El Radio",
    "gn:population":0,
    "gn:timezone":"America/Caracas",
    "iso:country":"VE",
    "wof:name":"El Radio",
    "wof:placetype":"locality"
},
  "geometry": {"coordinates":[-66.89896,10.36033],"type":"Point"}
}