{
  "type": "Feature",
  "properties": {
    "gn:admin1_code":"4.0",
    "gn:asciiname":"Tasajera",
    "gn:country_code":"VE",
    "gn:dem":1117,
    "gn:feature_class":"P",
    "gn:feature_code":"PPL",
    "gn:name":"Tasajera",
    "gn:population":0,
    "gn:timezone":"America/Caracas",
    "iso:country":"VE",
    "wof:name":"Tasajera",
    "wof:placetype":"locality"
},
  "geometry": {"coordinates":[-67.23425,10.19925],"type":"Point"}
}