{
  "type": "Feature",
  "properties": {
    "gn:admin1_code":"1",
    "gn:asciiname":"Cuperia",
    "gn:country_code":"VE",
    "gn:dem":113,
    "gn:feature_class":"P",
    "gn:feature_code":"PPL",
    "gn:name":"Cuper\u00eda",
    "gn:population":0,
    "gn:timezone":"America/Caracas",
    "iso:country":"VE",
    "wof:name":"Cuperia",
    "wof:placetype":"locality"
},
  "geometry": {"coordinates":[-66.26666999999999,2.65],"type":"Point"}
}