{
  "type": "Feature",
  "properties": {
    "gn:admin1_code":"4",
    "gn:asciiname":"Cambural",
    "gn:country_code":"VE",
    "gn:dem":265,
    "gn:feature_class":"P",
    "gn:feature_code":"PPL",
    "gn:name":"Cambural",
    "gn:population":0,
    "gn:timezone":"America/Caracas",
    "iso:country":"VE",
    "wof:name":"Cambural",
    "wof:placetype":"locality"
},
  "geometry": {"coordinates":[-66.93333,9.78333],"type":"Point"}
}