{
  "type": "Feature",
  "properties": {
    "gn:admin1_code":"8",
    "gn:asciiname":"Barro Negro",
    "gn:country_code":"VE",
    "gn:dem":189,
    "gn:feature_class":"P",
    "gn:feature_code":"PPL",
    "gn:name":"Barro Negro",
    "gn:population":0,
    "gn:timezone":"America/Caracas",
    "iso:country":"VE",
    "wof:name":"Barro Negro",
    "wof:placetype":"locality"
},
  "geometry": {"coordinates":[-68.60625,9.71082],"type":"Point"}
}