{
  "type": "Feature",
  "properties": {
    "gn:admin1_code":"12.0",
    "gn:asciiname":"El Guarico",
    "gn:country_code":"VE",
    "gn:dem":52,
    "gn:feature_class":"P",
    "gn:feature_code":"PPL",
    "gn:name":"El Gu\u00e1rico",
    "gn:population":0,
    "gn:timezone":"America/Caracas",
    "iso:country":"VE",
    "wof:name":"El Guarico",
    "wof:placetype":"locality"
},
  "geometry": {"coordinates":[-67.37778,7.97889],"type":"Point"}
}