{
  "type": "Feature",
  "properties": {
    "gn:admin1_code":"05",
    "gn:asciiname":"Maporita",
    "gn:country_code":"VE",
    "gn:dem":133,
    "gn:feature_class":"P",
    "gn:feature_code":"PPLL",
    "gn:name":"Maporita",
    "gn:population":0,
    "gn:timezone":"America/Caracas",
    "iso:country":"VE",
    "wof:name":"Maporita",
    "wof:placetype":"locality"
},
  "geometry": {"coordinates":[-70.39301999999998,8.15508],"type":"Point"}
}