{
  "type": "Feature",
  "properties": {
    "gn:admin1_code":"1",
    "gn:asciiname":"Pendare",
    "gn:country_code":"VE",
    "gn:dem":101,
    "gn:feature_class":"P",
    "gn:feature_code":"PPL",
    "gn:name":"Pendare",
    "gn:population":0,
    "gn:timezone":"America/Caracas",
    "iso:country":"VE",
    "wof:name":"Pendare",
    "wof:placetype":"locality"
},
  "geometry": {"coordinates":[-67.73841,4.90909],"type":"Point"}
}