{
  "type": "Feature",
  "properties": {
    "gn:admin1_code":"6.0",
    "gn:asciiname":"El Caracol",
    "gn:country_code":"VE",
    "gn:dem":225,
    "gn:feature_class":"P",
    "gn:feature_code":"PPL",
    "gn:name":"El Caracol",
    "gn:population":0,
    "gn:timezone":"America/Caracas",
    "iso:country":"VE",
    "wof:name":"El Caracol",
    "wof:placetype":"locality"
},
  "geometry": {"coordinates":[-66.04035999999999,7.21303],"type":"Point"}
}