{
  "type": "Feature",
  "properties": {
    "gn:admin1_code":"2",
    "gn:asciiname":"Cerro Blanco",
    "gn:country_code":"VE",
    "gn:dem":93,
    "gn:feature_class":"P",
    "gn:feature_code":"PPL",
    "gn:name":"Cerro Blanco",
    "gn:population":0,
    "gn:timezone":"America/Caracas",
    "iso:country":"VE",
    "wof:name":"Cerro Blanco",
    "wof:placetype":"locality"
},
  "geometry": {"coordinates":[-64.82485,9.97478],"type":"Point"}
}