{
  "type": "Feature",
  "properties": {
    "gn:admin1_code":"4.0",
    "gn:asciiname":"Valladolid",
    "gn:country_code":"VE",
    "gn:dem":748,
    "gn:feature_class":"P",
    "gn:feature_code":"PPL",
    "gn:name":"Valladolid",
    "gn:population":0,
    "gn:timezone":"America/Caracas",
    "iso:country":"VE",
    "wof:name":"Valladolid",
    "wof:placetype":"locality"
},
  "geometry": {"coordinates":[-67.11604,10.05671],"type":"Point"}
}