{
  "type": "Feature",
  "properties": {
    "gn:admin1_code":"11",
    "gn:asciiname":"Divisi",
    "gn:country_code":"VE",
    "gn:dem":621,
    "gn:feature_class":"P",
    "gn:feature_code":"PPL",
    "gn:name":"Divisi",
    "gn:population":0,
    "gn:timezone":"America/Caracas",
    "iso:country":"VE",
    "name:deu_x_preferred":[
        "Divisi"
    ],
    "name:fin_x_preferred":[
        "Divisi"
    ],
    "name:spa_x_preferred":[
        "Divisi"
    ],
    "wof:name":"Divisi",
    "wof:placetype":"locality"
},
  "geometry": {"coordinates":[-69.40000000000001,10.76667],"type":"Point"}
}