{
  "type": "Feature",
  "properties": {
    "gn:admin1_code":"2",
    "gn:asciiname":"Cia Texas",
    "gn:country_code":"VE",
    "gn:dem":233,
    "gn:feature_class":"P",
    "gn:feature_code":"PPL",
    "gn:name":"C\u00eda Texas",
    "gn:population":0,
    "gn:timezone":"America/Caracas",
    "iso:country":"VE",
    "wof:name":"Cia Texas",
    "wof:placetype":"locality"
},
  "geometry": {"coordinates":[-64.10871999999999,9.21299],"type":"Point"}
}