{
  "type": "Feature",
  "properties": {
    "gn:admin1_code":"01",
    "gn:asciiname":"Santa Maria de Los Guaicas",
    "gn:country_code":"VE",
    "gn:dem":135,
    "gn:feature_class":"P",
    "gn:feature_code":"PPL",
    "gn:name":"Santa Mar\u00eda de Los Guaicas",
    "gn:population":0,
    "gn:timezone":"America/Caracas",
    "iso:country":"VE",
    "name:spa_x_preferred":[
        "Santa Mar\u00eda de Los Guaicas"
    ],
    "wof:name":"Santa Maria de Los Guaicas",
    "wof:placetype":"locality"
},
  "geometry": {"coordinates":[-65.21114,2.79203],"type":"Point"}
}