{
  "type": "Feature",
  "properties": {
    "gn:admin1_code":"18",
    "gn:asciiname":"La Idea",
    "gn:country_code":"VE",
    "gn:dem":116,
    "gn:feature_class":"P",
    "gn:feature_code":"PPL",
    "gn:name":"La Idea",
    "gn:population":0,
    "gn:timezone":"America/Caracas",
    "iso:country":"VE",
    "wof:name":"La Idea",
    "wof:placetype":"locality"
},
  "geometry": {"coordinates":[-69.48763000000001,9.00246],"type":"Point"}
}