{
  "type": "Feature",
  "properties": {
    "gn:admin1_code":"11.0",
    "gn:asciiname":"Buenevara",
    "gn:country_code":"VE",
    "gn:dem":127,
    "gn:feature_class":"P",
    "gn:feature_code":"PPL",
    "gn:name":"Buenevara",
    "gn:population":0,
    "gn:timezone":"America/Caracas",
    "iso:country":"VE",
    "wof:name":"Buenevara",
    "wof:placetype":"locality"
},
  "geometry": {"coordinates":[-69.98706,11.97653],"type":"Point"}
}