{
  "type": "Feature",
  "properties": {
    "gn:admin1_code":"11.0",
    "gn:asciiname":"Culebra",
    "gn:country_code":"VE",
    "gn:dem":176,
    "gn:feature_class":"P",
    "gn:feature_code":"PPLL",
    "gn:name":"Culebra",
    "gn:population":0,
    "gn:timezone":"America/Caracas",
    "iso:country":"VE",
    "wof:name":"Culebra",
    "wof:placetype":"locality"
},
  "geometry": {"coordinates":[-70.29389,11.12167],"type":"Point"}
}