{
  "type": "Feature",
  "properties": {
    "gn:admin1_code":"13.0",
    "gn:asciiname":"Caro",
    "gn:country_code":"VE",
    "gn:dem":608,
    "gn:feature_class":"P",
    "gn:feature_code":"PPL",
    "gn:name":"Caro",
    "gn:population":0,
    "gn:timezone":"America/Caracas",
    "iso:country":"VE",
    "name:ceb_x_preferred":[
        "Caro"
    ],
    "name:ces_x_preferred":[
        "Caro"
    ],
    "name:deu_x_preferred":[
        "Caro"
    ],
    "name:fra_x_preferred":[
        "Caro"
    ],
    "name:heb_x_preferred":[
        "\u05e7\u05d0\u05e8\u05d5"
    ],
    "name:ita_x_preferred":[
        "Caro"
    ],
    "name:nds_x_preferred":[
        "Caro"
    ],
    "name:nld_x_preferred":[
        "Caro"
    ],
    "name:pms_x_preferred":[
        "Caro"
    ],
    "name:pol_x_preferred":[
        "Caro"
    ],
    "name:por_x_preferred":[
        "Caro"
    ],
    "name:ron_x_preferred":[
        "Caro"
    ],
    "name:slk_x_preferred":[
        "Caro"
    ],
    "name:spa_x_preferred":[
        "Caro"
    ],
    "name:swe_x_preferred":[
        "Caro"
    ],
    "wof:name":"Caro",
    "wof:placetype":"locality"
},
  "geometry": {"coordinates":[-70.10365,9.90849],"type":"Point"}
}