{
  "type": "Feature",
  "properties": {
    "gn:admin1_code":"13.0",
    "gn:asciiname":"Caro",
    "gn:country_code":"VE",
    "gn:dem":608,
    "gn:feature_class":"P",
    "gn:feature_code":"PPL",
    "gn:name":"Caro",
    "gn:population":0,
    "gn:timezone":"America/Caracas",
    "iso:country":"VE",
    "wof:name":"Caro",
    "wof:placetype":"locality"
},
  "geometry": {"coordinates":[-70.10365,9.90849],"type":"Point"}
}