{
  "type": "Feature",
  "properties": {
    "gn:admin1_code":"13",
    "gn:asciiname":"Los Salvajes",
    "gn:country_code":"VE",
    "gn:dem":1532,
    "gn:feature_class":"P",
    "gn:feature_code":"PPL",
    "gn:name":"Los Salvajes",
    "gn:population":0,
    "gn:timezone":"America/Caracas",
    "iso:country":"VE",
    "wof:name":"Los Salvajes",
    "wof:placetype":"locality"
},
  "geometry": {"coordinates":[-69.905,9.91],"type":"Point"}
}