{
  "type": "Feature",
  "properties": {
    "gn:admin1_code":"6.0",
    "gn:asciiname":"Granja La Trinidad",
    "gn:country_code":"VE",
    "gn:dem":130,
    "gn:feature_class":"P",
    "gn:feature_code":"PPL",
    "gn:name":"Granja La Trinidad",
    "gn:population":0,
    "gn:timezone":"America/Caracas",
    "iso:country":"VE",
    "wof:name":"Granja La Trinidad",
    "wof:placetype":"locality"
},
  "geometry": {"coordinates":[-63.54333000000001,8.06444],"type":"Point"}
}