{
  "type": "Feature",
  "properties": {
    "gn:admin1_code":"12.0",
    "gn:asciiname":"Meleral",
    "gn:country_code":"VE",
    "gn:dem":159,
    "gn:feature_class":"P",
    "gn:feature_code":"PPLL",
    "gn:name":"Meleral",
    "gn:population":0,
    "gn:timezone":"America/Caracas",
    "iso:country":"VE",
    "wof:name":"Meleral",
    "wof:placetype":"locality"
},
  "geometry": {"coordinates":[-66.77705999999999,9.25696],"type":"Point"}
}