{
  "type": "Feature",
  "properties": {
    "gn:admin1_code":"23.0",
    "gn:asciiname":"Paso de la Candelaria",
    "gn:country_code":"VE",
    "gn:dem":36,
    "gn:feature_class":"P",
    "gn:feature_code":"PPLL",
    "gn:name":"Paso de la Candelaria",
    "gn:population":0,
    "gn:timezone":"America/Caracas",
    "iso:country":"VE",
    "wof:name":"Paso de la Candelaria",
    "wof:placetype":"locality"
},
  "geometry": {"coordinates":[-72.14322,10.33456],"type":"Point"}
}