{
  "type": "Feature",
  "properties": {
    "gn:admin1_code":"14",
    "gn:asciiname":"San Pablo Arriba",
    "gn:country_code":"VE",
    "gn:dem":2061,
    "gn:feature_class":"P",
    "gn:feature_code":"PPL",
    "gn:name":"San Pablo Arriba",
    "gn:population":0,
    "gn:timezone":"America/Caracas",
    "iso:country":"VE",
    "wof:name":"San Pablo Arriba",
    "wof:placetype":"locality"
},
  "geometry": {"coordinates":[-71.51094999999999,8.27562],"type":"Point"}
}