{
  "type": "Feature",
  "properties": {
    "gn:admin1_code":"6.0",
    "gn:asciiname":"El Chorizo",
    "gn:country_code":"VE",
    "gn:dem":60,
    "gn:feature_class":"P",
    "gn:feature_code":"PPL",
    "gn:name":"El Chorizo",
    "gn:population":0,
    "gn:timezone":"America/Caracas",
    "iso:country":"VE",
    "wof:name":"El Chorizo",
    "wof:placetype":"locality"
},
  "geometry": {"coordinates":[-66.26509,7.18156],"type":"Point"}
}