{
  "type": "Feature",
  "properties": {
    "gn:admin1_code":"8",
    "gn:asciiname":"Chaparral",
    "gn:country_code":"VE",
    "gn:dem":180,
    "gn:feature_class":"P",
    "gn:feature_code":"PPL",
    "gn:name":"Chaparral",
    "gn:population":0,
    "gn:timezone":"America/Caracas",
    "iso:country":"VE",
    "wof:name":"Chaparral",
    "wof:placetype":"locality"
},
  "geometry": {"coordinates":[-68.21250000000001,9.72545],"type":"Point"}
}