{
  "type": "Feature",
  "properties": {
    "gn:admin1_code":"2",
    "gn:asciiname":"Los Pobres",
    "gn:country_code":"VE",
    "gn:dem":173,
    "gn:feature_class":"P",
    "gn:feature_code":"PPL",
    "gn:name":"Los Pobres",
    "gn:population":0,
    "gn:timezone":"America/Caracas",
    "iso:country":"VE",
    "wof:name":"Los Pobres",
    "wof:placetype":"locality"
},
  "geometry": {"coordinates":[-64.61667,8.65],"type":"Point"}
}