{
  "type": "Feature",
  "properties": {
    "gn:admin1_code":"4.0",
    "gn:asciiname":"Hernandez",
    "gn:country_code":"VE",
    "gn:dem":1325,
    "gn:feature_class":"P",
    "gn:feature_code":"PPL",
    "gn:name":"Hernandez",
    "gn:population":0,
    "gn:timezone":"America/Caracas",
    "iso:country":"VE",
    "wof:name":"Hernandez",
    "wof:placetype":"locality"
},
  "geometry": {"coordinates":[-67.21809,10.37041],"type":"Point"}
}