{
  "type": "Feature",
  "properties": {
    "gn:admin1_code":"14",
    "gn:asciiname":"San Rafael",
    "gn:country_code":"VE",
    "gn:dem":1624,
    "gn:feature_class":"P",
    "gn:feature_code":"PPL",
    "gn:name":"San Rafael",
    "gn:population":0,
    "gn:timezone":"America/Caracas",
    "iso:country":"VE",
    "wof:name":"San Rafael",
    "wof:placetype":"locality"
},
  "geometry": {"coordinates":[-71.20239000000002,8.53992],"type":"Point"}
}