{
  "type": "Feature",
  "properties": {
    "gn:admin1_code":"11.0",
    "gn:asciiname":"El Milagro",
    "gn:country_code":"VE",
    "gn:dem":526,
    "gn:feature_class":"P",
    "gn:feature_code":"PPLL",
    "gn:name":"El Milagro",
    "gn:population":0,
    "gn:timezone":"America/Caracas",
    "iso:country":"VE",
    "wof:name":"El Milagro",
    "wof:placetype":"locality"
},
  "geometry": {"coordinates":[-70.58745999999999,10.75074],"type":"Point"}
}