{
  "type": "Feature",
  "properties": {
    "gn:admin1_code":"19",
    "gn:asciiname":"Palenque",
    "gn:country_code":"VE",
    "gn:dem":119,
    "gn:feature_class":"P",
    "gn:feature_code":"PPL",
    "gn:name":"Palenque",
    "gn:population":0,
    "gn:timezone":"America/Caracas",
    "iso:country":"VE",
    "name:afr_x_preferred":[
        "Palenque"
    ],
    "name:ara_x_preferred":[
        "\u0628\u0627\u0644\u064a\u0646\u0643\u064a"
    ],
    "name:bel_x_preferred":[
        "\u041f\u0430\u043b\u0435\u043d\u043a\u0435"
    ],
    "name:bod_x_preferred":[
        "\u0f55\u0f0b\u0f63\u0f7c\u0f53\u0f0b\u0f41\u0f7a\u0f0d"
    ],
    "name:bre_x_preferred":[
        "Palenque"
    ],
    "name:bul_x_preferred":[
        "\u041f\u0430\u043b\u0435\u043d\u043a\u0435"
    ],
    "name:cat_x_preferred":[
        "Palenque"
    ],
    "name:ces_x_preferred":[
        "Palenque"
    ],
    "name:cym_x_preferred":[
        "Palenque"
    ],
    "name:dan_x_preferred":[
        "Palenque"
    ],
    "name:deu_x_preferred":[
        "Palenque"
    ],
    "name:epo_x_preferred":[
        "Palenque"
    ],
    "name:eus_x_preferred":[
        "Palenque"
    ],
    "name:fas_x_preferred":[
        "\u067e\u0627\u0644\u0646\u06a9\u0647"
    ],
    "name:fin_x_preferred":[
        "Palenque"
    ],
    "name:fra_x_preferred":[
        "Palenque"
    ],
    "name:glg_x_preferred":[
        "Palenque"
    ],
    "name:heb_x_preferred":[
        "\u05e4\u05dc\u05e0\u05e7\u05d4"
    ],
    "name:hin_x_preferred":[
        "\u092a\u0932\u0947\u0902\u0915"
    ],
    "name:hrv_x_preferred":[
        "Palenque"
    ],
    "name:hun_x_preferred":[
        "Palenque"
    ],
    "name:hye_x_preferred":[
        "\u054a\u0561\u056c\u0565\u0576\u056f\u0565"
    ],
    "name:ind_x_preferred":[
        "Palenque"
    ],
    "name:ita_x_preferred":[
        "Palenque"
    ],
    "name:jpn_x_preferred":[
        "\u30d1\u30ec\u30f3\u30b1"
    ],
    "name:kat_x_preferred":[
        "\u10de\u10d0\u10da\u10d4\u10dc\u10d9\u10d4"
    ],
    "name:kaz_x_preferred":[
        "\u041f\u0430\u043b\u0435\u043d\u043a\u0435"
    ],
    "name:kor_x_preferred":[
        "\ud314\ub81d\ucf00"
    ],
    "name:lit_x_preferred":[
        "Palenk\u0117"
    ],
    "name:mkd_x_preferred":[
        "\u041f\u0430\u043b\u0435\u043d\u043a\u0435"
    ],
    "name:nld_x_preferred":[
        "Palenque"
    ],
    "name:nor_x_preferred":[
        "Palenque"
    ],
    "name:pan_x_preferred":[
        "\u0a2a\u0a3e\u0a32\u0a47\u0a02\u0a15\u0a47"
    ],
    "name:por_x_preferred":[
        "Palenque"
    ],
    "name:ron_x_preferred":[
        "Palenque"
    ],
    "name:rus_x_preferred":[
        "\u041f\u0430\u043b\u0435\u043d\u043a\u0435"
    ],
    "name:sco_x_preferred":[
        "Palenque"
    ],
    "name:slk_x_preferred":[
        "Palenque"
    ],
    "name:slv_x_preferred":[
        "Palenque"
    ],
    "name:spa_x_preferred":[
        "Palenque"
    ],
    "name:swe_x_preferred":[
        "Palenque"
    ],
    "name:tgl_x_preferred":[
        "Palenque"
    ],
    "name:tur_x_preferred":[
        "Palenque"
    ],
    "name:ukr_x_preferred":[
        "\u041f\u0430\u043b\u0435\u043d\u043a\u0435"
    ],
    "name:urd_x_preferred":[
        "\u067e\u0627\u0644\u06cc\u0646\u06a9\u06d2"
    ],
    "name:war_x_preferred":[
        "Palenque"
    ],
    "name:xmf_x_preferred":[
        "\u10de\u10d0\u10da\u10d4\u10dc\u10d9\u10d4"
    ],
    "name:zho_x_preferred":[
        "\u5e15\u4f26\u514b"
    ],
    "wof:name":"Palenque",
    "wof:placetype":"locality"
},
  "geometry": {"coordinates":[-63.07383000000001,10.66672],"type":"Point"}
}