{
  "type": "Feature",
  "properties": {
    "gn:admin1_code":"8",
    "gn:asciiname":"Apartaderos",
    "gn:country_code":"VE",
    "gn:dem":171,
    "gn:feature_class":"P",
    "gn:feature_code":"PPL",
    "gn:name":"Apartaderos",
    "gn:population":0,
    "gn:timezone":"America/Caracas",
    "iso:country":"VE",
    "name:fas_x_preferred":[
        "\u0622\u067e\u0627\u0631\u062a\u0627\u062f\u0631\u0648\u0633"
    ],
    "name:fra_x_preferred":[
        "Apartaderos"
    ],
    "name:pol_x_preferred":[
        "Apartaderos"
    ],
    "name:por_x_preferred":[
        "Apartaderos"
    ],
    "name:spa_x_preferred":[
        "Apartaderos"
    ],
    "wof:name":"Apartaderos",
    "wof:placetype":"locality"
},
  "geometry": {"coordinates":[-68.9465,9.68422],"type":"Point"}
}