{
  "type": "Feature",
  "properties": {
    "gn:admin1_code":"5",
    "gn:asciiname":"Chorroquito",
    "gn:country_code":"VE",
    "gn:dem":83,
    "gn:feature_class":"P",
    "gn:feature_code":"PPL",
    "gn:name":"Chorroquito",
    "gn:population":0,
    "gn:timezone":"America/Caracas",
    "iso:country":"VE",
    "wof:name":"Chorroquito",
    "wof:placetype":"locality"
},
  "geometry": {"coordinates":[-69.26666999999999,8.36667],"type":"Point"}
}