{
  "type": "Feature",
  "properties": {
    "gn:admin1_code":"3",
    "gn:asciiname":"Infante",
    "gn:cc2":"VE",
    "gn:country_code":"VE",
    "gn:dem":109,
    "gn:feature_class":"P",
    "gn:feature_code":"PPL",
    "gn:name":"Infante",
    "gn:population":0,
    "gn:timezone":"America/Caracas",
    "iso:country":"VE",
    "name:und_x_variant":[
        "Infantes",
        "Infante"
    ],
    "wof:name":"Infante",
    "wof:placetype":"locality"
},
  "geometry": {"coordinates":[-70.03333000000001,7.03333],"type":"Point"}
}