{
  "type": "Feature",
  "properties": {
    "gn:admin1_code":"3",
    "gn:asciiname":"Infante",
    "gn:cc2":"VE",
    "gn:country_code":"VE",
    "gn:dem":109,
    "gn:feature_class":"P",
    "gn:feature_code":"PPL",
    "gn:name":"Infante",
    "gn:population":0,
    "gn:timezone":"America/Caracas",
    "iso:country":"VE",
    "name:ara_x_preferred":[
        "\u0625\u0646\u0641\u0627\u0646\u062a\u064a"
    ],
    "name:ast_x_preferred":[
        "Infante"
    ],
    "name:aze_x_preferred":[
        "\u0130nfant"
    ],
    "name:bel_x_preferred":[
        "\u0406\u043d\u0444\u0430\u043d\u0442"
    ],
    "name:bos_x_preferred":[
        "Infant"
    ],
    "name:bre_x_preferred":[
        "Infant"
    ],
    "name:ces_x_preferred":[
        "Infant"
    ],
    "name:dan_x_preferred":[
        "Infant"
    ],
    "name:deu_x_preferred":[
        "Infant"
    ],
    "name:epo_x_preferred":[
        "Infanto"
    ],
    "name:eus_x_preferred":[
        "Infante"
    ],
    "name:fas_x_preferred":[
        "\u0627\u06cc\u0646\u0641\u0627\u0646\u062a\u0647"
    ],
    "name:fra_x_preferred":[
        "Infant"
    ],
    "name:glg_x_preferred":[
        "Infante"
    ],
    "name:heb_x_preferred":[
        "\u05d0\u05d9\u05e0\u05e4\u05e0\u05d8\u05d4"
    ],
    "name:hrv_x_preferred":[
        "Infant"
    ],
    "name:hun_x_preferred":[
        "Inf\u00e1ns"
    ],
    "name:hye_x_preferred":[
        "\u053b\u0576\u0586\u0561\u0576\u057f"
    ],
    "name:ita_x_preferred":[
        "Infante"
    ],
    "name:jpn_x_preferred":[
        "\u30a4\u30f3\u30d5\u30a1\u30f3\u30c6"
    ],
    "name:kat_x_preferred":[
        "\u10d8\u10dc\u10e4\u10d0\u10dc\u10e2\u10d8"
    ],
    "name:kaz_x_preferred":[
        "\u0418\u043d\u0444\u0430\u043d\u0442"
    ],
    "name:kor_x_preferred":[
        "\uc778\ud310\ud14c"
    ],
    "name:lav_x_preferred":[
        "Infants"
    ],
    "name:nld_x_preferred":[
        "Infant"
    ],
    "name:nno_x_preferred":[
        "Infant"
    ],
    "name:nor_x_preferred":[
        "Infante"
    ],
    "name:pol_x_preferred":[
        "Infant"
    ],
    "name:por_x_preferred":[
        "Infante"
    ],
    "name:ron_x_preferred":[
        "Infante"
    ],
    "name:rus_x_preferred":[
        "\u0418\u043d\u0444\u0430\u043d\u0442"
    ],
    "name:slk_x_preferred":[
        "Infant"
    ],
    "name:spa_x_preferred":[
        "Infante"
    ],
    "name:srp_x_preferred":[
        "\u0418\u043d\u0444\u0430\u043d\u0442"
    ],
    "name:swe_x_preferred":[
        "Infant"
    ],
    "name:tha_x_preferred":[
        "\u0e2d\u0e34\u0e19\u0e1f\u0e31\u0e19\u0e40\u0e15"
    ],
    "name:ukr_x_preferred":[
        "\u0406\u043d\u0444\u0430\u043d\u0442"
    ],
    "name:und_x_variant":[
        "Infantes"
    ],
    "wof:name":"Infante",
    "wof:placetype":"locality"
},
  "geometry": {"coordinates":[-70.03333000000001,7.03333],"type":"Point"}
}