{
  "type": "Feature",
  "properties": {
    "gn:admin1_code":"23",
    "gn:asciiname":"Patiecito",
    "gn:country_code":"VE",
    "gn:dem":26,
    "gn:feature_class":"P",
    "gn:feature_code":"PPL",
    "gn:name":"Patiecito",
    "gn:population":0,
    "gn:timezone":"America/Caracas",
    "iso:country":"VE",
    "wof:name":"Patiecito",
    "wof:placetype":"locality"
},
  "geometry": {"coordinates":[-71.38333,10.38333],"type":"Point"}
}