{
  "type": "Feature",
  "properties": {
    "gn:admin1_code":"5",
    "gn:asciiname":"Lagunitas",
    "gn:country_code":"VE",
    "gn:dem":108,
    "gn:feature_class":"P",
    "gn:feature_code":"PPL",
    "gn:name":"Lagunitas",
    "gn:population":0,
    "gn:timezone":"America/Caracas",
    "iso:country":"VE",
    "wof:name":"Lagunitas",
    "wof:placetype":"locality"
},
  "geometry": {"coordinates":[-69.59999999999999,8.51667],"type":"Point"}
}