{
  "type": "Feature",
  "properties": {
    "gn:admin1_code":"13",
    "gn:asciiname":"El Mamon",
    "gn:cc2":"VE",
    "gn:country_code":"VE",
    "gn:dem":748,
    "gn:feature_class":"P",
    "gn:feature_code":"PPL",
    "gn:name":"El Mam\u00f3n",
    "gn:population":0,
    "gn:timezone":"America/Caracas",
    "iso:country":"VE",
    "name:und_x_variant":[
        "Mam\u00f3n",
        "El Mam\u00f3n"
    ],
    "wof:name":"El Mamon",
    "wof:placetype":"locality"
},
  "geometry": {"coordinates":[-69.40000000000001,10.13333],"type":"Point"}
}