{
  "type": "Feature",
  "properties": {
    "gn:admin1_code":"15",
    "gn:asciiname":"Burguillos",
    "gn:country_code":"VE",
    "gn:dem":14,
    "gn:feature_class":"P",
    "gn:feature_code":"PPL",
    "gn:name":"Burguillos",
    "gn:population":0,
    "gn:timezone":"America/Caracas",
    "iso:country":"VE",
    "name:arg_x_preferred":[
        "Burguillos"
    ],
    "name:ast_x_preferred":[
        "Burguillos"
    ],
    "name:bul_x_preferred":[
        "\u0411\u0443\u0440\u0433\u0438\u043b\u044c\u043e\u0441"
    ],
    "name:cat_x_preferred":[
        "Burguillos"
    ],
    "name:ceb_x_preferred":[
        "Burguillos"
    ],
    "name:epo_x_preferred":[
        "Burguillos"
    ],
    "name:eus_x_preferred":[
        "Burguillos"
    ],
    "name:fra_x_preferred":[
        "Burguillos"
    ],
    "name:hat_x_preferred":[
        "Burguillos"
    ],
    "name:hun_x_preferred":[
        "Burguillos"
    ],
    "name:hye_x_preferred":[
        "\u0532\u0578\u0582\u0580\u0563\u056b\u056c\u0575\u0578\u057d"
    ],
    "name:ind_x_preferred":[
        "Burguillos"
    ],
    "name:ita_x_preferred":[
        "Burguillos"
    ],
    "name:kaz_x_preferred":[
        "\u0411\u0443\u0440\u0433\u0438\u043b\u044c\u043e\u0441"
    ],
    "name:msa_x_preferred":[
        "Burguillos"
    ],
    "name:nld_x_preferred":[
        "Burguillos"
    ],
    "name:oci_x_preferred":[
        "Burguillos"
    ],
    "name:pol_x_preferred":[
        "Burguillos"
    ],
    "name:por_x_preferred":[
        "Burguillos"
    ],
    "name:ron_x_preferred":[
        "Burguillos"
    ],
    "name:rus_x_preferred":[
        "\u0411\u0443\u0440\u0433\u0438\u043b\u044c\u043e\u0441"
    ],
    "name:spa_x_preferred":[
        "Burguillos"
    ],
    "name:swe_x_preferred":[
        "Burguillos"
    ],
    "name:tur_x_preferred":[
        "Burguillos"
    ],
    "name:ukr_x_preferred":[
        "\u0411\u0443\u0440\u0433\u0456\u043b\u044c\u0439\u043e\u0441"
    ],
    "name:uzb_x_preferred":[
        "Burguillos"
    ],
    "name:war_x_preferred":[
        "Burguillos"
    ],
    "name:zho_x_preferred":[
        "\u5e03\u5c14\u5409\u7565\u65af"
    ],
    "wof:name":"Burguillos",
    "wof:placetype":"locality"
},
  "geometry": {"coordinates":[-66.01861,10.27111],"type":"Point"}
}