{
  "type": "Feature",
  "properties": {
    "gn:admin1_code":"15",
    "gn:asciiname":"Las Guamas",
    "gn:country_code":"VE",
    "gn:dem":1422,
    "gn:feature_class":"P",
    "gn:feature_code":"PPL",
    "gn:name":"Las Guamas",
    "gn:population":0,
    "gn:timezone":"America/Caracas",
    "iso:country":"VE",
    "wof:name":"Las Guamas",
    "wof:placetype":"locality"
},
  "geometry": {"coordinates":[-67.09510999999999,10.35],"type":"Point"}
}