{
  "type": "Feature",
  "properties": {
    "gn:admin1_code":"14",
    "gn:asciiname":"Cano Guayabo",
    "gn:country_code":"VE",
    "gn:dem":998,
    "gn:feature_class":"P",
    "gn:feature_code":"PPL",
    "gn:name":"Ca\u00f1o Guayabo",
    "gn:population":0,
    "gn:timezone":"America/Caracas",
    "iso:country":"VE",
    "wof:name":"Cano Guayabo",
    "wof:placetype":"locality"
},
  "geometry": {"coordinates":[-71.46988,8.76188],"type":"Point"}
}