{
  "type": "Feature",
  "properties": {
    "gn:admin1_code":"13.0",
    "gn:asciiname":"Sabaneta",
    "gn:country_code":"VE",
    "gn:dem":942,
    "gn:feature_class":"P",
    "gn:feature_code":"PPL",
    "gn:name":"Sabaneta",
    "gn:population":0,
    "gn:timezone":"America/Caracas",
    "iso:country":"VE",
    "name:bar_x_preferred":[
        "Sabaneta"
    ],
    "name:ceb_x_preferred":[
        "Sabaneta"
    ],
    "name:deu_x_preferred":[
        "Sabaneta"
    ],
    "name:fas_x_preferred":[
        "\u0633\u0627\u0628\u0627\u0646\u062a\u0627"
    ],
    "name:fra_x_preferred":[
        "Sabaneta"
    ],
    "name:ita_x_preferred":[
        "Sabaneta"
    ],
    "name:nld_x_preferred":[
        "Sabaneta"
    ],
    "name:pol_x_preferred":[
        "Sabaneta"
    ],
    "name:por_x_preferred":[
        "Sabaneta"
    ],
    "name:rus_x_preferred":[
        "\u0421\u0430\u0431\u0430\u043d\u0435\u0442\u0430"
    ],
    "name:sco_x_preferred":[
        "Sabaneta"
    ],
    "name:spa_x_preferred":[
        "Sabaneta"
    ],
    "name:srp_x_preferred":[
        "\u0421\u0430\u0431\u0430\u043d\u0435\u0442\u0430"
    ],
    "name:swe_x_preferred":[
        "Sabaneta"
    ],
    "name:vie_x_preferred":[
        "Sabaneta"
    ],
    "name:zho_x_preferred":[
        "\u8428\u74e6\u5185\u5854"
    ],
    "wof:name":"Sabaneta",
    "wof:placetype":"locality"
},
  "geometry": {"coordinates":[-69.97166999999999,9.98056],"type":"Point"}
}