{
  "type": "Feature",
  "properties": {
    "gn:admin1_code":"20",
    "gn:asciiname":"Las Mesitas",
    "gn:country_code":"VE",
    "gn:dem":306,
    "gn:feature_class":"P",
    "gn:feature_code":"PPL",
    "gn:name":"Las Mesitas",
    "gn:population":0,
    "gn:timezone":"America/Caracas",
    "iso:country":"VE",
    "wof:name":"Las Mesitas",
    "wof:placetype":"locality"
},
  "geometry": {"coordinates":[-72.04629,8.32631],"type":"Point"}
}