{
  "type": "Feature",
  "properties": {
    "gn:admin1_code":"11.0",
    "gn:asciiname":"Guasimal",
    "gn:country_code":"VE",
    "gn:dem":206,
    "gn:feature_class":"P",
    "gn:feature_code":"PPL",
    "gn:name":"Guasimal",
    "gn:population":0,
    "gn:timezone":"America/Caracas",
    "iso:country":"VE",
    "name:ceb_x_preferred":[
        "Guasimal"
    ],
    "name:deu_x_preferred":[
        "Guasimal"
    ],
    "name:hat_x_preferred":[
        "Guasimal"
    ],
    "name:nld_x_preferred":[
        "Guasimal"
    ],
    "wof:name":"Guasimal",
    "wof:placetype":"locality"
},
  "geometry": {"coordinates":[-69.11111,11.36722],"type":"Point"}
}