{
  "type": "Feature",
  "properties": {
    "gn:admin1_code":"02",
    "gn:asciiname":"Guatire",
    "gn:country_code":"VE",
    "gn:dem":136,
    "gn:feature_class":"P",
    "gn:feature_code":"PPLL",
    "gn:name":"Guatire",
    "gn:population":0,
    "gn:timezone":"America/Caracas",
    "iso:country":"VE",
    "wof:name":"Guatire",
    "wof:placetype":"locality"
},
  "geometry": {"coordinates":[-64.89338000000001,8.34247],"type":"Point"}
}