{
  "type": "Feature",
  "properties": {
    "gn:admin1_code":"02",
    "gn:asciiname":"Guatire",
    "gn:country_code":"VE",
    "gn:dem":136,
    "gn:feature_class":"P",
    "gn:feature_code":"PPLL",
    "gn:name":"Guatire",
    "gn:population":0,
    "gn:timezone":"America/Caracas",
    "iso:country":"VE",
    "name:bul_x_preferred":[
        "\u0413\u0443\u0430\u0442\u0438\u0440\u0435"
    ],
    "name:ceb_x_preferred":[
        "Guatire"
    ],
    "name:deu_x_preferred":[
        "Guatire"
    ],
    "name:epo_x_preferred":[
        "Guatire"
    ],
    "name:fra_x_preferred":[
        "Guatire"
    ],
    "name:ita_x_preferred":[
        "Guatire"
    ],
    "name:jpn_x_preferred":[
        "\u30b0\u30a2\u30c6\u30a3\u30ec"
    ],
    "name:kat_x_preferred":[
        "\u10d2\u10e3\u10d0\u10e2\u10d8\u10e0\u10d4"
    ],
    "name:kor_x_preferred":[
        "\uacfc\ud2f0\ub808"
    ],
    "name:pol_x_preferred":[
        "Guatire"
    ],
    "name:por_x_preferred":[
        "Guatire"
    ],
    "name:rus_x_preferred":[
        "\u0413\u0443\u0430\u0442\u0438\u0440\u0435"
    ],
    "name:spa_x_preferred":[
        "Guatire"
    ],
    "name:tat_x_preferred":[
        "\u0413\u0432\u0430\u0442\u0438\u0440\u0435"
    ],
    "name:ukr_x_preferred":[
        "\u0413\u0443\u0430\u0442\u0456\u0440\u0435"
    ],
    "name:vol_x_preferred":[
        "Guatire"
    ],
    "name:zho_x_preferred":[
        "\u74dc\u8482\u96f7"
    ],
    "wof:name":"Guatire",
    "wof:placetype":"locality"
},
  "geometry": {"coordinates":[-64.89338000000001,8.34247],"type":"Point"}
}