{
  "type": "Feature",
  "properties": {
    "gn:admin1_code":"6.0",
    "gn:asciiname":"Los Frijoles",
    "gn:country_code":"VE",
    "gn:dem":91,
    "gn:feature_class":"P",
    "gn:feature_code":"PPL",
    "gn:name":"Los Frijoles",
    "gn:population":0,
    "gn:timezone":"America/Caracas",
    "iso:country":"VE",
    "wof:name":"Los Frijoles",
    "wof:placetype":"locality"
},
  "geometry": {"coordinates":[-64.03384,7.75935],"type":"Point"}
}