{
  "type": "Feature",
  "properties": {
    "gn:admin1_code":"1.0",
    "gn:asciiname":"Yeisibibeteri",
    "gn:country_code":"VE",
    "gn:dem":328,
    "gn:feature_class":"P",
    "gn:feature_code":"PPL",
    "gn:name":"Yeisibibeteri",
    "gn:population":0,
    "gn:timezone":"America/Caracas",
    "iso:country":"VE",
    "wof:name":"Yeisibibeteri",
    "wof:placetype":"locality"
},
  "geometry": {"coordinates":[-64.7137,2.96717],"type":"Point"}
}