{
  "type": "Feature",
  "properties": {
    "gn:admin1_code":"14",
    "gn:asciiname":"El Cacique",
    "gn:country_code":"VE",
    "gn:dem":708,
    "gn:feature_class":"P",
    "gn:feature_code":"PPL",
    "gn:name":"El Cacique",
    "gn:population":0,
    "gn:timezone":"America/Caracas",
    "iso:country":"VE",
    "wof:name":"El Cacique",
    "wof:placetype":"locality"
},
  "geometry": {"coordinates":[-71.6919,8.3634],"type":"Point"}
}