{
  "type": "Feature",
  "properties": {
    "gn:admin1_code":"13",
    "gn:asciiname":"Humocaro Alto",
    "gn:country_code":"VE",
    "gn:dem":1045,
    "gn:feature_class":"P",
    "gn:feature_code":"PPL",
    "gn:name":"Humocaro Alto",
    "gn:population":0,
    "gn:timezone":"America/Caracas",
    "iso:country":"VE",
    "wof:name":"Humocaro Alto",
    "wof:placetype":"locality"
},
  "geometry": {"coordinates":[-69.98681999999999,9.60576],"type":"Point"}
}