{
  "type": "Feature",
  "properties": {
    "gn:admin1_code":"20.0",
    "gn:asciiname":"La Honda",
    "gn:country_code":"VE",
    "gn:dem":1766,
    "gn:feature_class":"P",
    "gn:feature_code":"PPLL",
    "gn:name":"La Honda",
    "gn:population":0,
    "gn:timezone":"America/Caracas",
    "iso:country":"VE",
    "wof:name":"La Honda",
    "wof:placetype":"locality"
},
  "geometry": {"coordinates":[-71.95328000000001,8.14244],"type":"Point"}
}