{
  "type": "Feature",
  "properties": {
    "gn:admin1_code":"23.0",
    "gn:asciiname":"El Pozo Blanco",
    "gn:country_code":"VE",
    "gn:dem":24,
    "gn:feature_class":"P",
    "gn:feature_code":"PPLL",
    "gn:name":"El Pozo Blanco",
    "gn:population":0,
    "gn:timezone":"America/Caracas",
    "iso:country":"VE",
    "wof:name":"El Pozo Blanco",
    "wof:placetype":"locality"
},
  "geometry": {"coordinates":[-71.84215999999998,10.91966],"type":"Point"}
}