{
  "type": "Feature",
  "properties": {
    "gn:admin1_code":"4",
    "gn:asciiname":"El Guayabito",
    "gn:country_code":"VE",
    "gn:dem":208,
    "gn:feature_class":"P",
    "gn:feature_code":"PPL",
    "gn:name":"El Guayabito",
    "gn:population":0,
    "gn:timezone":"America/Caracas",
    "iso:country":"VE",
    "wof:name":"El Guayabito",
    "wof:placetype":"locality"
},
  "geometry": {"coordinates":[-66.84546999999999,9.68728],"type":"Point"}
}