{
  "type": "Feature",
  "properties": {
    "gn:admin1_code":"2",
    "gn:asciiname":"Los Ranchos",
    "gn:country_code":"VE",
    "gn:dem":66,
    "gn:feature_class":"P",
    "gn:feature_code":"PPL",
    "gn:name":"Los Ranchos",
    "gn:population":0,
    "gn:timezone":"America/Caracas",
    "iso:country":"VE",
    "name:ceb_x_preferred":[
        "Los Ranchos"
    ],
    "name:swe_x_preferred":[
        "Los Ranchos"
    ],
    "wof:name":"Los Ranchos",
    "wof:placetype":"locality"
},
  "geometry": {"coordinates":[-65.2856,9.67413],"type":"Point"}
}