{
  "type": "Feature",
  "properties": {
    "gn:admin1_code":"2",
    "gn:asciiname":"Bajo Hondo",
    "gn:country_code":"VE",
    "gn:dem":281,
    "gn:feature_class":"P",
    "gn:feature_code":"PPL",
    "gn:name":"Bajo Hondo",
    "gn:population":0,
    "gn:timezone":"America/Caracas",
    "iso:country":"VE",
    "name:nld_x_preferred":[
        "Bajo Hondo"
    ],
    "name:spa_x_preferred":[
        "Bajo Hondo"
    ],
    "wof:name":"Bajo Hondo",
    "wof:placetype":"locality"
},
  "geometry": {"coordinates":[-64.31059999999999,9.04143],"type":"Point"}
}