{
  "type": "Feature",
  "properties": {
    "gn:admin1_code":"16",
    "gn:asciiname":"La Pica",
    "gn:country_code":"VE",
    "gn:dem":36,
    "gn:feature_class":"P",
    "gn:feature_code":"PPL",
    "gn:name":"La Pica",
    "gn:population":0,
    "gn:timezone":"America/Caracas",
    "iso:country":"VE",
    "wof:name":"La Pica",
    "wof:placetype":"locality"
},
  "geometry": {"coordinates":[-63.06624,9.79705],"type":"Point"}
}