{
  "type": "Feature",
  "properties": {
    "gn:admin1_code":"13",
    "gn:asciiname":"Raya del Caimito",
    "gn:country_code":"VE",
    "gn:dem":1007,
    "gn:feature_class":"P",
    "gn:feature_code":"PPL",
    "gn:name":"Raya del Caimito",
    "gn:population":0,
    "gn:timezone":"America/Caracas",
    "iso:country":"VE",
    "wof:name":"Raya del Caimito",
    "wof:placetype":"locality"
},
  "geometry": {"coordinates":[-69.55005,9.84339],"type":"Point"}
}