{
  "type": "Feature",
  "properties": {
    "gn:admin1_code":"5",
    "gn:asciiname":"El Sopeco",
    "gn:country_code":"VE",
    "gn:dem":76,
    "gn:feature_class":"P",
    "gn:feature_code":"PPL",
    "gn:name":"El Sopeco",
    "gn:population":0,
    "gn:timezone":"America/Caracas",
    "iso:country":"VE",
    "wof:name":"El Sopeco",
    "wof:placetype":"locality"
},
  "geometry": {"coordinates":[-69.06667,7.98333],"type":"Point"}
}