{
  "type": "Feature",
  "properties": {
    "gn:admin1_code":"6.0",
    "gn:asciiname":"Los Huevos",
    "gn:country_code":"VE",
    "gn:dem":235,
    "gn:feature_class":"P",
    "gn:feature_code":"PPL",
    "gn:name":"Los Huevos",
    "gn:population":0,
    "gn:timezone":"America/Caracas",
    "iso:country":"VE",
    "wof:name":"Los Huevos",
    "wof:placetype":"locality"
},
  "geometry": {"coordinates":[-62.29167,7.65833],"type":"Point"}
}