{
  "type": "Feature",
  "properties": {
    "gn:admin1_code":"14.0",
    "gn:asciiname":"Pie de Cuesta",
    "gn:country_code":"VE",
    "gn:dem":2676,
    "gn:feature_class":"P",
    "gn:feature_code":"PPL",
    "gn:name":"Pie de Cuesta",
    "gn:population":0,
    "gn:timezone":"America/Caracas",
    "iso:country":"VE",
    "wof:name":"Pie de Cuesta",
    "wof:placetype":"locality"
},
  "geometry": {"coordinates":[-70.75176999999999,8.95214],"type":"Point"}
}