{
  "type": "Feature",
  "properties": {
    "gn:admin1_code":"14",
    "gn:asciiname":"Jicacuy",
    "gn:country_code":"VE",
    "gn:dem":1781,
    "gn:feature_class":"P",
    "gn:feature_code":"PPL",
    "gn:name":"Jicacuy",
    "gn:population":0,
    "gn:timezone":"America/Caracas",
    "iso:country":"VE",
    "wof:name":"Jicacuy",
    "wof:placetype":"locality"
},
  "geometry": {"coordinates":[-71.38405999999998,8.43276],"type":"Point"}
}