{
  "type": "Feature",
  "properties": {
    "gn:admin1_code":"17",
    "gn:asciiname":"Guaraguao",
    "gn:country_code":"VE",
    "gn:dem":9,
    "gn:feature_class":"P",
    "gn:feature_code":"PPLL",
    "gn:name":"Guaraguao",
    "gn:population":0,
    "gn:timezone":"America/Caracas",
    "iso:country":"VE",
    "wof:name":"Guaraguao",
    "wof:placetype":"locality"
},
  "geometry": {"coordinates":[-63.84014000000001,10.96022],"type":"Point"}
}