{
  "type": "Feature",
  "properties": {
    "iso:country":"VE",
    "name:und_x_variant":[
        "Robledar"
    ],
    "qs:gn_country":"VE",
    "qs:gn_fcode":"PPL",
    "qs:gn_pop":0,
    "qs:name":"Robledal",
    "qs:name_adm0":"Venezuela",
    "qs:name_adm1":"Nueva Esparta",
    "qs:photos":21,
    "qs:photos_1k":4,
    "qs:photos_9k":1,
    "qs:photos_9r":1,
    "qs:photos_all":21,
    "qs:photos_sr":1,
    "qs:placetype":"Town",
    "qs:pop_sr":"0",
    "qs:woe_adm0":23424982,
    "wof:name":"Robledal",
    "wof:placetype":"locality"
},
  "geometry": {"coordinates":[-64.3715,11.02974],"type":"Point"}
}