{
  "type": "Feature",
  "properties": {
    "gn:admin1_code":"15.0",
    "gn:asciiname":"Los Tres Palos",
    "gn:country_code":"VE",
    "gn:dem":584,
    "gn:feature_class":"P",
    "gn:feature_code":"PPLL",
    "gn:name":"Los Tres Palos",
    "gn:population":0,
    "gn:timezone":"America/Caracas",
    "iso:country":"VE",
    "wof:name":"Los Tres Palos",
    "wof:placetype":"locality"
},
  "geometry": {"coordinates":[-67.07889,10.11098],"type":"Point"}
}