{
  "type": "Feature",
  "properties": {
    "gn:admin1_code":"12.0",
    "gn:asciiname":"Oro Fino",
    "gn:country_code":"VE",
    "gn:dem":94,
    "gn:feature_class":"P",
    "gn:feature_code":"PPL",
    "gn:name":"Oro Fino",
    "gn:population":0,
    "gn:timezone":"America/Caracas",
    "iso:country":"VE",
    "wof:name":"Oro Fino",
    "wof:placetype":"locality"
},
  "geometry": {"coordinates":[-67.85485,9.27779],"type":"Point"}
}