{
  "type": "Feature",
  "properties": {
    "gn:admin1_code":"18",
    "gn:asciiname":"Adjuntas",
    "gn:country_code":"VE",
    "gn:dem":940,
    "gn:feature_class":"P",
    "gn:feature_code":"PPL",
    "gn:name":"Adjuntas",
    "gn:population":0,
    "gn:timezone":"America/Caracas",
    "iso:country":"VE",
    "wof:name":"Adjuntas",
    "wof:placetype":"locality"
},
  "geometry": {"coordinates":[-69.93333,9.41667],"type":"Point"}
}