{
  "type": "Feature",
  "properties": {
    "gn:admin1_code":"3",
    "gn:asciiname":"Arauquita",
    "gn:country_code":"VE",
    "gn:dem":46,
    "gn:feature_class":"P",
    "gn:feature_code":"PPL",
    "gn:name":"Arauquita",
    "gn:population":0,
    "gn:timezone":"America/Caracas",
    "iso:country":"VE",
    "name:ceb_x_preferred":[
        "Arauquita"
    ],
    "name:deu_x_preferred":[
        "Arauquita"
    ],
    "name:fas_x_preferred":[
        "\u0622\u0631\u0627\u0626\u0648\u06a9\u06cc\u062a\u0627"
    ],
    "name:fra_x_preferred":[
        "Arauquita"
    ],
    "name:ilo_x_preferred":[
        "Arauquita"
    ],
    "name:ita_x_preferred":[
        "Arauquita"
    ],
    "name:kat_x_preferred":[
        "\u10d0\u10e0\u10d0\u10e3\u10d9\u10d8\u10e2\u10d0"
    ],
    "name:msa_x_preferred":[
        "Arauquita"
    ],
    "name:nld_x_preferred":[
        "Arauquita"
    ],
    "name:por_x_preferred":[
        "Arauquita"
    ],
    "name:rus_x_preferred":[
        "\u0410\u0440\u0430\u0443\u043a\u0438\u0442\u0430"
    ],
    "name:sco_x_preferred":[
        "Arauquita"
    ],
    "name:spa_x_preferred":[
        "Arauquita"
    ],
    "name:swe_x_preferred":[
        "Arauquita"
    ],
    "name:tgl_x_preferred":[
        "Arauquita"
    ],
    "name:vie_x_preferred":[
        "Arauquita"
    ],
    "name:war_x_preferred":[
        "Arauquita"
    ],
    "name:zho_x_preferred":[
        "\u963f\u52de\u57fa\u5854"
    ],
    "wof:name":"Arauquita",
    "wof:placetype":"locality"
},
  "geometry": {"coordinates":[-66.99781,7.19211],"type":"Point"}
}