{
  "type": "Feature",
  "properties": {
    "gn:admin1_code":"6",
    "gn:asciiname":"Las Mulas",
    "gn:country_code":"VE",
    "gn:dem":33,
    "gn:feature_class":"P",
    "gn:feature_code":"PPL",
    "gn:name":"Las Mulas",
    "gn:population":0,
    "gn:timezone":"America/Caracas",
    "iso:country":"VE",
    "wof:name":"Las Mulas",
    "wof:placetype":"locality"
},
  "geometry": {"coordinates":[-63.84482,8.08284],"type":"Point"}
}