{
  "type": "Feature",
  "properties": {
    "gn:admin1_code":"20.0",
    "gn:asciiname":"La Cordillera",
    "gn:country_code":"VE",
    "gn:dem":363,
    "gn:feature_class":"P",
    "gn:feature_code":"PPLL",
    "gn:name":"La Cordillera",
    "gn:population":0,
    "gn:timezone":"America/Caracas",
    "iso:country":"VE",
    "wof:name":"La Cordillera",
    "wof:placetype":"locality"
},
  "geometry": {"coordinates":[-71.98998,7.43491],"type":"Point"}
}