{
  "type": "Feature",
  "properties": {
    "gn:admin1_code":"3",
    "gn:asciiname":"El Caribe",
    "gn:country_code":"VE",
    "gn:dem":98,
    "gn:feature_class":"P",
    "gn:feature_code":"PPL",
    "gn:name":"El Caribe",
    "gn:population":0,
    "gn:timezone":"America/Caracas",
    "iso:country":"VE",
    "name:und_x_variant":[
        "Caribe",
        "El Caribe"
    ],
    "wof:name":"El Caribe",
    "wof:placetype":"locality"
},
  "geometry": {"coordinates":[-69.67035,6.93759],"type":"Point"}
}