{
  "type": "Feature",
  "properties": {
    "gn:admin1_code":"18.0",
    "gn:asciiname":"La Carama",
    "gn:country_code":"VE",
    "gn:dem":139,
    "gn:feature_class":"P",
    "gn:feature_code":"PPL",
    "gn:name":"La Carama",
    "gn:population":0,
    "gn:timezone":"America/Caracas",
    "iso:country":"VE",
    "name:spa_x_preferred":[
        "La Carama"
    ],
    "wof:name":"La Carama",
    "wof:placetype":"locality"
},
  "geometry": {"coordinates":[-69.33185999999999,9.26957],"type":"Point"}
}