{
  "type": "Feature",
  "properties": {
    "gn:admin1_code":"2",
    "gn:asciiname":"Los Peladeros",
    "gn:cc2":"VE",
    "gn:country_code":"VE",
    "gn:dem":88,
    "gn:feature_class":"P",
    "gn:feature_code":"PPL",
    "gn:name":"Los Peladeros",
    "gn:population":0,
    "gn:timezone":"America/Caracas",
    "iso:country":"VE",
    "name:und_x_variant":[
        "Los Paraderos",
        "Los Peladeros"
    ],
    "wof:name":"Los Peladeros",
    "wof:placetype":"locality"
},
  "geometry": {"coordinates":[-64.95,9.41667],"type":"Point"}
}