{
  "type": "Feature",
  "properties": {
    "gn:admin1_code":"12",
    "gn:asciiname":"Vilches",
    "gn:country_code":"VE",
    "gn:dem":226,
    "gn:feature_class":"P",
    "gn:feature_code":"PPL",
    "gn:name":"Vilches",
    "gn:population":0,
    "gn:timezone":"America/Caracas",
    "iso:country":"VE",
    "name:cat_x_preferred":[
        "Vilches"
    ],
    "name:ceb_x_preferred":[
        "Vilches"
    ],
    "name:deu_x_preferred":[
        "Vilches"
    ],
    "name:fra_x_preferred":[
        "Vilches"
    ],
    "name:ita_x_preferred":[
        "Vilches"
    ],
    "name:spa_x_preferred":[
        "Vilches"
    ],
    "name:swe_x_preferred":[
        "Vilches"
    ],
    "wof:name":"Vilches",
    "wof:placetype":"locality"
},
  "geometry": {"coordinates":[-67.25166999999999,9.675],"type":"Point"}
}