{
  "type": "Feature",
  "properties": {
    "gn:admin1_code":"13",
    "gn:asciiname":"Cogollal",
    "gn:cc2":"VE",
    "gn:country_code":"VE",
    "gn:dem":477,
    "gn:feature_class":"P",
    "gn:feature_code":"PPL",
    "gn:name":"Cogollal",
    "gn:population":0,
    "gn:timezone":"America/Caracas",
    "iso:country":"VE",
    "name:und_x_variant":[
        "Cogolcal",
        "Cogollal"
    ],
    "wof:name":"Cogollal",
    "wof:placetype":"locality"
},
  "geometry": {"coordinates":[-69.65000000000001,10.61667],"type":"Point"}
}