{
  "type": "Feature",
  "properties": {
    "gn:admin1_code":"15.0",
    "gn:asciiname":"Puerta Morocha",
    "gn:country_code":"VE",
    "gn:dem":1020,
    "gn:feature_class":"P",
    "gn:feature_code":"PPL",
    "gn:name":"Puerta Morocha",
    "gn:population":0,
    "gn:timezone":"America/Caracas",
    "iso:country":"VE",
    "wof:name":"Puerta Morocha",
    "wof:placetype":"locality"
},
  "geometry": {"coordinates":[-67.07165999999999,10.28999],"type":"Point"}
}