{
  "type": "Feature",
  "properties": {
    "gn:admin1_code":"19.0",
    "gn:asciiname":"El Saco",
    "gn:country_code":"VE",
    "gn:dem":637,
    "gn:feature_class":"P",
    "gn:feature_code":"PPL",
    "gn:name":"El Saco",
    "gn:population":0,
    "gn:timezone":"America/Caracas",
    "iso:country":"VE",
    "wof:name":"El Saco",
    "wof:placetype":"locality"
},
  "geometry": {"coordinates":[-64.48928000000001,10.21832],"type":"Point"}
}