{
  "type": "Feature",
  "properties": {
    "gn:admin1_code":"18",
    "gn:asciiname":"Cano Seco Abajo",
    "gn:country_code":"VE",
    "gn:dem":105,
    "gn:feature_class":"P",
    "gn:feature_code":"PPL",
    "gn:name":"Ca\u00f1o Seco Abajo",
    "gn:population":0,
    "gn:timezone":"America/Caracas",
    "iso:country":"VE",
    "wof:name":"Cano Seco Abajo",
    "wof:placetype":"locality"
},
  "geometry": {"coordinates":[-68.91667,9.35],"type":"Point"}
}