{
  "type": "Feature",
  "properties": {
    "gn:admin1_code":"11.0",
    "gn:asciiname":"Guarecal",
    "gn:country_code":"VE",
    "gn:dem":149,
    "gn:feature_class":"P",
    "gn:feature_code":"PPL",
    "gn:name":"Guarecal",
    "gn:population":0,
    "gn:timezone":"America/Caracas",
    "iso:country":"VE",
    "wof:name":"Guarecal",
    "wof:placetype":"locality"
},
  "geometry": {"coordinates":[-69.20477,11.31185],"type":"Point"}
}