{
  "type": "Feature",
  "properties": {
    "gn:admin1_code":"02",
    "gn:asciiname":"Chinchorreta",
    "gn:country_code":"VE",
    "gn:dem":79,
    "gn:feature_class":"P",
    "gn:feature_code":"PPL",
    "gn:name":"Chinchorreta",
    "gn:population":0,
    "gn:timezone":"America/Caracas",
    "iso:country":"VE",
    "wof:name":"Chinchorreta",
    "wof:placetype":"locality"
},
  "geometry": {"coordinates":[-63.60649,8.35404],"type":"Point"}
}