{
  "type": "Feature",
  "properties": {
    "gn:admin1_code":"6.0",
    "gn:asciiname":"Mogote Afuera",
    "gn:country_code":"VE",
    "gn:dem":49,
    "gn:feature_class":"P",
    "gn:feature_code":"PPL",
    "gn:name":"Mogote Afuera",
    "gn:population":0,
    "gn:timezone":"America/Caracas",
    "iso:country":"VE",
    "wof:name":"Mogote Afuera",
    "wof:placetype":"locality"
},
  "geometry": {"coordinates":[-67.24938,6.34256],"type":"Point"}
}