{
  "type": "Feature",
  "properties": {
    "gn:admin1_code":"15.0",
    "gn:asciiname":"Rio Arriba",
    "gn:country_code":"VE",
    "gn:dem":448,
    "gn:feature_class":"P",
    "gn:feature_code":"PPL",
    "gn:name":"R\u00edo Arriba",
    "gn:population":0,
    "gn:timezone":"America/Caracas",
    "iso:country":"VE",
    "wof:name":"Rio Arriba",
    "wof:placetype":"locality"
},
  "geometry": {"coordinates":[-66.47239999999999,10.47442],"type":"Point"}
}