{
  "type": "Feature",
  "properties": {
    "gn:admin1_code":"8",
    "gn:asciiname":"Ines",
    "gn:cc2":"VE",
    "gn:country_code":"VE",
    "gn:dem":61,
    "gn:feature_class":"P",
    "gn:feature_code":"PPL",
    "gn:name":"In\u00e9s",
    "gn:population":0,
    "gn:timezone":"America/Caracas",
    "iso:country":"VE",
    "name:und_x_variant":[
        "Boca Ines",
        "In\u00e9s"
    ],
    "wof:name":"Ines",
    "wof:placetype":"locality"
},
  "geometry": {"coordinates":[-68.11667,8.56667],"type":"Point"}
}