{
  "type": "Feature",
  "properties": {
    "gn:admin1_code":"18.0",
    "gn:asciiname":"La Vuelta del Chichero",
    "gn:country_code":"VE",
    "gn:dem":117,
    "gn:feature_class":"P",
    "gn:feature_code":"PPLL",
    "gn:name":"La Vuelta del Chichero",
    "gn:population":0,
    "gn:timezone":"America/Caracas",
    "iso:country":"VE",
    "name:spa_x_preferred":[
        "La Vuelta del Chichero"
    ],
    "wof:name":"La Vuelta del Chichero",
    "wof:placetype":"locality"
},
  "geometry": {"coordinates":[-69.63823000000001,8.77737],"type":"Point"}
}