{
  "type": "Feature",
  "properties": {
    "gn:admin1_code":"15",
    "gn:asciiname":"Las Dos Bocas",
    "gn:country_code":"VE",
    "gn:dem":107,
    "gn:feature_class":"P",
    "gn:feature_code":"PPL",
    "gn:name":"Las Dos Bocas",
    "gn:population":0,
    "gn:timezone":"America/Caracas",
    "iso:country":"VE",
    "wof:name":"Las Dos Bocas",
    "wof:placetype":"locality"
},
  "geometry": {"coordinates":[-66.4817,10.21773],"type":"Point"}
}