{
  "type": "Feature",
  "properties": {
    "gn:admin1_code":"14",
    "gn:asciiname":"Buscatera",
    "gn:country_code":"VE",
    "gn:dem":1230,
    "gn:feature_class":"P",
    "gn:feature_code":"PPL",
    "gn:name":"Buscatera",
    "gn:population":0,
    "gn:timezone":"America/Caracas",
    "iso:country":"VE",
    "wof:name":"Buscatera",
    "wof:placetype":"locality"
},
  "geometry": {"coordinates":[-71.74861,8.31726],"type":"Point"}
}