{
  "type": "Feature",
  "properties": {
    "gn:admin1_code":"21",
    "gn:asciiname":"Arenosa",
    "gn:country_code":"VE",
    "gn:dem":248,
    "gn:feature_class":"P",
    "gn:feature_code":"PPL",
    "gn:name":"Arenosa",
    "gn:population":0,
    "gn:timezone":"America/Caracas",
    "iso:country":"VE",
    "wof:name":"Arenosa",
    "wof:placetype":"locality"
},
  "geometry": {"coordinates":[-70.46666999999999,9.56667],"type":"Point"}
}