{
  "type": "Feature",
  "properties": {
    "gn:admin1_code":"13.0",
    "gn:asciiname":"Matias",
    "gn:country_code":"VE",
    "gn:dem":962,
    "gn:feature_class":"P",
    "gn:feature_code":"PPL",
    "gn:name":"Matias",
    "gn:population":0,
    "gn:timezone":"America/Caracas",
    "iso:country":"VE",
    "name:fin_x_preferred":[
        "Matias"
    ],
    "wof:name":"Matias",
    "wof:placetype":"locality"
},
  "geometry": {"coordinates":[-70.32890999999999,9.87366],"type":"Point"}
}