{
  "type": "Feature",
  "properties": {
    "gn:admin1_code":"8",
    "gn:asciiname":"Los Castores",
    "gn:country_code":"VE",
    "gn:dem":427,
    "gn:feature_class":"P",
    "gn:feature_code":"PPL",
    "gn:name":"Los Castores",
    "gn:population":0,
    "gn:timezone":"America/Caracas",
    "iso:country":"VE",
    "wof:name":"Los Castores",
    "wof:placetype":"locality"
},
  "geometry": {"coordinates":[-68.51036999999999,9.79693],"type":"Point"}
}