{
  "type": "Feature",
  "properties": {
    "iso:country":"VE",
    "qs:gn_pop":0,
    "qs:name":"Tubores",
    "qs:name_adm0":"Venezuela",
    "qs:name_adm1":"Nueva Esparta",
    "qs:photos":83,
    "qs:photos_1k":17,
    "qs:photos_9k":2,
    "qs:photos_9r":5,
    "qs:photos_all":340,
    "qs:photos_sr":3,
    "qs:placetype":"LocalAdmin",
    "qs:pop_sr":"0",
    "qs:woe_adm0":23424982,
    "wof:name":"Tubores",
    "wof:placetype":"localadmin"
},
  "geometry": {"coordinates":[-64.12685,10.982144],"type":"Point"}
}