{
  "type": "Feature",
  "properties": {
    "gn:admin1_code":"4",
    "gn:asciiname":"El Nicual",
    "gn:country_code":"VE",
    "gn:dem":164,
    "gn:feature_class":"P",
    "gn:feature_code":"PPL",
    "gn:name":"El Nicual",
    "gn:population":0,
    "gn:timezone":"America/Caracas",
    "iso:country":"VE",
    "wof:name":"El Nicual",
    "wof:placetype":"locality"
},
  "geometry": {"coordinates":[-67.78721999999999,10.38611],"type":"Point"}
}