{
  "type": "Feature",
  "properties": {
    "gn:admin1_code":"14",
    "gn:asciiname":"Muchaba",
    "gn:country_code":"VE",
    "gn:dem":2082,
    "gn:feature_class":"P",
    "gn:feature_code":"PPL",
    "gn:name":"Muchab\u00e1",
    "gn:population":0,
    "gn:timezone":"America/Caracas",
    "iso:country":"VE",
    "wof:name":"Muchaba",
    "wof:placetype":"locality"
},
  "geometry": {"coordinates":[-71.41889,8.34639],"type":"Point"}
}