{
  "type": "Feature",
  "properties": {
    "gn:admin1_code":"3",
    "gn:asciiname":"Las Montanitas",
    "gn:country_code":"VE",
    "gn:dem":113,
    "gn:feature_class":"P",
    "gn:feature_code":"PPL",
    "gn:name":"Las Monta\u00f1itas",
    "gn:population":0,
    "gn:timezone":"America/Caracas",
    "iso:country":"VE",
    "wof:name":"Las Montanitas",
    "wof:placetype":"locality"
},
  "geometry": {"coordinates":[-70.1099,6.9813],"type":"Point"}
}