{
  "type": "Feature",
  "properties": {
    "gn:admin1_code":"2",
    "gn:asciiname":"Barcelona",
    "gn:country_code":"VE",
    "gn:dem":208,
    "gn:feature_class":"P",
    "gn:feature_code":"PPL",
    "gn:name":"Barcelona",
    "gn:population":0,
    "gn:timezone":"America/Caracas",
    "iso:country":"VE",
    "wof:name":"Barcelona",
    "wof:placetype":"locality"
},
  "geometry": {"coordinates":[-64.61667,9.08333],"type":"Point"}
}