{
  "type": "Feature",
  "properties": {
    "gn:admin1_code":"12",
    "gn:asciiname":"Paso Real",
    "gn:country_code":"VE",
    "gn:dem":280,
    "gn:feature_class":"P",
    "gn:feature_code":"PPL",
    "gn:name":"Paso Real",
    "gn:population":0,
    "gn:timezone":"America/Caracas",
    "iso:country":"VE",
    "wof:name":"Paso Real",
    "wof:placetype":"locality"
},
  "geometry": {"coordinates":[-66.17435,9.80743],"type":"Point"}
}