{
  "type": "Feature",
  "properties": {
    "gn:admin1_code":"15",
    "gn:asciiname":"La Aguada Arriba",
    "gn:country_code":"VE",
    "gn:dem":211,
    "gn:feature_class":"P",
    "gn:feature_code":"PPL",
    "gn:name":"La Aguada Arriba",
    "gn:population":0,
    "gn:timezone":"America/Caracas",
    "iso:country":"VE",
    "wof:name":"La Aguada Arriba",
    "wof:placetype":"locality"
},
  "geometry": {"coordinates":[-66.75709000000001,10.22566],"type":"Point"}
}