{
  "type": "Feature",
  "properties": {
    "gn:admin1_code":"20",
    "gn:admin2_code":"2007.0",
    "gn:asciiname":"San Rafael del Pinal",
    "gn:country_code":"VE",
    "gn:dem":270,
    "gn:feature_class":"P",
    "gn:feature_code":"PPLA2",
    "gn:name":"San Rafael del Pi\u00f1al",
    "gn:population":0,
    "gn:timezone":"America/Caracas",
    "iso:country":"VE",
    "name:und_x_variant":[
        "El Pi\u00f1al"
    ],
    "wof:name":"San Rafael del Pinal",
    "wof:placetype":"locality"
},
  "geometry": {"coordinates":[-71.95922,7.52987],"type":"Point"}
}