{
  "type": "Feature",
  "properties": {
    "gn:admin1_code":"4.0",
    "gn:asciiname":"Cogollal",
    "gn:country_code":"VE",
    "gn:dem":680,
    "gn:feature_class":"P",
    "gn:feature_code":"PPL",
    "gn:name":"Cogollal",
    "gn:population":0,
    "gn:timezone":"America/Caracas",
    "iso:country":"VE",
    "wof:name":"Cogollal",
    "wof:placetype":"locality"
},
  "geometry": {"coordinates":[-67.51651,9.97385],"type":"Point"}
}