{
  "type": "Feature",
  "properties": {
    "gn:admin1_code":"3.0",
    "gn:asciiname":"El Muerto",
    "gn:country_code":"VE",
    "gn:dem":35,
    "gn:feature_class":"P",
    "gn:feature_code":"PPL",
    "gn:name":"El Muerto",
    "gn:population":0,
    "gn:timezone":"America/Caracas",
    "iso:country":"VE",
    "name:spa_x_preferred":[
        "El Muerto"
    ],
    "wof:name":"El Muerto",
    "wof:placetype":"locality"
},
  "geometry": {"coordinates":[-66.52484,7.65096],"type":"Point"}
}