{
  "type": "Feature",
  "properties": {
    "gn:admin1_code":"04",
    "gn:asciiname":"San Francisco de Asis",
    "gn:country_code":"VE",
    "gn:dem":469,
    "gn:feature_class":"P",
    "gn:feature_code":"PPL",
    "gn:name":"San Francisco de As\u00eds",
    "gn:population":0,
    "gn:timezone":"America/Caracas",
    "iso:country":"VE",
    "wof:name":"San Francisco de Asis",
    "wof:placetype":"locality"
},
  "geometry": {"coordinates":[-67.55431,10.07599],"type":"Point"}
}