{
  "type": "Feature",
  "properties": {
    "gn:admin1_code":"6.0",
    "gn:asciiname":"Las Tres Rosas",
    "gn:country_code":"VE",
    "gn:dem":166,
    "gn:feature_class":"P",
    "gn:feature_code":"PPL",
    "gn:name":"Las Tres Rosas",
    "gn:population":0,
    "gn:timezone":"America/Caracas",
    "iso:country":"VE",
    "wof:name":"Las Tres Rosas",
    "wof:placetype":"locality"
},
  "geometry": {"coordinates":[-61.49444,7.29333],"type":"Point"}
}