{
  "type": "Feature",
  "properties": {
    "gn:admin1_code":"11",
    "gn:asciiname":"Areguito",
    "gn:country_code":"VE",
    "gn:dem":876,
    "gn:feature_class":"P",
    "gn:feature_code":"PPL",
    "gn:name":"Areguito",
    "gn:population":0,
    "gn:timezone":"America/Caracas",
    "iso:country":"VE",
    "wof:name":"Areguito",
    "wof:placetype":"locality"
},
  "geometry": {"coordinates":[-69.24911,10.84429],"type":"Point"}
}