{
  "type": "Feature",
  "properties": {
    "gn:admin1_code":"11",
    "gn:asciiname":"El Oso",
    "gn:country_code":"VE",
    "gn:dem":96,
    "gn:feature_class":"P",
    "gn:feature_code":"PPL",
    "gn:name":"El Oso",
    "gn:population":0,
    "gn:timezone":"America/Caracas",
    "iso:country":"VE",
    "wof:name":"El Oso",
    "wof:placetype":"locality"
},
  "geometry": {"coordinates":[-68.86667,11.21667],"type":"Point"}
}