{
  "type": "Feature",
  "properties": {
    "gn:admin1_code":"20",
    "gn:asciiname":"Santa Cruz de Mora",
    "gn:cc2":"VE",
    "gn:country_code":"VE",
    "gn:dem":1151,
    "gn:feature_class":"P",
    "gn:feature_code":"PPL",
    "gn:name":"Santa Cruz de Mora",
    "gn:population":0,
    "gn:timezone":"America/Caracas",
    "iso:country":"VE",
    "name:und_x_variant":[
        "Santa Cruz",
        "Santa Cruz de Mora"
    ],
    "wof:name":"Santa Cruz de Mora",
    "wof:placetype":"locality"
},
  "geometry": {"coordinates":[-72.33333,7.73333],"type":"Point"}
}