{
  "type": "Feature",
  "properties": {
    "gn:admin1_code":"06",
    "gn:asciiname":"La Guardia de Pararuma",
    "gn:country_code":"VE",
    "gn:dem":35,
    "gn:feature_class":"P",
    "gn:feature_code":"PPL",
    "gn:name":"La Guardia de Pararuma",
    "gn:population":0,
    "gn:timezone":"America/Caracas",
    "iso:country":"VE",
    "wof:name":"La Guardia de Pararuma",
    "wof:placetype":"locality"
},
  "geometry": {"coordinates":[-67.14221999999999,6.46111],"type":"Point"}
}