{
  "type": "Feature",
  "properties": {
    "gn:admin1_code":"3",
    "gn:asciiname":"La Argentina",
    "gn:country_code":"VE",
    "gn:dem":75,
    "gn:feature_class":"P",
    "gn:feature_code":"PPL",
    "gn:name":"La Argentina",
    "gn:population":0,
    "gn:timezone":"America/Caracas",
    "iso:country":"VE",
    "name:ceb_x_preferred":[
        "La Argentina"
    ],
    "name:deu_x_preferred":[
        "La Argentina"
    ],
    "name:fra_x_preferred":[
        "La Argentina"
    ],
    "name:ita_x_preferred":[
        "La Argentina"
    ],
    "name:spa_x_preferred":[
        "La Argentina"
    ],
    "name:swe_x_preferred":[
        "La Argentina"
    ],
    "name:tur_x_preferred":[
        "La Argentina"
    ],
    "wof:name":"La Argentina",
    "wof:placetype":"locality"
},
  "geometry": {"coordinates":[-69.01527,6.89261],"type":"Point"}
}