{
  "type": "Feature",
  "properties": {
    "gn:admin1_code":"11",
    "gn:asciiname":"El Potrerito",
    "gn:country_code":"VE",
    "gn:dem":70,
    "gn:feature_class":"P",
    "gn:feature_code":"PPL",
    "gn:name":"El Potrerito",
    "gn:population":0,
    "gn:timezone":"America/Caracas",
    "iso:country":"VE",
    "wof:name":"El Potrerito",
    "wof:placetype":"locality"
},
  "geometry": {"coordinates":[-70.64801,11.04378],"type":"Point"}
}