{
  "type": "Feature",
  "properties": {
    "gn:admin1_code":"12.0",
    "gn:asciiname":"La Ventana",
    "gn:country_code":"VE",
    "gn:dem":35,
    "gn:feature_class":"P",
    "gn:feature_code":"PPLL",
    "gn:name":"La Ventana",
    "gn:population":0,
    "gn:timezone":"America/Caracas",
    "iso:country":"VE",
    "name:urd_x_preferred":[
        "\u0644\u0627 \u0648\u06cc\u0646\u0679\u0627\u0646\u0627"
    ],
    "wof:name":"La Ventana",
    "wof:placetype":"locality"
},
  "geometry": {"coordinates":[-66.58450000000001,7.78024],"type":"Point"}
}